Workbook

Sheet Cover
B2: Mighty Pilates
B3: Financial Model
B5: Last refreshed: June 23, 2026
B7: Tab Guide
B9: Summary & Controls | C9: Top-level KPIs, studio sales & EBITDA tables, charts
B10: Assumptions | C10: All model inputs: OpEx, sales forecast, rev rec curves, loan terms
B11: Cash Flow Forecast | C11: Monthly cash flow from operations + investing + financing
B12: P&L Summary | C12: Consolidated monthly P&L (Revenue → EBITDA)
B13: P&L Detail | C13: Account-level P&L matching accountant chart of accounts
B14: All Studios Summary | C14: Side-by-side studio comparison
B15: [Studio] FCST (×12) | C15: Per-studio P&L forecast (BK, CC, DN, LF, MR, OP, PH, RH, SB, SM, WP, WW)
B16: Cash, Debt & Equity | C16: Balance sheet, loan amortization schedules, equity tracking
B17: Sales Forecast | C17: Studio × month editable sales grid
B18: CapEx | C18: Capital expenditure project schedule
B19: QBO Actuals | C19: Historical accountant-booked P&L, BS, SCF (read-only)
B22: Conventions
B24: Yellow cells = inputs (edit these)
B25: Light green cells = actuals (closed months, do not edit)

Sheet Read Me
B2: Read Me — Model Architecture
B3: Last refreshed: June 23, 2026
B5: Tab Roles
B6: Summary & Controls | C6: Top-level dashboard. Sales + EBITDA by studio. Total EBITDA references P&L NOI directly.
B7: Assumptions | C7: Editable global parameters: rev rec curves, refund/discount/COGS rates, escalations, loan terms.
B8: Sales Forecast | C8: Per-studio × month sales grid. EDITABLE for forecast months (yellow). Drives revenue formulas. Hidden rows 101-113 hold 2025 history for lag formulas — do not delete.
B9: Cash, Debt & Equity | C9: Loan amortization schedule + debt service forecast.
B10: Cash Flow Forecast | C10: Monthly CF with operating/investing/financing.
B11: P&L (Consolidated) | C11: Consolidated monthly P&L. Revenue/COGS use direct lag formulas (with 2025 history). OpEx rows = SUM(per-studio) + HO + HO Other.
B12: All Studios Summary | C12: Side-by-side studio comparison.
B13: [Code] P&L (×12) | C13: Per-studio P&L: BK, CC, DN, LF, MR, OP, PH, RH, SB, SM, WP, WW. OpEx leaves are HARDCODED values (editable) summing to per-studio override. Revenue formulas use per-studio lag (2026+ from Sales Forecast, 2025 from hidden helper rows 102-113).
B14: HO P&L | C14: Head Office overhead (no revenue). Same leaf-summing structure. NOI is negative (= -Total OpEx).
B15: CapEx | C15: Project schedule (empty — add projects to populate Investing rows on CF).
B16: QBO Actuals | C16: Raw accountant-booked P&L/BS/SCF data. Read-only reference.
B18: Cell Conventions
B19: Yellow fill (FFFF99) | C19: EDITABLE input cell. Cat can change these.
B20: Light green fill | C20: Hardcoded actual from QBO/accountant. Do not edit (would diverge from source data).
B21: White/no fill | C21: Formula cell. Computed from other cells.
B22: Light blue fill | C22: Subtotal or total row.
B23: Bold green fill | C23: Key KPI (EBITDA, ending cash).
B25: Value Flow
B26: Sales edit | C26: Edit Sales Forecast cell → flows to: Studio P&L Sessions/Breakage (via lag formula) → Studio NOI → Summary & Controls studio row → Sales Forecast TOTAL row → Consolidated P&L revenue → Consolidated NOI → Summary & Controls Total EBITDA.
B27: OpEx leaf edit | C27: Edit per-studio OpEx leaf (e.g., BK Paid Ads) → Studio Marketing subtotal (=SUM leaves) → Studio Total OpEx → Studio NOI → Summary & Controls studio row → Consolidated P&L Marketing (=SUM studios + HO) → Consolidated Total OpEx → Consolidated NOI → Summary & Controls Total EBITDA. Full propagation works.
B28: Assumption edit | C28: Edit rate on Assumptions tab (refund %, discount %, escalation, etc.) → flows through all formulas referencing that cell.
B30: Hidden Helpers — DO NOT DELETE
B31: Sales Forecast rows 100-113 | C31: Hidden helper rows holding 2025 monthly sales (consolidated row 101 and per-studio rows 102-113). Required for 7-month lag formulas on Session/Breakage Revenue forecasts for May 2026 and Jun 2026.
B32: Sales Forecast row ~50+ | C32: Helper for chart data references on Summary & Controls. Removing breaks charts.
B34: Monthly Update Procedure (when QBO closes new month)
B35: Step 1 | C35: Upload new QBO export to Streamlit dashboard. Streamlit's committed_actuals.json gets updated.
B36: Step 2 | C36: Run refresh_from_streamlit.py (in /Users/chandlerclemons/financial-modeling/models/mighty/).
B37: Step 3 | C37: Refresh script will: (a) extend actuals columns by 1 month, (b) shift forecast forward, (c) refresh trailing-3-month avg lines (Taxes Paid, Property Taxes, Retail, Depreciation), (d) update 2025 helper row values if Streamlit data changed historicals.
B38: Step 4 | C38: Open the Excel and spot-check the new actuals column vs Streamlit. Save & share with stakeholders.
B40: Streamlit Source Repo
B41: GitHub | C41: github.com/c-clemons/mighty-pilates (private)
B42: Live app | C42: mighty-pilates-financial-model.streamlit.app
B43: Local files | C43: /Users/chandlerclemons/mighty-pilates/dashboard/data/

Sheet Summary
B2: Summary & Controls
B3: Top-level dashboard. Studio sales, EBITDA, YoY summary, charts.
B4: Monthly Total Session Sales by Studio
B5: Metric | C5: Studio | D5: Jan 2026 (A) | E5: Feb 2026 (A) | F5: Mar 2026 (A) | G5: Apr 2026 (A) | H5: May 2026 | I5: Jun 2026 | J5: Jul 2026 | K5: Aug 2026 | L5: Sep 2026 | M5: Oct 2026 | N5: Nov 2026 | O5: Dec 2026 | P5: Jan 2027 | Q5: Feb 2027 | R5: Mar 2027 | S5: Apr 2027 | T5: May 2027 | U5: Jun 2027 | V5: Jul 2027 | W5: Aug 2027 | X5: Sep 2027 | Y5: Oct 2027 | Z5: Nov 2027 | AA5: Dec 2027 | AB5: Jan 2028 | AC5: Feb 2028 | AD5: Mar 2028 | AE5: Apr 2028 | AF5: May 2028 | AG5: Jun 2028 | AH5: Jul 2028 | AI5: Aug 2028 | AJ5: Sep 2028 | AK5: Oct 2028 | AL5: Nov 2028 | AM5: Dec 2028
B6: Total Sales | D6: =SUM(D7:D19) | E6: =SUM(E7:E19) | F6: =SUM(F7:F19) | G6: =SUM(G7:G19) | H6: =SUM(H7:H19) | I6: =SUM(I7:I19) | J6: =SUM(J7:J19) | K6: =SUM(K7:K19) | ... AM6: =SUM(AM7:AM19)
C7: Berkeley | D7: ='Sales Forecast'!D6 | E7: ='Sales Forecast'!E6 | F7: ='Sales Forecast'!F6 | G7: ='Sales Forecast'!G6 | H7: ='Sales Forecast'!H6 | I7: ='Sales Forecast'!I6 | J7: ='Sales Forecast'!J6 | K7: ='Sales Forecast'!K6 | ... AM7: ='Sales Forecast'!AM6
C8: Culver City | D8: ='Sales Forecast'!D7 | E8: ='Sales Forecast'!E7 | F8: ='Sales Forecast'!F7 | G8: ='Sales Forecast'!G7 | H8: ='Sales Forecast'!H7 | I8: ='Sales Forecast'!I7 | J8: ='Sales Forecast'!J7 | K8: ='Sales Forecast'!K7 | ... AM8: ='Sales Forecast'!AM7
C9: Danville | D9: ='Sales Forecast'!D8 | E9: ='Sales Forecast'!E8 | F9: ='Sales Forecast'!F8 | G9: ='Sales Forecast'!G8 | H9: ='Sales Forecast'!H8 | I9: ='Sales Forecast'!I8 | J9: ='Sales Forecast'!J8 | K9: ='Sales Forecast'!K8 | ... AM9: ='Sales Forecast'!AM8
C10: Lafayette | D10: ='Sales Forecast'!D9 | E10: ='Sales Forecast'!E9 | F10: ='Sales Forecast'!F9 | G10: ='Sales Forecast'!G9 | H10: ='Sales Forecast'!H9 | I10: ='Sales Forecast'!I9 | J10: ='Sales Forecast'!J9 | K10: ='Sales Forecast'!K9 | ... AM10: ='Sales Forecast'!AM9
C11: Marin | D11: ='Sales Forecast'!D10 | E11: ='Sales Forecast'!E10 | F11: ='Sales Forecast'!F10 | G11: ='Sales Forecast'!G10 | H11: ='Sales Forecast'!H10 | I11: ='Sales Forecast'!I10 | J11: ='Sales Forecast'!J10 | K11: ='Sales Forecast'!K10 | ... AM11: ='Sales Forecast'!AM10
C12: Ocean Park | D12: ='Sales Forecast'!D11 | E12: ='Sales Forecast'!E11 | F12: ='Sales Forecast'!F11 | G12: ='Sales Forecast'!G11 | H12: ='Sales Forecast'!H11 | I12: ='Sales Forecast'!I11 | J12: ='Sales Forecast'!J11 | K12: ='Sales Forecast'!K11 | ... AM12: ='Sales Forecast'!AM11
C13: Presidio Heights | D13: ='Sales Forecast'!D12 | E13: ='Sales Forecast'!E12 | F13: ='Sales Forecast'!F12 | G13: ='Sales Forecast'!G12 | H13: ='Sales Forecast'!H12 | I13: ='Sales Forecast'!I12 | J13: ='Sales Forecast'!J12 | K13: ='Sales Forecast'!K12 | ... AM13: ='Sales Forecast'!AM12
C14: Russian Hill | D14: ='Sales Forecast'!D13 | E14: ='Sales Forecast'!E13 | F14: ='Sales Forecast'!F13 | G14: ='Sales Forecast'!G13 | H14: ='Sales Forecast'!H13 | I14: ='Sales Forecast'!I13 | J14: ='Sales Forecast'!J13 | K14: ='Sales Forecast'!K13 | ... AM14: ='Sales Forecast'!AM13
C15: Santa Barbara | D15: ='Sales Forecast'!D14 | E15: ='Sales Forecast'!E14 | F15: ='Sales Forecast'!F14 | G15: ='Sales Forecast'!G14 | H15: ='Sales Forecast'!H14 | I15: ='Sales Forecast'!I14 | J15: ='Sales Forecast'!J14 | K15: ='Sales Forecast'!K14 | ... AM15: ='Sales Forecast'!AM14
C16: Santa Monica | D16: ='Sales Forecast'!D15 | E16: ='Sales Forecast'!E15 | F16: ='Sales Forecast'!F15 | G16: ='Sales Forecast'!G15 | H16: ='Sales Forecast'!H15 | I16: ='Sales Forecast'!I15 | J16: ='Sales Forecast'!J15 | K16: ='Sales Forecast'!K15 | ... AM16: ='Sales Forecast'!AM15
C17: West Portal | D17: ='Sales Forecast'!D16 | E17: ='Sales Forecast'!E16 | F17: ='Sales Forecast'!F16 | G17: ='Sales Forecast'!G16 | H17: ='Sales Forecast'!H16 | I17: ='Sales Forecast'!I16 | J17: ='Sales Forecast'!J16 | K17: ='Sales Forecast'!K16 | ... AM17: ='Sales Forecast'!AM16
C18: Westwood | D18: ='Sales Forecast'!D17 | E18: ='Sales Forecast'!E17 | F18: ='Sales Forecast'!F17 | G18: ='Sales Forecast'!G17 | H18: ='Sales Forecast'!H17 | I18: ='Sales Forecast'!I17 | J18: ='Sales Forecast'!J17 | K18: ='Sales Forecast'!K17 | ... AM18: ='Sales Forecast'!AM17
C19: Head Office | D19: 0 | E19: 0 | F19: 0 | G19: 0 | H19: 0 | I19: 0 | J19: 0 | K19: 0 | L19: 0 | M19: 0 | N19: 0 | O19: 0 | P19: 0 | Q19: 0 | R19: 0 | S19: 0 | T19: 0 | U19: 0 | V19: 0 | W19: 0 | X19: 0 | Y19: 0 | Z19: 0 | AA19: 0 | AB19: 0 | AC19: 0 | AD19: 0 | AE19: 0 | AF19: 0 | AG19: 0 | AH19: 0 | AI19: 0 | AJ19: 0 | AK19: 0 | AL19: 0 | AM19: 0
B21: Monthly EBITDA by Studio
B22: Total EBITDA | D22: =SUM(D23:D35) | E22: =SUM(E23:E35) | F22: =SUM(F23:F35) | G22: =SUM(G23:G35) | H22: =SUM(H23:H35) | I22: =SUM(I23:I35) | J22: =SUM(J23:J35) | K22: =SUM(K23:K35) | ... AM22: =SUM(AM23:AM35)
C23: Berkeley | D23: ='BK P&L'!D63 | E23: ='BK P&L'!E63 | F23: ='BK P&L'!F63 | G23: ='BK P&L'!G63 | H23: ='BK P&L'!H63 | I23: ='BK P&L'!I63 | J23: ='BK P&L'!J63 | K23: ='BK P&L'!K63 | ... AM23: ='BK P&L'!AM63
C24: Culver City | D24: ='CC P&L'!D63 | E24: ='CC P&L'!E63 | F24: ='CC P&L'!F63 | G24: ='CC P&L'!G63 | H24: ='CC P&L'!H63 | I24: ='CC P&L'!I63 | J24: ='CC P&L'!J63 | K24: ='CC P&L'!K63 | ... AM24: ='CC P&L'!AM63
C25: Danville | D25: ='DN P&L'!D63 | E25: ='DN P&L'!E63 | F25: ='DN P&L'!F63 | G25: ='DN P&L'!G63 | H25: ='DN P&L'!H63 | I25: ='DN P&L'!I63 | J25: ='DN P&L'!J63 | K25: ='DN P&L'!K63 | ... AM25: ='DN P&L'!AM63
C26: Lafayette | D26: ='LF P&L'!D63 | E26: ='LF P&L'!E63 | F26: ='LF P&L'!F63 | G26: ='LF P&L'!G63 | H26: ='LF P&L'!H63 | I26: ='LF P&L'!I63 | J26: ='LF P&L'!J63 | K26: ='LF P&L'!K63 | ... AM26: ='LF P&L'!AM63
C27: Marin | D27: ='MR P&L'!D63 | E27: ='MR P&L'!E63 | F27: ='MR P&L'!F63 | G27: ='MR P&L'!G63 | H27: ='MR P&L'!H63 | I27: ='MR P&L'!I63 | J27: ='MR P&L'!J63 | K27: ='MR P&L'!K63 | ... AM27: ='MR P&L'!AM63
C28: Ocean Park | D28: ='OP P&L'!D63 | E28: ='OP P&L'!E63 | F28: ='OP P&L'!F63 | G28: ='OP P&L'!G63 | H28: ='OP P&L'!H63 | I28: ='OP P&L'!I63 | J28: ='OP P&L'!J63 | K28: ='OP P&L'!K63 | ... AM28: ='OP P&L'!AM63
C29: Presidio Heights | D29: ='PH P&L'!D63 | E29: ='PH P&L'!E63 | F29: ='PH P&L'!F63 | G29: ='PH P&L'!G63 | H29: ='PH P&L'!H63 | I29: ='PH P&L'!I63 | J29: ='PH P&L'!J63 | K29: ='PH P&L'!K63 | ... AM29: ='PH P&L'!AM63
C30: Russian Hill | D30: ='RH P&L'!D63 | E30: ='RH P&L'!E63 | F30: ='RH P&L'!F63 | G30: ='RH P&L'!G63 | H30: ='RH P&L'!H63 | I30: ='RH P&L'!I63 | J30: ='RH P&L'!J63 | K30: ='RH P&L'!K63 | ... AM30: ='RH P&L'!AM63
C31: Santa Barbara | D31: ='SB P&L'!D63 | E31: ='SB P&L'!E63 | F31: ='SB P&L'!F63 | G31: ='SB P&L'!G63 | H31: ='SB P&L'!H63 | I31: ='SB P&L'!I63 | J31: ='SB P&L'!J63 | K31: ='SB P&L'!K63 | ... AM31: ='SB P&L'!AM63
C32: Santa Monica | D32: ='SM P&L'!D63 | E32: ='SM P&L'!E63 | F32: ='SM P&L'!F63 | G32: ='SM P&L'!G63 | H32: ='SM P&L'!H63 | I32: ='SM P&L'!I63 | J32: ='SM P&L'!J63 | K32: ='SM P&L'!K63 | ... AM32: ='SM P&L'!AM63
C33: West Portal | D33: ='WP P&L'!D63 | E33: ='WP P&L'!E63 | F33: ='WP P&L'!F63 | G33: ='WP P&L'!G63 | H33: ='WP P&L'!H63 | I33: ='WP P&L'!I63 | J33: ='WP P&L'!J63 | K33: ='WP P&L'!K63 | ... AM33: ='WP P&L'!AM63
C34: Westwood | D34: ='WW P&L'!D63 | E34: ='WW P&L'!E63 | F34: ='WW P&L'!F63 | G34: ='WW P&L'!G63 | H34: ='WW P&L'!H63 | I34: ='WW P&L'!I63 | J34: ='WW P&L'!J63 | K34: ='WW P&L'!K63 | ... AM34: ='WW P&L'!AM63
C35: Head Office | D35: ='HO P&L'!D36 | E35: ='HO P&L'!E36 | F35: ='HO P&L'!F36 | G35: ='HO P&L'!G36 | H35: ='HO P&L'!H36 | I35: ='HO P&L'!I36 | J35: ='HO P&L'!J36 | K35: ='HO P&L'!K36 | ... AM35: ='HO P&L'!AM36
B37: Total Add Backs | D37: ='P&L'!D38 | E37: ='P&L'!E38 | F37: ='P&L'!F38 | G37: ='P&L'!G38 | H37: ='P&L'!H38 | I37: ='P&L'!I38 | J37: ='P&L'!J38 | K37: ='P&L'!K38 | ... AM37: ='P&L'!AM38
B38: Total Adj-EBITDA | D38: ='P&L'!D39 | E38: ='P&L'!E39 | F38: ='P&L'!F39 | G38: ='P&L'!G39 | H38: ='P&L'!H39 | I38: ='P&L'!I39 | J38: ='P&L'!J39 | K38: ='P&L'!K39 | ... AM38: ='P&L'!AM39
B40: Annual Summary
B41: Metric | C41: Studio | D41: 2026 | E41: 2027 | F41: 2028 | G41: 2027 YoY | H41: 2028 YoY
B42: Total Sales | D42: =SUM(D43:D55) | E42: =SUM(E43:E55) | F42: =SUM(F43:F55) | G42: =IFERROR((E42-D42)/D42,0) | H42: =IFERROR((F42-E42)/E42,0)
C43: Berkeley | D43: =SUM('Sales Forecast'!D6:O6) | E43: =SUM('Sales Forecast'!P6:AA6) | F43: =SUM('Sales Forecast'!AB6:AM6) | G43: =IFERROR((E41-D41)/D41,0) | H43: =IFERROR((F41-E41)/E41,0)
C44: Culver City | D44: =SUM('Sales Forecast'!D7:O7) | E44: =SUM('Sales Forecast'!P7:AA7) | F44: =SUM('Sales Forecast'!AB7:AM7) | G44: =IFERROR((E42-D42)/D42,0) | H44: =IFERROR((F42-E42)/E42,0)
C45: Danville | D45: =SUM('Sales Forecast'!D8:O8) | E45: =SUM('Sales Forecast'!P8:AA8) | F45: =SUM('Sales Forecast'!AB8:AM8) | G45: =IFERROR((E43-D43)/D43,0) | H45: =IFERROR((F43-E43)/E43,0)
C46: Lafayette | D46: =SUM('Sales Forecast'!D9:O9) | E46: =SUM('Sales Forecast'!P9:AA9) | F46: =SUM('Sales Forecast'!AB9:AM9) | G46: =IFERROR((E44-D44)/D44,0) | H46: =IFERROR((F44-E44)/E44,0)
C47: Marin | D47: =SUM('Sales Forecast'!D10:O10) | E47: =SUM('Sales Forecast'!P10:AA10) | F47: =SUM('Sales Forecast'!AB10:AM10) | G47: =IFERROR((E45-D45)/D45,0) | H47: =IFERROR((F45-E45)/E45,0)
C48: Ocean Park | D48: =SUM('Sales Forecast'!D11:O11) | E48: =SUM('Sales Forecast'!P11:AA11) | F48: =SUM('Sales Forecast'!AB11:AM11) | G48: =IFERROR((E46-D46)/D46,0) | H48: =IFERROR((F46-E46)/E46,0)
C49: Presidio Heights | D49: =SUM('Sales Forecast'!D12:O12) | E49: =SUM('Sales Forecast'!P12:AA12) | F49: =SUM('Sales Forecast'!AB12:AM12) | G49: =IFERROR((E47-D47)/D47,0) | H49: =IFERROR((F47-E47)/E47,0)
C50: Russian Hill | D50: =SUM('Sales Forecast'!D13:O13) | E50: =SUM('Sales Forecast'!P13:AA13) | F50: =SUM('Sales Forecast'!AB13:AM13) | G50: =IFERROR((E48-D48)/D48,0) | H50: =IFERROR((F48-E48)/E48,0)
C51: Santa Barbara | D51: =SUM('Sales Forecast'!D14:O14) | E51: =SUM('Sales Forecast'!P14:AA14) | F51: =SUM('Sales Forecast'!AB14:AM14) | G51: =IFERROR((E49-D49)/D49,0) | H51: =IFERROR((F49-E49)/E49,0)
C52: Santa Monica | D52: =SUM('Sales Forecast'!D15:O15) | E52: =SUM('Sales Forecast'!P15:AA15) | F52: =SUM('Sales Forecast'!AB15:AM15) | G52: =IFERROR((E50-D50)/D50,0) | H52: =IFERROR((F50-E50)/E50,0)
C53: West Portal | D53: =SUM('Sales Forecast'!D16:O16) | E53: =SUM('Sales Forecast'!P16:AA16) | F53: =SUM('Sales Forecast'!AB16:AM16) | G53: =IFERROR((E51-D51)/D51,0) | H53: =IFERROR((F51-E51)/E51,0)
C54: Westwood | D54: =SUM('Sales Forecast'!D17:O17) | E54: =SUM('Sales Forecast'!P17:AA17) | F54: =SUM('Sales Forecast'!AB17:AM17) | G54: =IFERROR((E52-D52)/D52,0) | H54: =IFERROR((F52-E52)/E52,0)
C55: Head Office | D55: 0 | E55: 0 | F55: 0 | G55: =IFERROR((E55-D55)/D55,0) | H55: =IFERROR((F55-E55)/E55,0)
B57: Total EBITDA | D57: =SUM(D58:D70) | E57: =SUM(E58:E70) | F57: =SUM(F58:F70) | G57: =IFERROR((E57-D57)/D57,0) | H57: =IFERROR((F57-E57)/E57,0)
C58: Berkeley | D58: =SUM(D23:O23) | E58: =SUM(P23:AA23) | F58: =SUM(AB23:AM23) | G58: =IFERROR((E58-D58)/D58,0) | H58: =IFERROR((F58-E58)/E58,0)
C59: Culver City | D59: =SUM(D24:O24) | E59: =SUM(P24:AA24) | F59: =SUM(AB24:AM24) | G59: =IFERROR((E59-D59)/D59,0) | H59: =IFERROR((F59-E59)/E59,0)
C60: Danville | D60: =SUM(D25:O25) | E60: =SUM(P25:AA25) | F60: =SUM(AB25:AM25) | G60: =IFERROR((E60-D60)/D60,0) | H60: =IFERROR((F60-E60)/E60,0)
C61: Lafayette | D61: =SUM(D26:O26) | E61: =SUM(P26:AA26) | F61: =SUM(AB26:AM26) | G61: =IFERROR((E61-D61)/D61,0) | H61: =IFERROR((F61-E61)/E61,0)
C62: Marin | D62: =SUM(D27:O27) | E62: =SUM(P27:AA27) | F62: =SUM(AB27:AM27) | G62: =IFERROR((E62-D62)/D62,0) | H62: =IFERROR((F62-E62)/E62,0)
C63: Ocean Park | D63: =SUM(D28:O28) | E63: =SUM(P28:AA28) | F63: =SUM(AB28:AM28) | G63: =IFERROR((E63-D63)/D63,0) | H63: =IFERROR((F63-E63)/E63,0)
C64: Presidio Heights | D64: =SUM(D29:O29) | E64: =SUM(P29:AA29) | F64: =SUM(AB29:AM29) | G64: =IFERROR((E64-D64)/D64,0) | H64: =IFERROR((F64-E64)/E64,0)
C65: Russian Hill | D65: =SUM(D30:O30) | E65: =SUM(P30:AA30) | F65: =SUM(AB30:AM30) | G65: =IFERROR((E65-D65)/D65,0) | H65: =IFERROR((F65-E65)/E65,0)
C66: Santa Barbara | D66: =SUM(D31:O31) | E66: =SUM(P31:AA31) | F66: =SUM(AB31:AM31) | G66: =IFERROR((E66-D66)/D66,0) | H66: =IFERROR((F66-E66)/E66,0)
C67: Santa Monica | D67: =SUM(D32:O32) | E67: =SUM(P32:AA32) | F67: =SUM(AB32:AM32) | G67: =IFERROR((E67-D67)/D67,0) | H67: =IFERROR((F67-E67)/E67,0)
C68: West Portal | D68: =SUM(D33:O33) | E68: =SUM(P33:AA33) | F68: =SUM(AB33:AM33) | G68: =IFERROR((E68-D68)/D68,0) | H68: =IFERROR((F68-E68)/E68,0)
C69: Westwood | D69: =SUM(D34:O34) | E69: =SUM(P34:AA34) | F69: =SUM(AB34:AM34) | G69: =IFERROR((E69-D69)/D69,0) | H69: =IFERROR((F69-E69)/E69,0)
C70: Head Office | D70: =SUM('HO P&L'!D36:O36) | E70: =SUM('HO P&L'!P36:AA36) | F70: =SUM('HO P&L'!AB36:AM36) | G70: =IFERROR((E70-D70)/D70,0) | H70: =IFERROR((F70-E70)/E70,0)
B72: Total Adj-EBITDA | D72: =SUM(D38:O38) | E72: =SUM(P38:AA38) | F72: =SUM(AB38:AM38) | G72: =IFERROR((E72-D72)/D72,0) | H72: =IFERROR((F72-E72)/E72,0)

Sheet Assumptions
B2: Assumptions
B3: Yellow cells are editable inputs. All other tabs reference these values.
B5: 1. Model Control
B6: Last Actuals Month | C6: May 2026
B7: Forecast Horizon (months) | C7: 32
B8: Forecast End Month | C8: Dec 2028
B10: 2. Revenue Recognition Curves
B11: Lag Month (0 = sale month) | C11: 0 | D11: 1 | E11: 2 | F11: 3 | G11: 4 | H11: 5 | I11: 6 | J11: Sum
B12: Earned % | C12: 0.3868 | D12: 0.2997 | E12: 0.0855 | F12: 0.0482 | G12: 0.0261 | H12: 0.0193 | I12: 0.0144 | J12: =SUM(C12:I12)
B13: Breakage % | C13: 0.0017 | D13: 0.0602 | E13: 0.0053 | F13: 0.0003 | G13: 0.0001 | H13: 0.0008 | I13: 0.0516 | J13: =SUM(C13:I13)
B14: Total (Earned + Breakage) | C14: =C12+C13 | D14: =D12+D13 | E14: =E12+E13 | F14: =F12+F13 | G14: =G12+G13 | H14: =H12+H13 | I14: =I12+I13 | J14: =SUM(C14:I14)
B16: 3. Rates (% of Gross Revenue)
B17: Refund Rate | C17: -0.0158 | D17: Refunds as % of gross revenue. Negative reduces net revenue.
B18: Discount Rate | C18: -0.0531 | D18: Discounts as % of gross revenue. Negative reduces net revenue.
B19: Merchant Fee % | C19: 0.0286 | D19: Payment processor fees as % of revenue.
B20: COGS % | C20: 0.0096 | D20: Cost of goods sold as % of revenue (retail).
B22: 4. Annual Escalation Rates
B23: Rent / Property Escalation | C23: 0.03 | D23: 3% annual rent step-up applied to forecast months
B24: Other OpEx Escalation | C24: 0.04 | D24: 4% annual escalation for all non-rent OpEx categories
B25: Sales YoY Growth | C25: 0.05 | D25: 5% YoY assumed for 2028 (applied to 2027 seasonal pattern)
B27: 5. Loan Terms (as of Apr 2026)
B28: Loan | C28: Original Amt | D28: Current Balance | E28: Rate (Annual) | F28: Avg Monthly Pmt | G28: Start Date | H28: Type
B29: MindBody Loan - SM | C29: 193706.66 | D29: 99348.21 | E29: 0 | F29: 18871.69 | G29: 2025-09 | H29: Amortizing
B30: MindBody Loan - PH | C30: 130000 | D30: 46989.79 | E30: 0 | F30: 16602.04 | G30: 2025-09 | H30: Amortizing
B31: MindBody Loan - LF | C31: 69249.28 | D31: 20599.85 | E31: 0 | F31: 12162.36 | G31: 2025-10 | H31: Amortizing
B32: MindBody Loan - MR | C32: 67443.81 | D32: 14815.18 | E32: 0 | F32: 13157.16 | G32: 2025-10 | H32: Amortizing
B33: Samson Loan | C33: 265414.78 | D33: 189034.12 | E33: 0 | F33: 25460.22 | G33: 2025-11 | H33: Amortizing
B34: Specialty Capital Loan | C34: 217184.21 | D34: 165407.89 | E34: 0 | F34: 25888.16 | G34: 2025-12 | H34: Amortizing
B35: Norbrook Inc Loan | C35: 162318 | D35: 162318 | E35: 0.08 | F35: 0 | G35: 2025-10 | H35: Interest-Only
B36: TOTAL DEBT | D36: =SUM(D29:D35) | F36: =SUM(F29:F35)
B38: 6. Active Studios
B39: Code | C39: Name
B40: BK | C40: Berkeley
B41: CC | C41: Culver City
B42: DN | C42: Danville
B43: LF | C43: Lafayette
B44: MR | C44: Marin
B45: OP | C45: Ocean Park
B46: PH | C46: Presidio Heights
B47: RH | C47: Russian Hill
B48: SB | C48: Santa Barbara
B49: SM | C49: Santa Monica
B50: WP | C50: West Portal
B51: WW | C51: Westwood

Sheet Sales Forecast
B2: Sales Forecast (Gross)
B3: Jan-Jul 2026 actuals (locked, Cat-authoritative). Aug 2026 onwards forecast (editable).
B4: Per-Studio Monthly Sales
B5: Code | C5: Studio | D5: Jan 2026 | E5: Feb 2026 | F5: Mar 2026 | G5: Apr 2026 | H5: May 2026 (A) | I5: Jun 2026 | J5: Jul 2026 (A) | K5: Aug 2026 | L5: Sep 2026 | M5: Oct 2026 | N5: Nov 2026 | O5: Dec 2026 | P5: Jan 2027 | Q5: Feb 2027 | R5: Mar 2027 | S5: Apr 2027 | T5: May 2027 | U5: Jun 2027 | V5: Jul 2027 | W5: Aug 2027 | X5: Sep 2027 | Y5: Oct 2027 | Z5: Nov 2027 | AA5: Dec 2027 | AB5: Jan 2028 | AC5: Feb 2028 | AD5: Mar 2028 | AE5: Apr 2028 | AF5: May 2028 | AG5: Jun 2028 | AH5: Jul 2028 | AI5: Aug 2028 | AJ5: Sep 2028 | AK5: Oct 2028 | AL5: Nov 2028 | AM5: Dec 2028
B6: BK | C6: Berkeley | D6: 124393 | E6: 129377 | F6: 103159 | G6: 136117 | H6: 83273 | I6: 100821 | J6: 99551 | K6: 120000 | L6: 120000 | M6: 130000 | N6: 130000 | O6: 149000 | P6: 130612.65 | Q6: 135845.85 | R6: 108316.95 | S6: 142922.85 | T6: 87649.8 | U6: 115500 | V6: 110250 | W6: 126000 | X6: 126000 | Y6: 136500 | Z6: 136500 | AA6: 156450 | AB6: 137143.28 | AC6: 142638.14 | AD6: 113732.8 | AE6: 150068.99 | AF6: 92032.29 | AG6: 121275 | AH6: 115762.5 | AI6: 132300 | AJ6: 132300 | AK6: 143325 | AL6: 143325 | AM6: 164272.5
B7: CC | C7: Culver City | D7: 43840 | E7: 38704 | F7: 42619 | G7: 39690 | H7: 43327 | I7: 32522 | J7: 42903 | K7: 50000 | L7: 53000 | M7: 60000 | N7: 64000 | O7: 60000 | P7: 61000 | Q7: 73307 | R7: 69238 | S7: 75096 | T7: 70949 | U7: 64231 | V7: 95489 | W7: 107456 | X7: 102425 | Y7: 95000 | Z7: 95000 | AA7: 95000 | AB7: 64050 | AC7: 76972.35 | AD7: 72699.9 | AE7: 78850.8 | AF7: 74496.45 | AG7: 67442.55 | AH7: 100263.45 | AI7: 112828.8 | AJ7: 107546.25 | AK7: 99750 | AL7: 99750 | AM7: 99750
B8: DN | C8: Danville | D8: 24286 | E8: 23358 | F8: 20289 | G8: 20363 | H8: 15337 | I8: 20327 | J8: 16795 | K8: 25000 | L8: 25000 | M8: 30000 | N8: 25000 | O8: 32000 | P8: 32000 | Q8: 40000 | R8: 40000 | S8: 45000 | T8: 45000 | U8: 50000 | V8: 50000 | W8: 50000 | X8: 55000 | Y8: 55000 | Z8: 55000 | AA8: 55000 | AB8: 33600 | AC8: 42000 | AD8: 42000 | AE8: 47250 | AF8: 47250 | AG8: 52500 | AH8: 52500 | AI8: 52500 | AJ8: 57750 | AK8: 57750 | AL8: 57750 | AM8: 57750
B9: LF | C9: Lafayette | D9: 92365 | E9: 126186 | F9: 78385 | G9: 106542 | H9: 71444 | I9: 81024 | J9: 86878 | K9: 80000 | L9: 80250 | M9: 85000 | N9: 95000 | O9: 110000 | P9: 96983.25 | Q9: 132495.3 | R9: 82304.25 | S9: 111869.1 | T9: 75832.05 | U9: 84000 | V9: 84262.5 | W9: 84000 | X9: 84262.5 | Y9: 89250 | Z9: 99750 | AA9: 115500 | AB9: 101832.41 | AC9: 139120.07 | AD9: 86419.46 | AE9: 117462.56 | AF9: 79623.65 | AG9: 88200 | AH9: 88475.62 | AI9: 88200 | AJ9: 88475.62 | AK9: 93712.5 | AL9: 104737.5 | AM9: 121275
B10: MR | C10: Marin | D10: 100589 | E10: 114193 | F10: 90196 | G10: 140256 | H10: 74382 | I10: 98742 | J10: 109856 | K10: 120000 | L10: 98000 | M10: 110000 | N10: 120000 | O10: 115000 | P10: 105618.45 | Q10: 119902.65 | R10: 94705.8 | S10: 147268.8 | T10: 78685.95 | U10: 101115 | V10: 99750 | W10: 126000 | X10: 102900 | Y10: 115500 | Z10: 126000 | AA10: 120750 | AB10: 110899.37 | AC10: 125897.78 | AD10: 99441.09 | AE10: 154632.24 | AF10: 82620.25 | AG10: 106170.75 | AH10: 104737.5 | AI10: 132300 | AJ10: 108045 | AK10: 121275 | AL10: 132300 | AM10: 126787.5
B11: OP | C11: Ocean Park | D11: 60583 | E11: 59614 | F11: 62052 | G11: 73815 | H11: 63770 | I11: 50286 | J11: 58162 | K11: 60000 | L11: 63000 | M11: 70000 | N11: 75000 | O11: 60000 | P11: 63612.15 | Q11: 62594.7 | R11: 65154.6 | S11: 77505.75 | T11: 67045.65 | U11: 67410 | V11: 78750 | W11: 63000 | X11: 66150 | Y11: 73500 | Z11: 78750 | AA11: 63000 | AB11: 66792.76 | AC11: 65724.43 | AD11: 68412.33 | AE11: 81381.04 | AF11: 70397.93 | AG11: 70780.5 | AH11: 82687.5 | AI11: 66150 | AJ11: 69457.5 | AK11: 77175 | AL11: 82687.5 | AM11: 66150
B12: PH | C12: Presidio Heights | D12: 124927 | E12: 180839 | F12: 115051 | G12: 179323 | H12: 93511 | I12: 113383 | J12: 117515 | K12: 155000 | L12: 120000 | M12: 125000 | N12: 140000 | O12: 150000 | P12: 131173.35 | Q12: 189880.95 | R12: 120803.55 | S12: 188289.15 | T12: 100401 | U12: 120750 | V12: 115500 | W12: 162750 | X12: 126000 | Y12: 131250 | Z12: 147000 | AA12: 157500 | AB12: 137732.02 | AC12: 199375 | AD12: 126843.73 | AE12: 197703.61 | AF12: 105421.05 | AG12: 126787.5 | AH12: 121275 | AI12: 170887.5 | AJ12: 132300 | AK12: 137812.5 | AL12: 154350 | AM12: 165375
B13: RH | C13: Russian Hill | D13: 96145 | E13: 94253 | F13: 85589 | G13: 108129 | H13: 66857 | I13: 71619 | J13: 75936 | K13: 95000 | L13: 80000 | M13: 82000 | N13: 80000 | O13: 88000 | P13: 100952.25 | Q13: 98965.65 | R13: 89868.45 | S13: 113535.45 | T13: 71700.3 | U13: 80850 | V13: 78750 | W13: 99750 | X13: 84000 | Y13: 86100 | Z13: 84000 | AA13: 92400 | AB13: 105999.86 | AC13: 103913.93 | AD13: 94361.87 | AE13: 119212.22 | AF13: 75285.32 | AG13: 84892.5 | AH13: 82687.5 | AI13: 104737.5 | AJ13: 88200 | AK13: 90405 | AL13: 88200 | AM13: 97020
B14: SB | C14: Santa Barbara | D14: 32747 | E14: 27799 | F14: 25898 | G14: 23393 | H14: 20133 | I14: 17783 | J14: 18714 | K14: 30000 | L14: 30000 | M14: 33000 | N14: 35000 | O14: 35000 | P14: 59231 | Q14: 60132 | R14: 52754 | S14: 51670 | T14: 60236 | U14: 51621 | V14: 62000 | W14: 63000 | X14: 73000 | Y14: 65000 | Z14: 64200 | AA14: 64200 | AB14: 62192.55 | AC14: 63138.6 | AD14: 55391.7 | AE14: 54253.5 | AF14: 63247.8 | AG14: 54202.05 | AH14: 65100 | AI14: 66150 | AJ14: 76650 | AK14: 68250 | AL14: 67410 | AM14: 67410
B15: SM | C15: Santa Monica | D15: 184491 | E15: 161597 | F15: 192258 | G15: 157521 | H15: 206632 | I15: 130716 | J15: 163688 | K15: 200000 | L15: 190000 | M15: 220000 | N15: 251450 | O15: 190000 | P15: 193715.55 | Q15: 169676.85 | R15: 201870.9 | S15: 165397.05 | T15: 217676.55 | U15: 210000 | V15: 210000 | W15: 210000 | X15: 199500 | Y15: 231000 | Z15: 264022.5 | AA15: 199500 | AB15: 203401.33 | AC15: 178160.69 | AD15: 211964.45 | AE15: 173666.9 | AF15: 228560.38 | AG15: 220500 | AH15: 220500 | AI15: 220500 | AJ15: 209475 | AK15: 242550 | AL15: 277223.62 | AM15: 209475
B16: WP | C16: West Portal | D16: 1573 | E16: 1513 | F16: 784 | G16: 370 | H16: 26 | I16: 225 | J16: 99 | K16: 78000 | L16: 75000 | M16: 80000 | N16: 80000 | O16: 80000 | P16: 90025 | Q16: 86822 | R16: 85300 | S16: 127703 | T16: 79689 | U16: 76768 | V16: 70767 | W16: 102739 | X16: 68837 | Y16: 83777 | Z16: 79979 | AA16: 79880 | AB16: 94526.25 | AC16: 91163.1 | AD16: 89565 | AE16: 134088.15 | AF16: 83673.45 | AG16: 80606.4 | AH16: 74305.35 | AI16: 107875.95 | AJ16: 72278.85 | AK16: 87965.85 | AL16: 83977.95 | AM16: 83874
B17: WW | C17: Westwood | D17: 71360 | E17: 69405 | F17: 62992 | G17: 49441 | H17: 60750 | I17: 41757 | J17: 47537 | K17: 64000 | L17: 72000 | M17: 80000 | N17: 85600 | O17: 74900 | P17: 74928 | Q17: 72875.25 | R17: 66141.6 | S17: 51913.05 | T17: 63897.75 | U17: 68250 | V17: 65100 | W17: 67200 | X17: 75600 | Y17: 84000 | Z17: 89880 | AA17: 78645 | AB17: 78674.4 | AC17: 76519.01 | AD17: 69448.68 | AE17: 54508.7 | AF17: 67092.64 | AG17: 71662.5 | AH17: 68355 | AI17: 70560 | AJ17: 79380 | AK17: 88200 | AL17: 94374 | AM17: 82577.25
B18: TOTAL | C18: All Studios | D18: =SUM(D6:D17) | E18: =SUM(E6:E17) | F18: =SUM(F6:F17) | G18: =SUM(G6:G17) | H18: =SUM(H6:H17) | I18: =SUM(I6:I17) | J18: =SUM(J6:J17) | K18: =SUM(K6:K17) | ... AM18: =SUM(AM6:AM17)
B20: Annual Summary
B21: Code | C21: Studio | D21: 2026 | E21: 2027 | F21: 2028 | G21: 2027 YoY | H21: 2028 YoY
B22: BK | C22: Berkeley | D22: =SUM(D6:O6) | E22: =SUM(P6:AA6) | F22: =SUM(AB6:AM6) | G22: =IFERROR((E22-D22)/D22,0) | H22: =IFERROR((F22-E22)/E22,0)
B23: CC | C23: Culver City | D23: =SUM(D7:O7) | E23: =SUM(P7:AA7) | F23: =SUM(AB7:AM7) | G23: =IFERROR((E23-D23)/D23,0) | H23: =IFERROR((F23-E23)/E23,0)
B24: DN | C24: Danville | D24: =SUM(D8:O8) | E24: =SUM(P8:AA8) | F24: =SUM(AB8:AM8) | G24: =IFERROR((E24-D24)/D24,0) | H24: =IFERROR((F24-E24)/E24,0)
B25: LF | C25: Lafayette | D25: =SUM(D9:O9) | E25: =SUM(P9:AA9) | F25: =SUM(AB9:AM9) | G25: =IFERROR((E25-D25)/D25,0) | H25: =IFERROR((F25-E25)/E25,0)
B26: MR | C26: Marin | D26: =SUM(D10:O10) | E26: =SUM(P10:AA10) | F26: =SUM(AB10:AM10) | G26: =IFERROR((E26-D26)/D26,0) | H26: =IFERROR((F26-E26)/E26,0)
B27: OP | C27: Ocean Park | D27: =SUM(D11:O11) | E27: =SUM(P11:AA11) | F27: =SUM(AB11:AM11) | G27: =IFERROR((E27-D27)/D27,0) | H27: =IFERROR((F27-E27)/E27,0)
B28: PH | C28: Presidio Heights | D28: =SUM(D12:O12) | E28: =SUM(P12:AA12) | F28: =SUM(AB12:AM12) | G28: =IFERROR((E28-D28)/D28,0) | H28: =IFERROR((F28-E28)/E28,0)
B29: RH | C29: Russian Hill | D29: =SUM(D13:O13) | E29: =SUM(P13:AA13) | F29: =SUM(AB13:AM13) | G29: =IFERROR((E29-D29)/D29,0) | H29: =IFERROR((F29-E29)/E29,0)
B30: SB | C30: Santa Barbara | D30: =SUM(D14:O14) | E30: =SUM(P14:AA14) | F30: =SUM(AB14:AM14) | G30: =IFERROR((E30-D30)/D30,0) | H30: =IFERROR((F30-E30)/E30,0)
B31: SM | C31: Santa Monica | D31: =SUM(D15:O15) | E31: =SUM(P15:AA15) | F31: =SUM(AB15:AM15) | G31: =IFERROR((E31-D31)/D31,0) | H31: =IFERROR((F31-E31)/E31,0)
B32: WP | C32: West Portal | D32: =SUM(D16:O16) | E32: =SUM(P16:AA16) | F32: =SUM(AB16:AM16) | G32: =IFERROR((E32-D32)/D32,0) | H32: =IFERROR((F32-E32)/E32,0)
B33: WW | C33: Westwood | D33: =SUM(D17:O17) | E33: =SUM(P17:AA17) | F33: =SUM(AB17:AM17) | G33: =IFERROR((E33-D33)/D33,0) | H33: =IFERROR((F33-E33)/E33,0)
B34: TOTAL | C34: All Studios | D34: =SUM(D22:D33) | E34: =SUM(E22:E33) | F34: =SUM(F22:F33) | G34: =IFERROR((E34-D34)/D34,0) | H34: =IFERROR((F34-E34)/E34,0)
B100: 2025 SALES HISTORY (hidden helper for lag formulas) | D100: 2025-07 | E100: 2025-08 | F100: 2025-09 | G100: 2025-10 | H100: 2025-11 | I100: 2025-12
D101: 808077 | E101: 930709 | F101: 758432 | G101: 830044 | H101: 833160 | I101: 847328
B102: 2025 helper: BK (Berkeley) | H102: 102111.01 | I102: 103847.42
B103: 2025 helper: CC (Culver City) | H103: 36886.61 | I103: 37513.88
B104: 2025 helper: DN (Danville) | H104: 18359.97 | I104: 18672.19
B105: 2025 helper: LF (Lafayette) | H105: 84253.69 | I105: 85686.43
B106: 2025 helper: MR (Marin) | H106: 92130.72 | I106: 93697.42
B107: 2025 helper: OP (Ocean Park) | H107: 56662.27 | I107: 57625.82
B108: 2025 helper: PH (Presidio Heights) | H108: 123229.91 | I108: 125325.45
B109: 2025 helper: RH (Russian Hill) | H109: 80127.42 | I109: 81490
B110: 2025 helper: SB (Santa Barbara) | H110: 23052.3 | I110: 23444.3
B111: 2025 helper: SM (Santa Monica) | H111: 159966.86 | I111: 162687.12
B112: 2025 helper: WP (West Portal) | H112: 755.57 | I112: 768.42
B113: 2025 helper: WW (Westwood) | H113: 55623.67 | I113: 56569.55

Sheet Cash, Debt & Equity
B2: Cash, Debt & Equity
B4: Item | D4: Jan 2026 | E4: Feb 2026 | F4: Mar 2026 | G4: Apr 2026 | H4: May 2026 | I4: Jun 2026 | J4: Jul 2026 | K4: Aug 2026 | L4: Sep 2026 | M4: Oct 2026 | N4: Nov 2026 | O4: Dec 2026 | P4: Jan 2027 | Q4: Feb 2027 | R4: Mar 2027 | S4: Apr 2027 | T4: May 2027 | U4: Jun 2027 | V4: Jul 2027 | W4: Aug 2027 | X4: Sep 2027 | Y4: Oct 2027 | Z4: Nov 2027 | AA4: Dec 2027 | AB4: Jan 2028 | AC4: Feb 2028 | AD4: Mar 2028 | AE4: Apr 2028 | AF4: May 2028 | AG4: Jun 2028 | AH4: Jul 2028 | AI4: Aug 2028 | AJ4: Sep 2028 | AK4: Oct 2028 | AL4: Nov 2028 | AM4: Dec 2028
B5: CASH POSITION
B6: Ending Cash Balance (from CF) | D6: ='Cash Flow Forecast'!D38 | E6: ='Cash Flow Forecast'!E38 | F6: ='Cash Flow Forecast'!F38 | G6: ='Cash Flow Forecast'!G38 | H6: ='Cash Flow Forecast'!H38 | I6: ='Cash Flow Forecast'!I38 | J6: ='Cash Flow Forecast'!J38 | K6: ='Cash Flow Forecast'!K38 | ... AM6: ='Cash Flow Forecast'!AM38
B8: DEBT SCHEDULE — Loan Balances by Month
B9: MindBody Loan - SM | D9: 0 | E9: 0 | F9: 0 | G9: 99348.21 | H9: 0 | I9: =MAX(H9-18871.69,0) | J9: =MAX(I9-18871.69,0) | K9: =MAX(J9-18871.69,0) | L9: =MAX(K9-18871.69,0) | M9: =MAX(L9-18871.69,0) | N9: =MAX(M9-18871.69,0) | O9: =MAX(N9-18871.69,0) | P9: =MAX(O9-18871.69,0) | ... AM9: =MAX(AL9-18871.69,0)
B10: MindBody Loan - PH | D10: 0 | E10: 0 | F10: 0 | G10: 46989.79 | H10: 0 | I10: =MAX(H10-16602.04,0) | J10: =MAX(I10-16602.04,0) | K10: =MAX(J10-16602.04,0) | L10: =MAX(K10-16602.04,0) | M10: =MAX(L10-16602.04,0) | N10: =MAX(M10-16602.04,0) | O10: =MAX(N10-16602.04,0) | P10: =MAX(O10-16602.04,0) | ... AM10: =MAX(AL10-16602.04,0)
B11: MindBody Loan - LF | D11: 0 | E11: 0 | F11: 0 | G11: 20599.85 | H11: 0 | I11: =MAX(H11-12162.36,0) | J11: =MAX(I11-12162.36,0) | K11: =MAX(J11-12162.36,0) | L11: =MAX(K11-12162.36,0) | M11: =MAX(L11-12162.36,0) | N11: =MAX(M11-12162.36,0) | O11: =MAX(N11-12162.36,0) | P11: =MAX(O11-12162.36,0) | ... AM11: =MAX(AL11-12162.36,0)
B12: MindBody Loan - MR | D12: 0 | E12: 0 | F12: 0 | G12: 14815.18 | H12: 0 | I12: =MAX(H12-13157.16,0) | J12: =MAX(I12-13157.16,0) | K12: =MAX(J12-13157.16,0) | L12: =MAX(K12-13157.16,0) | M12: =MAX(L12-13157.16,0) | N12: =MAX(M12-13157.16,0) | O12: =MAX(N12-13157.16,0) | P12: =MAX(O12-13157.16,0) | ... AM12: =MAX(AL12-13157.16,0)
B13: Samson Loan | D13: 205426.16 | E13: 189034.12 | F13: 154505.72 | G13: 129045.5 | H13: 94517.1 | I13: =MAX(H13-25460.22,0) | J13: =MAX(I13-25460.22,0) | K13: =MAX(J13-25460.22,0) | L13: =MAX(K13-25460.22,0) | M13: =MAX(L13-25460.22,0) | N13: =MAX(M13-25460.22,0) | O13: =MAX(N13-25460.22,0) | P13: =MAX(O13-25460.22,0) | ... AM13: =MAX(AL13-25460.22,0)
B14: Specialty Capital Loan | D14: 187921.05 | E14: 165407.89 | F14: 135078.94 | G14: 112565.78 | H14: 90052.62 | I14: =MAX(H14-25888.16,0) | J14: =MAX(I14-25888.16,0) | K14: =MAX(J14-25888.16,0) | L14: =MAX(K14-25888.16,0) | M14: =MAX(L14-25888.16,0) | N14: =MAX(M14-25888.16,0) | O14: =MAX(N14-25888.16,0) | P14: =MAX(O14-25888.16,0) | ... AM14: =MAX(AL14-25888.16,0)
B15: Norbrook Inc Loan | D15: 0 | E15: 0 | F15: 0 | G15: 162318 | H15: 0 | I15: =H15 | J15: =I15 | K15: =J15 | L15: =K15 | M15: =L15 | N15: =M15 | O15: =N15 | P15: =O15 | ... AM15: =AL15
B16: TOTAL DEBT | D16: =SUM(D9:D15) | E16: =SUM(E9:E15) | F16: =SUM(F9:F15) | G16: =SUM(G9:G15) | H16: =SUM(H9:H15) | I16: =SUM(I9:I15) | J16: =SUM(J9:J15) | K16: =SUM(K9:K15) | ... AM16: =SUM(AM9:AM15)
B18: MONTHLY DEBT SERVICE
B19: MindBody Loan - SM | D19: 0 | E19: 0 | F19: 0 | G19: 0 | H19: 0 | I19: =IF(I9>0,18871.69,0) | J19: =IF(J9>0,18871.69,0) | K19: =IF(K9>0,18871.69,0) | L19: =IF(L9>0,18871.69,0) | M19: =IF(M9>0,18871.69,0) | N19: =IF(N9>0,18871.69,0) | O19: =IF(O9>0,18871.69,0) | P19: =IF(P9>0,18871.69,0) | ... AM19: =IF(AM9>0,18871.69,0)
B20: MindBody Loan - PH | D20: 0 | E20: 0 | F20: 0 | G20: 0 | H20: 0 | I20: =IF(I10>0,16602.04,0) | J20: =IF(J10>0,16602.04,0) | K20: =IF(K10>0,16602.04,0) | L20: =IF(L10>0,16602.04,0) | M20: =IF(M10>0,16602.04,0) | N20: =IF(N10>0,16602.04,0) | O20: =IF(O10>0,16602.04,0) | P20: =IF(P10>0,16602.04,0) | ... AM20: =IF(AM10>0,16602.04,0)
B21: MindBody Loan - LF | D21: 0 | E21: 0 | F21: 0 | G21: 0 | H21: 0 | I21: =IF(I11>0,12162.36,0) | J21: =IF(J11>0,12162.36,0) | K21: =IF(K11>0,12162.36,0) | L21: =IF(L11>0,12162.36,0) | M21: =IF(M11>0,12162.36,0) | N21: =IF(N11>0,12162.36,0) | O21: =IF(O11>0,12162.36,0) | P21: =IF(P11>0,12162.36,0) | ... AM21: =IF(AM11>0,12162.36,0)
B22: MindBody Loan - MR | D22: 0 | E22: 0 | F22: 0 | G22: 0 | H22: 0 | I22: =IF(I12>0,13157.16,0) | J22: =IF(J12>0,13157.16,0) | K22: =IF(K12>0,13157.16,0) | L22: =IF(L12>0,13157.16,0) | M22: =IF(M12>0,13157.16,0) | N22: =IF(N12>0,13157.16,0) | O22: =IF(O12>0,13157.16,0) | P22: =IF(P12>0,13157.16,0) | ... AM22: =IF(AM12>0,13157.16,0)
B23: Samson Loan | D23: 0 | E23: 0 | F23: 0 | G23: 0 | H23: 94517.1 | I23: =IF(I13>0,25460.22,0) | J23: =IF(J13>0,25460.22,0) | K23: =IF(K13>0,25460.22,0) | L23: =IF(L13>0,25460.22,0) | M23: =IF(M13>0,25460.22,0) | N23: =IF(N13>0,25460.22,0) | O23: =IF(O13>0,25460.22,0) | P23: =IF(P13>0,25460.22,0) | ... AM23: =IF(AM13>0,25460.22,0)
B24: Specialty Capital Loan | D24: 0 | E24: 0 | F24: 0 | G24: 0 | H24: 90052.62 | I24: =IF(I14>0,25888.16,0) | J24: =IF(J14>0,25888.16,0) | K24: =IF(K14>0,25888.16,0) | L24: =IF(L14>0,25888.16,0) | M24: =IF(M14>0,25888.16,0) | N24: =IF(N14>0,25888.16,0) | O24: =IF(O14>0,25888.16,0) | P24: =IF(P14>0,25888.16,0) | ... AM24: =IF(AM14>0,25888.16,0)
B25: Norbrook Inc Loan | D25: 0 | E25: 0 | F25: 0 | G25: 0 | H25: 0 | I25: =I15*0.08/12 | J25: =J15*0.08/12 | K25: =K15*0.08/12 | L25: =L15*0.08/12 | M25: =M15*0.08/12 | N25: =N15*0.08/12 | O25: =O15*0.08/12 | P25: =P15*0.08/12 | ... AM25: =AM15*0.08/12
B26: TOTAL DEBT SERVICE | D26: =SUM(D19:D25) | E26: =SUM(E19:E25) | F26: =SUM(F19:F25) | G26: =SUM(G19:G25) | H26: =SUM(H19:H25) | I26: =SUM(I19:I25) | J26: =SUM(J19:J25) | K26: =SUM(K19:K25) | ... AM26: =SUM(AM19:AM25)
B28: OWNER EQUITY / INTERCOMPANY
B29: Intercompany Net Position | D29: 224773.04 | E29: 224773.04 | F29: 358106.37 | G29: 436439.7 | H29: 0 | I29: 0 | J29: 0 | K29: 0 | L29: 0 | M29: 0 | N29: 0 | O29: 0 | P29: 0 | Q29: 0 | R29: 0 | S29: 0 | T29: 0 | U29: 0 | V29: 0 | W29: 0 | X29: 0 | Y29: 0 | Z29: 0 | AA29: 0 | AB29: 0 | AC29: 0 | AD29: 0 | AE29: 0 | AF29: 0 | AG29: 0 | AH29: 0 | AI29: 0 | AJ29: 0 | AK29: 0 | AL29: 0 | AM29: 0

Sheet Cash Flow Forecast
B2: Cash Flow Forecast
B3: Actuals: Jan-Apr 2026 (light green). Forecast: May 2026 onwards. Net Change formulas sum operations + investing + financing.
B4: Monthly Cash Flow
B5: Line Item | C5: Annual Total | D5: Jan 2026 | E5: Feb 2026 | F5: Mar 2026 | G5: Apr 2026 | H5: May 2026 | I5: Jun 2026 | J5: Jul 2026 | K5: Aug 2026 | L5: Sep 2026 | M5: Oct 2026 | N5: Nov 2026 | O5: Dec 2026 | P5: Jan 2027 | Q5: Feb 2027 | R5: Mar 2027 | S5: Apr 2027 | T5: May 2027 | U5: Jun 2027 | V5: Jul 2027 | W5: Aug 2027 | X5: Sep 2027 | Y5: Oct 2027 | Z5: Nov 2027 | AA5: Dec 2027 | AB5: Jan 2028 | AC5: Feb 2028 | AD5: Mar 2028 | AE5: Apr 2028 | AF5: May 2028 | AG5: Jun 2028 | AH5: Jul 2028 | AI5: Aug 2028 | AJ5: Sep 2028 | AK5: Oct 2028 | AL5: Nov 2028 | AM5: Dec 2028
B6: CASH INFLOWS
B7: Total Cash Sales | D7: ='Sales Forecast'!D18 | E7: ='Sales Forecast'!E18 | F7: ='Sales Forecast'!F18 | G7: ='Sales Forecast'!G18 | H7: ='Sales Forecast'!H18 | I7: ='Sales Forecast'!I18 | J7: ='Sales Forecast'!J18 | K7: ='Sales Forecast'!K18 | ... AM7: ='Sales Forecast'!AM18
B9: OPERATING OUTFLOWS
B10: Property Costs | D10: 147113.46 | E10: 146344.65 | F10: 147382.66 | G10: 148059.43 | H10: 147112.25 | I10: 147112.25 | J10: 147112.25 | K10: 147112.25 | L10: 147112.25 | M10: 147112.25 | N10: 147112.25 | O10: 147112.25 | P10: 151525.62 | Q10: 151525.62 | R10: 151525.62 | S10: 151525.62 | T10: 151525.62 | U10: 151525.62 | V10: 151525.62 | W10: 151525.62 | X10: 151525.62 | Y10: 151525.62 | Z10: 151525.62 | AA10: 151525.62 | AB10: 156071.4 | AC10: 156071.4 | AD10: 156071.4 | AE10: 156071.4 | AF10: 156071.4 | AG10: 156071.4 | AH10: 156071.4 | AI10: 156071.4 | AJ10: 156071.4 | AK10: 156071.4 | AL10: 156071.4 | AM10: 156071.4
B11: Staff Costs | D11: 681232.98 | E11: 590412.06 | F11: 628953.81 | G11: 576480.98 | H11: 598615.61 | I11: 598615.61 | J11: 598615.61 | K11: 598615.61 | L11: 598615.61 | M11: 598615.61 | N11: 598615.61 | O11: 598615.61 | P11: 622560.23 | Q11: 622560.23 | R11: 622560.23 | S11: 622560.23 | T11: 622560.23 | U11: 622560.23 | V11: 622560.23 | W11: 622560.23 | X11: 622560.23 | Y11: 622560.23 | Z11: 622560.23 | AA11: 622560.23 | AB11: 647462.64 | AC11: 647462.64 | AD11: 647462.64 | AE11: 647462.64 | AF11: 647462.64 | AG11: 647462.64 | AH11: 647462.64 | AI11: 647462.64 | AJ11: 647462.64 | AK11: 647462.64 | AL11: 647462.64 | AM11: 647462.64
B12: Utilities | D12: 7087.42 | E12: 9973.09 | F12: 7034.72 | G12: 7270.22 | H12: 8720.11 | I12: 8720.11 | J12: 8720.11 | K12: 8720.11 | L12: 8720.11 | M12: 8720.11 | N12: 8720.11 | O12: 8720.11 | P12: 9043.82 | Q12: 9043.82 | R12: 9043.82 | S12: 9043.82 | T12: 9043.82 | U12: 9043.82 | V12: 9043.82 | W12: 9043.82 | X12: 9043.82 | Y12: 9043.82 | Z12: 9043.82 | AA12: 9043.82 | AB12: 9380.48 | AC12: 9380.48 | AD12: 8753.05 | AE12: 8753.05 | AF12: 8753.05 | AG12: 8753.05 | AH12: 8753.05 | AI12: 8753.05 | AJ12: 8753.05 | AK12: 8753.05 | AL12: 8753.05 | AM12: 8753.05
B13: Marketing & Promotion | D13: 27740.18 | E13: 27007.49 | F13: 16681.8 | G13: 5975.58 | H13: 16948.9 | I13: 16948.9 | J13: 16948.9 | K13: 16948.9 | L13: 16948.9 | M13: 16948.9 | N13: 16948.9 | O13: 16948.9 | P13: 17626.86 | Q13: 17626.86 | R13: 17626.86 | S13: 17626.86 | T13: 17626.86 | U13: 17626.86 | V13: 17626.86 | W13: 17626.86 | X13: 17626.86 | Y13: 17626.86 | Z13: 17626.86 | AA13: 17626.86 | AB13: 18331.93 | AC13: 18331.93 | AD13: 18331.93 | AE13: 18331.93 | AF13: 18331.93 | AG13: 18331.93 | AH13: 18331.93 | AI13: 18331.93 | AJ13: 18331.93 | AK13: 18331.93 | AL13: 18331.93 | AM13: 18331.93
B14: Administrative & G&A | D14: 32760.81 | E14: 38409.23 | F14: 33297.16 | G14: 28817.49 | H14: 37431.59 | I14: 37431.59 | J14: 37431.59 | K14: 37431.59 | L14: 37431.59 | M14: 37431.59 | N14: 37431.59 | O14: 37431.59 | P14: 38928.85 | Q14: 38928.85 | R14: 38928.85 | S14: 38928.85 | T14: 38928.85 | U14: 38928.85 | V14: 38928.85 | W14: 38928.85 | X14: 38928.85 | Y14: 38928.85 | Z14: 38928.85 | AA14: 38928.85 | AB14: 40486.01 | AC14: 40486.01 | AD14: 40486.01 | AE14: 40486.01 | AF14: 40486.01 | AG14: 40486.01 | AH14: 40486.01 | AI14: 40486.01 | AJ14: 40486.01 | AK14: 40486.01 | AL14: 40486.01 | AM14: 40486.01
B15: Professional Fees | D15: 42733.79 | E15: 24202.3 | F15: 22556.84 | G15: 25366 | H15: 24041.72 | I15: 24041.72 | J15: 24041.72 | K15: 24041.72 | L15: 24041.72 | M15: 24041.72 | N15: 24041.72 | O15: 24041.72 | P15: 25003.37 | Q15: 25003.37 | R15: 25003.37 | S15: 25003.37 | T15: 25003.37 | U15: 25003.37 | V15: 25003.37 | W15: 25003.37 | X15: 25003.37 | Y15: 25003.37 | Z15: 25003.37 | AA15: 25003.37 | AB15: 26003.5 | AC15: 26003.5 | AD15: 26003.5 | AE15: 26003.5 | AF15: 26003.5 | AG15: 26003.5 | AH15: 26003.5 | AI15: 26003.5 | AJ15: 26003.5 | AK15: 26003.5 | AL15: 26003.5 | AM15: 26003.5
B16: Travel & Meals | D16: 6819.03 | E16: 3543.33 | F16: 6002.36 | G16: 2789.61 | H16: 4111.78 | I16: 4111.78 | J16: 4111.78 | K16: 4111.78 | L16: 4111.78 | M16: 4111.78 | N16: 4111.78 | O16: 4111.78 | P16: 4276.25 | Q16: 4276.25 | R16: 4276.25 | S16: 4276.25 | T16: 4276.25 | U16: 4276.25 | V16: 4276.25 | W16: 4276.25 | X16: 4276.25 | Y16: 4276.25 | Z16: 4276.25 | AA16: 4276.25 | AB16: 4447.31 | AC16: 4447.31 | AD16: 4447.31 | AE16: 4447.31 | AF16: 4447.31 | AG16: 4447.31 | AH16: 4447.31 | AI16: 4447.31 | AJ16: 4447.31 | AK16: 4447.31 | AL16: 4447.31 | AM16: 4447.31
B17: Merchant Fees & COGS | D17: 65117.3 | E17: 67419.26 | F17: 61727.36 | G17: 65364.98 | H17: =H7*(Assumptions!$C$19+Assumptions!$C$20) | I17: =I7*(Assumptions!$C$19+Assumptions!$C$20) | J17: =J7*(Assumptions!$C$19+Assumptions!$C$20) | K17: =K7*(Assumptions!$C$19+Assumptions!$C$20) | L17: =L7*(Assumptions!$C$19+Assumptions!$C$20) | M17: =M7*(Assumptions!$C$19+Assumptions!$C$20) | N17: =N7*(Assumptions!$C$19+Assumptions!$C$20) | O17: =O7*(Assumptions!$C$19+Assumptions!$C$20) | ... AM17: =AM7*(Assumptions!$C$19+Assumptions!$C$20)
B18: Studio Start Up Costs | D18: 0 | E18: 0 | F18: 0 | G18: 0 | H18: 0 | I18: 0 | J18: 0 | K18: 0 | L18: 0 | M18: 0 | N18: 0 | O18: 0 | P18: 0 | Q18: 0 | R18: 0 | S18: 0 | T18: 0 | U18: 0 | V18: 0 | W18: 0 | X18: 0 | Y18: 0 | Z18: 0 | AA18: 0 | AB18: 0 | AC18: 0 | AD18: 0 | AE18: 0 | AF18: 0 | AG18: 0 | AH18: 0 | AI18: 0 | AJ18: 0 | AK18: 0 | AL18: 0 | AM18: 0
B19: Taxes | D19: 3673 | E19: 8816 | F19: 3673 | G19: 3673 | H19: 5387.33 | I19: 5387.33 | J19: 5387.33 | K19: 5387.33 | L19: 5387.33 | M19: 5387.33 | N19: 5387.33 | O19: 5387.33 | P19: 5602.82 | Q19: 5602.82 | R19: 5602.82 | S19: 5602.82 | T19: 5602.82 | U19: 5602.82 | V19: 5602.82 | W19: 5602.82 | X19: 5602.82 | Y19: 5602.82 | Z19: 5602.82 | AA19: 5602.82 | AB19: 5826.93 | AC19: 5826.93 | AD19: 5826.93 | AE19: 5826.93 | AF19: 5826.93 | AG19: 5826.93 | AH19: 5826.93 | AI19: 5826.93 | AJ19: 5826.93 | AK19: 5826.93 | AL19: 5826.93 | AM19: 5826.93
B20: Total Operating Expenses | D20: =SUM(D10:D19) | E20: =SUM(E10:E19) | F20: =SUM(F10:F19) | G20: =SUM(G10:G19) | H20: =SUM(H10:H19) | I20: =SUM(I10:I19) | J20: =SUM(J10:J19) | K20: =SUM(K10:K19) | ... AM20: =SUM(AM10:AM19)
B21: Net Cash from Operations | D21: =D7-D20 | E21: =E7-E20 | F21: =F7-F20 | G21: =G7-G20 | H21: =H7-H20 | I21: =I7-I20 | J21: =J7-J20 | K21: =K7-K20 | ... AM21: =AM7-AM20
B23: INVESTING ACTIVITIES
B24: Equipment & Furniture | D24: 0 | E24: 2497.4 | F24: 0 | G24: 0 | H24: 0 | I24: 0 | J24: 0 | K24: 0 | L24: 0 | M24: 0 | N24: 0 | O24: 0 | P24: 0 | Q24: 0 | R24: 0 | S24: 0 | T24: 0 | U24: 0 | V24: 0 | W24: 0 | X24: 0 | Y24: 0 | Z24: 0 | AA24: 0 | AB24: 0 | AC24: 0 | AD24: 0 | AE24: 0 | AF24: 0 | AG24: 0 | AH24: 0 | AI24: 0 | AJ24: 0 | AK24: 0 | AL24: 0 | AM24: 0
B25: Leasehold Improvements | D25: -17810.67 | E25: -7094.5 | F25: -24075 | G25: -1035.5 | H25: 0 | I25: 0 | J25: -275000 | K25: -160000 | L25: 0 | M25: 0 | N25: 0 | O25: 0 | P25: 0 | Q25: 0 | R25: 0 | S25: 0 | T25: 0 | U25: 0 | V25: 0 | W25: 0 | X25: 0 | Y25: 0 | Z25: 0 | AA25: 0 | AB25: 0 | AC25: 0 | AD25: 0 | AE25: 0 | AF25: 0 | AG25: 0 | AH25: 0 | AI25: 0 | AJ25: 0 | AK25: 0 | AL25: 0 | AM25: 0
B26: Deposits | D26: 0 | E26: 0 | F26: 0 | G26: 0 | H26: 0 | I26: 0 | J26: 0 | K26: 0 | L26: 0 | M26: 0 | N26: 0 | O26: 0 | P26: 0 | Q26: 0 | R26: 0 | S26: 0 | T26: 0 | U26: 0 | V26: 0 | W26: 0 | X26: 0 | Y26: 0 | Z26: 0 | AA26: 0 | AB26: 0 | AC26: 0 | AD26: 0 | AE26: 0 | AF26: 0 | AG26: 0 | AH26: 0 | AI26: 0 | AJ26: 0 | AK26: 0 | AL26: 0 | AM26: 0
B27: Net Investing | D27: =SUM(D24:D26) | E27: =SUM(E24:E26) | F27: =SUM(F24:F26) | G27: =SUM(G24:G26) | H27: =SUM(H24:H26) | I27: =SUM(I24:I26) | J27: =SUM(J24:J26) | K27: =SUM(K24:K26) | ... AM27: =SUM(AM24:AM26)
B29: FINANCING ACTIVITIES
B30: Loan Proceeds | D30: 9059.38 | E30: 9059.38 | F30: 9059.38 | G30: 12507.09 | H30: 0 | I30: 0 | J30: 0 | K30: 0 | L30: 0 | M30: 0 | N30: 0 | O30: 0 | P30: 0 | Q30: 0 | R30: 0 | S30: 0 | T30: 0 | U30: 0 | V30: 0 | W30: 0 | X30: 0 | Y30: 0 | Z30: 0 | AA30: 0 | AB30: 0 | AC30: 0 | AD30: 0 | AE30: 0 | AF30: 0 | AG30: 0 | AH30: 0 | AI30: 0 | AJ30: 0 | AK30: 0 | AL30: 0 | AM30: 0
B31: Loan Repayments | D31: -132128.24 | E31: -122128.76 | F31: -132834.5 | G31: -114793.66 | H31: =-'Cash, Debt & Equity'!H26 | I31: =-'Cash, Debt & Equity'!I26 | J31: =-'Cash, Debt & Equity'!J26 | K31: =-'Cash, Debt & Equity'!K26 | L31: =-'Cash, Debt & Equity'!L26 | M31: =-'Cash, Debt & Equity'!M26 | N31: =-'Cash, Debt & Equity'!N26 | O31: =-'Cash, Debt & Equity'!O26 | ... AM31: =-'Cash, Debt & Equity'!AM26
B32: Intercompany / Owner Contributions | D32: 0 | E32: 0 | F32: 133333.33 | G32: 78333.33 | H32: 0 | I32: 0 | J32: 0 | K32: 0 | L32: 0 | M32: 0 | N32: -100000 | O32: 0 | P32: 0 | Q32: 0 | R32: 0 | S32: 0 | T32: 0 | U32: 0 | V32: 0 | W32: 0 | X32: 0 | Y32: 0 | Z32: 0 | AA32: 0 | AB32: 0 | AC32: 0 | AD32: 0 | AE32: 0 | AF32: 0 | AG32: 0 | AH32: 0 | AI32: 0 | AJ32: 0 | AK32: 0 | AL32: 0 | AM32: 0
B33: Net Financing | D33: =SUM(D30:D32) | E33: =SUM(E30:E32) | F33: =SUM(F30:F32) | G33: =SUM(G30:G32) | H33: =SUM(H30:H32) | I33: =SUM(I30:I32) | J33: =SUM(J30:J32) | K33: =SUM(K30:K32) | ... AM33: =SUM(AM30:AM32)
B35: NET CHANGE IN CASH
B36: Net Change in Cash | D36: =D21+D27+D33 | E36: =E21+E27+E33 | F36: =F21+F27+F33 | G36: =G21+G27+G33 | H36: =H21+H27+H33 | I36: =I21+I27+I33 | J36: =J21+J27+J33 | K36: =K21+K27+K33 | ... AM36: =AM21+AM27+AM33
B37: Beginning Cash Balance | D37: =D38-D36 | E37: =D38 | F37: =E38 | G37: =F38 | H37: =G38 | I37: =H38 | J37: =I38 | K37: =J38 | L37: =K38 | ... AM37: =AL38
B38: Ending Cash Balance | D38: 187021.69 | E38: 261314.24 | F38: 237762.6 | G38: 473976.03 | H38: =H37+H36 | I38: =I37+I36 | J38: =J37+J36 | K38: =K37+K36 | L38: =L37+L36 | M38: =M37+M36 | N38: =N37+N36 | O38: =O37+O36 | ... AM38: =AM37+AM36

Sheet P&L
B2: Profit & Loss (Consolidated)
B3: Actuals Jan-Apr 2026. Forecast May 2026+ uses formulas from Sales Forecast and Assumptions.
B4: Monthly P&L
B5: Line Item | D5: Jan 2026 | E5: Feb 2026 | F5: Mar 2026 | G5: Apr 2026 | H5: May 2026 | I5: Jun 2026 | J5: Jul 2026 | K5: Aug 2026 | L5: Sep 2026 | M5: Oct 2026 | N5: Nov 2026 | O5: Dec 2026 | P5: Jan 2027 | Q5: Feb 2027 | R5: Mar 2027 | S5: Apr 2027 | T5: May 2027 | U5: Jun 2027 | V5: Jul 2027 | W5: Aug 2027 | X5: Sep 2027 | Y5: Oct 2027 | Z5: Nov 2027 | AA5: Dec 2027 | AB5: Jan 2028 | AC5: Feb 2028 | AD5: Mar 2028 | AE5: Apr 2028 | AF5: May 2028 | AG5: Jun 2028 | AH5: Jul 2028 | AI5: Aug 2028 | AJ5: Sep 2028 | AK5: Oct 2028 | AL5: Nov 2028 | AM5: Dec 2028
B6: Session Revenue | D6: 1000204 | E6: 866507.65 | F6: 867748.4 | G6: 790938.82 | H6: 807497.91 | I6: ='Sales Forecast'!I18*Assumptions!$C$12+'Sales Forecast'!H18*Assumptions!$D$12+'Sales Forecast'!G18*Assumptions!$E$12+'Sales Forecast'!F18*Assumptions!$F$12+'Sales Forecast'!E18*Assumptions!$G$12+'Sales Forecast'!D18*Assumptions!$H$12+'Sales Forecast'!I101*Assumptions!$I$12 | J6: ='Sales Forecast'!J18*Assumptions!$C$12+'Sales Forecast'!I18*Assumptions!$D$12+'Sales Forecast'!H18*Assumptions!$E$12+'Sales Forecast'!G18*Assumptions!$F$12+'Sales Forecast'!F18*Assumptions!$G$12+'Sales Forecast'!E18*Assumptions!$H$12+'Sales Forecast'!D18*Assumptions!$I$12 | K6: ='Sales Forecast'!K18*Assumptions!$C$12+'Sales Forecast'!J18*Assumptions!$D$12+'Sales Forecast'!I18*Assumptions!$E$12+'Sales Forecast'!H18*Assumptions!$F$12+'Sales Forecast'!G18*Assumptions!$G$12+'Sales Forecast'!F18*Assumptions!$H$12+'Sales Forecast'!E18*Assumptions!$I$12 | L6: ='Sales Forecast'!L18*Assumptions!$C$12+'Sales Forecast'!K18*Assumptions!$D$12+'Sales Forecast'!J18*Assumptions!$E$12+'Sales Forecast'!I18*Assumptions!$F$12+'Sales Forecast'!H18*Assumptions!$G$12+'Sales Forecast'!G18*Assumptions!$H$12+'Sales Forecast'!F18*Assumptions!$I$12 | M6: ='Sales Forecast'!M18*Assumptions!$C$12+'Sales Forecast'!L18*Assumptions!$D$12+'Sales Forecast'!K18*Assumptions!$E$12+'Sales Forecast'!J18*Assumptions!$F$12+'Sales Forecast'!I18*Assumptions!$G$12+'Sales Forecast'!H18*Assumptions!$H$12+'Sales Forecast'!G18*Assumptions!$I$12 | N6: ='Sales Forecast'!N18*Assumptions!$C$12+'Sales Forecast'!M18*Assumptions!$D$12+'Sales Forecast'!L18*Assumptions!$E$12+'Sales Forecast'!K18*Assumptions!$F$12+'Sales Forecast'!J18*Assumptions!$G$12+'Sales Forecast'!I18*Assumptions!$H$12+'Sales Forecast'!H18*Assumptions!$I$12 | O6: ='Sales Forecast'!O18*Assumptions!$C$12+'Sales Forecast'!N18*Assumptions!$D$12+'Sales Forecast'!M18*Assumptions!$E$12+'Sales Forecast'!L18*Assumptions!$F$12+'Sales Forecast'!K18*Assumptions!$G$12+'Sales Forecast'!J18*Assumptions!$H$12+'Sales Forecast'!I18*Assumptions!$I$12 | P6: ='Sales Forecast'!P18*Assumptions!$C$12+'Sales Forecast'!O18*Assumptions!$D$12+'Sales Forecast'!N18*Assumptions!$E$12+'Sales Forecast'!M18*Assumptions!$F$12+'Sales Forecast'!L18*Assumptions!$G$12+'Sales Forecast'!K18*Assumptions!$H$12+'Sales Forecast'!J18*Assumptions!$I$12 | Q6: ='Sales Forecast'!Q18*Assumptions!$C$12+'Sales Forecast'!P18*Assumptions!$D$12+'Sales Forecast'!O18*Assumptions!$E$12+'Sales Forecast'!N18*Assumptions!$F$12+'Sales Forecast'!M18*Assumptions!$G$12+'Sales Forecast'!L18*Assumptions!$H$12+'Sales Forecast'!K18*Assumptions!$I$12 | ... AM6: ='Sales Forecast'!AM18*Assumptions!$C$12+'Sales Forecast'!AL18*Assumptions!$D$12+'Sales Forecast'!AK18*Assumptions!$E$12+'Sales Forecast'!AJ18*Assumptions!$F$12+'Sales Forecast'!AI18*Assumptions!$G$12+'Sales Forecast'!AH18*Assumptions!$H$12+'Sales Forecast'!AG18*Assumptions!$I$12
B7: Breakage Revenue | D7: 139780.94 | E7: 155452.01 | F7: 132350.01 | G7: 142563.17 | H7: 141174.57 | I7: ='Sales Forecast'!I18*Assumptions!$C$13+'Sales Forecast'!H18*Assumptions!$D$13+'Sales Forecast'!G18*Assumptions!$E$13+'Sales Forecast'!F18*Assumptions!$F$13+'Sales Forecast'!E18*Assumptions!$G$13+'Sales Forecast'!D18*Assumptions!$H$13+'Sales Forecast'!I101*Assumptions!$I$13 | J7: ='Sales Forecast'!J18*Assumptions!$C$13+'Sales Forecast'!I18*Assumptions!$D$13+'Sales Forecast'!H18*Assumptions!$E$13+'Sales Forecast'!G18*Assumptions!$F$13+'Sales Forecast'!F18*Assumptions!$G$13+'Sales Forecast'!E18*Assumptions!$H$13+'Sales Forecast'!D18*Assumptions!$I$13 | K7: ='Sales Forecast'!K18*Assumptions!$C$13+'Sales Forecast'!J18*Assumptions!$D$13+'Sales Forecast'!I18*Assumptions!$E$13+'Sales Forecast'!H18*Assumptions!$F$13+'Sales Forecast'!G18*Assumptions!$G$13+'Sales Forecast'!F18*Assumptions!$H$13+'Sales Forecast'!E18*Assumptions!$I$13 | L7: ='Sales Forecast'!L18*Assumptions!$C$13+'Sales Forecast'!K18*Assumptions!$D$13+'Sales Forecast'!J18*Assumptions!$E$13+'Sales Forecast'!I18*Assumptions!$F$13+'Sales Forecast'!H18*Assumptions!$G$13+'Sales Forecast'!G18*Assumptions!$H$13+'Sales Forecast'!F18*Assumptions!$I$13 | M7: ='Sales Forecast'!M18*Assumptions!$C$13+'Sales Forecast'!L18*Assumptions!$D$13+'Sales Forecast'!K18*Assumptions!$E$13+'Sales Forecast'!J18*Assumptions!$F$13+'Sales Forecast'!I18*Assumptions!$G$13+'Sales Forecast'!H18*Assumptions!$H$13+'Sales Forecast'!G18*Assumptions!$I$13 | N7: ='Sales Forecast'!N18*Assumptions!$C$13+'Sales Forecast'!M18*Assumptions!$D$13+'Sales Forecast'!L18*Assumptions!$E$13+'Sales Forecast'!K18*Assumptions!$F$13+'Sales Forecast'!J18*Assumptions!$G$13+'Sales Forecast'!I18*Assumptions!$H$13+'Sales Forecast'!H18*Assumptions!$I$13 | O7: ='Sales Forecast'!O18*Assumptions!$C$13+'Sales Forecast'!N18*Assumptions!$D$13+'Sales Forecast'!M18*Assumptions!$E$13+'Sales Forecast'!L18*Assumptions!$F$13+'Sales Forecast'!K18*Assumptions!$G$13+'Sales Forecast'!J18*Assumptions!$H$13+'Sales Forecast'!I18*Assumptions!$I$13 | P7: ='Sales Forecast'!P18*Assumptions!$C$13+'Sales Forecast'!O18*Assumptions!$D$13+'Sales Forecast'!N18*Assumptions!$E$13+'Sales Forecast'!M18*Assumptions!$F$13+'Sales Forecast'!L18*Assumptions!$G$13+'Sales Forecast'!K18*Assumptions!$H$13+'Sales Forecast'!J18*Assumptions!$I$13 | Q7: ='Sales Forecast'!Q18*Assumptions!$C$13+'Sales Forecast'!P18*Assumptions!$D$13+'Sales Forecast'!O18*Assumptions!$E$13+'Sales Forecast'!N18*Assumptions!$F$13+'Sales Forecast'!M18*Assumptions!$G$13+'Sales Forecast'!L18*Assumptions!$H$13+'Sales Forecast'!K18*Assumptions!$I$13 | ... AM7: ='Sales Forecast'!AM18*Assumptions!$C$13+'Sales Forecast'!AL18*Assumptions!$D$13+'Sales Forecast'!AK18*Assumptions!$E$13+'Sales Forecast'!AJ18*Assumptions!$F$13+'Sales Forecast'!AI18*Assumptions!$G$13+'Sales Forecast'!AH18*Assumptions!$H$13+'Sales Forecast'!AG18*Assumptions!$I$13
B8: Retail Sales | D8: 23308 | E8: 19847 | F8: 17655 | G8: 18479 | H8: 13825.81 | I8: 16653.27 | J8: 16653.27 | K8: 16653.27 | L8: 16653.27 | M8: 16653.27 | N8: 16653.27 | O8: 16653.27 | P8: 16653.27 | Q8: 16653.27 | R8: 16653.27 | S8: 16653.27 | T8: 16653.27 | U8: 16653.27 | V8: 16653.27 | W8: 16653.27 | X8: 16653.27 | Y8: 16653.27 | Z8: 16653.27 | AA8: 16653.27 | AB8: 16653.27 | AC8: 16653.27 | AD8: 16653.27 | AE8: 16653.27 | AF8: 16653.27 | AG8: 16653.27 | AH8: 16653.27 | AI8: 16653.27 | AJ8: 16653.27 | AK8: 16653.27 | AL8: 16653.27 | AM8: 16653.27
B9: Refunds | D9: -20830.24 | E9: -15645.66 | F9: -16880.65 | G9: -12793.11 | H9: -9390.21 | I9: =(I6+I7)*Assumptions!$C$17 | J9: =(J6+J7)*Assumptions!$C$17 | K9: =(K6+K7)*Assumptions!$C$17 | L9: =(L6+L7)*Assumptions!$C$17 | M9: =(M6+M7)*Assumptions!$C$17 | N9: =(N6+N7)*Assumptions!$C$17 | O9: =(O6+O7)*Assumptions!$C$17 | P9: =(P6+P7)*Assumptions!$C$17 | ... AM9: =(AM6+AM7)*Assumptions!$C$17
B10: Discounts | D10: -59600.85 | E10: -56707.91 | F10: -53962.12 | G10: -51310.18 | H10: -35101.57 | I10: =(I6+I7)*Assumptions!$C$18 | J10: =(J6+J7)*Assumptions!$C$18 | K10: =(K6+K7)*Assumptions!$C$18 | L10: =(L6+L7)*Assumptions!$C$18 | M10: =(M6+M7)*Assumptions!$C$18 | N10: =(N6+N7)*Assumptions!$C$18 | O10: =(O6+O7)*Assumptions!$C$18 | P10: =(P6+P7)*Assumptions!$C$18 | ... AM10: =(AM6+AM7)*Assumptions!$C$18
B11: Total Revenue | D11: 1082861.8 | E11: 969453.09 | F11: 946910.64 | G11: 887877.7 | H11: 918006.51 | I11: =I6+I7+I8+I9+I10 | J11: =J6+J7+J8+J9+J10 | K11: =K6+K7+K8+K9+K10 | L11: =L6+L7+L8+L9+L10 | M11: =M6+M7+M8+M9+M10 | N11: =N6+N7+N8+N9+N10 | O11: =O6+O7+O8+O9+O10 | P11: =P6+P7+P8+P9+P10 | ... AM11: =AM6+AM7+AM8+AM9+AM10
B12: COGS & Merchant Fees | D12: 38009.85 | E12: 38497.03 | F12: 34960.53 | G12: 36936.49 | H12: 27088.66 | I12: =I11*(Assumptions!$C$19+Assumptions!$C$20) | J12: =J11*(Assumptions!$C$19+Assumptions!$C$20) | K12: =K11*(Assumptions!$C$19+Assumptions!$C$20) | L12: =L11*(Assumptions!$C$19+Assumptions!$C$20) | M12: =M11*(Assumptions!$C$19+Assumptions!$C$20) | N12: =N11*(Assumptions!$C$19+Assumptions!$C$20) | O12: =O11*(Assumptions!$C$19+Assumptions!$C$20) | P12: =P11*(Assumptions!$C$19+Assumptions!$C$20) | ... AM12: =AM11*(Assumptions!$C$19+Assumptions!$C$20)
B13: Gross Profit | D13: 1044852 | E13: 930956.06 | F13: 911950.11 | G13: 850941.21 | H13: 890917.85 | I13: =I11-I12 | J13: =J11-J12 | K13: =K11-K12 | L13: =L11-L12 | M13: =M11-M12 | N13: =N11-N12 | O13: =O11-O12 | P13: =P11-P12 | ... AM13: =AM11-AM12
B14: Marketing | D14: 27740.18 | E14: 27007.49 | F14: 16681.8 | G14: 5975.58 | H14: 5982.17 | I14: ='BK P&L'!I33+'CC P&L'!I33+'DN P&L'!I33+'LF P&L'!I33+'MR P&L'!I33+'OP P&L'!I33+'PH P&L'!I33+'RH P&L'!I33+'SB P&L'!I33+'SM P&L'!I33+'WP P&L'!I33+'WW P&L'!I33+'HO P&L'!I12 | J14: ='BK P&L'!J33+'CC P&L'!J33+'DN P&L'!J33+'LF P&L'!J33+'MR P&L'!J33+'OP P&L'!J33+'PH P&L'!J33+'RH P&L'!J33+'SB P&L'!J33+'SM P&L'!J33+'WP P&L'!J33+'WW P&L'!J33+'HO P&L'!J12 | K14: ='BK P&L'!K33+'CC P&L'!K33+'DN P&L'!K33+'LF P&L'!K33+'MR P&L'!K33+'OP P&L'!K33+'PH P&L'!K33+'RH P&L'!K33+'SB P&L'!K33+'SM P&L'!K33+'WP P&L'!K33+'WW P&L'!K33+'HO P&L'!K12 | L14: ='BK P&L'!L33+'CC P&L'!L33+'DN P&L'!L33+'LF P&L'!L33+'MR P&L'!L33+'OP P&L'!L33+'PH P&L'!L33+'RH P&L'!L33+'SB P&L'!L33+'SM P&L'!L33+'WP P&L'!L33+'WW P&L'!L33+'HO P&L'!L12 | M14: ='BK P&L'!M33+'CC P&L'!M33+'DN P&L'!M33+'LF P&L'!M33+'MR P&L'!M33+'OP P&L'!M33+'PH P&L'!M33+'RH P&L'!M33+'SB P&L'!M33+'SM P&L'!M33+'WP P&L'!M33+'WW P&L'!M33+'HO P&L'!M12 | N14: ='BK P&L'!N33+'CC P&L'!N33+'DN P&L'!N33+'LF P&L'!N33+'MR P&L'!N33+'OP P&L'!N33+'PH P&L'!N33+'RH P&L'!N33+'SB P&L'!N33+'SM P&L'!N33+'WP P&L'!N33+'WW P&L'!N33+'HO P&L'!N12 | O14: ='BK P&L'!O33+'CC P&L'!O33+'DN P&L'!O33+'LF P&L'!O33+'MR P&L'!O33+'OP P&L'!O33+'PH P&L'!O33+'RH P&L'!O33+'SB P&L'!O33+'SM P&L'!O33+'WP P&L'!O33+'WW P&L'!O33+'HO P&L'!O12 | P14: ='BK P&L'!P33+'CC P&L'!P33+'DN P&L'!P33+'LF P&L'!P33+'MR P&L'!P33+'OP P&L'!P33+'PH P&L'!P33+'RH P&L'!P33+'SB P&L'!P33+'SM P&L'!P33+'WP P&L'!P33+'WW P&L'!P33+'HO P&L'!P12 | ... AM14: ='BK P&L'!AM33+'CC P&L'!AM33+'DN P&L'!AM33+'LF P&L'!AM33+'MR P&L'!AM33+'OP P&L'!AM33+'PH P&L'!AM33+'RH P&L'!AM33+'SB P&L'!AM33+'SM P&L'!AM33+'WP P&L'!AM33+'WW P&L'!AM33+'HO P&L'!AM12
B15: Payroll | D15: 681232.98 | E15: 590412.06 | F15: 628953.81 | G15: 576480.98 | H15: 589210.62 | I15: ='BK P&L'!I38+'CC P&L'!I38+'DN P&L'!I38+'LF P&L'!I38+'MR P&L'!I38+'OP P&L'!I38+'PH P&L'!I38+'RH P&L'!I38+'SB P&L'!I38+'SM P&L'!I38+'WP P&L'!I38+'WW P&L'!I38+'HO P&L'!I17 | J15: ='BK P&L'!J38+'CC P&L'!J38+'DN P&L'!J38+'LF P&L'!J38+'MR P&L'!J38+'OP P&L'!J38+'PH P&L'!J38+'RH P&L'!J38+'SB P&L'!J38+'SM P&L'!J38+'WP P&L'!J38+'WW P&L'!J38+'HO P&L'!J17 | K15: ='BK P&L'!K38+'CC P&L'!K38+'DN P&L'!K38+'LF P&L'!K38+'MR P&L'!K38+'OP P&L'!K38+'PH P&L'!K38+'RH P&L'!K38+'SB P&L'!K38+'SM P&L'!K38+'WP P&L'!K38+'WW P&L'!K38+'HO P&L'!K17 | L15: ='BK P&L'!L38+'CC P&L'!L38+'DN P&L'!L38+'LF P&L'!L38+'MR P&L'!L38+'OP P&L'!L38+'PH P&L'!L38+'RH P&L'!L38+'SB P&L'!L38+'SM P&L'!L38+'WP P&L'!L38+'WW P&L'!L38+'HO P&L'!L17 | M15: ='BK P&L'!M38+'CC P&L'!M38+'DN P&L'!M38+'LF P&L'!M38+'MR P&L'!M38+'OP P&L'!M38+'PH P&L'!M38+'RH P&L'!M38+'SB P&L'!M38+'SM P&L'!M38+'WP P&L'!M38+'WW P&L'!M38+'HO P&L'!M17 | N15: ='BK P&L'!N38+'CC P&L'!N38+'DN P&L'!N38+'LF P&L'!N38+'MR P&L'!N38+'OP P&L'!N38+'PH P&L'!N38+'RH P&L'!N38+'SB P&L'!N38+'SM P&L'!N38+'WP P&L'!N38+'WW P&L'!N38+'HO P&L'!N17 | O15: ='BK P&L'!O38+'CC P&L'!O38+'DN P&L'!O38+'LF P&L'!O38+'MR P&L'!O38+'OP P&L'!O38+'PH P&L'!O38+'RH P&L'!O38+'SB P&L'!O38+'SM P&L'!O38+'WP P&L'!O38+'WW P&L'!O38+'HO P&L'!O17 | P15: ='BK P&L'!P38+'CC P&L'!P38+'DN P&L'!P38+'LF P&L'!P38+'MR P&L'!P38+'OP P&L'!P38+'PH P&L'!P38+'RH P&L'!P38+'SB P&L'!P38+'SM P&L'!P38+'WP P&L'!P38+'WW P&L'!P38+'HO P&L'!P17 | ... AM15: ='BK P&L'!AM38+'CC P&L'!AM38+'DN P&L'!AM38+'LF P&L'!AM38+'MR P&L'!AM38+'OP P&L'!AM38+'PH P&L'!AM38+'RH P&L'!AM38+'SB P&L'!AM38+'SM P&L'!AM38+'WP P&L'!AM38+'WW P&L'!AM38+'HO P&L'!AM17
B16: Software | D16: 14854.43 | E16: 23709.03 | F16: 10924.01 | G16: 13421.72 | H16: 14118.08 | I16: ='BK P&L'!I42+'CC P&L'!I42+'DN P&L'!I42+'LF P&L'!I42+'MR P&L'!I42+'OP P&L'!I42+'PH P&L'!I42+'RH P&L'!I42+'SB P&L'!I42+'SM P&L'!I42+'WP P&L'!I42+'WW P&L'!I42+'HO P&L'!I22 | J16: ='BK P&L'!J42+'CC P&L'!J42+'DN P&L'!J42+'LF P&L'!J42+'MR P&L'!J42+'OP P&L'!J42+'PH P&L'!J42+'RH P&L'!J42+'SB P&L'!J42+'SM P&L'!J42+'WP P&L'!J42+'WW P&L'!J42+'HO P&L'!J22 | K16: ='BK P&L'!K42+'CC P&L'!K42+'DN P&L'!K42+'LF P&L'!K42+'MR P&L'!K42+'OP P&L'!K42+'PH P&L'!K42+'RH P&L'!K42+'SB P&L'!K42+'SM P&L'!K42+'WP P&L'!K42+'WW P&L'!K42+'HO P&L'!K22 | L16: ='BK P&L'!L42+'CC P&L'!L42+'DN P&L'!L42+'LF P&L'!L42+'MR P&L'!L42+'OP P&L'!L42+'PH P&L'!L42+'RH P&L'!L42+'SB P&L'!L42+'SM P&L'!L42+'WP P&L'!L42+'WW P&L'!L42+'HO P&L'!L22 | M16: ='BK P&L'!M42+'CC P&L'!M42+'DN P&L'!M42+'LF P&L'!M42+'MR P&L'!M42+'OP P&L'!M42+'PH P&L'!M42+'RH P&L'!M42+'SB P&L'!M42+'SM P&L'!M42+'WP P&L'!M42+'WW P&L'!M42+'HO P&L'!M22 | N16: ='BK P&L'!N42+'CC P&L'!N42+'DN P&L'!N42+'LF P&L'!N42+'MR P&L'!N42+'OP P&L'!N42+'PH P&L'!N42+'RH P&L'!N42+'SB P&L'!N42+'SM P&L'!N42+'WP P&L'!N42+'WW P&L'!N42+'HO P&L'!N22 | O16: ='BK P&L'!O42+'CC P&L'!O42+'DN P&L'!O42+'LF P&L'!O42+'MR P&L'!O42+'OP P&L'!O42+'PH P&L'!O42+'RH P&L'!O42+'SB P&L'!O42+'SM P&L'!O42+'WP P&L'!O42+'WW P&L'!O42+'HO P&L'!O22 | P16: ='BK P&L'!P42+'CC P&L'!P42+'DN P&L'!P42+'LF P&L'!P42+'MR P&L'!P42+'OP P&L'!P42+'PH P&L'!P42+'RH P&L'!P42+'SB P&L'!P42+'SM P&L'!P42+'WP P&L'!P42+'WW P&L'!P42+'HO P&L'!P22 | ... AM16: ='BK P&L'!AM42+'CC P&L'!AM42+'DN P&L'!AM42+'LF P&L'!AM42+'MR P&L'!AM42+'OP P&L'!AM42+'PH P&L'!AM42+'RH P&L'!AM42+'SB P&L'!AM42+'SM P&L'!AM42+'WP P&L'!AM42+'WW P&L'!AM42+'HO P&L'!AM22
B17: Professional Fees | D17: 42733.79 | E17: 24202.3 | F17: 22556.84 | G17: 25366 | H17: 30273 | I17: ='BK P&L'!I47+'CC P&L'!I47+'DN P&L'!I47+'LF P&L'!I47+'MR P&L'!I47+'OP P&L'!I47+'PH P&L'!I47+'RH P&L'!I47+'SB P&L'!I47+'SM P&L'!I47+'WP P&L'!I47+'WW P&L'!I47+'HO P&L'!I27 | J17: ='BK P&L'!J47+'CC P&L'!J47+'DN P&L'!J47+'LF P&L'!J47+'MR P&L'!J47+'OP P&L'!J47+'PH P&L'!J47+'RH P&L'!J47+'SB P&L'!J47+'SM P&L'!J47+'WP P&L'!J47+'WW P&L'!J47+'HO P&L'!J27 | K17: ='BK P&L'!K47+'CC P&L'!K47+'DN P&L'!K47+'LF P&L'!K47+'MR P&L'!K47+'OP P&L'!K47+'PH P&L'!K47+'RH P&L'!K47+'SB P&L'!K47+'SM P&L'!K47+'WP P&L'!K47+'WW P&L'!K47+'HO P&L'!K27 | L17: ='BK P&L'!L47+'CC P&L'!L47+'DN P&L'!L47+'LF P&L'!L47+'MR P&L'!L47+'OP P&L'!L47+'PH P&L'!L47+'RH P&L'!L47+'SB P&L'!L47+'SM P&L'!L47+'WP P&L'!L47+'WW P&L'!L47+'HO P&L'!L27 | M17: ='BK P&L'!M47+'CC P&L'!M47+'DN P&L'!M47+'LF P&L'!M47+'MR P&L'!M47+'OP P&L'!M47+'PH P&L'!M47+'RH P&L'!M47+'SB P&L'!M47+'SM P&L'!M47+'WP P&L'!M47+'WW P&L'!M47+'HO P&L'!M27 | N17: ='BK P&L'!N47+'CC P&L'!N47+'DN P&L'!N47+'LF P&L'!N47+'MR P&L'!N47+'OP P&L'!N47+'PH P&L'!N47+'RH P&L'!N47+'SB P&L'!N47+'SM P&L'!N47+'WP P&L'!N47+'WW P&L'!N47+'HO P&L'!N27 | O17: ='BK P&L'!O47+'CC P&L'!O47+'DN P&L'!O47+'LF P&L'!O47+'MR P&L'!O47+'OP P&L'!O47+'PH P&L'!O47+'RH P&L'!O47+'SB P&L'!O47+'SM P&L'!O47+'WP P&L'!O47+'WW P&L'!O47+'HO P&L'!O27 | P17: ='BK P&L'!P47+'CC P&L'!P47+'DN P&L'!P47+'LF P&L'!P47+'MR P&L'!P47+'OP P&L'!P47+'PH P&L'!P47+'RH P&L'!P47+'SB P&L'!P47+'SM P&L'!P47+'WP P&L'!P47+'WW P&L'!P47+'HO P&L'!P27 | ... AM17: ='BK P&L'!AM47+'CC P&L'!AM47+'DN P&L'!AM47+'LF P&L'!AM47+'MR P&L'!AM47+'OP P&L'!AM47+'PH P&L'!AM47+'RH P&L'!AM47+'SB P&L'!AM47+'SM P&L'!AM47+'WP P&L'!AM47+'WW P&L'!AM47+'HO P&L'!AM27
B18: Utilities | D18: 7087.42 | E18: 9973.09 | F18: 7034.72 | G18: 7270.22 | H18: 7128.54 | I18: ='BK P&L'!I56+'CC P&L'!I56+'DN P&L'!I56+'LF P&L'!I56+'MR P&L'!I56+'OP P&L'!I56+'PH P&L'!I56+'RH P&L'!I56+'SB P&L'!I56+'SM P&L'!I56+'WP P&L'!I56+'WW P&L'!I56 | J18: ='BK P&L'!J56+'CC P&L'!J56+'DN P&L'!J56+'LF P&L'!J56+'MR P&L'!J56+'OP P&L'!J56+'PH P&L'!J56+'RH P&L'!J56+'SB P&L'!J56+'SM P&L'!J56+'WP P&L'!J56+'WW P&L'!J56 | K18: ='BK P&L'!K56+'CC P&L'!K56+'DN P&L'!K56+'LF P&L'!K56+'MR P&L'!K56+'OP P&L'!K56+'PH P&L'!K56+'RH P&L'!K56+'SB P&L'!K56+'SM P&L'!K56+'WP P&L'!K56+'WW P&L'!K56 | L18: ='BK P&L'!L56+'CC P&L'!L56+'DN P&L'!L56+'LF P&L'!L56+'MR P&L'!L56+'OP P&L'!L56+'PH P&L'!L56+'RH P&L'!L56+'SB P&L'!L56+'SM P&L'!L56+'WP P&L'!L56+'WW P&L'!L56 | M18: ='BK P&L'!M56+'CC P&L'!M56+'DN P&L'!M56+'LF P&L'!M56+'MR P&L'!M56+'OP P&L'!M56+'PH P&L'!M56+'RH P&L'!M56+'SB P&L'!M56+'SM P&L'!M56+'WP P&L'!M56+'WW P&L'!M56 | N18: ='BK P&L'!N56+'CC P&L'!N56+'DN P&L'!N56+'LF P&L'!N56+'MR P&L'!N56+'OP P&L'!N56+'PH P&L'!N56+'RH P&L'!N56+'SB P&L'!N56+'SM P&L'!N56+'WP P&L'!N56+'WW P&L'!N56 | O18: ='BK P&L'!O56+'CC P&L'!O56+'DN P&L'!O56+'LF P&L'!O56+'MR P&L'!O56+'OP P&L'!O56+'PH P&L'!O56+'RH P&L'!O56+'SB P&L'!O56+'SM P&L'!O56+'WP P&L'!O56+'WW P&L'!O56 | P18: ='BK P&L'!P56+'CC P&L'!P56+'DN P&L'!P56+'LF P&L'!P56+'MR P&L'!P56+'OP P&L'!P56+'PH P&L'!P56+'RH P&L'!P56+'SB P&L'!P56+'SM P&L'!P56+'WP P&L'!P56+'WW P&L'!P56 | ... AM18: ='BK P&L'!AM56+'CC P&L'!AM56+'DN P&L'!AM56+'LF P&L'!AM56+'MR P&L'!AM56+'OP P&L'!AM56+'PH P&L'!AM56+'RH P&L'!AM56+'SB P&L'!AM56+'SM P&L'!AM56+'WP P&L'!AM56+'WW P&L'!AM56
B19: Property Costs | D19: 147113.46 | E19: 146344.65 | F19: 147382.66 | G19: 148059.43 | H19: 149341.42 | I19: ='BK P&L'!I61+'CC P&L'!I61+'DN P&L'!I61+'LF P&L'!I61+'MR P&L'!I61+'OP P&L'!I61+'PH P&L'!I61+'RH P&L'!I61+'SB P&L'!I61+'SM P&L'!I61+'WP P&L'!I61+'WW P&L'!I61+'HO P&L'!I32 | J19: ='BK P&L'!J61+'CC P&L'!J61+'DN P&L'!J61+'LF P&L'!J61+'MR P&L'!J61+'OP P&L'!J61+'PH P&L'!J61+'RH P&L'!J61+'SB P&L'!J61+'SM P&L'!J61+'WP P&L'!J61+'WW P&L'!J61+'HO P&L'!J32 | K19: ='BK P&L'!K61+'CC P&L'!K61+'DN P&L'!K61+'LF P&L'!K61+'MR P&L'!K61+'OP P&L'!K61+'PH P&L'!K61+'RH P&L'!K61+'SB P&L'!K61+'SM P&L'!K61+'WP P&L'!K61+'WW P&L'!K61+'HO P&L'!K32 | L19: ='BK P&L'!L61+'CC P&L'!L61+'DN P&L'!L61+'LF P&L'!L61+'MR P&L'!L61+'OP P&L'!L61+'PH P&L'!L61+'RH P&L'!L61+'SB P&L'!L61+'SM P&L'!L61+'WP P&L'!L61+'WW P&L'!L61+'HO P&L'!L32 | M19: ='BK P&L'!M61+'CC P&L'!M61+'DN P&L'!M61+'LF P&L'!M61+'MR P&L'!M61+'OP P&L'!M61+'PH P&L'!M61+'RH P&L'!M61+'SB P&L'!M61+'SM P&L'!M61+'WP P&L'!M61+'WW P&L'!M61+'HO P&L'!M32 | N19: ='BK P&L'!N61+'CC P&L'!N61+'DN P&L'!N61+'LF P&L'!N61+'MR P&L'!N61+'OP P&L'!N61+'PH P&L'!N61+'RH P&L'!N61+'SB P&L'!N61+'SM P&L'!N61+'WP P&L'!N61+'WW P&L'!N61+'HO P&L'!N32 | O19: ='BK P&L'!O61+'CC P&L'!O61+'DN P&L'!O61+'LF P&L'!O61+'MR P&L'!O61+'OP P&L'!O61+'PH P&L'!O61+'RH P&L'!O61+'SB P&L'!O61+'SM P&L'!O61+'WP P&L'!O61+'WW P&L'!O61+'HO P&L'!O32 | P19: ='BK P&L'!P61+'CC P&L'!P61+'DN P&L'!P61+'LF P&L'!P61+'MR P&L'!P61+'OP P&L'!P61+'PH P&L'!P61+'RH P&L'!P61+'SB P&L'!P61+'SM P&L'!P61+'WP P&L'!P61+'WW P&L'!P61+'HO P&L'!P32 | ... AM19: ='BK P&L'!AM61+'CC P&L'!AM61+'DN P&L'!AM61+'LF P&L'!AM61+'MR P&L'!AM61+'OP P&L'!AM61+'PH P&L'!AM61+'RH P&L'!AM61+'SB P&L'!AM61+'SM P&L'!AM61+'WP P&L'!AM61+'WW P&L'!AM61+'HO P&L'!AM32
B20: HO Other (Util+Fin) | D20: 0 | E20: 0 | F20: 0 | G20: 0 | H20: 1193.14 | I20: 1193.14 | J20: 1193.14 | K20: 1193.14 | L20: 1193.14 | M20: 1193.14 | N20: 1193.14 | O20: 1193.14 | P20: 1193.14 | Q20: 1193.14 | R20: 1193.14 | S20: 1193.14 | T20: 1193.14 | U20: 1193.14 | V20: 1193.14 | W20: 1193.14 | X20: 1193.14 | Y20: 1193.14 | Z20: 1193.14 | AA20: 1193.14 | AB20: 1193.14 | AC20: 1193.14 | AD20: 0 | AE20: 0 | AF20: 0 | AG20: 0 | AH20: 0 | AI20: 0 | AJ20: 0 | AK20: 0 | AL20: 0 | AM20: 0
B21: Total Operating Expenses | D21: 945487.67 | E21: 846207.66 | F21: 863798.35 | G21: 797830.67 | H21: 817186.31 | I21: =I14+I15+I16+I17+I18+I19+I20 | J21: =J14+J15+J16+J17+J18+J19+J20 | K21: =K14+K15+K16+K17+K18+K19+K20 | L21: =L14+L15+L16+L17+L18+L19+L20 | M21: =M14+M15+M16+M17+M18+M19+M20 | N21: =N14+N15+N16+N17+N18+N19+N20 | O21: =O14+O15+O16+O17+O18+O19+O20 | P21: =P14+P15+P16+P17+P18+P19+P20 | ... AM21: =AM14+AM15+AM16+AM17+AM18+AM19+AM20
B22: Net Operating Income | D22: 99364.32 | E22: 84748.4 | F22: 48151.76 | G22: 53110.54 | H22: 73731.54 | I22: =I13-I21 | J22: =J13-J21 | K22: =K13-K21 | L22: =L13-L21 | M22: =M13-M21 | N22: =N13-N21 | O22: =O13-O21 | P22: =P13-P21 | ... AM22: =AM13-AM21
B23: Depreciation | D23: 30633.94 | E23: 30665.6 | F23: 30876.78 | G23: 30893.75 | H23: 30876.78 | I23: 30882.44 | J23: 30882.44 | K23: 30882.44 | L23: 30882.44 | M23: 30882.44 | N23: 30882.44 | O23: 30882.44 | P23: 30882.44 | Q23: 30882.44 | R23: 30882.44 | S23: 30882.44 | T23: 30882.44 | U23: 30882.44 | V23: 30882.44 | W23: 30882.44 | X23: 30882.44 | Y23: 30882.44 | Z23: 30882.44 | AA23: 30882.44 | AB23: 30882.44 | AC23: 30882.44 | AD23: 30882.44 | AE23: 30882.44 | AF23: 30882.44 | AG23: 30882.44 | AH23: 30882.44 | AI23: 30882.44 | AJ23: 30882.44 | AK23: 30882.44 | AL23: 30882.44 | AM23: 30882.44
B24: Interest Expense | D24: 28621.88 | E24: 28621.88 | F24: 28621.88 | G24: 32069.59 | H24: 23912.5 | I24: =14026 | J24: =7728 | K24: =1430 | L24: =1082 | M24: =1082 | N24: =1082 | O24: =1082 | P24: =1082 | Q24: =1082 | R24: =1082 | S24: =1082 | ... AM24: =1082
B25: Taxes Paid | D25: 0 | E25: 5143 | F25: 0 | G25: 0 | H25: 800 | I25: 266.67 | J25: 266.67 | K25: 266.67 | L25: 266.67 | M25: 266.67 | N25: 266.67 | O25: 266.67 | P25: 266.67 | Q25: 266.67 | R25: 266.67 | S25: 266.67 | T25: 266.67 | U25: 266.67 | V25: 266.67 | W25: 266.67 | X25: 266.67 | Y25: 266.67 | Z25: 266.67 | AA25: 266.67 | AB25: 266.67 | AC25: 266.67 | AD25: 266.67 | AE25: 266.67 | AF25: 266.67 | AG25: 266.67 | AH25: 266.67 | AI25: 266.67 | AJ25: 266.67 | AK25: 266.67 | AL25: 266.67 | AM25: 266.67
B26: Property Taxes | D26: 3673 | E26: 3673 | F26: 3673 | G26: 3673 | H26: 3673 | I26: 3673 | J26: 3673 | K26: 3673 | L26: 3673 | M26: 3673 | N26: 3673 | O26: 3673 | P26: 3673 | Q26: 3673 | R26: 3673 | S26: 3673 | T26: 3673 | U26: 3673 | V26: 3673 | W26: 3673 | X26: 3673 | Y26: 3673 | Z26: 3673 | AA26: 3673 | AB26: 3673 | AC26: 3673 | AD26: 3673 | AE26: 3673 | AF26: 3673 | AG26: 3673 | AH26: 3673 | AI26: 3673 | AJ26: 3673 | AK26: 3673 | AL26: 3673 | AM26: 3673
B27: Total Other Expenses | D27: 62905.92 | E27: 68103.48 | F27: 63171.66 | G27: 62636.34 | H27: 64262.28 | I27: =I22+I23+I24+I25 | J27: =J22+J23+J24+J25 | K27: =K22+K23+K24+K25 | L27: =L22+L23+L24+L25 | M27: =M22+M23+M24+M25 | N27: =N22+N23+N24+N25 | O27: =O22+O23+O24+O25 | P27: =P22+P23+P24+P25 | ... AM27: =AM22+AM23+AM24+AM25
B28: Net Income | D28: 36458.4 | E28: 16644.92 | F28: -15019.9 | G28: -9525.8 | H28: 9469.26 | I28: =I21-I26 | J28: =J21-J26 | K28: =K21-K26 | L28: =L21-L26 | M28: =M21-M26 | N28: =N21-N26 | O28: =O21-O26 | P28: =P21-P26 | ... AM28: =AM21-AM26
B30: ADJUSTED EBITDA RECONCILIATION
B31: Net Operating Income (from above) | D31: =D22 | E31: =E22 | F31: =F22 | G31: =G22 | H31: =H22 | I31: =I22 | J31: =J22 | K31: =K22 | ... AM31: =AM22
B32: Add Backs:
B33: West Portal Start-Up Costs | D33: 16222.39 | E33: 17111.26 | F33: 14310.31 | G33: 19092.69 | H33: 0 | I33: 0 | J33: 0 | K33: 0 | L33: 0 | M33: 0 | N33: 0 | O33: 0 | P33: 0 | Q33: 0 | R33: 0 | S33: 0 | T33: 0 | U33: 0 | V33: 0 | W33: 0 | X33: 0 | Y33: 0 | Z33: 0 | AA33: 0 | AB33: 0 | AC33: 0 | AD33: 0 | AE33: 0 | AF33: 0 | AG33: 0 | AH33: 0 | AI33: 0 | AJ33: 0 | AK33: 0 | AL33: 0 | AM33: 0
B34: ADP Error | D34: 0 | E34: 0 | F34: 45000 | G34: 0 | H34: 0 | I34: 0 | J34: 0 | K34: 0 | L34: 0 | M34: 0 | N34: 0 | O34: 0 | P34: 0 | Q34: 0 | R34: 0 | S34: 0 | T34: 0 | U34: 0 | V34: 0 | W34: 0 | X34: 0 | Y34: 0 | Z34: 0 | AA34: 0 | AB34: 0 | AC34: 0 | AD34: 0 | AE34: 0 | AF34: 0 | AG34: 0 | AH34: 0 | AI34: 0 | AJ34: 0 | AK34: 0 | AL34: 0 | AM34: 0
B35: One-Time Legal Fees | D35: 2957 | E35: 0 | F35: =3995.5 | G35: 0 | H35: 0 | I35: 0 | J35: 0 | K35: 0 | L35: 0 | M35: 0 | N35: 0 | O35: 0 | P35: 0 | Q35: 0 | R35: 0 | S35: 0 | T35: 0 | U35: 0 | V35: 0 | W35: 0 | X35: 0 | Y35: 0 | Z35: 0 | AA35: 0 | AB35: 0 | AC35: 0 | AD35: 0 | AE35: 0 | AF35: 0 | AG35: 0 | AH35: 0 | AI35: 0 | AJ35: 0 | AK35: 0 | AL35: 0 | AM35: 0
B36: Santa Barbara Start Up | D36: 3481 | E36: 0 | F36: 0 | G36: 0 | H36: 0 | I36: 0 | J36: 0 | K36: 0 | L36: 0 | M36: 0 | N36: 0 | O36: 0 | P36: 0 | Q36: 0 | R36: 0 | S36: 0 | T36: 0 | U36: 0 | V36: 0 | W36: 0 | X36: 0 | Y36: 0 | Z36: 0 | AA36: 0 | AB36: 0 | AC36: 0 | AD36: 0 | AE36: 0 | AF36: 0 | AG36: 0 | AH36: 0 | AI36: 0 | AJ36: 0 | AK36: 0 | AL36: 0 | AM36: 0
B37: One-Time Accounting Fees | D37: 19887.5 | E37: 0 | F37: 0 | G37: 0 | H37: 0 | I37: 0 | J37: 0 | K37: 0 | L37: 0 | M37: 0 | N37: 0 | O37: 0 | P37: 0 | Q37: 0 | R37: 0 | S37: 0 | T37: 0 | U37: 0 | V37: 0 | W37: 0 | X37: 0 | Y37: 0 | Z37: 0 | AA37: 0 | AB37: 0 | AC37: 0 | AD37: 0 | AE37: 0 | AF37: 0 | AG37: 0 | AH37: 0 | AI37: 0 | AJ37: 0 | AK37: 0 | AL37: 0 | AM37: 0
B38: Total Add Backs | D38: =SUM(D33:D37) | E38: =SUM(E33:E37) | F38: =SUM(F33:F37) | G38: =SUM(G33:G37) | H38: =SUM(H33:H37) | I38: =SUM(I33:I37) | J38: =SUM(J33:J37) | K38: =SUM(K33:K37) | ... AM38: =SUM(AM33:AM37)
B39: Adjusted EBITDA | D39: =D31+D38 | E39: =E31+E38 | F39: =F31+F38 | G39: =G31+G38 | H39: =H31+H38 | I39: =I31+I38 | J39: =J31+J38 | K39: =K31+K38 | ... AM39: =AM31+AM38

Sheet All Studios Summary
B2: All Studios — Summary
B4: Studio / Metric | D4: Jan 2026 | E4: Feb 2026 | F4: Mar 2026 | G4: Apr 2026 | H4: May 2026 | I4: Jun 2026 | J4: Jul 2026 | K4: Aug 2026 | L4: Sep 2026 | M4: Oct 2026 | N4: Nov 2026 | O4: Dec 2026 | P4: Jan 2027 | Q4: Feb 2027 | R4: Mar 2027 | S4: Apr 2027 | T4: May 2027 | U4: Jun 2027 | V4: Jul 2027 | W4: Aug 2027 | X4: Sep 2027 | Y4: Oct 2027 | Z4: Nov 2027 | AA4: Dec 2027 | AB4: Jan 2028 | AC4: Feb 2028 | AD4: Mar 2028 | AE4: Apr 2028 | AF4: May 2028 | AG4: Jun 2028 | AH4: Jul 2028 | AI4: Aug 2028 | AJ4: Sep 2028 | AK4: Oct 2028 | AL4: Nov 2028 | AM4: Dec 2028
B5: Berkeley (BK)
B6: Total Revenue | D6: ='BK P&L'!D21 | E6: ='BK P&L'!E21 | F6: ='BK P&L'!F21 | G6: ='BK P&L'!G21 | H6: ='BK P&L'!H21 | I6: ='BK P&L'!I21 | J6: ='BK P&L'!J21 | K6: ='BK P&L'!K21 | ... AM6: ='BK P&L'!AM21
B7: Gross Profit | D7: ='BK P&L'!D26 | E7: ='BK P&L'!E26 | F7: ='BK P&L'!F26 | G7: ='BK P&L'!G26 | H7: ='BK P&L'!H26 | I7: ='BK P&L'!I26 | J7: ='BK P&L'!J26 | K7: ='BK P&L'!K26 | ... AM7: ='BK P&L'!AM26
B8: Total Operating Expenses | D8: ='BK P&L'!D62 | E8: ='BK P&L'!E62 | F8: ='BK P&L'!F62 | G8: ='BK P&L'!G62 | H8: ='BK P&L'!H62 | I8: ='BK P&L'!I62 | J8: ='BK P&L'!J62 | K8: ='BK P&L'!K62 | ... AM8: ='BK P&L'!AM62
B9: Net Operating Income | D9: ='BK P&L'!D63 | E9: ='BK P&L'!E63 | F9: ='BK P&L'!F63 | G9: ='BK P&L'!G63 | H9: ='BK P&L'!H63 | I9: ='BK P&L'!I63 | J9: ='BK P&L'!J63 | K9: ='BK P&L'!K63 | ... AM9: ='BK P&L'!AM63
B11: Culver City (CC)
B12: Total Revenue | D12: ='CC P&L'!D21 | E12: ='CC P&L'!E21 | F12: ='CC P&L'!F21 | G12: ='CC P&L'!G21 | H12: ='CC P&L'!H21 | I12: ='CC P&L'!I21 | J12: ='CC P&L'!J21 | K12: ='CC P&L'!K21 | ... AM12: ='CC P&L'!AM21
B13: Gross Profit | D13: ='CC P&L'!D26 | E13: ='CC P&L'!E26 | F13: ='CC P&L'!F26 | G13: ='CC P&L'!G26 | H13: ='CC P&L'!H26 | I13: ='CC P&L'!I26 | J13: ='CC P&L'!J26 | K13: ='CC P&L'!K26 | ... AM13: ='CC P&L'!AM26
B14: Total Operating Expenses | D14: ='CC P&L'!D62 | E14: ='CC P&L'!E62 | F14: ='CC P&L'!F62 | G14: ='CC P&L'!G62 | H14: ='CC P&L'!H62 | I14: ='CC P&L'!I62 | J14: ='CC P&L'!J62 | K14: ='CC P&L'!K62 | ... AM14: ='CC P&L'!AM62
B15: Net Operating Income | D15: ='CC P&L'!D63 | E15: ='CC P&L'!E63 | F15: ='CC P&L'!F63 | G15: ='CC P&L'!G63 | H15: ='CC P&L'!H63 | I15: ='CC P&L'!I63 | J15: ='CC P&L'!J63 | K15: ='CC P&L'!K63 | ... AM15: ='CC P&L'!AM63
B17: Danville (DN)
B18: Total Revenue | D18: ='DN P&L'!D21 | E18: ='DN P&L'!E21 | F18: ='DN P&L'!F21 | G18: ='DN P&L'!G21 | H18: ='DN P&L'!H21 | I18: ='DN P&L'!I21 | J18: ='DN P&L'!J21 | K18: ='DN P&L'!K21 | ... AM18: ='DN P&L'!AM21
B19: Gross Profit | D19: ='DN P&L'!D26 | E19: ='DN P&L'!E26 | F19: ='DN P&L'!F26 | G19: ='DN P&L'!G26 | H19: ='DN P&L'!H26 | I19: ='DN P&L'!I26 | J19: ='DN P&L'!J26 | K19: ='DN P&L'!K26 | ... AM19: ='DN P&L'!AM26
B20: Total Operating Expenses | D20: ='DN P&L'!D62 | E20: ='DN P&L'!E62 | F20: ='DN P&L'!F62 | G20: ='DN P&L'!G62 | H20: ='DN P&L'!H62 | I20: ='DN P&L'!I62 | J20: ='DN P&L'!J62 | K20: ='DN P&L'!K62 | ... AM20: ='DN P&L'!AM62
B21: Net Operating Income | D21: ='DN P&L'!D63 | E21: ='DN P&L'!E63 | F21: ='DN P&L'!F63 | G21: ='DN P&L'!G63 | H21: ='DN P&L'!H63 | I21: ='DN P&L'!I63 | J21: ='DN P&L'!J63 | K21: ='DN P&L'!K63 | ... AM21: ='DN P&L'!AM63
B23: Lafayette (LF)
B24: Total Revenue | D24: ='LF P&L'!D21 | E24: ='LF P&L'!E21 | F24: ='LF P&L'!F21 | G24: ='LF P&L'!G21 | H24: ='LF P&L'!H21 | I24: ='LF P&L'!I21 | J24: ='LF P&L'!J21 | K24: ='LF P&L'!K21 | ... AM24: ='LF P&L'!AM21
B25: Gross Profit | D25: ='LF P&L'!D26 | E25: ='LF P&L'!E26 | F25: ='LF P&L'!F26 | G25: ='LF P&L'!G26 | H25: ='LF P&L'!H26 | I25: ='LF P&L'!I26 | J25: ='LF P&L'!J26 | K25: ='LF P&L'!K26 | ... AM25: ='LF P&L'!AM26
B26: Total Operating Expenses | D26: ='LF P&L'!D62 | E26: ='LF P&L'!E62 | F26: ='LF P&L'!F62 | G26: ='LF P&L'!G62 | H26: ='LF P&L'!H62 | I26: ='LF P&L'!I62 | J26: ='LF P&L'!J62 | K26: ='LF P&L'!K62 | ... AM26: ='LF P&L'!AM62
B27: Net Operating Income | D27: ='LF P&L'!D63 | E27: ='LF P&L'!E63 | F27: ='LF P&L'!F63 | G27: ='LF P&L'!G63 | H27: ='LF P&L'!H63 | I27: ='LF P&L'!I63 | J27: ='LF P&L'!J63 | K27: ='LF P&L'!K63 | ... AM27: ='LF P&L'!AM63
B29: Marin (MR)
B30: Total Revenue | D30: ='MR P&L'!D21 | E30: ='MR P&L'!E21 | F30: ='MR P&L'!F21 | G30: ='MR P&L'!G21 | H30: ='MR P&L'!H21 | I30: ='MR P&L'!I21 | J30: ='MR P&L'!J21 | K30: ='MR P&L'!K21 | ... AM30: ='MR P&L'!AM21
B31: Gross Profit | D31: ='MR P&L'!D26 | E31: ='MR P&L'!E26 | F31: ='MR P&L'!F26 | G31: ='MR P&L'!G26 | H31: ='MR P&L'!H26 | I31: ='MR P&L'!I26 | J31: ='MR P&L'!J26 | K31: ='MR P&L'!K26 | ... AM31: ='MR P&L'!AM26
B32: Total Operating Expenses | D32: ='MR P&L'!D62 | E32: ='MR P&L'!E62 | F32: ='MR P&L'!F62 | G32: ='MR P&L'!G62 | H32: ='MR P&L'!H62 | I32: ='MR P&L'!I62 | J32: ='MR P&L'!J62 | K32: ='MR P&L'!K62 | ... AM32: ='MR P&L'!AM62
B33: Net Operating Income | D33: ='MR P&L'!D63 | E33: ='MR P&L'!E63 | F33: ='MR P&L'!F63 | G33: ='MR P&L'!G63 | H33: ='MR P&L'!H63 | I33: ='MR P&L'!I63 | J33: ='MR P&L'!J63 | K33: ='MR P&L'!K63 | ... AM33: ='MR P&L'!AM63
B35: Ocean Park (OP)
B36: Total Revenue | D36: ='OP P&L'!D21 | E36: ='OP P&L'!E21 | F36: ='OP P&L'!F21 | G36: ='OP P&L'!G21 | H36: ='OP P&L'!H21 | I36: ='OP P&L'!I21 | J36: ='OP P&L'!J21 | K36: ='OP P&L'!K21 | ... AM36: ='OP P&L'!AM21
B37: Gross Profit | D37: ='OP P&L'!D26 | E37: ='OP P&L'!E26 | F37: ='OP P&L'!F26 | G37: ='OP P&L'!G26 | H37: ='OP P&L'!H26 | I37: ='OP P&L'!I26 | J37: ='OP P&L'!J26 | K37: ='OP P&L'!K26 | ... AM37: ='OP P&L'!AM26
B38: Total Operating Expenses | D38: ='OP P&L'!D62 | E38: ='OP P&L'!E62 | F38: ='OP P&L'!F62 | G38: ='OP P&L'!G62 | H38: ='OP P&L'!H62 | I38: ='OP P&L'!I62 | J38: ='OP P&L'!J62 | K38: ='OP P&L'!K62 | ... AM38: ='OP P&L'!AM62
B39: Net Operating Income | D39: ='OP P&L'!D63 | E39: ='OP P&L'!E63 | F39: ='OP P&L'!F63 | G39: ='OP P&L'!G63 | H39: ='OP P&L'!H63 | I39: ='OP P&L'!I63 | J39: ='OP P&L'!J63 | K39: ='OP P&L'!K63 | ... AM39: ='OP P&L'!AM63
B41: Presidio Heights (PH)
B42: Total Revenue | D42: ='PH P&L'!D21 | E42: ='PH P&L'!E21 | F42: ='PH P&L'!F21 | G42: ='PH P&L'!G21 | H42: ='PH P&L'!H21 | I42: ='PH P&L'!I21 | J42: ='PH P&L'!J21 | K42: ='PH P&L'!K21 | ... AM42: ='PH P&L'!AM21
B43: Gross Profit | D43: ='PH P&L'!D26 | E43: ='PH P&L'!E26 | F43: ='PH P&L'!F26 | G43: ='PH P&L'!G26 | H43: ='PH P&L'!H26 | I43: ='PH P&L'!I26 | J43: ='PH P&L'!J26 | K43: ='PH P&L'!K26 | ... AM43: ='PH P&L'!AM26
B44: Total Operating Expenses | D44: ='PH P&L'!D62 | E44: ='PH P&L'!E62 | F44: ='PH P&L'!F62 | G44: ='PH P&L'!G62 | H44: ='PH P&L'!H62 | I44: ='PH P&L'!I62 | J44: ='PH P&L'!J62 | K44: ='PH P&L'!K62 | ... AM44: ='PH P&L'!AM62
B45: Net Operating Income | D45: ='PH P&L'!D63 | E45: ='PH P&L'!E63 | F45: ='PH P&L'!F63 | G45: ='PH P&L'!G63 | H45: ='PH P&L'!H63 | I45: ='PH P&L'!I63 | J45: ='PH P&L'!J63 | K45: ='PH P&L'!K63 | ... AM45: ='PH P&L'!AM63
B47: Russian Hill (RH)
B48: Total Revenue | D48: ='RH P&L'!D21 | E48: ='RH P&L'!E21 | F48: ='RH P&L'!F21 | G48: ='RH P&L'!G21 | H48: ='RH P&L'!H21 | I48: ='RH P&L'!I21 | J48: ='RH P&L'!J21 | K48: ='RH P&L'!K21 | ... AM48: ='RH P&L'!AM21
B49: Gross Profit | D49: ='RH P&L'!D26 | E49: ='RH P&L'!E26 | F49: ='RH P&L'!F26 | G49: ='RH P&L'!G26 | H49: ='RH P&L'!H26 | I49: ='RH P&L'!I26 | J49: ='RH P&L'!J26 | K49: ='RH P&L'!K26 | ... AM49: ='RH P&L'!AM26
B50: Total Operating Expenses | D50: ='RH P&L'!D62 | E50: ='RH P&L'!E62 | F50: ='RH P&L'!F62 | G50: ='RH P&L'!G62 | H50: ='RH P&L'!H62 | I50: ='RH P&L'!I62 | J50: ='RH P&L'!J62 | K50: ='RH P&L'!K62 | ... AM50: ='RH P&L'!AM62
B51: Net Operating Income | D51: ='RH P&L'!D63 | E51: ='RH P&L'!E63 | F51: ='RH P&L'!F63 | G51: ='RH P&L'!G63 | H51: ='RH P&L'!H63 | I51: ='RH P&L'!I63 | J51: ='RH P&L'!J63 | K51: ='RH P&L'!K63 | ... AM51: ='RH P&L'!AM63
B53: Santa Barbara (SB)
B54: Total Revenue | D54: ='SB P&L'!D21 | E54: ='SB P&L'!E21 | F54: ='SB P&L'!F21 | G54: ='SB P&L'!G21 | H54: ='SB P&L'!H21 | I54: ='SB P&L'!I21 | J54: ='SB P&L'!J21 | K54: ='SB P&L'!K21 | ... AM54: ='SB P&L'!AM21
B55: Gross Profit | D55: ='SB P&L'!D26 | E55: ='SB P&L'!E26 | F55: ='SB P&L'!F26 | G55: ='SB P&L'!G26 | H55: ='SB P&L'!H26 | I55: ='SB P&L'!I26 | J55: ='SB P&L'!J26 | K55: ='SB P&L'!K26 | ... AM55: ='SB P&L'!AM26
B56: Total Operating Expenses | D56: ='SB P&L'!D62 | E56: ='SB P&L'!E62 | F56: ='SB P&L'!F62 | G56: ='SB P&L'!G62 | H56: ='SB P&L'!H62 | I56: ='SB P&L'!I62 | J56: ='SB P&L'!J62 | K56: ='SB P&L'!K62 | ... AM56: ='SB P&L'!AM62
B57: Net Operating Income | D57: ='SB P&L'!D63 | E57: ='SB P&L'!E63 | F57: ='SB P&L'!F63 | G57: ='SB P&L'!G63 | H57: ='SB P&L'!H63 | I57: ='SB P&L'!I63 | J57: ='SB P&L'!J63 | K57: ='SB P&L'!K63 | ... AM57: ='SB P&L'!AM63
B59: Santa Monica (SM)
B60: Total Revenue | D60: ='SM P&L'!D21 | E60: ='SM P&L'!E21 | F60: ='SM P&L'!F21 | G60: ='SM P&L'!G21 | H60: ='SM P&L'!H21 | I60: ='SM P&L'!I21 | J60: ='SM P&L'!J21 | K60: ='SM P&L'!K21 | ... AM60: ='SM P&L'!AM21
B61: Gross Profit | D61: ='SM P&L'!D26 | E61: ='SM P&L'!E26 | F61: ='SM P&L'!F26 | G61: ='SM P&L'!G26 | H61: ='SM P&L'!H26 | I61: ='SM P&L'!I26 | J61: ='SM P&L'!J26 | K61: ='SM P&L'!K26 | ... AM61: ='SM P&L'!AM26
B62: Total Operating Expenses | D62: ='SM P&L'!D62 | E62: ='SM P&L'!E62 | F62: ='SM P&L'!F62 | G62: ='SM P&L'!G62 | H62: ='SM P&L'!H62 | I62: ='SM P&L'!I62 | J62: ='SM P&L'!J62 | K62: ='SM P&L'!K62 | ... AM62: ='SM P&L'!AM62
B63: Net Operating Income | D63: ='SM P&L'!D63 | E63: ='SM P&L'!E63 | F63: ='SM P&L'!F63 | G63: ='SM P&L'!G63 | H63: ='SM P&L'!H63 | I63: ='SM P&L'!I63 | J63: ='SM P&L'!J63 | K63: ='SM P&L'!K63 | ... AM63: ='SM P&L'!AM63
B65: West Portal (WP)
B66: Total Revenue | D66: ='WP P&L'!D21 | E66: ='WP P&L'!E21 | F66: ='WP P&L'!F21 | G66: ='WP P&L'!G21 | H66: ='WP P&L'!H21 | I66: ='WP P&L'!I21 | J66: ='WP P&L'!J21 | K66: ='WP P&L'!K21 | ... AM66: ='WP P&L'!AM21
B67: Gross Profit | D67: ='WP P&L'!D26 | E67: ='WP P&L'!E26 | F67: ='WP P&L'!F26 | G67: ='WP P&L'!G26 | H67: ='WP P&L'!H26 | I67: ='WP P&L'!I26 | J67: ='WP P&L'!J26 | K67: ='WP P&L'!K26 | ... AM67: ='WP P&L'!AM26
B68: Total Operating Expenses | D68: ='WP P&L'!D62 | E68: ='WP P&L'!E62 | F68: ='WP P&L'!F62 | G68: ='WP P&L'!G62 | H68: ='WP P&L'!H62 | I68: ='WP P&L'!I62 | J68: ='WP P&L'!J62 | K68: ='WP P&L'!K62 | ... AM68: ='WP P&L'!AM62
B69: Net Operating Income | D69: ='WP P&L'!D63 | E69: ='WP P&L'!E63 | F69: ='WP P&L'!F63 | G69: ='WP P&L'!G63 | H69: ='WP P&L'!H63 | I69: ='WP P&L'!I63 | J69: ='WP P&L'!J63 | K69: ='WP P&L'!K63 | ... AM69: ='WP P&L'!AM63
B71: Westwood (WW)
B72: Total Revenue | D72: ='WW P&L'!D21 | E72: ='WW P&L'!E21 | F72: ='WW P&L'!F21 | G72: ='WW P&L'!G21 | H72: ='WW P&L'!H21 | I72: ='WW P&L'!I21 | J72: ='WW P&L'!J21 | K72: ='WW P&L'!K21 | ... AM72: ='WW P&L'!AM21
B73: Gross Profit | D73: ='WW P&L'!D26 | E73: ='WW P&L'!E26 | F73: ='WW P&L'!F26 | G73: ='WW P&L'!G26 | H73: ='WW P&L'!H26 | I73: ='WW P&L'!I26 | J73: ='WW P&L'!J26 | K73: ='WW P&L'!K26 | ... AM73: ='WW P&L'!AM26
B74: Total Operating Expenses | D74: ='WW P&L'!D62 | E74: ='WW P&L'!E62 | F74: ='WW P&L'!F62 | G74: ='WW P&L'!G62 | H74: ='WW P&L'!H62 | I74: ='WW P&L'!I62 | J74: ='WW P&L'!J62 | K74: ='WW P&L'!K62 | ... AM74: ='WW P&L'!AM62
B75: Net Operating Income | D75: ='WW P&L'!D63 | E75: ='WW P&L'!E63 | F75: ='WW P&L'!F63 | G75: ='WW P&L'!G63 | H75: ='WW P&L'!H63 | I75: ='WW P&L'!I63 | J75: ='WW P&L'!J63 | K75: ='WW P&L'!K63 | ... AM75: ='WW P&L'!AM63

Sheet BK P&L
B2: Berkeley (BK) — Profit & Loss
B4: Monthly P&L (Detail)
B5: Line Item | D5: Jan 2026 | E5: Feb 2026 | F5: Mar 2026 | G5: Apr 2026 | H5: May 2026 | I5: Jun 2026 | J5: Jul 2026 | K5: Aug 2026 | L5: Sep 2026 | M5: Oct 2026 | N5: Nov 2026 | O5: Dec 2026 | P5: Jan 2027 | Q5: Feb 2027 | R5: Mar 2027 | S5: Apr 2027 | T5: May 2027 | U5: Jun 2027 | V5: Jul 2027 | W5: Aug 2027 | X5: Sep 2027 | Y5: Oct 2027 | Z5: Nov 2027 | AA5: Dec 2027 | AB5: Jan 2028 | AC5: Feb 2028 | AD5: Mar 2028 | AE5: Apr 2028 | AF5: May 2028 | AG5: Jun 2028 | AH5: Jul 2028 | AI5: Aug 2028 | AJ5: Sep 2028 | AK5: Oct 2028 | AL5: Nov 2028 | AM5: Dec 2028
B6: INCOME
B7: 401001 Machine | D7: 67553.69 | E7: 60691.23 | F7: 63647.98 | G7: 60903.08 | H7: 59469.95 | I7: =I13*0.598021 | J7: =J13*0.598021 | K7: =K13*0.598021 | L7: =L13*0.598021 | M7: =M13*0.598021 | N7: =N13*0.598021 | O7: =O13*0.598021 | P7: =P13*0.598021 | ... AM7: =AM13*0.598021
B8: 401002 Private Pilates | D8: 4967 | E8: 6520 | F8: 7898 | G8: 6484 | H8: 4535 | I8: =I13*0.061196 | J8: =J13*0.061196 | K8: =K13*0.061196 | L8: =L13*0.061196 | M8: =M13*0.061196 | N8: =N13*0.061196 | O8: =O13*0.061196 | P8: =P13*0.061196 | ... AM8: =AM13*0.061196
B9: 401003 Class Pass | D9: 28869.3 | E9: 25522.33 | F9: 29455.32 | G9: 30289 | H9: 26097.27 | I9: =I13*0.270003 | J9: =J13*0.270003 | K9: =K13*0.270003 | L9: =L13*0.270003 | M9: =M13*0.270003 | N9: =N13*0.270003 | O9: =O13*0.270003 | P9: =P13*0.270003 | ... AM9: =AM13*0.270003
B10: 401004 Mighty Teacher Training | D10: 21644.5 | E10: 6831 | F10: 0 | G10: 0 | H10: 0 | I10: =I13*0.067362 | J10: =J13*0.067362 | K10: =K13*0.067362 | L10: =L13*0.067362 | M10: =M13*0.067362 | N10: =N13*0.067362 | O10: =O13*0.067362 | P10: =P13*0.067362 | ... AM10: =AM13*0.067362
B11: 401005 Livestream Classes | D11: 49.4 | E11: 64.9 | F11: 82.6 | G11: 18.22 | H11: 31.56 | I11: =I13*0.000509 | J11: =J13*0.000509 | K11: =K13*0.000509 | L11: =L13*0.000509 | M11: =M13*0.000509 | N11: =N13*0.000509 | O11: =O13*0.000509 | P11: =P13*0.000509 | ... AM11: =AM13*0.000509
B12: 401006 Wellhub | D12: 289 | E12: 341.54 | F12: 289 | G12: 309.99 | H12: 202.28 | I12: =I13*0.002909 | J12: =J13*0.002909 | K12: =K13*0.002909 | L12: =L13*0.002909 | M12: =M13*0.002909 | N12: =N13*0.002909 | O12: =O13*0.002909 | P12: =P13*0.002909 | ... AM12: =AM13*0.002909
B13: Total Sessions | D13: 123372.89 | E13: 99971 | F13: 101372.9 | G13: 98004.29 | H13: 90336.06 | I13: ='Sales Forecast'!I6*Assumptions!$C$12+'Sales Forecast'!H6*Assumptions!$D$12+'Sales Forecast'!G6*Assumptions!$E$12+'Sales Forecast'!F6*Assumptions!$F$12+'Sales Forecast'!E6*Assumptions!$G$12+'Sales Forecast'!D6*Assumptions!$H$12+'Sales Forecast'!I102*Assumptions!$I$12 | J13: ='Sales Forecast'!J6*Assumptions!$C$12+'Sales Forecast'!I6*Assumptions!$D$12+'Sales Forecast'!H6*Assumptions!$E$12+'Sales Forecast'!G6*Assumptions!$F$12+'Sales Forecast'!F6*Assumptions!$G$12+'Sales Forecast'!E6*Assumptions!$H$12+'Sales Forecast'!D6*Assumptions!$I$12 | K13: ='Sales Forecast'!K6*Assumptions!$C$12+'Sales Forecast'!J6*Assumptions!$D$12+'Sales Forecast'!I6*Assumptions!$E$12+'Sales Forecast'!H6*Assumptions!$F$12+'Sales Forecast'!G6*Assumptions!$G$12+'Sales Forecast'!F6*Assumptions!$H$12+'Sales Forecast'!E6*Assumptions!$I$12 | L13: ='Sales Forecast'!L6*Assumptions!$C$12+'Sales Forecast'!K6*Assumptions!$D$12+'Sales Forecast'!J6*Assumptions!$E$12+'Sales Forecast'!I6*Assumptions!$F$12+'Sales Forecast'!H6*Assumptions!$G$12+'Sales Forecast'!G6*Assumptions!$H$12+'Sales Forecast'!F6*Assumptions!$I$12 | M13: ='Sales Forecast'!M6*Assumptions!$C$12+'Sales Forecast'!L6*Assumptions!$D$12+'Sales Forecast'!K6*Assumptions!$E$12+'Sales Forecast'!J6*Assumptions!$F$12+'Sales Forecast'!I6*Assumptions!$G$12+'Sales Forecast'!H6*Assumptions!$H$12+'Sales Forecast'!G6*Assumptions!$I$12 | N13: ='Sales Forecast'!N6*Assumptions!$C$12+'Sales Forecast'!M6*Assumptions!$D$12+'Sales Forecast'!L6*Assumptions!$E$12+'Sales Forecast'!K6*Assumptions!$F$12+'Sales Forecast'!J6*Assumptions!$G$12+'Sales Forecast'!I6*Assumptions!$H$12+'Sales Forecast'!H6*Assumptions!$I$12 | O13: ='Sales Forecast'!O6*Assumptions!$C$12+'Sales Forecast'!N6*Assumptions!$D$12+'Sales Forecast'!M6*Assumptions!$E$12+'Sales Forecast'!L6*Assumptions!$F$12+'Sales Forecast'!K6*Assumptions!$G$12+'Sales Forecast'!J6*Assumptions!$H$12+'Sales Forecast'!I6*Assumptions!$I$12 | P13: ='Sales Forecast'!P6*Assumptions!$C$12+'Sales Forecast'!O6*Assumptions!$D$12+'Sales Forecast'!N6*Assumptions!$E$12+'Sales Forecast'!M6*Assumptions!$F$12+'Sales Forecast'!L6*Assumptions!$G$12+'Sales Forecast'!K6*Assumptions!$H$12+'Sales Forecast'!J6*Assumptions!$I$12 | Q13: ='Sales Forecast'!Q6*Assumptions!$C$12+'Sales Forecast'!P6*Assumptions!$D$12+'Sales Forecast'!O6*Assumptions!$E$12+'Sales Forecast'!N6*Assumptions!$F$12+'Sales Forecast'!M6*Assumptions!$G$12+'Sales Forecast'!L6*Assumptions!$H$12+'Sales Forecast'!K6*Assumptions!$I$12 | ... AM13: ='Sales Forecast'!AM6*Assumptions!$C$12+'Sales Forecast'!AL6*Assumptions!$D$12+'Sales Forecast'!AK6*Assumptions!$E$12+'Sales Forecast'!AJ6*Assumptions!$F$12+'Sales Forecast'!AI6*Assumptions!$G$12+'Sales Forecast'!AH6*Assumptions!$H$12+'Sales Forecast'!AG6*Assumptions!$I$12
B14: 403001 Machine Breakage | D14: 17169.98 | E14: 24950.31 | F14: 19308.85 | G14: 22389.08 | H14: 17746.33 | I14: =I17*0.952386 | J14: =J17*0.952386 | K14: =K17*0.952386 | L14: =L17*0.952386 | M14: =M17*0.952386 | N14: =N17*0.952386 | O14: =O17*0.952386 | P14: =P17*0.952386 | ... AM14: =AM17*0.952386
B15: 403003 Private Pilates Breakage | D15: 1385 | E15: 430 | F15: 965 | G15: 1375 | H15: 1085 | I15: =I17*0.047211 | J15: =J17*0.047211 | K15: =K17*0.047211 | L15: =L17*0.047211 | M15: =M17*0.047211 | N15: =N17*0.047211 | O15: =O17*0.047211 | P15: =P17*0.047211 | ... AM15: =AM17*0.047211
B16: 403004 Other Breakage | D16: 0 | E16: 35.4 | F16: 0 | G16: 0 | H16: 0 | I16: =I17*0.000402 | J16: =J17*0.000402 | K16: =K17*0.000402 | L16: =L17*0.000402 | M16: =M17*0.000402 | N16: =N17*0.000402 | O16: =O17*0.000402 | P16: =P17*0.000402 | ... AM16: =AM17*0.000402
B17: Total Breakage Revenue | D17: 18554.98 | E17: 25415.71 | F17: 20273.85 | G17: 23764.08 | H17: 18831.33 | I17: ='Sales Forecast'!I6*Assumptions!$C$13+'Sales Forecast'!H6*Assumptions!$D$13+'Sales Forecast'!G6*Assumptions!$E$13+'Sales Forecast'!F6*Assumptions!$F$13+'Sales Forecast'!E6*Assumptions!$G$13+'Sales Forecast'!D6*Assumptions!$H$13+'Sales Forecast'!I102*Assumptions!$I$13 | J17: ='Sales Forecast'!J6*Assumptions!$C$13+'Sales Forecast'!I6*Assumptions!$D$13+'Sales Forecast'!H6*Assumptions!$E$13+'Sales Forecast'!G6*Assumptions!$F$13+'Sales Forecast'!F6*Assumptions!$G$13+'Sales Forecast'!E6*Assumptions!$H$13+'Sales Forecast'!D6*Assumptions!$I$13 | K17: ='Sales Forecast'!K6*Assumptions!$C$13+'Sales Forecast'!J6*Assumptions!$D$13+'Sales Forecast'!I6*Assumptions!$E$13+'Sales Forecast'!H6*Assumptions!$F$13+'Sales Forecast'!G6*Assumptions!$G$13+'Sales Forecast'!F6*Assumptions!$H$13+'Sales Forecast'!E6*Assumptions!$I$13 | L17: ='Sales Forecast'!L6*Assumptions!$C$13+'Sales Forecast'!K6*Assumptions!$D$13+'Sales Forecast'!J6*Assumptions!$E$13+'Sales Forecast'!I6*Assumptions!$F$13+'Sales Forecast'!H6*Assumptions!$G$13+'Sales Forecast'!G6*Assumptions!$H$13+'Sales Forecast'!F6*Assumptions!$I$13 | M17: ='Sales Forecast'!M6*Assumptions!$C$13+'Sales Forecast'!L6*Assumptions!$D$13+'Sales Forecast'!K6*Assumptions!$E$13+'Sales Forecast'!J6*Assumptions!$F$13+'Sales Forecast'!I6*Assumptions!$G$13+'Sales Forecast'!H6*Assumptions!$H$13+'Sales Forecast'!G6*Assumptions!$I$13 | N17: ='Sales Forecast'!N6*Assumptions!$C$13+'Sales Forecast'!M6*Assumptions!$D$13+'Sales Forecast'!L6*Assumptions!$E$13+'Sales Forecast'!K6*Assumptions!$F$13+'Sales Forecast'!J6*Assumptions!$G$13+'Sales Forecast'!I6*Assumptions!$H$13+'Sales Forecast'!H6*Assumptions!$I$13 | O17: ='Sales Forecast'!O6*Assumptions!$C$13+'Sales Forecast'!N6*Assumptions!$D$13+'Sales Forecast'!M6*Assumptions!$E$13+'Sales Forecast'!L6*Assumptions!$F$13+'Sales Forecast'!K6*Assumptions!$G$13+'Sales Forecast'!J6*Assumptions!$H$13+'Sales Forecast'!I6*Assumptions!$I$13 | P17: ='Sales Forecast'!P6*Assumptions!$C$13+'Sales Forecast'!O6*Assumptions!$D$13+'Sales Forecast'!N6*Assumptions!$E$13+'Sales Forecast'!M6*Assumptions!$F$13+'Sales Forecast'!L6*Assumptions!$G$13+'Sales Forecast'!K6*Assumptions!$H$13+'Sales Forecast'!J6*Assumptions!$I$13 | Q17: ='Sales Forecast'!Q6*Assumptions!$C$13+'Sales Forecast'!P6*Assumptions!$D$13+'Sales Forecast'!O6*Assumptions!$E$13+'Sales Forecast'!N6*Assumptions!$F$13+'Sales Forecast'!M6*Assumptions!$G$13+'Sales Forecast'!L6*Assumptions!$H$13+'Sales Forecast'!K6*Assumptions!$I$13 | ... AM17: ='Sales Forecast'!AM6*Assumptions!$C$13+'Sales Forecast'!AL6*Assumptions!$D$13+'Sales Forecast'!AK6*Assumptions!$E$13+'Sales Forecast'!AJ6*Assumptions!$F$13+'Sales Forecast'!AI6*Assumptions!$G$13+'Sales Forecast'!AH6*Assumptions!$H$13+'Sales Forecast'!AG6*Assumptions!$I$13
B18: 404000 Retail Sales | D18: 2152 | E18: 1414 | F18: 1104 | G18: 2254 | H18: 2098 | I18: =1731 | J18: =1731 | K18: =1731 | L18: =1731 | M18: =1731 | N18: =1731 | O18: =1731 | P18: =1731 | ... AM18: =1731
B19: 406000 Refunds | D19: 3600 | E19: 1510 | F19: 2088 | G19: 3980 | H19: 1700 | I19: =('Sales Forecast'!I6*Assumptions!$C$12+'Sales Forecast'!H6*Assumptions!$D$12+'Sales Forecast'!G6*Assumptions!$E$12+'Sales Forecast'!F6*Assumptions!$F$12+'Sales Forecast'!E6*Assumptions!$G$12+'Sales Forecast'!D6*Assumptions!$H$12+'Sales Forecast'!I6*Assumptions!$C$13+'Sales Forecast'!H6*Assumptions!$D$13+'Sales Forecast'!G6*Assumptions!$E$13+'Sales Forecast'!F6*Assumptions!$F$13+'Sales Forecast'!E6*Assumptions!$G$13+'Sales Forecast'!D6*Assumptions!$H$13+1731)*Assumptions!$C$17 | J19: =('Sales Forecast'!J6*Assumptions!$C$12+'Sales Forecast'!I6*Assumptions!$D$12+'Sales Forecast'!H6*Assumptions!$E$12+'Sales Forecast'!G6*Assumptions!$F$12+'Sales Forecast'!F6*Assumptions!$G$12+'Sales Forecast'!E6*Assumptions!$H$12+'Sales Forecast'!D6*Assumptions!$I$12+'Sales Forecast'!J6*Assumptions!$C$13+'Sales Forecast'!I6*Assumptions!$D$13+'Sales Forecast'!H6*Assumptions!$E$13+'Sales Forecast'!G6*Assumptions!$F$13+'Sales Forecast'!F6*Assumptions!$G$13+'Sales Forecast'!E6*Assumptions!$H$13+'Sales Forecast'!D6*Assumptions!$I$13+1731)*Assumptions!$C$17 | K19: =('Sales Forecast'!K6*Assumptions!$C$12+'Sales Forecast'!J6*Assumptions!$D$12+'Sales Forecast'!I6*Assumptions!$E$12+'Sales Forecast'!H6*Assumptions!$F$12+'Sales Forecast'!G6*Assumptions!$G$12+'Sales Forecast'!F6*Assumptions!$H$12+'Sales Forecast'!E6*Assumptions!$I$12+'Sales Forecast'!K6*Assumptions!$C$13+'Sales Forecast'!J6*Assumptions!$D$13+'Sales Forecast'!I6*Assumptions!$E$13+'Sales Forecast'!H6*Assumptions!$F$13+'Sales Forecast'!G6*Assumptions!$G$13+'Sales Forecast'!F6*Assumptions!$H$13+'Sales Forecast'!E6*Assumptions!$I$13+1731)*Assumptions!$C$17 | L19: =('Sales Forecast'!L6*Assumptions!$C$12+'Sales Forecast'!K6*Assumptions!$D$12+'Sales Forecast'!J6*Assumptions!$E$12+'Sales Forecast'!I6*Assumptions!$F$12+'Sales Forecast'!H6*Assumptions!$G$12+'Sales Forecast'!G6*Assumptions!$H$12+'Sales Forecast'!F6*Assumptions!$I$12+'Sales Forecast'!L6*Assumptions!$C$13+'Sales Forecast'!K6*Assumptions!$D$13+'Sales Forecast'!J6*Assumptions!$E$13+'Sales Forecast'!I6*Assumptions!$F$13+'Sales Forecast'!H6*Assumptions!$G$13+'Sales Forecast'!G6*Assumptions!$H$13+'Sales Forecast'!F6*Assumptions!$I$13+1731)*Assumptions!$C$17 | M19: =('Sales Forecast'!M6*Assumptions!$C$12+'Sales Forecast'!L6*Assumptions!$D$12+'Sales Forecast'!K6*Assumptions!$E$12+'Sales Forecast'!J6*Assumptions!$F$12+'Sales Forecast'!I6*Assumptions!$G$12+'Sales Forecast'!H6*Assumptions!$H$12+'Sales Forecast'!G6*Assumptions!$I$12+'Sales Forecast'!M6*Assumptions!$C$13+'Sales Forecast'!L6*Assumptions!$D$13+'Sales Forecast'!K6*Assumptions!$E$13+'Sales Forecast'!J6*Assumptions!$F$13+'Sales Forecast'!I6*Assumptions!$G$13+'Sales Forecast'!H6*Assumptions!$H$13+'Sales Forecast'!G6*Assumptions!$I$13+1731)*Assumptions!$C$17 | N19: =('Sales Forecast'!N6*Assumptions!$C$12+'Sales Forecast'!M6*Assumptions!$D$12+'Sales Forecast'!L6*Assumptions!$E$12+'Sales Forecast'!K6*Assumptions!$F$12+'Sales Forecast'!J6*Assumptions!$G$12+'Sales Forecast'!I6*Assumptions!$H$12+'Sales Forecast'!H6*Assumptions!$I$12+'Sales Forecast'!N6*Assumptions!$C$13+'Sales Forecast'!M6*Assumptions!$D$13+'Sales Forecast'!L6*Assumptions!$E$13+'Sales Forecast'!K6*Assumptions!$F$13+'Sales Forecast'!J6*Assumptions!$G$13+'Sales Forecast'!I6*Assumptions!$H$13+'Sales Forecast'!H6*Assumptions!$I$13+1731)*Assumptions!$C$17 | O19: =('Sales Forecast'!O6*Assumptions!$C$12+'Sales Forecast'!N6*Assumptions!$D$12+'Sales Forecast'!M6*Assumptions!$E$12+'Sales Forecast'!L6*Assumptions!$F$12+'Sales Forecast'!K6*Assumptions!$G$12+'Sales Forecast'!J6*Assumptions!$H$12+'Sales Forecast'!I6*Assumptions!$I$12+'Sales Forecast'!O6*Assumptions!$C$13+'Sales Forecast'!N6*Assumptions!$D$13+'Sales Forecast'!M6*Assumptions!$E$13+'Sales Forecast'!L6*Assumptions!$F$13+'Sales Forecast'!K6*Assumptions!$G$13+'Sales Forecast'!J6*Assumptions!$H$13+'Sales Forecast'!I6*Assumptions!$I$13+1731)*Assumptions!$C$17 | P19: =('Sales Forecast'!P6*Assumptions!$C$12+'Sales Forecast'!O6*Assumptions!$D$12+'Sales Forecast'!N6*Assumptions!$E$12+'Sales Forecast'!M6*Assumptions!$F$12+'Sales Forecast'!L6*Assumptions!$G$12+'Sales Forecast'!K6*Assumptions!$H$12+'Sales Forecast'!J6*Assumptions!$I$12+'Sales Forecast'!P6*Assumptions!$C$13+'Sales Forecast'!O6*Assumptions!$D$13+'Sales Forecast'!N6*Assumptions!$E$13+'Sales Forecast'!M6*Assumptions!$F$13+'Sales Forecast'!L6*Assumptions!$G$13+'Sales Forecast'!K6*Assumptions!$H$13+'Sales Forecast'!J6*Assumptions!$I$13+1731)*Assumptions!$C$17 | Q19: =('Sales Forecast'!Q6*Assumptions!$C$12+'Sales Forecast'!P6*Assumptions!$D$12+'Sales Forecast'!O6*Assumptions!$E$12+'Sales Forecast'!N6*Assumptions!$F$12+'Sales Forecast'!M6*Assumptions!$G$12+'Sales Forecast'!L6*Assumptions!$H$12+'Sales Forecast'!K6*Assumptions!$I$12+'Sales Forecast'!Q6*Assumptions!$C$13+'Sales Forecast'!P6*Assumptions!$D$13+'Sales Forecast'!O6*Assumptions!$E$13+'Sales Forecast'!N6*Assumptions!$F$13+'Sales Forecast'!M6*Assumptions!$G$13+'Sales Forecast'!L6*Assumptions!$H$13+'Sales Forecast'!K6*Assumptions!$I$13+1731)*Assumptions!$C$17 | ... AM19: =('Sales Forecast'!AM6*Assumptions!$C$12+'Sales Forecast'!AL6*Assumptions!$D$12+'Sales Forecast'!AK6*Assumptions!$E$12+'Sales Forecast'!AJ6*Assumptions!$F$12+'Sales Forecast'!AI6*Assumptions!$G$12+'Sales Forecast'!AH6*Assumptions!$H$12+'Sales Forecast'!AG6*Assumptions!$I$12+'Sales Forecast'!AM6*Assumptions!$C$13+'Sales Forecast'!AL6*Assumptions!$D$13+'Sales Forecast'!AK6*Assumptions!$E$13+'Sales Forecast'!AJ6*Assumptions!$F$13+'Sales Forecast'!AI6*Assumptions!$G$13+'Sales Forecast'!AH6*Assumptions!$H$13+'Sales Forecast'!AG6*Assumptions!$I$13+1731)*Assumptions!$C$17
B20: 407000 Discounts | D20: 7048.4 | E20: 3527.26 | F20: 2111.8 | G20: 4735.7 | H20: 2292.2 | I20: =('Sales Forecast'!I6*Assumptions!$C$12+'Sales Forecast'!H6*Assumptions!$D$12+'Sales Forecast'!G6*Assumptions!$E$12+'Sales Forecast'!F6*Assumptions!$F$12+'Sales Forecast'!E6*Assumptions!$G$12+'Sales Forecast'!D6*Assumptions!$H$12+'Sales Forecast'!I6*Assumptions!$C$13+'Sales Forecast'!H6*Assumptions!$D$13+'Sales Forecast'!G6*Assumptions!$E$13+'Sales Forecast'!F6*Assumptions!$F$13+'Sales Forecast'!E6*Assumptions!$G$13+'Sales Forecast'!D6*Assumptions!$H$13+1731)*Assumptions!$C$18 | J20: =('Sales Forecast'!J6*Assumptions!$C$12+'Sales Forecast'!I6*Assumptions!$D$12+'Sales Forecast'!H6*Assumptions!$E$12+'Sales Forecast'!G6*Assumptions!$F$12+'Sales Forecast'!F6*Assumptions!$G$12+'Sales Forecast'!E6*Assumptions!$H$12+'Sales Forecast'!D6*Assumptions!$I$12+'Sales Forecast'!J6*Assumptions!$C$13+'Sales Forecast'!I6*Assumptions!$D$13+'Sales Forecast'!H6*Assumptions!$E$13+'Sales Forecast'!G6*Assumptions!$F$13+'Sales Forecast'!F6*Assumptions!$G$13+'Sales Forecast'!E6*Assumptions!$H$13+'Sales Forecast'!D6*Assumptions!$I$13+1731)*Assumptions!$C$18 | K20: =('Sales Forecast'!K6*Assumptions!$C$12+'Sales Forecast'!J6*Assumptions!$D$12+'Sales Forecast'!I6*Assumptions!$E$12+'Sales Forecast'!H6*Assumptions!$F$12+'Sales Forecast'!G6*Assumptions!$G$12+'Sales Forecast'!F6*Assumptions!$H$12+'Sales Forecast'!E6*Assumptions!$I$12+'Sales Forecast'!K6*Assumptions!$C$13+'Sales Forecast'!J6*Assumptions!$D$13+'Sales Forecast'!I6*Assumptions!$E$13+'Sales Forecast'!H6*Assumptions!$F$13+'Sales Forecast'!G6*Assumptions!$G$13+'Sales Forecast'!F6*Assumptions!$H$13+'Sales Forecast'!E6*Assumptions!$I$13+1731)*Assumptions!$C$18 | L20: =('Sales Forecast'!L6*Assumptions!$C$12+'Sales Forecast'!K6*Assumptions!$D$12+'Sales Forecast'!J6*Assumptions!$E$12+'Sales Forecast'!I6*Assumptions!$F$12+'Sales Forecast'!H6*Assumptions!$G$12+'Sales Forecast'!G6*Assumptions!$H$12+'Sales Forecast'!F6*Assumptions!$I$12+'Sales Forecast'!L6*Assumptions!$C$13+'Sales Forecast'!K6*Assumptions!$D$13+'Sales Forecast'!J6*Assumptions!$E$13+'Sales Forecast'!I6*Assumptions!$F$13+'Sales Forecast'!H6*Assumptions!$G$13+'Sales Forecast'!G6*Assumptions!$H$13+'Sales Forecast'!F6*Assumptions!$I$13+1731)*Assumptions!$C$18 | M20: =('Sales Forecast'!M6*Assumptions!$C$12+'Sales Forecast'!L6*Assumptions!$D$12+'Sales Forecast'!K6*Assumptions!$E$12+'Sales Forecast'!J6*Assumptions!$F$12+'Sales Forecast'!I6*Assumptions!$G$12+'Sales Forecast'!H6*Assumptions!$H$12+'Sales Forecast'!G6*Assumptions!$I$12+'Sales Forecast'!M6*Assumptions!$C$13+'Sales Forecast'!L6*Assumptions!$D$13+'Sales Forecast'!K6*Assumptions!$E$13+'Sales Forecast'!J6*Assumptions!$F$13+'Sales Forecast'!I6*Assumptions!$G$13+'Sales Forecast'!H6*Assumptions!$H$13+'Sales Forecast'!G6*Assumptions!$I$13+1731)*Assumptions!$C$18 | N20: =('Sales Forecast'!N6*Assumptions!$C$12+'Sales Forecast'!M6*Assumptions!$D$12+'Sales Forecast'!L6*Assumptions!$E$12+'Sales Forecast'!K6*Assumptions!$F$12+'Sales Forecast'!J6*Assumptions!$G$12+'Sales Forecast'!I6*Assumptions!$H$12+'Sales Forecast'!H6*Assumptions!$I$12+'Sales Forecast'!N6*Assumptions!$C$13+'Sales Forecast'!M6*Assumptions!$D$13+'Sales Forecast'!L6*Assumptions!$E$13+'Sales Forecast'!K6*Assumptions!$F$13+'Sales Forecast'!J6*Assumptions!$G$13+'Sales Forecast'!I6*Assumptions!$H$13+'Sales Forecast'!H6*Assumptions!$I$13+1731)*Assumptions!$C$18 | O20: =('Sales Forecast'!O6*Assumptions!$C$12+'Sales Forecast'!N6*Assumptions!$D$12+'Sales Forecast'!M6*Assumptions!$E$12+'Sales Forecast'!L6*Assumptions!$F$12+'Sales Forecast'!K6*Assumptions!$G$12+'Sales Forecast'!J6*Assumptions!$H$12+'Sales Forecast'!I6*Assumptions!$I$12+'Sales Forecast'!O6*Assumptions!$C$13+'Sales Forecast'!N6*Assumptions!$D$13+'Sales Forecast'!M6*Assumptions!$E$13+'Sales Forecast'!L6*Assumptions!$F$13+'Sales Forecast'!K6*Assumptions!$G$13+'Sales Forecast'!J6*Assumptions!$H$13+'Sales Forecast'!I6*Assumptions!$I$13+1731)*Assumptions!$C$18 | P20: =('Sales Forecast'!P6*Assumptions!$C$12+'Sales Forecast'!O6*Assumptions!$D$12+'Sales Forecast'!N6*Assumptions!$E$12+'Sales Forecast'!M6*Assumptions!$F$12+'Sales Forecast'!L6*Assumptions!$G$12+'Sales Forecast'!K6*Assumptions!$H$12+'Sales Forecast'!J6*Assumptions!$I$12+'Sales Forecast'!P6*Assumptions!$C$13+'Sales Forecast'!O6*Assumptions!$D$13+'Sales Forecast'!N6*Assumptions!$E$13+'Sales Forecast'!M6*Assumptions!$F$13+'Sales Forecast'!L6*Assumptions!$G$13+'Sales Forecast'!K6*Assumptions!$H$13+'Sales Forecast'!J6*Assumptions!$I$13+1731)*Assumptions!$C$18 | Q20: =('Sales Forecast'!Q6*Assumptions!$C$12+'Sales Forecast'!P6*Assumptions!$D$12+'Sales Forecast'!O6*Assumptions!$E$12+'Sales Forecast'!N6*Assumptions!$F$12+'Sales Forecast'!M6*Assumptions!$G$12+'Sales Forecast'!L6*Assumptions!$H$12+'Sales Forecast'!K6*Assumptions!$I$12+'Sales Forecast'!Q6*Assumptions!$C$13+'Sales Forecast'!P6*Assumptions!$D$13+'Sales Forecast'!O6*Assumptions!$E$13+'Sales Forecast'!N6*Assumptions!$F$13+'Sales Forecast'!M6*Assumptions!$G$13+'Sales Forecast'!L6*Assumptions!$H$13+'Sales Forecast'!K6*Assumptions!$I$13+1731)*Assumptions!$C$18 | ... AM20: =('Sales Forecast'!AM6*Assumptions!$C$12+'Sales Forecast'!AL6*Assumptions!$D$12+'Sales Forecast'!AK6*Assumptions!$E$12+'Sales Forecast'!AJ6*Assumptions!$F$12+'Sales Forecast'!AI6*Assumptions!$G$12+'Sales Forecast'!AH6*Assumptions!$H$12+'Sales Forecast'!AG6*Assumptions!$I$12+'Sales Forecast'!AM6*Assumptions!$C$13+'Sales Forecast'!AL6*Assumptions!$D$13+'Sales Forecast'!AK6*Assumptions!$E$13+'Sales Forecast'!AJ6*Assumptions!$F$13+'Sales Forecast'!AI6*Assumptions!$G$13+'Sales Forecast'!AH6*Assumptions!$H$13+'Sales Forecast'!AG6*Assumptions!$I$13+1731)*Assumptions!$C$18
B21: TOTAL REVENUE | D21: 133431.47 | E21: 121763.45 | F21: 118550.95 | G21: 115306.67 | H21: 107273.19 | I21: =I13+I17+I18+I19+I20 | J21: =J13+J17+J18+J19+J20 | K21: =K13+K17+K18+K19+K20 | L21: =L13+L17+L18+L19+L20 | M21: =M13+M17+M18+M19+M20 | N21: =N13+N17+N18+N19+N20 | O21: =O13+O17+O18+O19+O20 | P21: =P13+P17+P18+P19+P20 | ... AM21: =AM13+AM17+AM18+AM19+AM20
B22: COST OF GOODS SOLD
B23: 501000 Product Cost | D23: 1064.8 | E23: 699.7 | F23: 552 | G23: 1117 | H23: 1037.7 | I23: =I21*Assumptions!$C$20 | J23: =J21*Assumptions!$C$20 | K23: =K21*Assumptions!$C$20 | L23: =L21*Assumptions!$C$20 | M23: =M21*Assumptions!$C$20 | N23: =N21*Assumptions!$C$20 | O23: =O21*Assumptions!$C$20 | P23: =P21*Assumptions!$C$20 | ... AM23: =AM21*Assumptions!$C$20
B24: 506000 Merchant Account Fees | D24: 3389.06 | E24: 3622.31 | F24: 2884.21 | G24: 3288.71 | H24: 2178.41 | I24: =I21*Assumptions!$C$19 | J24: =J21*Assumptions!$C$19 | K24: =K21*Assumptions!$C$19 | L24: =L21*Assumptions!$C$19 | M24: =M21*Assumptions!$C$19 | N24: =N21*Assumptions!$C$19 | O24: =O21*Assumptions!$C$19 | P24: =P21*Assumptions!$C$19 | ... AM24: =AM21*Assumptions!$C$19
B25: Total Cost of Goods Sold | D25: 4453.86 | E25: 4322.01 | F25: 3436.21 | G25: 4405.71 | H25: 3216.11 | I25: =I23+I24 | J25: =J23+J24 | K25: =K23+K24 | L25: =L23+L24 | M25: =M23+M24 | N25: =N23+N24 | O25: =O23+O24 | P25: =P23+P24 | ... AM25: =AM23+AM24
B26: GROSS PROFIT | D26: 128977.61 | E26: 117441.44 | F26: 115114.74 | G26: 110900.96 | H26: 104057.08 | I26: =I21-I25 | J26: =J21-J25 | K26: =K21-K25 | L26: =L21-L25 | M26: =M21-M25 | N26: =N21-N25 | O26: =O21-O25 | P26: =P21-P25 | ... AM26: =AM21-AM25
B27: OPERATING EXPENSES
B28: 601001 Paid Ads | D28: 890.91 | E28: 89.99 | F28: 0 | G28: 0 | H28: 0 | I28: 0 | J28: 0 | K28: 0 | L28: 0 | M28: 0 | N28: 0 | O28: 0 | P28: 0 | Q28: 0 | R28: 0 | S28: 0 | T28: 0 | U28: 0 | V28: 0 | W28: 0 | X28: 0 | Y28: 0 | Z28: 0 | AA28: 0 | AB28: 0 | AC28: 0 | AD28: 0 | AE28: 0 | AF28: 0 | AG28: 0 | AH28: 0 | AI28: 0 | AJ28: 0 | AK28: 0 | AL28: 0 | AM28: 0
B29: 601005 Content Creation | D29: 0 | E29: 0 | F29: 0 | G29: 0 | H29: 0 | I29: 0 | J29: 0 | K29: 0 | L29: 0 | M29: 0 | N29: 0 | O29: 0 | P29: 0 | Q29: 0 | R29: 0 | S29: 0 | T29: 0 | U29: 0 | V29: 0 | W29: 0 | X29: 0 | Y29: 0 | Z29: 0 | AA29: 0 | AB29: 0 | AC29: 0 | AD29: 0 | AE29: 0 | AF29: 0 | AG29: 0 | AH29: 0 | AI29: 0 | AJ29: 0 | AK29: 0 | AL29: 0 | AM29: 0
B30: 601006 General Marketing | D30: 0 | E30: 0 | F30: 0 | G30: 0 | H30: 0 | I30: 0 | J30: 0 | K30: 0 | L30: 0 | M30: 0 | N30: 0 | O30: 0 | P30: 0 | Q30: 0 | R30: 0 | S30: 0 | T30: 0 | U30: 0 | V30: 0 | W30: 0 | X30: 0 | Y30: 0 | Z30: 0 | AA30: 0 | AB30: 0 | AC30: 0 | AD30: 0 | AE30: 0 | AF30: 0 | AG30: 0 | AH30: 0 | AI30: 0 | AJ30: 0 | AK30: 0 | AL30: 0 | AM30: 0
B31: 601007 Contractors/Agencies | D31: 0 | E31: 0 | F31: 0 | G31: 0 | H31: 0 | I31: 0 | J31: 0 | K31: 0 | L31: 0 | M31: 0 | N31: 0 | O31: 0 | P31: 0 | Q31: 0 | R31: 0 | S31: 0 | T31: 0 | U31: 0 | V31: 0 | W31: 0 | X31: 0 | Y31: 0 | Z31: 0 | AA31: 0 | AB31: 0 | AC31: 0 | AD31: 0 | AE31: 0 | AF31: 0 | AG31: 0 | AH31: 0 | AI31: 0 | AJ31: 0 | AK31: 0 | AL31: 0 | AM31: 0
B32: 601010 Website Development | D32: 0 | E32: 0 | F32: 0 | G32: 0 | H32: 0 | I32: 0 | J32: 0 | K32: 0 | L32: 0 | M32: 0 | N32: 0 | O32: 0 | P32: 0 | Q32: 0 | R32: 0 | S32: 0 | T32: 0 | U32: 0 | V32: 0 | W32: 0 | X32: 0 | Y32: 0 | Z32: 0 | AA32: 0 | AB32: 0 | AC32: 0 | AD32: 0 | AE32: 0 | AF32: 0 | AG32: 0 | AH32: 0 | AI32: 0 | AJ32: 0 | AK32: 0 | AL32: 0 | AM32: 0
B33: Total Marketing | D33: 890.91 | E33: 89.99 | F33: 0 | G33: 0 | H33: 0 | I33: =I28+I29+I30+I31+I32 | J33: =J28+J29+J30+J31+J32 | K33: =K28+K29+K30+K31+K32 | L33: =L28+L29+L30+L31+L32 | M33: =M28+M29+M30+M31+M32 | N33: =N28+N29+N30+N31+N32 | O33: =O28+O29+O30+O31+O32 | P33: =P28+P29+P30+P31+P32 | ... AM33: =AM28+AM29+AM30+AM31+AM32
B34: 602001 Wages | D34: 53569.86 | E34: 45269.74 | F34: 50483.61 | G34: 48918.6 | H34: 46519.09 | I34: 43315.25 | J34: 38833.52 | K34: 41413.73 | L34: 43268.43 | M34: 45285.75 | N34: 47951.33 | O34: 51055.88 | P34: 40664.36 | Q34: 40625.33 | R34: 34619.86 | S34: 35938.11 | T34: 42329.64 | U34: 37828.54 | V34: 34441.26 | W34: 36324.13 | X34: 37477.66 | Y34: 39849.89 | Z34: 40707.25 | AA34: 44854.49 | AB34: 40664.36 | AC34: 40625.33 | AD34: 34619.86 | AE34: 35938.11 | AF34: 42329.64 | AG34: 37828.54 | AH34: 34441.26 | AI34: 36324.13 | AJ34: 37477.66 | AK34: 39849.89 | AL34: 40707.25 | AM34: 44854.49
B35: 602004 Payroll Taxes | D35: 8608.49 | E35: 4671.71 | F35: 4875.87 | G35: 4083.91 | H35: 3866.81 | I35: 4859.37 | J35: 4356.58 | K35: 4646.05 | L35: 4854.12 | M35: 5080.43 | N35: 5379.47 | O35: 5727.76 | P35: 4561.98 | Q35: 4557.6 | R35: 3883.87 | S35: 4031.76 | T35: 4748.8 | U35: 4243.84 | V35: 3863.83 | W35: 4075.06 | X35: 4204.47 | Y35: 4470.6 | Z35: 4566.79 | AA35: 5032.05 | AB35: 4561.98 | AC35: 4557.6 | AD35: 3883.87 | AE35: 4031.76 | AF35: 4748.8 | AG35: 4243.84 | AH35: 3863.83 | AI35: 4075.06 | AJ35: 4204.47 | AK35: 4470.6 | AL35: 4566.79 | AM35: 5032.05
B36: 602005 Employee Benefits | D36: 576.08 | E36: 604.43 | F36: 788.96 | G36: 594.32 | H36: 505.23 | I36: 560.18 | J36: 502.22 | K36: 535.59 | L36: 559.58 | M36: 585.66 | N36: 620.14 | O36: 660.29 | P36: 525.9 | Q36: 525.39 | R36: 447.73 | S36: 464.77 | T36: 547.43 | U36: 489.22 | V36: 445.42 | W36: 469.77 | X36: 484.69 | Y36: 515.36 | Z36: 526.45 | AA36: 580.09 | AB36: 525.9 | AC36: 525.39 | AD36: 447.73 | AE36: 464.77 | AF36: 547.43 | AG36: 489.22 | AH36: 445.42 | AI36: 469.77 | AJ36: 484.69 | AK36: 515.36 | AL36: 526.45 | AM36: 580.09
B37: 602010 Payroll Processing Fees | D37: 2263.63 | E37: 2268.79 | F37: 3275.92 | G37: 2263.27 | H37: 2125.12 | I37: 2200.62 | J37: 1972.92 | K37: 2104.01 | L37: 2198.24 | M37: 2300.73 | N37: 2436.15 | O37: 2593.88 | P37: 2065.94 | Q37: 2063.96 | R37: 1758.85 | S37: 1825.82 | T37: 2150.54 | U37: 1921.87 | V37: 1749.78 | W37: 1845.44 | X37: 1904.04 | Y37: 2024.56 | Z37: 2068.12 | AA37: 2278.82 | AB37: 2065.94 | AC37: 2063.96 | AD37: 1758.85 | AE37: 1825.82 | AF37: 2150.54 | AG37: 1921.87 | AH37: 1749.78 | AI37: 1845.44 | AJ37: 1904.04 | AK37: 2024.56 | AL37: 2068.12 | AM37: 2278.82
B38: Total Payroll | D38: 65018.06 | E38: 52814.67 | F38: 59424.36 | G38: 55860.1 | H38: 53016.25 | I38: =I34+I35+I36+I37 | J38: =J34+J35+J36+J37 | K38: =K34+K35+K36+K37 | L38: =L34+L35+L36+L37 | M38: =M34+M35+M36+M37 | N38: =N34+N35+N36+N37 | O38: =O34+O35+O36+O37 | P38: =P34+P35+P36+P37 | ... AM38: =AM34+AM35+AM36+AM37
B39: 603000 Software & Web Services | D39: 790.53 | E39: 1351.94 | F39: 737.08 | G39: 763.26 | H39: 762.26 | I39: 864.31 | J39: 864.31 | K39: 864.31 | L39: 864.31 | M39: 864.31 | N39: 864.31 | O39: 864.31 | P39: 864.31 | Q39: 864.31 | R39: 864.31 | S39: 864.31 | T39: 864.31 | U39: 864.31 | V39: 864.31 | W39: 864.31 | X39: 864.31 | Y39: 864.31 | Z39: 864.31 | AA39: 864.31 | AB39: 864.31 | AC39: 864.31 | AD39: 864.31 | AE39: 864.31 | AF39: 864.31 | AG39: 864.31 | AH39: 864.31 | AI39: 864.31 | AJ39: 864.31 | AK39: 864.31 | AL39: 864.31 | AM39: 864.31
B40: 608000 Insurance | D40: 94.62 | E40: 94.62 | F40: 230.72 | G40: 230.72 | H40: 251.35 | I40: 154.38 | J40: 154.38 | K40: 154.38 | L40: 154.38 | M40: 154.38 | N40: 154.38 | O40: 154.38 | P40: 154.38 | Q40: 154.38 | R40: 154.38 | S40: 154.38 | T40: 154.38 | U40: 154.38 | V40: 154.38 | W40: 154.38 | X40: 154.38 | Y40: 154.38 | Z40: 154.38 | AA40: 154.38 | AB40: 154.38 | AC40: 154.38 | AD40: 154.38 | AE40: 154.38 | AF40: 154.38 | AG40: 154.38 | AH40: 154.38 | AI40: 154.38 | AJ40: 154.38 | AK40: 154.38 | AL40: 154.38 | AM40: 154.38
B41: 610000 Office Supplies | D41: 689.59 | E41: 149.49 | F41: 768.45 | G41: 736.05 | H41: 0 | I41: 556.05 | J41: 556.05 | K41: 556.05 | L41: 556.05 | M41: 556.05 | N41: 556.05 | O41: 556.05 | P41: 556.05 | Q41: 556.05 | R41: 556.05 | S41: 556.05 | T41: 556.05 | U41: 556.05 | V41: 556.05 | W41: 556.05 | X41: 556.05 | Y41: 556.05 | Z41: 556.05 | AA41: 556.05 | AB41: 556.05 | AC41: 556.05 | AD41: 556.05 | AE41: 556.05 | AF41: 556.05 | AG41: 556.05 | AH41: 556.05 | AI41: 556.05 | AJ41: 556.05 | AK41: 556.05 | AL41: 556.05 | AM41: 556.05
B42: Total Software & Admin | D42: =D39+D40+D41 | E42: =E39+E40+E41 | F42: =F39+F40+F41 | G42: =G39+G40+G41 | H42: =H39+H40+H41 | I42: =I39+I40+I41 | J42: =J39+J40+J41 | K42: =K39+K40+K41 | ... AM42: =AM39+AM40+AM41
B43: 604100 Legal Fees | D43: 0 | E43: 0 | F43: 0 | G43: 0 | H43: 0 | I43: 0 | J43: 0 | K43: 0 | L43: 0 | M43: 0 | N43: 0 | O43: 0 | P43: 0 | Q43: 0 | R43: 0 | S43: 0 | T43: 0 | U43: 0 | V43: 0 | W43: 0 | X43: 0 | Y43: 0 | Z43: 0 | AA43: 0 | AB43: 0 | AC43: 0 | AD43: 0 | AE43: 0 | AF43: 0 | AG43: 0 | AH43: 0 | AI43: 0 | AJ43: 0 | AK43: 0 | AL43: 0 | AM43: 0
B44: 604200 Accounting | D44: 0 | E44: 301.82 | F44: 440 | G44: 0 | H44: 0 | I44: 136.49 | J44: 136.49 | K44: 136.49 | L44: 136.49 | M44: 136.49 | N44: 136.49 | O44: 136.49 | P44: 136.49 | Q44: 136.49 | R44: 136.49 | S44: 136.49 | T44: 136.49 | U44: 136.49 | V44: 136.49 | W44: 136.49 | X44: 136.49 | Y44: 136.49 | Z44: 136.49 | AA44: 136.49 | AB44: 136.49 | AC44: 136.49 | AD44: 136.49 | AE44: 136.49 | AF44: 136.49 | AG44: 136.49 | AH44: 136.49 | AI44: 136.49 | AJ44: 136.49 | AK44: 136.49 | AL44: 136.49 | AM44: 136.49
B45: 604300 Recruiting | D45: 0 | E45: 0 | F45: 0 | G45: 0 | H45: 0 | I45: 0 | J45: 0 | K45: 0 | L45: 0 | M45: 0 | N45: 0 | O45: 0 | P45: 0 | Q45: 0 | R45: 0 | S45: 0 | T45: 0 | U45: 0 | V45: 0 | W45: 0 | X45: 0 | Y45: 0 | Z45: 0 | AA45: 0 | AB45: 0 | AC45: 0 | AD45: 0 | AE45: 0 | AF45: 0 | AG45: 0 | AH45: 0 | AI45: 0 | AJ45: 0 | AK45: 0 | AL45: 0 | AM45: 0
B46: 604400 Other Professional Fees | D46: 517 | E46: 517 | F46: 517 | G46: 517 | H46: 517 | I46: 380.51 | J46: 380.51 | K46: 380.51 | L46: 380.51 | M46: 380.51 | N46: 380.51 | O46: 380.51 | P46: 380.51 | Q46: 380.51 | R46: 380.51 | S46: 380.51 | T46: 380.51 | U46: 380.51 | V46: 380.51 | W46: 380.51 | X46: 380.51 | Y46: 380.51 | Z46: 380.51 | AA46: 380.51 | AB46: 380.51 | AC46: 380.51 | AD46: 380.51 | AE46: 380.51 | AF46: 380.51 | AG46: 380.51 | AH46: 380.51 | AI46: 380.51 | AJ46: 380.51 | AK46: 380.51 | AL46: 380.51 | AM46: 380.51
B47: Total Professional Fees | D47: 517 | E47: 818.82 | F47: 957 | G47: 517 | H47: 517 | I47: =I43+I44+I45+I46 | J47: =J43+J44+J45+J46 | K47: =K43+K44+K45+K46 | L47: =L43+L44+L45+L46 | M47: =M43+M44+M45+M46 | N47: =N43+N44+N45+N46 | O47: =O43+O44+O45+O46 | P47: =P43+P44+P45+P46 | ... AM47: =AM43+AM44+AM45+AM46
B48: 605000 Travel | D48: 17.1 | E48: 34 | F48: 6.02 | G48: 12.53 | H48: 0 | I48: 21.44 | J48: 21.44 | K48: 21.44 | L48: 21.44 | M48: 21.44 | N48: 21.44 | O48: 21.44 | P48: 21.44 | Q48: 21.44 | R48: 21.44 | S48: 21.44 | T48: 21.44 | U48: 21.44 | V48: 21.44 | W48: 21.44 | X48: 21.44 | Y48: 21.44 | Z48: 21.44 | AA48: 21.44 | AB48: 21.44 | AC48: 21.44 | AD48: 21.44 | AE48: 21.44 | AF48: 21.44 | AG48: 21.44 | AH48: 21.44 | AI48: 21.44 | AJ48: 21.44 | AK48: 21.44 | AL48: 21.44 | AM48: 21.44
B49: 606000 Meals | D49: 122.32 | E49: 90.59 | F49: 78.12 | G49: 92.19 | H49: 0 | I49: 117.98 | J49: 117.98 | K49: 117.98 | L49: 117.98 | M49: 117.98 | N49: 117.98 | O49: 117.98 | P49: 117.98 | Q49: 117.98 | R49: 117.98 | S49: 117.98 | T49: 117.98 | U49: 117.98 | V49: 117.98 | W49: 117.98 | X49: 117.98 | Y49: 117.98 | Z49: 117.98 | AA49: 117.98 | AB49: 117.98 | AC49: 117.98 | AD49: 117.98 | AE49: 117.98 | AF49: 117.98 | AG49: 117.98 | AH49: 117.98 | AI49: 117.98 | AJ49: 117.98 | AK49: 117.98 | AL49: 117.98 | AM49: 117.98
B50: Total Travel & Meals | D50: =D48+D49 | E50: =E48+E49 | F50: =F48+F49 | G50: =G48+G49 | H50: =H48+H49 | I50: =I48+I49 | J50: =J48+J49 | K50: =K48+K49 | ... AM50: =AM48+AM49
B51: 616001 Electricity | D51: 0 | E51: 0 | F51: 0 | G51: 0 | H51: 0 | I51: 0 | J51: 0 | K51: 0 | L51: 0 | M51: 0 | N51: 0 | O51: 0 | P51: 0 | Q51: 0 | R51: 0 | S51: 0 | T51: 0 | U51: 0 | V51: 0 | W51: 0 | X51: 0 | Y51: 0 | Z51: 0 | AA51: 0 | AB51: 0 | AC51: 0 | AD51: 0 | AE51: 0 | AF51: 0 | AG51: 0 | AH51: 0 | AI51: 0 | AJ51: 0 | AK51: 0 | AL51: 0 | AM51: 0
B52: 616002 Internet & TV | D52: 212.35 | E52: 212.35 | F52: 212.35 | G52: 212.35 | H52: 0 | I52: 70.32 | J52: 70.32 | K52: 70.32 | L52: 70.32 | M52: 70.32 | N52: 70.32 | O52: 70.32 | P52: 70.32 | Q52: 70.32 | R52: 70.32 | S52: 70.32 | T52: 70.32 | U52: 70.32 | V52: 70.32 | W52: 70.32 | X52: 70.32 | Y52: 70.32 | Z52: 70.32 | AA52: 70.32 | AB52: 70.32 | AC52: 70.32 | AD52: 70.32 | AE52: 70.32 | AF52: 70.32 | AG52: 70.32 | AH52: 70.32 | AI52: 70.32 | AJ52: 70.32 | AK52: 70.32 | AL52: 70.32 | AM52: 70.32
B53: 616003 Phone service | D53: 116.81 | E53: 2776.16 | F53: 116.75 | G53: 116.75 | H53: 116.73 | I53: 258.84 | J53: 258.84 | K53: 258.84 | L53: 258.84 | M53: 258.84 | N53: 258.84 | O53: 258.84 | P53: 258.84 | Q53: 258.84 | R53: 258.84 | S53: 258.84 | T53: 258.84 | U53: 258.84 | V53: 258.84 | W53: 258.84 | X53: 258.84 | Y53: 258.84 | Z53: 258.84 | AA53: 258.84 | AB53: 258.84 | AC53: 258.84 | AD53: 258.84 | AE53: 258.84 | AF53: 258.84 | AG53: 258.84 | AH53: 258.84 | AI53: 258.84 | AJ53: 258.84 | AK53: 258.84 | AL53: 258.84 | AM53: 258.84
B54: 616004 Water & sewer | D54: 0 | E54: 0 | F54: 0 | G54: 0 | H54: 0 | I54: 0 | J54: 0 | K54: 0 | L54: 0 | M54: 0 | N54: 0 | O54: 0 | P54: 0 | Q54: 0 | R54: 0 | S54: 0 | T54: 0 | U54: 0 | V54: 0 | W54: 0 | X54: 0 | Y54: 0 | Z54: 0 | AA54: 0 | AB54: 0 | AC54: 0 | AD54: 0 | AE54: 0 | AF54: 0 | AG54: 0 | AH54: 0 | AI54: 0 | AJ54: 0 | AK54: 0 | AL54: 0 | AM54: 0
B55: 616005 Disposal Services | D55: 0 | E55: 0 | F55: 0 | G55: 0 | H55: 0 | I55: 0 | J55: 0 | K55: 0 | L55: 0 | M55: 0 | N55: 0 | O55: 0 | P55: 0 | Q55: 0 | R55: 0 | S55: 0 | T55: 0 | U55: 0 | V55: 0 | W55: 0 | X55: 0 | Y55: 0 | Z55: 0 | AA55: 0 | AB55: 0 | AC55: 0 | AD55: 0 | AE55: 0 | AF55: 0 | AG55: 0 | AH55: 0 | AI55: 0 | AJ55: 0 | AK55: 0 | AL55: 0 | AM55: 0
B56: Total Utilities | D56: 329.16 | E56: 2988.51 | F56: 329.1 | G56: 329.1 | H56: 329.08 | I56: =I51+I52+I53+I54+I55 | J56: =J51+J52+J53+J54+J55 | K56: =K51+K52+K53+K54+K55 | L56: =L51+L52+L53+L54+L55 | M56: =M51+M52+M53+M54+M55 | N56: =N51+N52+N53+N54+N55 | O56: =O51+O52+O53+O54+O55 | P56: =P51+P52+P53+P54+P55 | ... AM56: =AM51+AM52+AM53+AM54+AM55
B57: 701000 Rent | D57: 6916.2 | E57: 6916.2 | F57: 6916.2 | G57: 6916.2 | H57: 6916.2 | I57: 7077.57 | J57: 7077.57 | K57: 7077.57 | L57: 7077.57 | M57: 7077.57 | N57: 7077.57 | O57: 7077.57 | P57: 7077.57 | Q57: 7077.57 | R57: 7077.57 | S57: 7077.57 | T57: 7077.57 | U57: 7077.57 | V57: 7077.57 | W57: 7077.57 | X57: 7077.57 | Y57: 7077.57 | Z57: 7077.57 | AA57: 7077.57 | AB57: 7077.57 | AC57: 7077.57 | AD57: 7077.57 | AE57: 7077.57 | AF57: 7077.57 | AG57: 7077.57 | AH57: 7077.57 | AI57: 7077.57 | AJ57: 7077.57 | AK57: 7077.57 | AL57: 7077.57 | AM57: 7077.57
B58: 702000 Security | D58: 34.99 | E58: 34.99 | F58: 34.99 | G58: 34.99 | H58: 34.99 | I58: 35.81 | J58: 35.81 | K58: 35.81 | L58: 35.81 | M58: 35.81 | N58: 35.81 | O58: 35.81 | P58: 35.81 | Q58: 35.81 | R58: 35.81 | S58: 35.81 | T58: 35.81 | U58: 35.81 | V58: 35.81 | W58: 35.81 | X58: 35.81 | Y58: 35.81 | Z58: 35.81 | AA58: 35.81 | AB58: 35.81 | AC58: 35.81 | AD58: 35.81 | AE58: 35.81 | AF58: 35.81 | AG58: 35.81 | AH58: 35.81 | AI58: 35.81 | AJ58: 35.81 | AK58: 35.81 | AL58: 35.81 | AM58: 35.81
B59: 703000 Cleaning | D59: 732.99 | E59: 198.34 | F59: 743.55 | G59: 346.55 | H59: 246.89 | I59: 517.15 | J59: 517.15 | K59: 517.15 | L59: 517.15 | M59: 517.15 | N59: 517.15 | O59: 517.15 | P59: 517.15 | Q59: 517.15 | R59: 517.15 | S59: 517.15 | T59: 517.15 | U59: 517.15 | V59: 517.15 | W59: 517.15 | X59: 517.15 | Y59: 517.15 | Z59: 517.15 | AA59: 517.15 | AB59: 517.15 | AC59: 517.15 | AD59: 517.15 | AE59: 517.15 | AF59: 517.15 | AG59: 517.15 | AH59: 517.15 | AI59: 517.15 | AJ59: 517.15 | AK59: 517.15 | AL59: 517.15 | AM59: 517.15
B60: 705000 Property Maintenance | D60: 800 | E60: 800 | F60: 800 | G60: 800 | H60: 800 | I60: 818.67 | J60: 818.67 | K60: 818.67 | L60: 818.67 | M60: 818.67 | N60: 818.67 | O60: 818.67 | P60: 818.67 | Q60: 818.67 | R60: 818.67 | S60: 818.67 | T60: 818.67 | U60: 818.67 | V60: 818.67 | W60: 818.67 | X60: 818.67 | Y60: 818.67 | Z60: 818.67 | AA60: 818.67 | AB60: 818.67 | AC60: 818.67 | AD60: 818.67 | AE60: 818.67 | AF60: 818.67 | AG60: 818.67 | AH60: 818.67 | AI60: 818.67 | AJ60: 818.67 | AK60: 818.67 | AL60: 818.67 | AM60: 818.67
B61: Total Property Costs | D61: 8484.18 | E61: 7949.53 | F61: 8494.74 | G61: 8097.74 | H61: 7998.08 | I61: =I57+I58+I59+I60 | J61: =J57+J58+J59+J60 | K61: =K57+K58+K59+K60 | L61: =L57+L58+L59+L60 | M61: =M57+M58+M59+M60 | N61: =N57+N58+N59+N60 | O61: =O57+O58+O59+O60 | P61: =P57+P58+P59+P60 | ... AM61: =AM57+AM58+AM59+AM60
B62: TOTAL OPERATING EXPENSES | D62: 76953.47 | E62: 66382.16 | F62: 71025.59 | G62: 67335.39 | H62: 64099.98 | I62: =I33+I38+I42+I47+I50+I56+I61 | J62: =J33+J38+J42+J47+J50+J56+J61 | K62: =K33+K38+K42+K47+K50+K56+K61 | L62: =L33+L38+L42+L47+L50+L56+L61 | M62: =M33+M38+M42+M47+M50+M56+M61 | N62: =N33+N38+N42+N47+N50+N56+N61 | O62: =O33+O38+O42+O47+O50+O56+O61 | P62: =P33+P38+P42+P47+P50+P56+P61 | ... AM62: =AM33+AM38+AM42+AM47+AM50+AM56+AM61
B63: NET OPERATING INCOME (EBITDA) | D63: 52024.14 | E63: 51059.28 | F63: 44089.15 | G63: 43565.57 | H63: 39957.1 | I63: =I26-I62 | J63: =J26-J62 | K63: =K26-K62 | L63: =L26-L62 | M63: =M26-M62 | N63: =N26-N62 | O63: =O26-O62 | P63: =P26-P62 | ... AM63: =AM26-AM62
B64: OTHER
B65: 810000 Depreciation | D65: 1833.55 | E65: 1833.55 | F65: 1833.55 | G65: 1833.55 | H65: 1833.55 | I65: =I69*0.929227 | J65: =J69*0.929227 | K65: =K69*0.929227 | L65: =L69*0.929227 | M65: =M69*0.929227 | N65: =N69*0.929227 | O65: =O69*0.929227 | P65: =P69*0.929227 | ... AM65: =AM69*0.929227
B66: 901000 Interest Expense | D66: 0 | E66: 0 | F66: 0 | G66: 0 | H66: 0 | I66: 0 | J66: 0 | K66: 0 | L66: 0 | M66: 0 | N66: 0 | O66: 0 | P66: 0 | Q66: 0 | R66: 0 | S66: 0 | T66: 0 | U66: 0 | V66: 0 | W66: 0 | X66: 0 | Y66: 0 | Z66: 0 | AA66: 0 | AB66: 0 | AC66: 0 | AD66: 0 | AE66: 0 | AF66: 0 | AG66: 0 | AH66: 0 | AI66: 0 | AJ66: 0 | AK66: 0 | AL66: 0 | AM66: 0
B67: 902000 Taxes Paid | D67: 0 | E67: 558.6 | F67: 0 | G67: 0 | H67: 0 | I67: =I69*0.070773 | J67: =J69*0.070773 | K67: =K69*0.070773 | L67: =L69*0.070773 | M67: =M69*0.070773 | N67: =N69*0.070773 | O67: =O69*0.070773 | P67: =P69*0.070773 | ... AM67: =AM69*0.070773
B68: 903000 Property taxes | D68: 0 | E68: 0 | F68: 0 | G68: 0 | H68: 0 | I68: 0 | J68: 0 | K68: 0 | L68: 0 | M68: 0 | N68: 0 | O68: 0 | P68: 0 | Q68: 0 | R68: 0 | S68: 0 | T68: 0 | U68: 0 | V68: 0 | W68: 0 | X68: 0 | Y68: 0 | Z68: 0 | AA68: 0 | AB68: 0 | AC68: 0 | AD68: 0 | AE68: 0 | AF68: 0 | AG68: 0 | AH68: 0 | AI68: 0 | AJ68: 0 | AK68: 0 | AL68: 0 | AM68: 0
B69: Total Other Expenses | D69: 1833.55 | E69: 2392.15 | F69: 1833.55 | G69: 1833.55 | H69: 1833.55 | I69: 0 | J69: 0 | K69: 0 | L69: 0 | M69: 0 | N69: 0 | O69: 0 | P69: 0 | Q69: 0 | R69: 0 | S69: 0 | T69: 0 | U69: 0 | V69: 0 | W69: 0 | X69: 0 | Y69: 0 | Z69: 0 | AA69: 0 | AB69: 0 | AC69: 0 | AD69: 0 | AE69: 0 | AF69: 0 | AG69: 0 | AH69: 0 | AI69: 0 | AJ69: 0 | AK69: 0 | AL69: 0 | AM69: 0
B70: NET INCOME | D70: 50190.59 | E70: 48667.13 | F70: 42255.6 | G70: 41732.02 | H70: 38123.55 | I70: =I63-I69 | J70: =J63-J69 | K70: =K63-K69 | L70: =L63-L69 | M70: =M63-M69 | N70: =N63-N69 | O70: =O63-O69 | P70: =P63-P69 | ... AM70: =AM63-AM69

Sheet CC P&L
B2: Culver City (CC) — Profit & Loss
B4: Monthly P&L (Detail)
B5: Line Item | D5: Jan 2026 | E5: Feb 2026 | F5: Mar 2026 | G5: Apr 2026 | H5: May 2026 | I5: Jun 2026 | J5: Jul 2026 | K5: Aug 2026 | L5: Sep 2026 | M5: Oct 2026 | N5: Nov 2026 | O5: Dec 2026 | P5: Jan 2027 | Q5: Feb 2027 | R5: Mar 2027 | S5: Apr 2027 | T5: May 2027 | U5: Jun 2027 | V5: Jul 2027 | W5: Aug 2027 | X5: Sep 2027 | Y5: Oct 2027 | Z5: Nov 2027 | AA5: Dec 2027 | AB5: Jan 2028 | AC5: Feb 2028 | AD5: Mar 2028 | AE5: Apr 2028 | AF5: May 2028 | AG5: Jun 2028 | AH5: Jul 2028 | AI5: Aug 2028 | AJ5: Sep 2028 | AK5: Oct 2028 | AL5: Nov 2028 | AM5: Dec 2028
B6: INCOME
B7: 401001 Machine | D7: 20397.9 | E7: 19548.71 | F7: 20502.29 | G7: 17774.52 | H7: 16596.07 | I7: =I13*0.510234 | J7: =J13*0.510234 | K7: =K13*0.510234 | L7: =L13*0.510234 | M7: =M13*0.510234 | N7: =N13*0.510234 | O7: =O13*0.510234 | P7: =P13*0.510234 | ... AM7: =AM13*0.510234
B8: 401002 Private Pilates | D8: 1170 | E8: 1512 | F8: 1002 | G8: 333 | H8: 628 | I8: =I13*0.026202 | J8: =J13*0.026202 | K8: =K13*0.026202 | L8: =L13*0.026202 | M8: =M13*0.026202 | N8: =N13*0.026202 | O8: =O13*0.026202 | P8: =P13*0.026202 | ... AM8: =AM13*0.026202
B9: 401003 Class Pass | D9: 16587.97 | E9: 15654.65 | F9: 18636.28 | G9: 15895 | H9: 15302.32 | I9: =I13*0.435551 | J9: =J13*0.435551 | K9: =K13*0.435551 | L9: =L13*0.435551 | M9: =M13*0.435551 | N9: =N13*0.435551 | O9: =O13*0.435551 | P9: =P13*0.435551 | ... AM9: =AM13*0.435551
B10: 401004 Mighty Teacher Training | D10: 0 | E10: 1845.46 | F10: 961.04 | G10: 0 | H10: 0 | I10: =I13*0.018306 | J10: =J13*0.018306 | K10: =K13*0.018306 | L10: =L13*0.018306 | M10: =M13*0.018306 | N10: =N13*0.018306 | O10: =O13*0.018306 | P10: =P13*0.018306 | ... AM10: =AM13*0.018306
B11: 401005 Livestream Classes | D11: 0 | E11: 0 | F11: 0 | G11: 37.6 | H11: 65.22 | I11: =I13*0.000245 | J11: =J13*0.000245 | K11: =K13*0.000245 | L11: =L13*0.000245 | M11: =M13*0.000245 | N11: =N13*0.000245 | O11: =O13*0.000245 | P11: =P13*0.000245 | ... AM11: =AM13*0.000245
B12: 401006 Wellhub | D12: 336.6 | E12: 367.2 | F12: 501.84 | G12: 244.8 | H12: 82.62 | I12: =I13*0.009461 | J12: =J13*0.009461 | K12: =K13*0.009461 | L12: =L13*0.009461 | M12: =M13*0.009461 | N12: =N13*0.009461 | O12: =O13*0.009461 | P12: =P13*0.009461 | ... AM12: =AM13*0.009461
B13: Total Sessions | D13: 38492.47 | E13: 38928.02 | F13: 41603.45 | G13: 34284.92 | H13: 32674.23 | I13: ='Sales Forecast'!I7*Assumptions!$C$12+'Sales Forecast'!H7*Assumptions!$D$12+'Sales Forecast'!G7*Assumptions!$E$12+'Sales Forecast'!F7*Assumptions!$F$12+'Sales Forecast'!E7*Assumptions!$G$12+'Sales Forecast'!D7*Assumptions!$H$12+'Sales Forecast'!I103*Assumptions!$I$12 | J13: ='Sales Forecast'!J7*Assumptions!$C$12+'Sales Forecast'!I7*Assumptions!$D$12+'Sales Forecast'!H7*Assumptions!$E$12+'Sales Forecast'!G7*Assumptions!$F$12+'Sales Forecast'!F7*Assumptions!$G$12+'Sales Forecast'!E7*Assumptions!$H$12+'Sales Forecast'!D7*Assumptions!$I$12 | K13: ='Sales Forecast'!K7*Assumptions!$C$12+'Sales Forecast'!J7*Assumptions!$D$12+'Sales Forecast'!I7*Assumptions!$E$12+'Sales Forecast'!H7*Assumptions!$F$12+'Sales Forecast'!G7*Assumptions!$G$12+'Sales Forecast'!F7*Assumptions!$H$12+'Sales Forecast'!E7*Assumptions!$I$12 | L13: ='Sales Forecast'!L7*Assumptions!$C$12+'Sales Forecast'!K7*Assumptions!$D$12+'Sales Forecast'!J7*Assumptions!$E$12+'Sales Forecast'!I7*Assumptions!$F$12+'Sales Forecast'!H7*Assumptions!$G$12+'Sales Forecast'!G7*Assumptions!$H$12+'Sales Forecast'!F7*Assumptions!$I$12 | M13: ='Sales Forecast'!M7*Assumptions!$C$12+'Sales Forecast'!L7*Assumptions!$D$12+'Sales Forecast'!K7*Assumptions!$E$12+'Sales Forecast'!J7*Assumptions!$F$12+'Sales Forecast'!I7*Assumptions!$G$12+'Sales Forecast'!H7*Assumptions!$H$12+'Sales Forecast'!G7*Assumptions!$I$12 | N13: ='Sales Forecast'!N7*Assumptions!$C$12+'Sales Forecast'!M7*Assumptions!$D$12+'Sales Forecast'!L7*Assumptions!$E$12+'Sales Forecast'!K7*Assumptions!$F$12+'Sales Forecast'!J7*Assumptions!$G$12+'Sales Forecast'!I7*Assumptions!$H$12+'Sales Forecast'!H7*Assumptions!$I$12 | O13: ='Sales Forecast'!O7*Assumptions!$C$12+'Sales Forecast'!N7*Assumptions!$D$12+'Sales Forecast'!M7*Assumptions!$E$12+'Sales Forecast'!L7*Assumptions!$F$12+'Sales Forecast'!K7*Assumptions!$G$12+'Sales Forecast'!J7*Assumptions!$H$12+'Sales Forecast'!I7*Assumptions!$I$12 | P13: ='Sales Forecast'!P7*Assumptions!$C$12+'Sales Forecast'!O7*Assumptions!$D$12+'Sales Forecast'!N7*Assumptions!$E$12+'Sales Forecast'!M7*Assumptions!$F$12+'Sales Forecast'!L7*Assumptions!$G$12+'Sales Forecast'!K7*Assumptions!$H$12+'Sales Forecast'!J7*Assumptions!$I$12 | Q13: ='Sales Forecast'!Q7*Assumptions!$C$12+'Sales Forecast'!P7*Assumptions!$D$12+'Sales Forecast'!O7*Assumptions!$E$12+'Sales Forecast'!N7*Assumptions!$F$12+'Sales Forecast'!M7*Assumptions!$G$12+'Sales Forecast'!L7*Assumptions!$H$12+'Sales Forecast'!K7*Assumptions!$I$12 | ... AM13: ='Sales Forecast'!AM7*Assumptions!$C$12+'Sales Forecast'!AL7*Assumptions!$D$12+'Sales Forecast'!AK7*Assumptions!$E$12+'Sales Forecast'!AJ7*Assumptions!$F$12+'Sales Forecast'!AI7*Assumptions!$G$12+'Sales Forecast'!AH7*Assumptions!$H$12+'Sales Forecast'!AG7*Assumptions!$I$12
B14: 403001 Machine Breakage | D14: 2890.72 | E14: 4105.76 | F14: 2843.53 | G14: 4737.65 | H14: 4879.41 | I14: =I17*0.979836 | J14: =J17*0.979836 | K14: =K17*0.979836 | L14: =L17*0.979836 | M14: =M17*0.979836 | N14: =N17*0.979836 | O14: =O17*0.979836 | P14: =P17*0.979836 | ... AM14: =AM17*0.979836
B15: 403003 Private Pilates Breakage | D15: 0 | E15: 225 | F15: 0 | G15: 75 | H15: 230 | I15: =I17*0.020164 | J15: =J17*0.020164 | K15: =K17*0.020164 | L15: =L17*0.020164 | M15: =M17*0.020164 | N15: =N17*0.020164 | O15: =O17*0.020164 | P15: =P17*0.020164 | ... AM15: =AM17*0.020164
B16: 403004 Other Breakage | D16: 0 | E16: 0 | F16: 0 | G16: 0 | H16: 0 | I16: 0 | J16: 0 | K16: 0 | L16: 0 | M16: 0 | N16: 0 | O16: 0 | P16: 0 | Q16: 0 | R16: 0 | S16: 0 | T16: 0 | U16: 0 | V16: 0 | W16: 0 | X16: 0 | Y16: 0 | Z16: 0 | AA16: 0 | AB16: 0 | AC16: 0 | AD16: 0 | AE16: 0 | AF16: 0 | AG16: 0 | AH16: 0 | AI16: 0 | AJ16: 0 | AK16: 0 | AL16: 0 | AM16: 0
B17: Total Breakage Revenue | D17: 2890.72 | E17: 4330.76 | F17: 2843.53 | G17: 4812.65 | H17: 5109.41 | I17: ='Sales Forecast'!I7*Assumptions!$C$13+'Sales Forecast'!H7*Assumptions!$D$13+'Sales Forecast'!G7*Assumptions!$E$13+'Sales Forecast'!F7*Assumptions!$F$13+'Sales Forecast'!E7*Assumptions!$G$13+'Sales Forecast'!D7*Assumptions!$H$13+'Sales Forecast'!I103*Assumptions!$I$13 | J17: ='Sales Forecast'!J7*Assumptions!$C$13+'Sales Forecast'!I7*Assumptions!$D$13+'Sales Forecast'!H7*Assumptions!$E$13+'Sales Forecast'!G7*Assumptions!$F$13+'Sales Forecast'!F7*Assumptions!$G$13+'Sales Forecast'!E7*Assumptions!$H$13+'Sales Forecast'!D7*Assumptions!$I$13 | K17: ='Sales Forecast'!K7*Assumptions!$C$13+'Sales Forecast'!J7*Assumptions!$D$13+'Sales Forecast'!I7*Assumptions!$E$13+'Sales Forecast'!H7*Assumptions!$F$13+'Sales Forecast'!G7*Assumptions!$G$13+'Sales Forecast'!F7*Assumptions!$H$13+'Sales Forecast'!E7*Assumptions!$I$13 | L17: ='Sales Forecast'!L7*Assumptions!$C$13+'Sales Forecast'!K7*Assumptions!$D$13+'Sales Forecast'!J7*Assumptions!$E$13+'Sales Forecast'!I7*Assumptions!$F$13+'Sales Forecast'!H7*Assumptions!$G$13+'Sales Forecast'!G7*Assumptions!$H$13+'Sales Forecast'!F7*Assumptions!$I$13 | M17: ='Sales Forecast'!M7*Assumptions!$C$13+'Sales Forecast'!L7*Assumptions!$D$13+'Sales Forecast'!K7*Assumptions!$E$13+'Sales Forecast'!J7*Assumptions!$F$13+'Sales Forecast'!I7*Assumptions!$G$13+'Sales Forecast'!H7*Assumptions!$H$13+'Sales Forecast'!G7*Assumptions!$I$13 | N17: ='Sales Forecast'!N7*Assumptions!$C$13+'Sales Forecast'!M7*Assumptions!$D$13+'Sales Forecast'!L7*Assumptions!$E$13+'Sales Forecast'!K7*Assumptions!$F$13+'Sales Forecast'!J7*Assumptions!$G$13+'Sales Forecast'!I7*Assumptions!$H$13+'Sales Forecast'!H7*Assumptions!$I$13 | O17: ='Sales Forecast'!O7*Assumptions!$C$13+'Sales Forecast'!N7*Assumptions!$D$13+'Sales Forecast'!M7*Assumptions!$E$13+'Sales Forecast'!L7*Assumptions!$F$13+'Sales Forecast'!K7*Assumptions!$G$13+'Sales Forecast'!J7*Assumptions!$H$13+'Sales Forecast'!I7*Assumptions!$I$13 | P17: ='Sales Forecast'!P7*Assumptions!$C$13+'Sales Forecast'!O7*Assumptions!$D$13+'Sales Forecast'!N7*Assumptions!$E$13+'Sales Forecast'!M7*Assumptions!$F$13+'Sales Forecast'!L7*Assumptions!$G$13+'Sales Forecast'!K7*Assumptions!$H$13+'Sales Forecast'!J7*Assumptions!$I$13 | Q17: ='Sales Forecast'!Q7*Assumptions!$C$13+'Sales Forecast'!P7*Assumptions!$D$13+'Sales Forecast'!O7*Assumptions!$E$13+'Sales Forecast'!N7*Assumptions!$F$13+'Sales Forecast'!M7*Assumptions!$G$13+'Sales Forecast'!L7*Assumptions!$H$13+'Sales Forecast'!K7*Assumptions!$I$13 | ... AM17: ='Sales Forecast'!AM7*Assumptions!$C$13+'Sales Forecast'!AL7*Assumptions!$D$13+'Sales Forecast'!AK7*Assumptions!$E$13+'Sales Forecast'!AJ7*Assumptions!$F$13+'Sales Forecast'!AI7*Assumptions!$G$13+'Sales Forecast'!AH7*Assumptions!$H$13+'Sales Forecast'!AG7*Assumptions!$I$13
B18: 404000 Retail Sales | D18: 1794 | E18: 1344 | F18: 1586 | G18: 946 | H18: 928 | I18: =1417.5 | J18: =1417.5 | K18: =1417.5 | L18: =1417.5 | M18: =1417.5 | N18: =1417.5 | O18: =1417.5 | P18: =1417.5 | ... AM18: =1417.5
B19: 406000 Refunds | D19: 1048 | E19: 740 | F19: 500 | G19: 245 | H19: 443 | I19: =('Sales Forecast'!I7*Assumptions!$C$12+'Sales Forecast'!H7*Assumptions!$D$12+'Sales Forecast'!G7*Assumptions!$E$12+'Sales Forecast'!F7*Assumptions!$F$12+'Sales Forecast'!E7*Assumptions!$G$12+'Sales Forecast'!D7*Assumptions!$H$12+'Sales Forecast'!I7*Assumptions!$C$13+'Sales Forecast'!H7*Assumptions!$D$13+'Sales Forecast'!G7*Assumptions!$E$13+'Sales Forecast'!F7*Assumptions!$F$13+'Sales Forecast'!E7*Assumptions!$G$13+'Sales Forecast'!D7*Assumptions!$H$13+1417.5)*Assumptions!$C$17 | J19: =('Sales Forecast'!J7*Assumptions!$C$12+'Sales Forecast'!I7*Assumptions!$D$12+'Sales Forecast'!H7*Assumptions!$E$12+'Sales Forecast'!G7*Assumptions!$F$12+'Sales Forecast'!F7*Assumptions!$G$12+'Sales Forecast'!E7*Assumptions!$H$12+'Sales Forecast'!D7*Assumptions!$I$12+'Sales Forecast'!J7*Assumptions!$C$13+'Sales Forecast'!I7*Assumptions!$D$13+'Sales Forecast'!H7*Assumptions!$E$13+'Sales Forecast'!G7*Assumptions!$F$13+'Sales Forecast'!F7*Assumptions!$G$13+'Sales Forecast'!E7*Assumptions!$H$13+'Sales Forecast'!D7*Assumptions!$I$13+1417.5)*Assumptions!$C$17 | K19: =('Sales Forecast'!K7*Assumptions!$C$12+'Sales Forecast'!J7*Assumptions!$D$12+'Sales Forecast'!I7*Assumptions!$E$12+'Sales Forecast'!H7*Assumptions!$F$12+'Sales Forecast'!G7*Assumptions!$G$12+'Sales Forecast'!F7*Assumptions!$H$12+'Sales Forecast'!E7*Assumptions!$I$12+'Sales Forecast'!K7*Assumptions!$C$13+'Sales Forecast'!J7*Assumptions!$D$13+'Sales Forecast'!I7*Assumptions!$E$13+'Sales Forecast'!H7*Assumptions!$F$13+'Sales Forecast'!G7*Assumptions!$G$13+'Sales Forecast'!F7*Assumptions!$H$13+'Sales Forecast'!E7*Assumptions!$I$13+1417.5)*Assumptions!$C$17 | L19: =('Sales Forecast'!L7*Assumptions!$C$12+'Sales Forecast'!K7*Assumptions!$D$12+'Sales Forecast'!J7*Assumptions!$E$12+'Sales Forecast'!I7*Assumptions!$F$12+'Sales Forecast'!H7*Assumptions!$G$12+'Sales Forecast'!G7*Assumptions!$H$12+'Sales Forecast'!F7*Assumptions!$I$12+'Sales Forecast'!L7*Assumptions!$C$13+'Sales Forecast'!K7*Assumptions!$D$13+'Sales Forecast'!J7*Assumptions!$E$13+'Sales Forecast'!I7*Assumptions!$F$13+'Sales Forecast'!H7*Assumptions!$G$13+'Sales Forecast'!G7*Assumptions!$H$13+'Sales Forecast'!F7*Assumptions!$I$13+1417.5)*Assumptions!$C$17 | M19: =('Sales Forecast'!M7*Assumptions!$C$12+'Sales Forecast'!L7*Assumptions!$D$12+'Sales Forecast'!K7*Assumptions!$E$12+'Sales Forecast'!J7*Assumptions!$F$12+'Sales Forecast'!I7*Assumptions!$G$12+'Sales Forecast'!H7*Assumptions!$H$12+'Sales Forecast'!G7*Assumptions!$I$12+'Sales Forecast'!M7*Assumptions!$C$13+'Sales Forecast'!L7*Assumptions!$D$13+'Sales Forecast'!K7*Assumptions!$E$13+'Sales Forecast'!J7*Assumptions!$F$13+'Sales Forecast'!I7*Assumptions!$G$13+'Sales Forecast'!H7*Assumptions!$H$13+'Sales Forecast'!G7*Assumptions!$I$13+1417.5)*Assumptions!$C$17 | N19: =('Sales Forecast'!N7*Assumptions!$C$12+'Sales Forecast'!M7*Assumptions!$D$12+'Sales Forecast'!L7*Assumptions!$E$12+'Sales Forecast'!K7*Assumptions!$F$12+'Sales Forecast'!J7*Assumptions!$G$12+'Sales Forecast'!I7*Assumptions!$H$12+'Sales Forecast'!H7*Assumptions!$I$12+'Sales Forecast'!N7*Assumptions!$C$13+'Sales Forecast'!M7*Assumptions!$D$13+'Sales Forecast'!L7*Assumptions!$E$13+'Sales Forecast'!K7*Assumptions!$F$13+'Sales Forecast'!J7*Assumptions!$G$13+'Sales Forecast'!I7*Assumptions!$H$13+'Sales Forecast'!H7*Assumptions!$I$13+1417.5)*Assumptions!$C$17 | O19: =('Sales Forecast'!O7*Assumptions!$C$12+'Sales Forecast'!N7*Assumptions!$D$12+'Sales Forecast'!M7*Assumptions!$E$12+'Sales Forecast'!L7*Assumptions!$F$12+'Sales Forecast'!K7*Assumptions!$G$12+'Sales Forecast'!J7*Assumptions!$H$12+'Sales Forecast'!I7*Assumptions!$I$12+'Sales Forecast'!O7*Assumptions!$C$13+'Sales Forecast'!N7*Assumptions!$D$13+'Sales Forecast'!M7*Assumptions!$E$13+'Sales Forecast'!L7*Assumptions!$F$13+'Sales Forecast'!K7*Assumptions!$G$13+'Sales Forecast'!J7*Assumptions!$H$13+'Sales Forecast'!I7*Assumptions!$I$13+1417.5)*Assumptions!$C$17 | P19: =('Sales Forecast'!P7*Assumptions!$C$12+'Sales Forecast'!O7*Assumptions!$D$12+'Sales Forecast'!N7*Assumptions!$E$12+'Sales Forecast'!M7*Assumptions!$F$12+'Sales Forecast'!L7*Assumptions!$G$12+'Sales Forecast'!K7*Assumptions!$H$12+'Sales Forecast'!J7*Assumptions!$I$12+'Sales Forecast'!P7*Assumptions!$C$13+'Sales Forecast'!O7*Assumptions!$D$13+'Sales Forecast'!N7*Assumptions!$E$13+'Sales Forecast'!M7*Assumptions!$F$13+'Sales Forecast'!L7*Assumptions!$G$13+'Sales Forecast'!K7*Assumptions!$H$13+'Sales Forecast'!J7*Assumptions!$I$13+1417.5)*Assumptions!$C$17 | Q19: =('Sales Forecast'!Q7*Assumptions!$C$12+'Sales Forecast'!P7*Assumptions!$D$12+'Sales Forecast'!O7*Assumptions!$E$12+'Sales Forecast'!N7*Assumptions!$F$12+'Sales Forecast'!M7*Assumptions!$G$12+'Sales Forecast'!L7*Assumptions!$H$12+'Sales Forecast'!K7*Assumptions!$I$12+'Sales Forecast'!Q7*Assumptions!$C$13+'Sales Forecast'!P7*Assumptions!$D$13+'Sales Forecast'!O7*Assumptions!$E$13+'Sales Forecast'!N7*Assumptions!$F$13+'Sales Forecast'!M7*Assumptions!$G$13+'Sales Forecast'!L7*Assumptions!$H$13+'Sales Forecast'!K7*Assumptions!$I$13+1417.5)*Assumptions!$C$17 | ... AM19: =('Sales Forecast'!AM7*Assumptions!$C$12+'Sales Forecast'!AL7*Assumptions!$D$12+'Sales Forecast'!AK7*Assumptions!$E$12+'Sales Forecast'!AJ7*Assumptions!$F$12+'Sales Forecast'!AI7*Assumptions!$G$12+'Sales Forecast'!AH7*Assumptions!$H$12+'Sales Forecast'!AG7*Assumptions!$I$12+'Sales Forecast'!AM7*Assumptions!$C$13+'Sales Forecast'!AL7*Assumptions!$D$13+'Sales Forecast'!AK7*Assumptions!$E$13+'Sales Forecast'!AJ7*Assumptions!$F$13+'Sales Forecast'!AI7*Assumptions!$G$13+'Sales Forecast'!AH7*Assumptions!$H$13+'Sales Forecast'!AG7*Assumptions!$I$13+1417.5)*Assumptions!$C$17
B20: 407000 Discounts | D20: 5079.6 | E20: 2303.3 | F20: 2607.5 | G20: 2783.2 | H20: 1884.8 | I20: =('Sales Forecast'!I7*Assumptions!$C$12+'Sales Forecast'!H7*Assumptions!$D$12+'Sales Forecast'!G7*Assumptions!$E$12+'Sales Forecast'!F7*Assumptions!$F$12+'Sales Forecast'!E7*Assumptions!$G$12+'Sales Forecast'!D7*Assumptions!$H$12+'Sales Forecast'!I7*Assumptions!$C$13+'Sales Forecast'!H7*Assumptions!$D$13+'Sales Forecast'!G7*Assumptions!$E$13+'Sales Forecast'!F7*Assumptions!$F$13+'Sales Forecast'!E7*Assumptions!$G$13+'Sales Forecast'!D7*Assumptions!$H$13+1417.5)*Assumptions!$C$18 | J20: =('Sales Forecast'!J7*Assumptions!$C$12+'Sales Forecast'!I7*Assumptions!$D$12+'Sales Forecast'!H7*Assumptions!$E$12+'Sales Forecast'!G7*Assumptions!$F$12+'Sales Forecast'!F7*Assumptions!$G$12+'Sales Forecast'!E7*Assumptions!$H$12+'Sales Forecast'!D7*Assumptions!$I$12+'Sales Forecast'!J7*Assumptions!$C$13+'Sales Forecast'!I7*Assumptions!$D$13+'Sales Forecast'!H7*Assumptions!$E$13+'Sales Forecast'!G7*Assumptions!$F$13+'Sales Forecast'!F7*Assumptions!$G$13+'Sales Forecast'!E7*Assumptions!$H$13+'Sales Forecast'!D7*Assumptions!$I$13+1417.5)*Assumptions!$C$18 | K20: =('Sales Forecast'!K7*Assumptions!$C$12+'Sales Forecast'!J7*Assumptions!$D$12+'Sales Forecast'!I7*Assumptions!$E$12+'Sales Forecast'!H7*Assumptions!$F$12+'Sales Forecast'!G7*Assumptions!$G$12+'Sales Forecast'!F7*Assumptions!$H$12+'Sales Forecast'!E7*Assumptions!$I$12+'Sales Forecast'!K7*Assumptions!$C$13+'Sales Forecast'!J7*Assumptions!$D$13+'Sales Forecast'!I7*Assumptions!$E$13+'Sales Forecast'!H7*Assumptions!$F$13+'Sales Forecast'!G7*Assumptions!$G$13+'Sales Forecast'!F7*Assumptions!$H$13+'Sales Forecast'!E7*Assumptions!$I$13+1417.5)*Assumptions!$C$18 | L20: =('Sales Forecast'!L7*Assumptions!$C$12+'Sales Forecast'!K7*Assumptions!$D$12+'Sales Forecast'!J7*Assumptions!$E$12+'Sales Forecast'!I7*Assumptions!$F$12+'Sales Forecast'!H7*Assumptions!$G$12+'Sales Forecast'!G7*Assumptions!$H$12+'Sales Forecast'!F7*Assumptions!$I$12+'Sales Forecast'!L7*Assumptions!$C$13+'Sales Forecast'!K7*Assumptions!$D$13+'Sales Forecast'!J7*Assumptions!$E$13+'Sales Forecast'!I7*Assumptions!$F$13+'Sales Forecast'!H7*Assumptions!$G$13+'Sales Forecast'!G7*Assumptions!$H$13+'Sales Forecast'!F7*Assumptions!$I$13+1417.5)*Assumptions!$C$18 | M20: =('Sales Forecast'!M7*Assumptions!$C$12+'Sales Forecast'!L7*Assumptions!$D$12+'Sales Forecast'!K7*Assumptions!$E$12+'Sales Forecast'!J7*Assumptions!$F$12+'Sales Forecast'!I7*Assumptions!$G$12+'Sales Forecast'!H7*Assumptions!$H$12+'Sales Forecast'!G7*Assumptions!$I$12+'Sales Forecast'!M7*Assumptions!$C$13+'Sales Forecast'!L7*Assumptions!$D$13+'Sales Forecast'!K7*Assumptions!$E$13+'Sales Forecast'!J7*Assumptions!$F$13+'Sales Forecast'!I7*Assumptions!$G$13+'Sales Forecast'!H7*Assumptions!$H$13+'Sales Forecast'!G7*Assumptions!$I$13+1417.5)*Assumptions!$C$18 | N20: =('Sales Forecast'!N7*Assumptions!$C$12+'Sales Forecast'!M7*Assumptions!$D$12+'Sales Forecast'!L7*Assumptions!$E$12+'Sales Forecast'!K7*Assumptions!$F$12+'Sales Forecast'!J7*Assumptions!$G$12+'Sales Forecast'!I7*Assumptions!$H$12+'Sales Forecast'!H7*Assumptions!$I$12+'Sales Forecast'!N7*Assumptions!$C$13+'Sales Forecast'!M7*Assumptions!$D$13+'Sales Forecast'!L7*Assumptions!$E$13+'Sales Forecast'!K7*Assumptions!$F$13+'Sales Forecast'!J7*Assumptions!$G$13+'Sales Forecast'!I7*Assumptions!$H$13+'Sales Forecast'!H7*Assumptions!$I$13+1417.5)*Assumptions!$C$18 | O20: =('Sales Forecast'!O7*Assumptions!$C$12+'Sales Forecast'!N7*Assumptions!$D$12+'Sales Forecast'!M7*Assumptions!$E$12+'Sales Forecast'!L7*Assumptions!$F$12+'Sales Forecast'!K7*Assumptions!$G$12+'Sales Forecast'!J7*Assumptions!$H$12+'Sales Forecast'!I7*Assumptions!$I$12+'Sales Forecast'!O7*Assumptions!$C$13+'Sales Forecast'!N7*Assumptions!$D$13+'Sales Forecast'!M7*Assumptions!$E$13+'Sales Forecast'!L7*Assumptions!$F$13+'Sales Forecast'!K7*Assumptions!$G$13+'Sales Forecast'!J7*Assumptions!$H$13+'Sales Forecast'!I7*Assumptions!$I$13+1417.5)*Assumptions!$C$18 | P20: =('Sales Forecast'!P7*Assumptions!$C$12+'Sales Forecast'!O7*Assumptions!$D$12+'Sales Forecast'!N7*Assumptions!$E$12+'Sales Forecast'!M7*Assumptions!$F$12+'Sales Forecast'!L7*Assumptions!$G$12+'Sales Forecast'!K7*Assumptions!$H$12+'Sales Forecast'!J7*Assumptions!$I$12+'Sales Forecast'!P7*Assumptions!$C$13+'Sales Forecast'!O7*Assumptions!$D$13+'Sales Forecast'!N7*Assumptions!$E$13+'Sales Forecast'!M7*Assumptions!$F$13+'Sales Forecast'!L7*Assumptions!$G$13+'Sales Forecast'!K7*Assumptions!$H$13+'Sales Forecast'!J7*Assumptions!$I$13+1417.5)*Assumptions!$C$18 | Q20: =('Sales Forecast'!Q7*Assumptions!$C$12+'Sales Forecast'!P7*Assumptions!$D$12+'Sales Forecast'!O7*Assumptions!$E$12+'Sales Forecast'!N7*Assumptions!$F$12+'Sales Forecast'!M7*Assumptions!$G$12+'Sales Forecast'!L7*Assumptions!$H$12+'Sales Forecast'!K7*Assumptions!$I$12+'Sales Forecast'!Q7*Assumptions!$C$13+'Sales Forecast'!P7*Assumptions!$D$13+'Sales Forecast'!O7*Assumptions!$E$13+'Sales Forecast'!N7*Assumptions!$F$13+'Sales Forecast'!M7*Assumptions!$G$13+'Sales Forecast'!L7*Assumptions!$H$13+'Sales Forecast'!K7*Assumptions!$I$13+1417.5)*Assumptions!$C$18 | ... AM20: =('Sales Forecast'!AM7*Assumptions!$C$12+'Sales Forecast'!AL7*Assumptions!$D$12+'Sales Forecast'!AK7*Assumptions!$E$12+'Sales Forecast'!AJ7*Assumptions!$F$12+'Sales Forecast'!AI7*Assumptions!$G$12+'Sales Forecast'!AH7*Assumptions!$H$12+'Sales Forecast'!AG7*Assumptions!$I$12+'Sales Forecast'!AM7*Assumptions!$C$13+'Sales Forecast'!AL7*Assumptions!$D$13+'Sales Forecast'!AK7*Assumptions!$E$13+'Sales Forecast'!AJ7*Assumptions!$F$13+'Sales Forecast'!AI7*Assumptions!$G$13+'Sales Forecast'!AH7*Assumptions!$H$13+'Sales Forecast'!AG7*Assumptions!$I$13+1417.5)*Assumptions!$C$18
B21: TOTAL REVENUE | D21: 37049.59 | E21: 41559.48 | F21: 42925.48 | G21: 37015.37 | H21: 36383.84 | I21: =I13+I17+I18+I19+I20 | J21: =J13+J17+J18+J19+J20 | K21: =K13+K17+K18+K19+K20 | L21: =L13+L17+L18+L19+L20 | M21: =M13+M17+M18+M19+M20 | N21: =N13+N17+N18+N19+N20 | O21: =O13+O17+O18+O19+O20 | P21: =P13+P17+P18+P19+P20 | ... AM21: =AM13+AM17+AM18+AM19+AM20
B22: COST OF GOODS SOLD
B23: 501000 Product Cost | D23: 817.2 | E23: 667.6 | F23: 782.7 | G23: 474.5 | H23: 464 | I23: =I21*Assumptions!$C$20 | J23: =J21*Assumptions!$C$20 | K23: =K21*Assumptions!$C$20 | L23: =L21*Assumptions!$C$20 | M23: =M21*Assumptions!$C$20 | N23: =N21*Assumptions!$C$20 | O23: =O21*Assumptions!$C$20 | P23: =P21*Assumptions!$C$20 | ... AM23: =AM21*Assumptions!$C$20
B24: 506000 Merchant Account Fees | D24: 997.56 | E24: 898.16 | F24: 1146.66 | G24: 855.58 | H24: 876.72 | I24: =I21*Assumptions!$C$19 | J24: =J21*Assumptions!$C$19 | K24: =K21*Assumptions!$C$19 | L24: =L21*Assumptions!$C$19 | M24: =M21*Assumptions!$C$19 | N24: =N21*Assumptions!$C$19 | O24: =O21*Assumptions!$C$19 | P24: =P21*Assumptions!$C$19 | ... AM24: =AM21*Assumptions!$C$19
B25: Total Cost of Goods Sold | D25: 1814.76 | E25: 1565.76 | F25: 1929.36 | G25: 1330.08 | H25: 1340.72 | I25: =I23+I24 | J25: =J23+J24 | K25: =K23+K24 | L25: =L23+L24 | M25: =M23+M24 | N25: =N23+N24 | O25: =O23+O24 | P25: =P23+P24 | ... AM25: =AM23+AM24
B26: GROSS PROFIT | D26: 35234.83 | E26: 39993.72 | F26: 40996.12 | G26: 35685.29 | H26: 35043.12 | I26: =I21-I25 | J26: =J21-J25 | K26: =K21-K25 | L26: =L21-L25 | M26: =M21-M25 | N26: =N21-N25 | O26: =O21-O25 | P26: =P21-P25 | ... AM26: =AM21-AM25
B27: OPERATING EXPENSES
B28: 601001 Paid Ads | D28: 1338.08 | E28: 1423.13 | F28: 557.1 | G28: 0 | H28: 0 | I28: 747.17 | J28: 747.17 | K28: 747.17 | L28: 747.17 | M28: 747.17 | N28: 747.17 | O28: 747.17 | P28: 747.17 | Q28: 747.17 | R28: 747.17 | S28: 747.17 | T28: 747.17 | U28: 747.17 | V28: 747.17 | W28: 747.17 | X28: 747.17 | Y28: 747.17 | Z28: 747.17 | AA28: 747.17 | AB28: 747.17 | AC28: 747.17 | AD28: 747.17 | AE28: 747.17 | AF28: 747.17 | AG28: 747.17 | AH28: 747.17 | AI28: 747.17 | AJ28: 747.17 | AK28: 747.17 | AL28: 747.17 | AM28: 747.17
B29: 601005 Content Creation | D29: 0 | E29: 0 | F29: 0 | G29: 0 | H29: 0 | I29: 0 | J29: 0 | K29: 0 | L29: 0 | M29: 0 | N29: 0 | O29: 0 | P29: 0 | Q29: 0 | R29: 0 | S29: 0 | T29: 0 | U29: 0 | V29: 0 | W29: 0 | X29: 0 | Y29: 0 | Z29: 0 | AA29: 0 | AB29: 0 | AC29: 0 | AD29: 0 | AE29: 0 | AF29: 0 | AG29: 0 | AH29: 0 | AI29: 0 | AJ29: 0 | AK29: 0 | AL29: 0 | AM29: 0
B30: 601006 General Marketing | D30: 0 | E30: 0 | F30: 0 | G30: 0 | H30: 0 | I30: 0 | J30: 0 | K30: 0 | L30: 0 | M30: 0 | N30: 0 | O30: 0 | P30: 0 | Q30: 0 | R30: 0 | S30: 0 | T30: 0 | U30: 0 | V30: 0 | W30: 0 | X30: 0 | Y30: 0 | Z30: 0 | AA30: 0 | AB30: 0 | AC30: 0 | AD30: 0 | AE30: 0 | AF30: 0 | AG30: 0 | AH30: 0 | AI30: 0 | AJ30: 0 | AK30: 0 | AL30: 0 | AM30: 0
B31: 601007 Contractors/Agencies | D31: 0 | E31: 0 | F31: 0 | G31: 0 | H31: 0 | I31: 0 | J31: 0 | K31: 0 | L31: 0 | M31: 0 | N31: 0 | O31: 0 | P31: 0 | Q31: 0 | R31: 0 | S31: 0 | T31: 0 | U31: 0 | V31: 0 | W31: 0 | X31: 0 | Y31: 0 | Z31: 0 | AA31: 0 | AB31: 0 | AC31: 0 | AD31: 0 | AE31: 0 | AF31: 0 | AG31: 0 | AH31: 0 | AI31: 0 | AJ31: 0 | AK31: 0 | AL31: 0 | AM31: 0
B32: 601010 Website Development | D32: 0 | E32: 0 | F32: 0 | G32: 0 | H32: 0 | I32: 0 | J32: 0 | K32: 0 | L32: 0 | M32: 0 | N32: 0 | O32: 0 | P32: 0 | Q32: 0 | R32: 0 | S32: 0 | T32: 0 | U32: 0 | V32: 0 | W32: 0 | X32: 0 | Y32: 0 | Z32: 0 | AA32: 0 | AB32: 0 | AC32: 0 | AD32: 0 | AE32: 0 | AF32: 0 | AG32: 0 | AH32: 0 | AI32: 0 | AJ32: 0 | AK32: 0 | AL32: 0 | AM32: 0
B33: Total Marketing | D33: 1338.08 | E33: 1423.13 | F33: 557.1 | G33: 0 | H33: 0 | I33: =I28+I29+I30+I31+I32 | J33: =J28+J29+J30+J31+J32 | K33: =K28+K29+K30+K31+K32 | L33: =L28+L29+L30+L31+L32 | M33: =M28+M29+M30+M31+M32 | N33: =N28+N29+N30+N31+N32 | O33: =O28+O29+O30+O31+O32 | P33: =P28+P29+P30+P31+P32 | ... AM33: =AM28+AM29+AM30+AM31+AM32
B34: 602001 Wages | D34: 19792.41 | E34: 21148.5 | F34: 23707.86 | G34: 21562.97 | H34: 20706.63 | I34: 20091.59 | J34: 21765.89 | K34: 19254.44 | L34: 20091.59 | M34: 21765.89 | N34: 22603.04 | O34: 21765.89 | P34: 21765.89 | Q34: 24277.34 | R34: 22603.04 | S34: 22022.61 | T34: 21786.79 | U34: 21760.62 | V34: 25464.53 | W34: 30068.98 | X34: 30715.76 | Y34: 29176.34 | Z34: 28512.63 | AA34: 28358.26 | AB34: 21765.89 | AC34: 24277.34 | AD34: 22603.04 | AE34: 22022.61 | AF34: 21786.79 | AG34: 21760.62 | AH34: 25464.53 | AI34: 30068.98 | AJ34: 30715.76 | AK34: 29176.34 | AL34: 28512.63 | AM34: 28358.26
B35: 602004 Payroll Taxes | D35: 3244.47 | E35: 2155.86 | F35: 2294.08 | G35: 2133.96 | H35: 1999.79 | I35: 2290.5 | J35: 2481.37 | K35: 2195.06 | L35: 2290.5 | M35: 2481.37 | N35: 2576.81 | O35: 2481.37 | P35: 2481.37 | Q35: 2767.68 | R35: 2576.81 | S35: 2510.64 | T35: 2483.75 | U35: 2480.77 | V35: 2903.02 | W35: 3427.94 | X35: 3501.68 | Y35: 3326.18 | Z35: 3250.52 | AA35: 3232.92 | AB35: 2481.37 | AC35: 2767.68 | AD35: 2576.81 | AE35: 2510.64 | AF35: 2483.75 | AG35: 2480.77 | AH35: 2903.02 | AI35: 3427.94 | AJ35: 3501.68 | AK35: 3326.18 | AL35: 3250.52 | AM35: 3232.92
B36: 602005 Employee Benefits | D36: 362.04 | E36: 867.02 | F36: 756.24 | G36: 567.73 | H36: 577.5 | I36: 594.98 | J36: 644.56 | K36: 570.19 | L36: 594.98 | M36: 644.56 | N36: 669.35 | O36: 644.56 | P36: 644.56 | Q36: 718.94 | R36: 669.35 | S36: 652.17 | T36: 645.18 | U36: 644.41 | V36: 754.09 | W36: 890.45 | X36: 909.6 | Y36: 864.01 | Z36: 844.36 | AA36: 839.79 | AB36: 644.56 | AC36: 718.94 | AD36: 669.35 | AE36: 652.17 | AF36: 645.18 | AG36: 644.41 | AH36: 754.09 | AI36: 890.45 | AJ36: 909.6 | AK36: 864.01 | AL36: 844.36 | AM36: 839.79
B37: 602010 Payroll Processing Fees | D37: 676.22 | E37: 1136.79 | F37: 1540.85 | G37: 1035.47 | H37: 857.68 | I37: 1022.93 | J37: 1108.17 | K37: 980.31 | L37: 1022.93 | M37: 1108.17 | N37: 1150.8 | O37: 1108.17 | P37: 1108.17 | Q37: 1236.04 | R37: 1150.8 | S37: 1121.25 | T37: 1109.24 | U37: 1107.91 | V37: 1296.48 | W37: 1530.91 | X37: 1563.84 | Y37: 1485.47 | Z37: 1451.67 | AA37: 1443.81 | AB37: 1108.17 | AC37: 1236.04 | AD37: 1150.8 | AE37: 1121.25 | AF37: 1109.24 | AG37: 1107.91 | AH37: 1296.48 | AI37: 1530.91 | AJ37: 1563.84 | AK37: 1485.47 | AL37: 1451.67 | AM37: 1443.81
B38: Total Payroll | D38: 24075.14 | E38: 25308.17 | F38: 28299.03 | G38: 25300.13 | H38: 24141.6 | I38: =I34+I35+I36+I37 | J38: =J34+J35+J36+J37 | K38: =K34+K35+K36+K37 | L38: =L34+L35+L36+L37 | M38: =M34+M35+M36+M37 | N38: =N34+N35+N36+N37 | O38: =O34+O35+O36+O37 | P38: =P34+P35+P36+P37 | ... AM38: =AM34+AM35+AM36+AM37
B39: 603000 Software & Web Services | D39: 910.98 | E39: 1253.44 | F39: 881.08 | G39: 840.06 | H39: 1223.66 | I39: 903.34 | J39: 903.34 | K39: 903.34 | L39: 903.34 | M39: 903.34 | N39: 903.34 | O39: 903.34 | P39: 903.34 | Q39: 903.34 | R39: 903.34 | S39: 903.34 | T39: 903.34 | U39: 903.34 | V39: 903.34 | W39: 903.34 | X39: 903.34 | Y39: 903.34 | Z39: 903.34 | AA39: 903.34 | AB39: 903.34 | AC39: 903.34 | AD39: 903.34 | AE39: 903.34 | AF39: 903.34 | AG39: 903.34 | AH39: 903.34 | AI39: 903.34 | AJ39: 903.34 | AK39: 903.34 | AL39: 903.34 | AM39: 903.34
B40: 608000 Insurance | D40: 314.75 | E40: 314.75 | F40: 612.95 | G40: 580.03 | H40: 431.04 | I40: 423.7 | J40: 423.7 | K40: 423.7 | L40: 423.7 | M40: 423.7 | N40: 423.7 | O40: 423.7 | P40: 423.7 | Q40: 423.7 | R40: 423.7 | S40: 423.7 | T40: 423.7 | U40: 423.7 | V40: 423.7 | W40: 423.7 | X40: 423.7 | Y40: 423.7 | Z40: 423.7 | AA40: 423.7 | AB40: 423.7 | AC40: 423.7 | AD40: 423.7 | AE40: 423.7 | AF40: 423.7 | AG40: 423.7 | AH40: 423.7 | AI40: 423.7 | AJ40: 423.7 | AK40: 423.7 | AL40: 423.7 | AM40: 423.7
B41: 610000 Office Supplies | D41: 601.06 | E41: 153.33 | F41: 1031.56 | G41: 363.63 | H41: 0 | I41: 499.75 | J41: 499.75 | K41: 499.75 | L41: 499.75 | M41: 499.75 | N41: 499.75 | O41: 499.75 | P41: 499.75 | Q41: 499.75 | R41: 499.75 | S41: 499.75 | T41: 499.75 | U41: 499.75 | V41: 499.75 | W41: 499.75 | X41: 499.75 | Y41: 499.75 | Z41: 499.75 | AA41: 499.75 | AB41: 499.75 | AC41: 499.75 | AD41: 499.75 | AE41: 499.75 | AF41: 499.75 | AG41: 499.75 | AH41: 499.75 | AI41: 499.75 | AJ41: 499.75 | AK41: 499.75 | AL41: 499.75 | AM41: 499.75
B42: Total Software & Admin | D42: =D39+D40+D41 | E42: =E39+E40+E41 | F42: =F39+F40+F41 | G42: =G39+G40+G41 | H42: =H39+H40+H41 | I42: =I39+I40+I41 | J42: =J39+J40+J41 | K42: =K39+K40+K41 | ... AM42: =AM39+AM40+AM41
B43: 604100 Legal Fees | D43: 0 | E43: 0 | F43: 0 | G43: 0 | H43: 0 | I43: 0 | J43: 0 | K43: 0 | L43: 0 | M43: 0 | N43: 0 | O43: 0 | P43: 0 | Q43: 0 | R43: 0 | S43: 0 | T43: 0 | U43: 0 | V43: 0 | W43: 0 | X43: 0 | Y43: 0 | Z43: 0 | AA43: 0 | AB43: 0 | AC43: 0 | AD43: 0 | AE43: 0 | AF43: 0 | AG43: 0 | AH43: 0 | AI43: 0 | AJ43: 0 | AK43: 0 | AL43: 0 | AM43: 0
B44: 604200 Accounting | D44: 0 | E44: 301.82 | F44: 880 | G44: 2870 | H44: 1116.82 | I44: 341.86 | J44: 341.86 | K44: 341.86 | L44: 341.86 | M44: 341.86 | N44: 341.86 | O44: 341.86 | P44: 341.86 | Q44: 341.86 | R44: 341.86 | S44: 341.86 | T44: 341.86 | U44: 341.86 | V44: 341.86 | W44: 341.86 | X44: 341.86 | Y44: 341.86 | Z44: 341.86 | AA44: 341.86 | AB44: 341.86 | AC44: 341.86 | AD44: 341.86 | AE44: 341.86 | AF44: 341.86 | AG44: 341.86 | AH44: 341.86 | AI44: 341.86 | AJ44: 341.86 | AK44: 341.86 | AL44: 341.86 | AM44: 341.86
B45: 604300 Recruiting | D45: 0 | E45: 0 | F45: 0 | G45: 0 | H45: 0 | I45: 0 | J45: 0 | K45: 0 | L45: 0 | M45: 0 | N45: 0 | O45: 0 | P45: 0 | Q45: 0 | R45: 0 | S45: 0 | T45: 0 | U45: 0 | V45: 0 | W45: 0 | X45: 0 | Y45: 0 | Z45: 0 | AA45: 0 | AB45: 0 | AC45: 0 | AD45: 0 | AE45: 0 | AF45: 0 | AG45: 0 | AH45: 0 | AI45: 0 | AJ45: 0 | AK45: 0 | AL45: 0 | AM45: 0
B46: 604400 Other Professional Fees | D46: 516 | E46: 516 | F46: 516 | G46: 516 | H46: 516 | I46: 174.14 | J46: 174.14 | K46: 174.14 | L46: 174.14 | M46: 174.14 | N46: 174.14 | O46: 174.14 | P46: 174.14 | Q46: 174.14 | R46: 174.14 | S46: 174.14 | T46: 174.14 | U46: 174.14 | V46: 174.14 | W46: 174.14 | X46: 174.14 | Y46: 174.14 | Z46: 174.14 | AA46: 174.14 | AB46: 174.14 | AC46: 174.14 | AD46: 174.14 | AE46: 174.14 | AF46: 174.14 | AG46: 174.14 | AH46: 174.14 | AI46: 174.14 | AJ46: 174.14 | AK46: 174.14 | AL46: 174.14 | AM46: 174.14
B47: Total Professional Fees | D47: 516 | E47: 817.82 | F47: 1396 | G47: 3386 | H47: 1632.82 | I47: =I43+I44+I45+I46 | J47: =J43+J44+J45+J46 | K47: =K43+K44+K45+K46 | L47: =L43+L44+L45+L46 | M47: =M43+M44+M45+M46 | N47: =N43+N44+N45+N46 | O47: =O43+O44+O45+O46 | P47: =P43+P44+P45+P46 | ... AM47: =AM43+AM44+AM45+AM46
B48: 605000 Travel | D48: 420.63 | E48: 159.5 | F48: 271.5 | G48: 0 | H48: 0 | I48: 340.41 | J48: 340.41 | K48: 340.41 | L48: 340.41 | M48: 340.41 | N48: 340.41 | O48: 340.41 | P48: 340.41 | Q48: 340.41 | R48: 340.41 | S48: 340.41 | T48: 340.41 | U48: 340.41 | V48: 340.41 | W48: 340.41 | X48: 340.41 | Y48: 340.41 | Z48: 340.41 | AA48: 340.41 | AB48: 340.41 | AC48: 340.41 | AD48: 340.41 | AE48: 340.41 | AF48: 340.41 | AG48: 340.41 | AH48: 340.41 | AI48: 340.41 | AJ48: 340.41 | AK48: 340.41 | AL48: 340.41 | AM48: 340.41
B49: 606000 Meals | D49: 0 | E49: 43.24 | F49: 141.74 | G49: 15.7 | H49: 63.02 | I49: 80.22 | J49: 80.22 | K49: 80.22 | L49: 80.22 | M49: 80.22 | N49: 80.22 | O49: 80.22 | P49: 80.22 | Q49: 80.22 | R49: 80.22 | S49: 80.22 | T49: 80.22 | U49: 80.22 | V49: 80.22 | W49: 80.22 | X49: 80.22 | Y49: 80.22 | Z49: 80.22 | AA49: 80.22 | AB49: 80.22 | AC49: 80.22 | AD49: 80.22 | AE49: 80.22 | AF49: 80.22 | AG49: 80.22 | AH49: 80.22 | AI49: 80.22 | AJ49: 80.22 | AK49: 80.22 | AL49: 80.22 | AM49: 80.22
B50: Total Travel & Meals | D50: =D48+D49 | E50: =E48+E49 | F50: =F48+F49 | G50: =G48+G49 | H50: =H48+H49 | I50: =I48+I49 | J50: =J48+J49 | K50: =K48+K49 | ... AM50: =AM48+AM49
B51: 616001 Electricity | D51: 347.43 | E51: 327.14 | F51: 449.57 | G51: 414.77 | H51: 384.52 | I51: 389.78 | J51: 389.78 | K51: 389.78 | L51: 389.78 | M51: 389.78 | N51: 389.78 | O51: 389.78 | P51: 389.78 | Q51: 389.78 | R51: 389.78 | S51: 389.78 | T51: 389.78 | U51: 389.78 | V51: 389.78 | W51: 389.78 | X51: 389.78 | Y51: 389.78 | Z51: 389.78 | AA51: 389.78 | AB51: 389.78 | AC51: 389.78 | AD51: 389.78 | AE51: 389.78 | AF51: 389.78 | AG51: 389.78 | AH51: 389.78 | AI51: 389.78 | AJ51: 389.78 | AK51: 389.78 | AL51: 389.78 | AM51: 389.78
B52: 616002 Internet & TV | D52: 81.25 | E52: 93.09 | F52: 93.09 | G52: 93 | H52: 0 | I52: 91.29 | J52: 91.29 | K52: 91.29 | L52: 91.29 | M52: 91.29 | N52: 91.29 | O52: 91.29 | P52: 91.29 | Q52: 91.29 | R52: 91.29 | S52: 91.29 | T52: 91.29 | U52: 91.29 | V52: 91.29 | W52: 91.29 | X52: 91.29 | Y52: 91.29 | Z52: 91.29 | AA52: 91.29 | AB52: 91.29 | AC52: 91.29 | AD52: 91.29 | AE52: 91.29 | AF52: 91.29 | AG52: 91.29 | AH52: 91.29 | AI52: 91.29 | AJ52: 91.29 | AK52: 91.29 | AL52: 91.29 | AM52: 91.29
B53: 616003 Phone service | D53: 150 | E53: 149.97 | F53: 149.97 | G53: 150.52 | H53: 151.44 | I53: 152.09 | J53: 152.09 | K53: 152.09 | L53: 152.09 | M53: 152.09 | N53: 152.09 | O53: 152.09 | P53: 152.09 | Q53: 152.09 | R53: 152.09 | S53: 152.09 | T53: 152.09 | U53: 152.09 | V53: 152.09 | W53: 152.09 | X53: 152.09 | Y53: 152.09 | Z53: 152.09 | AA53: 152.09 | AB53: 152.09 | AC53: 152.09 | AD53: 152.09 | AE53: 152.09 | AF53: 152.09 | AG53: 152.09 | AH53: 152.09 | AI53: 152.09 | AJ53: 152.09 | AK53: 152.09 | AL53: 152.09 | AM53: 152.09
B54: 616004 Water & sewer | D54: 0 | E54: 0 | F54: 0 | G54: 0 | H54: 0 | I54: 0 | J54: 0 | K54: 0 | L54: 0 | M54: 0 | N54: 0 | O54: 0 | P54: 0 | Q54: 0 | R54: 0 | S54: 0 | T54: 0 | U54: 0 | V54: 0 | W54: 0 | X54: 0 | Y54: 0 | Z54: 0 | AA54: 0 | AB54: 0 | AC54: 0 | AD54: 0 | AE54: 0 | AF54: 0 | AG54: 0 | AH54: 0 | AI54: 0 | AJ54: 0 | AK54: 0 | AL54: 0 | AM54: 0
B55: 616005 Disposal Services | D55: 77.98 | E55: 83.75 | F55: 91.6 | G55: 76.36 | H55: 70.14 | I55: 83.5 | J55: 83.5 | K55: 83.5 | L55: 83.5 | M55: 83.5 | N55: 83.5 | O55: 83.5 | P55: 83.5 | Q55: 83.5 | R55: 83.5 | S55: 83.5 | T55: 83.5 | U55: 83.5 | V55: 83.5 | W55: 83.5 | X55: 83.5 | Y55: 83.5 | Z55: 83.5 | AA55: 83.5 | AB55: 83.5 | AC55: 83.5 | AD55: 83.5 | AE55: 83.5 | AF55: 83.5 | AG55: 83.5 | AH55: 83.5 | AI55: 83.5 | AJ55: 83.5 | AK55: 83.5 | AL55: 83.5 | AM55: 83.5
B56: Total Utilities | D56: 656.66 | E56: 653.95 | F56: 784.23 | G56: 734.65 | H56: 699.1 | I56: =I51+I52+I53+I54+I55 | J56: =J51+J52+J53+J54+J55 | K56: =K51+K52+K53+K54+K55 | L56: =L51+L52+L53+L54+L55 | M56: =M51+M52+M53+M54+M55 | N56: =N51+N52+N53+N54+N55 | O56: =O51+O52+O53+O54+O55 | P56: =P51+P52+P53+P54+P55 | ... AM56: =AM51+AM52+AM53+AM54+AM55
B57: 701000 Rent | D57: 8122.98 | E57: 8122.98 | F57: 8122.98 | G57: 8122.98 | H57: 8122.98 | I57: 8028.77 | J57: 8028.77 | K57: 8028.77 | L57: 8028.77 | M57: 8028.77 | N57: 8028.77 | O57: 8028.77 | P57: 8028.77 | Q57: 8028.77 | R57: 8028.77 | S57: 8028.77 | T57: 8028.77 | U57: 8028.77 | V57: 8028.77 | W57: 8028.77 | X57: 8028.77 | Y57: 8028.77 | Z57: 8028.77 | AA57: 8028.77 | AB57: 8028.77 | AC57: 8028.77 | AD57: 8028.77 | AE57: 8028.77 | AF57: 8028.77 | AG57: 8028.77 | AH57: 8028.77 | AI57: 8028.77 | AJ57: 8028.77 | AK57: 8028.77 | AL57: 8028.77 | AM57: 8028.77
B58: 702000 Security | D58: 0 | E58: 0 | F58: 0 | G58: 0 | H58: 0 | I58: 0 | J58: 0 | K58: 0 | L58: 0 | M58: 0 | N58: 0 | O58: 0 | P58: 0 | Q58: 0 | R58: 0 | S58: 0 | T58: 0 | U58: 0 | V58: 0 | W58: 0 | X58: 0 | Y58: 0 | Z58: 0 | AA58: 0 | AB58: 0 | AC58: 0 | AD58: 0 | AE58: 0 | AF58: 0 | AG58: 0 | AH58: 0 | AI58: 0 | AJ58: 0 | AK58: 0 | AL58: 0 | AM58: 0
B59: 703000 Cleaning | D59: 140.57 | E59: 394.25 | F59: 414.89 | G59: -0.45 | H59: 84.04 | I59: 234.78 | J59: 234.78 | K59: 234.78 | L59: 234.78 | M59: 234.78 | N59: 234.78 | O59: 234.78 | P59: 234.78 | Q59: 234.78 | R59: 234.78 | S59: 234.78 | T59: 234.78 | U59: 234.78 | V59: 234.78 | W59: 234.78 | X59: 234.78 | Y59: 234.78 | Z59: 234.78 | AA59: 234.78 | AB59: 234.78 | AC59: 234.78 | AD59: 234.78 | AE59: 234.78 | AF59: 234.78 | AG59: 234.78 | AH59: 234.78 | AI59: 234.78 | AJ59: 234.78 | AK59: 234.78 | AL59: 234.78 | AM59: 234.78
B60: 705000 Property Maintenance | D60: 0 | E60: 0 | F60: 0 | G60: 0 | H60: 0 | I60: 0 | J60: 0 | K60: 0 | L60: 0 | M60: 0 | N60: 0 | O60: 0 | P60: 0 | Q60: 0 | R60: 0 | S60: 0 | T60: 0 | U60: 0 | V60: 0 | W60: 0 | X60: 0 | Y60: 0 | Z60: 0 | AA60: 0 | AB60: 0 | AC60: 0 | AD60: 0 | AE60: 0 | AF60: 0 | AG60: 0 | AH60: 0 | AI60: 0 | AJ60: 0 | AK60: 0 | AL60: 0 | AM60: 0
B61: Total Property Costs | D61: 8263.55 | E61: 8517.23 | F61: 8537.87 | G61: 8267.28 | H61: 8207.02 | I61: =I57+I58+I59+I60 | J61: =J57+J58+J59+J60 | K61: =K57+K58+K59+K60 | L61: =L57+L58+L59+L60 | M61: =M57+M58+M59+M60 | N61: =N57+N58+N59+N60 | O61: =O57+O58+O59+O60 | P61: =P57+P58+P59+P60 | ... AM61: =AM57+AM58+AM59+AM60
B62: TOTAL OPERATING EXPENSES | D62: 37096.85 | E62: 38680.31 | F62: 42513.06 | G62: 42818.4 | H62: 37822.43 | I62: =I33+I38+I42+I47+I50+I56+I61 | J62: =J33+J38+J42+J47+J50+J56+J61 | K62: =K33+K38+K42+K47+K50+K56+K61 | L62: =L33+L38+L42+L47+L50+L56+L61 | M62: =M33+M38+M42+M47+M50+M56+M61 | N62: =N33+N38+N42+N47+N50+N56+N61 | O62: =O33+O38+O42+O47+O50+O56+O61 | P62: =P33+P38+P42+P47+P50+P56+P61 | ... AM62: =AM33+AM38+AM42+AM47+AM50+AM56+AM61
B63: NET OPERATING INCOME (EBITDA) | D63: -1862.02 | E63: 1313.41 | F63: -1516.94 | G63: -7133.11 | H63: -2779.31 | I63: =I26-I62 | J63: =J26-J62 | K63: =K26-K62 | L63: =L26-L62 | M63: =M26-M62 | N63: =N26-N62 | O63: =O26-O62 | P63: =P26-P62 | ... AM63: =AM26-AM62
B64: OTHER
B65: 810000 Depreciation | D65: 4691.67 | E65: 4691.67 | F65: 4691.67 | G65: 4691.67 | H65: 4691.67 | I65: =I69*0.979862 | J65: =J69*0.979862 | K65: =K69*0.979862 | L65: =L69*0.979862 | M65: =M69*0.979862 | N65: =N69*0.979862 | O65: =O69*0.979862 | P65: =P69*0.979862 | ... AM65: =AM69*0.979862
B66: 901000 Interest Expense | D66: 0 | E66: 0 | F66: 0 | G66: 0 | H66: 0 | I66: 0 | J66: 0 | K66: 0 | L66: 0 | M66: 0 | N66: 0 | O66: 0 | P66: 0 | Q66: 0 | R66: 0 | S66: 0 | T66: 0 | U66: 0 | V66: 0 | W66: 0 | X66: 0 | Y66: 0 | Z66: 0 | AA66: 0 | AB66: 0 | AC66: 0 | AD66: 0 | AE66: 0 | AF66: 0 | AG66: 0 | AH66: 0 | AI66: 0 | AJ66: 0 | AK66: 0 | AL66: 0 | AM66: 0
B67: 902000 Taxes Paid | D67: 0 | E67: 385.69 | F67: 0 | G67: 0 | H67: 0 | I67: =I69*0.020138 | J67: =J69*0.020138 | K67: =K69*0.020138 | L67: =L69*0.020138 | M67: =M69*0.020138 | N67: =N69*0.020138 | O67: =O69*0.020138 | P67: =P69*0.020138 | ... AM67: =AM69*0.020138
B68: 903000 Property taxes | D68: 0 | E68: 0 | F68: 0 | G68: 0 | H68: 0 | I68: 0 | J68: 0 | K68: 0 | L68: 0 | M68: 0 | N68: 0 | O68: 0 | P68: 0 | Q68: 0 | R68: 0 | S68: 0 | T68: 0 | U68: 0 | V68: 0 | W68: 0 | X68: 0 | Y68: 0 | Z68: 0 | AA68: 0 | AB68: 0 | AC68: 0 | AD68: 0 | AE68: 0 | AF68: 0 | AG68: 0 | AH68: 0 | AI68: 0 | AJ68: 0 | AK68: 0 | AL68: 0 | AM68: 0
B69: Total Other Expenses | D69: 4691.67 | E69: 5077.36 | F69: 4691.67 | G69: 4691.67 | H69: 4691.67 | I69: 0 | J69: 0 | K69: 0 | L69: 0 | M69: 0 | N69: 0 | O69: 0 | P69: 0 | Q69: 0 | R69: 0 | S69: 0 | T69: 0 | U69: 0 | V69: 0 | W69: 0 | X69: 0 | Y69: 0 | Z69: 0 | AA69: 0 | AB69: 0 | AC69: 0 | AD69: 0 | AE69: 0 | AF69: 0 | AG69: 0 | AH69: 0 | AI69: 0 | AJ69: 0 | AK69: 0 | AL69: 0 | AM69: 0
B70: NET INCOME | D70: -6553.69 | E70: -3763.95 | F70: -6208.61 | G70: -11824.78 | H70: -7470.98 | I70: =I63-I69 | J70: =J63-J69 | K70: =K63-K69 | L70: =L63-L69 | M70: =M63-M69 | N70: =N63-N69 | O70: =O63-O69 | P70: =P63-P69 | ... AM70: =AM63-AM69

Sheet DN P&L
B2: Danville (DN) — Profit & Loss
B4: Monthly P&L (Detail)
B5: Line Item | D5: Jan 2026 | E5: Feb 2026 | F5: Mar 2026 | G5: Apr 2026 | H5: May 2026 | I5: Jun 2026 | J5: Jul 2026 | K5: Aug 2026 | L5: Sep 2026 | M5: Oct 2026 | N5: Nov 2026 | O5: Dec 2026 | P5: Jan 2027 | Q5: Feb 2027 | R5: Mar 2027 | S5: Apr 2027 | T5: May 2027 | U5: Jun 2027 | V5: Jul 2027 | W5: Aug 2027 | X5: Sep 2027 | Y5: Oct 2027 | Z5: Nov 2027 | AA5: Dec 2027 | AB5: Jan 2028 | AC5: Feb 2028 | AD5: Mar 2028 | AE5: Apr 2028 | AF5: May 2028 | AG5: Jun 2028 | AH5: Jul 2028 | AI5: Aug 2028 | AJ5: Sep 2028 | AK5: Oct 2028 | AL5: Nov 2028 | AM5: Dec 2028
B6: INCOME
B7: 401001 Machine | D7: 13528.97 | E7: 12132.96 | F7: 13736.52 | G7: 12829.22 | H7: 10784.93 | I7: =I13*0.654061 | J7: =J13*0.654061 | K7: =K13*0.654061 | L7: =L13*0.654061 | M7: =M13*0.654061 | N7: =N13*0.654061 | O7: =O13*0.654061 | P7: =P13*0.654061 | ... AM7: =AM13*0.654061
B8: 401002 Private Pilates | D8: 450 | E8: 1593 | F8: 1977 | G8: 1360 | H8: 1031.67 | I8: =I13*0.067375 | J8: =J13*0.067375 | K8: =K13*0.067375 | L8: =L13*0.067375 | M8: =M13*0.067375 | N8: =N13*0.067375 | O8: =O13*0.067375 | P8: =P13*0.067375 | ... AM8: =AM13*0.067375
B9: 401003 Class Pass | D9: 6572 | E9: 5183.81 | F9: 5673.02 | G9: 4787 | H9: 4644.86 | I9: =I13*0.278215 | J9: =J13*0.278215 | K9: =K13*0.278215 | L9: =L13*0.278215 | M9: =M13*0.278215 | N9: =N13*0.278215 | O9: =O13*0.278215 | P9: =P13*0.278215 | ... AM9: =AM13*0.278215
B10: 401004 Mighty Teacher Training | D10: 0 | E10: 0 | F10: 0 | G10: 0 | H10: 0 | I10: 0 | J10: 0 | K10: 0 | L10: 0 | M10: 0 | N10: 0 | O10: 0 | P10: 0 | Q10: 0 | R10: 0 | S10: 0 | T10: 0 | U10: 0 | V10: 0 | W10: 0 | X10: 0 | Y10: 0 | Z10: 0 | AA10: 0 | AB10: 0 | AC10: 0 | AD10: 0 | AE10: 0 | AF10: 0 | AG10: 0 | AH10: 0 | AI10: 0 | AJ10: 0 | AK10: 0 | AL10: 0 | AM10: 0
B11: 401005 Livestream Classes | D11: 0 | E11: 0 | F11: 0 | G11: 0 | H11: 0 | I11: 0 | J11: 0 | K11: 0 | L11: 0 | M11: 0 | N11: 0 | O11: 0 | P11: 0 | Q11: 0 | R11: 0 | S11: 0 | T11: 0 | U11: 0 | V11: 0 | W11: 0 | X11: 0 | Y11: 0 | Z11: 0 | AA11: 0 | AB11: 0 | AC11: 0 | AD11: 0 | AE11: 0 | AF11: 0 | AG11: 0 | AH11: 0 | AI11: 0 | AJ11: 0 | AK11: 0 | AL11: 0 | AM11: 0
B12: 401006 Wellhub | D12: 0 | E12: 0 | F12: 27.82 | G12: 0 | H12: 0 | I12: =I13*0.000348 | J12: =J13*0.000348 | K12: =K13*0.000348 | L12: =L13*0.000348 | M12: =M13*0.000348 | N12: =N13*0.000348 | O12: =O13*0.000348 | P12: =P13*0.000348 | ... AM12: =AM13*0.000348
B13: Total Sessions | D13: 20550.97 | E13: 18909.77 | F13: 21414.36 | G13: 18976.22 | H13: 16461.46 | I13: ='Sales Forecast'!I8*Assumptions!$C$12+'Sales Forecast'!H8*Assumptions!$D$12+'Sales Forecast'!G8*Assumptions!$E$12+'Sales Forecast'!F8*Assumptions!$F$12+'Sales Forecast'!E8*Assumptions!$G$12+'Sales Forecast'!D8*Assumptions!$H$12+'Sales Forecast'!I104*Assumptions!$I$12 | J13: ='Sales Forecast'!J8*Assumptions!$C$12+'Sales Forecast'!I8*Assumptions!$D$12+'Sales Forecast'!H8*Assumptions!$E$12+'Sales Forecast'!G8*Assumptions!$F$12+'Sales Forecast'!F8*Assumptions!$G$12+'Sales Forecast'!E8*Assumptions!$H$12+'Sales Forecast'!D8*Assumptions!$I$12 | K13: ='Sales Forecast'!K8*Assumptions!$C$12+'Sales Forecast'!J8*Assumptions!$D$12+'Sales Forecast'!I8*Assumptions!$E$12+'Sales Forecast'!H8*Assumptions!$F$12+'Sales Forecast'!G8*Assumptions!$G$12+'Sales Forecast'!F8*Assumptions!$H$12+'Sales Forecast'!E8*Assumptions!$I$12 | L13: ='Sales Forecast'!L8*Assumptions!$C$12+'Sales Forecast'!K8*Assumptions!$D$12+'Sales Forecast'!J8*Assumptions!$E$12+'Sales Forecast'!I8*Assumptions!$F$12+'Sales Forecast'!H8*Assumptions!$G$12+'Sales Forecast'!G8*Assumptions!$H$12+'Sales Forecast'!F8*Assumptions!$I$12 | M13: ='Sales Forecast'!M8*Assumptions!$C$12+'Sales Forecast'!L8*Assumptions!$D$12+'Sales Forecast'!K8*Assumptions!$E$12+'Sales Forecast'!J8*Assumptions!$F$12+'Sales Forecast'!I8*Assumptions!$G$12+'Sales Forecast'!H8*Assumptions!$H$12+'Sales Forecast'!G8*Assumptions!$I$12 | N13: ='Sales Forecast'!N8*Assumptions!$C$12+'Sales Forecast'!M8*Assumptions!$D$12+'Sales Forecast'!L8*Assumptions!$E$12+'Sales Forecast'!K8*Assumptions!$F$12+'Sales Forecast'!J8*Assumptions!$G$12+'Sales Forecast'!I8*Assumptions!$H$12+'Sales Forecast'!H8*Assumptions!$I$12 | O13: ='Sales Forecast'!O8*Assumptions!$C$12+'Sales Forecast'!N8*Assumptions!$D$12+'Sales Forecast'!M8*Assumptions!$E$12+'Sales Forecast'!L8*Assumptions!$F$12+'Sales Forecast'!K8*Assumptions!$G$12+'Sales Forecast'!J8*Assumptions!$H$12+'Sales Forecast'!I8*Assumptions!$I$12 | P13: ='Sales Forecast'!P8*Assumptions!$C$12+'Sales Forecast'!O8*Assumptions!$D$12+'Sales Forecast'!N8*Assumptions!$E$12+'Sales Forecast'!M8*Assumptions!$F$12+'Sales Forecast'!L8*Assumptions!$G$12+'Sales Forecast'!K8*Assumptions!$H$12+'Sales Forecast'!J8*Assumptions!$I$12 | Q13: ='Sales Forecast'!Q8*Assumptions!$C$12+'Sales Forecast'!P8*Assumptions!$D$12+'Sales Forecast'!O8*Assumptions!$E$12+'Sales Forecast'!N8*Assumptions!$F$12+'Sales Forecast'!M8*Assumptions!$G$12+'Sales Forecast'!L8*Assumptions!$H$12+'Sales Forecast'!K8*Assumptions!$I$12 | ... AM13: ='Sales Forecast'!AM8*Assumptions!$C$12+'Sales Forecast'!AL8*Assumptions!$D$12+'Sales Forecast'!AK8*Assumptions!$E$12+'Sales Forecast'!AJ8*Assumptions!$F$12+'Sales Forecast'!AI8*Assumptions!$G$12+'Sales Forecast'!AH8*Assumptions!$H$12+'Sales Forecast'!AG8*Assumptions!$I$12
B14: 403001 Machine Breakage | D14: 3417.25 | E14: 3639.02 | F14: 3973.02 | G14: 3208.35 | H14: 4144.05 | I14: =I17*0.958916 | J14: =J17*0.958916 | K14: =K17*0.958916 | L14: =L17*0.958916 | M14: =M17*0.958916 | N14: =N17*0.958916 | O14: =O17*0.958916 | P14: =P17*0.958916 | ... AM14: =AM17*0.958916
B15: 403003 Private Pilates Breakage | D15: 0 | E15: 150 | F15: 460 | G15: 0 | H15: 200 | I15: =I17*0.041084 | J15: =J17*0.041084 | K15: =K17*0.041084 | L15: =L17*0.041084 | M15: =M17*0.041084 | N15: =N17*0.041084 | O15: =O17*0.041084 | P15: =P17*0.041084 | ... AM15: =AM17*0.041084
B16: 403004 Other Breakage | D16: 0 | E16: 0 | F16: 0 | G16: 0 | H16: 0 | I16: 0 | J16: 0 | K16: 0 | L16: 0 | M16: 0 | N16: 0 | O16: 0 | P16: 0 | Q16: 0 | R16: 0 | S16: 0 | T16: 0 | U16: 0 | V16: 0 | W16: 0 | X16: 0 | Y16: 0 | Z16: 0 | AA16: 0 | AB16: 0 | AC16: 0 | AD16: 0 | AE16: 0 | AF16: 0 | AG16: 0 | AH16: 0 | AI16: 0 | AJ16: 0 | AK16: 0 | AL16: 0 | AM16: 0
B17: Total Breakage Revenue | D17: 3417.25 | E17: 3789.02 | F17: 4433.02 | G17: 3208.35 | H17: 4344.05 | I17: ='Sales Forecast'!I8*Assumptions!$C$13+'Sales Forecast'!H8*Assumptions!$D$13+'Sales Forecast'!G8*Assumptions!$E$13+'Sales Forecast'!F8*Assumptions!$F$13+'Sales Forecast'!E8*Assumptions!$G$13+'Sales Forecast'!D8*Assumptions!$H$13+'Sales Forecast'!I104*Assumptions!$I$13 | J17: ='Sales Forecast'!J8*Assumptions!$C$13+'Sales Forecast'!I8*Assumptions!$D$13+'Sales Forecast'!H8*Assumptions!$E$13+'Sales Forecast'!G8*Assumptions!$F$13+'Sales Forecast'!F8*Assumptions!$G$13+'Sales Forecast'!E8*Assumptions!$H$13+'Sales Forecast'!D8*Assumptions!$I$13 | K17: ='Sales Forecast'!K8*Assumptions!$C$13+'Sales Forecast'!J8*Assumptions!$D$13+'Sales Forecast'!I8*Assumptions!$E$13+'Sales Forecast'!H8*Assumptions!$F$13+'Sales Forecast'!G8*Assumptions!$G$13+'Sales Forecast'!F8*Assumptions!$H$13+'Sales Forecast'!E8*Assumptions!$I$13 | L17: ='Sales Forecast'!L8*Assumptions!$C$13+'Sales Forecast'!K8*Assumptions!$D$13+'Sales Forecast'!J8*Assumptions!$E$13+'Sales Forecast'!I8*Assumptions!$F$13+'Sales Forecast'!H8*Assumptions!$G$13+'Sales Forecast'!G8*Assumptions!$H$13+'Sales Forecast'!F8*Assumptions!$I$13 | M17: ='Sales Forecast'!M8*Assumptions!$C$13+'Sales Forecast'!L8*Assumptions!$D$13+'Sales Forecast'!K8*Assumptions!$E$13+'Sales Forecast'!J8*Assumptions!$F$13+'Sales Forecast'!I8*Assumptions!$G$13+'Sales Forecast'!H8*Assumptions!$H$13+'Sales Forecast'!G8*Assumptions!$I$13 | N17: ='Sales Forecast'!N8*Assumptions!$C$13+'Sales Forecast'!M8*Assumptions!$D$13+'Sales Forecast'!L8*Assumptions!$E$13+'Sales Forecast'!K8*Assumptions!$F$13+'Sales Forecast'!J8*Assumptions!$G$13+'Sales Forecast'!I8*Assumptions!$H$13+'Sales Forecast'!H8*Assumptions!$I$13 | O17: ='Sales Forecast'!O8*Assumptions!$C$13+'Sales Forecast'!N8*Assumptions!$D$13+'Sales Forecast'!M8*Assumptions!$E$13+'Sales Forecast'!L8*Assumptions!$F$13+'Sales Forecast'!K8*Assumptions!$G$13+'Sales Forecast'!J8*Assumptions!$H$13+'Sales Forecast'!I8*Assumptions!$I$13 | P17: ='Sales Forecast'!P8*Assumptions!$C$13+'Sales Forecast'!O8*Assumptions!$D$13+'Sales Forecast'!N8*Assumptions!$E$13+'Sales Forecast'!M8*Assumptions!$F$13+'Sales Forecast'!L8*Assumptions!$G$13+'Sales Forecast'!K8*Assumptions!$H$13+'Sales Forecast'!J8*Assumptions!$I$13 | Q17: ='Sales Forecast'!Q8*Assumptions!$C$13+'Sales Forecast'!P8*Assumptions!$D$13+'Sales Forecast'!O8*Assumptions!$E$13+'Sales Forecast'!N8*Assumptions!$F$13+'Sales Forecast'!M8*Assumptions!$G$13+'Sales Forecast'!L8*Assumptions!$H$13+'Sales Forecast'!K8*Assumptions!$I$13 | ... AM17: ='Sales Forecast'!AM8*Assumptions!$C$13+'Sales Forecast'!AL8*Assumptions!$D$13+'Sales Forecast'!AK8*Assumptions!$E$13+'Sales Forecast'!AJ8*Assumptions!$F$13+'Sales Forecast'!AI8*Assumptions!$G$13+'Sales Forecast'!AH8*Assumptions!$H$13+'Sales Forecast'!AG8*Assumptions!$I$13
B18: 404000 Retail Sales | D18: 768 | E18: 416 | F18: 528 | G18: 598 | H18: 332 | I18: =577.5 | J18: =577.5 | K18: =577.5 | L18: =577.5 | M18: =577.5 | N18: =577.5 | O18: =577.5 | P18: =577.5 | ... AM18: =577.5
B19: 406000 Refunds | D19: 0 | E19: 0 | F19: 245 | G19: 245 | H19: 245 | I19: =('Sales Forecast'!I8*Assumptions!$C$12+'Sales Forecast'!H8*Assumptions!$D$12+'Sales Forecast'!G8*Assumptions!$E$12+'Sales Forecast'!F8*Assumptions!$F$12+'Sales Forecast'!E8*Assumptions!$G$12+'Sales Forecast'!D8*Assumptions!$H$12+'Sales Forecast'!I8*Assumptions!$C$13+'Sales Forecast'!H8*Assumptions!$D$13+'Sales Forecast'!G8*Assumptions!$E$13+'Sales Forecast'!F8*Assumptions!$F$13+'Sales Forecast'!E8*Assumptions!$G$13+'Sales Forecast'!D8*Assumptions!$H$13+577.5)*Assumptions!$C$17 | J19: =('Sales Forecast'!J8*Assumptions!$C$12+'Sales Forecast'!I8*Assumptions!$D$12+'Sales Forecast'!H8*Assumptions!$E$12+'Sales Forecast'!G8*Assumptions!$F$12+'Sales Forecast'!F8*Assumptions!$G$12+'Sales Forecast'!E8*Assumptions!$H$12+'Sales Forecast'!D8*Assumptions!$I$12+'Sales Forecast'!J8*Assumptions!$C$13+'Sales Forecast'!I8*Assumptions!$D$13+'Sales Forecast'!H8*Assumptions!$E$13+'Sales Forecast'!G8*Assumptions!$F$13+'Sales Forecast'!F8*Assumptions!$G$13+'Sales Forecast'!E8*Assumptions!$H$13+'Sales Forecast'!D8*Assumptions!$I$13+577.5)*Assumptions!$C$17 | K19: =('Sales Forecast'!K8*Assumptions!$C$12+'Sales Forecast'!J8*Assumptions!$D$12+'Sales Forecast'!I8*Assumptions!$E$12+'Sales Forecast'!H8*Assumptions!$F$12+'Sales Forecast'!G8*Assumptions!$G$12+'Sales Forecast'!F8*Assumptions!$H$12+'Sales Forecast'!E8*Assumptions!$I$12+'Sales Forecast'!K8*Assumptions!$C$13+'Sales Forecast'!J8*Assumptions!$D$13+'Sales Forecast'!I8*Assumptions!$E$13+'Sales Forecast'!H8*Assumptions!$F$13+'Sales Forecast'!G8*Assumptions!$G$13+'Sales Forecast'!F8*Assumptions!$H$13+'Sales Forecast'!E8*Assumptions!$I$13+577.5)*Assumptions!$C$17 | L19: =('Sales Forecast'!L8*Assumptions!$C$12+'Sales Forecast'!K8*Assumptions!$D$12+'Sales Forecast'!J8*Assumptions!$E$12+'Sales Forecast'!I8*Assumptions!$F$12+'Sales Forecast'!H8*Assumptions!$G$12+'Sales Forecast'!G8*Assumptions!$H$12+'Sales Forecast'!F8*Assumptions!$I$12+'Sales Forecast'!L8*Assumptions!$C$13+'Sales Forecast'!K8*Assumptions!$D$13+'Sales Forecast'!J8*Assumptions!$E$13+'Sales Forecast'!I8*Assumptions!$F$13+'Sales Forecast'!H8*Assumptions!$G$13+'Sales Forecast'!G8*Assumptions!$H$13+'Sales Forecast'!F8*Assumptions!$I$13+577.5)*Assumptions!$C$17 | M19: =('Sales Forecast'!M8*Assumptions!$C$12+'Sales Forecast'!L8*Assumptions!$D$12+'Sales Forecast'!K8*Assumptions!$E$12+'Sales Forecast'!J8*Assumptions!$F$12+'Sales Forecast'!I8*Assumptions!$G$12+'Sales Forecast'!H8*Assumptions!$H$12+'Sales Forecast'!G8*Assumptions!$I$12+'Sales Forecast'!M8*Assumptions!$C$13+'Sales Forecast'!L8*Assumptions!$D$13+'Sales Forecast'!K8*Assumptions!$E$13+'Sales Forecast'!J8*Assumptions!$F$13+'Sales Forecast'!I8*Assumptions!$G$13+'Sales Forecast'!H8*Assumptions!$H$13+'Sales Forecast'!G8*Assumptions!$I$13+577.5)*Assumptions!$C$17 | N19: =('Sales Forecast'!N8*Assumptions!$C$12+'Sales Forecast'!M8*Assumptions!$D$12+'Sales Forecast'!L8*Assumptions!$E$12+'Sales Forecast'!K8*Assumptions!$F$12+'Sales Forecast'!J8*Assumptions!$G$12+'Sales Forecast'!I8*Assumptions!$H$12+'Sales Forecast'!H8*Assumptions!$I$12+'Sales Forecast'!N8*Assumptions!$C$13+'Sales Forecast'!M8*Assumptions!$D$13+'Sales Forecast'!L8*Assumptions!$E$13+'Sales Forecast'!K8*Assumptions!$F$13+'Sales Forecast'!J8*Assumptions!$G$13+'Sales Forecast'!I8*Assumptions!$H$13+'Sales Forecast'!H8*Assumptions!$I$13+577.5)*Assumptions!$C$17 | O19: =('Sales Forecast'!O8*Assumptions!$C$12+'Sales Forecast'!N8*Assumptions!$D$12+'Sales Forecast'!M8*Assumptions!$E$12+'Sales Forecast'!L8*Assumptions!$F$12+'Sales Forecast'!K8*Assumptions!$G$12+'Sales Forecast'!J8*Assumptions!$H$12+'Sales Forecast'!I8*Assumptions!$I$12+'Sales Forecast'!O8*Assumptions!$C$13+'Sales Forecast'!N8*Assumptions!$D$13+'Sales Forecast'!M8*Assumptions!$E$13+'Sales Forecast'!L8*Assumptions!$F$13+'Sales Forecast'!K8*Assumptions!$G$13+'Sales Forecast'!J8*Assumptions!$H$13+'Sales Forecast'!I8*Assumptions!$I$13+577.5)*Assumptions!$C$17 | P19: =('Sales Forecast'!P8*Assumptions!$C$12+'Sales Forecast'!O8*Assumptions!$D$12+'Sales Forecast'!N8*Assumptions!$E$12+'Sales Forecast'!M8*Assumptions!$F$12+'Sales Forecast'!L8*Assumptions!$G$12+'Sales Forecast'!K8*Assumptions!$H$12+'Sales Forecast'!J8*Assumptions!$I$12+'Sales Forecast'!P8*Assumptions!$C$13+'Sales Forecast'!O8*Assumptions!$D$13+'Sales Forecast'!N8*Assumptions!$E$13+'Sales Forecast'!M8*Assumptions!$F$13+'Sales Forecast'!L8*Assumptions!$G$13+'Sales Forecast'!K8*Assumptions!$H$13+'Sales Forecast'!J8*Assumptions!$I$13+577.5)*Assumptions!$C$17 | Q19: =('Sales Forecast'!Q8*Assumptions!$C$12+'Sales Forecast'!P8*Assumptions!$D$12+'Sales Forecast'!O8*Assumptions!$E$12+'Sales Forecast'!N8*Assumptions!$F$12+'Sales Forecast'!M8*Assumptions!$G$12+'Sales Forecast'!L8*Assumptions!$H$12+'Sales Forecast'!K8*Assumptions!$I$12+'Sales Forecast'!Q8*Assumptions!$C$13+'Sales Forecast'!P8*Assumptions!$D$13+'Sales Forecast'!O8*Assumptions!$E$13+'Sales Forecast'!N8*Assumptions!$F$13+'Sales Forecast'!M8*Assumptions!$G$13+'Sales Forecast'!L8*Assumptions!$H$13+'Sales Forecast'!K8*Assumptions!$I$13+577.5)*Assumptions!$C$17 | ... AM19: =('Sales Forecast'!AM8*Assumptions!$C$12+'Sales Forecast'!AL8*Assumptions!$D$12+'Sales Forecast'!AK8*Assumptions!$E$12+'Sales Forecast'!AJ8*Assumptions!$F$12+'Sales Forecast'!AI8*Assumptions!$G$12+'Sales Forecast'!AH8*Assumptions!$H$12+'Sales Forecast'!AG8*Assumptions!$I$12+'Sales Forecast'!AM8*Assumptions!$C$13+'Sales Forecast'!AL8*Assumptions!$D$13+'Sales Forecast'!AK8*Assumptions!$E$13+'Sales Forecast'!AJ8*Assumptions!$F$13+'Sales Forecast'!AI8*Assumptions!$G$13+'Sales Forecast'!AH8*Assumptions!$H$13+'Sales Forecast'!AG8*Assumptions!$I$13+577.5)*Assumptions!$C$17
B20: 407000 Discounts | D20: 3930.1 | E20: 2252.3 | F20: 2380.1 | G20: 1371.5 | H20: 1163 | I20: =('Sales Forecast'!I8*Assumptions!$C$12+'Sales Forecast'!H8*Assumptions!$D$12+'Sales Forecast'!G8*Assumptions!$E$12+'Sales Forecast'!F8*Assumptions!$F$12+'Sales Forecast'!E8*Assumptions!$G$12+'Sales Forecast'!D8*Assumptions!$H$12+'Sales Forecast'!I8*Assumptions!$C$13+'Sales Forecast'!H8*Assumptions!$D$13+'Sales Forecast'!G8*Assumptions!$E$13+'Sales Forecast'!F8*Assumptions!$F$13+'Sales Forecast'!E8*Assumptions!$G$13+'Sales Forecast'!D8*Assumptions!$H$13+577.5)*Assumptions!$C$18 | J20: =('Sales Forecast'!J8*Assumptions!$C$12+'Sales Forecast'!I8*Assumptions!$D$12+'Sales Forecast'!H8*Assumptions!$E$12+'Sales Forecast'!G8*Assumptions!$F$12+'Sales Forecast'!F8*Assumptions!$G$12+'Sales Forecast'!E8*Assumptions!$H$12+'Sales Forecast'!D8*Assumptions!$I$12+'Sales Forecast'!J8*Assumptions!$C$13+'Sales Forecast'!I8*Assumptions!$D$13+'Sales Forecast'!H8*Assumptions!$E$13+'Sales Forecast'!G8*Assumptions!$F$13+'Sales Forecast'!F8*Assumptions!$G$13+'Sales Forecast'!E8*Assumptions!$H$13+'Sales Forecast'!D8*Assumptions!$I$13+577.5)*Assumptions!$C$18 | K20: =('Sales Forecast'!K8*Assumptions!$C$12+'Sales Forecast'!J8*Assumptions!$D$12+'Sales Forecast'!I8*Assumptions!$E$12+'Sales Forecast'!H8*Assumptions!$F$12+'Sales Forecast'!G8*Assumptions!$G$12+'Sales Forecast'!F8*Assumptions!$H$12+'Sales Forecast'!E8*Assumptions!$I$12+'Sales Forecast'!K8*Assumptions!$C$13+'Sales Forecast'!J8*Assumptions!$D$13+'Sales Forecast'!I8*Assumptions!$E$13+'Sales Forecast'!H8*Assumptions!$F$13+'Sales Forecast'!G8*Assumptions!$G$13+'Sales Forecast'!F8*Assumptions!$H$13+'Sales Forecast'!E8*Assumptions!$I$13+577.5)*Assumptions!$C$18 | L20: =('Sales Forecast'!L8*Assumptions!$C$12+'Sales Forecast'!K8*Assumptions!$D$12+'Sales Forecast'!J8*Assumptions!$E$12+'Sales Forecast'!I8*Assumptions!$F$12+'Sales Forecast'!H8*Assumptions!$G$12+'Sales Forecast'!G8*Assumptions!$H$12+'Sales Forecast'!F8*Assumptions!$I$12+'Sales Forecast'!L8*Assumptions!$C$13+'Sales Forecast'!K8*Assumptions!$D$13+'Sales Forecast'!J8*Assumptions!$E$13+'Sales Forecast'!I8*Assumptions!$F$13+'Sales Forecast'!H8*Assumptions!$G$13+'Sales Forecast'!G8*Assumptions!$H$13+'Sales Forecast'!F8*Assumptions!$I$13+577.5)*Assumptions!$C$18 | M20: =('Sales Forecast'!M8*Assumptions!$C$12+'Sales Forecast'!L8*Assumptions!$D$12+'Sales Forecast'!K8*Assumptions!$E$12+'Sales Forecast'!J8*Assumptions!$F$12+'Sales Forecast'!I8*Assumptions!$G$12+'Sales Forecast'!H8*Assumptions!$H$12+'Sales Forecast'!G8*Assumptions!$I$12+'Sales Forecast'!M8*Assumptions!$C$13+'Sales Forecast'!L8*Assumptions!$D$13+'Sales Forecast'!K8*Assumptions!$E$13+'Sales Forecast'!J8*Assumptions!$F$13+'Sales Forecast'!I8*Assumptions!$G$13+'Sales Forecast'!H8*Assumptions!$H$13+'Sales Forecast'!G8*Assumptions!$I$13+577.5)*Assumptions!$C$18 | N20: =('Sales Forecast'!N8*Assumptions!$C$12+'Sales Forecast'!M8*Assumptions!$D$12+'Sales Forecast'!L8*Assumptions!$E$12+'Sales Forecast'!K8*Assumptions!$F$12+'Sales Forecast'!J8*Assumptions!$G$12+'Sales Forecast'!I8*Assumptions!$H$12+'Sales Forecast'!H8*Assumptions!$I$12+'Sales Forecast'!N8*Assumptions!$C$13+'Sales Forecast'!M8*Assumptions!$D$13+'Sales Forecast'!L8*Assumptions!$E$13+'Sales Forecast'!K8*Assumptions!$F$13+'Sales Forecast'!J8*Assumptions!$G$13+'Sales Forecast'!I8*Assumptions!$H$13+'Sales Forecast'!H8*Assumptions!$I$13+577.5)*Assumptions!$C$18 | O20: =('Sales Forecast'!O8*Assumptions!$C$12+'Sales Forecast'!N8*Assumptions!$D$12+'Sales Forecast'!M8*Assumptions!$E$12+'Sales Forecast'!L8*Assumptions!$F$12+'Sales Forecast'!K8*Assumptions!$G$12+'Sales Forecast'!J8*Assumptions!$H$12+'Sales Forecast'!I8*Assumptions!$I$12+'Sales Forecast'!O8*Assumptions!$C$13+'Sales Forecast'!N8*Assumptions!$D$13+'Sales Forecast'!M8*Assumptions!$E$13+'Sales Forecast'!L8*Assumptions!$F$13+'Sales Forecast'!K8*Assumptions!$G$13+'Sales Forecast'!J8*Assumptions!$H$13+'Sales Forecast'!I8*Assumptions!$I$13+577.5)*Assumptions!$C$18 | P20: =('Sales Forecast'!P8*Assumptions!$C$12+'Sales Forecast'!O8*Assumptions!$D$12+'Sales Forecast'!N8*Assumptions!$E$12+'Sales Forecast'!M8*Assumptions!$F$12+'Sales Forecast'!L8*Assumptions!$G$12+'Sales Forecast'!K8*Assumptions!$H$12+'Sales Forecast'!J8*Assumptions!$I$12+'Sales Forecast'!P8*Assumptions!$C$13+'Sales Forecast'!O8*Assumptions!$D$13+'Sales Forecast'!N8*Assumptions!$E$13+'Sales Forecast'!M8*Assumptions!$F$13+'Sales Forecast'!L8*Assumptions!$G$13+'Sales Forecast'!K8*Assumptions!$H$13+'Sales Forecast'!J8*Assumptions!$I$13+577.5)*Assumptions!$C$18 | Q20: =('Sales Forecast'!Q8*Assumptions!$C$12+'Sales Forecast'!P8*Assumptions!$D$12+'Sales Forecast'!O8*Assumptions!$E$12+'Sales Forecast'!N8*Assumptions!$F$12+'Sales Forecast'!M8*Assumptions!$G$12+'Sales Forecast'!L8*Assumptions!$H$12+'Sales Forecast'!K8*Assumptions!$I$12+'Sales Forecast'!Q8*Assumptions!$C$13+'Sales Forecast'!P8*Assumptions!$D$13+'Sales Forecast'!O8*Assumptions!$E$13+'Sales Forecast'!N8*Assumptions!$F$13+'Sales Forecast'!M8*Assumptions!$G$13+'Sales Forecast'!L8*Assumptions!$H$13+'Sales Forecast'!K8*Assumptions!$I$13+577.5)*Assumptions!$C$18 | ... AM20: =('Sales Forecast'!AM8*Assumptions!$C$12+'Sales Forecast'!AL8*Assumptions!$D$12+'Sales Forecast'!AK8*Assumptions!$E$12+'Sales Forecast'!AJ8*Assumptions!$F$12+'Sales Forecast'!AI8*Assumptions!$G$12+'Sales Forecast'!AH8*Assumptions!$H$12+'Sales Forecast'!AG8*Assumptions!$I$12+'Sales Forecast'!AM8*Assumptions!$C$13+'Sales Forecast'!AL8*Assumptions!$D$13+'Sales Forecast'!AK8*Assumptions!$E$13+'Sales Forecast'!AJ8*Assumptions!$F$13+'Sales Forecast'!AI8*Assumptions!$G$13+'Sales Forecast'!AH8*Assumptions!$H$13+'Sales Forecast'!AG8*Assumptions!$I$13+577.5)*Assumptions!$C$18
B21: TOTAL REVENUE | D21: 20806.12 | E21: 20862.49 | F21: 23750.28 | G21: 21166.07 | H21: 19729.51 | I21: =I13+I17+I18+I19+I20 | J21: =J13+J17+J18+J19+J20 | K21: =K13+K17+K18+K19+K20 | L21: =L13+L17+L18+L19+L20 | M21: =M13+M17+M18+M19+M20 | N21: =N13+N17+N18+N19+N20 | O21: =O13+O17+O18+O19+O20 | P21: =P13+P17+P18+P19+P20 | ... AM21: =AM13+AM17+AM18+AM19+AM20
B22: COST OF GOODS SOLD
B23: 501000 Product Cost | D23: 384 | E23: 208 | F23: 264 | G23: 297 | H23: 163 | I23: =I21*Assumptions!$C$20 | J23: =J21*Assumptions!$C$20 | K23: =K21*Assumptions!$C$20 | L23: =L21*Assumptions!$C$20 | M23: =M21*Assumptions!$C$20 | N23: =N21*Assumptions!$C$20 | O23: =O21*Assumptions!$C$20 | P23: =P21*Assumptions!$C$20 | ... AM23: =AM21*Assumptions!$C$20
B24: 506000 Merchant Account Fees | D24: 678.49 | E24: 641.48 | F24: 475.8 | G24: 545.99 | H24: 360.62 | I24: =I21*Assumptions!$C$19 | J24: =J21*Assumptions!$C$19 | K24: =K21*Assumptions!$C$19 | L24: =L21*Assumptions!$C$19 | M24: =M21*Assumptions!$C$19 | N24: =N21*Assumptions!$C$19 | O24: =O21*Assumptions!$C$19 | P24: =P21*Assumptions!$C$19 | ... AM24: =AM21*Assumptions!$C$19
B25: Total Cost of Goods Sold | D25: 1062.49 | E25: 849.48 | F25: 739.8 | G25: 842.99 | H25: 523.62 | I25: =I23+I24 | J25: =J23+J24 | K25: =K23+K24 | L25: =L23+L24 | M25: =M23+M24 | N25: =N23+N24 | O25: =O23+O24 | P25: =P23+P24 | ... AM25: =AM23+AM24
B26: GROSS PROFIT | D26: 19743.63 | E26: 20013.01 | F26: 23010.48 | G26: 20323.08 | H26: 19205.89 | I26: =I21-I25 | J26: =J21-J25 | K26: =K21-K25 | L26: =L21-L25 | M26: =M21-M25 | N26: =N21-N25 | O26: =O21-O25 | P26: =P21-P25 | ... AM26: =AM21-AM25
B27: OPERATING EXPENSES
B28: 601001 Paid Ads | D28: 939 | E28: 119.9 | F28: 0 | G28: 0 | H28: 0 | I28: 287.6 | J28: 287.6 | K28: 287.6 | L28: 287.6 | M28: 287.6 | N28: 287.6 | O28: 287.6 | P28: 287.6 | Q28: 287.6 | R28: 287.6 | S28: 287.6 | T28: 287.6 | U28: 287.6 | V28: 287.6 | W28: 287.6 | X28: 287.6 | Y28: 287.6 | Z28: 287.6 | AA28: 287.6 | AB28: 287.6 | AC28: 287.6 | AD28: 287.6 | AE28: 287.6 | AF28: 287.6 | AG28: 287.6 | AH28: 287.6 | AI28: 287.6 | AJ28: 287.6 | AK28: 287.6 | AL28: 287.6 | AM28: 287.6
B29: 601005 Content Creation | D29: 0 | E29: 0 | F29: 0 | G29: 0 | H29: 0 | I29: 0 | J29: 0 | K29: 0 | L29: 0 | M29: 0 | N29: 0 | O29: 0 | P29: 0 | Q29: 0 | R29: 0 | S29: 0 | T29: 0 | U29: 0 | V29: 0 | W29: 0 | X29: 0 | Y29: 0 | Z29: 0 | AA29: 0 | AB29: 0 | AC29: 0 | AD29: 0 | AE29: 0 | AF29: 0 | AG29: 0 | AH29: 0 | AI29: 0 | AJ29: 0 | AK29: 0 | AL29: 0 | AM29: 0
B30: 601006 General Marketing | D30: 700 | E30: 700 | F30: 700 | G30: 700 | H30: 700 | I30: 760.49 | J30: 760.49 | K30: 760.49 | L30: 760.49 | M30: 760.49 | N30: 760.49 | O30: 760.49 | P30: 760.49 | Q30: 760.49 | R30: 760.49 | S30: 760.49 | T30: 760.49 | U30: 760.49 | V30: 760.49 | W30: 760.49 | X30: 760.49 | Y30: 760.49 | Z30: 760.49 | AA30: 760.49 | AB30: 760.49 | AC30: 760.49 | AD30: 760.49 | AE30: 760.49 | AF30: 760.49 | AG30: 760.49 | AH30: 760.49 | AI30: 760.49 | AJ30: 760.49 | AK30: 760.49 | AL30: 760.49 | AM30: 760.49
B31: 601007 Contractors/Agencies | D31: 0 | E31: 0 | F31: 0 | G31: 0 | H31: 0 | I31: 0 | J31: 0 | K31: 0 | L31: 0 | M31: 0 | N31: 0 | O31: 0 | P31: 0 | Q31: 0 | R31: 0 | S31: 0 | T31: 0 | U31: 0 | V31: 0 | W31: 0 | X31: 0 | Y31: 0 | Z31: 0 | AA31: 0 | AB31: 0 | AC31: 0 | AD31: 0 | AE31: 0 | AF31: 0 | AG31: 0 | AH31: 0 | AI31: 0 | AJ31: 0 | AK31: 0 | AL31: 0 | AM31: 0
B32: 601010 Website Development | D32: 0 | E32: 0 | F32: 0 | G32: 0 | H32: 0 | I32: 0 | J32: 0 | K32: 0 | L32: 0 | M32: 0 | N32: 0 | O32: 0 | P32: 0 | Q32: 0 | R32: 0 | S32: 0 | T32: 0 | U32: 0 | V32: 0 | W32: 0 | X32: 0 | Y32: 0 | Z32: 0 | AA32: 0 | AB32: 0 | AC32: 0 | AD32: 0 | AE32: 0 | AF32: 0 | AG32: 0 | AH32: 0 | AI32: 0 | AJ32: 0 | AK32: 0 | AL32: 0 | AM32: 0
B33: Total Marketing | D33: 1639 | E33: 819.9 | F33: 700 | G33: 700 | H33: 700 | I33: =I28+I29+I30+I31+I32 | J33: =J28+J29+J30+J31+J32 | K33: =K28+K29+K30+K31+K32 | L33: =L28+L29+L30+L31+L32 | M33: =M28+M29+M30+M31+M32 | N33: =N28+N29+N30+N31+N32 | O33: =O28+O29+O30+O31+O32 | P33: =P28+P29+P30+P31+P32 | ... AM33: =AM28+AM29+AM30+AM31+AM32
B34: 602001 Wages | D34: 12689.22 | E34: 11932.17 | F34: 13130.37 | G34: 12113.96 | H34: 12729.83 | I34: 14097.87 | J34: 20824.18 | K34: 20862.76 | L34: 20848.92 | M34: 20850.98 | N34: 20858.7 | O34: 20862.69 | P34: 20863.38 | Q34: 20890.63 | R34: 20901.89 | S34: 20921.93 | T34: 20929.06 | U34: 20948.05 | V34: 20955.14 | W34: 20957.11 | X34: 20974.16 | Y34: 20981.24 | Z34: 20983.16 | AA34: 20983.22 | AB34: 20863.38 | AC34: 20890.63 | AD34: 20901.89 | AE34: 20921.93 | AF34: 20929.06 | AG34: 20948.05 | AH34: 20955.14 | AI34: 20957.11 | AJ34: 20974.16 | AK34: 20981.24 | AL34: 20983.16 | AM34: 20983.22
B35: 602004 Payroll Taxes | D35: 2561.18 | E35: 1437.75 | F35: 1373.4 | G35: 1235.26 | H35: 1196.14 | I35: 1868.08 | J35: 2759.36 | K35: 2764.48 | L35: 2762.64 | M35: 2762.91 | N35: 2763.94 | O35: 2764.47 | P35: 2764.56 | Q35: 2768.17 | R35: 2769.66 | S35: 2772.32 | T35: 2773.26 | U35: 2775.78 | V35: 2776.72 | W35: 2776.98 | X35: 2779.24 | Y35: 2780.18 | Z35: 2780.43 | AA35: 2780.44 | AB35: 2764.56 | AC35: 2768.17 | AD35: 2769.66 | AE35: 2772.32 | AF35: 2773.26 | AG35: 2775.78 | AH35: 2776.72 | AI35: 2776.98 | AJ35: 2779.24 | AK35: 2780.18 | AL35: 2780.43 | AM35: 2780.44
B36: 602005 Employee Benefits | D36: 40 | E36: 80 | F36: 62 | G36: 0 | H36: 0 | I36: 51.45 | J36: 76 | K36: 76.14 | L36: 76.09 | M36: 76.1 | N36: 76.13 | O36: 76.14 | P36: 76.15 | Q36: 76.25 | R36: 76.29 | S36: 76.36 | T36: 76.39 | U36: 76.46 | V36: 76.48 | W36: 76.49 | X36: 76.55 | Y36: 76.58 | Z36: 76.58 | AA36: 76.58 | AB36: 76.15 | AC36: 76.25 | AD36: 76.29 | AE36: 76.36 | AF36: 76.39 | AG36: 76.46 | AH36: 76.48 | AI36: 76.49 | AJ36: 76.55 | AK36: 76.58 | AL36: 76.58 | AM36: 76.58
B37: 602010 Payroll Processing Fees | D37: 587.32 | E37: 571.91 | F37: 844.86 | G37: 562.35 | H37: 567 | I37: 725.58 | J37: 1071.76 | K37: 1073.74 | L37: 1073.03 | M37: 1073.14 | N37: 1073.54 | O37: 1073.74 | P37: 1073.78 | Q37: 1075.18 | R37: 1075.76 | S37: 1076.79 | T37: 1077.16 | U37: 1078.13 | V37: 1078.5 | W37: 1078.6 | X37: 1079.48 | Y37: 1079.84 | Z37: 1079.94 | AA37: 1079.94 | AB37: 1073.78 | AC37: 1075.18 | AD37: 1075.76 | AE37: 1076.79 | AF37: 1077.16 | AG37: 1078.13 | AH37: 1078.5 | AI37: 1078.6 | AJ37: 1079.48 | AK37: 1079.84 | AL37: 1079.94 | AM37: 1079.94
B38: Total Payroll | D38: 15877.72 | E38: 14021.83 | F38: 15410.63 | G38: 13911.57 | H38: 14492.97 | I38: =I34+I35+I36+I37 | J38: =J34+J35+J36+J37 | K38: =K34+K35+K36+K37 | L38: =L34+L35+L36+L37 | M38: =M34+M35+M36+M37 | N38: =N34+N35+N36+N37 | O38: =O34+O35+O36+O37 | P38: =P34+P35+P36+P37 | ... AM38: =AM34+AM35+AM36+AM37
B39: 603000 Software & Web Services | D39: 723.09 | E39: 1181.45 | F39: 723.09 | G39: 748.27 | H39: 748.27 | I39: 654.75 | J39: 654.75 | K39: 654.75 | L39: 654.75 | M39: 654.75 | N39: 654.75 | O39: 654.75 | P39: 654.75 | Q39: 654.75 | R39: 654.75 | S39: 654.75 | T39: 654.75 | U39: 654.75 | V39: 654.75 | W39: 654.75 | X39: 654.75 | Y39: 654.75 | Z39: 654.75 | AA39: 654.75 | AB39: 654.75 | AC39: 654.75 | AD39: 654.75 | AE39: 654.75 | AF39: 654.75 | AG39: 654.75 | AH39: 654.75 | AI39: 654.75 | AJ39: 654.75 | AK39: 654.75 | AL39: 654.75 | AM39: 654.75
B40: 608000 Insurance | D40: 322.57 | E40: 322.57 | F40: 500.79 | G40: 302.12 | H40: 298.04 | I40: 280.85 | J40: 280.85 | K40: 280.85 | L40: 280.85 | M40: 280.85 | N40: 280.85 | O40: 280.85 | P40: 280.85 | Q40: 280.85 | R40: 280.85 | S40: 280.85 | T40: 280.85 | U40: 280.85 | V40: 280.85 | W40: 280.85 | X40: 280.85 | Y40: 280.85 | Z40: 280.85 | AA40: 280.85 | AB40: 280.85 | AC40: 280.85 | AD40: 280.85 | AE40: 280.85 | AF40: 280.85 | AG40: 280.85 | AH40: 280.85 | AI40: 280.85 | AJ40: 280.85 | AK40: 280.85 | AL40: 280.85 | AM40: 280.85
B41: 610000 Office Supplies | D41: 87.8 | E41: 146.81 | F41: 633.64 | G41: 151.95 | H41: 0 | I41: 197.87 | J41: 197.87 | K41: 197.87 | L41: 197.87 | M41: 197.87 | N41: 197.87 | O41: 197.87 | P41: 197.87 | Q41: 197.87 | R41: 197.87 | S41: 197.87 | T41: 197.87 | U41: 197.87 | V41: 197.87 | W41: 197.87 | X41: 197.87 | Y41: 197.87 | Z41: 197.87 | AA41: 197.87 | AB41: 197.87 | AC41: 197.87 | AD41: 197.87 | AE41: 197.87 | AF41: 197.87 | AG41: 197.87 | AH41: 197.87 | AI41: 197.87 | AJ41: 197.87 | AK41: 197.87 | AL41: 197.87 | AM41: 197.87
B42: Total Software & Admin | D42: =D39+D40+D41 | E42: =E39+E40+E41 | F42: =F39+F40+F41 | G42: =G39+G40+G41 | H42: =H39+H40+H41 | I42: =I39+I40+I41 | J42: =J39+J40+J41 | K42: =K39+K40+K41 | ... AM42: =AM39+AM40+AM41
B43: 604100 Legal Fees | D43: 0 | E43: 0 | F43: 0 | G43: 0 | H43: 0 | I43: 0 | J43: 0 | K43: 0 | L43: 0 | M43: 0 | N43: 0 | O43: 0 | P43: 0 | Q43: 0 | R43: 0 | S43: 0 | T43: 0 | U43: 0 | V43: 0 | W43: 0 | X43: 0 | Y43: 0 | Z43: 0 | AA43: 0 | AB43: 0 | AC43: 0 | AD43: 0 | AE43: 0 | AF43: 0 | AG43: 0 | AH43: 0 | AI43: 0 | AJ43: 0 | AK43: 0 | AL43: 0 | AM43: 0
B44: 604200 Accounting | D44: 0 | E44: 301.82 | F44: 0 | G44: 0 | H44: 1116.82 | I44: 65.83 | J44: 65.83 | K44: 65.83 | L44: 65.83 | M44: 65.83 | N44: 65.83 | O44: 65.83 | P44: 65.83 | Q44: 65.83 | R44: 65.83 | S44: 65.83 | T44: 65.83 | U44: 65.83 | V44: 65.83 | W44: 65.83 | X44: 65.83 | Y44: 65.83 | Z44: 65.83 | AA44: 65.83 | AB44: 65.83 | AC44: 65.83 | AD44: 65.83 | AE44: 65.83 | AF44: 65.83 | AG44: 65.83 | AH44: 65.83 | AI44: 65.83 | AJ44: 65.83 | AK44: 65.83 | AL44: 65.83 | AM44: 65.83
B45: 604300 Recruiting | D45: 0 | E45: 0 | F45: 0 | G45: 0 | H45: 0 | I45: 0 | J45: 0 | K45: 0 | L45: 0 | M45: 0 | N45: 0 | O45: 0 | P45: 0 | Q45: 0 | R45: 0 | S45: 0 | T45: 0 | U45: 0 | V45: 0 | W45: 0 | X45: 0 | Y45: 0 | Z45: 0 | AA45: 0 | AB45: 0 | AC45: 0 | AD45: 0 | AE45: 0 | AF45: 0 | AG45: 0 | AH45: 0 | AI45: 0 | AJ45: 0 | AK45: 0 | AL45: 0 | AM45: 0
B46: 604400 Other Professional Fees | D46: 516 | E46: 516 | F46: 516 | G46: 516 | H46: 516 | I46: 450.17 | J46: 450.17 | K46: 450.17 | L46: 450.17 | M46: 450.17 | N46: 450.17 | O46: 450.17 | P46: 450.17 | Q46: 450.17 | R46: 450.17 | S46: 450.17 | T46: 450.17 | U46: 450.17 | V46: 450.17 | W46: 450.17 | X46: 450.17 | Y46: 450.17 | Z46: 450.17 | AA46: 450.17 | AB46: 450.17 | AC46: 450.17 | AD46: 450.17 | AE46: 450.17 | AF46: 450.17 | AG46: 450.17 | AH46: 450.17 | AI46: 450.17 | AJ46: 450.17 | AK46: 450.17 | AL46: 450.17 | AM46: 450.17
B47: Total Professional Fees | D47: 516 | E47: 817.82 | F47: 516 | G47: 516 | H47: 1632.82 | I47: =I43+I44+I45+I46 | J47: =J43+J44+J45+J46 | K47: =K43+K44+K45+K46 | L47: =L43+L44+L45+L46 | M47: =M43+M44+M45+M46 | N47: =N43+N44+N45+N46 | O47: =O43+O44+O45+O46 | P47: =P43+P44+P45+P46 | ... AM47: =AM43+AM44+AM45+AM46
B48: 605000 Travel | D48: 0 | E48: 0 | F48: 0 | G48: 0 | H48: 0 | I48: 0 | J48: 0 | K48: 0 | L48: 0 | M48: 0 | N48: 0 | O48: 0 | P48: 0 | Q48: 0 | R48: 0 | S48: 0 | T48: 0 | U48: 0 | V48: 0 | W48: 0 | X48: 0 | Y48: 0 | Z48: 0 | AA48: 0 | AB48: 0 | AC48: 0 | AD48: 0 | AE48: 0 | AF48: 0 | AG48: 0 | AH48: 0 | AI48: 0 | AJ48: 0 | AK48: 0 | AL48: 0 | AM48: 0
B49: 606000 Meals | D49: 0 | E49: 0 | F49: 0 | G49: 0 | H49: 32.84 | I49: 0 | J49: 0 | K49: 0 | L49: 0 | M49: 0 | N49: 0 | O49: 0 | P49: 0 | Q49: 0 | R49: 0 | S49: 0 | T49: 0 | U49: 0 | V49: 0 | W49: 0 | X49: 0 | Y49: 0 | Z49: 0 | AA49: 0 | AB49: 0 | AC49: 0 | AD49: 0 | AE49: 0 | AF49: 0 | AG49: 0 | AH49: 0 | AI49: 0 | AJ49: 0 | AK49: 0 | AL49: 0 | AM49: 0
B50: Total Travel & Meals | D50: =D48+D49 | E50: =E48+E49 | F50: =F48+F49 | G50: =G48+G49 | H50: =H48+H49 | I50: =I48+I49 | J50: =J48+J49 | K50: =K48+K49 | ... AM50: =AM48+AM49
B51: 616001 Electricity | D51: 116.98 | E51: 105 | F51: 139.04 | G51: 83.53 | H51: 124.29 | I51: 112.01 | J51: 112.01 | K51: 112.01 | L51: 112.01 | M51: 112.01 | N51: 112.01 | O51: 112.01 | P51: 112.01 | Q51: 112.01 | R51: 112.01 | S51: 112.01 | T51: 112.01 | U51: 112.01 | V51: 112.01 | W51: 112.01 | X51: 112.01 | Y51: 112.01 | Z51: 112.01 | AA51: 112.01 | AB51: 112.01 | AC51: 112.01 | AD51: 112.01 | AE51: 112.01 | AF51: 112.01 | AG51: 112.01 | AH51: 112.01 | AI51: 112.01 | AJ51: 112.01 | AK51: 112.01 | AL51: 112.01 | AM51: 112.01
B52: 616002 Internet & TV | D52: 165.39 | E52: 165.39 | F52: 165.39 | G52: 165.39 | H52: 0 | I52: 166.69 | J52: 166.69 | K52: 166.69 | L52: 166.69 | M52: 166.69 | N52: 166.69 | O52: 166.69 | P52: 166.69 | Q52: 166.69 | R52: 166.69 | S52: 166.69 | T52: 166.69 | U52: 166.69 | V52: 166.69 | W52: 166.69 | X52: 166.69 | Y52: 166.69 | Z52: 166.69 | AA52: 166.69 | AB52: 166.69 | AC52: 166.69 | AD52: 166.69 | AE52: 166.69 | AF52: 166.69 | AG52: 166.69 | AH52: 166.69 | AI52: 166.69 | AJ52: 166.69 | AK52: 166.69 | AL52: 166.69 | AM52: 166.69
B53: 616003 Phone service | D53: 108.06 | E53: 108.04 | F53: 108 | G53: 108.01 | H53: 108 | I53: 108.88 | J53: 108.88 | K53: 108.88 | L53: 108.88 | M53: 108.88 | N53: 108.88 | O53: 108.88 | P53: 108.88 | Q53: 108.88 | R53: 108.88 | S53: 108.88 | T53: 108.88 | U53: 108.88 | V53: 108.88 | W53: 108.88 | X53: 108.88 | Y53: 108.88 | Z53: 108.88 | AA53: 108.88 | AB53: 108.88 | AC53: 108.88 | AD53: 108.88 | AE53: 108.88 | AF53: 108.88 | AG53: 108.88 | AH53: 108.88 | AI53: 108.88 | AJ53: 108.88 | AK53: 108.88 | AL53: 108.88 | AM53: 108.88
B54: 616004 Water & sewer | D54: 0 | E54: 0 | F54: 0 | G54: 0 | H54: 0 | I54: 0 | J54: 0 | K54: 0 | L54: 0 | M54: 0 | N54: 0 | O54: 0 | P54: 0 | Q54: 0 | R54: 0 | S54: 0 | T54: 0 | U54: 0 | V54: 0 | W54: 0 | X54: 0 | Y54: 0 | Z54: 0 | AA54: 0 | AB54: 0 | AC54: 0 | AD54: 0 | AE54: 0 | AF54: 0 | AG54: 0 | AH54: 0 | AI54: 0 | AJ54: 0 | AK54: 0 | AL54: 0 | AM54: 0
B55: 616005 Disposal Services | D55: 362.25 | E55: 362.25 | F55: 362.25 | G55: 362.25 | H55: 362.25 | I55: 365.1 | J55: 365.1 | K55: 365.1 | L55: 365.1 | M55: 365.1 | N55: 365.1 | O55: 365.1 | P55: 365.1 | Q55: 365.1 | R55: 365.1 | S55: 365.1 | T55: 365.1 | U55: 365.1 | V55: 365.1 | W55: 365.1 | X55: 365.1 | Y55: 365.1 | Z55: 365.1 | AA55: 365.1 | AB55: 365.1 | AC55: 365.1 | AD55: 365.1 | AE55: 365.1 | AF55: 365.1 | AG55: 365.1 | AH55: 365.1 | AI55: 365.1 | AJ55: 365.1 | AK55: 365.1 | AL55: 365.1 | AM55: 365.1
B56: Total Utilities | D56: 752.68 | E56: 740.68 | F56: 774.68 | G56: 719.18 | H56: 759.93 | I56: =I51+I52+I53+I54+I55 | J56: =J51+J52+J53+J54+J55 | K56: =K51+K52+K53+K54+K55 | L56: =L51+L52+L53+L54+L55 | M56: =M51+M52+M53+M54+M55 | N56: =N51+N52+N53+N54+N55 | O56: =O51+O52+O53+O54+O55 | P56: =P51+P52+P53+P54+P55 | ... AM56: =AM51+AM52+AM53+AM54+AM55
