Workbook

Sheet Company Prepared Model>>>

Sheet Sources and Uses
B2: NOTE: Model assumes transaction closes on August 1, 2026
B4: Entry Valuation
B6: EBITDA Multiple | C6: 5.5
B7: LTM May 2026 Studio Level EBITDA | C7: =SUM(Summary!BF24:BF35)
B8: Pre Money TEV | C8: =C7*C6
B10: Sources and Uses
B11: Uses
B12: Pre Money TEV | C12: =C8
B13: Existing Debt Paydown (at August 2026) | C13: ='Cash, Debt & Equity'!W26
B14: New Studio Build (in Jan 2027) | C14: =-'Cash Flow Forecast (w prototype'!AB26
B15: Cash on balance sheet for working capital | C15: =C18-SUM(C12,C17,C16,C13,C14)
B16: Legal Fees | C16: 50000
B17: Financing Fees (2% of raise) | C17: =D17*C21 | D17: 0.02 | E17: <<< Fee
B18: Total Uses | C18: =C23
B20: Sources
B21: New Debt (leasehold, certain amount covers losses) | C21: 1650000 | D21: 0.1 | E21: <<< Cash Interest, paid monthly
B22: Management Rollover | C22: =C12
B23: Total Uses | C23: =SUM(C21:C22)
B25: Debt Service Coverage Metrics
C26: LTM May 2026 | D26: 2026 | E26: =D26+1 | F26: =E26+1
B27: ='Cash Flow Forecast (w prototype'!B55 | C27: ='Cash Flow Forecast (w prototype'!BF55 | D27: ='Cash Flow Forecast (w prototype'!BB55 | E27: ='Cash Flow Forecast (w prototype'!BC55 | F27: ='Cash Flow Forecast (w prototype'!BD55
B28: ='Cash Flow Forecast (w prototype'!B56 | C28: ='Cash Flow Forecast (w prototype'!BF56 | D28: ='Cash Flow Forecast (w prototype'!BB56 | E28: ='Cash Flow Forecast (w prototype'!BC56 | F28: ='Cash Flow Forecast (w prototype'!BD56
B29: ='Cash Flow Forecast (w prototype'!B57 | C29: ='Cash Flow Forecast (w prototype'!BF57 | D29: ='Cash Flow Forecast (w prototype'!BB57 | E29: ='Cash Flow Forecast (w prototype'!BC57 | F29: ='Cash Flow Forecast (w prototype'!BD57
B30: ='Cash Flow Forecast (w prototype'!B58 | C30: ='Cash Flow Forecast (w prototype'!BF58 | D30: =IFERROR('Cash Flow Forecast (w prototype'!BB58,"NA") | E30: ='Cash Flow Forecast (w prototype'!BC58 | F30: ='Cash Flow Forecast (w prototype'!BD58

Sheet Charts
B2: Consolidated Revenue
C3: 2025 | D3: =C3+1 | E3: =D3+1 | F3: =E3+1
C4: =Summary!BA6 | D4: =Summary!BB6 | E4: =Summary!BC6 | F4: =Summary!BD6
B6: Consolidated Studio Level EBITDA
C7: 2025 | D7: =C7+1 | E7: =D7+1 | F7: =E7+1
C8: =Summary!BA39 | D8: =Summary!BB39 | E8: =Summary!BC39 | F8: =Summary!BD39
B11: Consolidated Adjusted EBITDA, Post Corp Overhead
C12: 2025 | D12: =C12+1 | E12: =D12+1 | F12: =E12+1
C13: =Summary!BA59 | D13: =Summary!BB59 | E13: =Summary!BC59 | F13: =Summary!BD59
B16: Consolidated EBITDA, Post Corp Overhead
C17: 2025 | D17: =C17+1 | E17: =D17+1 | F17: =E17+1
C18: =Summary!BA41 | D18: =Summary!BB41 | E18: =Summary!BC41 | F18: =Summary!BD41
B33: Studio By Studio Revenue, Monthly Roll Up
B35: Jan 2025 | C35: Feb 2025 | D35: March 2025 | E35: April 2025 | F35: May 2025 | G35: Jun 2025 | H35: Jul 2025 | I35: Aug 2025 | J35: Sep 2025 | K35: Oct 2025 | L35: Nov 2025 | M35: Dec 2025 | N35: Jan 2026 | O35: Feb 2026 | P35: Mar 2026 | Q35: Apr 2026 | R35: May 2026
A36: =Summary!C7 | B36: =Summary!D7 | C36: =Summary!E7 | D36: =Summary!F7 | E36: =Summary!G7 | F36: =Summary!H7 | G36: =Summary!I7 | H36: =Summary!J7 | ... R36: =Summary!T7
A37: =Summary!C8 | B37: =Summary!D8 | C37: =Summary!E8 | D37: =Summary!F8 | E37: =Summary!G8 | F37: =Summary!H8 | G37: =Summary!I8 | H37: =Summary!J8 | ... R37: =Summary!T8
A38: =Summary!C9 | B38: =Summary!D9 | C38: =Summary!E9 | D38: =Summary!F9 | E38: =Summary!G9 | F38: =Summary!H9 | G38: =Summary!I9 | H38: =Summary!J9 | ... R38: =Summary!T9
A39: =Summary!C10 | B39: =Summary!D10 | C39: =Summary!E10 | D39: =Summary!F10 | E39: =Summary!G10 | F39: =Summary!H10 | G39: =Summary!I10 | H39: =Summary!J10 | ... R39: =Summary!T10
A40: =Summary!C11 | B40: =Summary!D11 | C40: =Summary!E11 | D40: =Summary!F11 | E40: =Summary!G11 | F40: =Summary!H11 | G40: =Summary!I11 | H40: =Summary!J11 | ... R40: =Summary!T11
A41: =Summary!C12 | B41: =Summary!D12 | C41: =Summary!E12 | D41: =Summary!F12 | E41: =Summary!G12 | F41: =Summary!H12 | G41: =Summary!I12 | H41: =Summary!J12 | ... R41: =Summary!T12
A42: =Summary!C13 | B42: =Summary!D13 | C42: =Summary!E13 | D42: =Summary!F13 | E42: =Summary!G13 | F42: =Summary!H13 | G42: =Summary!I13 | H42: =Summary!J13 | ... R42: =Summary!T13
A43: =Summary!C14 | B43: =Summary!D14 | C43: =Summary!E14 | D43: =Summary!F14 | E43: =Summary!G14 | F43: =Summary!H14 | G43: =Summary!I14 | H43: =Summary!J14 | ... R43: =Summary!T14
A44: =Summary!C15 | B44: =Summary!D15 | C44: =Summary!E15 | D44: =Summary!F15 | E44: =Summary!G15 | F44: =Summary!H15 | G44: =Summary!I15 | H44: =Summary!J15 | ... R44: =Summary!T15
A45: =Summary!C16 | B45: =Summary!D16 | C45: =Summary!E16 | D45: =Summary!F16 | E45: =Summary!G16 | F45: =Summary!H16 | G45: =Summary!I16 | H45: =Summary!J16 | ... R45: =Summary!T16
A46: =Summary!C17 | B46: =Summary!D17 | C46: =Summary!E17 | D46: =Summary!F17 | E46: =Summary!G17 | F46: =Summary!H17 | G46: =Summary!I17 | H46: =Summary!J17 | ... R46: =Summary!T17
A47: =Summary!C18 | B47: =Summary!D18 | C47: =Summary!E18 | D47: =Summary!F18 | E47: =Summary!G18 | F47: =Summary!H18 | G47: =Summary!I18 | H47: =Summary!J18 | ... R47: =Summary!T18
B50: Revenue Segement Breakdown
A51: Berkeley
A52: Culver City
A53: Danville
A54: Lafayette
A55: Marin
A56: Ocean Park
A57: Presidio Heights
A58: Russian Hill
A59: Santa Barbara
A60: Santa Monica
A61: West Portal
A62: Westwood

Sheet Financials Commentary
C3: Cash Sales vs. Accrual (Earned) Revenue — how to read the two revenue lines in the model
C4: Sales Forecast & Summary tabs show CASH SALES — the total dollar value of packs, memberships, and workshops purchased at the MindBody / ClassPass / GymPass point-of-sale in the period. This is the operating KPI.
C5: Studio P&L, All Studios, and Consolidated P&L show ACCRUAL (GAAP) REVENUE — Sessions recognized over the package usage window + Breakage on expired unused packages − Refunds − Discounts. This is what shows up on the P&L / EBITDA line.
C6: They diverge in any given month by design. A pack sold in June is booked as cash sales in June but recognized as P&L revenue across the months a member actually uses it (or when it expires).
C9: Presidio Heights and Marina historical results
C10: Presidio Heights and Marina historical results are not directly comparable due to a system migration in April 2025. Prior to April 2025, both physical locations were tracked as a single studio (Presidio Heights) in MindBody. Beginning in April 2025, the locations were separated into two distinct studios, creating a reporting discontinuity in the historical results.

Sheet Cover
B2: Mighty Pilates
B3: Financial Model
B5: Last refreshed: June 23, 2026 | C5: 2026-08-24
B7: Tab Guide
B9: Summary & Controls | C9: Top-level KPIs, studio sales & EBITDA tables, charts
B10: Assumptions | C10: All model inputs: OpEx, sales forecast, rev rec curves, loan terms
B11: Cash Flow Forecast | C11: Monthly cash flow from operations + investing + financing
B12: P&L Summary | C12: Consolidated monthly P&L (Revenue → EBITDA)
B13: P&L Detail | C13: Account-level P&L matching accountant chart of accounts
B14: All Studios Summary | C14: Side-by-side studio comparison
B15: [Studio] FCST (×12) | C15: Per-studio P&L forecast (BK, CC, DN, LF, MR, OP, PH, RH, SB, SM, WP, WW)
B16: Cash, Debt & Equity | C16: Balance sheet, loan amortization schedules, equity tracking
B17: Sales Forecast | C17: Studio × month editable sales grid
B18: CapEx | C18: Capital expenditure project schedule
B19: QBO Actuals | C19: Historical accountant-booked P&L, BS, SCF (read-only)
B22: Conventions
B24: Yellow cells = inputs (edit these)
B25: Light green cells = actuals (closed months, do not edit)

Sheet Read Me
B2: Read Me — Model Architecture
B3: Last refreshed: June 23, 2026
B5: Tab Roles
B6: Summary & Controls | C6: Top-level dashboard. Sales + EBITDA by studio. Total EBITDA references P&L NOI directly.
B7: Assumptions | C7: Editable global parameters: rev rec curves, refund/discount/COGS rates, escalations, loan terms.
B8: Sales Forecast | C8: Per-studio × month sales grid. EDITABLE for forecast months (yellow). Drives revenue formulas. Hidden rows 101-113 hold 2025 history for lag formulas — do not delete.
B9: Cash, Debt & Equity | C9: Loan amortization schedule + debt service forecast.
B10: Cash Flow Forecast | C10: Monthly CF with operating/investing/financing.
B11: P&L (Consolidated) | C11: Consolidated monthly P&L. Revenue/COGS use direct lag formulas (with 2025 history). OpEx rows = SUM(per-studio) + HO + HO Other.
B12: All Studios Summary | C12: Side-by-side studio comparison.
B13: [Code] P&L (×12) | C13: Per-studio P&L: BK, CC, DN, LF, MR, OP, PH, RH, SB, SM, WP, WW. OpEx leaves are HARDCODED values (editable) summing to per-studio override. Revenue formulas use per-studio lag (2026+ from Sales Forecast, 2025 from hidden helper rows 102-113).
B14: HO P&L | C14: Head Office overhead (no revenue). Same leaf-summing structure. NOI is negative (= -Total OpEx).
B15: CapEx | C15: Project schedule (empty — add projects to populate Investing rows on CF).
B16: QBO Actuals | C16: Raw accountant-booked P&L/BS/SCF data. Read-only reference.
B18: Cell Conventions
B19: Yellow fill (FFFF99) | C19: EDITABLE input cell. Cat can change these.
B20: Light green fill | C20: Hardcoded actual from QBO/accountant. Do not edit (would diverge from source data).
B21: White/no fill | C21: Formula cell. Computed from other cells.
B22: Light blue fill | C22: Subtotal or total row.
B23: Bold green fill | C23: Key KPI (EBITDA, ending cash).
B25: Value Flow
B26: Sales edit | C26: Edit Sales Forecast cell → flows to: Studio P&L Sessions/Breakage (via lag formula) → Studio NOI → Summary & Controls studio row → Sales Forecast TOTAL row → Consolidated P&L revenue → Consolidated NOI → Summary & Controls Total EBITDA.
B27: OpEx leaf edit | C27: Edit per-studio OpEx leaf (e.g., BK Paid Ads) → Studio Marketing subtotal (=SUM leaves) → Studio Total OpEx → Studio NOI → Summary & Controls studio row → Consolidated P&L Marketing (=SUM studios + HO) → Consolidated Total OpEx → Consolidated NOI → Summary & Controls Total EBITDA. Full propagation works.
B28: Assumption edit | C28: Edit rate on Assumptions tab (refund %, discount %, escalation, etc.) → flows through all formulas referencing that cell.
B30: Hidden Helpers — DO NOT DELETE
B31: Sales Forecast rows 100-113 | C31: Hidden helper rows holding 2025 monthly sales (consolidated row 101 and per-studio rows 102-113). Required for 7-month lag formulas on Session/Breakage Revenue forecasts for May 2026 and Jun 2026.
B32: Sales Forecast row ~50+ | C32: Helper for chart data references on Summary & Controls. Removing breaks charts.
B34: Monthly Update Procedure (when QBO closes new month)
B35: Step 1 | C35: Upload new QBO export to Streamlit dashboard. Streamlit's committed_actuals.json gets updated.
B36: Step 2 | C36: Run refresh_from_streamlit.py (in /Users/chandlerclemons/financial-modeling/models/mighty/).
B37: Step 3 | C37: Refresh script will: (a) extend actuals columns by 1 month, (b) shift forecast forward, (c) refresh trailing-3-month avg lines (Taxes Paid, Property Taxes, Retail, Depreciation), (d) update 2025 helper row values if Streamlit data changed historicals.
B38: Step 4 | C38: Open the Excel and spot-check the new actuals column vs Streamlit. Save & share with stakeholders.
B41: Cash Sales vs Accrual Revenue
B42: Sales Forecast / Summary | C42: These tabs show CASH SALES: Total Sales captured at the MindBody/ClassPass/GymPass point-of-sale when a member buys a class pack, membership, or workshop.
B43: Studio P&L / All Studios | C43: These tabs show ACCRUAL P&L REVENUE: Sessions recognized over the package usage window + Breakage when unused packages expire − Refunds − Discounts.
B44: Reconciliation horizon | C44: These metrics diverge in any individual month by design. They reconcile only over the full lifecycle of a cohort of packages (typically 6-12 months from purchase).
B45: Both are correct | C45: Cash Sales is the operating KPI (Total cash value of sales in period). Accrual Revenue is the GAAP P&L line (what's earned).
B47: Why hardcoded | C47: Property Tax on consolidated P&L row 26 is kept as a hardcoded forecast value rather than linked to individual P&L tabs because the QBO source booked property tax at corporate (Norbrook) level, not per-studio. Studio P&L row 68 ('903000 Property taxes') is $0 in actuals.
B48: Forecast basis | C48: Forecast value $4178.19/mo = 2025 actual annual Property Taxes ($50,138.23) / 12. Conservative assumption that 2026 onwards will run at the same rate.
B50: Categories tracked | C50: The consolidated P&L tracks 7 OpEx categories: Marketing (r14), Payroll (r15), Software & Admin (r16), Professional Fees (r17), Utilities (r18), Property Costs (r19), Travel & Meals (r20).
B51: Categories NOT separately tracked | C51: The accountant's actuals include a handful of smaller categories the model doesn't break out: 610100 Furniture & Equipment, 611000 Shipping & postage, 613000 Bank fees (corporate), 615000 Parking Lot Rental, 609000 Business licenses, 607000 Entertainment. Combined ~$5-10K/month.
B53: Why 2025 is hardcoded from QBO | C53: 2025 consolidated P&L values are pulled directly from the QBO 2025 financial package (Mighty Pilates_Financials_2025_062326.xlsx) to guarantee tie-out to accountant.
B54: Where Old Mighty Revenue lives | C54: QBO has a 402000 Revenue from Old Mighty line ($440K in 2025, tailing from $180K Jan to $1K Dec). It is absorbed into r6 Session Revenue for 2025 (no separate row). For 2026+ it is $0.

Sheet Summary
B2: Summary & Controls
B3: Top-level dashboard. Studio sales, EBITDA, YoY summary, charts.
B4: Monthly Total Session Sales by Studio
B5: Metric | C5: Studio | D5: Jan 2025 (A) | E5: Feb 2025 (A) | F5: Mar 2025 (A) | G5: Apr 2025 (A) | H5: May 2025 (A) | I5: Jun 2025 (A) | J5: Jul 2025 (A) | K5: Aug 2025 (A) | L5: Sep 2025 (A) | M5: Oct 2025 (A) | N5: Nov 2025 (A) | O5: Dec 2025 (A) | P5: Jan 2026 (A) | Q5: Feb 2026 (A) | R5: Mar 2026 (A) | S5: Apr 2026 (A) | T5: May 2026 (A) | U5: June 2026 (A) | V5: Jul 2026 | W5: Aug 2026 | X5: Sep 2026 | Y5: Oct 2026 | Z5: Nov 2026 | AA5: Dec 2026 | AB5: Jan 2027 | AC5: Feb 2027 | AD5: Mar 2027 | AE5: Apr 2027 | AF5: May 2027 | AG5: Jun 2027 | AH5: Jul 2027 | AI5: Aug 2027 | AJ5: Sep 2027 | AK5: Oct 2027 | AL5: Nov 2027 | AM5: Dec 2027 | AN5: Jan 2028 | AO5: Feb 2028 | AP5: Mar 2028 | AQ5: Apr 2028 | AR5: May 2028 | AS5: Jun 2028 | AT5: Jul 2028 | AU5: Aug 2028 | AV5: Sep 2028 | AW5: Oct 2028 | AX5: Nov 2028 | AY5: Dec 2028 | BA5: 2025 | BB5: =BA5+1 | BC5: =BB5+1 | BD5: =BC5+1 | BF5: LTM May 2026
B6: Total Sales | D6: =SUM(D7:D20) | E6: =SUM(E7:E20) | F6: =SUM(F7:F20) | G6: =SUM(G7:G20) | H6: =SUM(H7:H20) | I6: =SUM(I7:I20) | J6: =SUM(J7:J20) | K6: =SUM(K7:K20) | ... AY6: =SUM(AY7:AY20) | BA6: =SUM(D6:O6) | BB6: =SUM(P6:AA6) | BC6: =SUM(AB6:AM6) | BD6: =SUM(AN6:AY6) | BF6: =SUM(I6:T6) | BH6: =SUM(BA6:BD6)-SUM(D6:AY6)
C7: Berkeley | D7: ='Sales Forecast'!D6 | E7: ='Sales Forecast'!E6 | F7: ='Sales Forecast'!F6 | G7: ='Sales Forecast'!G6 | H7: ='Sales Forecast'!H6 | I7: ='Sales Forecast'!I6 | J7: ='Sales Forecast'!J6 | K7: ='Sales Forecast'!K6 | ... AY7: ='Sales Forecast'!AY6 | BA7: =SUM(D7:O7) | BB7: =SUM(P7:AA7) | BC7: =SUM(AB7:AM7) | BD7: =SUM(AN7:AY7) | BF7: =SUM(I7:T7) | BH7: =SUM(BA7:BD7)-SUM(D7:AY7)
C8: Culver City | D8: ='Sales Forecast'!D7 | E8: ='Sales Forecast'!E7 | F8: ='Sales Forecast'!F7 | G8: ='Sales Forecast'!G7 | H8: ='Sales Forecast'!H7 | I8: ='Sales Forecast'!I7 | J8: ='Sales Forecast'!J7 | K8: ='Sales Forecast'!K7 | ... AY8: ='Sales Forecast'!AY7 | BA8: =SUM(D8:O8) | BB8: =SUM(P8:AA8) | BC8: =SUM(AB8:AM8) | BD8: =SUM(AN8:AY8) | BF8: =SUM(I8:T8) | BH8: =SUM(BA8:BD8)-SUM(D8:AY8)
C9: Danville | D9: ='Sales Forecast'!D8 | E9: ='Sales Forecast'!E8 | F9: ='Sales Forecast'!F8 | G9: ='Sales Forecast'!G8 | H9: ='Sales Forecast'!H8 | I9: ='Sales Forecast'!I8 | J9: ='Sales Forecast'!J8 | K9: ='Sales Forecast'!K8 | ... AY9: ='Sales Forecast'!AY8 | BA9: =SUM(D9:O9) | BB9: =SUM(P9:AA9) | BC9: =SUM(AB9:AM9) | BD9: =SUM(AN9:AY9) | BF9: =SUM(I9:T9) | BH9: =SUM(BA9:BD9)-SUM(D9:AY9)
C10: Lafayette | D10: ='Sales Forecast'!D9 | E10: ='Sales Forecast'!E9 | F10: ='Sales Forecast'!F9 | G10: ='Sales Forecast'!G9 | H10: ='Sales Forecast'!H9 | I10: ='Sales Forecast'!I9 | J10: ='Sales Forecast'!J9 | K10: ='Sales Forecast'!K9 | ... AY10: ='Sales Forecast'!AY9 | BA10: =SUM(D10:O10) | BB10: =SUM(P10:AA10) | BC10: =SUM(AB10:AM10) | BD10: =SUM(AN10:AY10) | BF10: =SUM(I10:T10) | BH10: =SUM(BA10:BD10)-SUM(D10:AY10)
C11: Marin | D11: ='Sales Forecast'!D10 | E11: ='Sales Forecast'!E10 | F11: ='Sales Forecast'!F10 | G11: ='Sales Forecast'!G10 | H11: ='Sales Forecast'!H10 | I11: ='Sales Forecast'!I10 | J11: ='Sales Forecast'!J10 | K11: ='Sales Forecast'!K10 | ... AY11: ='Sales Forecast'!AY10 | BA11: =SUM(D11:O11) | BB11: =SUM(P11:AA11) | BC11: =SUM(AB11:AM11) | BD11: =SUM(AN11:AY11) | BF11: =SUM(I11:T11) | BH11: =SUM(BA11:BD11)-SUM(D11:AY11)
C12: Ocean Park | D12: ='Sales Forecast'!D11 | E12: ='Sales Forecast'!E11 | F12: ='Sales Forecast'!F11 | G12: ='Sales Forecast'!G11 | H12: ='Sales Forecast'!H11 | I12: ='Sales Forecast'!I11 | J12: ='Sales Forecast'!J11 | K12: ='Sales Forecast'!K11 | ... AY12: ='Sales Forecast'!AY11 | BA12: =SUM(D12:O12) | BB12: =SUM(P12:AA12) | BC12: =SUM(AB12:AM12) | BD12: =SUM(AN12:AY12) | BF12: =SUM(I12:T12) | BH12: =SUM(BA12:BD12)-SUM(D12:AY12)
C13: Presidio Heights | D13: ='Sales Forecast'!D12 | E13: ='Sales Forecast'!E12 | F13: ='Sales Forecast'!F12 | G13: ='Sales Forecast'!G12 | H13: ='Sales Forecast'!H12 | I13: ='Sales Forecast'!I12 | J13: ='Sales Forecast'!J12 | K13: ='Sales Forecast'!K12 | ... AY13: ='Sales Forecast'!AY12 | BA13: =SUM(D13:O13) | BB13: =SUM(P13:AA13) | BC13: =SUM(AB13:AM13) | BD13: =SUM(AN13:AY13) | BF13: =SUM(I13:T13) | BH13: =SUM(BA13:BD13)-SUM(D13:AY13)
C14: Russian Hill | D14: ='Sales Forecast'!D13 | E14: ='Sales Forecast'!E13 | F14: ='Sales Forecast'!F13 | G14: ='Sales Forecast'!G13 | H14: ='Sales Forecast'!H13 | I14: ='Sales Forecast'!I13 | J14: ='Sales Forecast'!J13 | K14: ='Sales Forecast'!K13 | ... AY14: ='Sales Forecast'!AY13 | BA14: =SUM(D14:O14) | BB14: =SUM(P14:AA14) | BC14: =SUM(AB14:AM14) | BD14: =SUM(AN14:AY14) | BF14: =SUM(I14:T14) | BH14: =SUM(BA14:BD14)-SUM(D14:AY14)
C15: Santa Barbara | D15: ='Sales Forecast'!D14 | E15: ='Sales Forecast'!E14 | F15: ='Sales Forecast'!F14 | G15: ='Sales Forecast'!G14 | H15: ='Sales Forecast'!H14 | I15: ='Sales Forecast'!I14 | J15: ='Sales Forecast'!J14 | K15: ='Sales Forecast'!K14 | ... AY15: ='Sales Forecast'!AY14 | BA15: =SUM(D15:O15) | BB15: =SUM(P15:AA15) | BC15: =SUM(AB15:AM15) | BD15: =SUM(AN15:AY15) | BF15: =SUM(I15:T15) | BH15: =SUM(BA15:BD15)-SUM(D15:AY15)
C16: Santa Monica | D16: ='Sales Forecast'!D15 | E16: ='Sales Forecast'!E15 | F16: ='Sales Forecast'!F15 | G16: ='Sales Forecast'!G15 | H16: ='Sales Forecast'!H15 | I16: ='Sales Forecast'!I15 | J16: ='Sales Forecast'!J15 | K16: ='Sales Forecast'!K15 | ... AY16: ='Sales Forecast'!AY15 | BA16: =SUM(D16:O16) | BB16: =SUM(P16:AA16) | BC16: =SUM(AB16:AM16) | BD16: =SUM(AN16:AY16) | BF16: =SUM(I16:T16) | BH16: =SUM(BA16:BD16)-SUM(D16:AY16)
C17: West Portal | D17: ='Sales Forecast'!D16 | E17: ='Sales Forecast'!E16 | F17: ='Sales Forecast'!F16 | G17: ='Sales Forecast'!G16 | H17: ='Sales Forecast'!H16 | I17: ='Sales Forecast'!I16 | J17: ='Sales Forecast'!J16 | K17: ='Sales Forecast'!K16 | ... AY17: ='Sales Forecast'!AY16 | BA17: =SUM(D17:O17) | BB17: =SUM(P17:AA17) | BC17: =SUM(AB17:AM17) | BD17: =SUM(AN17:AY17) | BF17: =SUM(I17:T17) | BH17: =SUM(BA17:BD17)-SUM(D17:AY17)
C18: Westwood | D18: ='Sales Forecast'!D17 | E18: ='Sales Forecast'!E17 | F18: ='Sales Forecast'!F17 | G18: ='Sales Forecast'!G17 | H18: ='Sales Forecast'!H17 | I18: ='Sales Forecast'!I17 | J18: ='Sales Forecast'!J17 | K18: ='Sales Forecast'!K17 | ... AY18: ='Sales Forecast'!AY17 | BA18: =SUM(D18:O18) | BB18: =SUM(P18:AA18) | BC18: =SUM(AB18:AM18) | BD18: =SUM(AN18:AY18) | BF18: =SUM(I18:T18) | BH18: =SUM(BA18:BD18)-SUM(D18:AY18)
C19: New Location (Prototype Build) | AB19: =Prototype!B35 | AC19: =Prototype!C35 | AD19: =Prototype!D35 | AE19: =Prototype!E35 | AF19: =Prototype!F35 | AG19: =Prototype!G35 | AH19: =Prototype!H35 | AI19: =Prototype!I35 | ... AY19: =Prototype!Y35 | BA19: =SUM(D19:O19) | BB19: =SUM(P19:AA19) | BC19: =SUM(AB19:AM19) | BD19: =SUM(AN19:AY19) | BF19: =SUM(I19:T19)
C20: Head Office | D20: 0 | E20: 0 | F20: 0 | G20: 0 | H20: 0 | I20: 0 | J20: 0 | K20: 0 | L20: 0 | M20: 0 | N20: 0 | O20: 0 | P20: 0 | Q20: 0 | R20: 0 | S20: 0 | T20: 0 | U20: 0 | V20: 0 | W20: 0 | X20: 0 | Y20: 0 | Z20: 0 | AA20: 0 | AB20: 0 | AC20: 0 | AD20: 0 | AE20: 0 | AF20: 0 | AG20: 0 | AH20: 0 | AI20: 0 | AJ20: 0 | AK20: 0 | AL20: 0 | AM20: 0 | AN20: 0 | AO20: 0 | AP20: 0 | AQ20: 0 | AR20: 0 | AS20: 0 | AT20: 0 | AU20: 0 | AV20: 0 | AW20: 0 | AX20: 0 | AY20: 0 | BA20: =SUM(D20:O20) | BB20: =SUM(P20:AA20) | BC20: =SUM(AB20:AM20) | BD20: =SUM(AN20:AY20) | BF20: =SUM(I20:T20) | BH20: =SUM(BA20:BD20)-SUM(D20:AY20)
B22: Monthly EBITDA by Studio
B23: Total EBITDA | D23: =SUM(D24:D37) | E23: =SUM(E24:E37) | F23: =SUM(F24:F37) | G23: =SUM(G24:G37) | H23: =SUM(H24:H37) | I23: =SUM(I24:I37) | J23: =SUM(J24:J37) | K23: =SUM(K24:K37) | ... AY23: =SUM(AY24:AY37) | BA23: =SUM(D23:O23) | BB23: =SUM(P23:AA23) | BC23: =SUM(AB23:AM23) | BD23: =SUM(AN23:AY23) | BF23: =SUM(I23:T23) | BH23: =SUM(BA23:BD23)-SUM(D23:AY23)
C24: Berkeley | D24: ='BK P&L'!D64 | E24: ='BK P&L'!E64 | F24: ='BK P&L'!F64 | G24: ='BK P&L'!G64 | H24: ='BK P&L'!H64 | I24: ='BK P&L'!I64 | J24: ='BK P&L'!J64 | K24: ='BK P&L'!K64 | ... AY24: ='BK P&L'!AY64 | BA24: =SUM(D24:O24) | BB24: =SUM(P24:AA24) | BC24: =SUM(AB24:AM24) | BD24: =SUM(AN24:AY24) | BF24: =SUM(I24:T24) | BH24: =SUM(BA24:BD24)-SUM(D24:AY24)
C25: Culver City | D25: ='CC P&L'!D63 | E25: ='CC P&L'!E63 | F25: ='CC P&L'!F63 | G25: ='CC P&L'!G63 | H25: ='CC P&L'!H63 | I25: ='CC P&L'!I63 | J25: ='CC P&L'!J63 | K25: ='CC P&L'!K63 | ... AY25: ='CC P&L'!AY63 | BA25: =SUM(D25:O25) | BB25: =SUM(P25:AA25) | BC25: =SUM(AB25:AM25) | BD25: =SUM(AN25:AY25) | BF25: =SUM(I25:T25) | BH25: =SUM(BA25:BD25)-SUM(D25:AY25)
C26: Danville | D26: ='DN P&L'!D63 | E26: ='DN P&L'!E63 | F26: ='DN P&L'!F63 | G26: ='DN P&L'!G63 | H26: ='DN P&L'!H63 | I26: ='DN P&L'!I63 | J26: ='DN P&L'!J63 | K26: ='DN P&L'!K63 | ... AY26: ='DN P&L'!AY63 | BA26: =SUM(D26:O26) | BB26: =SUM(P26:AA26) | BC26: =SUM(AB26:AM26) | BD26: =SUM(AN26:AY26) | BF26: =SUM(I26:T26) | BH26: =SUM(BA26:BD26)-SUM(D26:AY26)
C27: Lafayette | D27: ='LF P&L'!D64 | E27: ='LF P&L'!E64 | F27: ='LF P&L'!F64 | G27: ='LF P&L'!G64 | H27: ='LF P&L'!H64 | I27: ='LF P&L'!I64 | J27: ='LF P&L'!J64 | K27: ='LF P&L'!K64 | ... AY27: ='LF P&L'!AY64 | BA27: =SUM(D27:O27) | BB27: =SUM(P27:AA27) | BC27: =SUM(AB27:AM27) | BD27: =SUM(AN27:AY27) | BF27: =SUM(I27:T27) | BH27: =SUM(BA27:BD27)-SUM(D27:AY27)
C28: Marin | D28: ='MR P&L'!D63 | E28: ='MR P&L'!E63 | F28: ='MR P&L'!F63 | G28: ='MR P&L'!G63 | H28: ='MR P&L'!H63 | I28: ='MR P&L'!I63 | J28: ='MR P&L'!J63 | K28: ='MR P&L'!K63 | ... AY28: ='MR P&L'!AY63 | BA28: =SUM(D28:O28) | BB28: =SUM(P28:AA28) | BC28: =SUM(AB28:AM28) | BD28: =SUM(AN28:AY28) | BF28: =SUM(I28:T28) | BH28: =SUM(BA28:BD28)-SUM(D28:AY28)
C29: Ocean Park | D29: ='OP P&L'!D63 | E29: ='OP P&L'!E63 | F29: ='OP P&L'!F63 | G29: ='OP P&L'!G63 | H29: ='OP P&L'!H63 | I29: ='OP P&L'!I63 | J29: ='OP P&L'!J63 | K29: ='OP P&L'!K63 | ... AY29: ='OP P&L'!AY63 | BA29: =SUM(D29:O29) | BB29: =SUM(P29:AA29) | BC29: =SUM(AB29:AM29) | BD29: =SUM(AN29:AY29) | BF29: =SUM(I29:T29) | BH29: =SUM(BA29:BD29)-SUM(D29:AY29)
C30: Presidio Heights | D30: ='PH P&L'!D64 | E30: ='PH P&L'!E64 | F30: ='PH P&L'!F64 | G30: ='PH P&L'!G64 | H30: ='PH P&L'!H64 | I30: ='PH P&L'!I64 | J30: ='PH P&L'!J64 | K30: ='PH P&L'!K64 | ... AY30: ='PH P&L'!AY64 | BA30: =SUM(D30:O30) | BB30: =SUM(P30:AA30) | BC30: =SUM(AB30:AM30) | BD30: =SUM(AN30:AY30) | BF30: =SUM(I30:T30) | BH30: =SUM(BA30:BD30)-SUM(D30:AY30)
C31: Russian Hill | D31: ='RH P&L'!D63 | E31: ='RH P&L'!E63 | F31: ='RH P&L'!F63 | G31: ='RH P&L'!G63 | H31: ='RH P&L'!H63 | I31: ='RH P&L'!I63 | J31: ='RH P&L'!J63 | K31: ='RH P&L'!K63 | ... AY31: ='RH P&L'!AY63 | BA31: =SUM(D31:O31) | BB31: =SUM(P31:AA31) | BC31: =SUM(AB31:AM31) | BD31: =SUM(AN31:AY31) | BF31: =SUM(I31:T31) | BH31: =SUM(BA31:BD31)-SUM(D31:AY31)
C32: Santa Barbara | D32: ='SB P&L'!D63 | E32: ='SB P&L'!E63 | F32: ='SB P&L'!F63 | G32: ='SB P&L'!G63 | H32: ='SB P&L'!H63 | I32: ='SB P&L'!I63 | J32: ='SB P&L'!J63 | K32: ='SB P&L'!K63 | ... AY32: ='SB P&L'!AY63 | BA32: =SUM(D32:O32) | BB32: =SUM(P32:AA32) | BC32: =SUM(AB32:AM32) | BD32: =SUM(AN32:AY32) | BF32: =SUM(I32:T32) | BH32: =SUM(BA32:BD32)-SUM(D32:AY32)
C33: Santa Monica | D33: ='SM P&L'!D64 | E33: ='SM P&L'!E64 | F33: ='SM P&L'!F64 | G33: ='SM P&L'!G64 | H33: ='SM P&L'!H64 | I33: ='SM P&L'!I64 | J33: ='SM P&L'!J64 | K33: ='SM P&L'!K64 | ... AY33: ='SM P&L'!AY64 | BA33: =SUM(D33:O33) | BB33: =SUM(P33:AA33) | BC33: =SUM(AB33:AM33) | BD33: =SUM(AN33:AY33) | BF33: =SUM(I33:T33) | BH33: =SUM(BA33:BD33)-SUM(D33:AY33)
C34: West Portal | D34: ='WP P&L'!D63 | E34: ='WP P&L'!E63 | F34: ='WP P&L'!F63 | G34: ='WP P&L'!G63 | H34: ='WP P&L'!H63 | I34: ='WP P&L'!I63 | J34: ='WP P&L'!J63 | K34: ='WP P&L'!K63 | ... AY34: ='WP P&L'!AY63 | BA34: =SUM(D34:O34) | BB34: =SUM(P34:AA34) | BC34: =SUM(AB34:AM34) | BD34: =SUM(AN34:AY34) | BF34: =SUM(I34:T34) | BH34: =SUM(BA34:BD34)-SUM(D34:AY34)
C35: Westwood | D35: ='WW P&L'!D64 | E35: ='WW P&L'!E64 | F35: ='WW P&L'!F64 | G35: ='WW P&L'!G64 | H35: ='WW P&L'!H64 | I35: ='WW P&L'!I64 | J35: ='WW P&L'!J64 | K35: ='WW P&L'!K64 | ... AY35: ='WW P&L'!AY64 | BA35: =SUM(D35:O35) | BB35: =SUM(P35:AA35) | BC35: =SUM(AB35:AM35) | BD35: =SUM(AN35:AY35) | BF35: =SUM(I35:T35) | BH35: =SUM(BA35:BD35)-SUM(D35:AY35)
C36: New Location (Prototype Build) | AB36: =Prototype!B48 | AC36: =Prototype!C48 | AD36: =Prototype!D48 | AE36: =Prototype!E48 | AF36: =Prototype!F48 | AG36: =Prototype!G48 | AH36: =Prototype!H48 | AI36: =Prototype!I48 | ... AY36: =Prototype!Y48 | BA36: =SUM(D36:O36) | BB36: =SUM(P36:AA36) | BC36: =SUM(AB36:AM36) | BD36: =SUM(AN36:AY36) | BF36: =SUM(I36:T36)
C37: Head Office | D37: ='HO P&L'!D36 | E37: ='HO P&L'!E36 | F37: ='HO P&L'!F36 | G37: ='HO P&L'!G36 | H37: ='HO P&L'!H36 | I37: ='HO P&L'!I36 | J37: ='HO P&L'!J36 | K37: ='HO P&L'!K36 | ... AY37: ='HO P&L'!AY36 | BA37: =SUM(D37:O37) | BB37: =SUM(P37:AA37) | BC37: =SUM(AB37:AM37) | BD37: =SUM(AN37:AY37) | BF37: =SUM(I37:T37) | BH37: =SUM(BA37:BD37)-SUM(D37:AY37)
B39: Studio Level EBITDA | D39: =SUM(D24:D36) | E39: =SUM(E24:E36) | F39: =SUM(F24:F36) | G39: =SUM(G24:G36) | H39: =SUM(H24:H36) | I39: =SUM(I24:I36) | J39: =SUM(J24:J36) | K39: =SUM(K24:K36) | ... AY39: =SUM(AY24:AY36) | BA39: =SUM(D39:O39) | BB39: =SUM(P39:AA39) | BC39: =SUM(AB39:AM39) | BD39: =SUM(AN39:AY39) | BF39: =SUM(I39:T39)
B40: Head Office | D40: =D37 | E40: =E37 | F40: =F37 | G40: =G37 | H40: =H37 | I40: =I37 | J40: =J37 | K40: =K37 | ... AY40: =AY37 | BA40: =SUM(D40:O40) | BB40: =SUM(P40:AA40) | BC40: =SUM(AB40:AM40) | BD40: =SUM(AN40:AY40) | BF40: =SUM(I40:T40)
B41: EBITDA, Post Corp Overhead | D41: =SUM(D39:D40) | E41: =SUM(E39:E40) | F41: =SUM(F39:F40) | G41: =SUM(G39:G40) | H41: =SUM(H39:H40) | I41: =SUM(I39:I40) | J41: =SUM(J39:J40) | K41: =SUM(K39:K40) | ... AY41: =SUM(AY39:AY40) | BA41: =SUM(BA39:BA40) | BB41: =SUM(BB39:BB40) | BC41: =SUM(BC39:BC40) | BD41: =SUM(BD39:BD40) | BF41: =SUM(I41:T41)
B42: Russian Hill Start-Up Costs | D42: 27678.97 | E42: 46607.8 | F42: 2621.08 | G42: 3676.99 | H42: 3252 | I42: 0 | J42: 0 | K42: 1306.25 | L42: 0 | M42: 0 | N42: 0 | O42: 0 | BA42: =SUM(D42:O42) | BB42: =SUM(P42:AA42) | BC42: =SUM(AB42:AM42) | BD42: =SUM(AN42:AY42) | BF42: =SUM(I42:T42)
B43: Ocean Park Start-Up Costs | D43: 719.87 | E43: 5189.83 | F43: 27247.86 | G43: 9987.27 | H43: 543.23 | I43: 777.13 | J43: 0 | K43: 0 | L43: 387.59 | M43: 0 | N43: 0 | O43: 0 | BA43: =SUM(D43:O43) | BB43: =SUM(P43:AA43) | BC43: =SUM(AB43:AM43) | BD43: =SUM(AN43:AY43) | BF43: =SUM(I43:T43)
B44: Danville Start-Up Costs | D44: 0 | E44: 132.98 | F44: 2286 | G44: 6670.78 | H44: 19624.68 | I44: 52723.88 | J44: 2276.32 | K44: 2394.01 | L44: 600 | M44: 0 | N44: 0 | O44: 0 | BA44: =SUM(D44:O44) | BB44: =SUM(P44:AA44) | BC44: =SUM(AB44:AM44) | BD44: =SUM(AN44:AY44) | BF44: =SUM(I44:T44)
B45: Culver City Start-Up Costs | D45: 0 | E45: 0 | F45: 0 | G45: 0 | H45: 0 | I45: 9139.65 | J45: 2529.94 | K45: 9485.01 | L45: 45764.83 | M45: 7688.86 | N45: 0 | O45: 0 | BA45: =SUM(D45:O45) | BB45: =SUM(P45:AA45) | BC45: =SUM(AB45:AM45) | BD45: =SUM(AN45:AY45) | BF45: =SUM(I45:T45)
B46: Santa Monica Leasehold Improvements | X46: 10000 | Y46: 5000 | Z46: 5000 | AA46: 5000 | BA46: =SUM(D46:O46) | BB46: =SUM(P46:AA46) | BC46: =SUM(AB46:AM46) | BD46: =SUM(AN46:AY46) | BF46: =SUM(I46:T46)
B47: West Portal Start-Up Costs | P47: 16222.39 | Q47: 17111.26 | R47: 14310.31 | S47: 19092.69 | T47: 16668 | U47: 11669.37 | V47: 15000 | W47: 15000 | X47: 60000 | Y47: 35000 | Z47: 15000 | AA47: 10000 | BA47: =SUM(D47:O47) | BB47: =SUM(P47:AA47) | BC47: =SUM(AB47:AM47) | BD47: =SUM(AN47:AY47) | BF47: =SUM(I47:T47)
B48: ADP Error | R48: 45000 | BA48: =SUM(D48:O48) | BB48: =SUM(P48:AA48) | BC48: =SUM(AB48:AM48) | BD48: =SUM(AN48:AY48) | BF48: =SUM(I48:T48)
B49: One-Time Legal Fees | H49: 500 | K49: 7200 | L49: 12500 | M49: =2540 | O49: =2359.5 | P49: 2957 | R49: =3995.5 | U49: 770 | W49: 5000 | BA49: =SUM(D49:O49) | BB49: =SUM(P49:AA49) | BC49: =SUM(AB49:AM49) | BD49: =SUM(AN49:AY49) | BF49: =SUM(I49:T49)
B50: Santa Barbara Start Up | K50: 11875.72 | L50: 10160.11 | M50: 23932.64 | N50: 66186.75 | O50: 1772.78 | P50: 3481 | V50: 5000 | BA50: =SUM(D50:O50) | BB50: =SUM(P50:AA50) | BC50: =SUM(AB50:AM50) | BD50: =SUM(AN50:AY50) | BF50: =SUM(I50:T50)
B51: One-Time Accounting Fees | K51: 1700 | L51: 2415 | M51: 27200 | N51: 22632 | O51: 28128 | P51: 19887.5 | BA51: =SUM(D51:O51) | BB51: =SUM(P51:AA51) | BC51: =SUM(AB51:AM51) | BD51: =SUM(AN51:AY51) | BF51: =SUM(I51:T51)
B52: One-Time Professional Fees | I52: =13840 | J52: 8249 | L52: 760 | BA52: =SUM(D52:O52) | BB52: =SUM(P52:AA52) | BC52: =SUM(AB52:AM52) | BD52: =SUM(AN52:AY52) | BF52: =SUM(I52:T52)
B53: Special Marketing Projects One-Time | F53: =1107.42 | H53: =1218.03 | K53: 400 | L53: =20.84 | M53: =396.92 | O53: =254.31 | W53: 5000 | Y53: 10000 | BA53: =SUM(D53:O53) | BB53: =SUM(P53:AA53) | BC53: =SUM(AB53:AM53) | BD53: =SUM(AN53:AY53) | BF53: =SUM(I53:T53)
B54: Corporate Transaction Fees | I54: 10000 | O54: 11500 | BA54: =SUM(D54:O54) | BB54: =SUM(P54:AA54) | BC54: =SUM(AB54:AM54) | BD54: =SUM(AN54:AY54) | BF54: =SUM(I54:T54)
B55: One-Time GE | F55: 1144 | L55: 656.8 | M55: 5000 | N55: 2264.81 | O55: 2205.93 | BA55: =SUM(D55:O55) | BB55: =SUM(P55:AA55) | BC55: =SUM(AB55:AM55) | BD55: =SUM(AN55:AY55) | BF55: =SUM(I55:T55)
B56: Costs for Potentional Studios Not Opened | K56: =2869+1275 | M56: =459 | N56: =97.6 | BA56: =SUM(D56:O56) | BB56: =SUM(P56:AA56) | BC56: =SUM(AB56:AM56) | BD56: =SUM(AN56:AY56) | BF56: =SUM(I56:T56)
B57: Other One-Time Costs | E57: 254 | J57: 198 | BA57: =SUM(D57:O57) | BB57: =SUM(P57:AA57) | BC57: =SUM(AB57:AM57) | BD57: =SUM(AN57:AY57) | BF57: =SUM(I57:T57)
B58: Total Add Backs (not including new prototype build one time costs) | D58: =SUM(D42:D57) | E58: =SUM(E42:E57) | F58: =SUM(F42:F57) | G58: =SUM(G42:G57) | H58: =SUM(H42:H57) | I58: =SUM(I42:I57) | J58: =SUM(J42:J57) | K58: =SUM(K42:K57) | ... AY58: =SUM(AY42:AY57) | BA58: =SUM(D58:O58) | BB58: =SUM(P58:AA58) | BC58: =SUM(AB58:AM58) | BD58: =SUM(AN58:AY58) | BF58: =SUM(I58:T58)
B59: Total Adj-EBITDA | D59: =D23+D58 | E59: =E23+E58 | F59: =F23+F58 | G59: =G23+G58 | H59: =H23+H58 | I59: =I23+I58 | J59: =J23+J58 | K59: =K23+K58 | ... AY59: =AY23+AY58 | BA59: =SUM(D59:O59) | BB59: =SUM(P59:AA59) | BC59: =SUM(AB59:AM59) | BD59: =SUM(AN59:AY59) | BF59: =SUM(I59:T59) | BH59: =SUM(BA59:BD59)-SUM(D59:AY59)
B61: Annual Summary
B62: Metric | C62: Studio | D62: 2025 | E62: 2026 | F62: 2027 | G62: 2028 | H62: 2026 YoY | I62: 2027 YoY | J62: 2028 YoY
B63: Total Sales | D63: =SUM(D64:D76) | E63: =SUM(E64:E76) | F63: =SUM(F64:F76) | G63: =SUM(G64:G76) | H63: =IFERROR((E63-D63)/D63,0) | I63: =IFERROR((F63-E63)/E63,0) | J63: =IFERROR((G63-F63)/F63,0)
C64: Berkeley | D64: =SUM('Sales Forecast'!D6:O6) | E64: =SUM('Sales Forecast'!P6:AA6) | F64: =SUM('Sales Forecast'!AB6:AM6) | G64: =SUM('Sales Forecast'!AN6:AY6) | H64: =IFERROR((E62-D62)/D62,0) | I64: =IFERROR((F62-E62)/E62,0) | J64: =IFERROR((G62-F62)/F62,0)
C65: Culver City | D65: =SUM('Sales Forecast'!D7:O7) | E65: =SUM('Sales Forecast'!P7:AA7) | F65: =SUM('Sales Forecast'!AB7:AM7) | G65: =SUM('Sales Forecast'!AN7:AY7) | H65: =IFERROR((E63-D63)/D63,0) | I65: =IFERROR((F63-E63)/E63,0) | J65: =IFERROR((G63-F63)/F63,0)
C66: Danville | D66: =SUM('Sales Forecast'!D8:O8) | E66: =SUM('Sales Forecast'!P8:AA8) | F66: =SUM('Sales Forecast'!AB8:AM8) | G66: =SUM('Sales Forecast'!AN8:AY8) | H66: =IFERROR((E64-D64)/D64,0) | I66: =IFERROR((F64-E64)/E64,0) | J66: =IFERROR((G64-F64)/F64,0)
C67: Lafayette | D67: =SUM('Sales Forecast'!D9:O9) | E67: =SUM('Sales Forecast'!P9:AA9) | F67: =SUM('Sales Forecast'!AB9:AM9) | G67: =SUM('Sales Forecast'!AN9:AY9) | H67: =IFERROR((E65-D65)/D65,0) | I67: =IFERROR((F65-E65)/E65,0) | J67: =IFERROR((G65-F65)/F65,0)
C68: Marin | D68: =SUM('Sales Forecast'!D10:O10) | E68: =SUM('Sales Forecast'!P10:AA10) | F68: =SUM('Sales Forecast'!AB10:AM10) | G68: =SUM('Sales Forecast'!AN10:AY10) | H68: =IFERROR((E66-D66)/D66,0) | I68: =IFERROR((F66-E66)/E66,0) | J68: =IFERROR((G66-F66)/F66,0)
C69: Ocean Park | D69: =SUM('Sales Forecast'!D11:O11) | E69: =SUM('Sales Forecast'!P11:AA11) | F69: =SUM('Sales Forecast'!AB11:AM11) | G69: =SUM('Sales Forecast'!AN11:AY11) | H69: =IFERROR((E67-D67)/D67,0) | I69: =IFERROR((F67-E67)/E67,0) | J69: =IFERROR((G67-F67)/F67,0)
C70: Presidio Heights | D70: =SUM('Sales Forecast'!D12:O12) | E70: =SUM('Sales Forecast'!P12:AA12) | F70: =SUM('Sales Forecast'!AB12:AM12) | G70: =SUM('Sales Forecast'!AN12:AY12) | H70: =IFERROR((E68-D68)/D68,0) | I70: =IFERROR((F68-E68)/E68,0) | J70: =IFERROR((G68-F68)/F68,0)
C71: Russian Hill | D71: =SUM('Sales Forecast'!D13:O13) | E71: =SUM('Sales Forecast'!P13:AA13) | F71: =SUM('Sales Forecast'!AB13:AM13) | G71: =SUM('Sales Forecast'!AN13:AY13) | H71: =IFERROR((E69-D69)/D69,0) | I71: =IFERROR((F69-E69)/E69,0) | J71: =IFERROR((G69-F69)/F69,0)
C72: Santa Barbara | D72: =SUM('Sales Forecast'!D14:O14) | E72: =SUM('Sales Forecast'!P14:AA14) | F72: =SUM('Sales Forecast'!AB14:AM14) | G72: =SUM('Sales Forecast'!AN14:AY14) | H72: =IFERROR((E70-D70)/D70,0) | I72: =IFERROR((F70-E70)/E70,0) | J72: =IFERROR((G70-F70)/F70,0)
C73: Santa Monica | D73: =SUM('Sales Forecast'!D15:O15) | E73: =SUM('Sales Forecast'!P15:AA15) | F73: =SUM('Sales Forecast'!AB15:AM15) | G73: =SUM('Sales Forecast'!AN15:AY15) | H73: =IFERROR((E71-D71)/D71,0) | I73: =IFERROR((F71-E71)/E71,0) | J73: =IFERROR((G71-F71)/F71,0)
C74: West Portal | D74: =SUM('Sales Forecast'!D16:O16) | E74: =SUM('Sales Forecast'!P16:AA16) | F74: =SUM('Sales Forecast'!AB16:AM16) | G74: =SUM('Sales Forecast'!AN16:AY16) | H74: =IFERROR((E72-D72)/D72,0) | I74: =IFERROR((F72-E72)/E72,0) | J74: =IFERROR((G72-F72)/F72,0)
C75: Westwood | D75: =SUM('Sales Forecast'!D17:O17) | E75: =SUM('Sales Forecast'!P17:AA17) | F75: =SUM('Sales Forecast'!AB17:AM17) | G75: =SUM('Sales Forecast'!AN17:AY17) | H75: =IFERROR((E73-D73)/D73,0) | I75: =IFERROR((F73-E73)/E73,0) | J75: =IFERROR((G73-F73)/F73,0)
C76: Head Office | D76: 0 | E76: 0 | F76: 0 | G76: 0 | H76: =IFERROR((E76-D76)/D76,0) | I76: =IFERROR((F76-E76)/E76,0) | J76: =IFERROR((G76-F76)/F76,0)
B78: Total EBITDA | D78: =SUM(D79:D91) | E78: =SUM(E79:E91) | F78: =SUM(F79:F91) | G78: =SUM(G79:G91) | H78: =IFERROR((E78-D78)/D78,0) | I78: =IFERROR((F78-E78)/E78,0) | J78: =IFERROR((G78-F78)/F78,0)
C79: Berkeley | D79: =SUM(D24:O24) | E79: =SUM(P24:AA24) | F79: =SUM(AB24:AM24) | G79: =SUM(AN24:AY24) | H79: =IFERROR((E79-D79)/D79,0) | I79: =IFERROR((F79-E79)/E79,0) | J79: =IFERROR((G79-F79)/F79,0)
C80: Culver City | D80: =SUM(D25:O25) | E80: =SUM(P25:AA25) | F80: =SUM(AB25:AM25) | G80: =SUM(AN25:AY25) | H80: =IFERROR((E80-D80)/D80,0) | I80: =IFERROR((F80-E80)/E80,0) | J80: =IFERROR((G80-F80)/F80,0)
C81: Danville | D81: =SUM(D26:O26) | E81: =SUM(P26:AA26) | F81: =SUM(AB26:AM26) | G81: =SUM(AN26:AY26) | H81: =IFERROR((E81-D81)/D81,0) | I81: =IFERROR((F81-E81)/E81,0) | J81: =IFERROR((G81-F81)/F81,0)
C82: Lafayette | D82: =SUM(D27:O27) | E82: =SUM(P27:AA27) | F82: =SUM(AB27:AM27) | G82: =SUM(AN27:AY27) | H82: =IFERROR((E82-D82)/D82,0) | I82: =IFERROR((F82-E82)/E82,0) | J82: =IFERROR((G82-F82)/F82,0)
C83: Marin | D83: =SUM(D28:O28) | E83: =SUM(P28:AA28) | F83: =SUM(AB28:AM28) | G83: =SUM(AN28:AY28) | H83: =IFERROR((E83-D83)/D83,0) | I83: =IFERROR((F83-E83)/E83,0) | J83: =IFERROR((G83-F83)/F83,0)
C84: Ocean Park | D84: =SUM(D29:O29) | E84: =SUM(P29:AA29) | F84: =SUM(AB29:AM29) | G84: =SUM(AN29:AY29) | H84: =IFERROR((E84-D84)/D84,0) | I84: =IFERROR((F84-E84)/E84,0) | J84: =IFERROR((G84-F84)/F84,0)
C85: Presidio Heights | D85: =SUM(D30:O30) | E85: =SUM(P30:AA30) | F85: =SUM(AB30:AM30) | G85: =SUM(AN30:AY30) | H85: =IFERROR((E85-D85)/D85,0) | I85: =IFERROR((F85-E85)/E85,0) | J85: =IFERROR((G85-F85)/F85,0)
C86: Russian Hill | D86: =SUM(D31:O31) | E86: =SUM(P31:AA31) | F86: =SUM(AB31:AM31) | G86: =SUM(AN31:AY31) | H86: =IFERROR((E86-D86)/D86,0) | I86: =IFERROR((F86-E86)/E86,0) | J86: =IFERROR((G86-F86)/F86,0)
C87: Santa Barbara | D87: =SUM(D32:O32) | E87: =SUM(P32:AA32) | F87: =SUM(AB32:AM32) | G87: =SUM(AN32:AY32) | H87: =IFERROR((E87-D87)/D87,0) | I87: =IFERROR((F87-E87)/E87,0) | J87: =IFERROR((G87-F87)/F87,0)
C88: Santa Monica | D88: =SUM(D33:O33) | E88: =SUM(P33:AA33) | F88: =SUM(AB33:AM33) | G88: =SUM(AN33:AY33) | H88: =IFERROR((E88-D88)/D88,0) | I88: =IFERROR((F88-E88)/E88,0) | J88: =IFERROR((G88-F88)/F88,0)
C89: West Portal | D89: =SUM(D34:O34) | E89: =SUM(P34:AA34) | F89: =SUM(AB34:AM34) | G89: =SUM(AN34:AY34) | H89: =IFERROR((E89-D89)/D89,0) | I89: =IFERROR((F89-E89)/E89,0) | J89: =IFERROR((G89-F89)/F89,0)
C90: Westwood | D90: =SUM(D35:O35) | E90: =SUM(P35:AA35) | F90: =SUM(AB35:AM35) | G90: =SUM(AN35:AY35) | H90: =IFERROR((E90-D90)/D90,0) | I90: =IFERROR((F90-E90)/E90,0) | J90: =IFERROR((G90-F90)/F90,0)
C91: Head Office | D91: =SUM('HO P&L'!D36:O36) | E91: =SUM('HO P&L'!P36:AA36) | F91: =SUM('HO P&L'!AB36:AM36) | G91: =SUM('HO P&L'!AN36:AY36) | H91: =IFERROR((E91-D91)/D91,0) | I91: =IFERROR((F91-E91)/E91,0) | J91: =IFERROR((G91-F91)/F91,0)
B93: Total Adj-EBITDA | D93: =SUM(D59:O59) | E93: =SUM(P59:AA59) | F93: =SUM(AB59:AM59) | G93: =SUM(AN59:AY59) | H93: =IFERROR((E93-D93)/D93,0) | I93: =IFERROR((F93-E93)/E93,0) | J93: =IFERROR((G93-F93)/F93,0)

Sheet Sales Forecast
B2: Sales Forecast (Gross)
B3: Jan-Jun 2026 actuals (locked, Cat-authoritative). Jul 2026 onwards forecast (editable).
B4: Per-Studio Monthly Sales
B5: Code | C5: Studio | D5: Jan 2025 | E5: Feb 2025 | F5: Mar 2025 | G5: Apr 2025 | H5: May 2025 | I5: Jun 2025 | J5: Jul 2025 | K5: Aug 2025 | L5: Sep 2025 | M5: Oct 2025 | N5: Nov 2025 | O5: Dec 2025 | P5: Jan 2026 | Q5: Feb 2026 | R5: Mar 2026 | S5: Apr 2026 | T5: 46143 | U5: Jun 2026 | V5: Jul 2026 | W5: Aug 2026 | X5: Sep 2026 | Y5: Oct 2026 | Z5: Nov 2026 | AA5: Dec 2026 | AB5: Jan 2027 | AC5: Feb 2027 | AD5: Mar 2027 | AE5: Apr 2027 | AF5: May 2027 | AG5: Jun 2027 | AH5: Jul 2027 | AI5: Aug 2027 | AJ5: Sep 2027 | AK5: Oct 2027 | AL5: Nov 2027 | AM5: Dec 2027 | AN5: Jan 2028 | AO5: Feb 2028 | AP5: Mar 2028 | AQ5: Apr 2028 | AR5: May 2028 | AS5: Jun 2028 | AT5: Jul 2028 | AU5: Aug 2028 | AV5: Sep 2028 | AW5: Oct 2028 | AX5: Nov 2028 | AY5: Dec 2028
B6: BK | C6: Berkeley | D6: 122672 | E6: 124750 | F6: 112908 | G6: 140814 | H6: 111061 | I6: 107458 | J6: 101618 | K6: 142373 | L6: 101097 | M6: 115965 | N6: 101860 | O6: 99707 | P6: 124393 | Q6: 129377 | R6: 103159 | S6: 136117 | T6: 83273 | U6: 100821 | V6: 99551 | W6: 120000 | X6: 120000 | Y6: 130000 | Z6: 130000 | AA6: 149000 | AB6: 130612.65 | AC6: 135845.85 | AD6: 108316.95 | AE6: 142922.85 | AF6: 87649.8 | AG6: 115500 | AH6: 110250 | AI6: 126000 | AJ6: 126000 | AK6: 136500 | AL6: 136500 | AM6: 156450 | AN6: 137143.28 | AO6: 142638.14 | AP6: 113732.8 | AQ6: 150068.99 | AR6: 92032.29 | AS6: 121275 | AT6: 115762.5 | AU6: 132300 | AV6: 132300 | AW6: 143325 | AX6: 143325 | AY6: 164272.5
B7: CC | C7: Culver City | D7: 0 | E7: 0 | F7: 0 | G7: 0 | H7: 0 | I7: 0 | J7: 0 | K7: 0 | L7: 16118 | M7: 31030 | N7: 31622 | O7: 31310 | P7: 43840 | Q7: 38704 | R7: 42619 | S7: 39690 | T7: 43327 | U7: 32522 | V7: 42903 | W7: 50000 | X7: 53000 | Y7: 60000 | Z7: 64000 | AA7: 60000 | AB7: 61000 | AC7: 73307 | AD7: 69238 | AE7: 75096 | AF7: 70949 | AG7: 64231 | AH7: 95489 | AI7: 107456 | AJ7: 102425 | AK7: 95000 | AL7: 95000 | AM7: 95000 | AN7: 64050 | AO7: 76972.35 | AP7: 72699.9 | AQ7: 78850.8 | AR7: 74496.45 | AS7: 67442.55 | AT7: 100263.45 | AU7: 112828.8 | AV7: 107546.25 | AW7: 99750 | AX7: 99750 | AY7: 99750
B8: DN | C8: Danville | D8: 0 | E8: 0 | F8: 0 | G8: 0 | H8: 0 | I8: 8385 | J8: 14789 | K8: 16531 | L8: 16660 | M8: 14843 | N8: 15819 | O8: 17950 | P8: 24286 | Q8: 23358 | R8: 20289 | S8: 20363 | T8: 15337 | U8: 20327 | V8: 16795 | W8: 25000 | X8: 25000 | Y8: 30000 | Z8: 25000 | AA8: 32000 | AB8: 32000 | AC8: 40000 | AD8: 40000 | AE8: 45000 | AF8: 45000 | AG8: 50000 | AH8: 50000 | AI8: 50000 | AJ8: 55000 | AK8: 55000 | AL8: 55000 | AM8: 55000 | AN8: 33600 | AO8: 42000 | AP8: 42000 | AQ8: 47250 | AR8: 47250 | AS8: 52500 | AT8: 52500 | AU8: 52500 | AV8: 57750 | AW8: 57750 | AX8: 57750 | AY8: 57750
B9: LF | C9: Lafayette | D9: 90025 | E9: 86822 | F9: 85300 | G9: 127703 | H9: 79380 | I9: 76768 | J9: 70767 | K9: 102739 | L9: 68837 | M9: 83777 | N9: 79979 | O9: 79880 | P9: 92365 | Q9: 126186 | R9: 78385 | S9: 106542 | T9: 71444 | U9: 81024 | V9: 86878 | W9: 80000 | X9: 80250 | Y9: 85000 | Z9: 95000 | AA9: 110000 | AB9: 96983.25 | AC9: 132495.3 | AD9: 82304.25 | AE9: 111869.1 | AF9: 75832.05 | AG9: 84000 | AH9: 84262.5 | AI9: 84000 | AJ9: 84262.5 | AK9: 89250 | AL9: 99750 | AM9: 115500 | AN9: 101832.41 | AO9: 139120.07 | AP9: 86419.46 | AQ9: 117462.56 | AR9: 79623.65 | AS9: 88200 | AT9: 88475.62 | AU9: 88200 | AV9: 88475.62 | AW9: 93712.5 | AX9: 104737.5 | AY9: 121275
B10: MR | C10: Marin | D10: 16838.6 | E10: 13867.046 | F10: 14508.233 | G10: 36538 | H10: 90956 | I10: 87668 | J10: 91349 | K10: 113973 | L10: 81190 | M10: 98516 | N10: 90001 | O10: 104919 | P10: 100589 | Q10: 114193 | R10: 90196 | S10: 140256 | T10: 74382 | U10: 98742 | V10: 109856 | W10: 120000 | X10: 98000 | Y10: 110000 | Z10: 120000 | AA10: 115000 | AB10: 105618.45 | AC10: 119902.65 | AD10: 94705.8 | AE10: 147268.8 | AF10: 78685.95 | AG10: 101115 | AH10: 99750 | AI10: 126000 | AJ10: 102900 | AK10: 115500 | AL10: 126000 | AM10: 120750 | AN10: 110899.37 | AO10: 125897.78 | AP10: 99441.09 | AQ10: 154632.24 | AR10: 82620.25 | AS10: 106170.75 | AT10: 104737.5 | AU10: 132300 | AV10: 108045 | AW10: 121275 | AX10: 132300 | AY10: 126787.5
B11: OP | C11: Ocean Park | D11: 0 | E11: 0 | F11: 0 | G11: 30025 | H11: 45379 | I11: 50782 | J11: 59231 | K11: 60132 | L11: 52754 | M11: 51670 | N11: 60236 | O11: 51621 | P11: 60583 | Q11: 59614 | R11: 62052 | S11: 73815 | T11: 63770 | U11: 50286 | V11: 58162 | W11: 60000 | X11: 63000 | Y11: 70000 | Z11: 75000 | AA11: 60000 | AB11: 63612.15 | AC11: 62594.7 | AD11: 65154.6 | AE11: 77505.75 | AF11: 67045.65 | AG11: 67410 | AH11: 78750 | AI11: 63000 | AJ11: 66150 | AK11: 73500 | AL11: 78750 | AM11: 63000 | AN11: 66792.76 | AO11: 65724.43 | AP11: 68412.33 | AQ11: 81381.04 | AR11: 70397.93 | AS11: 70780.5 | AT11: 82687.5 | AU11: 66150 | AV11: 69457.5 | AW11: 77175 | AX11: 82687.5 | AY11: 66150
B12: PH | C12: Presidio Heights | D12: 233958.4 | E12: 218217.95 | F12: 206588.77 | G12: 189694 | H12: 117239 | I12: 109486 | J12: 91214 | K12: 179728 | L12: 107500 | M12: 134780 | N12: 113334 | O12: 128126 | P12: 124927 | Q12: 180839 | R12: 115051 | S12: 179323 | T12: 93511 | U12: 113383 | V12: 117515 | W12: 155000 | X12: 120000 | Y12: 125000 | Z12: 140000 | AA12: 150000 | AB12: 131173.35 | AC12: 189880.95 | AD12: 120803.55 | AE12: 188289.15 | AF12: 100401 | AG12: 120750 | AH12: 115500 | AI12: 162750 | AJ12: 126000 | AK12: 131250 | AL12: 147000 | AM12: 157500 | AN12: 137732.02 | AO12: 199375 | AP12: 126843.73 | AQ12: 197703.61 | AR12: 105421.05 | AS12: 126787.5 | AT12: 121275 | AU12: 170887.5 | AV12: 132300 | AW12: 137812.5 | AX12: 154350 | AY12: 165375
B13: RH | C13: Russian Hill | D13: 0 | E13: 31933 | F13: 55412 | G13: 81989 | H13: 70953 | I13: 67470 | J13: 72141 | K13: 93312 | L13: 69913 | M13: 80685 | N13: 76340 | O13: 72252 | P13: 96145 | Q13: 94253 | R13: 85589 | S13: 108129 | T13: 66857 | U13: 71619 | V13: 75936 | W13: 95000 | X13: 80000 | Y13: 82000 | Z13: 80000 | AA13: 88000 | AB13: 100952.25 | AC13: 98965.65 | AD13: 89868.45 | AE13: 113535.45 | AF13: 71700.3 | AG13: 80850 | AH13: 78750 | AI13: 99750 | AJ13: 84000 | AK13: 86100 | AL13: 84000 | AM13: 92400 | AN13: 105999.86 | AO13: 103913.93 | AP13: 94361.87 | AQ13: 119212.22 | AR13: 75285.32 | AS13: 84892.5 | AT13: 82687.5 | AU13: 104737.5 | AV13: 88200 | AW13: 90405 | AX13: 88200 | AY13: 97020
B14: SB | C14: Santa Barbara | D14: 0 | E14: 0 | F14: 0 | G14: 0 | H14: 0 | I14: 0 | J14: 0 | K14: 0 | L14: 0 | M14: 0 | N14: 8231 | O14: 17514 | P14: 32747 | Q14: 27799 | R14: 25898 | S14: 23393 | T14: 20133 | U14: 17783 | V14: 18714 | W14: 30000 | X14: 30000 | Y14: 33000 | Z14: 35000 | AA14: 35000 | AB14: 59231 | AC14: 60132 | AD14: 52754 | AE14: 51670 | AF14: 60236 | AG14: 51621 | AH14: 62000 | AI14: 63000 | AJ14: 73000 | AK14: 65000 | AL14: 64200 | AM14: 64200 | AN14: 62192.55 | AO14: 63138.6 | AP14: 55391.7 | AQ14: 54253.5 | AR14: 63247.8 | AS14: 54202.05 | AT14: 65100 | AU14: 66150 | AV14: 76650 | AW14: 68250 | AX14: 67410 | AY14: 67410
B15: SM | C15: Santa Monica | D15: 143755 | E15: 203570 | F15: 268747 | G15: 164726 | H15: 193168 | I15: 169753 | J15: 231840 | K15: 162408 | L15: 176867 | M15: 154064 | N15: 188610 | O15: 178478 | P15: 184491 | Q15: 161597 | R15: 192258 | S15: 157521 | T15: 206632 | U15: 130716 | V15: 163688 | W15: 200000 | X15: 190000 | Y15: 220000 | Z15: 251450 | AA15: 190000 | AB15: 215000 | AC15: 190000 | AD15: 215000 | AE15: 200000 | AF15: 235000 | AG15: 210000 | AH15: 200000 | AI15: 210000 | AJ15: 215000 | AK15: 231000 | AL15: 264022.5 | AM15: 199500 | AN15: =1.05*AB15 | AO15: =1.05*AC15 | AP15: =1.05*AD15 | AQ15: =1.05*AE15 | AR15: =1.05*AF15 | AS15: =1.05*AG15 | AT15: =1.05*AH15 | AU15: =1.05*AI15 | ... AY15: =1.05*AM15
B16: WP | C16: West Portal | D16: 0 | E16: 0 | F16: 0 | G16: 0 | H16: 0 | I16: 0 | J16: 0 | K16: 0 | L16: 0 | M16: 0 | N16: 470 | O16: 4114 | P16: 1573 | Q16: 1513 | R16: 784 | S16: 370 | T16: 26 | U16: 225 | V16: 99 | W16: 0 | X16: 0 | Y16: 40000 | Z16: 70000 | AA16: 78000 | AB16: 75000 | AC16: 86822 | AD16: 85300 | AE16: 127703 | AF16: 79689 | AG16: 76768 | AH16: 70767 | AI16: 102739 | AJ16: 68837 | AK16: 83777 | AL16: 79979 | AM16: 79880 | AN16: 94526.25 | AO16: 91163.1 | AP16: 89565 | AQ16: 134088.15 | AR16: 83673.45 | AS16: 80606.4 | AT16: 74305.35 | AU16: 107875.95 | AV16: 72278.85 | AW16: 87965.85 | AX16: 83977.95 | AY16: 83874
B17: WW | C17: Westwood | D17: 71187 | E17: 96307 | F17: 93607 | G17: 77241 | H17: 90103 | I17: 75890 | J17: 75128 | K17: 59513 | L17: 67496 | M17: 64714 | N17: 67128 | O17: 61457 | P17: 71360 | Q17: 69405 | R17: 62992 | S17: 49441 | T17: 60750 | U17: 41757 | V17: 47537 | W17: 64000 | X17: 72000 | Y17: 80000 | Z17: 85600 | AA17: 74900 | AB17: 74928 | AC17: 75000 | AD17: 66141.6 | AE17: 61000 | AF17: 75000 | AG17: 75000 | AH17: 65100 | AI17: 67200 | AJ17: 75600 | AK17: 84000 | AL17: 89880 | AM17: 78645 | AN17: 78674.4 | AO17: 76519.01 | AP17: 69448.68 | AQ17: 61000 | AR17: 71000 | AS17: 71662.5 | AT17: 68355 | AU17: 70560 | AV17: 79380 | AW17: 88200 | AX17: 94374 | AY17: 82577.25
B18: TOTAL | C18: All Studios | D18: =SUM(D6:D17) | E18: =SUM(E6:E17) | F18: =SUM(F6:F17) | G18: =SUM(G6:G17) | H18: =SUM(H6:H17) | I18: =SUM(I6:I17) | J18: =SUM(J6:J17) | K18: =SUM(K6:K17) | ... AY18: =SUM(AY6:AY17)
B20: Annual Summary
B21: Code | C21: Studio | D21: 2025 | E21: 2026 | F21: 2027 | G21: 2028
B22: BK | C22: Berkeley | D22: =SUM(D6:O6) | E22: =SUM(P6:AA6) | F22: =SUM(AB6:AM6) | G22: =SUM(AN6:AY6)
B23: CC | C23: Culver City | D23: =SUM(D7:O7) | E23: =SUM(P7:AA7) | F23: =SUM(AB7:AM7) | G23: =SUM(AN7:AY7)
B24: DN | C24: Danville | D24: =SUM(D8:O8) | E24: =SUM(P8:AA8) | F24: =SUM(AB8:AM8) | G24: =SUM(AN8:AY8)
B25: LF | C25: Lafayette | D25: =SUM(D9:O9) | E25: =SUM(P9:AA9) | F25: =SUM(AB9:AM9) | G25: =SUM(AN9:AY9)
B26: MR | C26: Marin | D26: =SUM(D10:O10) | E26: =SUM(P10:AA10) | F26: =SUM(AB10:AM10) | G26: =SUM(AN10:AY10)
B27: OP | C27: Ocean Park | D27: =SUM(D11:O11) | E27: =SUM(P11:AA11) | F27: =SUM(AB11:AM11) | G27: =SUM(AN11:AY11)
B28: PH | C28: Presidio Heights | D28: =SUM(D12:O12) | E28: =SUM(P12:AA12) | F28: =SUM(AB12:AM12) | G28: =SUM(AN12:AY12)
B29: RH | C29: Russian Hill | D29: =SUM(D13:O13) | E29: =SUM(P13:AA13) | F29: =SUM(AB13:AM13) | G29: =SUM(AN13:AY13)
B30: SB | C30: Santa Barbara | D30: =SUM(D14:O14) | E30: =SUM(P14:AA14) | F30: =SUM(AB14:AM14) | G30: =SUM(AN14:AY14)
B31: SM | C31: Santa Monica | D31: =SUM(D15:O15) | E31: =SUM(P15:AA15) | F31: =SUM(AB15:AM15) | G31: =SUM(AN15:AY15)
B32: WP | C32: West Portal | D32: =SUM(D16:O16) | E32: =SUM(P16:AA16) | F32: =SUM(AB16:AM16) | G32: =SUM(AN16:AY16)
B33: WW | C33: Westwood | D33: =SUM(D17:O17) | E33: =SUM(P17:AA17) | F33: =SUM(AB17:AM17) | G33: =SUM(AN17:AY17)
B34: TOTAL | C34: All Studios | D34: =SUM(D22:D33) | E34: =SUM(E22:E33) | F34: =SUM(F22:F33) | G34: =SUM(G22:G33)
B100: 2025 SALES HISTORY (hidden helper for lag formulas) | P100: 2025-07 | Q100: 2025-08 | R100: 2025-09 | S100: 2025-10 | T100: 2025-11 | U100: 2025-12
P101: 808077 | Q101: 930709 | R101: 758432 | S101: 830044 | T101: 833160 | U101: 847328
B102: 2025 helper: BK (Berkeley) | T102: 102111.01 | U102: 103847.42
B103: 2025 helper: CC (Culver City) | T103: 36886.61 | U103: 37513.88
B104: 2025 helper: DN (Danville) | T104: 18359.97 | U104: 18672.19
B105: 2025 helper: LF (Lafayette) | T105: 84253.69 | U105: 85686.43
B106: 2025 helper: MR (Marin) | T106: 92130.72 | U106: 93697.42
B107: 2025 helper: OP (Ocean Park) | T107: 56662.27 | U107: 57625.82
B108: 2025 helper: PH (Presidio Heights) | T108: 123229.91 | U108: 125325.45
B109: 2025 helper: RH (Russian Hill) | T109: 80127.42 | U109: 81490
B110: 2025 helper: SB (Santa Barbara) | T110: 23052.3 | U110: 23444.3
B111: 2025 helper: SM (Santa Monica) | T111: 159966.86 | U111: 162687.12
B112: 2025 helper: WP (West Portal) | T112: 755.57 | U112: 768.42
B113: 2025 helper: WW (Westwood) | T113: 55623.67 | U113: 56569.55

Sheet Assumptions
B2: Assumptions
B3: Yellow cells are editable inputs. All other tabs reference these values.
B5: 1. Model Control
B6: Last Actuals Month | C6: Jul 2026
B7: Forecast Horizon (months) | C7: 32
B8: Forecast End Month | C8: Dec 2028
B10: 2. Revenue Recognition Curves
B11: Lag Month (0 = sale month) | C11: 0 | D11: 1 | E11: 2 | F11: 3 | G11: 4 | H11: 5 | I11: 6 | J11: Sum
B12: Earned % | C12: 0.3868 | D12: 0.2997 | E12: 0.0855 | F12: 0.0482 | G12: 0.0261 | H12: 0.0193 | I12: 0.0144 | J12: =SUM(C12:I12)
B13: Breakage % | C13: 0.0017 | D13: 0.0602 | E13: 0.0053 | F13: 0.0003 | G13: 0.0001 | H13: 0.0008 | I13: 0.0516 | J13: =SUM(C13:I13)
B14: Total (Earned + Breakage) | C14: =C12+C13 | D14: =D12+D13 | E14: =E12+E13 | F14: =F12+F13 | G14: =G12+G13 | H14: =H12+H13 | I14: =I12+I13 | J14: =SUM(C14:I14)
B16: 3. Rates (% of Gross Revenue)
B17: Refund Rate | C17: -0.0158 | D17: Refunds as % of gross revenue. Negative reduces net revenue.
B18: Discount Rate | C18: -0.0531 | D18: Discounts as % of gross revenue. Negative reduces net revenue.
B19: Merchant Fee % | C19: 0.0286 | D19: Payment processor fees as % of revenue.
B20: COGS % | C20: 0.0096 | D20: Cost of goods sold as % of revenue (retail).
B22: 4. Annual Escalation Rates
B23: Rent / Property Escalation | C23: 0.03 | D23: 3% annual rent step-up applied to forecast months
B24: Other OpEx Escalation | C24: 0.04 | D24: 4% annual escalation for all non-rent OpEx categories
B25: Sales YoY Growth | C25: 0.05 | D25: 5% YoY assumed for 2028 (applied to 2027 seasonal pattern)
B27: 5. Loan Terms (as of Apr 2026)
B28: Loan | C28: Original Amt | D28: Current Balance | E28: Rate (Annual) | F28: Avg Monthly Pmt | G28: Start Date | H28: Type
B29: MindBody Loan - SM | C29: 193706.66 | D29: 99348.21 | E29: 0 | F29: 18871.69 | G29: 2025-09 | H29: Amortizing
B30: MindBody Loan - PH | C30: 130000 | D30: 46989.79 | E30: 0 | F30: 16602.04 | G30: 2025-09 | H30: Amortizing
B31: MindBody Loan - LF | C31: 69249.28 | D31: 20599.85 | E31: 0 | F31: 12162.36 | G31: 2025-10 | H31: Amortizing
B32: MindBody Loan - MR | C32: 67443.81 | D32: 14815.18 | E32: 0 | F32: 13157.16 | G32: 2025-10 | H32: Amortizing
B33: Samson Loan | C33: 265414.78 | D33: 189034.12 | E33: 0 | F33: 25460.22 | G33: 2025-11 | H33: Amortizing
B34: Specialty Capital Loan | C34: 217184.21 | D34: 165407.89 | E34: 0 | F34: 25888.16 | G34: 2025-12 | H34: Amortizing
B35: Norbrook Inc Loan | C35: 162318 | D35: 162318 | E35: 0.08 | F35: 0 | G35: 2025-10 | H35: Interest-Only
B36: TOTAL DEBT | D36: =SUM(D29:D35) | F36: =SUM(F29:F35)
B38: 6. Active Studios
B39: Code | C39: Name
B40: BK | C40: Berkeley
B41: CC | C41: Culver City
B42: DN | C42: Danville
B43: LF | C43: Lafayette
B44: MR | C44: Marin
B45: OP | C45: Ocean Park
B46: PH | C46: Presidio Heights
B47: RH | C47: Russian Hill
B48: SB | C48: Santa Barbara
B49: SM | C49: Santa Monica
B50: WP | C50: West Portal
B51: WW | C51: Westwood

Sheet Cash, Debt & Equity
B2: Cash, Debt & Equity
B4: Item | P4: Jan 2026 | Q4: Feb 2026 | R4: Mar 2026 | S4: Apr 2026 | T4: May 2026 | U4: Jun 2026 | V4: Jul 2026 | W4: Aug 2026 | X4: Sep 2026 | Y4: Oct 2026 | Z4: Nov 2026 | AA4: Dec 2026 | AB4: Jan 2027 | AC4: Feb 2027 | AD4: Mar 2027 | AE4: Apr 2027 | AF4: May 2027 | AG4: Jun 2027 | AH4: Jul 2027 | AI4: Aug 2027 | AJ4: Sep 2027 | AK4: Oct 2027 | AL4: Nov 2027 | AM4: Dec 2027 | AN4: Jan 2028 | AO4: Feb 2028 | AP4: Mar 2028 | AQ4: Apr 2028 | AR4: May 2028 | AS4: Jun 2028 | AT4: Jul 2028 | AU4: Aug 2028 | AV4: Sep 2028 | AW4: Oct 2028 | AX4: Nov 2028 | AY4: Dec 2028
B5: CASH POSITION | D5: Jan 2025 | E5: Feb 2025 | F5: Mar 2025 | G5: Apr 2025 | H5: May 2025 | I5: Jun 2025 | J5: Jul 2025 | K5: Aug 2025 | L5: Sep 2025 | M5: Oct 2025 | N5: Nov 2025 | O5: Dec 2025
B6: Ending Cash Balance (from CF) | P6: ='Cash Flow Forecast (w prototype'!P40 | Q6: ='Cash Flow Forecast (w prototype'!Q40 | R6: ='Cash Flow Forecast (w prototype'!R40 | S6: ='Cash Flow Forecast (w prototype'!S40 | T6: ='Cash Flow Forecast (w prototype'!T40 | U6: ='Cash Flow Forecast (w prototype'!U40 | V6: ='Cash Flow Forecast (w prototype'!V40 | W6: ='Cash Flow Forecast (w prototype'!W40 | ... AY6: ='Cash Flow Forecast (w prototype'!AY40
B8: DEBT SCHEDULE — Loan Balances by Month
B9: MindBody Loan - SM | P9: ='QBO Actuals'!C195 | Q9: ='QBO Actuals'!D195 | R9: ='QBO Actuals'!E195 | S9: ='QBO Actuals'!F195 | T9: ='QBO Actuals'!G195 | U9: ='QBO Actuals'!H195 | V9: =MAX(U9-18871.69,0) | W9: =MAX(V9-18871.69,0) | X9: =MAX(W9-18871.69,0) | Y9: =MAX(X9-18871.69,0) | Z9: =MAX(Y9-18871.69,0) | AA9: =MAX(Z9-18871.69,0) | AB9: =MAX(AA9-18871.69,0) | AC9: =MAX(AB9-18871.69,0) | ... AY9: =MAX(AX9-18871.69,0)
B10: MindBody Loan - PH | P10: ='QBO Actuals'!C198 | Q10: ='QBO Actuals'!D198 | R10: ='QBO Actuals'!E198 | S10: ='QBO Actuals'!F198 | T10: ='QBO Actuals'!G198 | U10: ='QBO Actuals'!H198 | V10: =MAX(U10-16602.04,0) | W10: =MAX(V10-16602.04,0) | X10: =MAX(W10-16602.04,0) | Y10: =MAX(X10-16602.04,0) | Z10: =MAX(Y10-16602.04,0) | AA10: =MAX(Z10-16602.04,0) | AB10: =MAX(AA10-16602.04,0) | AC10: =MAX(AB10-16602.04,0) | ... AY10: =MAX(AX10-16602.04,0)
B11: MindBody Loan - LF | P11: ='QBO Actuals'!C201 | Q11: ='QBO Actuals'!D201 | R11: ='QBO Actuals'!E201 | S11: ='QBO Actuals'!F201 | T11: ='QBO Actuals'!G201 | U11: ='QBO Actuals'!H201 | V11: =MAX(U11-12162.36,0) | W11: =MAX(V11-12162.36,0) | X11: =MAX(W11-12162.36,0) | Y11: =MAX(X11-12162.36,0) | Z11: =MAX(Y11-12162.36,0) | AA11: =MAX(Z11-12162.36,0) | AB11: =MAX(AA11-12162.36,0) | AC11: =MAX(AB11-12162.36,0) | ... AY11: =MAX(AX11-12162.36,0)
B12: MindBody Loan - MR | P12: ='QBO Actuals'!C204 | Q12: ='QBO Actuals'!D204 | R12: ='QBO Actuals'!E204 | S12: ='QBO Actuals'!F204 | T12: ='QBO Actuals'!G204 | U12: ='QBO Actuals'!H204 | V12: =MAX(U12-13157.16,0) | W12: =MAX(V12-13157.16,0) | X12: =MAX(W12-13157.16,0) | Y12: =MAX(X12-13157.16,0) | Z12: =MAX(Y12-13157.16,0) | AA12: =MAX(Z12-13157.16,0) | AB12: =MAX(AA12-13157.16,0) | AC12: =MAX(AB12-13157.16,0) | ... AY12: =MAX(AX12-13157.16,0)
B13: Samson Loan | P13: ='QBO Actuals'!C206 | Q13: ='QBO Actuals'!D206 | R13: ='QBO Actuals'!E206 | S13: ='QBO Actuals'!F206 | T13: ='QBO Actuals'!G206 | U13: ='QBO Actuals'!H206 | V13: =MAX(U13-25460.22,0) | W13: =MAX(V13-25460.22,0) | X13: =MAX(W13-25460.22,0) | Y13: =MAX(X13-25460.22,0) | Z13: =MAX(Y13-25460.22,0) | AA13: =MAX(Z13-25460.22,0) | AB13: =MAX(AA13-25460.22,0) | AC13: =MAX(AB13-25460.22,0) | ... AY13: =MAX(AX13-25460.22,0)
B14: Specialty Capital Loan | P14: ='QBO Actuals'!C207 | Q14: ='QBO Actuals'!D207 | R14: ='QBO Actuals'!E207 | S14: ='QBO Actuals'!F207 | T14: ='QBO Actuals'!G207 | U14: ='QBO Actuals'!H207 | V14: =MAX(U14-25888.16,0) | W14: =MAX(V14-25888.16,0) | X14: =MAX(W14-25888.16,0) | Y14: =MAX(X14-25888.16,0) | Z14: =MAX(Y14-25888.16,0) | AA14: =MAX(Z14-25888.16,0) | AB14: =MAX(AA14-25888.16,0) | AC14: =MAX(AB14-25888.16,0) | ... AY14: =MAX(AX14-25888.16,0)
B15: Norbrook Inc Loan | P15: 0 | Q15: 0 | R15: 0 | S15: 162318 | T15: 162318 | U15: =T15 | V15: =U15 | W15: =V15 | X15: =W15 | Y15: =X15 | Z15: =Y15 | AA15: =Z15 | AB15: =AA15 | ... AY15: =AX15
B16: TOTAL DEBT | P16: =SUM(P9:P15) | Q16: =SUM(Q9:Q15) | R16: =SUM(R9:R15) | S16: =SUM(S9:S15) | T16: =SUM(T9:T15) | U16: =SUM(U9:U15) | V16: =SUM(V9:V15) | W16: =SUM(W9:W15) | ... AY16: =SUM(AY9:AY15)
B18: MONTHLY DEBT SERVICE
B19: MindBody Loan - SM | P19: 0 | Q19: 0 | R19: 0 | S19: 0 | T19: 0 | U19: =IF(U9>0,18871.69,0) | V19: =IF(V9>0,18871.69,0) | W19: =IF(W9>0,18871.69,0) | X19: =IF(X9>0,18871.69,0) | Y19: =IF(Y9>0,18871.69,0) | Z19: =IF(Z9>0,18871.69,0) | AA19: =IF(AA9>0,18871.69,0) | AB19: =IF(AB9>0,18871.69,0) | ... AY19: =IF(AY9>0,18871.69,0)
B20: MindBody Loan - PH | P20: 0 | Q20: 0 | R20: 0 | S20: 0 | T20: 0 | U20: =IF(U10>0,16602.04,0) | V20: =IF(V10>0,16602.04,0) | W20: =IF(W10>0,16602.04,0) | X20: =IF(X10>0,16602.04,0) | Y20: =IF(Y10>0,16602.04,0) | Z20: =IF(Z10>0,16602.04,0) | AA20: =IF(AA10>0,16602.04,0) | AB20: =IF(AB10>0,16602.04,0) | ... AY20: =IF(AY10>0,16602.04,0)
B21: MindBody Loan - LF | P21: 0 | Q21: 0 | R21: 0 | S21: 0 | T21: 0 | U21: =IF(U11>0,12162.36,0) | V21: =IF(V11>0,12162.36,0) | W21: =IF(W11>0,12162.36,0) | X21: =IF(X11>0,12162.36,0) | Y21: =IF(Y11>0,12162.36,0) | Z21: =IF(Z11>0,12162.36,0) | AA21: =IF(AA11>0,12162.36,0) | AB21: =IF(AB11>0,12162.36,0) | ... AY21: =IF(AY11>0,12162.36,0)
B22: MindBody Loan - MR | P22: 0 | Q22: 0 | R22: 0 | S22: 0 | T22: 0 | U22: =IF(U12>0,13157.16,0) | V22: =IF(V12>0,13157.16,0) | W22: =IF(W12>0,13157.16,0) | X22: =IF(X12>0,13157.16,0) | Y22: =IF(Y12>0,13157.16,0) | Z22: =IF(Z12>0,13157.16,0) | AA22: =IF(AA12>0,13157.16,0) | AB22: =IF(AB12>0,13157.16,0) | ... AY22: =IF(AY12>0,13157.16,0)
B23: Samson Loan | P23: 0 | Q23: 0 | R23: 0 | S23: 0 | T23: 94517.1 | U23: =IF(U13>0,25460.22,0) | V23: =IF(V13>0,25460.22,0) | W23: =IF(W13>0,25460.22,0) | X23: =IF(X13>0,25460.22,0) | Y23: =IF(Y13>0,25460.22,0) | Z23: =IF(Z13>0,25460.22,0) | AA23: =IF(AA13>0,25460.22,0) | AB23: =IF(AB13>0,25460.22,0) | ... AY23: =IF(AY13>0,25460.22,0)
B24: Specialty Capital Loan | P24: 0 | Q24: 0 | R24: 0 | S24: 0 | T24: 90052.62 | U24: =IF(U14>0,25888.16,0) | V24: =IF(V14>0,25888.16,0) | W24: =IF(W14>0,25888.16,0) | X24: =IF(X14>0,25888.16,0) | Y24: =IF(Y14>0,25888.16,0) | Z24: =IF(Z14>0,25888.16,0) | AA24: =IF(AA14>0,25888.16,0) | AB24: =IF(AB14>0,25888.16,0) | ... AY24: =IF(AY14>0,25888.16,0)
B25: Norbrook Inc Loan | P25: 0 | Q25: 0 | R25: 0 | S25: 0 | T25: 0 | U25: =U15*0.08/12 | V25: =V15*0.08/12 | W25: =W15*0.08/12 | X25: =X15*0.08/12 | Y25: =Y15*0.08/12 | Z25: =Z15*0.08/12 | AA25: =AA15*0.08/12 | AB25: =AB15*0.08/12 | ... AY25: =AY15*0.08/12
B26: TOTAL DEBT SERVICE | P26: =SUM(P19:P25) | Q26: =SUM(Q19:Q25) | R26: =SUM(R19:R25) | S26: =SUM(S19:S25) | T26: =SUM(T19:T25) | U26: =SUM(U19:U25) | V26: =SUM(V19:V25) | W26: =SUM(W19:W25) | ... AY26: =SUM(AY19:AY25)
B28: OWNER EQUITY / INTERCOMPANY
B29: Intercompany Net Position | P29: 224773.04 | Q29: 224773.04 | R29: 358106.37 | S29: 436439.7 | T29: 0 | U29: 0 | V29: 0 | W29: 0 | X29: 0 | Y29: 0 | Z29: 0 | AA29: 0 | AB29: 0 | AC29: 0 | AD29: 0 | AE29: 0 | AF29: 0 | AG29: 0 | AH29: 0 | AI29: 0 | AJ29: 0 | AK29: 0 | AL29: 0 | AM29: 0 | AN29: 0 | AO29: 0 | AP29: 0 | AQ29: 0 | AR29: 0 | AS29: 0 | AT29: 0 | AU29: 0 | AV29: 0 | AW29: 0 | AX29: 0 | AY29: 0

Sheet Cash Flow Forecast (w prototype
B2: Cash Flow Forecast with 1 Prototype (Cash Basis Cash Flow Statement - as such, no deffereds / no D&A add back / etc.)
B4: Monthly Cash Flow
B5: Line Item | C5: Annual Total | D5: Jan 2025 | E5: Feb 2025 | F5: Mar 2025 | G5: Apr 2025 | H5: May 2025 | I5: Jun 2025 | J5: Jul 2025 | K5: Aug 2025 | L5: Sep 2025 | M5: Oct 2025 | N5: Nov 2025 | O5: Dec 2025 | P5: Jan 2026 | Q5: Feb 2026 | R5: Mar 2026 | S5: Apr 2026 | T5: May 2026 | U5: Jun 2026 | V5: Jul 2026 | W5: Aug 2026 | X5: Sep 2026 | Y5: Oct 2026 | Z5: Nov 2026 | AA5: Dec 2026 | AB5: Jan 2027 | AC5: Feb 2027 | AD5: Mar 2027 | AE5: Apr 2027 | AF5: May 2027 | AG5: Jun 2027 | AH5: Jul 2027 | AI5: Aug 2027 | AJ5: Sep 2027 | AK5: Oct 2027 | AL5: Nov 2027 | AM5: Dec 2027 | AN5: Jan 2028 | AO5: Feb 2028 | AP5: Mar 2028 | AQ5: Apr 2028 | AR5: May 2028 | AS5: Jun 2028 | AT5: Jul 2028 | AU5: Aug 2028 | AV5: Sep 2028 | AW5: Oct 2028 | AX5: Nov 2028 | AY5: Dec 2028 | BA5: 2025 | BB5: =BA5+1 | BC5: =BB5+1 | BD5: =BC5+1 | BF5: LTM May 2026
B6: CASH INFLOWS
B7: Total Cash Sales | P7: =Summary!P6 | Q7: =Summary!Q6 | R7: =Summary!R6 | S7: =Summary!S6 | T7: =Summary!T6 | U7: =Summary!U6 | V7: =Summary!V6 | W7: =Summary!W6 | ... AY7: =Summary!AY6
B9: OPERATING OUTFLOWS
A10: =Prototype!A37 | B10: Property Costs | P10: ='P&L (Existing Locations)'!P19 | Q10: ='P&L (Existing Locations)'!Q19 | R10: ='P&L (Existing Locations)'!R19 | S10: ='P&L (Existing Locations)'!S19 | T10: ='P&L (Existing Locations)'!T19 | U10: ='P&L (Existing Locations)'!U19 | V10: ='P&L (Existing Locations)'!V19 | W10: ='P&L (Existing Locations)'!W19 | ... AA10: ='P&L (Existing Locations)'!AA19 | AB10: ='P&L (Existing Locations)'!AB19+Prototype!B37 | AC10: ='P&L (Existing Locations)'!AC19+Prototype!C37 | AD10: ='P&L (Existing Locations)'!AD19+Prototype!D37 | AE10: ='P&L (Existing Locations)'!AE19+Prototype!E37 | AF10: ='P&L (Existing Locations)'!AF19+Prototype!F37 | AG10: ='P&L (Existing Locations)'!AG19+Prototype!G37 | AH10: ='P&L (Existing Locations)'!AH19+Prototype!H37 | AI10: ='P&L (Existing Locations)'!AI19+Prototype!I37 | ... AY10: ='P&L (Existing Locations)'!AY19+Prototype!Y37
A11: =Prototype!A38 | B11: Staff Costs | P11: ='P&L (Existing Locations)'!P15 | Q11: ='P&L (Existing Locations)'!Q15 | R11: ='P&L (Existing Locations)'!R15 | S11: ='P&L (Existing Locations)'!S15 | T11: ='P&L (Existing Locations)'!T15 | U11: ='P&L (Existing Locations)'!U15 | V11: ='P&L (Existing Locations)'!V15 | W11: ='P&L (Existing Locations)'!W15 | ... AA11: ='P&L (Existing Locations)'!AA15 | AB11: ='P&L (Existing Locations)'!AB15+Prototype!B38 | AC11: ='P&L (Existing Locations)'!AC15+Prototype!C38 | AD11: ='P&L (Existing Locations)'!AD15+Prototype!D38 | AE11: ='P&L (Existing Locations)'!AE15+Prototype!E38 | AF11: ='P&L (Existing Locations)'!AF15+Prototype!F38 | AG11: ='P&L (Existing Locations)'!AG15+Prototype!G38 | AH11: ='P&L (Existing Locations)'!AH15+Prototype!H38 | AI11: ='P&L (Existing Locations)'!AI15+Prototype!I38 | ... AY11: ='P&L (Existing Locations)'!AY15+Prototype!Y38
A12: Utilities and Equipment, Maintineince, Moter Vehicles even through ZERO | B12: Utilities | P12: ='P&L (Existing Locations)'!P18 | Q12: ='P&L (Existing Locations)'!Q18 | R12: ='P&L (Existing Locations)'!R18 | S12: ='P&L (Existing Locations)'!S18 | T12: ='P&L (Existing Locations)'!T18 | U12: ='P&L (Existing Locations)'!U18 | V12: ='P&L (Existing Locations)'!V18 | W12: ='P&L (Existing Locations)'!W18 | ... AA12: ='P&L (Existing Locations)'!AA18 | AB12: ='P&L (Existing Locations)'!AB18+Prototype!B39+Prototype!B40+Prototype!B44 | AC12: ='P&L (Existing Locations)'!AC18+Prototype!C39+Prototype!C40+Prototype!C44 | AD12: ='P&L (Existing Locations)'!AD18+Prototype!D39+Prototype!D40+Prototype!D44 | AE12: ='P&L (Existing Locations)'!AE18+Prototype!E39+Prototype!E40+Prototype!E44 | AF12: ='P&L (Existing Locations)'!AF18+Prototype!F39+Prototype!F40+Prototype!F44 | AG12: ='P&L (Existing Locations)'!AG18+Prototype!G39+Prototype!G40+Prototype!G44 | AH12: ='P&L (Existing Locations)'!AH18+Prototype!H39+Prototype!H40+Prototype!H44 | AI12: ='P&L (Existing Locations)'!AI18+Prototype!I39+Prototype!I40+Prototype!I44 | ... AY12: ='P&L (Existing Locations)'!AY18+Prototype!Y39+Prototype!Y40+Prototype!Y44
A13: =Prototype!A41 | B13: Marketing & Promotion | P13: ='P&L (Existing Locations)'!P14 | Q13: ='P&L (Existing Locations)'!Q14 | R13: ='P&L (Existing Locations)'!R14 | S13: ='P&L (Existing Locations)'!S14 | T13: ='P&L (Existing Locations)'!T14 | U13: ='P&L (Existing Locations)'!U14 | V13: ='P&L (Existing Locations)'!V14 | W13: ='P&L (Existing Locations)'!W14 | ... AA13: ='P&L (Existing Locations)'!AA14 | AB13: ='P&L (Existing Locations)'!AB14+Prototype!B41 | AC13: ='P&L (Existing Locations)'!AC14+Prototype!C41 | AD13: ='P&L (Existing Locations)'!AD14+Prototype!D41 | AE13: ='P&L (Existing Locations)'!AE14+Prototype!E41 | AF13: ='P&L (Existing Locations)'!AF14+Prototype!F41 | AG13: ='P&L (Existing Locations)'!AG14+Prototype!G41 | AH13: ='P&L (Existing Locations)'!AH14+Prototype!H41 | AI13: ='P&L (Existing Locations)'!AI14+Prototype!I41 | ... AY13: ='P&L (Existing Locations)'!AY14+Prototype!Y41
A14: Admin and Finaince and Policy | B14: Administrative & G&A | P14: ='P&L (Existing Locations)'!P16 | Q14: ='P&L (Existing Locations)'!Q16 | R14: ='P&L (Existing Locations)'!R16 | S14: ='P&L (Existing Locations)'!S16 | T14: ='P&L (Existing Locations)'!T16 | U14: ='P&L (Existing Locations)'!U16 | V14: ='P&L (Existing Locations)'!V16 | W14: ='P&L (Existing Locations)'!W16 | ... AA14: ='P&L (Existing Locations)'!AA16 | AB14: ='P&L (Existing Locations)'!AB16+Prototype!B42+Prototype!B46 | AC14: ='P&L (Existing Locations)'!AC16+Prototype!C42+Prototype!C46 | AD14: ='P&L (Existing Locations)'!AD16+Prototype!D42+Prototype!D46 | AE14: ='P&L (Existing Locations)'!AE16+Prototype!E42+Prototype!E46 | AF14: ='P&L (Existing Locations)'!AF16+Prototype!F42+Prototype!F46 | AG14: ='P&L (Existing Locations)'!AG16+Prototype!G42+Prototype!G46 | AH14: ='P&L (Existing Locations)'!AH16+Prototype!H42+Prototype!H46 | AI14: ='P&L (Existing Locations)'!AI16+Prototype!I42+Prototype!I46 | ... AY14: ='P&L (Existing Locations)'!AY16+Prototype!Y42+Prototype!Y46
A15: =Prototype!A45 | B15: Professional Fees | P15: ='P&L (Existing Locations)'!P17 | Q15: ='P&L (Existing Locations)'!Q17 | R15: ='P&L (Existing Locations)'!R17 | S15: ='P&L (Existing Locations)'!S17 | T15: ='P&L (Existing Locations)'!T17 | U15: ='P&L (Existing Locations)'!U17 | V15: ='P&L (Existing Locations)'!V17 | W15: ='P&L (Existing Locations)'!W17 | ... AA15: ='P&L (Existing Locations)'!AA17 | AB15: ='P&L (Existing Locations)'!AB17+Prototype!B45 | AC15: ='P&L (Existing Locations)'!AC17+Prototype!C45 | AD15: ='P&L (Existing Locations)'!AD17+Prototype!D45 | AE15: ='P&L (Existing Locations)'!AE17+Prototype!E45 | AF15: ='P&L (Existing Locations)'!AF17+Prototype!F45 | AG15: ='P&L (Existing Locations)'!AG17+Prototype!G45 | AH15: ='P&L (Existing Locations)'!AH17+Prototype!H45 | AI15: ='P&L (Existing Locations)'!AI17+Prototype!I45 | ... AY15: ='P&L (Existing Locations)'!AY17+Prototype!Y45
A16: =Prototype!A43 | B16: Travel & Meals | P16: ='BK P&L'!P51+'CC P&L'!P50+'DN P&L'!P50+'LF P&L'!P51+'MR P&L'!P50+'OP P&L'!P50+'PH P&L'!P51+'RH P&L'!P50+'SB P&L'!P50+'SM P&L'!P51+'WP P&L'!P50+'WW P&L'!P51+'HO P&L'!P30 | Q16: ='BK P&L'!Q51+'CC P&L'!Q50+'DN P&L'!Q50+'LF P&L'!Q51+'MR P&L'!Q50+'OP P&L'!Q50+'PH P&L'!Q51+'RH P&L'!Q50+'SB P&L'!Q50+'SM P&L'!Q51+'WP P&L'!Q50+'WW P&L'!Q51+'HO P&L'!Q30 | R16: ='BK P&L'!R51+'CC P&L'!R50+'DN P&L'!R50+'LF P&L'!R51+'MR P&L'!R50+'OP P&L'!R50+'PH P&L'!R51+'RH P&L'!R50+'SB P&L'!R50+'SM P&L'!R51+'WP P&L'!R50+'WW P&L'!R51+'HO P&L'!R30 | S16: ='BK P&L'!S51+'CC P&L'!S50+'DN P&L'!S50+'LF P&L'!S51+'MR P&L'!S50+'OP P&L'!S50+'PH P&L'!S51+'RH P&L'!S50+'SB P&L'!S50+'SM P&L'!S51+'WP P&L'!S50+'WW P&L'!S51+'HO P&L'!S30 | T16: ='BK P&L'!T51+'CC P&L'!T50+'DN P&L'!T50+'LF P&L'!T51+'MR P&L'!T50+'OP P&L'!T50+'PH P&L'!T51+'RH P&L'!T50+'SB P&L'!T50+'SM P&L'!T51+'WP P&L'!T50+'WW P&L'!T51+'HO P&L'!T30 | U16: ='BK P&L'!U51+'CC P&L'!U50+'DN P&L'!U50+'LF P&L'!U51+'MR P&L'!U50+'OP P&L'!U50+'PH P&L'!U51+'RH P&L'!U50+'SB P&L'!U50+'SM P&L'!U51+'WP P&L'!U50+'WW P&L'!U51+'HO P&L'!U30 | V16: ='BK P&L'!V51+'CC P&L'!V50+'DN P&L'!V50+'LF P&L'!V51+'MR P&L'!V50+'OP P&L'!V50+'PH P&L'!V51+'RH P&L'!V50+'SB P&L'!V50+'SM P&L'!V51+'WP P&L'!V50+'WW P&L'!V51+'HO P&L'!V30 | W16: ='BK P&L'!W51+'CC P&L'!W50+'DN P&L'!W50+'LF P&L'!W51+'MR P&L'!W50+'OP P&L'!W50+'PH P&L'!W51+'RH P&L'!W50+'SB P&L'!W50+'SM P&L'!W51+'WP P&L'!W50+'WW P&L'!W51+'HO P&L'!W30 | ... AA16: ='BK P&L'!AA51+'CC P&L'!AA50+'DN P&L'!AA50+'LF P&L'!AA51+'MR P&L'!AA50+'OP P&L'!AA50+'PH P&L'!AA51+'RH P&L'!AA50+'SB P&L'!AA50+'SM P&L'!AA51+'WP P&L'!AA50+'WW P&L'!AA51+'HO P&L'!AA30 | AB16: ='BK P&L'!AB51+'CC P&L'!AB50+'DN P&L'!AB50+'LF P&L'!AB51+'MR P&L'!AB50+'OP P&L'!AB50+'PH P&L'!AB51+'RH P&L'!AB50+'SB P&L'!AB50+'SM P&L'!AB51+'WP P&L'!AB50+'WW P&L'!AB51+'HO P&L'!AB30+Prototype!B43 | AC16: ='BK P&L'!AC51+'CC P&L'!AC50+'DN P&L'!AC50+'LF P&L'!AC51+'MR P&L'!AC50+'OP P&L'!AC50+'PH P&L'!AC51+'RH P&L'!AC50+'SB P&L'!AC50+'SM P&L'!AC51+'WP P&L'!AC50+'WW P&L'!AC51+'HO P&L'!AC30+Prototype!C43 | AD16: ='BK P&L'!AD51+'CC P&L'!AD50+'DN P&L'!AD50+'LF P&L'!AD51+'MR P&L'!AD50+'OP P&L'!AD50+'PH P&L'!AD51+'RH P&L'!AD50+'SB P&L'!AD50+'SM P&L'!AD51+'WP P&L'!AD50+'WW P&L'!AD51+'HO P&L'!AD30+Prototype!D43 | AE16: ='BK P&L'!AE51+'CC P&L'!AE50+'DN P&L'!AE50+'LF P&L'!AE51+'MR P&L'!AE50+'OP P&L'!AE50+'PH P&L'!AE51+'RH P&L'!AE50+'SB P&L'!AE50+'SM P&L'!AE51+'WP P&L'!AE50+'WW P&L'!AE51+'HO P&L'!AE30+Prototype!E43 | AF16: ='BK P&L'!AF51+'CC P&L'!AF50+'DN P&L'!AF50+'LF P&L'!AF51+'MR P&L'!AF50+'OP P&L'!AF50+'PH P&L'!AF51+'RH P&L'!AF50+'SB P&L'!AF50+'SM P&L'!AF51+'WP P&L'!AF50+'WW P&L'!AF51+'HO P&L'!AF30+Prototype!F43 | AG16: ='BK P&L'!AG51+'CC P&L'!AG50+'DN P&L'!AG50+'LF P&L'!AG51+'MR P&L'!AG50+'OP P&L'!AG50+'PH P&L'!AG51+'RH P&L'!AG50+'SB P&L'!AG50+'SM P&L'!AG51+'WP P&L'!AG50+'WW P&L'!AG51+'HO P&L'!AG30+Prototype!G43 | AH16: ='BK P&L'!AH51+'CC P&L'!AH50+'DN P&L'!AH50+'LF P&L'!AH51+'MR P&L'!AH50+'OP P&L'!AH50+'PH P&L'!AH51+'RH P&L'!AH50+'SB P&L'!AH50+'SM P&L'!AH51+'WP P&L'!AH50+'WW P&L'!AH51+'HO P&L'!AH30+Prototype!H43 | AI16: ='BK P&L'!AI51+'CC P&L'!AI50+'DN P&L'!AI50+'LF P&L'!AI51+'MR P&L'!AI50+'OP P&L'!AI50+'PH P&L'!AI51+'RH P&L'!AI50+'SB P&L'!AI50+'SM P&L'!AI51+'WP P&L'!AI50+'WW P&L'!AI51+'HO P&L'!AI30+Prototype!I43 | ... AY16: ='BK P&L'!AY51+'CC P&L'!AY50+'DN P&L'!AY50+'LF P&L'!AY51+'MR P&L'!AY50+'OP P&L'!AY50+'PH P&L'!AY51+'RH P&L'!AY50+'SB P&L'!AY50+'SM P&L'!AY51+'WP P&L'!AY50+'WW P&L'!AY51+'HO P&L'!AY30+Prototype!Y43
B17: Merchant Fees & COGS | P17: ='P&L (Existing Locations)'!P12 | Q17: ='P&L (Existing Locations)'!Q12 | R17: ='P&L (Existing Locations)'!R12 | S17: ='P&L (Existing Locations)'!S12 | T17: ='P&L (Existing Locations)'!T12 | U17: ='P&L (Existing Locations)'!U12 | V17: ='P&L (Existing Locations)'!V12 | W17: ='P&L (Existing Locations)'!W12 | ... AY17: ='P&L (Existing Locations)'!AY12
B18: Studio Start Up Costs | P18: 0 | Q18: 0 | R18: 0 | S18: 0 | T18: 0 | U18: 0 | V18: 0 | W18: 0 | X18: 0 | Y18: 0 | Z18: 0 | AA18: 0 | AB18: 0 | AC18: 0 | AD18: 0 | AE18: 0 | AF18: 0 | AG18: 0 | AH18: 0 | AI18: 0 | AJ18: 0 | AK18: 0 | AL18: 0 | AM18: 0 | AN18: 0 | AO18: 0 | AP18: 0 | AQ18: 0 | AR18: 0 | AS18: 0 | AT18: 0 | AU18: 0 | AV18: 0 | AW18: 0 | AX18: 0 | AY18: 0
B19: Taxes | P19: ='P&L (Existing Locations)'!P25+'P&L (Existing Locations)'!P26 | Q19: ='P&L (Existing Locations)'!Q25+'P&L (Existing Locations)'!Q26 | R19: ='P&L (Existing Locations)'!R25+'P&L (Existing Locations)'!R26 | S19: ='P&L (Existing Locations)'!S25+'P&L (Existing Locations)'!S26 | T19: ='P&L (Existing Locations)'!T25+'P&L (Existing Locations)'!T26 | U19: ='P&L (Existing Locations)'!U25+'P&L (Existing Locations)'!U26 | V19: ='P&L (Existing Locations)'!V25+'P&L (Existing Locations)'!V26 | W19: ='P&L (Existing Locations)'!W25+'P&L (Existing Locations)'!W26 | ... AY19: ='P&L (Existing Locations)'!AY25+'P&L (Existing Locations)'!AY26
B20: PF Interest Expense | W20: =W49 | X20: =X49 | Y20: =Y49 | Z20: =Z49 | AA20: =AA49 | AB20: =AB49 | AC20: =AC49 | AD20: =AD49 | ... AY20: =AY49
B21: PF Fees (Debt Fees and Legal) | W21: ='Sources and Uses'!C16+'Sources and Uses'!C17
B22: Total Operating Cash Outflows | P22: =SUM(P10:P21) | Q22: =SUM(Q10:Q21) | R22: =SUM(R10:R21) | S22: =SUM(S10:S21) | T22: =SUM(T10:T21) | U22: =SUM(U10:U21) | V22: =SUM(V10:V21) | W22: =SUM(W10:W21) | ... AY22: =SUM(AY10:AY21)
B23: Net Cash from Operations | P23: =P7-P22 | Q23: =Q7-Q22 | R23: =R7-R22 | S23: =S7-S22 | T23: =T7-T22 | U23: =U7-U22 | V23: =V7-V22 | W23: =W7-W22 | ... AY23: =AY7-AY22
B25: INVESTING ACTIVITIES
B26: Equipment & Furniture | P26: 0 | Q26: 2497.4 | R26: 0 | S26: 0 | T26: 0 | U26: 0 | V26: 0 | W26: 0 | X26: 0 | Y26: 0 | Z26: 0 | AA26: 0 | AB26: =-Prototype!E30 | AC26: 0 | AD26: 0 | AE26: 0 | AF26: 0 | AG26: 0 | AH26: 0 | AI26: 0 | AJ26: 0 | AK26: 0 | AL26: 0 | AM26: 0 | AN26: 0 | AO26: 0 | AP26: 0 | AQ26: 0 | AR26: 0 | AS26: 0 | AT26: 0 | AU26: 0 | AV26: 0 | AW26: 0 | AX26: 0 | AY26: 0
B27: Leasehold Improvements | P27: -17810.67 | Q27: -7094.5 | R27: -24075 | S27: -1035.5 | T27: 0 | U27: 0 | V27: -275000 | W27: -160000 | X27: 0 | Y27: 0 | Z27: 0 | AA27: 0 | AB27: 0 | AC27: 0 | AD27: 0 | AE27: 0 | AF27: 0 | AG27: 0 | AH27: 0 | AI27: 0 | AJ27: 0 | AK27: 0 | AL27: 0 | AM27: 0 | AN27: 0 | AO27: 0 | AP27: 0 | AQ27: 0 | AR27: 0 | AS27: 0 | AT27: 0 | AU27: 0 | AV27: 0 | AW27: 0 | AX27: 0 | AY27: 0
B28: Deposits | P28: 0 | Q28: 0 | R28: 0 | S28: 0 | T28: 0 | U28: 0 | V28: 0 | W28: 0 | X28: 0 | Y28: 0 | Z28: 0 | AA28: 0 | AB28: 0 | AC28: 0 | AD28: 0 | AE28: 0 | AF28: 0 | AG28: 0 | AH28: 0 | AI28: 0 | AJ28: 0 | AK28: 0 | AL28: 0 | AM28: 0 | AN28: 0 | AO28: 0 | AP28: 0 | AQ28: 0 | AR28: 0 | AS28: 0 | AT28: 0 | AU28: 0 | AV28: 0 | AW28: 0 | AX28: 0 | AY28: 0
B29: Net Investing | P29: =SUM(P26:P28) | Q29: =SUM(Q26:Q28) | R29: =SUM(R26:R28) | S29: =SUM(S26:S28) | T29: =SUM(T26:T28) | U29: =SUM(U26:U28) | V29: =SUM(V26:V28) | W29: =SUM(W26:W28) | ... AY29: =SUM(AY26:AY28)
B31: FINANCING ACTIVITIES
B32: Loan Proceeds | P32: 9059.38 | Q32: 9059.38 | R32: 9059.38 | S32: 12507.09 | T32: 0 | U32: 0 | V32: 0 | W32: =W45 | X32: =X45 | Y32: 0 | Z32: 0 | AB32: 0 | AC32: 0 | AD32: 0 | AE32: 0 | AF32: 0 | AG32: 0 | AH32: 0 | AI32: 0 | AJ32: 0 | AK32: 0 | AL32: 0 | AM32: 0 | AN32: 0 | AO32: 0 | AP32: 0 | AQ32: 0 | AR32: 0 | AS32: 0 | AT32: 0 | AU32: 0 | AV32: 0 | AW32: 0 | AX32: 0 | AY32: 0
B33: Loan Repayments | P33: -132128.24 | Q33: -122128.76 | R33: -132834.5 | S33: -114793.66 | T33: =-'Cash, Debt & Equity'!T26 | U33: =-'Cash, Debt & Equity'!U26 | V33: =-'Cash, Debt & Equity'!V26 | W33: ='Cash, Debt & Equity'!X16*-1 | X33: 0 | Y33: 0 | Z33: 0 | AA33: 0 | AB33: 0 | AC33: 0 | AD33: 0 | AE33: 0 | AF33: 0 | AG33: 0 | AH33: 0 | AI33: 0 | AJ33: 0 | AK33: 0 | AL33: 0 | AM33: 0 | AN33: 0 | AO33: 0 | AP33: 0 | AQ33: 0 | AR33: 0 | AS33: 0 | AT33: 0 | AU33: 0 | AV33: 0 | AW33: 0 | AX33: 0 | AY33: 0
B34: Intercompany / Owner Contributions | P34: 0 | Q34: 0 | R34: 133333.33 | S34: 78333.33 | T34: 0 | U34: 0 | V34: 0 | W34: 0 | X34: 0 | Y34: 0 | Z34: -100000 | AA34: 0 | AB34: 0 | AC34: 0 | AD34: 0 | AE34: 0 | AF34: 0 | AG34: 0 | AH34: 0 | AI34: 0 | AJ34: 0 | AK34: 0 | AL34: 0 | AM34: 0 | AN34: 0 | AO34: 0 | AP34: 0 | AQ34: 0 | AR34: 0 | AS34: 0 | AT34: 0 | AU34: 0 | AV34: 0 | AW34: 0 | AX34: 0 | AY34: 0
B35: Net Financing | P35: =SUM(P32:P34) | Q35: =SUM(Q32:Q34) | R35: =SUM(R32:R34) | S35: =SUM(S32:S34) | T35: =SUM(T32:T34) | U35: =SUM(U32:U34) | V35: =SUM(V32:V34) | W35: =SUM(W32:W34) | ... AY35: =SUM(AY32:AY34)
B37: NET CHANGE IN CASH
B38: Net Change in Cash | P38: =P23+P29+P35 | Q38: =Q23+Q29+Q35 | R38: =R23+R29+R35 | S38: =S23+S29+S35 | T38: =T23+T29+T35 | U38: =U23+U29+U35 | V38: =V23+V29+V35 | W38: =W23+W29+W35 | ... AY38: =AY23+AY29+AY35
B39: Beginning Cash Balance | P39: =P40-P38 | Q39: =P40 | R39: =Q40 | S39: =R40 | T39: =S40 | U39: =T40 | V39: =U40 | W39: =V40 | X39: =W40 | ... AY39: =AX40
B40: Ending Cash Balance | P40: ='QBO Actuals'!C104 | Q40: ='QBO Actuals'!D104 | R40: ='QBO Actuals'!E104 | S40: ='QBO Actuals'!F104 | T40: ='QBO Actuals'!G104 | U40: ='QBO Actuals'!H104 | V40: =V39+V38 | W40: =W39+W38 | X40: =X39+X38 | Y40: =Y39+Y38 | Z40: =Z39+Z38 | AA40: =AA39+AA38 | AB40: =AB39+AB38 | AC40: =AC39+AC38 | ... AY40: =AY39+AY38
B42: PF Debt At Close
B44: New Debt, Beg of Period | W44: 0 | X44: =W47 | Y44: =X47 | Z44: =Y47 | AA44: =Z47 | AB44: =AA47 | AC44: =AB47 | AD44: =AC47 | AE44: =AD47 | ... AY44: =AX47
B45: Increase (+) | W45: ='Sources and Uses'!C21
B46: Paydown (-) | W46: 0 | X46: 0 | Y46: 0 | Z46: 0 | AA46: 0 | AB46: 0 | AC46: 0 | AD46: 0 | AE46: 0 | AF46: 0 | AG46: 0 | AH46: 0 | AI46: 0 | AJ46: 0 | AK46: 0 | AL46: 0 | AM46: 0 | AN46: 0 | AO46: 0 | AP46: 0 | AQ46: 0 | AR46: 0 | AS46: 0 | AT46: 0 | AU46: 0 | AV46: 0 | AW46: 0 | AX46: 0 | AY46: 0
B47: New Debt, End of Period | W47: =SUM(W44:W46) | X47: =SUM(X44:X46) | Y47: =SUM(Y44:Y46) | Z47: =SUM(Z44:Z46) | AA47: =SUM(AA44:AA46) | AB47: =SUM(AB44:AB46) | AC47: =SUM(AC44:AC46) | AD47: =SUM(AD44:AD46) | ... AY47: =SUM(AY44:AY46) | BB47: =AA47 | BC47: =AM47 | BD47: =AY47 | BF47: =BB47
B49: Cash Interest | C49: ='Sources and Uses'!D21 | W49: =$C$49*AVERAGE(W44,W47)/12 | X49: =$C$49*AVERAGE(X44,X47)/12 | Y49: =$C$49*AVERAGE(Y44,Y47)/12 | Z49: =$C$49*AVERAGE(Z44,Z47)/12 | AA49: =$C$49*AVERAGE(AA44,AA47)/12 | AB49: =$C$49*AVERAGE(AB44,AB47)/12 | AC49: =$C$49*AVERAGE(AC44,AC47)/12 | AD49: =$C$49*AVERAGE(AD44,AD47)/12 | ... AY49: =$C$49*AVERAGE(AY44,AY47)/12 | BB49: =SUM(P49:AA49) | BC49: =SUM(AB49:AM49) | BD49: =SUM(AN49:AY49)
B51: Studio Level EBITDA | D51: =Summary!D39 | E51: =Summary!E39 | F51: =Summary!F39 | G51: =Summary!G39 | H51: =Summary!H39 | I51: =Summary!I39 | J51: =Summary!J39 | K51: =Summary!K39 | ... AY51: =Summary!AY39 | BB51: =SUM(P51:AA51) | BC51: =SUM(AB51:AM51) | BD51: =SUM(AN51:AY51) | BF51: =SUM(I51:T51)
B52: Corporate Level EBITDA | D52: =Summary!D23 | E52: =Summary!E23 | F52: =Summary!F23 | G52: =Summary!G23 | H52: =Summary!H23 | I52: =Summary!I23 | J52: =Summary!J23 | K52: =Summary!K23 | ... AY52: =Summary!AY23 | BB52: =SUM(P52:AA52) | BC52: =SUM(AB52:AM52) | BD52: =SUM(AN52:AY52) | BF52: =SUM(I52:T52)
B53: Adjusted Corporate Level EBITDA | D53: =Summary!D59 | E53: =Summary!E59 | F53: =Summary!F59 | G53: =Summary!G59 | H53: =Summary!H59 | I53: =Summary!I59 | J53: =Summary!J59 | K53: =Summary!K59 | ... AY53: =Summary!AY59 | BB53: =SUM(P53:AA53) | BC53: =SUM(AB53:AM53) | BD53: =SUM(AN53:AY53) | BF53: =SUM(I53:T53)
B55: Debt / LTM Studio Level EBITDA | W55: =W47/SUM(L51:W51) | X55: =X47/SUM(M51:X51) | Y55: =Y47/SUM(N51:Y51) | Z55: =Z47/SUM(O51:Z51) | AA55: =AA47/SUM(P51:AA51) | AB55: =AB47/SUM(Q51:AB51) | AC55: =AC47/SUM(R51:AC51) | AD55: =AD47/SUM(S51:AD51) | ... AY55: =AY47/SUM(AN51:AY51) | BB55: =BB47/BB51 | BC55: =BC47/BC51 | BD55: =BD47/BD51 | BF55: =BF47/BF51
B56: Debt / Corporate Level EBITDA | W56: =W47/SUM(L52:W52) | X56: =X47/SUM(M52:X52) | Y56: =Y47/SUM(N52:Y52) | Z56: =Z47/SUM(O52:Z52) | AA56: =AA47/SUM(P52:AA52) | AB56: =AB47/SUM(Q52:AB52) | AC56: =AC47/SUM(R52:AC52) | AD56: =AD47/SUM(S52:AD52) | ... AY56: =AY47/SUM(AN52:AY52) | BB56: =BB47/BB52 | BC56: =BC47/BC52 | BD56: =BD47/BD52 | BF56: =BF47/BF52
B57: Debt / Adjusted Corporate Level EBITDA | W57: =W47/SUM(L53:W53) | X57: =X47/SUM(M53:X53) | Y57: =Y47/SUM(N53:Y53) | Z57: =Z47/SUM(O53:Z53) | AA57: =AA47/SUM(P53:AA53) | AB57: =AB47/SUM(Q53:AB53) | AC57: =AC47/SUM(R53:AC53) | AD57: =AD47/SUM(S53:AD53) | ... AY57: =AY47/SUM(AN53:AY53) | BB57: =BB47/BB53 | BC57: =BC47/BC53 | BD57: =BD47/BD53 | BF57: =BF47/BF53
B58: Corporate Level EBITDA / Cash Interest | W58: =W52/W49 | X58: =X52/X49 | Y58: =Y52/Y49 | Z58: =Z52/Z49 | AA58: =AA52/AA49 | AB58: =AB52/AB49 | AC58: =AC52/AC49 | AD58: =AD52/AD49 | ... AY58: =AY52/AY49 | BB58: =IFERROR(BB52/BB49,"NA") | BC58: =IFERROR(BC52/BC49,"NA") | BD58: =IFERROR(BD52/BD49,"NA") | BF58: =IFERROR(BF52/BF49,"NA")

Sheet P&L (Existing Locations)
B2: Profit & Loss (Consolidated)
B3: Actuals Jan-Jul 2026. Forecast Aug 2026+ uses formulas from Sales Forecast and Assumptions.
B4: Monthly P&L
B5: Line Item | D5: Jan 2025 | E5: Feb 2025 | F5: Mar 2025 | G5: Apr 2025 | H5: May 2025 | I5: Jun 2025 | J5: Jul 2025 | K5: Aug 2025 | L5: Sep 2025 | M5: Oct 2025 | N5: Nov 2025 | O5: Dec 2025 | P5: Jan 2026 | Q5: Feb 2026 | R5: Mar 2026 | S5: Apr 2026 | T5: May 2026 | U5: Jun 2026 | V5: Jul 2026 | W5: Aug 2026 | X5: Sep 2026 | Y5: Oct 2026 | Z5: Nov 2026 | AA5: Dec 2026 | AB5: Jan 2027 | AC5: Feb 2027 | AD5: Mar 2027 | AE5: Apr 2027 | AF5: May 2027 | AG5: Jun 2027 | AH5: Jul 2027 | AI5: Aug 2027 | AJ5: Sep 2027 | AK5: Oct 2027 | AL5: Nov 2027 | AM5: Dec 2027 | AN5: Jan 2028 | AO5: Feb 2028 | AP5: Mar 2028 | AQ5: Apr 2028 | AR5: May 2028 | AS5: Jun 2028 | AT5: Jul 2028 | AU5: Aug 2028 | AV5: Sep 2028 | AW5: Oct 2028 | AX5: Nov 2028 | AY5: Dec 2028
B6: Session Revenue | D6: 624194.18 | E6: 640401.13 | F6: 771305.41 | G6: 721737.32 | H6: 765537.02 | I6: 745441.08 | J6: 736428.09 | K6: 724732.03 | L6: 722621.96 | M6: 738386.52 | N6: 707731.79 | O6: 691997.32 | P6: ='QBO Actuals'!C80 | Q6: ='QBO Actuals'!D80 | R6: ='QBO Actuals'!E80 | S6: ='QBO Actuals'!F80 | T6: ='QBO Actuals'!G80 | U6: ='QBO Actuals'!H80 | V6: ='QBO Actuals'!I80 | W6: ='Sales Forecast'!W18*Assumptions!$C$12+'Sales Forecast'!V18*Assumptions!$D$12+'Sales Forecast'!U18*Assumptions!$E$12+'Sales Forecast'!T18*Assumptions!$F$12+'Sales Forecast'!S18*Assumptions!$G$12+'Sales Forecast'!R18*Assumptions!$H$12+'Sales Forecast'!Q18*Assumptions!$I$12 | X6: ='Sales Forecast'!X18*Assumptions!$C$12+'Sales Forecast'!W18*Assumptions!$D$12+'Sales Forecast'!V18*Assumptions!$E$12+'Sales Forecast'!U18*Assumptions!$F$12+'Sales Forecast'!T18*Assumptions!$G$12+'Sales Forecast'!S18*Assumptions!$H$12+'Sales Forecast'!R18*Assumptions!$I$12 | Y6: ='Sales Forecast'!Y18*Assumptions!$C$12+'Sales Forecast'!X18*Assumptions!$D$12+'Sales Forecast'!W18*Assumptions!$E$12+'Sales Forecast'!V18*Assumptions!$F$12+'Sales Forecast'!U18*Assumptions!$G$12+'Sales Forecast'!T18*Assumptions!$H$12+'Sales Forecast'!S18*Assumptions!$I$12 | Z6: ='Sales Forecast'!Z18*Assumptions!$C$12+'Sales Forecast'!Y18*Assumptions!$D$12+'Sales Forecast'!X18*Assumptions!$E$12+'Sales Forecast'!W18*Assumptions!$F$12+'Sales Forecast'!V18*Assumptions!$G$12+'Sales Forecast'!U18*Assumptions!$H$12+'Sales Forecast'!T18*Assumptions!$I$12 | AA6: ='Sales Forecast'!AA18*Assumptions!$C$12+'Sales Forecast'!Z18*Assumptions!$D$12+'Sales Forecast'!Y18*Assumptions!$E$12+'Sales Forecast'!X18*Assumptions!$F$12+'Sales Forecast'!W18*Assumptions!$G$12+'Sales Forecast'!V18*Assumptions!$H$12+'Sales Forecast'!U18*Assumptions!$I$12 | AB6: ='Sales Forecast'!AB18*Assumptions!$C$12+'Sales Forecast'!AA18*Assumptions!$D$12+'Sales Forecast'!Z18*Assumptions!$E$12+'Sales Forecast'!Y18*Assumptions!$F$12+'Sales Forecast'!X18*Assumptions!$G$12+'Sales Forecast'!W18*Assumptions!$H$12+'Sales Forecast'!V18*Assumptions!$I$12 | AC6: ='Sales Forecast'!AC18*Assumptions!$C$12+'Sales Forecast'!AB18*Assumptions!$D$12+'Sales Forecast'!AA18*Assumptions!$E$12+'Sales Forecast'!Z18*Assumptions!$F$12+'Sales Forecast'!Y18*Assumptions!$G$12+'Sales Forecast'!X18*Assumptions!$H$12+'Sales Forecast'!W18*Assumptions!$I$12 | AD6: ='Sales Forecast'!AD18*Assumptions!$C$12+'Sales Forecast'!AC18*Assumptions!$D$12+'Sales Forecast'!AB18*Assumptions!$E$12+'Sales Forecast'!AA18*Assumptions!$F$12+'Sales Forecast'!Z18*Assumptions!$G$12+'Sales Forecast'!Y18*Assumptions!$H$12+'Sales Forecast'!X18*Assumptions!$I$12 | ... AY6: ='Sales Forecast'!AY18*Assumptions!$C$12+'Sales Forecast'!AX18*Assumptions!$D$12+'Sales Forecast'!AW18*Assumptions!$E$12+'Sales Forecast'!AV18*Assumptions!$F$12+'Sales Forecast'!AU18*Assumptions!$G$12+'Sales Forecast'!AT18*Assumptions!$H$12+'Sales Forecast'!AS18*Assumptions!$I$12
B7: Breakage Revenue | D7: 75237.94 | E7: 109399.17 | F7: 140651.46 | G7: 149516.51 | H7: 181344.3 | I7: 149213.5 | J7: 157965.23 | K7: 206864.97 | L7: 213185.16 | M7: 179766.24 | N7: 238121.51 | O7: 304457.14 | P7: ='QBO Actuals'!C81 | Q7: ='QBO Actuals'!D81 | R7: ='QBO Actuals'!E81 | S7: ='QBO Actuals'!F81 | T7: ='QBO Actuals'!G81 | U7: ='QBO Actuals'!H81 | V7: ='QBO Actuals'!I81 | W7: ='Sales Forecast'!W18*Assumptions!$C$13+'Sales Forecast'!V18*Assumptions!$D$13+'Sales Forecast'!U18*Assumptions!$E$13+'Sales Forecast'!T18*Assumptions!$F$13+'Sales Forecast'!S18*Assumptions!$G$13+'Sales Forecast'!R18*Assumptions!$H$13+'Sales Forecast'!Q18*Assumptions!$I$13 | X7: ='Sales Forecast'!X18*Assumptions!$C$13+'Sales Forecast'!W18*Assumptions!$D$13+'Sales Forecast'!V18*Assumptions!$E$13+'Sales Forecast'!U18*Assumptions!$F$13+'Sales Forecast'!T18*Assumptions!$G$13+'Sales Forecast'!S18*Assumptions!$H$13+'Sales Forecast'!R18*Assumptions!$I$13 | Y7: ='Sales Forecast'!Y18*Assumptions!$C$13+'Sales Forecast'!X18*Assumptions!$D$13+'Sales Forecast'!W18*Assumptions!$E$13+'Sales Forecast'!V18*Assumptions!$F$13+'Sales Forecast'!U18*Assumptions!$G$13+'Sales Forecast'!T18*Assumptions!$H$13+'Sales Forecast'!S18*Assumptions!$I$13 | Z7: ='Sales Forecast'!Z18*Assumptions!$C$13+'Sales Forecast'!Y18*Assumptions!$D$13+'Sales Forecast'!X18*Assumptions!$E$13+'Sales Forecast'!W18*Assumptions!$F$13+'Sales Forecast'!V18*Assumptions!$G$13+'Sales Forecast'!U18*Assumptions!$H$13+'Sales Forecast'!T18*Assumptions!$I$13 | AA7: ='Sales Forecast'!AA18*Assumptions!$C$13+'Sales Forecast'!Z18*Assumptions!$D$13+'Sales Forecast'!Y18*Assumptions!$E$13+'Sales Forecast'!X18*Assumptions!$F$13+'Sales Forecast'!W18*Assumptions!$G$13+'Sales Forecast'!V18*Assumptions!$H$13+'Sales Forecast'!U18*Assumptions!$I$13 | AB7: ='Sales Forecast'!AB18*Assumptions!$C$13+'Sales Forecast'!AA18*Assumptions!$D$13+'Sales Forecast'!Z18*Assumptions!$E$13+'Sales Forecast'!Y18*Assumptions!$F$13+'Sales Forecast'!X18*Assumptions!$G$13+'Sales Forecast'!W18*Assumptions!$H$13+'Sales Forecast'!V18*Assumptions!$I$13 | AC7: ='Sales Forecast'!AC18*Assumptions!$C$13+'Sales Forecast'!AB18*Assumptions!$D$13+'Sales Forecast'!AA18*Assumptions!$E$13+'Sales Forecast'!Z18*Assumptions!$F$13+'Sales Forecast'!Y18*Assumptions!$G$13+'Sales Forecast'!X18*Assumptions!$H$13+'Sales Forecast'!W18*Assumptions!$I$13 | AD7: ='Sales Forecast'!AD18*Assumptions!$C$13+'Sales Forecast'!AC18*Assumptions!$D$13+'Sales Forecast'!AB18*Assumptions!$E$13+'Sales Forecast'!AA18*Assumptions!$F$13+'Sales Forecast'!Z18*Assumptions!$G$13+'Sales Forecast'!Y18*Assumptions!$H$13+'Sales Forecast'!X18*Assumptions!$I$13 | ... AY7: ='Sales Forecast'!AY18*Assumptions!$C$13+'Sales Forecast'!AX18*Assumptions!$D$13+'Sales Forecast'!AW18*Assumptions!$E$13+'Sales Forecast'!AV18*Assumptions!$F$13+'Sales Forecast'!AU18*Assumptions!$G$13+'Sales Forecast'!AT18*Assumptions!$H$13+'Sales Forecast'!AS18*Assumptions!$I$13
B8: Retail Sales | D8: 20273 | E8: 19453.92 | F8: 17164.03 | G8: 18478 | H8: 19384 | I8: 28826 | J8: 20010 | K8: 19175 | L8: 19247.98 | M8: 19640 | N8: 21643.2 | O8: 20189 | P8: ='QBO Actuals'!C19 | Q8: ='QBO Actuals'!D19 | R8: ='QBO Actuals'!E19 | S8: ='QBO Actuals'!F19 | T8: ='QBO Actuals'!G19 | U8: ='QBO Actuals'!H19 | V8: ='QBO Actuals'!I19 | W8: ='BK P&L'!W19+'CC P&L'!W18+'DN P&L'!W18+'LF P&L'!W19+'MR P&L'!W18+'OP P&L'!W18+'PH P&L'!W19+'RH P&L'!W18+'SB P&L'!W18+'SM P&L'!W19+'WP P&L'!W18+'WW P&L'!W19 | X8: ='BK P&L'!X19+'CC P&L'!X18+'DN P&L'!X18+'LF P&L'!X19+'MR P&L'!X18+'OP P&L'!X18+'PH P&L'!X19+'RH P&L'!X18+'SB P&L'!X18+'SM P&L'!X19+'WP P&L'!X18+'WW P&L'!X19 | Y8: ='BK P&L'!Y19+'CC P&L'!Y18+'DN P&L'!Y18+'LF P&L'!Y19+'MR P&L'!Y18+'OP P&L'!Y18+'PH P&L'!Y19+'RH P&L'!Y18+'SB P&L'!Y18+'SM P&L'!Y19+'WP P&L'!Y18+'WW P&L'!Y19 | Z8: ='BK P&L'!Z19+'CC P&L'!Z18+'DN P&L'!Z18+'LF P&L'!Z19+'MR P&L'!Z18+'OP P&L'!Z18+'PH P&L'!Z19+'RH P&L'!Z18+'SB P&L'!Z18+'SM P&L'!Z19+'WP P&L'!Z18+'WW P&L'!Z19 | AA8: ='BK P&L'!AA19+'CC P&L'!AA18+'DN P&L'!AA18+'LF P&L'!AA19+'MR P&L'!AA18+'OP P&L'!AA18+'PH P&L'!AA19+'RH P&L'!AA18+'SB P&L'!AA18+'SM P&L'!AA19+'WP P&L'!AA18+'WW P&L'!AA19 | AB8: ='BK P&L'!AB19+'CC P&L'!AB18+'DN P&L'!AB18+'LF P&L'!AB19+'MR P&L'!AB18+'OP P&L'!AB18+'PH P&L'!AB19+'RH P&L'!AB18+'SB P&L'!AB18+'SM P&L'!AB19+'WP P&L'!AB18+'WW P&L'!AB19 | AC8: ='BK P&L'!AC19+'CC P&L'!AC18+'DN P&L'!AC18+'LF P&L'!AC19+'MR P&L'!AC18+'OP P&L'!AC18+'PH P&L'!AC19+'RH P&L'!AC18+'SB P&L'!AC18+'SM P&L'!AC19+'WP P&L'!AC18+'WW P&L'!AC19 | AD8: ='BK P&L'!AD19+'CC P&L'!AD18+'DN P&L'!AD18+'LF P&L'!AD19+'MR P&L'!AD18+'OP P&L'!AD18+'PH P&L'!AD19+'RH P&L'!AD18+'SB P&L'!AD18+'SM P&L'!AD19+'WP P&L'!AD18+'WW P&L'!AD19 | ... AY8: ='BK P&L'!AY19+'CC P&L'!AY18+'DN P&L'!AY18+'LF P&L'!AY19+'MR P&L'!AY18+'OP P&L'!AY18+'PH P&L'!AY19+'RH P&L'!AY18+'SB P&L'!AY18+'SM P&L'!AY19+'WP P&L'!AY18+'WW P&L'!AY19
B9: Refunds | D9: -16377.01 | E9: -10335.55 | F9: -14180.05 | G9: -17645.51 | H9: -12735.29 | I9: -10897.91 | J9: -13385.21 | K9: -12377.04 | L9: -18282.51 | M9: -22049.66 | N9: -15320.98 | O9: -18935.02 | P9: ='QBO Actuals'!C20 | Q9: ='QBO Actuals'!D20 | R9: ='QBO Actuals'!E20 | S9: ='QBO Actuals'!F20 | T9: ='QBO Actuals'!G20 | U9: ='QBO Actuals'!H20 | V9: ='QBO Actuals'!I20 | W9: =(W6+W7)*Assumptions!$C$17 | X9: =(X6+X7)*Assumptions!$C$17 | Y9: =(Y6+Y7)*Assumptions!$C$17 | Z9: =(Z6+Z7)*Assumptions!$C$17 | AA9: =(AA6+AA7)*Assumptions!$C$17 | AB9: =(AB6+AB7)*Assumptions!$C$17 | AC9: =(AC6+AC7)*Assumptions!$C$17 | AD9: =(AD6+AD7)*Assumptions!$C$17 | ... AY9: =(AY6+AY7)*Assumptions!$C$17
B10: Discounts | D10: -73972.55 | E10: -63470.28 | F10: -69852.24 | G10: -68577.95 | H10: -75810.5 | I10: -59569.88 | J10: -56128.38 | K10: -56204.78 | L10: -59582.4 | M10: -54374.17 | N10: -48649.06 | O10: -54144.13 | P10: ='QBO Actuals'!C21 | Q10: ='QBO Actuals'!D21 | R10: ='QBO Actuals'!E21 | S10: ='QBO Actuals'!F21 | T10: ='QBO Actuals'!G21 | U10: ='QBO Actuals'!H21 | V10: ='QBO Actuals'!I21 | W10: =(W6+W7)*Assumptions!$C$18 | X10: =(X6+X7)*Assumptions!$C$18 | Y10: =(Y6+Y7)*Assumptions!$C$18 | Z10: =(Z6+Z7)*Assumptions!$C$18 | AA10: =(AA6+AA7)*Assumptions!$C$18 | AB10: =(AB6+AB7)*Assumptions!$C$18 | AC10: =(AC6+AC7)*Assumptions!$C$18 | AD10: =(AD6+AD7)*Assumptions!$C$18 | ... AY10: =(AY6+AY7)*Assumptions!$C$18
B11: Total Revenue | D11: =SUM(D6:D10) | E11: =SUM(E6:E10) | F11: =SUM(F6:F10) | G11: =SUM(G6:G10) | H11: =SUM(H6:H10) | I11: =SUM(I6:I10) | J11: =SUM(J6:J10) | K11: =SUM(K6:K10) | ... AM11: =SUM(AM6:AM10) | AN11: =AN6+AN7+AN8+AN9+AN10 | AO11: =AO6+AO7+AO8+AO9+AO10 | AP11: =AP6+AP7+AP8+AP9+AP10 | AQ11: =AQ6+AQ7+AQ8+AQ9+AQ10 | AR11: =AR6+AR7+AR8+AR9+AR10 | AS11: =AS6+AS7+AS8+AS9+AS10 | AT11: =AT6+AT7+AT8+AT9+AT10 | AU11: =AU6+AU7+AU8+AU9+AU10 | ... AY11: =AY6+AY7+AY8+AY9+AY10
B12: COGS & Merchant Fees | D12: 41641.16 | E12: 30846.42 | F12: 34854.82 | G12: 37107.82 | H12: 31160.63 | I12: 35143.51 | J12: 33198.03 | K12: 34927.63 | L12: 32453.66 | M12: 32055.74 | N12: 33975.06 | O12: 54721.69 | P12: ='QBO Actuals'!C87 | Q12: ='QBO Actuals'!D87 | R12: ='QBO Actuals'!E87 | S12: ='QBO Actuals'!F87 | T12: ='QBO Actuals'!G87 | U12: ='QBO Actuals'!H87 | V12: ='QBO Actuals'!I87 | W12: =W11*(Assumptions!$C$19+Assumptions!$C$20) | X12: =X11*(Assumptions!$C$19+Assumptions!$C$20) | Y12: =Y11*(Assumptions!$C$19+Assumptions!$C$20) | Z12: =Z11*(Assumptions!$C$19+Assumptions!$C$20) | AA12: =AA11*(Assumptions!$C$19+Assumptions!$C$20) | AB12: =AB11*(Assumptions!$C$19+Assumptions!$C$20) | AC12: =AC11*(Assumptions!$C$19+Assumptions!$C$20) | AD12: =AD11*(Assumptions!$C$19+Assumptions!$C$20) | ... AY12: =AY11*(Assumptions!$C$19+Assumptions!$C$20)
B13: Gross Profit | D13: =D11-D12 | E13: =E11-E12 | F13: =F11-F12 | G13: =G11-G12 | H13: =H11-H12 | I13: =I11-I12 | J13: =J11-J12 | K13: =K11-K12 | ... AY13: =AY11-AY12
B14: Marketing | D14: 19034.32 | E14: 17063.4 | F14: 25178.17 | G14: 17943.65 | H14: 25913.01 | I14: 34869.84 | J14: 23544.8 | K14: 25878.64 | L14: 30151.1 | M14: 31586.11 | N14: 40588.79 | O14: 31249.9 | P14: ='QBO Actuals'!C82 | Q14: ='QBO Actuals'!D82 | R14: ='QBO Actuals'!E82 | S14: ='QBO Actuals'!F82 | T14: ='QBO Actuals'!G82 | U14: ='QBO Actuals'!H82 | V14: ='QBO Actuals'!I82 | W14: ='BK P&L'!W34+'CC P&L'!W33+'DN P&L'!W33+'LF P&L'!W34+'MR P&L'!W33+'OP P&L'!W33+'PH P&L'!W34+'RH P&L'!W33+'SB P&L'!W33+'SM P&L'!W34+'WP P&L'!W33+'WW P&L'!W34+'HO P&L'!W12 | X14: ='BK P&L'!X34+'CC P&L'!X33+'DN P&L'!X33+'LF P&L'!X34+'MR P&L'!X33+'OP P&L'!X33+'PH P&L'!X34+'RH P&L'!X33+'SB P&L'!X33+'SM P&L'!X34+'WP P&L'!X33+'WW P&L'!X34+'HO P&L'!X12 | Y14: ='BK P&L'!Y34+'CC P&L'!Y33+'DN P&L'!Y33+'LF P&L'!Y34+'MR P&L'!Y33+'OP P&L'!Y33+'PH P&L'!Y34+'RH P&L'!Y33+'SB P&L'!Y33+'SM P&L'!Y34+'WP P&L'!Y33+'WW P&L'!Y34+'HO P&L'!Y12 | Z14: ='BK P&L'!Z34+'CC P&L'!Z33+'DN P&L'!Z33+'LF P&L'!Z34+'MR P&L'!Z33+'OP P&L'!Z33+'PH P&L'!Z34+'RH P&L'!Z33+'SB P&L'!Z33+'SM P&L'!Z34+'WP P&L'!Z33+'WW P&L'!Z34+'HO P&L'!Z12 | AA14: ='BK P&L'!AA34+'CC P&L'!AA33+'DN P&L'!AA33+'LF P&L'!AA34+'MR P&L'!AA33+'OP P&L'!AA33+'PH P&L'!AA34+'RH P&L'!AA33+'SB P&L'!AA33+'SM P&L'!AA34+'WP P&L'!AA33+'WW P&L'!AA34+'HO P&L'!AA12 | AB14: ='BK P&L'!AB34+'CC P&L'!AB33+'DN P&L'!AB33+'LF P&L'!AB34+'MR P&L'!AB33+'OP P&L'!AB33+'PH P&L'!AB34+'RH P&L'!AB33+'SB P&L'!AB33+'SM P&L'!AB34+'WP P&L'!AB33+'WW P&L'!AB34+'HO P&L'!AB12 | AC14: ='BK P&L'!AC34+'CC P&L'!AC33+'DN P&L'!AC33+'LF P&L'!AC34+'MR P&L'!AC33+'OP P&L'!AC33+'PH P&L'!AC34+'RH P&L'!AC33+'SB P&L'!AC33+'SM P&L'!AC34+'WP P&L'!AC33+'WW P&L'!AC34+'HO P&L'!AC12 | AD14: ='BK P&L'!AD34+'CC P&L'!AD33+'DN P&L'!AD33+'LF P&L'!AD34+'MR P&L'!AD33+'OP P&L'!AD33+'PH P&L'!AD34+'RH P&L'!AD33+'SB P&L'!AD33+'SM P&L'!AD34+'WP P&L'!AD33+'WW P&L'!AD34+'HO P&L'!AD12 | ... AY14: ='BK P&L'!AY34+'CC P&L'!AY33+'DN P&L'!AY33+'LF P&L'!AY34+'MR P&L'!AY33+'OP P&L'!AY33+'PH P&L'!AY34+'RH P&L'!AY33+'SB P&L'!AY33+'SM P&L'!AY34+'WP P&L'!AY33+'WW P&L'!AY34+'HO P&L'!AY12
B15: Payroll | D15: 419319.36 | E15: 423621.65 | F15: 479539.11 | G15: 456441.26 | H15: 558270.32 | I15: 533362.29 | J15: 551786.76 | K15: 563606.75 | L15: 576144.94 | M15: 597447.09 | N15: 566914.01 | O15: 601056.92 | P15: ='QBO Actuals'!C83 | Q15: ='QBO Actuals'!D83 | R15: ='QBO Actuals'!E83 | S15: ='QBO Actuals'!F83 | T15: ='QBO Actuals'!G83 | U15: ='QBO Actuals'!H83 | V15: ='QBO Actuals'!I83 | W15: ='BK P&L'!W39+'CC P&L'!W38+'DN P&L'!W38+'LF P&L'!W39+'MR P&L'!W38+'OP P&L'!W38+'PH P&L'!W39+'RH P&L'!W38+'SB P&L'!W38+'SM P&L'!W39+'WP P&L'!W38+'WW P&L'!W39+'HO P&L'!W17 | X15: ='BK P&L'!X39+'CC P&L'!X38+'DN P&L'!X38+'LF P&L'!X39+'MR P&L'!X38+'OP P&L'!X38+'PH P&L'!X39+'RH P&L'!X38+'SB P&L'!X38+'SM P&L'!X39+'WP P&L'!X38+'WW P&L'!X39+'HO P&L'!X17 | Y15: ='BK P&L'!Y39+'CC P&L'!Y38+'DN P&L'!Y38+'LF P&L'!Y39+'MR P&L'!Y38+'OP P&L'!Y38+'PH P&L'!Y39+'RH P&L'!Y38+'SB P&L'!Y38+'SM P&L'!Y39+'WP P&L'!Y38+'WW P&L'!Y39+'HO P&L'!Y17 | Z15: ='BK P&L'!Z39+'CC P&L'!Z38+'DN P&L'!Z38+'LF P&L'!Z39+'MR P&L'!Z38+'OP P&L'!Z38+'PH P&L'!Z39+'RH P&L'!Z38+'SB P&L'!Z38+'SM P&L'!Z39+'WP P&L'!Z38+'WW P&L'!Z39+'HO P&L'!Z17 | AA15: ='BK P&L'!AA39+'CC P&L'!AA38+'DN P&L'!AA38+'LF P&L'!AA39+'MR P&L'!AA38+'OP P&L'!AA38+'PH P&L'!AA39+'RH P&L'!AA38+'SB P&L'!AA38+'SM P&L'!AA39+'WP P&L'!AA38+'WW P&L'!AA39+'HO P&L'!AA17 | AB15: ='BK P&L'!AB39+'CC P&L'!AB38+'DN P&L'!AB38+'LF P&L'!AB39+'MR P&L'!AB38+'OP P&L'!AB38+'PH P&L'!AB39+'RH P&L'!AB38+'SB P&L'!AB38+'SM P&L'!AB39+'WP P&L'!AB38+'WW P&L'!AB39+'HO P&L'!AB17 | AC15: ='BK P&L'!AC39+'CC P&L'!AC38+'DN P&L'!AC38+'LF P&L'!AC39+'MR P&L'!AC38+'OP P&L'!AC38+'PH P&L'!AC39+'RH P&L'!AC38+'SB P&L'!AC38+'SM P&L'!AC39+'WP P&L'!AC38+'WW P&L'!AC39+'HO P&L'!AC17 | AD15: ='BK P&L'!AD39+'CC P&L'!AD38+'DN P&L'!AD38+'LF P&L'!AD39+'MR P&L'!AD38+'OP P&L'!AD38+'PH P&L'!AD39+'RH P&L'!AD38+'SB P&L'!AD38+'SM P&L'!AD39+'WP P&L'!AD38+'WW P&L'!AD39+'HO P&L'!AD17 | ... AY15: ='BK P&L'!AY39+'CC P&L'!AY38+'DN P&L'!AY38+'LF P&L'!AY39+'MR P&L'!AY38+'OP P&L'!AY38+'PH P&L'!AY39+'RH P&L'!AY38+'SB P&L'!AY38+'SM P&L'!AY39+'WP P&L'!AY38+'WW P&L'!AY39+'HO P&L'!AY17
B16: Software | D16: 26665.07 | E16: 27275.25 | F16: 26973.42 | G16: 28105.36 | H16: 27900.43 | I16: 28473.7 | J16: 21660.15 | K16: 28481.27 | L16: 36334.95 | M16: 49834.79 | N16: 38787.02 | O16: 32961.91 | P16: ='QBO Actuals'!C38+'QBO Actuals'!C47+'QBO Actuals'!C49 | Q16: ='QBO Actuals'!D38+'QBO Actuals'!D47+'QBO Actuals'!D49 | R16: ='QBO Actuals'!E38+'QBO Actuals'!E47+'QBO Actuals'!E49 | S16: ='QBO Actuals'!F38+'QBO Actuals'!F47+'QBO Actuals'!F49 | T16: ='QBO Actuals'!G38+'QBO Actuals'!G47+'QBO Actuals'!G49 | U16: ='QBO Actuals'!H38+'QBO Actuals'!H47+'QBO Actuals'!H49 | V16: ='QBO Actuals'!I38+'QBO Actuals'!I47+'QBO Actuals'!I49 | W16: ='BK P&L'!W43+'CC P&L'!W42+'DN P&L'!W42+'LF P&L'!W43+'MR P&L'!W42+'OP P&L'!W42+'PH P&L'!W43+'RH P&L'!W42+'SB P&L'!W42+'SM P&L'!W43+'WP P&L'!W42+'WW P&L'!W43+'HO P&L'!W22 | X16: ='BK P&L'!X43+'CC P&L'!X42+'DN P&L'!X42+'LF P&L'!X43+'MR P&L'!X42+'OP P&L'!X42+'PH P&L'!X43+'RH P&L'!X42+'SB P&L'!X42+'SM P&L'!X43+'WP P&L'!X42+'WW P&L'!X43+'HO P&L'!X22 | Y16: ='BK P&L'!Y43+'CC P&L'!Y42+'DN P&L'!Y42+'LF P&L'!Y43+'MR P&L'!Y42+'OP P&L'!Y42+'PH P&L'!Y43+'RH P&L'!Y42+'SB P&L'!Y42+'SM P&L'!Y43+'WP P&L'!Y42+'WW P&L'!Y43+'HO P&L'!Y22 | Z16: ='BK P&L'!Z43+'CC P&L'!Z42+'DN P&L'!Z42+'LF P&L'!Z43+'MR P&L'!Z42+'OP P&L'!Z42+'PH P&L'!Z43+'RH P&L'!Z42+'SB P&L'!Z42+'SM P&L'!Z43+'WP P&L'!Z42+'WW P&L'!Z43+'HO P&L'!Z22 | AA16: ='BK P&L'!AA43+'CC P&L'!AA42+'DN P&L'!AA42+'LF P&L'!AA43+'MR P&L'!AA42+'OP P&L'!AA42+'PH P&L'!AA43+'RH P&L'!AA42+'SB P&L'!AA42+'SM P&L'!AA43+'WP P&L'!AA42+'WW P&L'!AA43+'HO P&L'!AA22 | AB16: ='BK P&L'!AB43+'CC P&L'!AB42+'DN P&L'!AB42+'LF P&L'!AB43+'MR P&L'!AB42+'OP P&L'!AB42+'PH P&L'!AB43+'RH P&L'!AB42+'SB P&L'!AB42+'SM P&L'!AB43+'WP P&L'!AB42+'WW P&L'!AB43+'HO P&L'!AB22 | AC16: ='BK P&L'!AC43+'CC P&L'!AC42+'DN P&L'!AC42+'LF P&L'!AC43+'MR P&L'!AC42+'OP P&L'!AC42+'PH P&L'!AC43+'RH P&L'!AC42+'SB P&L'!AC42+'SM P&L'!AC43+'WP P&L'!AC42+'WW P&L'!AC43+'HO P&L'!AC22 | AD16: ='BK P&L'!AD43+'CC P&L'!AD42+'DN P&L'!AD42+'LF P&L'!AD43+'MR P&L'!AD42+'OP P&L'!AD42+'PH P&L'!AD43+'RH P&L'!AD42+'SB P&L'!AD42+'SM P&L'!AD43+'WP P&L'!AD42+'WW P&L'!AD43+'HO P&L'!AD22 | ... AY16: ='BK P&L'!AY43+'CC P&L'!AY42+'DN P&L'!AY42+'LF P&L'!AY43+'MR P&L'!AY42+'OP P&L'!AY42+'PH P&L'!AY43+'RH P&L'!AY42+'SB P&L'!AY42+'SM P&L'!AY43+'WP P&L'!AY42+'WW P&L'!AY43+'HO P&L'!AY22
B17: Professional Fees | D17: 12762.86 | E17: 6986.62 | F17: 6754.78 | G17: 2824.89 | H17: 14193.46 | I17: 28217.6 | J17: 16267.87 | K17: 22546.69 | L17: 25022.6 | M17: 59823.54 | N17: 47681.74 | O17: 59459.49 | P17: ='QBO Actuals'!C84 | Q17: ='QBO Actuals'!D84 | R17: ='QBO Actuals'!E84 | S17: ='QBO Actuals'!F84 | T17: ='QBO Actuals'!G84 | U17: ='QBO Actuals'!H84 | V17: ='QBO Actuals'!I84 | W17: ='BK P&L'!W48+'CC P&L'!W47+'DN P&L'!W47+'LF P&L'!W48+'MR P&L'!W47+'OP P&L'!W47+'PH P&L'!W48+'RH P&L'!W47+'SB P&L'!W47+'SM P&L'!W48+'WP P&L'!W47+'WW P&L'!W48+'HO P&L'!W27 | X17: ='BK P&L'!X48+'CC P&L'!X47+'DN P&L'!X47+'LF P&L'!X48+'MR P&L'!X47+'OP P&L'!X47+'PH P&L'!X48+'RH P&L'!X47+'SB P&L'!X47+'SM P&L'!X48+'WP P&L'!X47+'WW P&L'!X48+'HO P&L'!X27 | Y17: ='BK P&L'!Y48+'CC P&L'!Y47+'DN P&L'!Y47+'LF P&L'!Y48+'MR P&L'!Y47+'OP P&L'!Y47+'PH P&L'!Y48+'RH P&L'!Y47+'SB P&L'!Y47+'SM P&L'!Y48+'WP P&L'!Y47+'WW P&L'!Y48+'HO P&L'!Y27 | Z17: ='BK P&L'!Z48+'CC P&L'!Z47+'DN P&L'!Z47+'LF P&L'!Z48+'MR P&L'!Z47+'OP P&L'!Z47+'PH P&L'!Z48+'RH P&L'!Z47+'SB P&L'!Z47+'SM P&L'!Z48+'WP P&L'!Z47+'WW P&L'!Z48+'HO P&L'!Z27 | AA17: ='BK P&L'!AA48+'CC P&L'!AA47+'DN P&L'!AA47+'LF P&L'!AA48+'MR P&L'!AA47+'OP P&L'!AA47+'PH P&L'!AA48+'RH P&L'!AA47+'SB P&L'!AA47+'SM P&L'!AA48+'WP P&L'!AA47+'WW P&L'!AA48+'HO P&L'!AA27 | AB17: ='BK P&L'!AB48+'CC P&L'!AB47+'DN P&L'!AB47+'LF P&L'!AB48+'MR P&L'!AB47+'OP P&L'!AB47+'PH P&L'!AB48+'RH P&L'!AB47+'SB P&L'!AB47+'SM P&L'!AB48+'WP P&L'!AB47+'WW P&L'!AB48+'HO P&L'!AB27 | AC17: ='BK P&L'!AC48+'CC P&L'!AC47+'DN P&L'!AC47+'LF P&L'!AC48+'MR P&L'!AC47+'OP P&L'!AC47+'PH P&L'!AC48+'RH P&L'!AC47+'SB P&L'!AC47+'SM P&L'!AC48+'WP P&L'!AC47+'WW P&L'!AC48+'HO P&L'!AC27 | AD17: ='BK P&L'!AD48+'CC P&L'!AD47+'DN P&L'!AD47+'LF P&L'!AD48+'MR P&L'!AD47+'OP P&L'!AD47+'PH P&L'!AD48+'RH P&L'!AD47+'SB P&L'!AD47+'SM P&L'!AD48+'WP P&L'!AD47+'WW P&L'!AD48+'HO P&L'!AD27 | ... AY17: ='BK P&L'!AY48+'CC P&L'!AY47+'DN P&L'!AY47+'LF P&L'!AY48+'MR P&L'!AY47+'OP P&L'!AY47+'PH P&L'!AY48+'RH P&L'!AY47+'SB P&L'!AY47+'SM P&L'!AY48+'WP P&L'!AY47+'WW P&L'!AY48+'HO P&L'!AY27
B18: Utilities | D18: 3290.78 | E18: 5292.9 | F18: 4950.78 | G18: 5342.61 | H18: 5724.64 | I18: 5320.05 | J18: 5193.56 | K18: 7807.63 | L18: 8276.28 | M18: 8293.94 | N18: 9023.46 | O18: 7849.86 | P18: ='QBO Actuals'!C85 | Q18: ='QBO Actuals'!D85 | R18: ='QBO Actuals'!E85 | S18: ='QBO Actuals'!F85 | T18: ='QBO Actuals'!G85 | U18: ='QBO Actuals'!H85 | V18: ='QBO Actuals'!I85 | W18: ='BK P&L'!W57+'CC P&L'!W56+'DN P&L'!W56+'LF P&L'!W57+'MR P&L'!W56+'OP P&L'!W56+'PH P&L'!W57+'RH P&L'!W56+'SB P&L'!W56+'SM P&L'!W57+'WP P&L'!W56+'WW P&L'!W57 | X18: ='BK P&L'!X57+'CC P&L'!X56+'DN P&L'!X56+'LF P&L'!X57+'MR P&L'!X56+'OP P&L'!X56+'PH P&L'!X57+'RH P&L'!X56+'SB P&L'!X56+'SM P&L'!X57+'WP P&L'!X56+'WW P&L'!X57 | Y18: ='BK P&L'!Y57+'CC P&L'!Y56+'DN P&L'!Y56+'LF P&L'!Y57+'MR P&L'!Y56+'OP P&L'!Y56+'PH P&L'!Y57+'RH P&L'!Y56+'SB P&L'!Y56+'SM P&L'!Y57+'WP P&L'!Y56+'WW P&L'!Y57 | Z18: ='BK P&L'!Z57+'CC P&L'!Z56+'DN P&L'!Z56+'LF P&L'!Z57+'MR P&L'!Z56+'OP P&L'!Z56+'PH P&L'!Z57+'RH P&L'!Z56+'SB P&L'!Z56+'SM P&L'!Z57+'WP P&L'!Z56+'WW P&L'!Z57 | AA18: ='BK P&L'!AA57+'CC P&L'!AA56+'DN P&L'!AA56+'LF P&L'!AA57+'MR P&L'!AA56+'OP P&L'!AA56+'PH P&L'!AA57+'RH P&L'!AA56+'SB P&L'!AA56+'SM P&L'!AA57+'WP P&L'!AA56+'WW P&L'!AA57 | AB18: ='BK P&L'!AB57+'CC P&L'!AB56+'DN P&L'!AB56+'LF P&L'!AB57+'MR P&L'!AB56+'OP P&L'!AB56+'PH P&L'!AB57+'RH P&L'!AB56+'SB P&L'!AB56+'SM P&L'!AB57+'WP P&L'!AB56+'WW P&L'!AB57 | AC18: ='BK P&L'!AC57+'CC P&L'!AC56+'DN P&L'!AC56+'LF P&L'!AC57+'MR P&L'!AC56+'OP P&L'!AC56+'PH P&L'!AC57+'RH P&L'!AC56+'SB P&L'!AC56+'SM P&L'!AC57+'WP P&L'!AC56+'WW P&L'!AC57 | AD18: ='BK P&L'!AD57+'CC P&L'!AD56+'DN P&L'!AD56+'LF P&L'!AD57+'MR P&L'!AD56+'OP P&L'!AD56+'PH P&L'!AD57+'RH P&L'!AD56+'SB P&L'!AD56+'SM P&L'!AD57+'WP P&L'!AD56+'WW P&L'!AD57 | ... AY18: ='BK P&L'!AY57+'CC P&L'!AY56+'DN P&L'!AY56+'LF P&L'!AY57+'MR P&L'!AY56+'OP P&L'!AY56+'PH P&L'!AY57+'RH P&L'!AY56+'SB P&L'!AY56+'SM P&L'!AY57+'WP P&L'!AY56+'WW P&L'!AY57
B19: Property Costs | D19: 109746.49 | E19: 96893.54 | F19: 108142.11 | G19: 115917.92 | H19: 114881.56 | I19: 116880.2 | J19: 119885.67 | K19: 130853.31 | L19: 139047 | M19: 145628.28 | N19: 161382.55 | O19: 146607.13 | P19: ='QBO Actuals'!C86 | Q19: ='QBO Actuals'!D86 | R19: ='QBO Actuals'!E86 | S19: ='QBO Actuals'!F86 | T19: ='QBO Actuals'!G86 | U19: ='QBO Actuals'!H86 | V19: ='QBO Actuals'!I86 | W19: ='BK P&L'!W62+'CC P&L'!W61+'DN P&L'!W61+'LF P&L'!W62+'MR P&L'!W61+'OP P&L'!W61+'PH P&L'!W62+'RH P&L'!W61+'SB P&L'!W61+'SM P&L'!W62+'WP P&L'!W61+'WW P&L'!W62+'HO P&L'!W32 | X19: ='BK P&L'!X62+'CC P&L'!X61+'DN P&L'!X61+'LF P&L'!X62+'MR P&L'!X61+'OP P&L'!X61+'PH P&L'!X62+'RH P&L'!X61+'SB P&L'!X61+'SM P&L'!X62+'WP P&L'!X61+'WW P&L'!X62+'HO P&L'!X32 | Y19: ='BK P&L'!Y62+'CC P&L'!Y61+'DN P&L'!Y61+'LF P&L'!Y62+'MR P&L'!Y61+'OP P&L'!Y61+'PH P&L'!Y62+'RH P&L'!Y61+'SB P&L'!Y61+'SM P&L'!Y62+'WP P&L'!Y61+'WW P&L'!Y62+'HO P&L'!Y32 | Z19: ='BK P&L'!Z62+'CC P&L'!Z61+'DN P&L'!Z61+'LF P&L'!Z62+'MR P&L'!Z61+'OP P&L'!Z61+'PH P&L'!Z62+'RH P&L'!Z61+'SB P&L'!Z61+'SM P&L'!Z62+'WP P&L'!Z61+'WW P&L'!Z62+'HO P&L'!Z32 | AA19: ='BK P&L'!AA62+'CC P&L'!AA61+'DN P&L'!AA61+'LF P&L'!AA62+'MR P&L'!AA61+'OP P&L'!AA61+'PH P&L'!AA62+'RH P&L'!AA61+'SB P&L'!AA61+'SM P&L'!AA62+'WP P&L'!AA61+'WW P&L'!AA62+'HO P&L'!AA32 | AB19: ='BK P&L'!AB62+'CC P&L'!AB61+'DN P&L'!AB61+'LF P&L'!AB62+'MR P&L'!AB61+'OP P&L'!AB61+'PH P&L'!AB62+'RH P&L'!AB61+'SB P&L'!AB61+'SM P&L'!AB62+'WP P&L'!AB61+'WW P&L'!AB62+'HO P&L'!AB32 | AC19: ='BK P&L'!AC62+'CC P&L'!AC61+'DN P&L'!AC61+'LF P&L'!AC62+'MR P&L'!AC61+'OP P&L'!AC61+'PH P&L'!AC62+'RH P&L'!AC61+'SB P&L'!AC61+'SM P&L'!AC62+'WP P&L'!AC61+'WW P&L'!AC62+'HO P&L'!AC32 | AD19: ='BK P&L'!AD62+'CC P&L'!AD61+'DN P&L'!AD61+'LF P&L'!AD62+'MR P&L'!AD61+'OP P&L'!AD61+'PH P&L'!AD62+'RH P&L'!AD61+'SB P&L'!AD61+'SM P&L'!AD62+'WP P&L'!AD61+'WW P&L'!AD62+'HO P&L'!AD32 | ... AY19: ='BK P&L'!AY62+'CC P&L'!AY61+'DN P&L'!AY61+'LF P&L'!AY62+'MR P&L'!AY61+'OP P&L'!AY61+'PH P&L'!AY62+'RH P&L'!AY61+'SB P&L'!AY61+'SM P&L'!AY62+'WP P&L'!AY61+'WW P&L'!AY62+'HO P&L'!AY32
B20: Other Operating Expenses | D20: 8034.14 | E20: 14148.41 | F20: 9953.23 | G20: 17478.67 | H20: 13403.16 | I20: 38520.63 | J20: 21395.57 | K20: 22835.22 | L20: 19114.82 | M20: 18241.93 | N20: 20910.16 | O20: 14368.51 | P20: ='QBO Actuals'!C89-(P14+P15+P16+P17+P18+P19) | Q20: ='QBO Actuals'!D89-(Q14+Q15+Q16+Q17+Q18+Q19) | R20: ='QBO Actuals'!E89-(R14+R15+R16+R17+R18+R19) | S20: ='QBO Actuals'!F89-(S14+S15+S16+S17+S18+S19) | T20: ='QBO Actuals'!G89-(T14+T15+T16+T17+T18+T19) | U20: ='QBO Actuals'!H89-(U14+U15+U16+U17+U18+U19) | V20: ='QBO Actuals'!I89-(V14+V15+V16+V17+V18+V19) | W20: ='BK P&L'!W51+'CC P&L'!W50+'DN P&L'!W50+'LF P&L'!W51+'MR P&L'!W50+'OP P&L'!W50+'PH P&L'!W51+'RH P&L'!W50+'SB P&L'!W50+'SM P&L'!W51+'WP P&L'!W50+'WW P&L'!W51+'HO P&L'!W30 | X20: ='BK P&L'!X51+'CC P&L'!X50+'DN P&L'!X50+'LF P&L'!X51+'MR P&L'!X50+'OP P&L'!X50+'PH P&L'!X51+'RH P&L'!X50+'SB P&L'!X50+'SM P&L'!X51+'WP P&L'!X50+'WW P&L'!X51+'HO P&L'!X30 | Y20: ='BK P&L'!Y51+'CC P&L'!Y50+'DN P&L'!Y50+'LF P&L'!Y51+'MR P&L'!Y50+'OP P&L'!Y50+'PH P&L'!Y51+'RH P&L'!Y50+'SB P&L'!Y50+'SM P&L'!Y51+'WP P&L'!Y50+'WW P&L'!Y51+'HO P&L'!Y30 | Z20: ='BK P&L'!Z51+'CC P&L'!Z50+'DN P&L'!Z50+'LF P&L'!Z51+'MR P&L'!Z50+'OP P&L'!Z50+'PH P&L'!Z51+'RH P&L'!Z50+'SB P&L'!Z50+'SM P&L'!Z51+'WP P&L'!Z50+'WW P&L'!Z51+'HO P&L'!Z30 | AA20: ='BK P&L'!AA51+'CC P&L'!AA50+'DN P&L'!AA50+'LF P&L'!AA51+'MR P&L'!AA50+'OP P&L'!AA50+'PH P&L'!AA51+'RH P&L'!AA50+'SB P&L'!AA50+'SM P&L'!AA51+'WP P&L'!AA50+'WW P&L'!AA51+'HO P&L'!AA30 | AB20: ='BK P&L'!AB51+'CC P&L'!AB50+'DN P&L'!AB50+'LF P&L'!AB51+'MR P&L'!AB50+'OP P&L'!AB50+'PH P&L'!AB51+'RH P&L'!AB50+'SB P&L'!AB50+'SM P&L'!AB51+'WP P&L'!AB50+'WW P&L'!AB51+'HO P&L'!AB30 | AC20: ='BK P&L'!AC51+'CC P&L'!AC50+'DN P&L'!AC50+'LF P&L'!AC51+'MR P&L'!AC50+'OP P&L'!AC50+'PH P&L'!AC51+'RH P&L'!AC50+'SB P&L'!AC50+'SM P&L'!AC51+'WP P&L'!AC50+'WW P&L'!AC51+'HO P&L'!AC30 | AD20: ='BK P&L'!AD51+'CC P&L'!AD50+'DN P&L'!AD50+'LF P&L'!AD51+'MR P&L'!AD50+'OP P&L'!AD50+'PH P&L'!AD51+'RH P&L'!AD50+'SB P&L'!AD50+'SM P&L'!AD51+'WP P&L'!AD50+'WW P&L'!AD51+'HO P&L'!AD30 | ... AY20: ='BK P&L'!AY51+'CC P&L'!AY50+'DN P&L'!AY50+'LF P&L'!AY51+'MR P&L'!AY50+'OP P&L'!AY50+'PH P&L'!AY51+'RH P&L'!AY50+'SB P&L'!AY50+'SM P&L'!AY51+'WP P&L'!AY50+'WW P&L'!AY51+'HO P&L'!AY30
B21: Total Operating Expenses | D21: =SUM(D14:D20) | E21: =SUM(E14:E20) | F21: =SUM(F14:F20) | G21: =SUM(G14:G20) | H21: =SUM(H14:H20) | I21: =SUM(I14:I20) | J21: =SUM(J14:J20) | K21: =SUM(K14:K20) | ... AM21: =SUM(AM14:AM20) | AN21: =AN14+AN15+AN16+AN17+AN18+AN19+AN20 | AO21: =AO14+AO15+AO16+AO17+AO18+AO19+AO20 | AP21: =AP14+AP15+AP16+AP17+AP18+AP19+AP20 | AQ21: =AQ14+AQ15+AQ16+AQ17+AQ18+AQ19+AQ20 | AR21: =AR14+AR15+AR16+AR17+AR18+AR19+AR20 | AS21: =AS14+AS15+AS16+AS17+AS18+AS19+AS20 | AT21: =AT14+AT15+AT16+AT17+AT18+AT19+AT20 | AU21: =AU14+AU15+AU16+AU17+AU18+AU19+AU20 | ... AY21: =AY14+AY15+AY16+AY17+AY18+AY19+AY20
B22: Net Operating Income | D22: =D13-D21 | E22: =E13-E21 | F22: =F13-F21 | G22: =G13-G21 | H22: =H13-H21 | I22: =I13-I21 | J22: =J13-J21 | K22: =K13-K21 | ... AY22: =AY13-AY21
B23: Depreciation | D23: 15294.91 | E23: 17544.5 | F23: 17656.42 | G23: 19776.91 | H23: 19918.2 | I23: 23461.73 | J23: 23564.06 | K23: 24731.79 | L23: 28257.89 | M23: 30554.12 | N23: 31457.54 | O23: 18346.69 | P23: ='QBO Actuals'!C66 | Q23: ='QBO Actuals'!D66 | R23: ='QBO Actuals'!E66 | S23: ='QBO Actuals'!F66 | T23: ='QBO Actuals'!G66 | U23: ='QBO Actuals'!H66 | V23: ='QBO Actuals'!I66 | W23: ='BK P&L'!W66+'CC P&L'!W65+'DN P&L'!W65+'LF P&L'!W66+'MR P&L'!W65+'OP P&L'!W65+'PH P&L'!W66+'RH P&L'!W65+'SB P&L'!W65+'SM P&L'!W66+'WP P&L'!W65+'WW P&L'!W66+'HO P&L'!W38 | X23: ='BK P&L'!X66+'CC P&L'!X65+'DN P&L'!X65+'LF P&L'!X66+'MR P&L'!X65+'OP P&L'!X65+'PH P&L'!X66+'RH P&L'!X65+'SB P&L'!X65+'SM P&L'!X66+'WP P&L'!X65+'WW P&L'!X66+'HO P&L'!X38 | Y23: ='BK P&L'!Y66+'CC P&L'!Y65+'DN P&L'!Y65+'LF P&L'!Y66+'MR P&L'!Y65+'OP P&L'!Y65+'PH P&L'!Y66+'RH P&L'!Y65+'SB P&L'!Y65+'SM P&L'!Y66+'WP P&L'!Y65+'WW P&L'!Y66+'HO P&L'!Y38 | Z23: ='BK P&L'!Z66+'CC P&L'!Z65+'DN P&L'!Z65+'LF P&L'!Z66+'MR P&L'!Z65+'OP P&L'!Z65+'PH P&L'!Z66+'RH P&L'!Z65+'SB P&L'!Z65+'SM P&L'!Z66+'WP P&L'!Z65+'WW P&L'!Z66+'HO P&L'!Z38 | AA23: ='BK P&L'!AA66+'CC P&L'!AA65+'DN P&L'!AA65+'LF P&L'!AA66+'MR P&L'!AA65+'OP P&L'!AA65+'PH P&L'!AA66+'RH P&L'!AA65+'SB P&L'!AA65+'SM P&L'!AA66+'WP P&L'!AA65+'WW P&L'!AA66+'HO P&L'!AA38 | AB23: ='BK P&L'!AB66+'CC P&L'!AB65+'DN P&L'!AB65+'LF P&L'!AB66+'MR P&L'!AB65+'OP P&L'!AB65+'PH P&L'!AB66+'RH P&L'!AB65+'SB P&L'!AB65+'SM P&L'!AB66+'WP P&L'!AB65+'WW P&L'!AB66+'HO P&L'!AB38 | AC23: ='BK P&L'!AC66+'CC P&L'!AC65+'DN P&L'!AC65+'LF P&L'!AC66+'MR P&L'!AC65+'OP P&L'!AC65+'PH P&L'!AC66+'RH P&L'!AC65+'SB P&L'!AC65+'SM P&L'!AC66+'WP P&L'!AC65+'WW P&L'!AC66+'HO P&L'!AC38 | AD23: ='BK P&L'!AD66+'CC P&L'!AD65+'DN P&L'!AD65+'LF P&L'!AD66+'MR P&L'!AD65+'OP P&L'!AD65+'PH P&L'!AD66+'RH P&L'!AD65+'SB P&L'!AD65+'SM P&L'!AD66+'WP P&L'!AD65+'WW P&L'!AD66+'HO P&L'!AD38 | ... AY23: ='BK P&L'!AY66+'CC P&L'!AY65+'DN P&L'!AY65+'LF P&L'!AY66+'MR P&L'!AY65+'OP P&L'!AY65+'PH P&L'!AY66+'RH P&L'!AY65+'SB P&L'!AY65+'SM P&L'!AY66+'WP P&L'!AY65+'WW P&L'!AY66+'HO P&L'!AY38
B24: Interest Expense | D24: 0 | E24: 0 | F24: 0 | G24: 0 | H24: 0 | I24: 0 | J24: 0 | K24: 0 | L24: 14445 | M24: 8376.01 | N24: 18871.88 | O24: 19871.88 | P24: ='QBO Actuals'!C68+'QBO Actuals'!C67 | Q24: ='QBO Actuals'!D68+'QBO Actuals'!D67 | R24: ='QBO Actuals'!E68+'QBO Actuals'!E67 | S24: ='QBO Actuals'!F68+'QBO Actuals'!F67 | T24: ='QBO Actuals'!G68+'QBO Actuals'!G67 | U24: ='QBO Actuals'!H68+'QBO Actuals'!H67 | V24: ='QBO Actuals'!I68+'QBO Actuals'!I67 | W24: ='BK P&L'!W67+'CC P&L'!W66+'DN P&L'!W66+'LF P&L'!W67+'MR P&L'!W66+'OP P&L'!W66+'PH P&L'!W67+'RH P&L'!W66+'SB P&L'!W66+'SM P&L'!W67+'WP P&L'!W66+'WW P&L'!W67+'HO P&L'!W40 | X24: ='BK P&L'!X67+'CC P&L'!X66+'DN P&L'!X66+'LF P&L'!X67+'MR P&L'!X66+'OP P&L'!X66+'PH P&L'!X67+'RH P&L'!X66+'SB P&L'!X66+'SM P&L'!X67+'WP P&L'!X66+'WW P&L'!X67+'HO P&L'!X40 | Y24: ='BK P&L'!Y67+'CC P&L'!Y66+'DN P&L'!Y66+'LF P&L'!Y67+'MR P&L'!Y66+'OP P&L'!Y66+'PH P&L'!Y67+'RH P&L'!Y66+'SB P&L'!Y66+'SM P&L'!Y67+'WP P&L'!Y66+'WW P&L'!Y67+'HO P&L'!Y40 | Z24: ='BK P&L'!Z67+'CC P&L'!Z66+'DN P&L'!Z66+'LF P&L'!Z67+'MR P&L'!Z66+'OP P&L'!Z66+'PH P&L'!Z67+'RH P&L'!Z66+'SB P&L'!Z66+'SM P&L'!Z67+'WP P&L'!Z66+'WW P&L'!Z67+'HO P&L'!Z40 | AA24: ='BK P&L'!AA67+'CC P&L'!AA66+'DN P&L'!AA66+'LF P&L'!AA67+'MR P&L'!AA66+'OP P&L'!AA66+'PH P&L'!AA67+'RH P&L'!AA66+'SB P&L'!AA66+'SM P&L'!AA67+'WP P&L'!AA66+'WW P&L'!AA67+'HO P&L'!AA40 | AB24: ='BK P&L'!AB67+'CC P&L'!AB66+'DN P&L'!AB66+'LF P&L'!AB67+'MR P&L'!AB66+'OP P&L'!AB66+'PH P&L'!AB67+'RH P&L'!AB66+'SB P&L'!AB66+'SM P&L'!AB67+'WP P&L'!AB66+'WW P&L'!AB67+'HO P&L'!AB40 | AC24: ='BK P&L'!AC67+'CC P&L'!AC66+'DN P&L'!AC66+'LF P&L'!AC67+'MR P&L'!AC66+'OP P&L'!AC66+'PH P&L'!AC67+'RH P&L'!AC66+'SB P&L'!AC66+'SM P&L'!AC67+'WP P&L'!AC66+'WW P&L'!AC67+'HO P&L'!AC40 | AD24: ='BK P&L'!AD67+'CC P&L'!AD66+'DN P&L'!AD66+'LF P&L'!AD67+'MR P&L'!AD66+'OP P&L'!AD66+'PH P&L'!AD67+'RH P&L'!AD66+'SB P&L'!AD66+'SM P&L'!AD67+'WP P&L'!AD66+'WW P&L'!AD67+'HO P&L'!AD40 | ... AY24: ='BK P&L'!AY67+'CC P&L'!AY66+'DN P&L'!AY66+'LF P&L'!AY67+'MR P&L'!AY66+'OP P&L'!AY66+'PH P&L'!AY67+'RH P&L'!AY66+'SB P&L'!AY66+'SM P&L'!AY67+'WP P&L'!AY66+'WW P&L'!AY67+'HO P&L'!AY40
B25: Taxes Paid | D25: 0 | E25: 9041.24 | F25: 1700 | G25: 800 | H25: 0 | I25: 0 | J25: 0 | K25: 0 | L25: 0 | M25: 11790 | N25: 0 | O25: 0 | P25: ='QBO Actuals'!C69 | Q25: ='QBO Actuals'!D69 | R25: ='QBO Actuals'!E69 | S25: ='QBO Actuals'!F69 | T25: ='QBO Actuals'!G69 | U25: ='QBO Actuals'!H69 | V25: ='QBO Actuals'!I69 | W25: ='BK P&L'!W68+'CC P&L'!W67+'DN P&L'!W67+'LF P&L'!W68+'MR P&L'!W67+'OP P&L'!W67+'PH P&L'!W68+'RH P&L'!W67+'SB P&L'!W67+'SM P&L'!W68+'WP P&L'!W67+'WW P&L'!W68+'HO P&L'!W33 | X25: ='BK P&L'!X68+'CC P&L'!X67+'DN P&L'!X67+'LF P&L'!X68+'MR P&L'!X67+'OP P&L'!X67+'PH P&L'!X68+'RH P&L'!X67+'SB P&L'!X67+'SM P&L'!X68+'WP P&L'!X67+'WW P&L'!X68+'HO P&L'!X33 | Y25: ='BK P&L'!Y68+'CC P&L'!Y67+'DN P&L'!Y67+'LF P&L'!Y68+'MR P&L'!Y67+'OP P&L'!Y67+'PH P&L'!Y68+'RH P&L'!Y67+'SB P&L'!Y67+'SM P&L'!Y68+'WP P&L'!Y67+'WW P&L'!Y68+'HO P&L'!Y33 | Z25: ='BK P&L'!Z68+'CC P&L'!Z67+'DN P&L'!Z67+'LF P&L'!Z68+'MR P&L'!Z67+'OP P&L'!Z67+'PH P&L'!Z68+'RH P&L'!Z67+'SB P&L'!Z67+'SM P&L'!Z68+'WP P&L'!Z67+'WW P&L'!Z68+'HO P&L'!Z33 | AA25: ='BK P&L'!AA68+'CC P&L'!AA67+'DN P&L'!AA67+'LF P&L'!AA68+'MR P&L'!AA67+'OP P&L'!AA67+'PH P&L'!AA68+'RH P&L'!AA67+'SB P&L'!AA67+'SM P&L'!AA68+'WP P&L'!AA67+'WW P&L'!AA68+'HO P&L'!AA33 | AB25: ='BK P&L'!AB68+'CC P&L'!AB67+'DN P&L'!AB67+'LF P&L'!AB68+'MR P&L'!AB67+'OP P&L'!AB67+'PH P&L'!AB68+'RH P&L'!AB67+'SB P&L'!AB67+'SM P&L'!AB68+'WP P&L'!AB67+'WW P&L'!AB68+'HO P&L'!AB33 | AC25: ='BK P&L'!AC68+'CC P&L'!AC67+'DN P&L'!AC67+'LF P&L'!AC68+'MR P&L'!AC67+'OP P&L'!AC67+'PH P&L'!AC68+'RH P&L'!AC67+'SB P&L'!AC67+'SM P&L'!AC68+'WP P&L'!AC67+'WW P&L'!AC68+'HO P&L'!AC33 | AD25: ='BK P&L'!AD68+'CC P&L'!AD67+'DN P&L'!AD67+'LF P&L'!AD68+'MR P&L'!AD67+'OP P&L'!AD67+'PH P&L'!AD68+'RH P&L'!AD67+'SB P&L'!AD67+'SM P&L'!AD68+'WP P&L'!AD67+'WW P&L'!AD68+'HO P&L'!AD33 | ... AY25: ='BK P&L'!AY68+'CC P&L'!AY67+'DN P&L'!AY67+'LF P&L'!AY68+'MR P&L'!AY67+'OP P&L'!AY67+'PH P&L'!AY68+'RH P&L'!AY67+'SB P&L'!AY67+'SM P&L'!AY68+'WP P&L'!AY67+'WW P&L'!AY68+'HO P&L'!AY33
B26: Property Taxes (not allocated on studio by studio level) | D26: 3356.51 | E26: 3526.51 | F26: 3441.51 | G26: 3807.51 | H26: 3441.51 | I26: 4369.71 | J26: 8502.45 | K26: 3441.51 | L26: 3441.51 | M26: 5926.47 | N26: 3441.51 | O26: 3441.52 | P26: ='QBO Actuals'!C70 | Q26: ='QBO Actuals'!D70 | R26: ='QBO Actuals'!E70 | S26: ='QBO Actuals'!F70 | T26: ='QBO Actuals'!G70 | U26: ='QBO Actuals'!H70 | V26: ='QBO Actuals'!I70 | W26: 4178.19 | X26: 4178.19 | Y26: 4178.19 | Z26: 4178.19 | AA26: 4178.19 | AB26: 4178.19 | AC26: 4178.19 | AD26: 4178.19 | AE26: 4178.19 | AF26: 4178.19 | AG26: 4178.19 | AH26: 4178.19 | AI26: 4178.19 | AJ26: 4178.19 | AK26: 4178.19 | AL26: 4178.19 | AM26: 4178.19 | AN26: 4178.19 | AO26: 4178.19 | AP26: 4178.19 | AQ26: 4178.19 | AR26: 4178.19 | AS26: 4178.19 | AT26: 4178.19 | AU26: 4178.19 | AV26: 4178.19 | AW26: 4178.19 | AX26: 4178.19 | AY26: 4178.19
B27: Total Other Expenses | D27: =SUM(D23:D26) | E27: =SUM(E23:E26) | F27: =SUM(F23:F26) | G27: =SUM(G23:G26) | H27: =SUM(H23:H26) | I27: =SUM(I23:I26) | J27: =SUM(J23:J26) | K27: =SUM(K23:K26) | ... AM27: =SUM(AM23:AM26) | AN27: =AN23+AN24+AN25+AN26 | AO27: =AO23+AO24+AO25+AO26 | AP27: =AP23+AP24+AP25+AP26 | AQ27: =AQ23+AQ24+AQ25+AQ26 | AR27: =AR23+AR24+AR25+AR26 | AS27: =AS23+AS24+AS25+AS26 | AT27: =AT23+AT24+AT25+AT26 | AU27: =AU23+AU24+AU25+AU26 | ... AY27: =AY23+AY24+AY25+AY26
B28: Net Income | D28: =D22-D27 | E28: =E22-E27 | F28: =F22-F27 | G28: =G22-G27 | H28: =H22-H27 | I28: =I22-I27 | J28: =J22-J27 | K28: =K22-K27 | ... AY28: =AY22-AY27
B30: ADJUSTED EBITDA RECONCILIATION
B31: Net Operating Income (from above) | D31: =D22 | E31: =E22 | F31: =F22 | G31: =G22 | H31: =H22 | I31: =I22 | J31: =J22 | K31: =K22 | ... AY31: =AY22
B32: Add Backs:
B33: West Portal Start-Up Costs | P33: 16222.39 | Q33: 17111.26 | R33: 14310.31 | S33: 19092.69 | T33: 16815 | U33: 11669.37 | V33: 0 | W33: 0 | X33: 0 | Y33: 0 | Z33: 0 | AA33: 0 | AB33: 0 | AC33: 0 | AD33: 0 | AE33: 0 | AF33: 0 | AG33: 0 | AH33: 0 | AI33: 0 | AJ33: 0 | AK33: 0 | AL33: 0 | AM33: 0 | AN33: 0 | AO33: 0 | AP33: 0 | AQ33: 0 | AR33: 0 | AS33: 0 | AT33: 0 | AU33: 0 | AV33: 0 | AW33: 0 | AX33: 0 | AY33: 0
B34: ADP Error | P34: 0 | Q34: 0 | R34: 45000 | S34: 0 | T34: 0 | U34: 0 | V34: 0 | W34: 0 | X34: 0 | Y34: 0 | Z34: 0 | AA34: 0 | AB34: 0 | AC34: 0 | AD34: 0 | AE34: 0 | AF34: 0 | AG34: 0 | AH34: 0 | AI34: 0 | AJ34: 0 | AK34: 0 | AL34: 0 | AM34: 0 | AN34: 0 | AO34: 0 | AP34: 0 | AQ34: 0 | AR34: 0 | AS34: 0 | AT34: 0 | AU34: 0 | AV34: 0 | AW34: 0 | AX34: 0 | AY34: 0
B35: One-Time Legal Fees | P35: 2957 | Q35: 0 | R35: =3995.5 | S35: 0 | T35: 0 | U35: 770 | V35: 0 | W35: 0 | X35: 0 | Y35: 0 | Z35: 0 | AA35: 0 | AB35: 0 | AC35: 0 | AD35: 0 | AE35: 0 | AF35: 0 | AG35: 0 | AH35: 0 | AI35: 0 | AJ35: 0 | AK35: 0 | AL35: 0 | AM35: 0 | AN35: 0 | AO35: 0 | AP35: 0 | AQ35: 0 | AR35: 0 | AS35: 0 | AT35: 0 | AU35: 0 | AV35: 0 | AW35: 0 | AX35: 0 | AY35: 0
B36: Santa Barbara Start Up | P36: 3481 | Q36: 0 | R36: 0 | S36: 0 | T36: 0 | U36: 0 | V36: 0 | W36: 0 | X36: 0 | Y36: 0 | Z36: 0 | AA36: 0 | AB36: 0 | AC36: 0 | AD36: 0 | AE36: 0 | AF36: 0 | AG36: 0 | AH36: 0 | AI36: 0 | AJ36: 0 | AK36: 0 | AL36: 0 | AM36: 0 | AN36: 0 | AO36: 0 | AP36: 0 | AQ36: 0 | AR36: 0 | AS36: 0 | AT36: 0 | AU36: 0 | AV36: 0 | AW36: 0 | AX36: 0 | AY36: 0
B37: One-Time Accounting Fees | P37: 19887.5 | Q37: 0 | R37: 0 | S37: 0 | T37: 0 | U37: 0 | V37: 0 | W37: 0 | X37: 0 | Y37: 0 | Z37: 0 | AA37: 0 | AB37: 0 | AC37: 0 | AD37: 0 | AE37: 0 | AF37: 0 | AG37: 0 | AH37: 0 | AI37: 0 | AJ37: 0 | AK37: 0 | AL37: 0 | AM37: 0 | AN37: 0 | AO37: 0 | AP37: 0 | AQ37: 0 | AR37: 0 | AS37: 0 | AT37: 0 | AU37: 0 | AV37: 0 | AW37: 0 | AX37: 0 | AY37: 0
B38: Total Add Backs | D38: =SUM(D33:D37) | E38: =SUM(E33:E37) | F38: =SUM(F33:F37) | G38: =SUM(G33:G37) | H38: =SUM(H33:H37) | I38: =SUM(I33:I37) | J38: =SUM(J33:J37) | K38: =SUM(K33:K37) | ... AY38: =SUM(AY33:AY37)
B39: Adjusted EBITDA | D39: =D31+D38 | E39: =E31+E38 | F39: =F31+F38 | G39: =G31+G38 | H39: =H31+H38 | I39: =I31+I38 | J39: =J31+J38 | K39: =K31+K38 | ... AY39: =AY31+AY38

Sheet All Studios Summary (Existing)
B2: All Studios — Summary
B4: Studio / Metric | D4: Jan 2025 | E4: Feb 2025 | F4: Mar 2025 | G4: Apr 2025 | H4: May 2025 | I4: Jun 2025 | J4: Jul 2025 | K4: Aug 2025 | L4: Sep 2025 | M4: Oct 2025 | N4: Nov 2025 | O4: Dec 2025 | P4: Jan 2026 | Q4: Feb 2026 | R4: Mar 2026 | S4: Apr 2026 | T4: May 2026 | U4: Jun 2026 | V4: Jul 2026 | W4: Aug 2026 | X4: Sep 2026 | Y4: Oct 2026 | Z4: Nov 2026 | AA4: Dec 2026 | AB4: Jan 2027 | AC4: Feb 2027 | AD4: Mar 2027 | AE4: Apr 2027 | AF4: May 2027 | AG4: Jun 2027 | AH4: Jul 2027 | AI4: Aug 2027 | AJ4: Sep 2027 | AK4: Oct 2027 | AL4: Nov 2027 | AM4: Dec 2027 | AN4: Jan 2028 | AO4: Feb 2028 | AP4: Mar 2028 | AQ4: Apr 2028 | AR4: May 2028 | AS4: Jun 2028 | AT4: Jul 2028 | AU4: Aug 2028 | AV4: Sep 2028 | AW4: Oct 2028 | AX4: Nov 2028 | AY4: Dec 2028
B5: Berkeley (BK)
B6: Total Revenue | D6: ='BK P&L'!D22 | E6: ='BK P&L'!E22 | F6: ='BK P&L'!F22 | G6: ='BK P&L'!G22 | H6: ='BK P&L'!H22 | I6: ='BK P&L'!I22 | J6: ='BK P&L'!J22 | K6: ='BK P&L'!K22 | ... AY6: ='BK P&L'!AY22
B7: Gross Profit | D7: ='BK P&L'!D27 | E7: ='BK P&L'!E27 | F7: ='BK P&L'!F27 | G7: ='BK P&L'!G27 | H7: ='BK P&L'!H27 | I7: ='BK P&L'!I27 | J7: ='BK P&L'!J27 | K7: ='BK P&L'!K27 | ... AY7: ='BK P&L'!AY27
B8: Total Operating Expenses | D8: ='BK P&L'!D63 | E8: ='BK P&L'!E63 | F8: ='BK P&L'!F63 | G8: ='BK P&L'!G63 | H8: ='BK P&L'!H63 | I8: ='BK P&L'!I63 | J8: ='BK P&L'!J63 | K8: ='BK P&L'!K63 | ... AY8: ='BK P&L'!AY63
B9: Net Operating Income | D9: ='BK P&L'!D64 | E9: ='BK P&L'!E64 | F9: ='BK P&L'!F64 | G9: ='BK P&L'!G64 | H9: ='BK P&L'!H64 | I9: ='BK P&L'!I64 | J9: ='BK P&L'!J64 | K9: ='BK P&L'!K64 | ... AY9: ='BK P&L'!AY64
B11: Culver City (CC)
B12: Total Revenue | D12: ='CC P&L'!D21 | E12: ='CC P&L'!E21 | F12: ='CC P&L'!F21 | G12: ='CC P&L'!G21 | H12: ='CC P&L'!H21 | I12: ='CC P&L'!I21 | J12: ='CC P&L'!J21 | K12: ='CC P&L'!K21 | ... AY12: ='CC P&L'!AY21
B13: Gross Profit | D13: ='CC P&L'!D26 | E13: ='CC P&L'!E26 | F13: ='CC P&L'!F26 | G13: ='CC P&L'!G26 | H13: ='CC P&L'!H26 | I13: ='CC P&L'!I26 | J13: ='CC P&L'!J26 | K13: ='CC P&L'!K26 | ... AY13: ='CC P&L'!AY26
B14: Total Operating Expenses | D14: ='CC P&L'!D62 | E14: ='CC P&L'!E62 | F14: ='CC P&L'!F62 | G14: ='CC P&L'!G62 | H14: ='CC P&L'!H62 | I14: ='CC P&L'!I62 | J14: ='CC P&L'!J62 | K14: ='CC P&L'!K62 | ... AY14: ='CC P&L'!AY62
B15: Net Operating Income | D15: ='CC P&L'!D63 | E15: ='CC P&L'!E63 | F15: ='CC P&L'!F63 | G15: ='CC P&L'!G63 | H15: ='CC P&L'!H63 | I15: ='CC P&L'!I63 | J15: ='CC P&L'!J63 | K15: ='CC P&L'!K63 | ... AY15: ='CC P&L'!AY63
B17: Danville (DN)
B18: Total Revenue | D18: ='DN P&L'!D21 | E18: ='DN P&L'!E21 | F18: ='DN P&L'!F21 | G18: ='DN P&L'!G21 | H18: ='DN P&L'!H21 | I18: ='DN P&L'!I21 | J18: ='DN P&L'!J21 | K18: ='DN P&L'!K21 | ... AY18: ='DN P&L'!AY21
B19: Gross Profit | D19: ='DN P&L'!D26 | E19: ='DN P&L'!E26 | F19: ='DN P&L'!F26 | G19: ='DN P&L'!G26 | H19: ='DN P&L'!H26 | I19: ='DN P&L'!I26 | J19: ='DN P&L'!J26 | K19: ='DN P&L'!K26 | ... AY19: ='DN P&L'!AY26
B20: Total Operating Expenses | D20: ='DN P&L'!D62 | E20: ='DN P&L'!E62 | F20: ='DN P&L'!F62 | G20: ='DN P&L'!G62 | H20: ='DN P&L'!H62 | I20: ='DN P&L'!I62 | J20: ='DN P&L'!J62 | K20: ='DN P&L'!K62 | ... AY20: ='DN P&L'!AY62
B21: Net Operating Income | D21: ='DN P&L'!D63 | E21: ='DN P&L'!E63 | F21: ='DN P&L'!F63 | G21: ='DN P&L'!G63 | H21: ='DN P&L'!H63 | I21: ='DN P&L'!I63 | J21: ='DN P&L'!J63 | K21: ='DN P&L'!K63 | ... AY21: ='DN P&L'!AY63
B23: Lafayette (LF)
B24: Total Revenue | D24: ='LF P&L'!D22 | E24: ='LF P&L'!E22 | F24: ='LF P&L'!F22 | G24: ='LF P&L'!G22 | H24: ='LF P&L'!H22 | I24: ='LF P&L'!I22 | J24: ='LF P&L'!J22 | K24: ='LF P&L'!K22 | ... AY24: ='LF P&L'!AY22
B25: Gross Profit | D25: ='LF P&L'!D27 | E25: ='LF P&L'!E27 | F25: ='LF P&L'!F27 | G25: ='LF P&L'!G27 | H25: ='LF P&L'!H27 | I25: ='LF P&L'!I27 | J25: ='LF P&L'!J27 | K25: ='LF P&L'!K27 | ... AY25: ='LF P&L'!AY27
B26: Total Operating Expenses | D26: ='LF P&L'!D63 | E26: ='LF P&L'!E63 | F26: ='LF P&L'!F63 | G26: ='LF P&L'!G63 | H26: ='LF P&L'!H63 | I26: ='LF P&L'!I63 | J26: ='LF P&L'!J63 | K26: ='LF P&L'!K63 | ... AY26: ='LF P&L'!AY63
B27: Net Operating Income | D27: ='LF P&L'!D64 | E27: ='LF P&L'!E64 | F27: ='LF P&L'!F64 | G27: ='LF P&L'!G64 | H27: ='LF P&L'!H64 | I27: ='LF P&L'!I64 | J27: ='LF P&L'!J64 | K27: ='LF P&L'!K64 | ... AY27: ='LF P&L'!AY64
B29: Marin (MR)
B30: Total Revenue | D30: ='MR P&L'!D21 | E30: ='MR P&L'!E21 | F30: ='MR P&L'!F21 | G30: ='MR P&L'!G21 | H30: ='MR P&L'!H21 | I30: ='MR P&L'!I21 | J30: ='MR P&L'!J21 | K30: ='MR P&L'!K21 | ... AY30: ='MR P&L'!AY21
B31: Gross Profit | D31: ='MR P&L'!D26 | E31: ='MR P&L'!E26 | F31: ='MR P&L'!F26 | G31: ='MR P&L'!G26 | H31: ='MR P&L'!H26 | I31: ='MR P&L'!I26 | J31: ='MR P&L'!J26 | K31: ='MR P&L'!K26 | ... AY31: ='MR P&L'!AY26
B32: Total Operating Expenses | D32: ='MR P&L'!D62 | E32: ='MR P&L'!E62 | F32: ='MR P&L'!F62 | G32: ='MR P&L'!G62 | H32: ='MR P&L'!H62 | I32: ='MR P&L'!I62 | J32: ='MR P&L'!J62 | K32: ='MR P&L'!K62 | ... AY32: ='MR P&L'!AY62
B33: Net Operating Income | D33: ='MR P&L'!D63 | E33: ='MR P&L'!E63 | F33: ='MR P&L'!F63 | G33: ='MR P&L'!G63 | H33: ='MR P&L'!H63 | I33: ='MR P&L'!I63 | J33: ='MR P&L'!J63 | K33: ='MR P&L'!K63 | ... AY33: ='MR P&L'!AY63
B35: Ocean Park (OP)
B36: Total Revenue | D36: ='OP P&L'!D21 | E36: ='OP P&L'!E21 | F36: ='OP P&L'!F21 | G36: ='OP P&L'!G21 | H36: ='OP P&L'!H21 | I36: ='OP P&L'!I21 | J36: ='OP P&L'!J21 | K36: ='OP P&L'!K21 | ... AY36: ='OP P&L'!AY21
B37: Gross Profit | D37: ='OP P&L'!D26 | E37: ='OP P&L'!E26 | F37: ='OP P&L'!F26 | G37: ='OP P&L'!G26 | H37: ='OP P&L'!H26 | I37: ='OP P&L'!I26 | J37: ='OP P&L'!J26 | K37: ='OP P&L'!K26 | ... AY37: ='OP P&L'!AY26
B38: Total Operating Expenses | D38: ='OP P&L'!D62 | E38: ='OP P&L'!E62 | F38: ='OP P&L'!F62 | G38: ='OP P&L'!G62 | H38: ='OP P&L'!H62 | I38: ='OP P&L'!I62 | J38: ='OP P&L'!J62 | K38: ='OP P&L'!K62 | ... AY38: ='OP P&L'!AY62
B39: Net Operating Income | D39: ='OP P&L'!D63 | E39: ='OP P&L'!E63 | F39: ='OP P&L'!F63 | G39: ='OP P&L'!G63 | H39: ='OP P&L'!H63 | I39: ='OP P&L'!I63 | J39: ='OP P&L'!J63 | K39: ='OP P&L'!K63 | ... AY39: ='OP P&L'!AY63
B41: Presidio Heights (PH)
B42: Total Revenue | D42: ='PH P&L'!D22 | E42: ='PH P&L'!E22 | F42: ='PH P&L'!F22 | G42: ='PH P&L'!G22 | H42: ='PH P&L'!H22 | I42: ='PH P&L'!I22 | J42: ='PH P&L'!J22 | K42: ='PH P&L'!K22 | ... AY42: ='PH P&L'!AY22
B43: Gross Profit | D43: ='PH P&L'!D27 | E43: ='PH P&L'!E27 | F43: ='PH P&L'!F27 | G43: ='PH P&L'!G27 | H43: ='PH P&L'!H27 | I43: ='PH P&L'!I27 | J43: ='PH P&L'!J27 | K43: ='PH P&L'!K27 | ... AY43: ='PH P&L'!AY27
B44: Total Operating Expenses | D44: ='PH P&L'!D63 | E44: ='PH P&L'!E63 | F44: ='PH P&L'!F63 | G44: ='PH P&L'!G63 | H44: ='PH P&L'!H63 | I44: ='PH P&L'!I63 | J44: ='PH P&L'!J63 | K44: ='PH P&L'!K63 | ... AY44: ='PH P&L'!AY63
B45: Net Operating Income | D45: ='PH P&L'!D64 | E45: ='PH P&L'!E64 | F45: ='PH P&L'!F64 | G45: ='PH P&L'!G64 | H45: ='PH P&L'!H64 | I45: ='PH P&L'!I64 | J45: ='PH P&L'!J64 | K45: ='PH P&L'!K64 | ... AY45: ='PH P&L'!AY64
B47: Russian Hill (RH)
B48: Total Revenue | D48: ='RH P&L'!D21 | E48: ='RH P&L'!E21 | F48: ='RH P&L'!F21 | G48: ='RH P&L'!G21 | H48: ='RH P&L'!H21 | I48: ='RH P&L'!I21 | J48: ='RH P&L'!J21 | K48: ='RH P&L'!K21 | ... AY48: ='RH P&L'!AY21
B49: Gross Profit | D49: ='RH P&L'!D26 | E49: ='RH P&L'!E26 | F49: ='RH P&L'!F26 | G49: ='RH P&L'!G26 | H49: ='RH P&L'!H26 | I49: ='RH P&L'!I26 | J49: ='RH P&L'!J26 | K49: ='RH P&L'!K26 | ... AY49: ='RH P&L'!AY26
B50: Total Operating Expenses | D50: ='RH P&L'!D62 | E50: ='RH P&L'!E62 | F50: ='RH P&L'!F62 | G50: ='RH P&L'!G62 | H50: ='RH P&L'!H62 | I50: ='RH P&L'!I62 | J50: ='RH P&L'!J62 | K50: ='RH P&L'!K62 | ... AY50: ='RH P&L'!AY62
B51: Net Operating Income | D51: ='RH P&L'!D63 | E51: ='RH P&L'!E63 | F51: ='RH P&L'!F63 | G51: ='RH P&L'!G63 | H51: ='RH P&L'!H63 | I51: ='RH P&L'!I63 | J51: ='RH P&L'!J63 | K51: ='RH P&L'!K63 | ... AY51: ='RH P&L'!AY63
B53: Santa Barbara (SB)
B54: Total Revenue | D54: ='SB P&L'!D21 | E54: ='SB P&L'!E21 | F54: ='SB P&L'!F21 | G54: ='SB P&L'!G21 | H54: ='SB P&L'!H21 | I54: ='SB P&L'!I21 | J54: ='SB P&L'!J21 | K54: ='SB P&L'!K21 | ... AY54: ='SB P&L'!AY21
B55: Gross Profit | D55: ='SB P&L'!D26 | E55: ='SB P&L'!E26 | F55: ='SB P&L'!F26 | G55: ='SB P&L'!G26 | H55: ='SB P&L'!H26 | I55: ='SB P&L'!I26 | J55: ='SB P&L'!J26 | K55: ='SB P&L'!K26 | ... AY55: ='SB P&L'!AY26
B56: Total Operating Expenses | D56: ='SB P&L'!D62 | E56: ='SB P&L'!E62 | F56: ='SB P&L'!F62 | G56: ='SB P&L'!G62 | H56: ='SB P&L'!H62 | I56: ='SB P&L'!I62 | J56: ='SB P&L'!J62 | K56: ='SB P&L'!K62 | ... AY56: ='SB P&L'!AY62
B57: Net Operating Income | D57: ='SB P&L'!D63 | E57: ='SB P&L'!E63 | F57: ='SB P&L'!F63 | G57: ='SB P&L'!G63 | H57: ='SB P&L'!H63 | I57: ='SB P&L'!I63 | J57: ='SB P&L'!J63 | K57: ='SB P&L'!K63 | ... AY57: ='SB P&L'!AY63
B59: Santa Monica (SM)
B60: Total Revenue | D60: ='SM P&L'!D22 | E60: ='SM P&L'!E22 | F60: ='SM P&L'!F22 | G60: ='SM P&L'!G22 | H60: ='SM P&L'!H22 | I60: ='SM P&L'!I22 | J60: ='SM P&L'!J22 | K60: ='SM P&L'!K22 | ... AY60: ='SM P&L'!AY22
B61: Gross Profit | D61: ='SM P&L'!D27 | E61: ='SM P&L'!E27 | F61: ='SM P&L'!F27 | G61: ='SM P&L'!G27 | H61: ='SM P&L'!H27 | I61: ='SM P&L'!I27 | J61: ='SM P&L'!J27 | K61: ='SM P&L'!K27 | ... AY61: ='SM P&L'!AY27
B62: Total Operating Expenses | D62: ='SM P&L'!D63 | E62: ='SM P&L'!E63 | F62: ='SM P&L'!F63 | G62: ='SM P&L'!G63 | H62: ='SM P&L'!H63 | I62: ='SM P&L'!I63 | J62: ='SM P&L'!J63 | K62: ='SM P&L'!K63 | ... AY62: ='SM P&L'!AY63
B63: Net Operating Income | D63: ='SM P&L'!D64 | E63: ='SM P&L'!E64 | F63: ='SM P&L'!F64 | G63: ='SM P&L'!G64 | H63: ='SM P&L'!H64 | I63: ='SM P&L'!I64 | J63: ='SM P&L'!J64 | K63: ='SM P&L'!K64 | ... AY63: ='SM P&L'!AY64
B65: West Portal (WP)
B66: Total Revenue | D66: ='WP P&L'!D21 | E66: ='WP P&L'!E21 | F66: ='WP P&L'!F21 | G66: ='WP P&L'!G21 | H66: ='WP P&L'!H21 | I66: ='WP P&L'!I21 | J66: ='WP P&L'!J21 | K66: ='WP P&L'!K21 | ... AY66: ='WP P&L'!AY21
B67: Gross Profit | D67: ='WP P&L'!D26 | E67: ='WP P&L'!E26 | F67: ='WP P&L'!F26 | G67: ='WP P&L'!G26 | H67: ='WP P&L'!H26 | I67: ='WP P&L'!I26 | J67: ='WP P&L'!J26 | K67: ='WP P&L'!K26 | ... AY67: ='WP P&L'!AY26
B68: Total Operating Expenses | D68: ='WP P&L'!D62 | E68: ='WP P&L'!E62 | F68: ='WP P&L'!F62 | G68: ='WP P&L'!G62 | H68: ='WP P&L'!H62 | I68: ='WP P&L'!I62 | J68: ='WP P&L'!J62 | K68: ='WP P&L'!K62 | ... AY68: ='WP P&L'!AY62
B69: Net Operating Income | D69: ='WP P&L'!D63 | E69: ='WP P&L'!E63 | F69: ='WP P&L'!F63 | G69: ='WP P&L'!G63 | H69: ='WP P&L'!H63 | I69: ='WP P&L'!I63 | J69: ='WP P&L'!J63 | K69: ='WP P&L'!K63 | ... AY69: ='WP P&L'!AY63
B71: Westwood (WW)
B72: Total Revenue | D72: ='WW P&L'!D22 | E72: ='WW P&L'!E22 | F72: ='WW P&L'!F22 | G72: ='WW P&L'!G22 | H72: ='WW P&L'!H22 | I72: ='WW P&L'!I22 | J72: ='WW P&L'!J22 | K72: ='WW P&L'!K22 | ... AY72: ='WW P&L'!AY22
B73: Gross Profit | D73: ='WW P&L'!D27 | E73: ='WW P&L'!E27 | F73: ='WW P&L'!F27 | G73: ='WW P&L'!G27 | H73: ='WW P&L'!H27 | I73: ='WW P&L'!I27 | J73: ='WW P&L'!J27 | K73: ='WW P&L'!K27 | ... AY73: ='WW P&L'!AY27
B74: Total Operating Expenses | D74: ='WW P&L'!D63 | E74: ='WW P&L'!E63 | F74: ='WW P&L'!F63 | G74: ='WW P&L'!G63 | H74: ='WW P&L'!H63 | I74: ='WW P&L'!I63 | J74: ='WW P&L'!J63 | K74: ='WW P&L'!K63 | ... AY74: ='WW P&L'!AY63
B75: Net Operating Income | D75: ='WW P&L'!D64 | E75: ='WW P&L'!E64 | F75: ='WW P&L'!F64 | G75: ='WW P&L'!G64 | H75: ='WW P&L'!H64 | I75: ='WW P&L'!I64 | J75: ='WW P&L'!J64 | K75: ='WW P&L'!K64 | ... AY75: ='WW P&L'!AY64

Sheet BK P&L
B2: Berkeley (BK) — Profit & Loss | Q2: -1
B4: Monthly P&L (Detail)
B5: Line Item | D5: Jan 2025 | E5: Feb 2025 | F5: Mar 2025 | G5: Apr 2025 | H5: May 2025 | I5: Jun 2025 | J5: Jul 2025 | K5: Aug 2025 | L5: Sep 2025 | M5: Oct 2025 | N5: Nov 2025 | O5: Dec 2025 | P5: Jan 2026 | Q5: Feb 2026 | R5: Mar 2026 | S5: Apr 2026 | T5: May 2026 | U5: Jun 2026 | V5: Jul 2026 | W5: Aug 2026 | X5: Sep 2026 | Y5: Oct 2026 | Z5: Nov 2026 | AA5: Dec 2026 | AB5: Jan 2027 | AC5: Feb 2027 | AD5: Mar 2027 | AE5: Apr 2027 | AF5: May 2027 | AG5: Jun 2027 | AH5: Jul 2027 | AI5: Aug 2027 | AJ5: Sep 2027 | AK5: Oct 2027 | AL5: Nov 2027 | AM5: Dec 2027 | AN5: Jan 2028 | AO5: Feb 2028 | AP5: Mar 2028 | AQ5: Apr 2028 | AR5: May 2028 | AS5: Jun 2028 | AT5: Jul 2028 | AU5: Aug 2028 | AV5: Sep 2028 | AW5: Oct 2028 | AX5: Nov 2028 | AY5: Dec 2028 | BA5: Revenue Segments as % of Total (LTM)
B6: INCOME | D6: 0 | E6: 0 | F6: 0 | G6: 0 | H6: 0 | I6: 0 | J6: 0 | K6: 0 | L6: 0 | M6: 0 | N6: 0 | O6: 0 | BA6: LTM May 2026
B7: 401001 Machine | D7: 48512.85 | E7: 54342.24 | F7: 64934.84 | G7: 59274.01 | H7: 61380.05 | I7: 59220.81 | J7: 60156.33 | K7: 65762.1 | L7: 63020.69 | M7: 62222.95 | N7: 58675.46 | O7: 57148.4 | P7: 67553.69 | Q7: 60691.23 | R7: 63647.98 | S7: 60903.08 | T7: 59469.95 | U7: 52194.4 | V7: 53280.2 | W7: =W13*0.598021 | X7: =X13*0.598021 | Y7: =Y13*0.598021 | Z7: =Z13*0.598021 | AA7: =AA13*0.598021 | AB7: =AB13*0.598021 | AC7: =AC13*0.598021 | AD7: =AD13*0.598021 | ... AY7: =AY13*0.598021 | BA7: =SUM(I7:T7) | BB7: =BA7/$BA$22
B8: 401002 Private Pilates | D8: 3365 | E8: 5164 | F8: 6259.32 | G8: 7063.11 | H8: 6195.11 | I8: 4351.11 | J8: 4420.26 | K8: 6743.11 | L8: 6140 | M8: 3768.5 | N8: 5134 | O8: 4124 | P8: 4967 | Q8: 6520 | R8: 7898 | S8: 6484 | T8: 4535 | U8: 5050 | V8: 4219 | W8: =W13*0.061196 | X8: =X13*0.061196 | Y8: =Y13*0.061196 | Z8: =Z13*0.061196 | AA8: =AA13*0.061196 | AB8: =AB13*0.061196 | AC8: =AC13*0.061196 | AD8: =AD13*0.061196 | ... AY8: =AY13*0.061196 | BA8: =SUM(I8:T8) | BB8: =BA8/$BA$22
B9: 401003 Class Pass | D9: 28443.58 | E9: 27468.5 | F9: 27758.08 | G9: 30356.52 | H9: 29776.53 | I9: 29108.34 | J9: 28187.52 | K9: 27520.95 | L9: 26184.97 | M9: 24804.33 | N9: 26840.92 | O9: 26286.98 | P9: 28869.3 | Q9: 25522.33 | R9: 29455.32 | S9: 30289 | T9: 26097.27 | U9: 24871.98 | V9: 22681 | W9: =W13*0.270003 | X9: =X13*0.270003 | Y9: =Y13*0.270003 | Z9: =Z13*0.270003 | AA9: =AA13*0.270003 | AB9: =AB13*0.270003 | AC9: =AC13*0.270003 | AD9: =AD13*0.270003 | ... AY9: =AY13*0.270003 | BA9: =SUM(I9:T9) | BB9: =BA9/$BA$22
B10: 401004 Mighty Teacher Training | D10: 640 | E10: 320 | F10: 0 | G10: 0 | H10: 1280 | I10: 2320 | J10: 5457.5 | K10: 0 | L10: 0 | M10: 0 | N10: 0 | O10: 0 | P10: 21644.5 | Q10: 0 | R10: 0 | S10: 0 | T10: 0 | U10: 0 | V10: 0 | W10: =W13*0.067362 | X10: =X13*0.067362 | Y10: =Y13*0.067362 | Z10: =Z13*0.067362 | AA10: =AA13*0.067362 | AB10: =AB13*0.067362 | AC10: =AC13*0.067362 | AD10: =AD13*0.067362 | ... AY10: =AY13*0.067362 | BA10: =SUM(I10:T10) | BB10: =BA10/$BA$22
B11: 401005 Livestream Classes | D11: 0 | E11: 14 | F11: 25.8 | G11: 65.6 | H11: 23.6 | I11: 73 | J11: 59 | K11: 132 | L11: 115 | M11: 23.6 | N11: 23.6 | O11: 14 | P11: 49.4 | Q11: 64.9 | R11: 82.6 | S11: 18.22 | T11: 31.56 | U11: 28 | V11: 39.8 | W11: =W13*0.000509 | X11: =X13*0.000509 | Y11: =Y13*0.000509 | Z11: =Z13*0.000509 | AA11: =AA13*0.000509 | AB11: =AB13*0.000509 | AC11: =AC13*0.000509 | AD11: =AD13*0.000509 | ... AY11: =AY13*0.000509 | BA11: =SUM(I11:T11) | BB11: =BA11/$BA$22
B12: 401006 Wellhub | D12: 0 | E12: 0 | F12: 0 | G12: 0 | H12: 0 | I12: 0 | J12: 44.66 | K12: 52.54 | L12: 52.54 | M12: 0 | N12: 149.74 | O12: 202.28 | P12: 289 | Q12: 341.54 | R12: 289 | S12: 309.99 | T12: 202.28 | U12: 44.66 | V12: 157.62 | W12: =W13*0.002909 | X12: =X13*0.002909 | Y12: =Y13*0.002909 | Z12: =Z13*0.002909 | AA12: =AA13*0.002909 | AB12: =AB13*0.002909 | AC12: =AC13*0.002909 | AD12: =AD13*0.002909 | ... AY12: =AY13*0.002909 | BA12: =SUM(I12:T12) | BB12: =BA12/$BA$22
B13: Total Sessions | D13: =SUM(D7:D12) | E13: =SUM(E7:E12) | F13: =SUM(F7:F12) | G13: =SUM(G7:G12) | H13: =SUM(H7:H12) | I13: =SUM(I7:I12) | J13: =SUM(J7:J12) | K13: =SUM(K7:K12) | ... O13: =SUM(O7:O12) | P13: =P7+P8+P9+P10+P11+P12 | Q13: =Q7+Q8+Q9+Q10+Q11+Q12 | R13: =R7+R8+R9+R10+R11+R12 | S13: =S7+S8+S9+S10+S11+S12 | T13: =T7+T8+T9+T10+T11+T12 | U13: =U7+U8+U9+U10+U11+U12 | V13: =V7+V8+V9+V10+V11+V12 | W13: ='Sales Forecast'!W6*Assumptions!$C$12+'Sales Forecast'!V6*Assumptions!$D$12+'Sales Forecast'!U6*Assumptions!$E$12+'Sales Forecast'!T6*Assumptions!$F$12+'Sales Forecast'!S6*Assumptions!$G$12+'Sales Forecast'!R6*Assumptions!$H$12+'Sales Forecast'!Q6*Assumptions!$I$12 | X13: ='Sales Forecast'!X6*Assumptions!$C$12+'Sales Forecast'!W6*Assumptions!$D$12+'Sales Forecast'!V6*Assumptions!$E$12+'Sales Forecast'!U6*Assumptions!$F$12+'Sales Forecast'!T6*Assumptions!$G$12+'Sales Forecast'!S6*Assumptions!$H$12+'Sales Forecast'!R6*Assumptions!$I$12 | Y13: ='Sales Forecast'!Y6*Assumptions!$C$12+'Sales Forecast'!X6*Assumptions!$D$12+'Sales Forecast'!W6*Assumptions!$E$12+'Sales Forecast'!V6*Assumptions!$F$12+'Sales Forecast'!U6*Assumptions!$G$12+'Sales Forecast'!T6*Assumptions!$H$12+'Sales Forecast'!S6*Assumptions!$I$12 | Z13: ='Sales Forecast'!Z6*Assumptions!$C$12+'Sales Forecast'!Y6*Assumptions!$D$12+'Sales Forecast'!X6*Assumptions!$E$12+'Sales Forecast'!W6*Assumptions!$F$12+'Sales Forecast'!V6*Assumptions!$G$12+'Sales Forecast'!U6*Assumptions!$H$12+'Sales Forecast'!T6*Assumptions!$I$12 | AA13: ='Sales Forecast'!AA6*Assumptions!$C$12+'Sales Forecast'!Z6*Assumptions!$D$12+'Sales Forecast'!Y6*Assumptions!$E$12+'Sales Forecast'!X6*Assumptions!$F$12+'Sales Forecast'!W6*Assumptions!$G$12+'Sales Forecast'!V6*Assumptions!$H$12+'Sales Forecast'!U6*Assumptions!$I$12 | AB13: ='Sales Forecast'!AB6*Assumptions!$C$12+'Sales Forecast'!AA6*Assumptions!$D$12+'Sales Forecast'!Z6*Assumptions!$E$12+'Sales Forecast'!Y6*Assumptions!$F$12+'Sales Forecast'!X6*Assumptions!$G$12+'Sales Forecast'!W6*Assumptions!$H$12+'Sales Forecast'!V6*Assumptions!$I$12 | AC13: ='Sales Forecast'!AC6*Assumptions!$C$12+'Sales Forecast'!AB6*Assumptions!$D$12+'Sales Forecast'!AA6*Assumptions!$E$12+'Sales Forecast'!Z6*Assumptions!$F$12+'Sales Forecast'!Y6*Assumptions!$G$12+'Sales Forecast'!X6*Assumptions!$H$12+'Sales Forecast'!W6*Assumptions!$I$12 | AD13: ='Sales Forecast'!AD6*Assumptions!$C$12+'Sales Forecast'!AC6*Assumptions!$D$12+'Sales Forecast'!AB6*Assumptions!$E$12+'Sales Forecast'!AA6*Assumptions!$F$12+'Sales Forecast'!Z6*Assumptions!$G$12+'Sales Forecast'!Y6*Assumptions!$H$12+'Sales Forecast'!X6*Assumptions!$I$12 | ... AY13: ='Sales Forecast'!AY6*Assumptions!$C$12+'Sales Forecast'!AX6*Assumptions!$D$12+'Sales Forecast'!AW6*Assumptions!$E$12+'Sales Forecast'!AV6*Assumptions!$F$12+'Sales Forecast'!AU6*Assumptions!$G$12+'Sales Forecast'!AT6*Assumptions!$H$12+'Sales Forecast'!AS6*Assumptions!$I$12
B14: Revenue from Old Mighty | D14: 17270.2 | E14: 7154.43 | F14: 4880.41 | G14: 3618.45 | H14: 1819.33 | I14: 919.05 | J14: 596.83 | K14: 276.5 | L14: 75 | M14: 0 | N14: 0 | O14: 0 | P14: 0 | Q14: 0 | R14: 0 | S14: 0 | T14: 0 | U14: 0 | V14: 0
B15: 403001 Machine Breakage | D15: 10480.79 | E15: 16179.03 | F15: 20305.86 | G15: 20513.48 | H15: 23721.52 | I15: 17938.2 | J15: 14764.55 | K15: 15127.93 | L15: 32901.88 | M15: 22861.69 | N15: 31868.08 | O15: 31038.14 | P15: 17169.98 | Q15: 24950.31 | R15: 19308.85 | S15: 22389.08 | T15: 17746.33 | U15: 17161.6 | V15: 17800.85 | W15: =W18*0.952386 | X15: =X18*0.952386 | Y15: =Y18*0.952386 | Z15: =Z18*0.952386 | AA15: =AA18*0.952386 | AB15: =AB18*0.952386 | AC15: =AC18*0.952386 | AD15: =AD18*0.952386 | ... AY15: =AY18*0.952386 | BA15: =SUM(I15:T15) | BB15: =BA15/$BA$22
B16: 403003 Private Pilates Breakage | D16: 495 | E16: 3040 | F16: 2615 | G16: 1345 | H16: 1185 | I16: 3540 | J16: 2208 | K16: 2677.5 | L16: 1750 | M16: 1282 | N16: 3100 | O16: 2415 | P16: 1385 | Q16: 430 | R16: 965 | S16: 1375 | T16: 1085 | U16: 220 | V16: 1301.67 | W16: =W18*0.047211 | X16: =X18*0.047211 | Y16: =Y18*0.047211 | Z16: =Z18*0.047211 | AA16: =AA18*0.047211 | AB16: =AB18*0.047211 | AC16: =AC18*0.047211 | AD16: =AD18*0.047211 | ... AY16: =AY18*0.047211 | BA16: =SUM(I16:T16) | BB16: =BA16/$BA$22
B17: 403004 Other Breakage (incl MTT Breakage) | D17: 0 | E17: 0 | F17: 0 | G17: 47.2 | H17: 0 | I17: 1680 | J17: 2265 | K17: 7380 | L17: 0 | M17: 285.4 | N17: 3142 | O17: 4909.7 | P17: 0 | Q17: 35.4 | R17: 0 | S17: 0 | T17: 0 | U17: 0 | V17: 35.4 | W17: =W18*0.000402 | X17: =X18*0.000402 | Y17: =Y18*0.000402 | Z17: =Z18*0.000402 | AA17: =AA18*0.000402 | AB17: =AB18*0.000402 | AC17: =AC18*0.000402 | AD17: =AD18*0.000402 | ... AY17: =AY18*0.000402 | BA17: =SUM(I17:T17) | BB17: =BA17/$BA$22
B18: Total Breakage Revenue | D18: =SUM(D15:D17) | E18: =SUM(E15:E17) | F18: =SUM(F15:F17) | G18: =SUM(G15:G17) | H18: =SUM(H15:H17) | I18: =SUM(I15:I17) | J18: =SUM(J15:J17) | K18: =SUM(K15:K17) | ... O18: =SUM(O15:O17) | P18: =P15+P16+P17 | Q18: =Q15+Q16+Q17 | R18: =R15+R16+R17 | S18: =S15+S16+S17 | T18: =T15+T16+T17 | U18: =U15+U16+U17 | V18: =V15+V16+V17 | W18: ='Sales Forecast'!W6*Assumptions!$C$13+'Sales Forecast'!V6*Assumptions!$D$13+'Sales Forecast'!U6*Assumptions!$E$13+'Sales Forecast'!T6*Assumptions!$F$13+'Sales Forecast'!S6*Assumptions!$G$13+'Sales Forecast'!R6*Assumptions!$H$13+'Sales Forecast'!Q6*Assumptions!$I$13 | X18: ='Sales Forecast'!X6*Assumptions!$C$13+'Sales Forecast'!W6*Assumptions!$D$13+'Sales Forecast'!V6*Assumptions!$E$13+'Sales Forecast'!U6*Assumptions!$F$13+'Sales Forecast'!T6*Assumptions!$G$13+'Sales Forecast'!S6*Assumptions!$H$13+'Sales Forecast'!R6*Assumptions!$I$13 | Y18: ='Sales Forecast'!Y6*Assumptions!$C$13+'Sales Forecast'!X6*Assumptions!$D$13+'Sales Forecast'!W6*Assumptions!$E$13+'Sales Forecast'!V6*Assumptions!$F$13+'Sales Forecast'!U6*Assumptions!$G$13+'Sales Forecast'!T6*Assumptions!$H$13+'Sales Forecast'!S6*Assumptions!$I$13 | Z18: ='Sales Forecast'!Z6*Assumptions!$C$13+'Sales Forecast'!Y6*Assumptions!$D$13+'Sales Forecast'!X6*Assumptions!$E$13+'Sales Forecast'!W6*Assumptions!$F$13+'Sales Forecast'!V6*Assumptions!$G$13+'Sales Forecast'!U6*Assumptions!$H$13+'Sales Forecast'!T6*Assumptions!$I$13 | AA18: ='Sales Forecast'!AA6*Assumptions!$C$13+'Sales Forecast'!Z6*Assumptions!$D$13+'Sales Forecast'!Y6*Assumptions!$E$13+'Sales Forecast'!X6*Assumptions!$F$13+'Sales Forecast'!W6*Assumptions!$G$13+'Sales Forecast'!V6*Assumptions!$H$13+'Sales Forecast'!U6*Assumptions!$I$13 | AB18: ='Sales Forecast'!AB6*Assumptions!$C$13+'Sales Forecast'!AA6*Assumptions!$D$13+'Sales Forecast'!Z6*Assumptions!$E$13+'Sales Forecast'!Y6*Assumptions!$F$13+'Sales Forecast'!X6*Assumptions!$G$13+'Sales Forecast'!W6*Assumptions!$H$13+'Sales Forecast'!V6*Assumptions!$I$13 | AC18: ='Sales Forecast'!AC6*Assumptions!$C$13+'Sales Forecast'!AB6*Assumptions!$D$13+'Sales Forecast'!AA6*Assumptions!$E$13+'Sales Forecast'!Z6*Assumptions!$F$13+'Sales Forecast'!Y6*Assumptions!$G$13+'Sales Forecast'!X6*Assumptions!$H$13+'Sales Forecast'!W6*Assumptions!$I$13 | AD18: ='Sales Forecast'!AD6*Assumptions!$C$13+'Sales Forecast'!AC6*Assumptions!$D$13+'Sales Forecast'!AB6*Assumptions!$E$13+'Sales Forecast'!AA6*Assumptions!$F$13+'Sales Forecast'!Z6*Assumptions!$G$13+'Sales Forecast'!Y6*Assumptions!$H$13+'Sales Forecast'!X6*Assumptions!$I$13 | ... AY18: ='Sales Forecast'!AY6*Assumptions!$C$13+'Sales Forecast'!AX6*Assumptions!$D$13+'Sales Forecast'!AW6*Assumptions!$E$13+'Sales Forecast'!AV6*Assumptions!$F$13+'Sales Forecast'!AU6*Assumptions!$G$13+'Sales Forecast'!AT6*Assumptions!$H$13+'Sales Forecast'!AS6*Assumptions!$I$13
B19: 404000 Retail Sales | D19: 3473 | E19: 2711 | F19: 2259 | G19: 2631 | H19: 2405 | I19: 4161 | J19: 2652 | K19: 2867 | L19: 2571 | M19: 1868 | N19: 1688 | O19: 2220 | P19: 2152 | Q19: 1414 | R19: 1104 | S19: 2254 | T19: 2098 | U19: 2408 | V19: 1855 | W19: =1731 | X19: =1731 | Y19: =1731 | Z19: =1731 | AA19: =1731 | AB19: =1731 | AC19: =1731 | AD19: =1731 | ... AY19: =1731 | BA19: =SUM(I19:T19) | BB19: =BA19/$BA$22
B20: 406000 Refunds | D20: -3038 | E20: -3570 | F20: -4134 | G20: -6153 | H20: -2902 | I20: -1475.01 | J20: -1196 | K20: -914.01 | L20: -1970 | M20: -1215 | N20: -1510 | O20: -3423 | P20: -3600 | Q20: -1510 | R20: -2088 | S20: -3980 | T20: -1700 | U20: -2083 | V20: -2563 | W20: =('Sales Forecast'!W6*Assumptions!$C$12+'Sales Forecast'!V6*Assumptions!$D$12+'Sales Forecast'!U6*Assumptions!$E$12+'Sales Forecast'!T6*Assumptions!$F$12+'Sales Forecast'!S6*Assumptions!$G$12+'Sales Forecast'!R6*Assumptions!$H$12+'Sales Forecast'!Q6*Assumptions!$I$12+'Sales Forecast'!W6*Assumptions!$C$13+'Sales Forecast'!V6*Assumptions!$D$13+'Sales Forecast'!U6*Assumptions!$E$13+'Sales Forecast'!T6*Assumptions!$F$13+'Sales Forecast'!S6*Assumptions!$G$13+'Sales Forecast'!R6*Assumptions!$H$13+'Sales Forecast'!Q6*Assumptions!$I$13+1731)*Assumptions!$C$17 | X20: =('Sales Forecast'!X6*Assumptions!$C$12+'Sales Forecast'!W6*Assumptions!$D$12+'Sales Forecast'!V6*Assumptions!$E$12+'Sales Forecast'!U6*Assumptions!$F$12+'Sales Forecast'!T6*Assumptions!$G$12+'Sales Forecast'!S6*Assumptions!$H$12+'Sales Forecast'!R6*Assumptions!$I$12+'Sales Forecast'!X6*Assumptions!$C$13+'Sales Forecast'!W6*Assumptions!$D$13+'Sales Forecast'!V6*Assumptions!$E$13+'Sales Forecast'!U6*Assumptions!$F$13+'Sales Forecast'!T6*Assumptions!$G$13+'Sales Forecast'!S6*Assumptions!$H$13+'Sales Forecast'!R6*Assumptions!$I$13+1731)*Assumptions!$C$17 | Y20: =('Sales Forecast'!Y6*Assumptions!$C$12+'Sales Forecast'!X6*Assumptions!$D$12+'Sales Forecast'!W6*Assumptions!$E$12+'Sales Forecast'!V6*Assumptions!$F$12+'Sales Forecast'!U6*Assumptions!$G$12+'Sales Forecast'!T6*Assumptions!$H$12+'Sales Forecast'!S6*Assumptions!$I$12+'Sales Forecast'!Y6*Assumptions!$C$13+'Sales Forecast'!X6*Assumptions!$D$13+'Sales Forecast'!W6*Assumptions!$E$13+'Sales Forecast'!V6*Assumptions!$F$13+'Sales Forecast'!U6*Assumptions!$G$13+'Sales Forecast'!T6*Assumptions!$H$13+'Sales Forecast'!S6*Assumptions!$I$13+1731)*Assumptions!$C$17 | Z20: =('Sales Forecast'!Z6*Assumptions!$C$12+'Sales Forecast'!Y6*Assumptions!$D$12+'Sales Forecast'!X6*Assumptions!$E$12+'Sales Forecast'!W6*Assumptions!$F$12+'Sales Forecast'!V6*Assumptions!$G$12+'Sales Forecast'!U6*Assumptions!$H$12+'Sales Forecast'!T6*Assumptions!$I$12+'Sales Forecast'!Z6*Assumptions!$C$13+'Sales Forecast'!Y6*Assumptions!$D$13+'Sales Forecast'!X6*Assumptions!$E$13+'Sales Forecast'!W6*Assumptions!$F$13+'Sales Forecast'!V6*Assumptions!$G$13+'Sales Forecast'!U6*Assumptions!$H$13+'Sales Forecast'!T6*Assumptions!$I$13+1731)*Assumptions!$C$17 | AA20: =('Sales Forecast'!AA6*Assumptions!$C$12+'Sales Forecast'!Z6*Assumptions!$D$12+'Sales Forecast'!Y6*Assumptions!$E$12+'Sales Forecast'!X6*Assumptions!$F$12+'Sales Forecast'!W6*Assumptions!$G$12+'Sales Forecast'!V6*Assumptions!$H$12+'Sales Forecast'!U6*Assumptions!$I$12+'Sales Forecast'!AA6*Assumptions!$C$13+'Sales Forecast'!Z6*Assumptions!$D$13+'Sales Forecast'!Y6*Assumptions!$E$13+'Sales Forecast'!X6*Assumptions!$F$13+'Sales Forecast'!W6*Assumptions!$G$13+'Sales Forecast'!V6*Assumptions!$H$13+'Sales Forecast'!U6*Assumptions!$I$13+1731)*Assumptions!$C$17 | AB20: =('Sales Forecast'!AB6*Assumptions!$C$12+'Sales Forecast'!AA6*Assumptions!$D$12+'Sales Forecast'!Z6*Assumptions!$E$12+'Sales Forecast'!Y6*Assumptions!$F$12+'Sales Forecast'!X6*Assumptions!$G$12+'Sales Forecast'!W6*Assumptions!$H$12+'Sales Forecast'!V6*Assumptions!$I$12+'Sales Forecast'!AB6*Assumptions!$C$13+'Sales Forecast'!AA6*Assumptions!$D$13+'Sales Forecast'!Z6*Assumptions!$E$13+'Sales Forecast'!Y6*Assumptions!$F$13+'Sales Forecast'!X6*Assumptions!$G$13+'Sales Forecast'!W6*Assumptions!$H$13+'Sales Forecast'!V6*Assumptions!$I$13+1731)*Assumptions!$C$17 | AC20: =('Sales Forecast'!AC6*Assumptions!$C$12+'Sales Forecast'!AB6*Assumptions!$D$12+'Sales Forecast'!AA6*Assumptions!$E$12+'Sales Forecast'!Z6*Assumptions!$F$12+'Sales Forecast'!Y6*Assumptions!$G$12+'Sales Forecast'!X6*Assumptions!$H$12+'Sales Forecast'!W6*Assumptions!$I$12+'Sales Forecast'!AC6*Assumptions!$C$13+'Sales Forecast'!AB6*Assumptions!$D$13+'Sales Forecast'!AA6*Assumptions!$E$13+'Sales Forecast'!Z6*Assumptions!$F$13+'Sales Forecast'!Y6*Assumptions!$G$13+'Sales Forecast'!X6*Assumptions!$H$13+'Sales Forecast'!W6*Assumptions!$I$13+1731)*Assumptions!$C$17 | AD20: =('Sales Forecast'!AD6*Assumptions!$C$12+'Sales Forecast'!AC6*Assumptions!$D$12+'Sales Forecast'!AB6*Assumptions!$E$12+'Sales Forecast'!AA6*Assumptions!$F$12+'Sales Forecast'!Z6*Assumptions!$G$12+'Sales Forecast'!Y6*Assumptions!$H$12+'Sales Forecast'!X6*Assumptions!$I$12+'Sales Forecast'!AD6*Assumptions!$C$13+'Sales Forecast'!AC6*Assumptions!$D$13+'Sales Forecast'!AB6*Assumptions!$E$13+'Sales Forecast'!AA6*Assumptions!$F$13+'Sales Forecast'!Z6*Assumptions!$G$13+'Sales Forecast'!Y6*Assumptions!$H$13+'Sales Forecast'!X6*Assumptions!$I$13+1731)*Assumptions!$C$17 | ... AY20: =('Sales Forecast'!AY6*Assumptions!$C$12+'Sales Forecast'!AX6*Assumptions!$D$12+'Sales Forecast'!AW6*Assumptions!$E$12+'Sales Forecast'!AV6*Assumptions!$F$12+'Sales Forecast'!AU6*Assumptions!$G$12+'Sales Forecast'!AT6*Assumptions!$H$12+'Sales Forecast'!AS6*Assumptions!$I$12+'Sales Forecast'!AY6*Assumptions!$C$13+'Sales Forecast'!AX6*Assumptions!$D$13+'Sales Forecast'!AW6*Assumptions!$E$13+'Sales Forecast'!AV6*Assumptions!$F$13+'Sales Forecast'!AU6*Assumptions!$G$13+'Sales Forecast'!AT6*Assumptions!$H$13+'Sales Forecast'!AS6*Assumptions!$I$13+1731)*Assumptions!$C$17 | BA20: =SUM(I20:T20) | BB20: =BA20/$BA$22
B21: 407000 Discounts | D21: -7378.7 | E21: -4533.12 | F21: -6389.54 | G21: -5172.1 | H21: -5087.8 | I21: -7287.54 | J21: -3691.2 | K21: -5800.96 | L21: -3071.62 | M21: -3528.96 | N21: -3664.12 | O21: -2720.3 | P21: -7048.4 | Q21: -3527.26 | R21: -2111.8 | S21: -4735.7 | T21: -2292.2 | U21: -2914.6 | V21: -946.2 | W21: =('Sales Forecast'!W6*Assumptions!$C$12+'Sales Forecast'!V6*Assumptions!$D$12+'Sales Forecast'!U6*Assumptions!$E$12+'Sales Forecast'!T6*Assumptions!$F$12+'Sales Forecast'!S6*Assumptions!$G$12+'Sales Forecast'!R6*Assumptions!$H$12+'Sales Forecast'!Q6*Assumptions!$I$12+'Sales Forecast'!W6*Assumptions!$C$13+'Sales Forecast'!V6*Assumptions!$D$13+'Sales Forecast'!U6*Assumptions!$E$13+'Sales Forecast'!T6*Assumptions!$F$13+'Sales Forecast'!S6*Assumptions!$G$13+'Sales Forecast'!R6*Assumptions!$H$13+'Sales Forecast'!Q6*Assumptions!$I$13+1731)*Assumptions!$C$18 | X21: =('Sales Forecast'!X6*Assumptions!$C$12+'Sales Forecast'!W6*Assumptions!$D$12+'Sales Forecast'!V6*Assumptions!$E$12+'Sales Forecast'!U6*Assumptions!$F$12+'Sales Forecast'!T6*Assumptions!$G$12+'Sales Forecast'!S6*Assumptions!$H$12+'Sales Forecast'!R6*Assumptions!$I$12+'Sales Forecast'!X6*Assumptions!$C$13+'Sales Forecast'!W6*Assumptions!$D$13+'Sales Forecast'!V6*Assumptions!$E$13+'Sales Forecast'!U6*Assumptions!$F$13+'Sales Forecast'!T6*Assumptions!$G$13+'Sales Forecast'!S6*Assumptions!$H$13+'Sales Forecast'!R6*Assumptions!$I$13+1731)*Assumptions!$C$18 | Y21: =('Sales Forecast'!Y6*Assumptions!$C$12+'Sales Forecast'!X6*Assumptions!$D$12+'Sales Forecast'!W6*Assumptions!$E$12+'Sales Forecast'!V6*Assumptions!$F$12+'Sales Forecast'!U6*Assumptions!$G$12+'Sales Forecast'!T6*Assumptions!$H$12+'Sales Forecast'!S6*Assumptions!$I$12+'Sales Forecast'!Y6*Assumptions!$C$13+'Sales Forecast'!X6*Assumptions!$D$13+'Sales Forecast'!W6*Assumptions!$E$13+'Sales Forecast'!V6*Assumptions!$F$13+'Sales Forecast'!U6*Assumptions!$G$13+'Sales Forecast'!T6*Assumptions!$H$13+'Sales Forecast'!S6*Assumptions!$I$13+1731)*Assumptions!$C$18 | Z21: =('Sales Forecast'!Z6*Assumptions!$C$12+'Sales Forecast'!Y6*Assumptions!$D$12+'Sales Forecast'!X6*Assumptions!$E$12+'Sales Forecast'!W6*Assumptions!$F$12+'Sales Forecast'!V6*Assumptions!$G$12+'Sales Forecast'!U6*Assumptions!$H$12+'Sales Forecast'!T6*Assumptions!$I$12+'Sales Forecast'!Z6*Assumptions!$C$13+'Sales Forecast'!Y6*Assumptions!$D$13+'Sales Forecast'!X6*Assumptions!$E$13+'Sales Forecast'!W6*Assumptions!$F$13+'Sales Forecast'!V6*Assumptions!$G$13+'Sales Forecast'!U6*Assumptions!$H$13+'Sales Forecast'!T6*Assumptions!$I$13+1731)*Assumptions!$C$18 | AA21: =('Sales Forecast'!AA6*Assumptions!$C$12+'Sales Forecast'!Z6*Assumptions!$D$12+'Sales Forecast'!Y6*Assumptions!$E$12+'Sales Forecast'!X6*Assumptions!$F$12+'Sales Forecast'!W6*Assumptions!$G$12+'Sales Forecast'!V6*Assumptions!$H$12+'Sales Forecast'!U6*Assumptions!$I$12+'Sales Forecast'!AA6*Assumptions!$C$13+'Sales Forecast'!Z6*Assumptions!$D$13+'Sales Forecast'!Y6*Assumptions!$E$13+'Sales Forecast'!X6*Assumptions!$F$13+'Sales Forecast'!W6*Assumptions!$G$13+'Sales Forecast'!V6*Assumptions!$H$13+'Sales Forecast'!U6*Assumptions!$I$13+1731)*Assumptions!$C$18 | AB21: =('Sales Forecast'!AB6*Assumptions!$C$12+'Sales Forecast'!AA6*Assumptions!$D$12+'Sales Forecast'!Z6*Assumptions!$E$12+'Sales Forecast'!Y6*Assumptions!$F$12+'Sales Forecast'!X6*Assumptions!$G$12+'Sales Forecast'!W6*Assumptions!$H$12+'Sales Forecast'!V6*Assumptions!$I$12+'Sales Forecast'!AB6*Assumptions!$C$13+'Sales Forecast'!AA6*Assumptions!$D$13+'Sales Forecast'!Z6*Assumptions!$E$13+'Sales Forecast'!Y6*Assumptions!$F$13+'Sales Forecast'!X6*Assumptions!$G$13+'Sales Forecast'!W6*Assumptions!$H$13+'Sales Forecast'!V6*Assumptions!$I$13+1731)*Assumptions!$C$18 | AC21: =('Sales Forecast'!AC6*Assumptions!$C$12+'Sales Forecast'!AB6*Assumptions!$D$12+'Sales Forecast'!AA6*Assumptions!$E$12+'Sales Forecast'!Z6*Assumptions!$F$12+'Sales Forecast'!Y6*Assumptions!$G$12+'Sales Forecast'!X6*Assumptions!$H$12+'Sales Forecast'!W6*Assumptions!$I$12+'Sales Forecast'!AC6*Assumptions!$C$13+'Sales Forecast'!AB6*Assumptions!$D$13+'Sales Forecast'!AA6*Assumptions!$E$13+'Sales Forecast'!Z6*Assumptions!$F$13+'Sales Forecast'!Y6*Assumptions!$G$13+'Sales Forecast'!X6*Assumptions!$H$13+'Sales Forecast'!W6*Assumptions!$I$13+1731)*Assumptions!$C$18 | AD21: =('Sales Forecast'!AD6*Assumptions!$C$12+'Sales Forecast'!AC6*Assumptions!$D$12+'Sales Forecast'!AB6*Assumptions!$E$12+'Sales Forecast'!AA6*Assumptions!$F$12+'Sales Forecast'!Z6*Assumptions!$G$12+'Sales Forecast'!Y6*Assumptions!$H$12+'Sales Forecast'!X6*Assumptions!$I$12+'Sales Forecast'!AD6*Assumptions!$C$13+'Sales Forecast'!AC6*Assumptions!$D$13+'Sales Forecast'!AB6*Assumptions!$E$13+'Sales Forecast'!AA6*Assumptions!$F$13+'Sales Forecast'!Z6*Assumptions!$G$13+'Sales Forecast'!Y6*Assumptions!$H$13+'Sales Forecast'!X6*Assumptions!$I$13+1731)*Assumptions!$C$18 | ... AY21: =('Sales Forecast'!AY6*Assumptions!$C$12+'Sales Forecast'!AX6*Assumptions!$D$12+'Sales Forecast'!AW6*Assumptions!$E$12+'Sales Forecast'!AV6*Assumptions!$F$12+'Sales Forecast'!AU6*Assumptions!$G$12+'Sales Forecast'!AT6*Assumptions!$H$12+'Sales Forecast'!AS6*Assumptions!$I$12+'Sales Forecast'!AY6*Assumptions!$C$13+'Sales Forecast'!AX6*Assumptions!$D$13+'Sales Forecast'!AW6*Assumptions!$E$13+'Sales Forecast'!AV6*Assumptions!$F$13+'Sales Forecast'!AU6*Assumptions!$G$13+'Sales Forecast'!AT6*Assumptions!$H$13+'Sales Forecast'!AS6*Assumptions!$I$13+1731)*Assumptions!$C$18 | BA21: =SUM(I21:T21) | BB21: =BA21/$BA$22
B22: TOTAL REVENUE | D22: =SUM(D13,D14,D18,D19,D20,D21) | E22: =SUM(E13,E14,E18,E19,E20,E21) | F22: =SUM(F13,F14,F18,F19,F20,F21) | G22: =SUM(G13,G14,G18,G19,G20,G21) | H22: =SUM(H13,H14,H18,H19,H20,H21) | I22: =SUM(I13,I14,I18,I19,I20,I21) | J22: =SUM(J13,J14,J18,J19,J20,J21) | K22: =SUM(K13,K14,K18,K19,K20,K21) | ... O22: =SUM(O13,O14,O18,O19,O20,O21) | P22: =P13+P14+P18+P19+P20+P21 | Q22: =Q13+Q14+Q18+Q19+Q20+Q21 | R22: =R13+R14+R18+R19+R20+R21 | S22: =S13+S14+S18+S19+S20+S21 | T22: =T13+T14+T18+T19+T20+T21 | U22: =U13+U14+U18+U19+U20+U21 | V22: =V13+V14+V18+V19+V20+V21 | W22: =W13+W18+W19+W20+W21 | X22: =X13+X18+X19+X20+X21 | Y22: =Y13+Y18+Y19+Y20+Y21 | Z22: =Z13+Z18+Z19+Z20+Z21 | AA22: =AA13+AA18+AA19+AA20+AA21 | AB22: =AB13+AB18+AB19+AB20+AB21 | AC22: =AC13+AC18+AC19+AC20+AC21 | AD22: =AD13+AD18+AD19+AD20+AD21 | ... AY22: =AY13+AY18+AY19+AY20+AY21 | BA22: =SUM(I22:T22) | BB22: =SUM(BB7:BB21)
B23: COST OF GOODS SOLD | D23: 0 | E23: 0 | F23: 0 | G23: 0 | H23: 0 | I23: 0 | J23: 0 | K23: 0 | L23: 0 | M23: 0 | N23: 0 | O23: 0
B24: 501000 Product Cost (incl Inventory Shrinkage) | D24: 1635 | E24: 1240.75 | F24: 1097.25 | G24: 1298.5 | H24: 1160.5 | I24: 1974.75 | J24: 1301 | K24: 1424.5 | L24: 1231 | M24: 896.5 | N24: 836.5 | O24: 2191.37 | P24: 1064.8 | Q24: 699.7 | R24: 552 | S24: 1117 | T24: 1037.7 | U24: 1175 | V24: 917 | W24: =W22*Assumptions!$C$20 | X24: =X22*Assumptions!$C$20 | Y24: =Y22*Assumptions!$C$20 | Z24: =Z22*Assumptions!$C$20 | AA24: =AA22*Assumptions!$C$20 | AB24: =AB22*Assumptions!$C$20 | AC24: =AC22*Assumptions!$C$20 | AD24: =AD22*Assumptions!$C$20 | ... AY24: =AY22*Assumptions!$C$20
B25: 506000 Merchant Account Fees | D25: 3612.09 | E25: 3333.58 | F25: 3314.08 | G25: 3895.12 | H25: 2604.04 | I25: 2902.85 | J25: 2543.4 | K25: 3738.8 | L25: 2974.49 | M25: 2918.1 | N25: 2598.16 | O25: 2820.42 | P25: 3389.06 | Q25: 3622.31 | R25: 2884.21 | S25: 3288.71 | T25: 2178.41 | U25: 2530.03 | V25: 2678.11 | W25: =W22*Assumptions!$C$19 | X25: =X22*Assumptions!$C$19 | Y25: =Y22*Assumptions!$C$19 | Z25: =Z22*Assumptions!$C$19 | AA25: =AA22*Assumptions!$C$19 | AB25: =AB22*Assumptions!$C$19 | AC25: =AC22*Assumptions!$C$19 | AD25: =AD22*Assumptions!$C$19 | ... AY25: =AY22*Assumptions!$C$19
B26: Total Cost of Goods Sold | D26: =SUM(D24:D25) | E26: =SUM(E24:E25) | F26: =SUM(F24:F25) | G26: =SUM(G24:G25) | H26: =SUM(H24:H25) | I26: =SUM(I24:I25) | J26: =SUM(J24:J25) | K26: =SUM(K24:K25) | ... O26: =SUM(O24:O25) | P26: =P24+P25 | Q26: =Q24+Q25 | R26: =R24+R25 | S26: =S24+S25 | T26: =T24+T25 | U26: =U24+U25 | V26: =V24+V25 | W26: =W24+W25 | ... AY26: =AY24+AY25
B27: GROSS PROFIT | D27: =D22-D26 | E27: =E22-E26 | F27: =F22-F26 | G27: =G22-G26 | H27: =H22-H26 | I27: =I22-I26 | J27: =J22-J26 | K27: =K22-K26 | ... AY27: =AY22-AY26
B28: OPERATING EXPENSES
B29: 601001 Paid Ads | D29: 1300 | E29: 300 | F29: 0 | G29: 0 | H29: 0 | I29: 2407.42 | J29: 300 | K29: 0 | L29: 0 | M29: 0 | N29: 890.91 | O29: 607.27 | P29: 972.72 | Q29: 89.99 | R29: 0 | S29: 0 | T29: 0 | U29: 0 | V29: 0 | W29: 0 | X29: 0 | Y29: 0 | Z29: 0 | AA29: 0 | AB29: 0 | AC29: 0 | AD29: 0 | AE29: 0 | AF29: 0 | AG29: 0 | AH29: 0 | AI29: 0 | AJ29: 0 | AK29: 0 | AL29: 0 | AM29: 0 | AN29: 0 | AO29: 0 | AP29: 0 | AQ29: 0 | AR29: 0 | AS29: 0 | AT29: 0 | AU29: 0 | AV29: 0 | AW29: 0 | AX29: 0 | AY29: 0
B30: 601005 Content Creation | D30: 0 | E30: 0 | F30: 0 | G30: 0 | H30: 0 | I30: 0 | J30: 0 | K30: 0 | L30: 0 | M30: 0 | N30: 0 | O30: 0 | P30: 0 | Q30: 0 | R30: 0 | S30: 0 | T30: 0 | U30: 0 | V30: 0 | W30: 0 | X30: 0 | Y30: 0 | Z30: 0 | AA30: 0 | AB30: 0 | AC30: 0 | AD30: 0 | AE30: 0 | AF30: 0 | AG30: 0 | AH30: 0 | AI30: 0 | AJ30: 0 | AK30: 0 | AL30: 0 | AM30: 0 | AN30: 0 | AO30: 0 | AP30: 0 | AQ30: 0 | AR30: 0 | AS30: 0 | AT30: 0 | AU30: 0 | AV30: 0 | AW30: 0 | AX30: 0 | AY30: 0
B31: 601006 General Marketing (incl Affiliate, PR, Trade Shows) | D31: 0 | E31: 0 | F31: 0 | G31: 0 | H31: 0 | I31: 0 | J31: 0 | K31: 0 | L31: 0 | M31: 0 | N31: 0 | O31: 128.98 | P31: 0 | Q31: 0 | R31: 0 | S31: 0 | T31: 0 | U31: 0 | V31: 0 | W31: 0 | X31: 0 | Y31: 0 | Z31: 0 | AA31: 0 | AB31: 0 | AC31: 0 | AD31: 0 | AE31: 0 | AF31: 0 | AG31: 0 | AH31: 0 | AI31: 0 | AJ31: 0 | AK31: 0 | AL31: 0 | AM31: 0 | AN31: 0 | AO31: 0 | AP31: 0 | AQ31: 0 | AR31: 0 | AS31: 0 | AT31: 0 | AU31: 0 | AV31: 0 | AW31: 0 | AX31: 0 | AY31: 0
B32: 601007 Contractors/Agencies | D32: 0 | E32: 0 | F32: 0 | G32: 0 | H32: 0 | I32: 0 | J32: 0 | K32: 0 | L32: 0 | M32: 0 | N32: 0 | O32: 0 | P32: 0 | Q32: 0 | R32: 0 | S32: 0 | T32: 0 | U32: 0 | V32: 0 | W32: 0 | X32: 0 | Y32: 0 | Z32: 0 | AA32: 0 | AB32: 0 | AC32: 0 | AD32: 0 | AE32: 0 | AF32: 0 | AG32: 0 | AH32: 0 | AI32: 0 | AJ32: 0 | AK32: 0 | AL32: 0 | AM32: 0 | AN32: 0 | AO32: 0 | AP32: 0 | AQ32: 0 | AR32: 0 | AS32: 0 | AT32: 0 | AU32: 0 | AV32: 0 | AW32: 0 | AX32: 0 | AY32: 0
B33: 601010 Website Development | D33: 0 | E33: 0 | F33: 0 | G33: 0 | H33: 0 | I33: 0 | J33: 0 | K33: 0 | L33: 0 | M33: 0 | N33: 0 | O33: 0 | P33: 0 | Q33: 0 | R33: 0 | S33: 0 | T33: 0 | U33: 0 | V33: 0 | W33: 0 | X33: 0 | Y33: 0 | Z33: 0 | AA33: 0 | AB33: 0 | AC33: 0 | AD33: 0 | AE33: 0 | AF33: 0 | AG33: 0 | AH33: 0 | AI33: 0 | AJ33: 0 | AK33: 0 | AL33: 0 | AM33: 0 | AN33: 0 | AO33: 0 | AP33: 0 | AQ33: 0 | AR33: 0 | AS33: 0 | AT33: 0 | AU33: 0 | AV33: 0 | AW33: 0 | AX33: 0 | AY33: 0
B34: Total Marketing | D34: =SUM(D29:D33) | E34: =SUM(E29:E33) | F34: =SUM(F29:F33) | G34: =SUM(G29:G33) | H34: =SUM(H29:H33) | I34: =SUM(I29:I33) | J34: =SUM(J29:J33) | K34: =SUM(K29:K33) | ... O34: =SUM(O29:O33) | P34: =P29+P30+P31+P32+P33 | Q34: =Q29+Q30+Q31+Q32+Q33 | R34: =R29+R30+R31+R32+R33 | S34: =S29+S30+S31+S32+S33 | T34: =T29+T30+T31+T32+T33 | U34: =U29+U30+U31+U32+U33 | V34: =V29+V30+V31+V32+V33 | W34: =W29+W30+W31+W32+W33 | ... AY34: =AY29+AY30+AY31+AY32+AY33
B35: 602001 Wages (incl 1099 & Bonus) | D35: 47131.67 | E35: 44706.41 | F35: 51633.23 | G35: 44141.5 | H35: 49761.89 | I35: 46010.63 | J35: 45228.67 | K35: 49076.32 | L35: 46071.96 | M35: 45374.11 | N35: 46265.48 | O35: 48476.44 | P35: 53569.86 | Q35: 45269.74 | R35: 50483.61 | S35: 48918.6 | T35: 46338.59 | U35: 43849.66 | V35: 43106.63 | W35: 41413.73 | X35: 43268.43 | Y35: 45285.75 | Z35: 47951.33 | AA35: 51055.88 | AB35: 40664.36 | AC35: 40625.33 | AD35: 34619.86 | AE35: 35938.11 | AF35: 42329.64 | AG35: 37828.54 | AH35: 34441.26 | AI35: 36324.13 | AJ35: 37477.66 | AK35: 39849.89 | AL35: 40707.25 | AM35: 44854.49 | AN35: 40664.36 | AO35: 40625.33 | AP35: 34619.86 | AQ35: 35938.11 | AR35: 42329.64 | AS35: 37828.54 | AT35: 34441.26 | AU35: 36324.13 | AV35: 37477.66 | AW35: 39849.89 | AX35: 40707.25 | AY35: 44854.49
B36: 602004 Payroll Taxes | D36: 5601.59 | E36: 4241.17 | F36: 4058.89 | G36: 3607.45 | H36: 3918.25 | I36: 3681.89 | J36: 3764.68 | K36: 4102.57 | L36: 3992.68 | M36: 3965.95 | N36: 4189.02 | O36: 4860.72 | P36: 8608.49 | Q36: 4671.71 | R36: 4875.87 | S36: 4083.91 | T36: 3854.15 | U36: 3654.53 | V36: 3575.32 | W36: 4646.05 | X36: 4854.12 | Y36: 5080.43 | Z36: 5379.47 | AA36: 5727.76 | AB36: 4561.98 | AC36: 4557.6 | AD36: 3883.87 | AE36: 4031.76 | AF36: 4748.8 | AG36: 4243.84 | AH36: 3863.83 | AI36: 4075.06 | AJ36: 4204.47 | AK36: 4470.6 | AL36: 4566.79 | AM36: 5032.05 | AN36: 4561.98 | AO36: 4557.6 | AP36: 3883.87 | AQ36: 4031.76 | AR36: 4748.8 | AS36: 4243.84 | AT36: 3863.83 | AU36: 4075.06 | AV36: 4204.47 | AW36: 4470.6 | AX36: 4566.79 | AY36: 5032.05
B37: 602005 Employee Benefits (incl Workers Comp) | D37: 1710.25 | E37: 2203.27 | F37: 411.99 | G37: -506.25 | H37: -792.69 | I37: 715.06 | J37: 1448.58 | K37: 1990.15 | L37: 2014.72 | M37: 3048.32 | N37: 1185.44 | O37: 500.23 | P37: 576.08 | Q37: 604.43 | R37: 788.96 | S37: 633.32 | T37: 505.23 | U37: 643.24 | V37: 554.54 | W37: 535.59 | X37: 559.58 | Y37: 585.66 | Z37: 620.14 | AA37: 660.29 | AB37: 525.9 | AC37: 525.39 | AD37: 447.73 | AE37: 464.77 | AF37: 547.43 | AG37: 489.22 | AH37: 445.42 | AI37: 469.77 | AJ37: 484.69 | AK37: 515.36 | AL37: 526.45 | AM37: 580.09 | AN37: 525.9 | AO37: 525.39 | AP37: 447.73 | AQ37: 464.77 | AR37: 547.43 | AS37: 489.22 | AT37: 445.42 | AU37: 469.77 | AV37: 484.69 | AW37: 515.36 | AX37: 526.45 | AY37: 580.09
B38: 602010 Payroll Processing Fees | D38: 862.93 | E38: 334.34 | F38: 331.49 | G38: 463.71 | H38: 345.74 | I38: 342.89 | J38: 342.89 | K38: 518.61 | L38: 351.44 | M38: 351.44 | N38: 357.14 | O38: 1458.02 | P38: 2263.63 | Q38: 2268.79 | R38: 3275.92 | S38: 2263.27 | T38: 2125.12 | U38: 2043.79 | V38: 1944.91 | W38: 2104.01 | X38: 2198.24 | Y38: 2300.73 | Z38: 2436.15 | AA38: 2593.88 | AB38: 2065.94 | AC38: 2063.96 | AD38: 1758.85 | AE38: 1825.82 | AF38: 2150.54 | AG38: 1921.87 | AH38: 1749.78 | AI38: 1845.44 | AJ38: 1904.04 | AK38: 2024.56 | AL38: 2068.12 | AM38: 2278.82 | AN38: 2065.94 | AO38: 2063.96 | AP38: 1758.85 | AQ38: 1825.82 | AR38: 2150.54 | AS38: 1921.87 | AT38: 1749.78 | AU38: 1845.44 | AV38: 1904.04 | AW38: 2024.56 | AX38: 2068.12 | AY38: 2278.82
B39: Total Payroll | D39: =SUM(D35:D38) | E39: =SUM(E35:E38) | F39: =SUM(F35:F38) | G39: =SUM(G35:G38) | H39: =SUM(H35:H38) | I39: =SUM(I35:I38) | J39: =SUM(J35:J38) | K39: =SUM(K35:K38) | ... O39: =SUM(O35:O38) | P39: =P35+P36+P37+P38 | Q39: =Q35+Q36+Q37+Q38 | R39: =R35+R36+R37+R38 | S39: =S35+S36+S37+S38 | T39: =T35+T36+T37+T38 | U39: =U35+U36+U37+U38 | V39: =V35+V36+V37+V38 | W39: =W35+W36+W37+W38 | ... AY39: =AY35+AY36+AY37+AY38
B40: 603000 Software & Web Services | D40: 789.62 | E40: 837.5 | F40: 595.3 | G40: 1222.24 | H40: 1287.99 | I40: 1042.77 | J40: 707.99 | K40: 1705.78 | L40: 626.99 | M40: 736.08 | N40: 831.09 | O40: 736.08 | P40: 790.53 | Q40: 1351.94 | R40: 737.08 | S40: 1555.7 | T40: 762.26 | U40: 762.26 | V40: 1106.46 | W40: 864.31 | X40: 864.31 | Y40: 864.31 | Z40: 864.31 | AA40: 864.31 | AB40: 864.31 | AC40: 864.31 | AD40: 864.31 | AE40: 864.31 | AF40: 864.31 | AG40: 864.31 | AH40: 864.31 | AI40: 864.31 | AJ40: 864.31 | AK40: 864.31 | AL40: 864.31 | AM40: 864.31 | AN40: 864.31 | AO40: 864.31 | AP40: 864.31 | AQ40: 864.31 | AR40: 864.31 | AS40: 864.31 | AT40: 864.31 | AU40: 864.31 | AV40: 864.31 | AW40: 864.31 | AX40: 864.31 | AY40: 864.31
B41: 608000 Insurance | D41: 239.07 | E41: 239.07 | F41: 239.07 | G41: 239.07 | H41: 239.07 | I41: 239.07 | J41: 239.07 | K41: 239.07 | L41: 239.07 | M41: 451.07 | N41: 451.07 | O41: 451.07 | P41: 94.62 | Q41: 94.62 | R41: 230.72 | S41: 230.72 | T41: 294.83 | U41: 290.82 | V41: 290.82 | W41: 154.38 | X41: 154.38 | Y41: 154.38 | Z41: 154.38 | AA41: 154.38 | AB41: 154.38 | AC41: 154.38 | AD41: 154.38 | AE41: 154.38 | AF41: 154.38 | AG41: 154.38 | AH41: 154.38 | AI41: 154.38 | AJ41: 154.38 | AK41: 154.38 | AL41: 154.38 | AM41: 154.38 | AN41: 154.38 | AO41: 154.38 | AP41: 154.38 | AQ41: 154.38 | AR41: 154.38 | AS41: 154.38 | AT41: 154.38 | AU41: 154.38 | AV41: 154.38 | AW41: 154.38 | AX41: 154.38 | AY41: 154.38
B42: 610000 Office Supplies & GE (incl Licenses, Furniture, Shipping, Bank Fees, Start-Up Costs) | D42: 2040.15 | E42: 2230.91 | F42: 896.1 | G42: 1133.09 | H42: 2169.23 | I42: 1548.7 | J42: 5132.93 | K42: 597.22 | L42: 797.03 | M42: 567.04 | N42: 1108.61 | O42: 352.71 | P42: 689.59 | Q42: 852.3 | R42: 1294.74 | S42: 1959.04 | T42: 1238.49 | U42: 1359.53 | V42: 1027.5 | W42: 556.05 | X42: 556.05 | Y42: 556.05 | Z42: 556.05 | AA42: 556.05 | AB42: 556.05 | AC42: 556.05 | AD42: 556.05 | AE42: 556.05 | AF42: 556.05 | AG42: 556.05 | AH42: 556.05 | AI42: 556.05 | AJ42: 556.05 | AK42: 556.05 | AL42: 556.05 | AM42: 556.05 | AN42: 556.05 | AO42: 556.05 | AP42: 556.05 | AQ42: 556.05 | AR42: 556.05 | AS42: 556.05 | AT42: 556.05 | AU42: 556.05 | AV42: 556.05 | AW42: 556.05 | AX42: 556.05 | AY42: 556.05
B43: Total Software & Admin | D43: =D40+D41+D42 | E43: =E40+E41+E42 | F43: =F40+F41+F42 | G43: =G40+G41+G42 | H43: =H40+H41+H42 | I43: =I40+I41+I42 | J43: =J40+J41+J42 | K43: =K40+K41+K42 | ... AY43: =AY40+AY41+AY42
B44: 604100 Legal Fees | D44: 0 | E44: 0 | F44: 220 | G44: 0 | H44: 0 | I44: 0 | J44: 0 | K44: 0 | L44: 0 | M44: 0 | N44: 0 | O44: 0 | P44: 0 | Q44: 0 | R44: 0 | S44: 0 | T44: 0 | U44: 0 | V44: 0 | W44: 0 | X44: 0 | Y44: 0 | Z44: 0 | AA44: 0 | AB44: 0 | AC44: 0 | AD44: 0 | AE44: 0 | AF44: 0 | AG44: 0 | AH44: 0 | AI44: 0 | AJ44: 0 | AK44: 0 | AL44: 0 | AM44: 0 | AN44: 0 | AO44: 0 | AP44: 0 | AQ44: 0 | AR44: 0 | AS44: 0 | AT44: 0 | AU44: 0 | AV44: 0 | AW44: 0 | AX44: 0 | AY44: 0
B45: 604200 Accounting | D45: 321.75 | E45: 143 | F45: 225.5 | G45: 45.5 | H45: 2095.5 | I45: 45.5 | J45: 45.5 | K45: 951.75 | L45: 52.5 | M45: 0 | N45: 154.54 | O45: 101.6 | P45: 0 | Q45: 301.82 | R45: 440 | S45: 0 | T45: 0 | U45: 0 | V45: 0 | W45: 136.49 | X45: 136.49 | Y45: 136.49 | Z45: 136.49 | AA45: 136.49 | AB45: 136.49 | AC45: 136.49 | AD45: 136.49 | AE45: 136.49 | AF45: 136.49 | AG45: 136.49 | AH45: 136.49 | AI45: 136.49 | AJ45: 136.49 | AK45: 136.49 | AL45: 136.49 | AM45: 136.49 | AN45: 136.49 | AO45: 136.49 | AP45: 136.49 | AQ45: 136.49 | AR45: 136.49 | AS45: 136.49 | AT45: 136.49 | AU45: 136.49 | AV45: 136.49 | AW45: 136.49 | AX45: 136.49 | AY45: 136.49
B46: 604300 Recruiting | D46: 0 | E46: 0 | F46: 0 | G46: 75 | H46: 0 | I46: 0 | J46: 0 | K46: 0 | L46: 0 | M46: 0 | N46: 0 | O46: 0 | P46: 0 | Q46: 0 | R46: 0 | S46: 0 | T46: 0 | U46: 0 | V46: 0 | W46: 0 | X46: 0 | Y46: 0 | Z46: 0 | AA46: 0 | AB46: 0 | AC46: 0 | AD46: 0 | AE46: 0 | AF46: 0 | AG46: 0 | AH46: 0 | AI46: 0 | AJ46: 0 | AK46: 0 | AL46: 0 | AM46: 0 | AN46: 0 | AO46: 0 | AP46: 0 | AQ46: 0 | AR46: 0 | AS46: 0 | AT46: 0 | AU46: 0 | AV46: 0 | AW46: 0 | AX46: 0 | AY46: 0
B47: 604400 Other Professional Fees | D47: 0 | E47: 0 | F47: 0 | G47: 0 | H47: 0 | I47: 0 | J47: 479.1 | K47: 479.1 | L47: 479.1 | M47: 481 | N47: 481 | O47: 497.2 | P47: 517 | Q47: 517 | R47: 517 | S47: 517 | T47: 517 | U47: 517 | V47: 517 | W47: 380.51 | X47: 380.51 | Y47: 380.51 | Z47: 380.51 | AA47: 380.51 | AB47: 380.51 | AC47: 380.51 | AD47: 380.51 | AE47: 380.51 | AF47: 380.51 | AG47: 380.51 | AH47: 380.51 | AI47: 380.51 | AJ47: 380.51 | AK47: 380.51 | AL47: 380.51 | AM47: 380.51 | AN47: 380.51 | AO47: 380.51 | AP47: 380.51 | AQ47: 380.51 | AR47: 380.51 | AS47: 380.51 | AT47: 380.51 | AU47: 380.51 | AV47: 380.51 | AW47: 380.51 | AX47: 380.51 | AY47: 380.51
B48: Total Professional Fees | D48: =SUM(D44:D47) | E48: =SUM(E44:E47) | F48: =SUM(F44:F47) | G48: =SUM(G44:G47) | H48: =SUM(H44:H47) | I48: =SUM(I44:I47) | J48: =SUM(J44:J47) | K48: =SUM(K44:K47) | ... O48: =SUM(O44:O47) | P48: =P44+P45+P46+P47 | Q48: =Q44+Q45+Q46+Q47 | R48: =R44+R45+R46+R47 | S48: =S44+S45+S46+S47 | T48: =T44+T45+T46+T47 | U48: =U44+U45+U46+U47 | V48: =V44+V45+V46+V47 | W48: =W44+W45+W46+W47 | ... AY48: =AY44+AY45+AY46+AY47
B49: 605000 Travel | D49: 36.4 | E49: 0 | F49: 24 | G49: 69.25 | H49: 117.75 | I49: 147.75 | J49: 0 | K49: 273.1 | L49: 252.7 | M49: 118.25 | N49: 35.86 | O49: 61.25 | P49: 17.1 | Q49: 34 | R49: 6.02 | S49: 17.28 | T49: 153.82 | U49: 476.36 | V49: 0 | W49: 21.44 | X49: 21.44 | Y49: 21.44 | Z49: 21.44 | AA49: 21.44 | AB49: 21.44 | AC49: 21.44 | AD49: 21.44 | AE49: 21.44 | AF49: 21.44 | AG49: 21.44 | AH49: 21.44 | AI49: 21.44 | AJ49: 21.44 | AK49: 21.44 | AL49: 21.44 | AM49: 21.44 | AN49: 21.44 | AO49: 21.44 | AP49: 21.44 | AQ49: 21.44 | AR49: 21.44 | AS49: 21.44 | AT49: 21.44 | AU49: 21.44 | AV49: 21.44 | AW49: 21.44 | AX49: 21.44 | AY49: 21.44
B50: 606000 Meals (incl Entertainment) | D50: 208.29 | E50: 0 | F50: 93.28 | G50: 96.02 | H50: 0 | I50: 17.77 | J50: 0 | K50: 114.05 | L50: 280.75 | M50: 72.09 | N50: 357.66 | O50: 224.29 | P50: 122.32 | Q50: 90.59 | R50: 78.12 | S50: 92.19 | T50: 0 | U50: 122.69 | V50: 80.94 | W50: 117.98 | X50: 117.98 | Y50: 117.98 | Z50: 117.98 | AA50: 117.98 | AB50: 117.98 | AC50: 117.98 | AD50: 117.98 | AE50: 117.98 | AF50: 117.98 | AG50: 117.98 | AH50: 117.98 | AI50: 117.98 | AJ50: 117.98 | AK50: 117.98 | AL50: 117.98 | AM50: 117.98 | AN50: 117.98 | AO50: 117.98 | AP50: 117.98 | AQ50: 117.98 | AR50: 117.98 | AS50: 117.98 | AT50: 117.98 | AU50: 117.98 | AV50: 117.98 | AW50: 117.98 | AX50: 117.98 | AY50: 117.98
B51: Total Travel & Meals | D51: =D49+D50 | E51: =E49+E50 | F51: =F49+F50 | G51: =G49+G50 | H51: =H49+H50 | I51: =I49+I50 | J51: =J49+J50 | K51: =K49+K50 | ... AY51: =AY49+AY50
B52: 616001 Electricity | D52: 0 | E52: 0 | F52: 0 | G52: 0 | H52: 0 | I52: 0 | J52: 0 | K52: 0 | L52: 0 | M52: 0 | N52: 0 | O52: 0 | P52: 0 | Q52: 0 | R52: 0 | S52: 0 | T52: 0 | U52: 0 | V52: 0 | W52: 0 | X52: 0 | Y52: 0 | Z52: 0 | AA52: 0 | AB52: 0 | AC52: 0 | AD52: 0 | AE52: 0 | AF52: 0 | AG52: 0 | AH52: 0 | AI52: 0 | AJ52: 0 | AK52: 0 | AL52: 0 | AM52: 0 | AN52: 0 | AO52: 0 | AP52: 0 | AQ52: 0 | AR52: 0 | AS52: 0 | AT52: 0 | AU52: 0 | AV52: 0 | AW52: 0 | AX52: 0 | AY52: 0
B53: 616002 Internet & TV | D53: 0 | E53: 0 | F53: 0 | G53: 0 | H53: 0 | I53: 0 | J53: 0 | K53: 0 | L53: 0 | M53: 0 | N53: 0 | O53: 0 | P53: 212.35 | Q53: 212.35 | R53: 212.35 | S53: 212.35 | T53: 212.35 | U53: 212.35 | V53: 212.35 | W53: 70.32 | X53: 70.32 | Y53: 70.32 | Z53: 70.32 | AA53: 70.32 | AB53: 70.32 | AC53: 70.32 | AD53: 70.32 | AE53: 70.32 | AF53: 70.32 | AG53: 70.32 | AH53: 70.32 | AI53: 70.32 | AJ53: 70.32 | AK53: 70.32 | AL53: 70.32 | AM53: 70.32 | AN53: 70.32 | AO53: 70.32 | AP53: 70.32 | AQ53: 70.32 | AR53: 70.32 | AS53: 70.32 | AT53: 70.32 | AU53: 70.32 | AV53: 70.32 | AW53: 70.32 | AX53: 70.32 | AY53: 70.32
B54: 616003 Phone service | D54: 107.21 | E54: 107.34 | F54: 107.34 | G54: 107.34 | H54: 107.12 | I54: 192.37 | J54: 107.12 | K54: 107.12 | L54: 107.12 | M54: 109.65 | N54: 109.7 | O54: 116.73 | P54: 116.81 | Q54: 2776.16 | R54: 116.75 | S54: 116.75 | T54: 116.73 | U54: 116.73 | V54: 116.73 | W54: 258.84 | X54: 258.84 | Y54: 258.84 | Z54: 258.84 | AA54: 258.84 | AB54: 258.84 | AC54: 258.84 | AD54: 258.84 | AE54: 258.84 | AF54: 258.84 | AG54: 258.84 | AH54: 258.84 | AI54: 258.84 | AJ54: 258.84 | AK54: 258.84 | AL54: 258.84 | AM54: 258.84 | AN54: 258.84 | AO54: 258.84 | AP54: 258.84 | AQ54: 258.84 | AR54: 258.84 | AS54: 258.84 | AT54: 258.84 | AU54: 258.84 | AV54: 258.84 | AW54: 258.84 | AX54: 258.84 | AY54: 258.84
B55: 616004 Water & sewer | D55: 0 | E55: 0 | F55: 0 | G55: 0 | H55: 0 | I55: 0 | J55: 0 | K55: 0 | L55: 0 | M55: 0 | N55: 0 | O55: 0 | P55: 0 | Q55: 0 | R55: 0 | S55: 0 | T55: 0 | U55: 0 | V55: 0 | W55: 0 | X55: 0 | Y55: 0 | Z55: 0 | AA55: 0 | AB55: 0 | AC55: 0 | AD55: 0 | AE55: 0 | AF55: 0 | AG55: 0 | AH55: 0 | AI55: 0 | AJ55: 0 | AK55: 0 | AL55: 0 | AM55: 0 | AN55: 0 | AO55: 0 | AP55: 0 | AQ55: 0 | AR55: 0 | AS55: 0 | AT55: 0 | AU55: 0 | AV55: 0 | AW55: 0 | AX55: 0 | AY55: 0
B56: 616005 Disposal Services | D56: 0 | E56: 0 | F56: 0 | G56: 0 | H56: 0 | I56: 0 | J56: 0 | K56: 0 | L56: 0 | M56: 0 | N56: 0 | O56: 0 | P56: 0 | Q56: 0 | R56: 0 | S56: 0 | T56: 0 | U56: 0 | V56: 0 | W56: 0 | X56: 0 | Y56: 0 | Z56: 0 | AA56: 0 | AB56: 0 | AC56: 0 | AD56: 0 | AE56: 0 | AF56: 0 | AG56: 0 | AH56: 0 | AI56: 0 | AJ56: 0 | AK56: 0 | AL56: 0 | AM56: 0 | AN56: 0 | AO56: 0 | AP56: 0 | AQ56: 0 | AR56: 0 | AS56: 0 | AT56: 0 | AU56: 0 | AV56: 0 | AW56: 0 | AX56: 0 | AY56: 0
B57: Total Utilities | D57: =SUM(D52:D56) | E57: =SUM(E52:E56) | F57: =SUM(F52:F56) | G57: =SUM(G52:G56) | H57: =SUM(H52:H56) | I57: =SUM(I52:I56) | J57: =SUM(J52:J56) | K57: =SUM(K52:K56) | ... O57: =SUM(O52:O56) | P57: =P52+P53+P54+P55+P56 | Q57: =Q52+Q53+Q54+Q55+Q56 | R57: =R52+R53+R54+R55+R56 | S57: =S52+S53+S54+S55+S56 | T57: =T52+T53+T54+T55+T56 | U57: =U52+U53+U54+U55+U56 | V57: =V52+V53+V54+V55+V56 | W57: =W52+W53+W54+W55+W56 | ... AY57: =AY52+AY53+AY54+AY55+AY56
B58: 701000 Rent | D58: 6916.2 | E58: 6916.2 | F58: 6916.2 | G58: 6916.2 | H58: 6916.2 | I58: 6916.2 | J58: 6916.2 | K58: 6916.2 | L58: 6916.2 | M58: 6916.2 | N58: 6916.2 | O58: 6916.2 | P58: 6916.2 | Q58: 6916.2 | R58: 6916.2 | S58: 6916.2 | T58: 6916.2 | U58: 6916.2 | V58: 6916.2 | W58: 7077.57 | X58: 7077.57 | Y58: 7077.57 | Z58: 7077.57 | AA58: 7077.57 | AB58: 7077.57 | AC58: 7077.57 | AD58: 7077.57 | AE58: 7077.57 | AF58: 7077.57 | AG58: 7077.57 | AH58: 7077.57 | AI58: 7077.57 | AJ58: 7077.57 | AK58: 7077.57 | AL58: 7077.57 | AM58: 7077.57 | AN58: 7077.57 | AO58: 7077.57 | AP58: 7077.57 | AQ58: 7077.57 | AR58: 7077.57 | AS58: 7077.57 | AT58: 7077.57 | AU58: 7077.57 | AV58: 7077.57 | AW58: 7077.57 | AX58: 7077.57 | AY58: 7077.57
B59: 702000 Security | D59: 0 | E59: 0 | F59: 31.99 | G59: 31.99 | H59: 31.99 | I59: 31.99 | J59: 31.99 | K59: 31.99 | L59: 31.99 | M59: 31.99 | N59: 31.99 | O59: 34.99 | P59: 34.99 | Q59: 34.99 | R59: 34.99 | S59: 34.99 | T59: 34.99 | U59: 34.99 | V59: 34.99 | W59: 35.81 | X59: 35.81 | Y59: 35.81 | Z59: 35.81 | AA59: 35.81 | AB59: 35.81 | AC59: 35.81 | AD59: 35.81 | AE59: 35.81 | AF59: 35.81 | AG59: 35.81 | AH59: 35.81 | AI59: 35.81 | AJ59: 35.81 | AK59: 35.81 | AL59: 35.81 | AM59: 35.81 | AN59: 35.81 | AO59: 35.81 | AP59: 35.81 | AQ59: 35.81 | AR59: 35.81 | AS59: 35.81 | AT59: 35.81 | AU59: 35.81 | AV59: 35.81 | AW59: 35.81 | AX59: 35.81 | AY59: 35.81
B60: 703000 Cleaning | D60: 98.68 | E60: 0 | F60: 0 | G60: 0 | H60: 155.45 | I60: 122.39 | J60: 418.3 | K60: 93.4 | L60: 83.79 | M60: 199.79 | N60: 913.28 | O60: 223.88 | P60: 732.99 | Q60: 198.34 | R60: 743.55 | S60: 346.55 | T60: 246.89 | U60: 403.09 | V60: 420.5 | W60: 517.15 | X60: 517.15 | Y60: 517.15 | Z60: 517.15 | AA60: 517.15 | AB60: 517.15 | AC60: 517.15 | AD60: 517.15 | AE60: 517.15 | AF60: 517.15 | AG60: 517.15 | AH60: 517.15 | AI60: 517.15 | AJ60: 517.15 | AK60: 517.15 | AL60: 517.15 | AM60: 517.15 | AN60: 517.15 | AO60: 517.15 | AP60: 517.15 | AQ60: 517.15 | AR60: 517.15 | AS60: 517.15 | AT60: 517.15 | AU60: 517.15 | AV60: 517.15 | AW60: 517.15 | AX60: 517.15 | AY60: 517.15
B61: 705000 Property Maintenance (incl Repairs & Parking) | D61: 7856.16 | E61: 1203.41 | F61: 1203.41 | G61: 1203.41 | H61: 1353.41 | I61: 1303.41 | J61: 1203.41 | K61: 1763.48 | L61: 1203.41 | M61: 1203.41 | N61: 1203.41 | O61: 1203.41 | P61: 800 | Q61: 800 | R61: 800 | S61: 800 | T61: 800 | U61: 800 | V61: 580.59 | W61: 818.67 | X61: 818.67 | Y61: 818.67 | Z61: 818.67 | AA61: 818.67 | AB61: 818.67 | AC61: 818.67 | AD61: 818.67 | AE61: 818.67 | AF61: 818.67 | AG61: 818.67 | AH61: 818.67 | AI61: 818.67 | AJ61: 818.67 | AK61: 818.67 | AL61: 818.67 | AM61: 818.67 | AN61: 818.67 | AO61: 818.67 | AP61: 818.67 | AQ61: 818.67 | AR61: 818.67 | AS61: 818.67 | AT61: 818.67 | AU61: 818.67 | AV61: 818.67 | AW61: 818.67 | AX61: 818.67 | AY61: 818.67
B62: Total Property Costs | D62: =SUM(D58:D61) | E62: =SUM(E58:E61) | F62: =SUM(F58:F61) | G62: =SUM(G58:G61) | H62: =SUM(H58:H61) | I62: =SUM(I58:I61) | J62: =SUM(J58:J61) | K62: =SUM(K58:K61) | ... O62: =SUM(O58:O61) | P62: =P58+P59+P60+P61 | Q62: =Q58+Q59+Q60+Q61 | R62: =R58+R59+R60+R61 | S62: =S58+S59+S60+S61 | T62: =T58+T59+T60+T61 | U62: =U58+U59+U60+U61 | V62: =V58+V59+V60+V61 | W62: =W58+W59+W60+W61 | ... AY62: =AY58+AY59+AY60+AY61
B63: TOTAL OPERATING EXPENSES | D63: =D34+D39+D43+D48+D51+D57+D62 | E63: =E34+E39+E43+E48+E51+E57+E62 | F63: =F34+F39+F43+F48+F51+F57+F62 | G63: =G34+G39+G43+G48+G51+G57+G62 | H63: =H34+H39+H43+H48+H51+H57+H62 | I63: =I34+I39+I43+I48+I51+I57+I62 | J63: =J34+J39+J43+J48+J51+J57+J62 | K63: =K34+K39+K43+K48+K51+K57+K62 | ... AY63: =AY34+AY39+AY43+AY48+AY51+AY57+AY62
B64: NET OPERATING INCOME (EBITDA) | D64: =D27-D63 | E64: =E27-E63 | F64: =F27-F63 | G64: =G27-G63 | H64: =H27-H63 | I64: =I27-I63 | J64: =J27-J63 | K64: =K27-K63 | ... AY64: =AY27-AY63
B65: OTHER
B66: 810000 Depreciation | D66: 1842.1 | E66: 1850.23 | F66: 1850.23 | G66: 1853.38 | H66: 1855.96 | I66: 1855.96 | J66: 1855.96 | K66: 1855.96 | L66: 1882.97 | M66: 1882.97 | N66: 1882.97 | O66: 1483.6 | P66: 1833.55 | Q66: 1833.55 | R66: 1833.55 | S66: 1833.55 | T66: 1833.55 | U66: 1833.55 | V66: 1833.55 | W66: 1833.55 | X66: 1833.55 | Y66: 1833.55 | Z66: 1833.55 | AA66: 1833.55 | AB66: 1833.55 | AC66: 1833.55 | AD66: 1833.55 | AE66: 1833.55 | AF66: 1833.55 | AG66: 1833.55 | AH66: 1833.55 | AI66: 1833.55 | AJ66: 1833.55 | AK66: 1833.55 | AL66: 1833.55 | AM66: 1833.55 | AN66: 1833.55 | AO66: 1833.55 | AP66: 1833.55 | AQ66: 1833.55 | AR66: 1833.55 | AS66: 1833.55 | AT66: 1833.55 | AU66: 1833.55 | AV66: 1833.55 | AW66: 1833.55 | AX66: 1833.55 | AY66: 1833.55
B67: 901000 Interest Expense (incl Other Exp/Inc) | D67: 0 | E67: 0 | F67: 0 | G67: 0 | H67: 0 | I67: 0 | J67: 0 | K67: 0 | L67: 0 | M67: 0 | N67: 0 | O67: 0 | P67: 0 | Q67: 0 | R67: 0 | S67: 0 | T67: 0 | U67: 0 | V67: 0 | W67: 0 | X67: 0 | Y67: 0 | Z67: 0 | AA67: 0 | AB67: 0 | AC67: 0 | AD67: 0 | AE67: 0 | AF67: 0 | AG67: 0 | AH67: 0 | AI67: 0 | AJ67: 0 | AK67: 0 | AL67: 0 | AM67: 0 | AN67: 0 | AO67: 0 | AP67: 0 | AQ67: 0 | AR67: 0 | AS67: 0 | AT67: 0 | AU67: 0 | AV67: 0 | AW67: 0 | AX67: 0 | AY67: 0
B68: 902000 Taxes Paid | D68: 0 | E68: 0 | F68: 0 | G68: 0 | H68: 0 | I68: 0 | J68: 0 | K68: 0 | L68: 0 | M68: 0 | N68: 0 | O68: 0 | P68: 0 | Q68: 0 | R68: 0 | S68: 0 | T68: 0 | U68: 0 | V68: 0 | W68: 0 | X68: 0 | Y68: 0 | Z68: 0 | AA68: 0 | AB68: 0 | AC68: 0 | AD68: 0 | AE68: 0 | AF68: 0 | AG68: 0 | AH68: 0 | AI68: 0 | AJ68: 0 | AK68: 0 | AL68: 0 | AM68: 0 | AN68: =AN70*0.070773 | AO68: =AO70*0.070773 | AP68: =AP70*0.070773 | AQ68: =AQ70*0.070773 | AR68: =AR70*0.070773 | AS68: =AS70*0.070773 | AT68: =AT70*0.070773 | AU68: =AU70*0.070773 | ... AY68: =AY70*0.070773
B69: 903000 Property taxes | D69: 0 | E69: 0 | F69: 0 | G69: 366 | H69: 0 | I69: 0 | J69: 0 | K69: 0 | L69: 0 | M69: 0 | N69: 0 | O69: 0 | P69: 0 | Q69: 0 | R69: 0 | S69: 0 | T69: 0 | U69: 0 | V69: 0 | W69: 0 | X69: 0 | Y69: 0 | Z69: 0 | AA69: 0 | AB69: 0 | AC69: 0 | AD69: 0 | AE69: 0 | AF69: 0 | AG69: 0 | AH69: 0 | AI69: 0 | AJ69: 0 | AK69: 0 | AL69: 0 | AM69: 0 | AN69: 0 | AO69: 0 | AP69: 0 | AQ69: 0 | AR69: 0 | AS69: 0 | AT69: 0 | AU69: 0 | AV69: 0 | AW69: 0 | AX69: 0 | AY69: 0
B70: Total Other Expenses | D70: =SUM(D66:D69) | E70: =SUM(E66:E69) | F70: =SUM(F66:F69) | G70: =SUM(G66:G69) | H70: =SUM(H66:H69) | I70: =SUM(I66:I69) | J70: =SUM(J66:J69) | K70: =SUM(K66:K69) | ... O70: =SUM(O66:O69) | P70: =P66+P67+P68+P69 | Q70: =Q66+Q67+Q68+Q69 | R70: =R66+R67+R68+R69 | S70: =S66+S67+S68+S69 | T70: =T66+T67+T68+T69 | U70: =U66+U67+U68+U69 | V70: =V66+V67+V68+V69 | W70: =SUM(W66:W69) | X70: =SUM(X66:X69) | Y70: =SUM(Y66:Y69) | Z70: =SUM(Z66:Z69) | AA70: =SUM(AA66:AA69) | AB70: =SUM(AB66:AB69) | AC70: =SUM(AC66:AC69) | AD70: =SUM(AD66:AD69) | ... AM70: =SUM(AM66:AM69) | AN70: 0 | AO70: 0 | AP70: 0 | AQ70: 0 | AR70: 0 | AS70: 0 | AT70: 0 | AU70: 0 | AV70: 0 | AW70: 0 | AX70: 0 | AY70: 0
B71: NET INCOME | D71: =D64-D70 | E71: =E64-E70 | F71: =F64-F70 | G71: =G64-G70 | H71: =H64-H70 | I71: =I64-I70 | J71: =J64-J70 | K71: =K64-K70 | ... AY71: =AY64-AY70

Sheet CC P&L
B2: Culver City (CC) — Profit & Loss
B4: Monthly P&L (Detail)
B5: Line Item | D5: Jan 2025 | E5: Feb 2025 | F5: Mar 2025 | G5: Apr 2025 | H5: May 2025 | I5: Jun 2025 | J5: Jul 2025 | K5: Aug 2025 | L5: Sep 2025 | M5: Oct 2025 | N5: Nov 2025 | O5: Dec 2025 | P5: Jan 2026 | Q5: Feb 2026 | R5: Mar 2026 | S5: Apr 2026 | T5: May 2026 | U5: Jun 2026 | V5: Jul 2026 | W5: Aug 2026 | X5: Sep 2026 | Y5: Oct 2026 | Z5: Nov 2026 | AA5: Dec 2026 | AB5: Jan 2027 | AC5: Feb 2027 | AD5: Mar 2027 | AE5: Apr 2027 | AF5: May 2027 | AG5: Jun 2027 | AH5: Jul 2027 | AI5: Aug 2027 | AJ5: Sep 2027 | AK5: Oct 2027 | AL5: Nov 2027 | AM5: Dec 2027 | AN5: Jan 2028 | AO5: Feb 2028 | AP5: Mar 2028 | AQ5: Apr 2028 | AR5: May 2028 | AS5: Jun 2028 | AT5: Jul 2028 | AU5: Aug 2028 | AV5: Sep 2028 | AW5: Oct 2028 | AX5: Nov 2028 | AY5: Dec 2028 | BA5: Revenue Segments as % of Total (LTM)
B6: INCOME | D6: 0 | E6: 0 | F6: 0 | G6: 0 | H6: 0 | I6: 0 | J6: 0 | K6: 0 | L6: 0 | M6: 0 | N6: 0 | O6: 0 | BA6: LTM May 2026
B7: 401001 Machine | D7: 0 | E7: 0 | F7: 0 | G7: 0 | H7: 0 | I7: 0 | J7: 0 | K7: 42 | L7: 7077.37 | M7: 16280.87 | N7: 14326 | O7: 16551.11 | P7: 20397.9 | Q7: 19548.71 | R7: 20502.29 | S7: 17774.52 | T7: 16596.07 | U7: 16167.62 | V7: 17174.48 | W7: =W13*0.510234 | X7: =X13*0.510234 | Y7: =Y13*0.510234 | Z7: =Z13*0.510234 | AA7: =AA13*0.510234 | AB7: =AB13*0.510234 | AC7: =AC13*0.510234 | AD7: =AD13*0.510234 | ... AY7: =AY13*0.510234 | BA7: =SUM(I7:T7) | BB7: =BA7/$BA$21
B8: 401002 Private Pilates | D8: 0 | E8: 0 | F8: 0 | G8: 0 | H8: 0 | I8: 0 | J8: 0 | K8: 0 | L8: 415 | M8: 945 | N8: 860 | O8: 940 | P8: 1170 | Q8: 1512 | R8: 1002 | S8: 333 | T8: 628 | U8: 961 | V8: 270 | W8: =W13*0.026202 | X8: =X13*0.026202 | Y8: =Y13*0.026202 | Z8: =Z13*0.026202 | AA8: =AA13*0.026202 | AB8: =AB13*0.026202 | AC8: =AC13*0.026202 | AD8: =AD13*0.026202 | ... AY8: =AY13*0.026202 | BA8: =SUM(I8:T8) | BB8: =BA8/$BA$21
B9: 401003 Class Pass | D9: 0 | E9: 0 | F9: 0 | G9: 0 | H9: 0 | I9: 0 | J9: 0 | K9: 0 | L9: 4370.27 | M9: 10831.25 | N9: 12060.69 | O9: 11638.45 | P9: 16587.97 | Q9: 15654.65 | R9: 18636.28 | S9: 15895 | T9: 15302.32 | U9: 15926.08 | V9: 16616 | W9: =W13*0.435551 | X9: =X13*0.435551 | Y9: =Y13*0.435551 | Z9: =Z13*0.435551 | AA9: =AA13*0.435551 | AB9: =AB13*0.435551 | AC9: =AC13*0.435551 | AD9: =AD13*0.435551 | ... AY9: =AY13*0.435551 | BA9: =SUM(I9:T9) | BB9: =BA9/$BA$21
B10: 401004 Mighty Teacher Training | D10: 0 | E10: 0 | F10: 0 | G10: 0 | H10: 0 | I10: 0 | J10: 0 | K10: 0 | L10: 0 | M10: 0 | N10: 0 | O10: 0 | P10: 0 | Q10: 0 | R10: 0 | S10: 0 | T10: 0 | U10: 0 | V10: 0 | W10: =W13*0.018306 | X10: =X13*0.018306 | Y10: =Y13*0.018306 | Z10: =Z13*0.018306 | AA10: =AA13*0.018306 | AB10: =AB13*0.018306 | AC10: =AC13*0.018306 | AD10: =AD13*0.018306 | ... AY10: =AY13*0.018306 | BA10: =SUM(I10:T10) | BB10: =BA10/$BA$21
B11: 401005 Livestream Classes | D11: 0 | E11: 0 | F11: 0 | G11: 0 | H11: 0 | I11: 0 | J11: 0 | K11: 0 | L11: 0 | M11: 0 | N11: 0 | O11: 0 | P11: 0 | Q11: 0 | R11: 0 | S11: 37.6 | T11: 65.22 | U11: 0 | V11: 0 | W11: =W13*0.000245 | X11: =X13*0.000245 | Y11: =Y13*0.000245 | Z11: =Z13*0.000245 | AA11: =AA13*0.000245 | AB11: =AB13*0.000245 | AC11: =AC13*0.000245 | AD11: =AD13*0.000245 | ... AY11: =AY13*0.000245 | BA11: =SUM(I11:T11) | BB11: =BA11/$BA$21
B12: 401006 Wellhub | D12: 0 | E12: 0 | F12: 0 | G12: 0 | H12: 0 | I12: 0 | J12: 0 | K12: 0 | L12: 0 | M12: 0 | N12: 0 | O12: 122.4 | P12: 336.6 | Q12: 367.2 | R12: 501.84 | S12: 244.8 | T12: 82.62 | U12: 214.2 | V12: 306 | W12: =W13*0.009461 | X12: =X13*0.009461 | Y12: =Y13*0.009461 | Z12: =Z13*0.009461 | AA12: =AA13*0.009461 | AB12: =AB13*0.009461 | AC12: =AC13*0.009461 | AD12: =AD13*0.009461 | ... AY12: =AY13*0.009461 | BA12: =SUM(I12:T12) | BB12: =BA12/$BA$21
B13: Total Sessions | D13: =SUM(D7:D12) | E13: =SUM(E7:E12) | F13: =SUM(F7:F12) | G13: =SUM(G7:G12) | H13: =SUM(H7:H12) | I13: =SUM(I7:I12) | J13: =SUM(J7:J12) | K13: =SUM(K7:K12) | ... O13: =SUM(O7:O12) | P13: =P7+P8+P9+P10+P11+P12 | Q13: =Q7+Q8+Q9+Q10+Q11+Q12 | R13: =R7+R8+R9+R10+R11+R12 | S13: =S7+S8+S9+S10+S11+S12 | T13: =T7+T8+T9+T10+T11+T12 | U13: =U7+U8+U9+U10+U11+U12 | V13: =V7+V8+V9+V10+V11+V12 | W13: ='Sales Forecast'!W7*Assumptions!$C$12+'Sales Forecast'!V7*Assumptions!$D$12+'Sales Forecast'!U7*Assumptions!$E$12+'Sales Forecast'!T7*Assumptions!$F$12+'Sales Forecast'!S7*Assumptions!$G$12+'Sales Forecast'!R7*Assumptions!$H$12+'Sales Forecast'!Q7*Assumptions!$I$12 | X13: ='Sales Forecast'!X7*Assumptions!$C$12+'Sales Forecast'!W7*Assumptions!$D$12+'Sales Forecast'!V7*Assumptions!$E$12+'Sales Forecast'!U7*Assumptions!$F$12+'Sales Forecast'!T7*Assumptions!$G$12+'Sales Forecast'!S7*Assumptions!$H$12+'Sales Forecast'!R7*Assumptions!$I$12 | Y13: ='Sales Forecast'!Y7*Assumptions!$C$12+'Sales Forecast'!X7*Assumptions!$D$12+'Sales Forecast'!W7*Assumptions!$E$12+'Sales Forecast'!V7*Assumptions!$F$12+'Sales Forecast'!U7*Assumptions!$G$12+'Sales Forecast'!T7*Assumptions!$H$12+'Sales Forecast'!S7*Assumptions!$I$12 | Z13: ='Sales Forecast'!Z7*Assumptions!$C$12+'Sales Forecast'!Y7*Assumptions!$D$12+'Sales Forecast'!X7*Assumptions!$E$12+'Sales Forecast'!W7*Assumptions!$F$12+'Sales Forecast'!V7*Assumptions!$G$12+'Sales Forecast'!U7*Assumptions!$H$12+'Sales Forecast'!T7*Assumptions!$I$12 | AA13: ='Sales Forecast'!AA7*Assumptions!$C$12+'Sales Forecast'!Z7*Assumptions!$D$12+'Sales Forecast'!Y7*Assumptions!$E$12+'Sales Forecast'!X7*Assumptions!$F$12+'Sales Forecast'!W7*Assumptions!$G$12+'Sales Forecast'!V7*Assumptions!$H$12+'Sales Forecast'!U7*Assumptions!$I$12 | AB13: ='Sales Forecast'!AB7*Assumptions!$C$12+'Sales Forecast'!AA7*Assumptions!$D$12+'Sales Forecast'!Z7*Assumptions!$E$12+'Sales Forecast'!Y7*Assumptions!$F$12+'Sales Forecast'!X7*Assumptions!$G$12+'Sales Forecast'!W7*Assumptions!$H$12+'Sales Forecast'!V7*Assumptions!$I$12 | AC13: ='Sales Forecast'!AC7*Assumptions!$C$12+'Sales Forecast'!AB7*Assumptions!$D$12+'Sales Forecast'!AA7*Assumptions!$E$12+'Sales Forecast'!Z7*Assumptions!$F$12+'Sales Forecast'!Y7*Assumptions!$G$12+'Sales Forecast'!X7*Assumptions!$H$12+'Sales Forecast'!W7*Assumptions!$I$12 | AD13: ='Sales Forecast'!AD7*Assumptions!$C$12+'Sales Forecast'!AC7*Assumptions!$D$12+'Sales Forecast'!AB7*Assumptions!$E$12+'Sales Forecast'!AA7*Assumptions!$F$12+'Sales Forecast'!Z7*Assumptions!$G$12+'Sales Forecast'!Y7*Assumptions!$H$12+'Sales Forecast'!X7*Assumptions!$I$12 | ... AY13: ='Sales Forecast'!AY7*Assumptions!$C$12+'Sales Forecast'!AX7*Assumptions!$D$12+'Sales Forecast'!AW7*Assumptions!$E$12+'Sales Forecast'!AV7*Assumptions!$F$12+'Sales Forecast'!AU7*Assumptions!$G$12+'Sales Forecast'!AT7*Assumptions!$H$12+'Sales Forecast'!AS7*Assumptions!$I$12
B14: 403001 Machine Breakage | D14: 0 | E14: 0 | F14: 0 | G14: 0 | H14: 0 | I14: 0 | J14: 0 | K14: 0 | L14: 251.2 | M14: 1268.4 | N14: 4314.82 | O14: 5585 | P14: 2890.72 | Q14: 4105.76 | R14: 2843.53 | S14: 4737.65 | T14: 4879.41 | U14: 5029.8 | V14: 5801.87 | W14: =W17*0.979836 | X14: =X17*0.979836 | Y14: =Y17*0.979836 | Z14: =Z17*0.979836 | AA14: =AA17*0.979836 | AB14: =AB17*0.979836 | AC14: =AC17*0.979836 | AD14: =AD17*0.979836 | ... AY14: =AY17*0.979836 | BA14: =SUM(I14:T14) | BB14: =BA14/$BA$21
B15: 403003 Private Pilates Breakage | D15: 0 | E15: 0 | F15: 0 | G15: 0 | H15: 0 | I15: 0 | J15: 0 | K15: 0 | L15: 0 | M15: 595 | N15: 675 | O15: 785 | P15: 0 | Q15: 225 | R15: 0 | S15: 75 | T15: 230 | U15: 340 | V15: 543 | W15: =W17*0.020164 | X15: =X17*0.020164 | Y15: =Y17*0.020164 | Z15: =Z17*0.020164 | AA15: =AA17*0.020164 | AB15: =AB17*0.020164 | AC15: =AC17*0.020164 | AD15: =AD17*0.020164 | ... AY15: =AY17*0.020164 | BA15: =SUM(I15:T15) | BB15: =BA15/$BA$21
B16: 403004 Other Breakage (incl MTT Breakage) | D16: 0 | E16: 0 | F16: 0 | G16: 0 | H16: 0 | I16: 0 | J16: 0 | K16: 0 | L16: 0 | M16: 0 | N16: 0 | O16: 0 | P16: 0 | Q16: 0 | R16: 0 | S16: 0 | T16: 0 | U16: 0 | V16: 0 | W16: 0 | X16: 0 | Y16: 0 | Z16: 0 | AA16: 0 | AB16: 0 | AC16: 0 | AD16: 0 | AE16: 0 | AF16: 0 | AG16: 0 | AH16: 0 | AI16: 0 | AJ16: 0 | AK16: 0 | AL16: 0 | AM16: 0 | AN16: 0 | AO16: 0 | AP16: 0 | AQ16: 0 | AR16: 0 | AS16: 0 | AT16: 0 | AU16: 0 | AV16: 0 | AW16: 0 | AX16: 0 | AY16: 0 | BA16: =SUM(I16:T16) | BB16: =BA16/$BA$21
B17: Total Breakage Revenue | D17: =SUM(D14:D16) | E17: =SUM(E14:E16) | F17: =SUM(F14:F16) | G17: =SUM(G14:G16) | H17: =SUM(H14:H16) | I17: =SUM(I14:I16) | J17: =SUM(J14:J16) | K17: =SUM(K14:K16) | ... O17: =SUM(O14:O16) | P17: =P14+P15+P16 | Q17: =Q14+Q15+Q16 | R17: =R14+R15+R16 | S17: =S14+S15+S16 | T17: =T14+T15+T16 | U17: =U14+U15+U16 | V17: =V14+V15+V16 | W17: ='Sales Forecast'!W7*Assumptions!$C$13+'Sales Forecast'!V7*Assumptions!$D$13+'Sales Forecast'!U7*Assumptions!$E$13+'Sales Forecast'!T7*Assumptions!$F$13+'Sales Forecast'!S7*Assumptions!$G$13+'Sales Forecast'!R7*Assumptions!$H$13+'Sales Forecast'!Q7*Assumptions!$I$13 | X17: ='Sales Forecast'!X7*Assumptions!$C$13+'Sales Forecast'!W7*Assumptions!$D$13+'Sales Forecast'!V7*Assumptions!$E$13+'Sales Forecast'!U7*Assumptions!$F$13+'Sales Forecast'!T7*Assumptions!$G$13+'Sales Forecast'!S7*Assumptions!$H$13+'Sales Forecast'!R7*Assumptions!$I$13 | Y17: ='Sales Forecast'!Y7*Assumptions!$C$13+'Sales Forecast'!X7*Assumptions!$D$13+'Sales Forecast'!W7*Assumptions!$E$13+'Sales Forecast'!V7*Assumptions!$F$13+'Sales Forecast'!U7*Assumptions!$G$13+'Sales Forecast'!T7*Assumptions!$H$13+'Sales Forecast'!S7*Assumptions!$I$13 | Z17: ='Sales Forecast'!Z7*Assumptions!$C$13+'Sales Forecast'!Y7*Assumptions!$D$13+'Sales Forecast'!X7*Assumptions!$E$13+'Sales Forecast'!W7*Assumptions!$F$13+'Sales Forecast'!V7*Assumptions!$G$13+'Sales Forecast'!U7*Assumptions!$H$13+'Sales Forecast'!T7*Assumptions!$I$13 | AA17: ='Sales Forecast'!AA7*Assumptions!$C$13+'Sales Forecast'!Z7*Assumptions!$D$13+'Sales Forecast'!Y7*Assumptions!$E$13+'Sales Forecast'!X7*Assumptions!$F$13+'Sales Forecast'!W7*Assumptions!$G$13+'Sales Forecast'!V7*Assumptions!$H$13+'Sales Forecast'!U7*Assumptions!$I$13 | AB17: ='Sales Forecast'!AB7*Assumptions!$C$13+'Sales Forecast'!AA7*Assumptions!$D$13+'Sales Forecast'!Z7*Assumptions!$E$13+'Sales Forecast'!Y7*Assumptions!$F$13+'Sales Forecast'!X7*Assumptions!$G$13+'Sales Forecast'!W7*Assumptions!$H$13+'Sales Forecast'!V7*Assumptions!$I$13 | AC17: ='Sales Forecast'!AC7*Assumptions!$C$13+'Sales Forecast'!AB7*Assumptions!$D$13+'Sales Forecast'!AA7*Assumptions!$E$13+'Sales Forecast'!Z7*Assumptions!$F$13+'Sales Forecast'!Y7*Assumptions!$G$13+'Sales Forecast'!X7*Assumptions!$H$13+'Sales Forecast'!W7*Assumptions!$I$13 | AD17: ='Sales Forecast'!AD7*Assumptions!$C$13+'Sales Forecast'!AC7*Assumptions!$D$13+'Sales Forecast'!AB7*Assumptions!$E$13+'Sales Forecast'!AA7*Assumptions!$F$13+'Sales Forecast'!Z7*Assumptions!$G$13+'Sales Forecast'!Y7*Assumptions!$H$13+'Sales Forecast'!X7*Assumptions!$I$13 | ... AY17: ='Sales Forecast'!AY7*Assumptions!$C$13+'Sales Forecast'!AX7*Assumptions!$D$13+'Sales Forecast'!AW7*Assumptions!$E$13+'Sales Forecast'!AV7*Assumptions!$F$13+'Sales Forecast'!AU7*Assumptions!$G$13+'Sales Forecast'!AT7*Assumptions!$H$13+'Sales Forecast'!AS7*Assumptions!$I$13
B18: 404000 Retail Sales | D18: 0 | E18: 0 | F18: 0 | G18: 0 | H18: 0 | I18: 0 | J18: 0 | K18: 0 | L18: 1068 | M18: 1968 | N18: 1402 | O18: 1200 | P18: 1794 | Q18: 1344 | R18: 1586 | S18: 946 | T18: 928 | U18: 656 | V18: 836 | W18: =1417.5 | X18: =1417.5 | Y18: =1417.5 | Z18: =1417.5 | AA18: =1417.5 | AB18: =1417.5 | AC18: =1417.5 | AD18: =1417.5 | ... AY18: =1417.5 | BA18: =SUM(I18:T18) | BB18: =BA18/$BA$21
B19: 406000 Refunds | D19: 0 | E19: 0 | F19: 0 | G19: 0 | H19: 0 | I19: 0 | J19: 0 | K19: 0 | L19: 0 | M19: 0 | N19: -1110 | O19: -414 | P19: -1048 | Q19: -740 | R19: -500 | S19: -245 | T19: -443 | U19: -1053.33 | V19: -324.2 | W19: =('Sales Forecast'!W7*Assumptions!$C$12+'Sales Forecast'!V7*Assumptions!$D$12+'Sales Forecast'!U7*Assumptions!$E$12+'Sales Forecast'!T7*Assumptions!$F$12+'Sales Forecast'!S7*Assumptions!$G$12+'Sales Forecast'!R7*Assumptions!$H$12+'Sales Forecast'!Q7*Assumptions!$I$12+'Sales Forecast'!W7*Assumptions!$C$13+'Sales Forecast'!V7*Assumptions!$D$13+'Sales Forecast'!U7*Assumptions!$E$13+'Sales Forecast'!T7*Assumptions!$F$13+'Sales Forecast'!S7*Assumptions!$G$13+'Sales Forecast'!R7*Assumptions!$H$13+'Sales Forecast'!Q7*Assumptions!$I$13+1417.5)*Assumptions!$C$17 | X19: =('Sales Forecast'!X7*Assumptions!$C$12+'Sales Forecast'!W7*Assumptions!$D$12+'Sales Forecast'!V7*Assumptions!$E$12+'Sales Forecast'!U7*Assumptions!$F$12+'Sales Forecast'!T7*Assumptions!$G$12+'Sales Forecast'!S7*Assumptions!$H$12+'Sales Forecast'!R7*Assumptions!$I$12+'Sales Forecast'!X7*Assumptions!$C$13+'Sales Forecast'!W7*Assumptions!$D$13+'Sales Forecast'!V7*Assumptions!$E$13+'Sales Forecast'!U7*Assumptions!$F$13+'Sales Forecast'!T7*Assumptions!$G$13+'Sales Forecast'!S7*Assumptions!$H$13+'Sales Forecast'!R7*Assumptions!$I$13+1417.5)*Assumptions!$C$17 | Y19: =('Sales Forecast'!Y7*Assumptions!$C$12+'Sales Forecast'!X7*Assumptions!$D$12+'Sales Forecast'!W7*Assumptions!$E$12+'Sales Forecast'!V7*Assumptions!$F$12+'Sales Forecast'!U7*Assumptions!$G$12+'Sales Forecast'!T7*Assumptions!$H$12+'Sales Forecast'!S7*Assumptions!$I$12+'Sales Forecast'!Y7*Assumptions!$C$13+'Sales Forecast'!X7*Assumptions!$D$13+'Sales Forecast'!W7*Assumptions!$E$13+'Sales Forecast'!V7*Assumptions!$F$13+'Sales Forecast'!U7*Assumptions!$G$13+'Sales Forecast'!T7*Assumptions!$H$13+'Sales Forecast'!S7*Assumptions!$I$13+1417.5)*Assumptions!$C$17 | Z19: =('Sales Forecast'!Z7*Assumptions!$C$12+'Sales Forecast'!Y7*Assumptions!$D$12+'Sales Forecast'!X7*Assumptions!$E$12+'Sales Forecast'!W7*Assumptions!$F$12+'Sales Forecast'!V7*Assumptions!$G$12+'Sales Forecast'!U7*Assumptions!$H$12+'Sales Forecast'!T7*Assumptions!$I$12+'Sales Forecast'!Z7*Assumptions!$C$13+'Sales Forecast'!Y7*Assumptions!$D$13+'Sales Forecast'!X7*Assumptions!$E$13+'Sales Forecast'!W7*Assumptions!$F$13+'Sales Forecast'!V7*Assumptions!$G$13+'Sales Forecast'!U7*Assumptions!$H$13+'Sales Forecast'!T7*Assumptions!$I$13+1417.5)*Assumptions!$C$17 | AA19: =('Sales Forecast'!AA7*Assumptions!$C$12+'Sales Forecast'!Z7*Assumptions!$D$12+'Sales Forecast'!Y7*Assumptions!$E$12+'Sales Forecast'!X7*Assumptions!$F$12+'Sales Forecast'!W7*Assumptions!$G$12+'Sales Forecast'!V7*Assumptions!$H$12+'Sales Forecast'!U7*Assumptions!$I$12+'Sales Forecast'!AA7*Assumptions!$C$13+'Sales Forecast'!Z7*Assumptions!$D$13+'Sales Forecast'!Y7*Assumptions!$E$13+'Sales Forecast'!X7*Assumptions!$F$13+'Sales Forecast'!W7*Assumptions!$G$13+'Sales Forecast'!V7*Assumptions!$H$13+'Sales Forecast'!U7*Assumptions!$I$13+1417.5)*Assumptions!$C$17 | AB19: =('Sales Forecast'!AB7*Assumptions!$C$12+'Sales Forecast'!AA7*Assumptions!$D$12+'Sales Forecast'!Z7*Assumptions!$E$12+'Sales Forecast'!Y7*Assumptions!$F$12+'Sales Forecast'!X7*Assumptions!$G$12+'Sales Forecast'!W7*Assumptions!$H$12+'Sales Forecast'!V7*Assumptions!$I$12+'Sales Forecast'!AB7*Assumptions!$C$13+'Sales Forecast'!AA7*Assumptions!$D$13+'Sales Forecast'!Z7*Assumptions!$E$13+'Sales Forecast'!Y7*Assumptions!$F$13+'Sales Forecast'!X7*Assumptions!$G$13+'Sales Forecast'!W7*Assumptions!$H$13+'Sales Forecast'!V7*Assumptions!$I$13+1417.5)*Assumptions!$C$17 | AC19: =('Sales Forecast'!AC7*Assumptions!$C$12+'Sales Forecast'!AB7*Assumptions!$D$12+'Sales Forecast'!AA7*Assumptions!$E$12+'Sales Forecast'!Z7*Assumptions!$F$12+'Sales Forecast'!Y7*Assumptions!$G$12+'Sales Forecast'!X7*Assumptions!$H$12+'Sales Forecast'!W7*Assumptions!$I$12+'Sales Forecast'!AC7*Assumptions!$C$13+'Sales Forecast'!AB7*Assumptions!$D$13+'Sales Forecast'!AA7*Assumptions!$E$13+'Sales Forecast'!Z7*Assumptions!$F$13+'Sales Forecast'!Y7*Assumptions!$G$13+'Sales Forecast'!X7*Assumptions!$H$13+'Sales Forecast'!W7*Assumptions!$I$13+1417.5)*Assumptions!$C$17 | AD19: =('Sales Forecast'!AD7*Assumptions!$C$12+'Sales Forecast'!AC7*Assumptions!$D$12+'Sales Forecast'!AB7*Assumptions!$E$12+'Sales Forecast'!AA7*Assumptions!$F$12+'Sales Forecast'!Z7*Assumptions!$G$12+'Sales Forecast'!Y7*Assumptions!$H$12+'Sales Forecast'!X7*Assumptions!$I$12+'Sales Forecast'!AD7*Assumptions!$C$13+'Sales Forecast'!AC7*Assumptions!$D$13+'Sales Forecast'!AB7*Assumptions!$E$13+'Sales Forecast'!AA7*Assumptions!$F$13+'Sales Forecast'!Z7*Assumptions!$G$13+'Sales Forecast'!Y7*Assumptions!$H$13+'Sales Forecast'!X7*Assumptions!$I$13+1417.5)*Assumptions!$C$17 | ... AY19: =('Sales Forecast'!AY7*Assumptions!$C$12+'Sales Forecast'!AX7*Assumptions!$D$12+'Sales Forecast'!AW7*Assumptions!$E$12+'Sales Forecast'!AV7*Assumptions!$F$12+'Sales Forecast'!AU7*Assumptions!$G$12+'Sales Forecast'!AT7*Assumptions!$H$12+'Sales Forecast'!AS7*Assumptions!$I$12+'Sales Forecast'!AY7*Assumptions!$C$13+'Sales Forecast'!AX7*Assumptions!$D$13+'Sales Forecast'!AW7*Assumptions!$E$13+'Sales Forecast'!AV7*Assumptions!$F$13+'Sales Forecast'!AU7*Assumptions!$G$13+'Sales Forecast'!AT7*Assumptions!$H$13+'Sales Forecast'!AS7*Assumptions!$I$13+1417.5)*Assumptions!$C$17 | BA19: =SUM(I19:T19) | BB19: =BA19/$BA$21
