Workbook

Sheet Company Prepared Model>>>

Sheet Sources and Uses
B2: NOTE: Model assumes transaction closes on Sept 1, 2026
B4: Entry Valuation
B6: EBITDA Multiple | C6: 5.5
B7: LTM May 2026 Studio Level EBITDA | C7: =SUM(Summary!BF23:BF34)
B8: Pre Money TEV | C8: =C7*C6
B10: Sources and Uses
B11: Uses
B12: Pre Money TEV | C12: =C8
B13: Existing Debt Paydown (at August 2026) | C13: ='Cash, Debt & Equity'!W26
B14: Cash on balance sheet for working capital, studio buildouts, etc. | C14: =C17-SUM(C12,C16,C15,C13)
B15: Legal Fees | C15: 50000
B16: Financing Fees (2% of raise) | C16: =D16*C20 | D16: 0.02 | E16: <<< Fee
B17: Total Uses | C17: =C22
B19: Sources
B20: New Debt (leasehold, certain amount covers losses) | C20: 1500000 | D20: 0.1 | E20: <<< Cash Interest, paid monthly
B21: Management Rollover | C21: =C12
B22: Total Uses | C22: =SUM(C20:C21)
B24: Debt Service Coverage Metrics
C25: LTM May 2026 | D25: 2026 | E25: =D25+1 | F25: =E25+1
B26: ='Cash Flow Forecast'!B55 | C26: ='Cash Flow Forecast'!BF55 | D26: ='Cash Flow Forecast'!BB55 | E26: ='Cash Flow Forecast'!BC55 | F26: ='Cash Flow Forecast'!BD55
B27: ='Cash Flow Forecast'!B56 | C27: ='Cash Flow Forecast'!BF56 | D27: ='Cash Flow Forecast'!BB56 | E27: ='Cash Flow Forecast'!BC56 | F27: ='Cash Flow Forecast'!BD56
B28: ='Cash Flow Forecast'!B57 | C28: ='Cash Flow Forecast'!BF57 | D28: ='Cash Flow Forecast'!BB57 | E28: ='Cash Flow Forecast'!BC57 | F28: ='Cash Flow Forecast'!BD57
B29: ='Cash Flow Forecast'!B58 | C29: ='Cash Flow Forecast'!BF58 | D29: =IFERROR('Cash Flow Forecast'!BB58,"NA") | E29: ='Cash Flow Forecast'!BC58 | F29: ='Cash Flow Forecast'!BD58

Sheet Cover
B2: Mighty Pilates
B3: Financial Model
B5: Last refreshed: June 23, 2026
B7: Tab Guide
B9: Summary & Controls | C9: Top-level KPIs, studio sales & EBITDA tables, charts
B10: Assumptions | C10: All model inputs: OpEx, sales forecast, rev rec curves, loan terms
B11: Cash Flow Forecast | C11: Monthly cash flow from operations + investing + financing
B12: P&L Summary | C12: Consolidated monthly P&L (Revenue → EBITDA)
B13: P&L Detail | C13: Account-level P&L matching accountant chart of accounts
B14: All Studios Summary | C14: Side-by-side studio comparison
B15: [Studio] FCST (×12) | C15: Per-studio P&L forecast (BK, CC, DN, LF, MR, OP, PH, RH, SB, SM, WP, WW)
B16: Cash, Debt & Equity | C16: Balance sheet, loan amortization schedules, equity tracking
B17: Sales Forecast | C17: Studio × month editable sales grid
B18: CapEx | C18: Capital expenditure project schedule
B19: QBO Actuals | C19: Historical accountant-booked P&L, BS, SCF (read-only)
B22: Conventions
B24: Yellow cells = inputs (edit these)
B25: Light green cells = actuals (closed months, do not edit)

Sheet Read Me
B2: Read Me — Model Architecture
B3: Last refreshed: June 23, 2026
B5: Tab Roles
B6: Summary & Controls | C6: Top-level dashboard. Sales + EBITDA by studio. Total EBITDA references P&L NOI directly.
B7: Assumptions | C7: Editable global parameters: rev rec curves, refund/discount/COGS rates, escalations, loan terms.
B8: Sales Forecast | C8: Per-studio × month sales grid. EDITABLE for forecast months (yellow). Drives revenue formulas. Hidden rows 101-113 hold 2025 history for lag formulas — do not delete.
B9: Cash, Debt & Equity | C9: Loan amortization schedule + debt service forecast.
B10: Cash Flow Forecast | C10: Monthly CF with operating/investing/financing.
B11: P&L (Consolidated) | C11: Consolidated monthly P&L. Revenue/COGS use direct lag formulas (with 2025 history). OpEx rows = SUM(per-studio) + HO + HO Other.
B12: All Studios Summary | C12: Side-by-side studio comparison.
B13: [Code] P&L (×12) | C13: Per-studio P&L: BK, CC, DN, LF, MR, OP, PH, RH, SB, SM, WP, WW. OpEx leaves are HARDCODED values (editable) summing to per-studio override. Revenue formulas use per-studio lag (2026+ from Sales Forecast, 2025 from hidden helper rows 102-113).
B14: HO P&L | C14: Head Office overhead (no revenue). Same leaf-summing structure. NOI is negative (= -Total OpEx).
B15: CapEx | C15: Project schedule (empty — add projects to populate Investing rows on CF).
B16: QBO Actuals | C16: Raw accountant-booked P&L/BS/SCF data. Read-only reference.
B18: Cell Conventions
B19: Yellow fill (FFFF99) | C19: EDITABLE input cell. Cat can change these.
B20: Light green fill | C20: Hardcoded actual from QBO/accountant. Do not edit (would diverge from source data).
B21: White/no fill | C21: Formula cell. Computed from other cells.
B22: Light blue fill | C22: Subtotal or total row.
B23: Bold green fill | C23: Key KPI (EBITDA, ending cash).
B25: Value Flow
B26: Sales edit | C26: Edit Sales Forecast cell → flows to: Studio P&L Sessions/Breakage (via lag formula) → Studio NOI → Summary & Controls studio row → Sales Forecast TOTAL row → Consolidated P&L revenue → Consolidated NOI → Summary & Controls Total EBITDA.
B27: OpEx leaf edit | C27: Edit per-studio OpEx leaf (e.g., BK Paid Ads) → Studio Marketing subtotal (=SUM leaves) → Studio Total OpEx → Studio NOI → Summary & Controls studio row → Consolidated P&L Marketing (=SUM studios + HO) → Consolidated Total OpEx → Consolidated NOI → Summary & Controls Total EBITDA. Full propagation works.
B28: Assumption edit | C28: Edit rate on Assumptions tab (refund %, discount %, escalation, etc.) → flows through all formulas referencing that cell.
B30: Hidden Helpers — DO NOT DELETE
B31: Sales Forecast rows 100-113 | C31: Hidden helper rows holding 2025 monthly sales (consolidated row 101 and per-studio rows 102-113). Required for 7-month lag formulas on Session/Breakage Revenue forecasts for May 2026 and Jun 2026.
B32: Sales Forecast row ~50+ | C32: Helper for chart data references on Summary & Controls. Removing breaks charts.
B34: Monthly Update Procedure (when QBO closes new month)
B35: Step 1 | C35: Upload new QBO export to Streamlit dashboard. Streamlit's committed_actuals.json gets updated.
B36: Step 2 | C36: Run refresh_from_streamlit.py (in /Users/chandlerclemons/financial-modeling/models/mighty/).
B37: Step 3 | C37: Refresh script will: (a) extend actuals columns by 1 month, (b) shift forecast forward, (c) refresh trailing-3-month avg lines (Taxes Paid, Property Taxes, Retail, Depreciation), (d) update 2025 helper row values if Streamlit data changed historicals.
B38: Step 4 | C38: Open the Excel and spot-check the new actuals column vs Streamlit. Save & share with stakeholders.
B40: Streamlit Source Repo
B41: GitHub | C41: github.com/c-clemons/mighty-pilates (private)
B42: Live app | C42: mighty-pilates-financial-model.streamlit.app
B43: Local files | C43: /Users/chandlerclemons/mighty-pilates/dashboard/data/
B45: Cash Sales vs Accrual Revenue
B46: Sales Forecast / Summary | C46: These tabs show CASH SALES: Total Sales captured at the MindBody point-of-sale when a member buys a class pack, membership, or workshop.
B47: Studio P&L / All Studios | C47: These tabs show ACCRUAL P&L REVENUE: Sessions recognized over the package usage window + Breakage when unused packages expire − Refunds − Discounts.
B48: Worked example | C48: Berkeley Dec 2028: Cash Sales $164K, Accrual Revenue $140K. The $24K gap = packages sold in Dec 2028 that will be USED (or breakage'd) in later months.
B49: Reconciliation horizon | C49: These metrics diverge in any individual month by design. They reconcile only over the full lifecycle of a cohort of packages (typically 6-12 months from purchase).
B50: Both are correct | C50: Cash Sales is the operating KPI (what closed at the counter). Accrual Revenue is the GAAP P&L line (what's earned). Neither is wrong.

Sheet Summary
B2: Summary & Controls
B3: Top-level dashboard. Studio sales, EBITDA, YoY summary, charts.
B4: Monthly Total Session Sales by Studio
B5: Metric | C5: Studio | D5: Jan 2025 (A) | E5: Feb 2025 (A) | F5: Mar 2025 (A) | G5: Apr 2025 (A) | H5: May 2025 (A) | I5: Jun 2025 (A) | J5: Jul 2025 (A) | K5: Aug 2025 (A) | L5: Sep 2025 (A) | M5: Oct 2025 (A) | N5: Nov 2025 (A) | O5: Dec 2025 (A) | P5: Jan 2026 (A) | Q5: Feb 2026 (A) | R5: Mar 2026 (A) | S5: Apr 2026 (A) | T5: May 2026 (A) | U5: Jun 2026 | V5: Jul 2026 | W5: Aug 2026 | X5: Sep 2026 | Y5: Oct 2026 | Z5: Nov 2026 | AA5: Dec 2026 | AB5: Jan 2027 | AC5: Feb 2027 | AD5: Mar 2027 | AE5: Apr 2027 | AF5: May 2027 | AG5: Jun 2027 | AH5: Jul 2027 | AI5: Aug 2027 | AJ5: Sep 2027 | AK5: Oct 2027 | AL5: Nov 2027 | AM5: Dec 2027 | AN5: Jan 2028 | AO5: Feb 2028 | AP5: Mar 2028 | AQ5: Apr 2028 | AR5: May 2028 | AS5: Jun 2028 | AT5: Jul 2028 | AU5: Aug 2028 | AV5: Sep 2028 | AW5: Oct 2028 | AX5: Nov 2028 | AY5: Dec 2028 | BA5: 2025 | BB5: =BA5+1 | BC5: =BB5+1 | BD5: =BC5+1 | BF5: LTM May 2026
B6: Total Sales | D6: =SUM(D7:D19) | E6: =SUM(E7:E19) | F6: =SUM(F7:F19) | G6: =SUM(G7:G19) | H6: =SUM(H7:H19) | I6: =SUM(I7:I19) | J6: =SUM(J7:J19) | K6: =SUM(K7:K19) | ... AY6: =SUM(AY7:AY19) | BA6: =SUM(D6:O6) | BB6: =SUM(P6:AA6) | BC6: =SUM(AB6:AM6) | BD6: =SUM(AN6:AY6) | BF6: =SUM(I6:T6) | BH6: =SUM(BA6:BD6)-SUM(D6:AY6)
C7: Berkeley | D7: ='Sales Forecast'!D6 | E7: ='Sales Forecast'!E6 | F7: ='Sales Forecast'!F6 | G7: ='Sales Forecast'!G6 | H7: ='Sales Forecast'!H6 | I7: ='Sales Forecast'!I6 | J7: ='Sales Forecast'!J6 | K7: ='Sales Forecast'!K6 | ... AY7: ='Sales Forecast'!AY6 | BA7: =SUM(D7:O7) | BB7: =SUM(P7:AA7) | BC7: =SUM(AB7:AM7) | BD7: =SUM(AN7:AY7) | BF7: =SUM(I7:T7) | BH7: =SUM(BA7:BD7)-SUM(D7:AY7)
C8: Culver City | D8: ='Sales Forecast'!D7 | E8: ='Sales Forecast'!E7 | F8: ='Sales Forecast'!F7 | G8: ='Sales Forecast'!G7 | H8: ='Sales Forecast'!H7 | I8: ='Sales Forecast'!I7 | J8: ='Sales Forecast'!J7 | K8: ='Sales Forecast'!K7 | ... AY8: ='Sales Forecast'!AY7 | BA8: =SUM(D8:O8) | BB8: =SUM(P8:AA8) | BC8: =SUM(AB8:AM8) | BD8: =SUM(AN8:AY8) | BF8: =SUM(I8:T8) | BH8: =SUM(BA8:BD8)-SUM(D8:AY8)
C9: Danville | D9: ='Sales Forecast'!D8 | E9: ='Sales Forecast'!E8 | F9: ='Sales Forecast'!F8 | G9: ='Sales Forecast'!G8 | H9: ='Sales Forecast'!H8 | I9: ='Sales Forecast'!I8 | J9: ='Sales Forecast'!J8 | K9: ='Sales Forecast'!K8 | ... AY9: ='Sales Forecast'!AY8 | BA9: =SUM(D9:O9) | BB9: =SUM(P9:AA9) | BC9: =SUM(AB9:AM9) | BD9: =SUM(AN9:AY9) | BF9: =SUM(I9:T9) | BH9: =SUM(BA9:BD9)-SUM(D9:AY9)
C10: Lafayette | D10: ='Sales Forecast'!D9 | E10: ='Sales Forecast'!E9 | F10: ='Sales Forecast'!F9 | G10: ='Sales Forecast'!G9 | H10: ='Sales Forecast'!H9 | I10: ='Sales Forecast'!I9 | J10: ='Sales Forecast'!J9 | K10: ='Sales Forecast'!K9 | ... AY10: ='Sales Forecast'!AY9 | BA10: =SUM(D10:O10) | BB10: =SUM(P10:AA10) | BC10: =SUM(AB10:AM10) | BD10: =SUM(AN10:AY10) | BF10: =SUM(I10:T10) | BH10: =SUM(BA10:BD10)-SUM(D10:AY10)
C11: Marin | D11: ='Sales Forecast'!D10 | E11: ='Sales Forecast'!E10 | F11: ='Sales Forecast'!F10 | G11: ='Sales Forecast'!G10 | H11: ='Sales Forecast'!H10 | I11: ='Sales Forecast'!I10 | J11: ='Sales Forecast'!J10 | K11: ='Sales Forecast'!K10 | ... AY11: ='Sales Forecast'!AY10 | BA11: =SUM(D11:O11) | BB11: =SUM(P11:AA11) | BC11: =SUM(AB11:AM11) | BD11: =SUM(AN11:AY11) | BF11: =SUM(I11:T11) | BH11: =SUM(BA11:BD11)-SUM(D11:AY11)
C12: Ocean Park | D12: ='Sales Forecast'!D11 | E12: ='Sales Forecast'!E11 | F12: ='Sales Forecast'!F11 | G12: ='Sales Forecast'!G11 | H12: ='Sales Forecast'!H11 | I12: ='Sales Forecast'!I11 | J12: ='Sales Forecast'!J11 | K12: ='Sales Forecast'!K11 | ... AY12: ='Sales Forecast'!AY11 | BA12: =SUM(D12:O12) | BB12: =SUM(P12:AA12) | BC12: =SUM(AB12:AM12) | BD12: =SUM(AN12:AY12) | BF12: =SUM(I12:T12) | BH12: =SUM(BA12:BD12)-SUM(D12:AY12)
C13: Presidio Heights | D13: ='Sales Forecast'!D12 | E13: ='Sales Forecast'!E12 | F13: ='Sales Forecast'!F12 | G13: ='Sales Forecast'!G12 | H13: ='Sales Forecast'!H12 | I13: ='Sales Forecast'!I12 | J13: ='Sales Forecast'!J12 | K13: ='Sales Forecast'!K12 | ... AY13: ='Sales Forecast'!AY12 | BA13: =SUM(D13:O13) | BB13: =SUM(P13:AA13) | BC13: =SUM(AB13:AM13) | BD13: =SUM(AN13:AY13) | BF13: =SUM(I13:T13) | BH13: =SUM(BA13:BD13)-SUM(D13:AY13)
C14: Russian Hill | D14: ='Sales Forecast'!D13 | E14: ='Sales Forecast'!E13 | F14: ='Sales Forecast'!F13 | G14: ='Sales Forecast'!G13 | H14: ='Sales Forecast'!H13 | I14: ='Sales Forecast'!I13 | J14: ='Sales Forecast'!J13 | K14: ='Sales Forecast'!K13 | ... AY14: ='Sales Forecast'!AY13 | BA14: =SUM(D14:O14) | BB14: =SUM(P14:AA14) | BC14: =SUM(AB14:AM14) | BD14: =SUM(AN14:AY14) | BF14: =SUM(I14:T14) | BH14: =SUM(BA14:BD14)-SUM(D14:AY14)
C15: Santa Barbara | D15: ='Sales Forecast'!D14 | E15: ='Sales Forecast'!E14 | F15: ='Sales Forecast'!F14 | G15: ='Sales Forecast'!G14 | H15: ='Sales Forecast'!H14 | I15: ='Sales Forecast'!I14 | J15: ='Sales Forecast'!J14 | K15: ='Sales Forecast'!K14 | ... AY15: ='Sales Forecast'!AY14 | BA15: =SUM(D15:O15) | BB15: =SUM(P15:AA15) | BC15: =SUM(AB15:AM15) | BD15: =SUM(AN15:AY15) | BF15: =SUM(I15:T15) | BH15: =SUM(BA15:BD15)-SUM(D15:AY15)
C16: Santa Monica | D16: ='Sales Forecast'!D15 | E16: ='Sales Forecast'!E15 | F16: ='Sales Forecast'!F15 | G16: ='Sales Forecast'!G15 | H16: ='Sales Forecast'!H15 | I16: ='Sales Forecast'!I15 | J16: ='Sales Forecast'!J15 | K16: ='Sales Forecast'!K15 | ... AY16: ='Sales Forecast'!AY15 | BA16: =SUM(D16:O16) | BB16: =SUM(P16:AA16) | BC16: =SUM(AB16:AM16) | BD16: =SUM(AN16:AY16) | BF16: =SUM(I16:T16) | BH16: =SUM(BA16:BD16)-SUM(D16:AY16)
C17: West Portal | D17: ='Sales Forecast'!D16 | E17: ='Sales Forecast'!E16 | F17: ='Sales Forecast'!F16 | G17: ='Sales Forecast'!G16 | H17: ='Sales Forecast'!H16 | I17: ='Sales Forecast'!I16 | J17: ='Sales Forecast'!J16 | K17: ='Sales Forecast'!K16 | ... AY17: ='Sales Forecast'!AY16 | BA17: =SUM(D17:O17) | BB17: =SUM(P17:AA17) | BC17: =SUM(AB17:AM17) | BD17: =SUM(AN17:AY17) | BF17: =SUM(I17:T17) | BH17: =SUM(BA17:BD17)-SUM(D17:AY17)
C18: Westwood | D18: ='Sales Forecast'!D17 | E18: ='Sales Forecast'!E17 | F18: ='Sales Forecast'!F17 | G18: ='Sales Forecast'!G17 | H18: ='Sales Forecast'!H17 | I18: ='Sales Forecast'!I17 | J18: ='Sales Forecast'!J17 | K18: ='Sales Forecast'!K17 | ... AY18: ='Sales Forecast'!AY17 | BA18: =SUM(D18:O18) | BB18: =SUM(P18:AA18) | BC18: =SUM(AB18:AM18) | BD18: =SUM(AN18:AY18) | BF18: =SUM(I18:T18) | BH18: =SUM(BA18:BD18)-SUM(D18:AY18)
C19: Head Office | D19: 0 | E19: 0 | F19: 0 | G19: 0 | H19: 0 | I19: 0 | J19: 0 | K19: 0 | L19: 0 | M19: 0 | N19: 0 | O19: 0 | P19: 0 | Q19: 0 | R19: 0 | S19: 0 | T19: 0 | U19: 0 | V19: 0 | W19: 0 | X19: 0 | Y19: 0 | Z19: 0 | AA19: 0 | AB19: 0 | AC19: 0 | AD19: 0 | AE19: 0 | AF19: 0 | AG19: 0 | AH19: 0 | AI19: 0 | AJ19: 0 | AK19: 0 | AL19: 0 | AM19: 0 | AN19: 0 | AO19: 0 | AP19: 0 | AQ19: 0 | AR19: 0 | AS19: 0 | AT19: 0 | AU19: 0 | AV19: 0 | AW19: 0 | AX19: 0 | AY19: 0 | BA19: =SUM(D19:O19) | BB19: =SUM(P19:AA19) | BC19: =SUM(AB19:AM19) | BD19: =SUM(AN19:AY19) | BF19: =SUM(I19:T19) | BH19: =SUM(BA19:BD19)-SUM(D19:AY19)
B21: Monthly EBITDA by Studio
B22: Total EBITDA | D22: =SUM(D23:D35) | E22: =SUM(E23:E35) | F22: =SUM(F23:F35) | G22: =SUM(G23:G35) | H22: =SUM(H23:H35) | I22: =SUM(I23:I35) | J22: =SUM(J23:J35) | K22: =SUM(K23:K35) | ... AY22: =SUM(AY23:AY35) | BA22: =SUM(D22:O22) | BB22: =SUM(P22:AA22) | BC22: =SUM(AB22:AM22) | BD22: =SUM(AN22:AY22) | BF22: =SUM(I22:T22) | BH22: =SUM(BA22:BD22)-SUM(D22:AY22)
C23: Berkeley | D23: ='BK P&L'!D63 | E23: ='BK P&L'!E63 | F23: ='BK P&L'!F63 | G23: ='BK P&L'!G63 | H23: ='BK P&L'!H63 | I23: ='BK P&L'!I63 | J23: ='BK P&L'!J63 | K23: ='BK P&L'!K63 | ... AY23: ='BK P&L'!AY63 | BA23: =SUM(D23:O23) | BB23: =SUM(P23:AA23) | BC23: =SUM(AB23:AM23) | BD23: =SUM(AN23:AY23) | BF23: =SUM(I23:T23) | BH23: =SUM(BA23:BD23)-SUM(D23:AY23)
C24: Culver City | D24: ='CC P&L'!D63 | E24: ='CC P&L'!E63 | F24: ='CC P&L'!F63 | G24: ='CC P&L'!G63 | H24: ='CC P&L'!H63 | I24: ='CC P&L'!I63 | J24: ='CC P&L'!J63 | K24: ='CC P&L'!K63 | ... AY24: ='CC P&L'!AY63 | BA24: =SUM(D24:O24) | BB24: =SUM(P24:AA24) | BC24: =SUM(AB24:AM24) | BD24: =SUM(AN24:AY24) | BF24: =SUM(I24:T24) | BH24: =SUM(BA24:BD24)-SUM(D24:AY24)
C25: Danville | D25: ='DN P&L'!D63 | E25: ='DN P&L'!E63 | F25: ='DN P&L'!F63 | G25: ='DN P&L'!G63 | H25: ='DN P&L'!H63 | I25: ='DN P&L'!I63 | J25: ='DN P&L'!J63 | K25: ='DN P&L'!K63 | ... AY25: ='DN P&L'!AY63 | BA25: =SUM(D25:O25) | BB25: =SUM(P25:AA25) | BC25: =SUM(AB25:AM25) | BD25: =SUM(AN25:AY25) | BF25: =SUM(I25:T25) | BH25: =SUM(BA25:BD25)-SUM(D25:AY25)
C26: Lafayette | D26: ='LF P&L'!D63 | E26: ='LF P&L'!E63 | F26: ='LF P&L'!F63 | G26: ='LF P&L'!G63 | H26: ='LF P&L'!H63 | I26: ='LF P&L'!I63 | J26: ='LF P&L'!J63 | K26: ='LF P&L'!K63 | ... AY26: ='LF P&L'!AY63 | BA26: =SUM(D26:O26) | BB26: =SUM(P26:AA26) | BC26: =SUM(AB26:AM26) | BD26: =SUM(AN26:AY26) | BF26: =SUM(I26:T26) | BH26: =SUM(BA26:BD26)-SUM(D26:AY26)
C27: Marin | D27: ='MR P&L'!D63 | E27: ='MR P&L'!E63 | F27: ='MR P&L'!F63 | G27: ='MR P&L'!G63 | H27: ='MR P&L'!H63 | I27: ='MR P&L'!I63 | J27: ='MR P&L'!J63 | K27: ='MR P&L'!K63 | ... AY27: ='MR P&L'!AY63 | BA27: =SUM(D27:O27) | BB27: =SUM(P27:AA27) | BC27: =SUM(AB27:AM27) | BD27: =SUM(AN27:AY27) | BF27: =SUM(I27:T27) | BH27: =SUM(BA27:BD27)-SUM(D27:AY27)
C28: Ocean Park | D28: ='OP P&L'!D63 | E28: ='OP P&L'!E63 | F28: ='OP P&L'!F63 | G28: ='OP P&L'!G63 | H28: ='OP P&L'!H63 | I28: ='OP P&L'!I63 | J28: ='OP P&L'!J63 | K28: ='OP P&L'!K63 | ... AY28: ='OP P&L'!AY63 | BA28: =SUM(D28:O28) | BB28: =SUM(P28:AA28) | BC28: =SUM(AB28:AM28) | BD28: =SUM(AN28:AY28) | BF28: =SUM(I28:T28) | BH28: =SUM(BA28:BD28)-SUM(D28:AY28)
C29: Presidio Heights | D29: ='PH P&L'!D63 | E29: ='PH P&L'!E63 | F29: ='PH P&L'!F63 | G29: ='PH P&L'!G63 | H29: ='PH P&L'!H63 | I29: ='PH P&L'!I63 | J29: ='PH P&L'!J63 | K29: ='PH P&L'!K63 | ... AY29: ='PH P&L'!AY63 | BA29: =SUM(D29:O29) | BB29: =SUM(P29:AA29) | BC29: =SUM(AB29:AM29) | BD29: =SUM(AN29:AY29) | BF29: =SUM(I29:T29) | BH29: =SUM(BA29:BD29)-SUM(D29:AY29)
C30: Russian Hill | D30: ='RH P&L'!D63 | E30: ='RH P&L'!E63 | F30: ='RH P&L'!F63 | G30: ='RH P&L'!G63 | H30: ='RH P&L'!H63 | I30: ='RH P&L'!I63 | J30: ='RH P&L'!J63 | K30: ='RH P&L'!K63 | ... AY30: ='RH P&L'!AY63 | BA30: =SUM(D30:O30) | BB30: =SUM(P30:AA30) | BC30: =SUM(AB30:AM30) | BD30: =SUM(AN30:AY30) | BF30: =SUM(I30:T30) | BH30: =SUM(BA30:BD30)-SUM(D30:AY30)
C31: Santa Barbara | D31: ='SB P&L'!D63 | E31: ='SB P&L'!E63 | F31: ='SB P&L'!F63 | G31: ='SB P&L'!G63 | H31: ='SB P&L'!H63 | I31: ='SB P&L'!I63 | J31: ='SB P&L'!J63 | K31: ='SB P&L'!K63 | ... AY31: ='SB P&L'!AY63 | BA31: =SUM(D31:O31) | BB31: =SUM(P31:AA31) | BC31: =SUM(AB31:AM31) | BD31: =SUM(AN31:AY31) | BF31: =SUM(I31:T31) | BH31: =SUM(BA31:BD31)-SUM(D31:AY31)
C32: Santa Monica | D32: ='SM P&L'!D63 | E32: ='SM P&L'!E63 | F32: ='SM P&L'!F63 | G32: ='SM P&L'!G63 | H32: ='SM P&L'!H63 | I32: ='SM P&L'!I63 | J32: ='SM P&L'!J63 | K32: ='SM P&L'!K63 | ... AY32: ='SM P&L'!AY63 | BA32: =SUM(D32:O32) | BB32: =SUM(P32:AA32) | BC32: =SUM(AB32:AM32) | BD32: =SUM(AN32:AY32) | BF32: =SUM(I32:T32) | BH32: =SUM(BA32:BD32)-SUM(D32:AY32)
C33: West Portal | D33: ='WP P&L'!D63 | E33: ='WP P&L'!E63 | F33: ='WP P&L'!F63 | G33: ='WP P&L'!G63 | H33: ='WP P&L'!H63 | I33: ='WP P&L'!I63 | J33: ='WP P&L'!J63 | K33: ='WP P&L'!K63 | ... AY33: ='WP P&L'!AY63 | BA33: =SUM(D33:O33) | BB33: =SUM(P33:AA33) | BC33: =SUM(AB33:AM33) | BD33: =SUM(AN33:AY33) | BF33: =SUM(I33:T33) | BH33: =SUM(BA33:BD33)-SUM(D33:AY33)
C34: Westwood | D34: ='WW P&L'!D63 | E34: ='WW P&L'!E63 | F34: ='WW P&L'!F63 | G34: ='WW P&L'!G63 | H34: ='WW P&L'!H63 | I34: ='WW P&L'!I63 | J34: ='WW P&L'!J63 | K34: ='WW P&L'!K63 | ... AY34: ='WW P&L'!AY63 | BA34: =SUM(D34:O34) | BB34: =SUM(P34:AA34) | BC34: =SUM(AB34:AM34) | BD34: =SUM(AN34:AY34) | BF34: =SUM(I34:T34) | BH34: =SUM(BA34:BD34)-SUM(D34:AY34)
C35: Head Office | D35: ='HO P&L'!D36 | E35: ='HO P&L'!E36 | F35: ='HO P&L'!F36 | G35: ='HO P&L'!G36 | H35: ='HO P&L'!H36 | I35: ='HO P&L'!I36 | J35: ='HO P&L'!J36 | K35: ='HO P&L'!K36 | ... AY35: ='HO P&L'!AY36 | BA35: =SUM(D35:O35) | BB35: =SUM(P35:AA35) | BC35: =SUM(AB35:AM35) | BD35: =SUM(AN35:AY35) | BF35: =SUM(I35:T35) | BH35: =SUM(BA35:BD35)-SUM(D35:AY35)
B37: Studio Level EBITDA | D37: =SUM(D23:D34) | E37: =SUM(E23:E34) | F37: =SUM(F23:F34) | G37: =SUM(G23:G34) | H37: =SUM(H23:H34) | I37: =SUM(I23:I34) | J37: =SUM(J23:J34) | K37: =SUM(K23:K34) | ... AY37: =SUM(AY23:AY34) | BA37: =SUM(D37:O37) | BB37: =SUM(P37:AA37) | BC37: =SUM(AB37:AM37) | BD37: =SUM(AN37:AY37) | BF37: =SUM(I37:T37)
B38: Total Add Backs | D38: 28398.84 | E38: 52184.59 | F38: 34406.02 | G38: 20335.04 | H38: 25137.94 | I38: 86480.66 | J38: 13252.8 | K38: 38505.24 | L38: 73265.17 | M38: 67217.42 | N38: 91181.16 | O38: 46220.52 | P38: ='P&L'!P38 | Q38: ='P&L'!Q38 | R38: ='P&L'!R38 | S38: ='P&L'!S38 | T38: 16815.41 | U38: 25000 | V38: 25000 | W38: 25000 | X38: 70000 | Y38: 50000 | Z38: 20000 | AA38: 15000 | AB38: 15000 | AC38: 15000 | AD38: 15000 | AE38: 15000 | AF38: 15000 | AG38: 15000 | AH38: 15000 | AI38: 15000 | AJ38: 15000 | AK38: 15000 | AL38: 15000 | AM38: 15000 | AN38: 15000 | AO38: 15000 | AP38: 15000 | AQ38: 15000 | AR38: 15000 | AS38: 15000 | AT38: 15000 | AU38: 15000 | AV38: 15000 | AW38: 15000 | AX38: 15000 | AY38: 15000 | BA38: =SUM(D38:O38) | BB38: =SUM(P38:AA38) | BC38: =SUM(AB38:AM38) | BD38: =SUM(AN38:AY38) | BF38: =SUM(I38:T38) | BH38: =SUM(BA38:BD38)-SUM(D38:AY38)
B39: Total Adj-EBITDA | D39: =D22+D38 | E39: =E22+E38 | F39: =F22+F38 | G39: =G22+G38 | H39: =H22+H38 | I39: =I22+I38 | J39: =J22+J38 | K39: =K22+K38 | ... P39: =P22+P38 | Q39: ='P&L'!Q39 | R39: ='P&L'!R39 | S39: ='P&L'!S39 | T39: ='P&L'!T39 | U39: =U22+U38 | V39: =V22+V38 | W39: =W22+W38 | X39: =X22+X38 | Y39: =Y22+Y38 | Z39: =Z22+Z38 | AA39: =AA22+AA38 | AB39: =AB22+AB38 | ... AY39: =AY22+AY38 | BA39: =SUM(D39:O39) | BB39: =SUM(P39:AA39) | BC39: =SUM(AB39:AM39) | BD39: =SUM(AN39:AY39) | BF39: =SUM(I39:T39) | BH39: =SUM(BA39:BD39)-SUM(D39:AY39)
B41: Annual Summary
B42: Metric | C42: Studio | D42: 2025 | E42: 2026 | F42: 2027 | G42: 2028 | H42: 2026 YoY | I42: 2027 YoY | J42: 2028 YoY
B43: Total Sales | D43: =SUM(D44:D56) | E43: =SUM(E44:E56) | F43: =SUM(F44:F56) | G43: =SUM(G44:G56) | H43: =IFERROR((E43-D43)/D43,0) | I43: =IFERROR((F43-E43)/E43,0) | J43: =IFERROR((G43-F43)/F43,0)
C44: Berkeley | D44: =SUM('Sales Forecast'!D6:O6) | E44: =SUM('Sales Forecast'!P6:AA6) | F44: =SUM('Sales Forecast'!AB6:AM6) | G44: =SUM('Sales Forecast'!AN6:AY6) | H44: =IFERROR((E42-D42)/D42,0) | I44: =IFERROR((F42-E42)/E42,0) | J44: =IFERROR((G42-F42)/F42,0)
C45: Culver City | D45: =SUM('Sales Forecast'!D7:O7) | E45: =SUM('Sales Forecast'!P7:AA7) | F45: =SUM('Sales Forecast'!AB7:AM7) | G45: =SUM('Sales Forecast'!AN7:AY7) | H45: =IFERROR((E43-D43)/D43,0) | I45: =IFERROR((F43-E43)/E43,0) | J45: =IFERROR((G43-F43)/F43,0)
C46: Danville | D46: =SUM('Sales Forecast'!D8:O8) | E46: =SUM('Sales Forecast'!P8:AA8) | F46: =SUM('Sales Forecast'!AB8:AM8) | G46: =SUM('Sales Forecast'!AN8:AY8) | H46: =IFERROR((E44-D44)/D44,0) | I46: =IFERROR((F44-E44)/E44,0) | J46: =IFERROR((G44-F44)/F44,0)
C47: Lafayette | D47: =SUM('Sales Forecast'!D9:O9) | E47: =SUM('Sales Forecast'!P9:AA9) | F47: =SUM('Sales Forecast'!AB9:AM9) | G47: =SUM('Sales Forecast'!AN9:AY9) | H47: =IFERROR((E45-D45)/D45,0) | I47: =IFERROR((F45-E45)/E45,0) | J47: =IFERROR((G45-F45)/F45,0)
C48: Marin | D48: =SUM('Sales Forecast'!D10:O10) | E48: =SUM('Sales Forecast'!P10:AA10) | F48: =SUM('Sales Forecast'!AB10:AM10) | G48: =SUM('Sales Forecast'!AN10:AY10) | H48: =IFERROR((E46-D46)/D46,0) | I48: =IFERROR((F46-E46)/E46,0) | J48: =IFERROR((G46-F46)/F46,0)
C49: Ocean Park | D49: =SUM('Sales Forecast'!D11:O11) | E49: =SUM('Sales Forecast'!P11:AA11) | F49: =SUM('Sales Forecast'!AB11:AM11) | G49: =SUM('Sales Forecast'!AN11:AY11) | H49: =IFERROR((E47-D47)/D47,0) | I49: =IFERROR((F47-E47)/E47,0) | J49: =IFERROR((G47-F47)/F47,0)
C50: Presidio Heights | D50: =SUM('Sales Forecast'!D12:O12) | E50: =SUM('Sales Forecast'!P12:AA12) | F50: =SUM('Sales Forecast'!AB12:AM12) | G50: =SUM('Sales Forecast'!AN12:AY12) | H50: =IFERROR((E48-D48)/D48,0) | I50: =IFERROR((F48-E48)/E48,0) | J50: =IFERROR((G48-F48)/F48,0)
C51: Russian Hill | D51: =SUM('Sales Forecast'!D13:O13) | E51: =SUM('Sales Forecast'!P13:AA13) | F51: =SUM('Sales Forecast'!AB13:AM13) | G51: =SUM('Sales Forecast'!AN13:AY13) | H51: =IFERROR((E49-D49)/D49,0) | I51: =IFERROR((F49-E49)/E49,0) | J51: =IFERROR((G49-F49)/F49,0)
C52: Santa Barbara | D52: =SUM('Sales Forecast'!D14:O14) | E52: =SUM('Sales Forecast'!P14:AA14) | F52: =SUM('Sales Forecast'!AB14:AM14) | G52: =SUM('Sales Forecast'!AN14:AY14) | H52: =IFERROR((E50-D50)/D50,0) | I52: =IFERROR((F50-E50)/E50,0) | J52: =IFERROR((G50-F50)/F50,0)
C53: Santa Monica | D53: =SUM('Sales Forecast'!D15:O15) | E53: =SUM('Sales Forecast'!P15:AA15) | F53: =SUM('Sales Forecast'!AB15:AM15) | G53: =SUM('Sales Forecast'!AN15:AY15) | H53: =IFERROR((E51-D51)/D51,0) | I53: =IFERROR((F51-E51)/E51,0) | J53: =IFERROR((G51-F51)/F51,0)
C54: West Portal | D54: =SUM('Sales Forecast'!D16:O16) | E54: =SUM('Sales Forecast'!P16:AA16) | F54: =SUM('Sales Forecast'!AB16:AM16) | G54: =SUM('Sales Forecast'!AN16:AY16) | H54: =IFERROR((E52-D52)/D52,0) | I54: =IFERROR((F52-E52)/E52,0) | J54: =IFERROR((G52-F52)/F52,0)
C55: Westwood | D55: =SUM('Sales Forecast'!D17:O17) | E55: =SUM('Sales Forecast'!P17:AA17) | F55: =SUM('Sales Forecast'!AB17:AM17) | G55: =SUM('Sales Forecast'!AN17:AY17) | H55: =IFERROR((E53-D53)/D53,0) | I55: =IFERROR((F53-E53)/E53,0) | J55: =IFERROR((G53-F53)/F53,0)
C56: Head Office | D56: 0 | E56: 0 | F56: 0 | G56: 0 | H56: =IFERROR((E56-D56)/D56,0) | I56: =IFERROR((F56-E56)/E56,0) | J56: =IFERROR((G56-F56)/F56,0)
B58: Total EBITDA | D58: =SUM(D59:D71) | E58: =SUM(E59:E71) | F58: =SUM(F59:F71) | G58: =SUM(G59:G71) | H58: =IFERROR((E58-D58)/D58,0) | I58: =IFERROR((F58-E58)/E58,0) | J58: =IFERROR((G58-F58)/F58,0)
C59: Berkeley | D59: =SUM(D23:O23) | E59: =SUM(P23:AA23) | F59: =SUM(AB23:AM23) | G59: =SUM(AN23:AY23) | H59: =IFERROR((E59-D59)/D59,0) | I59: =IFERROR((F59-E59)/E59,0) | J59: =IFERROR((G59-F59)/F59,0)
C60: Culver City | D60: =SUM(D24:O24) | E60: =SUM(P24:AA24) | F60: =SUM(AB24:AM24) | G60: =SUM(AN24:AY24) | H60: =IFERROR((E60-D60)/D60,0) | I60: =IFERROR((F60-E60)/E60,0) | J60: =IFERROR((G60-F60)/F60,0)
C61: Danville | D61: =SUM(D25:O25) | E61: =SUM(P25:AA25) | F61: =SUM(AB25:AM25) | G61: =SUM(AN25:AY25) | H61: =IFERROR((E61-D61)/D61,0) | I61: =IFERROR((F61-E61)/E61,0) | J61: =IFERROR((G61-F61)/F61,0)
C62: Lafayette | D62: =SUM(D26:O26) | E62: =SUM(P26:AA26) | F62: =SUM(AB26:AM26) | G62: =SUM(AN26:AY26) | H62: =IFERROR((E62-D62)/D62,0) | I62: =IFERROR((F62-E62)/E62,0) | J62: =IFERROR((G62-F62)/F62,0)
C63: Marin | D63: =SUM(D27:O27) | E63: =SUM(P27:AA27) | F63: =SUM(AB27:AM27) | G63: =SUM(AN27:AY27) | H63: =IFERROR((E63-D63)/D63,0) | I63: =IFERROR((F63-E63)/E63,0) | J63: =IFERROR((G63-F63)/F63,0)
C64: Ocean Park | D64: =SUM(D28:O28) | E64: =SUM(P28:AA28) | F64: =SUM(AB28:AM28) | G64: =SUM(AN28:AY28) | H64: =IFERROR((E64-D64)/D64,0) | I64: =IFERROR((F64-E64)/E64,0) | J64: =IFERROR((G64-F64)/F64,0)
C65: Presidio Heights | D65: =SUM(D29:O29) | E65: =SUM(P29:AA29) | F65: =SUM(AB29:AM29) | G65: =SUM(AN29:AY29) | H65: =IFERROR((E65-D65)/D65,0) | I65: =IFERROR((F65-E65)/E65,0) | J65: =IFERROR((G65-F65)/F65,0)
C66: Russian Hill | D66: =SUM(D30:O30) | E66: =SUM(P30:AA30) | F66: =SUM(AB30:AM30) | G66: =SUM(AN30:AY30) | H66: =IFERROR((E66-D66)/D66,0) | I66: =IFERROR((F66-E66)/E66,0) | J66: =IFERROR((G66-F66)/F66,0)
C67: Santa Barbara | D67: =SUM(D31:O31) | E67: =SUM(P31:AA31) | F67: =SUM(AB31:AM31) | G67: =SUM(AN31:AY31) | H67: =IFERROR((E67-D67)/D67,0) | I67: =IFERROR((F67-E67)/E67,0) | J67: =IFERROR((G67-F67)/F67,0)
C68: Santa Monica | D68: =SUM(D32:O32) | E68: =SUM(P32:AA32) | F68: =SUM(AB32:AM32) | G68: =SUM(AN32:AY32) | H68: =IFERROR((E68-D68)/D68,0) | I68: =IFERROR((F68-E68)/E68,0) | J68: =IFERROR((G68-F68)/F68,0)
C69: West Portal | D69: =SUM(D33:O33) | E69: =SUM(P33:AA33) | F69: =SUM(AB33:AM33) | G69: =SUM(AN33:AY33) | H69: =IFERROR((E69-D69)/D69,0) | I69: =IFERROR((F69-E69)/E69,0) | J69: =IFERROR((G69-F69)/F69,0)
C70: Westwood | D70: =SUM(D34:O34) | E70: =SUM(P34:AA34) | F70: =SUM(AB34:AM34) | G70: =SUM(AN34:AY34) | H70: =IFERROR((E70-D70)/D70,0) | I70: =IFERROR((F70-E70)/E70,0) | J70: =IFERROR((G70-F70)/F70,0)
C71: Head Office | D71: =SUM('HO P&L'!D36:O36) | E71: =SUM('HO P&L'!P36:AA36) | F71: =SUM('HO P&L'!AB36:AM36) | G71: =SUM('HO P&L'!AN36:AY36) | H71: =IFERROR((E71-D71)/D71,0) | I71: =IFERROR((F71-E71)/E71,0) | J71: =IFERROR((G71-F71)/F71,0)
B73: Total Adj-EBITDA | D73: =SUM(D39:O39) | E73: =SUM(P39:AA39) | F73: =SUM(AB39:AM39) | G73: =SUM(AN39:AY39) | H73: =IFERROR((E73-D73)/D73,0) | I73: =IFERROR((F73-E73)/E73,0) | J73: =IFERROR((G73-F73)/F73,0)
B76: Pro Forma Cash Flow Model
B78: EBITDA | AB78: =AB39 | AC78: =AC39 | AD78: =AD39 | AE78: =AE39 | AF78: =AF39 | AG78: =AG39 | AH78: =AH39 | AI78: =AI39 | ... AY78: =AY39
B79: D&A (-) | AB79: 0
B80: Interest (-)
B81: EBIT

Sheet Assumptions
B2: Assumptions
B3: Yellow cells are editable inputs. All other tabs reference these values.
B5: 1. Model Control
B6: Last Actuals Month | C6: May 2026
B7: Forecast Horizon (months) | C7: 32
B8: Forecast End Month | C8: Dec 2028
B10: 2. Revenue Recognition Curves
B11: Lag Month (0 = sale month) | C11: 0 | D11: 1 | E11: 2 | F11: 3 | G11: 4 | H11: 5 | I11: 6 | J11: Sum
B12: Earned % | C12: 0.3868 | D12: 0.2997 | E12: 0.0855 | F12: 0.0482 | G12: 0.0261 | H12: 0.0193 | I12: 0.0144 | J12: =SUM(C12:I12)
B13: Breakage % | C13: 0.0017 | D13: 0.0602 | E13: 0.0053 | F13: 0.0003 | G13: 0.0001 | H13: 0.0008 | I13: 0.0516 | J13: =SUM(C13:I13)
B14: Total (Earned + Breakage) | C14: =C12+C13 | D14: =D12+D13 | E14: =E12+E13 | F14: =F12+F13 | G14: =G12+G13 | H14: =H12+H13 | I14: =I12+I13 | J14: =SUM(C14:I14)
B16: 3. Rates (% of Gross Revenue)
B17: Refund Rate | C17: -0.0158 | D17: Refunds as % of gross revenue. Negative reduces net revenue.
B18: Discount Rate | C18: -0.0531 | D18: Discounts as % of gross revenue. Negative reduces net revenue.
B19: Merchant Fee % | C19: 0.0286 | D19: Payment processor fees as % of revenue.
B20: COGS % | C20: 0.0096 | D20: Cost of goods sold as % of revenue (retail).
B22: 4. Annual Escalation Rates
B23: Rent / Property Escalation | C23: 0.03 | D23: 3% annual rent step-up applied to forecast months
B24: Other OpEx Escalation | C24: 0.04 | D24: 4% annual escalation for all non-rent OpEx categories
B25: Sales YoY Growth | C25: 0.05 | D25: 5% YoY assumed for 2028 (applied to 2027 seasonal pattern)
B27: 5. Loan Terms (as of Apr 2026)
B28: Loan | C28: Original Amt | D28: Current Balance | E28: Rate (Annual) | F28: Avg Monthly Pmt | G28: Start Date | H28: Type
B29: MindBody Loan - SM | C29: 193706.66 | D29: 99348.21 | E29: 0 | F29: 18871.69 | G29: 2025-09 | H29: Amortizing
B30: MindBody Loan - PH | C30: 130000 | D30: 46989.79 | E30: 0 | F30: 16602.04 | G30: 2025-09 | H30: Amortizing
B31: MindBody Loan - LF | C31: 69249.28 | D31: 20599.85 | E31: 0 | F31: 12162.36 | G31: 2025-10 | H31: Amortizing
B32: MindBody Loan - MR | C32: 67443.81 | D32: 14815.18 | E32: 0 | F32: 13157.16 | G32: 2025-10 | H32: Amortizing
B33: Samson Loan | C33: 265414.78 | D33: 189034.12 | E33: 0 | F33: 25460.22 | G33: 2025-11 | H33: Amortizing
B34: Specialty Capital Loan | C34: 217184.21 | D34: 165407.89 | E34: 0 | F34: 25888.16 | G34: 2025-12 | H34: Amortizing
B35: Norbrook Inc Loan | C35: 162318 | D35: 162318 | E35: 0.08 | F35: 0 | G35: 2025-10 | H35: Interest-Only
B36: TOTAL DEBT | D36: =SUM(D29:D35) | F36: =SUM(F29:F35)
B38: 6. Active Studios
B39: Code | C39: Name
B40: BK | C40: Berkeley
B41: CC | C41: Culver City
B42: DN | C42: Danville
B43: LF | C43: Lafayette
B44: MR | C44: Marin
B45: OP | C45: Ocean Park
B46: PH | C46: Presidio Heights
B47: RH | C47: Russian Hill
B48: SB | C48: Santa Barbara
B49: SM | C49: Santa Monica
B50: WP | C50: West Portal
B51: WW | C51: Westwood

Sheet Sales Forecast
B2: Sales Forecast (Gross)
B3: Jan-May 2026 actuals (locked, Cat-authoritative). Jun 2026 onwards forecast (editable).
B4: Per-Studio Monthly Sales
B5: Code | C5: Studio | D5: Jan 2025 | E5: Feb 2025 | F5: Mar 2025 | G5: Apr 2025 | H5: May 2025 | I5: Jun 2025 | J5: Jul 2025 | K5: Aug 2025 | L5: Sep 2025 | M5: Oct 2025 | N5: Nov 2025 | O5: Dec 2025 | P5: Jan 2026 | Q5: Feb 2026 | R5: Mar 2026 | S5: Apr 2026 | T5: 46143 | U5: Jun 2026 | V5: Jul 2026 | W5: Aug 2026 | X5: Sep 2026 | Y5: Oct 2026 | Z5: Nov 2026 | AA5: Dec 2026 | AB5: Jan 2027 | AC5: Feb 2027 | AD5: Mar 2027 | AE5: Apr 2027 | AF5: May 2027 | AG5: Jun 2027 | AH5: Jul 2027 | AI5: Aug 2027 | AJ5: Sep 2027 | AK5: Oct 2027 | AL5: Nov 2027 | AM5: Dec 2027 | AN5: Jan 2028 | AO5: Feb 2028 | AP5: Mar 2028 | AQ5: Apr 2028 | AR5: May 2028 | AS5: Jun 2028 | AT5: Jul 2028 | AU5: Aug 2028 | AV5: Sep 2028 | AW5: Oct 2028 | AX5: Nov 2028 | AY5: Dec 2028
B6: BK | C6: Berkeley | D6: 122672 | E6: 124750 | F6: 112908 | G6: 140814 | H6: 111061 | I6: 107458 | J6: 101618 | K6: 142373 | L6: 101097 | M6: 115965 | N6: 101860 | O6: 99707 | P6: 124393 | Q6: 129377 | R6: 103159 | S6: 136117 | T6: 83273 | U6: 110000 | V6: 105000 | W6: 120000 | X6: 120000 | Y6: 130000 | Z6: 130000 | AA6: 149000 | AB6: 130612.65 | AC6: 135845.85 | AD6: 108316.95 | AE6: 142922.85 | AF6: 87649.8 | AG6: 115500 | AH6: 110250 | AI6: 126000 | AJ6: 126000 | AK6: 136500 | AL6: 136500 | AM6: 156450 | AN6: 137143.28 | AO6: 142638.14 | AP6: 113732.8 | AQ6: 150068.99 | AR6: 92032.29 | AS6: 121275 | AT6: 115762.5 | AU6: 132300 | AV6: 132300 | AW6: 143325 | AX6: 143325 | AY6: 164272.5
B7: CC | C7: Culver City | D7: 0 | E7: 0 | F7: 0 | G7: 0 | H7: 0 | I7: 0 | J7: 0 | K7: 0 | L7: 16118 | M7: 31030 | N7: 31622 | O7: 31310 | P7: 43840 | Q7: 38704 | R7: 42619 | S7: 39690 | T7: 43327 | U7: 52000 | V7: 59000 | W7: 50000 | X7: 53000 | Y7: 60000 | Z7: 64000 | AA7: 60000 | AB7: 61000 | AC7: 73307 | AD7: 69238 | AE7: 75096 | AF7: 70949 | AG7: 64231 | AH7: 95489 | AI7: 107456 | AJ7: 102425 | AK7: 95000 | AL7: 95000 | AM7: 95000 | AN7: 64050 | AO7: 76972.35 | AP7: 72699.9 | AQ7: 78850.8 | AR7: 74496.45 | AS7: 67442.55 | AT7: 100263.45 | AU7: 112828.8 | AV7: 107546.25 | AW7: 99750 | AX7: 99750 | AY7: 99750
B8: DN | C8: Danville | D8: 0 | E8: 0 | F8: 0 | G8: 0 | H8: 0 | I8: 8385 | J8: 14789 | K8: 16531 | L8: 16660 | M8: 14843 | N8: 15819 | O8: 17950 | P8: 24286 | Q8: 23358 | R8: 20289 | S8: 20363 | T8: 15337 | U8: 20000 | V8: 20000 | W8: 25000 | X8: 25000 | Y8: 30000 | Z8: 25000 | AA8: 32000 | AB8: 32000 | AC8: 40000 | AD8: 40000 | AE8: 45000 | AF8: 45000 | AG8: 50000 | AH8: 50000 | AI8: 50000 | AJ8: 55000 | AK8: 55000 | AL8: 55000 | AM8: 55000 | AN8: 33600 | AO8: 42000 | AP8: 42000 | AQ8: 47250 | AR8: 47250 | AS8: 52500 | AT8: 52500 | AU8: 52500 | AV8: 57750 | AW8: 57750 | AX8: 57750 | AY8: 57750
B9: LF | C9: Lafayette | D9: 90025 | E9: 86822 | F9: 85300 | G9: 127703 | H9: 79380 | I9: 76768 | J9: 70767 | K9: 102739 | L9: 68837 | M9: 83777 | N9: 79979 | O9: 79880 | P9: 92365 | Q9: 126186 | R9: 78385 | S9: 106542 | T9: 71444 | U9: 80000 | V9: 80250 | W9: 80000 | X9: 80250 | Y9: 85000 | Z9: 95000 | AA9: 110000 | AB9: 96983.25 | AC9: 132495.3 | AD9: 82304.25 | AE9: 111869.1 | AF9: 75832.05 | AG9: 84000 | AH9: 84262.5 | AI9: 84000 | AJ9: 84262.5 | AK9: 89250 | AL9: 99750 | AM9: 115500 | AN9: 101832.41 | AO9: 139120.07 | AP9: 86419.46 | AQ9: 117462.56 | AR9: 79623.65 | AS9: 88200 | AT9: 88475.62 | AU9: 88200 | AV9: 88475.62 | AW9: 93712.5 | AX9: 104737.5 | AY9: 121275
B10: MR | C10: Marin | D10: 16838.6 | E10: 13867.046 | F10: 14508.233 | G10: 36538 | H10: 90956 | I10: 87668 | J10: 91349 | K10: 113973 | L10: 81190 | M10: 98516 | N10: 90001 | O10: 104919 | P10: 100589 | Q10: 114193 | R10: 90196 | S10: 140256 | T10: 74382 | U10: 96300 | V10: 95000 | W10: 120000 | X10: 98000 | Y10: 110000 | Z10: 120000 | AA10: 115000 | AB10: 105618.45 | AC10: 119902.65 | AD10: 94705.8 | AE10: 147268.8 | AF10: 78685.95 | AG10: 101115 | AH10: 99750 | AI10: 126000 | AJ10: 102900 | AK10: 115500 | AL10: 126000 | AM10: 120750 | AN10: 110899.37 | AO10: 125897.78 | AP10: 99441.09 | AQ10: 154632.24 | AR10: 82620.25 | AS10: 106170.75 | AT10: 104737.5 | AU10: 132300 | AV10: 108045 | AW10: 121275 | AX10: 132300 | AY10: 126787.5
B11: OP | C11: Ocean Park | D11: 0 | E11: 0 | F11: 0 | G11: 30025 | H11: 45379 | I11: 50782 | J11: 59231 | K11: 60132 | L11: 52754 | M11: 51670 | N11: 60236 | O11: 51621 | P11: 60583 | Q11: 59614 | R11: 62052 | S11: 73815 | T11: 63770 | U11: 64200 | V11: 75000 | W11: 60000 | X11: 63000 | Y11: 70000 | Z11: 75000 | AA11: 60000 | AB11: 63612.15 | AC11: 62594.7 | AD11: 65154.6 | AE11: 77505.75 | AF11: 67045.65 | AG11: 67410 | AH11: 78750 | AI11: 63000 | AJ11: 66150 | AK11: 73500 | AL11: 78750 | AM11: 63000 | AN11: 66792.76 | AO11: 65724.43 | AP11: 68412.33 | AQ11: 81381.04 | AR11: 70397.93 | AS11: 70780.5 | AT11: 82687.5 | AU11: 66150 | AV11: 69457.5 | AW11: 77175 | AX11: 82687.5 | AY11: 66150
B12: PH | C12: Presidio Heights | D12: 233958.4 | E12: 218217.95 | F12: 206588.77 | G12: 189694 | H12: 117239 | I12: 109486 | J12: 91214 | K12: 179728 | L12: 107500 | M12: 134780 | N12: 113334 | O12: 128126 | P12: 124927 | Q12: 180839 | R12: 115051 | S12: 179323 | T12: 93511 | U12: 115000 | V12: 110000 | W12: 155000 | X12: 120000 | Y12: 125000 | Z12: 140000 | AA12: 150000 | AB12: 131173.35 | AC12: 189880.95 | AD12: 120803.55 | AE12: 188289.15 | AF12: 100401 | AG12: 120750 | AH12: 115500 | AI12: 162750 | AJ12: 126000 | AK12: 131250 | AL12: 147000 | AM12: 157500 | AN12: 137732.02 | AO12: 199375 | AP12: 126843.73 | AQ12: 197703.61 | AR12: 105421.05 | AS12: 126787.5 | AT12: 121275 | AU12: 170887.5 | AV12: 132300 | AW12: 137812.5 | AX12: 154350 | AY12: 165375
B13: RH | C13: Russian Hill | D13: 0 | E13: 31933 | F13: 55412 | G13: 81989 | H13: 70953 | I13: 67470 | J13: 72141 | K13: 93312 | L13: 69913 | M13: 80685 | N13: 76340 | O13: 72252 | P13: 96145 | Q13: 94253 | R13: 85589 | S13: 108129 | T13: 66857 | U13: 77000 | V13: 75000 | W13: 95000 | X13: 80000 | Y13: 82000 | Z13: 80000 | AA13: 88000 | AB13: 100952.25 | AC13: 98965.65 | AD13: 89868.45 | AE13: 113535.45 | AF13: 71700.3 | AG13: 80850 | AH13: 78750 | AI13: 99750 | AJ13: 84000 | AK13: 86100 | AL13: 84000 | AM13: 92400 | AN13: 105999.86 | AO13: 103913.93 | AP13: 94361.87 | AQ13: 119212.22 | AR13: 75285.32 | AS13: 84892.5 | AT13: 82687.5 | AU13: 104737.5 | AV13: 88200 | AW13: 90405 | AX13: 88200 | AY13: 97020
B14: SB | C14: Santa Barbara | D14: 0 | E14: 0 | F14: 0 | G14: 0 | H14: 0 | I14: 0 | J14: 0 | K14: 0 | L14: 0 | M14: 0 | N14: 8231 | O14: 17514 | P14: 32747 | Q14: 27799 | R14: 25898 | S14: 23393 | T14: 20133 | U14: 25000 | V14: 25000 | W14: 30000 | X14: 30000 | Y14: 33000 | Z14: 35000 | AA14: 35000 | AB14: 59231 | AC14: 60132 | AD14: 52754 | AE14: 51670 | AF14: 60236 | AG14: 51621 | AH14: 62000 | AI14: 63000 | AJ14: 73000 | AK14: 65000 | AL14: 64200 | AM14: 64200 | AN14: 62192.55 | AO14: 63138.6 | AP14: 55391.7 | AQ14: 54253.5 | AR14: 63247.8 | AS14: 54202.05 | AT14: 65100 | AU14: 66150 | AV14: 76650 | AW14: 68250 | AX14: 67410 | AY14: 67410
B15: SM | C15: Santa Monica | D15: 143755 | E15: 203570 | F15: 268747 | G15: 164726 | H15: 193168 | I15: 169753 | J15: 231840 | K15: 162408 | L15: 176867 | M15: 154064 | N15: 188610 | O15: 178478 | P15: 184491 | Q15: 161597 | R15: 192258 | S15: 157521 | T15: 206632 | U15: 200000 | V15: 200000 | W15: 200000 | X15: 190000 | Y15: 220000 | Z15: 251450 | AA15: 190000 | AB15: 193715.55 | AC15: 169676.85 | AD15: 201870.9 | AE15: 165397.05 | AF15: 217676.55 | AG15: 210000 | AH15: 210000 | AI15: 210000 | AJ15: 199500 | AK15: 231000 | AL15: 264022.5 | AM15: 199500 | AN15: 203401.33 | AO15: 178160.69 | AP15: 211964.45 | AQ15: 173666.9 | AR15: 228560.38 | AS15: 220500 | AT15: 220500 | AU15: 220500 | AV15: 209475 | AW15: 242550 | AX15: 277223.62 | AY15: 209475
B16: WP | C16: West Portal | D16: 0 | E16: 0 | F16: 0 | G16: 0 | H16: 0 | I16: 0 | J16: 0 | K16: 0 | L16: 0 | M16: 0 | N16: 470 | O16: 4114 | P16: 1573 | Q16: 1513 | R16: 784 | S16: 370 | T16: 26 | U16: 40000 | V16: 70000 | W16: 78000 | X16: 75000 | Y16: 80000 | Z16: 80000 | AA16: 80000 | AB16: 90025 | AC16: 86822 | AD16: 85300 | AE16: 127703 | AF16: 79689 | AG16: 76768 | AH16: 70767 | AI16: 102739 | AJ16: 68837 | AK16: 83777 | AL16: 79979 | AM16: 79880 | AN16: 94526.25 | AO16: 91163.1 | AP16: 89565 | AQ16: 134088.15 | AR16: 83673.45 | AS16: 80606.4 | AT16: 74305.35 | AU16: 107875.95 | AV16: 72278.85 | AW16: 87965.85 | AX16: 83977.95 | AY16: 83874
B17: WW | C17: Westwood | D17: 71187 | E17: 96307 | F17: 93607 | G17: 77241 | H17: 90103 | I17: 75890 | J17: 75128 | K17: 59513 | L17: 67496 | M17: 64714 | N17: 67128 | O17: 61457 | P17: 71360 | Q17: 69405 | R17: 62992 | S17: 49441 | T17: 60750 | U17: 65000 | V17: 62000 | W17: 64000 | X17: 72000 | Y17: 80000 | Z17: 85600 | AA17: 74900 | AB17: 74928 | AC17: 72875.25 | AD17: 66141.6 | AE17: 51913.05 | AF17: 63897.75 | AG17: 68250 | AH17: 65100 | AI17: 67200 | AJ17: 75600 | AK17: 84000 | AL17: 89880 | AM17: 78645 | AN17: 78674.4 | AO17: 76519.01 | AP17: 69448.68 | AQ17: 54508.7 | AR17: 67092.64 | AS17: 71662.5 | AT17: 68355 | AU17: 70560 | AV17: 79380 | AW17: 88200 | AX17: 94374 | AY17: 82577.25
B18: TOTAL | C18: All Studios | D18: =SUM(D6:D17) | E18: =SUM(E6:E17) | F18: =SUM(F6:F17) | G18: =SUM(G6:G17) | H18: =SUM(H6:H17) | I18: =SUM(I6:I17) | J18: =SUM(J6:J17) | K18: =SUM(K6:K17) | ... AY18: =SUM(AY6:AY17)
B20: Annual Summary
B21: Code | C21: Studio | D21: 2025 | E21: 2026 | F21: 2027 | G21: 2028
B22: BK | C22: Berkeley | D22: =SUM(D6:O6) | E22: =SUM(P6:AA6) | F22: =SUM(AB6:AM6) | G22: =SUM(AN6:AY6)
B23: CC | C23: Culver City | D23: =SUM(D7:O7) | E23: =SUM(P7:AA7) | F23: =SUM(AB7:AM7) | G23: =SUM(AN7:AY7)
B24: DN | C24: Danville | D24: =SUM(D8:O8) | E24: =SUM(P8:AA8) | F24: =SUM(AB8:AM8) | G24: =SUM(AN8:AY8)
B25: LF | C25: Lafayette | D25: =SUM(D9:O9) | E25: =SUM(P9:AA9) | F25: =SUM(AB9:AM9) | G25: =SUM(AN9:AY9)
B26: MR | C26: Marin | D26: =SUM(D10:O10) | E26: =SUM(P10:AA10) | F26: =SUM(AB10:AM10) | G26: =SUM(AN10:AY10)
B27: OP | C27: Ocean Park | D27: =SUM(D11:O11) | E27: =SUM(P11:AA11) | F27: =SUM(AB11:AM11) | G27: =SUM(AN11:AY11)
B28: PH | C28: Presidio Heights | D28: =SUM(D12:O12) | E28: =SUM(P12:AA12) | F28: =SUM(AB12:AM12) | G28: =SUM(AN12:AY12)
B29: RH | C29: Russian Hill | D29: =SUM(D13:O13) | E29: =SUM(P13:AA13) | F29: =SUM(AB13:AM13) | G29: =SUM(AN13:AY13)
B30: SB | C30: Santa Barbara | D30: =SUM(D14:O14) | E30: =SUM(P14:AA14) | F30: =SUM(AB14:AM14) | G30: =SUM(AN14:AY14)
B31: SM | C31: Santa Monica | D31: =SUM(D15:O15) | E31: =SUM(P15:AA15) | F31: =SUM(AB15:AM15) | G31: =SUM(AN15:AY15)
B32: WP | C32: West Portal | D32: =SUM(D16:O16) | E32: =SUM(P16:AA16) | F32: =SUM(AB16:AM16) | G32: =SUM(AN16:AY16)
B33: WW | C33: Westwood | D33: =SUM(D17:O17) | E33: =SUM(P17:AA17) | F33: =SUM(AB17:AM17) | G33: =SUM(AN17:AY17)
B34: TOTAL | C34: All Studios | D34: =SUM(D22:D33) | E34: =SUM(E22:E33) | F34: =SUM(F22:F33) | G34: =SUM(G22:G33)
B100: 2025 SALES HISTORY (hidden helper for lag formulas) | P100: 2025-07 | Q100: 2025-08 | R100: 2025-09 | S100: 2025-10 | T100: 2025-11 | U100: 2025-12
P101: 808077 | Q101: 930709 | R101: 758432 | S101: 830044 | T101: 833160 | U101: 847328
B102: 2025 helper: BK (Berkeley) | T102: 102111.01 | U102: 103847.42
B103: 2025 helper: CC (Culver City) | T103: 36886.61 | U103: 37513.88
B104: 2025 helper: DN (Danville) | T104: 18359.97 | U104: 18672.19
B105: 2025 helper: LF (Lafayette) | T105: 84253.69 | U105: 85686.43
B106: 2025 helper: MR (Marin) | T106: 92130.72 | U106: 93697.42
B107: 2025 helper: OP (Ocean Park) | T107: 56662.27 | U107: 57625.82
B108: 2025 helper: PH (Presidio Heights) | T108: 123229.91 | U108: 125325.45
B109: 2025 helper: RH (Russian Hill) | T109: 80127.42 | U109: 81490
B110: 2025 helper: SB (Santa Barbara) | T110: 23052.3 | U110: 23444.3
B111: 2025 helper: SM (Santa Monica) | T111: 159966.86 | U111: 162687.12
B112: 2025 helper: WP (West Portal) | T112: 755.57 | U112: 768.42
B113: 2025 helper: WW (Westwood) | T113: 55623.67 | U113: 56569.55

Sheet Cash, Debt & Equity
B2: Cash, Debt & Equity
B4: Item | P4: Jan 2026 | Q4: Feb 2026 | R4: Mar 2026 | S4: Apr 2026 | T4: May 2026 | U4: Jun 2026 | V4: Jul 2026 | W4: Aug 2026 | X4: Sep 2026 | Y4: Oct 2026 | Z4: Nov 2026 | AA4: Dec 2026 | AB4: Jan 2027 | AC4: Feb 2027 | AD4: Mar 2027 | AE4: Apr 2027 | AF4: May 2027 | AG4: Jun 2027 | AH4: Jul 2027 | AI4: Aug 2027 | AJ4: Sep 2027 | AK4: Oct 2027 | AL4: Nov 2027 | AM4: Dec 2027 | AN4: Jan 2028 | AO4: Feb 2028 | AP4: Mar 2028 | AQ4: Apr 2028 | AR4: May 2028 | AS4: Jun 2028 | AT4: Jul 2028 | AU4: Aug 2028 | AV4: Sep 2028 | AW4: Oct 2028 | AX4: Nov 2028 | AY4: Dec 2028
B5: CASH POSITION | D5: Jan 2025 | E5: Feb 2025 | F5: Mar 2025 | G5: Apr 2025 | H5: May 2025 | I5: Jun 2025 | J5: Jul 2025 | K5: Aug 2025 | L5: Sep 2025 | M5: Oct 2025 | N5: Nov 2025 | O5: Dec 2025
B6: Ending Cash Balance (from CF) | P6: ='Cash Flow Forecast'!P40 | Q6: ='Cash Flow Forecast'!Q40 | R6: ='Cash Flow Forecast'!R40 | S6: ='Cash Flow Forecast'!S40 | T6: ='Cash Flow Forecast'!T40 | U6: ='Cash Flow Forecast'!U40 | V6: ='Cash Flow Forecast'!V40 | W6: ='Cash Flow Forecast'!W40 | ... AY6: ='Cash Flow Forecast'!AY40
B8: DEBT SCHEDULE — Loan Balances by Month
B9: MindBody Loan - SM | P9: 0 | Q9: 0 | R9: 0 | S9: 99348.21 | T9: 0 | U9: =MAX(T9-18871.69,0) | V9: =MAX(U9-18871.69,0) | W9: =MAX(V9-18871.69,0) | X9: =MAX(W9-18871.69,0) | Y9: =MAX(X9-18871.69,0) | Z9: =MAX(Y9-18871.69,0) | AA9: =MAX(Z9-18871.69,0) | AB9: =MAX(AA9-18871.69,0) | ... AY9: =MAX(AX9-18871.69,0)
B10: MindBody Loan - PH | P10: 0 | Q10: 0 | R10: 0 | S10: 46989.79 | T10: 0 | U10: =MAX(T10-16602.04,0) | V10: =MAX(U10-16602.04,0) | W10: =MAX(V10-16602.04,0) | X10: =MAX(W10-16602.04,0) | Y10: =MAX(X10-16602.04,0) | Z10: =MAX(Y10-16602.04,0) | AA10: =MAX(Z10-16602.04,0) | AB10: =MAX(AA10-16602.04,0) | ... AY10: =MAX(AX10-16602.04,0)
B11: MindBody Loan - LF | P11: 0 | Q11: 0 | R11: 0 | S11: 20599.85 | T11: 0 | U11: =MAX(T11-12162.36,0) | V11: =MAX(U11-12162.36,0) | W11: =MAX(V11-12162.36,0) | X11: =MAX(W11-12162.36,0) | Y11: =MAX(X11-12162.36,0) | Z11: =MAX(Y11-12162.36,0) | AA11: =MAX(Z11-12162.36,0) | AB11: =MAX(AA11-12162.36,0) | ... AY11: =MAX(AX11-12162.36,0)
B12: MindBody Loan - MR | P12: 0 | Q12: 0 | R12: 0 | S12: 14815.18 | T12: 0 | U12: =MAX(T12-13157.16,0) | V12: =MAX(U12-13157.16,0) | W12: =MAX(V12-13157.16,0) | X12: =MAX(W12-13157.16,0) | Y12: =MAX(X12-13157.16,0) | Z12: =MAX(Y12-13157.16,0) | AA12: =MAX(Z12-13157.16,0) | AB12: =MAX(AA12-13157.16,0) | ... AY12: =MAX(AX12-13157.16,0)
B13: Samson Loan | P13: 205426.16 | Q13: 189034.12 | R13: 154505.72 | S13: 129045.5 | T13: 94517.1 | U13: =MAX(T13-25460.22,0) | V13: =MAX(U13-25460.22,0) | W13: =MAX(V13-25460.22,0) | X13: =MAX(W13-25460.22,0) | Y13: =MAX(X13-25460.22,0) | Z13: =MAX(Y13-25460.22,0) | AA13: =MAX(Z13-25460.22,0) | AB13: =MAX(AA13-25460.22,0) | ... AY13: =MAX(AX13-25460.22,0)
B14: Specialty Capital Loan | P14: 187921.05 | Q14: 165407.89 | R14: 135078.94 | S14: 112565.78 | T14: 90052.62 | U14: =MAX(T14-25888.16,0) | V14: =MAX(U14-25888.16,0) | W14: =MAX(V14-25888.16,0) | X14: =MAX(W14-25888.16,0) | Y14: =MAX(X14-25888.16,0) | Z14: =MAX(Y14-25888.16,0) | AA14: =MAX(Z14-25888.16,0) | AB14: =MAX(AA14-25888.16,0) | ... AY14: =MAX(AX14-25888.16,0)
B15: Norbrook Inc Loan | P15: 0 | Q15: 0 | R15: 0 | S15: 162318 | T15: 0 | U15: =T15 | V15: =U15 | W15: =V15 | X15: =W15 | Y15: =X15 | Z15: =Y15 | AA15: =Z15 | AB15: =AA15 | ... AY15: =AX15
B16: TOTAL DEBT | P16: =SUM(P9:P15) | Q16: =SUM(Q9:Q15) | R16: =SUM(R9:R15) | S16: =SUM(S9:S15) | T16: =SUM(T9:T15) | U16: =SUM(U9:U15) | V16: =SUM(V9:V15) | W16: =SUM(W9:W15) | ... AY16: =SUM(AY9:AY15)
B18: MONTHLY DEBT SERVICE
B19: MindBody Loan - SM | P19: 0 | Q19: 0 | R19: 0 | S19: 0 | T19: 0 | U19: =IF(U9>0,18871.69,0) | V19: =IF(V9>0,18871.69,0) | W19: =IF(W9>0,18871.69,0) | X19: =IF(X9>0,18871.69,0) | Y19: =IF(Y9>0,18871.69,0) | Z19: =IF(Z9>0,18871.69,0) | AA19: =IF(AA9>0,18871.69,0) | AB19: =IF(AB9>0,18871.69,0) | ... AY19: =IF(AY9>0,18871.69,0)
B20: MindBody Loan - PH | P20: 0 | Q20: 0 | R20: 0 | S20: 0 | T20: 0 | U20: =IF(U10>0,16602.04,0) | V20: =IF(V10>0,16602.04,0) | W20: =IF(W10>0,16602.04,0) | X20: =IF(X10>0,16602.04,0) | Y20: =IF(Y10>0,16602.04,0) | Z20: =IF(Z10>0,16602.04,0) | AA20: =IF(AA10>0,16602.04,0) | AB20: =IF(AB10>0,16602.04,0) | ... AY20: =IF(AY10>0,16602.04,0)
B21: MindBody Loan - LF | P21: 0 | Q21: 0 | R21: 0 | S21: 0 | T21: 0 | U21: =IF(U11>0,12162.36,0) | V21: =IF(V11>0,12162.36,0) | W21: =IF(W11>0,12162.36,0) | X21: =IF(X11>0,12162.36,0) | Y21: =IF(Y11>0,12162.36,0) | Z21: =IF(Z11>0,12162.36,0) | AA21: =IF(AA11>0,12162.36,0) | AB21: =IF(AB11>0,12162.36,0) | ... AY21: =IF(AY11>0,12162.36,0)
B22: MindBody Loan - MR | P22: 0 | Q22: 0 | R22: 0 | S22: 0 | T22: 0 | U22: =IF(U12>0,13157.16,0) | V22: =IF(V12>0,13157.16,0) | W22: =IF(W12>0,13157.16,0) | X22: =IF(X12>0,13157.16,0) | Y22: =IF(Y12>0,13157.16,0) | Z22: =IF(Z12>0,13157.16,0) | AA22: =IF(AA12>0,13157.16,0) | AB22: =IF(AB12>0,13157.16,0) | ... AY22: =IF(AY12>0,13157.16,0)
B23: Samson Loan | P23: 0 | Q23: 0 | R23: 0 | S23: 0 | T23: 94517.1 | U23: =IF(U13>0,25460.22,0) | V23: =IF(V13>0,25460.22,0) | W23: =IF(W13>0,25460.22,0) | X23: =IF(X13>0,25460.22,0) | Y23: =IF(Y13>0,25460.22,0) | Z23: =IF(Z13>0,25460.22,0) | AA23: =IF(AA13>0,25460.22,0) | AB23: =IF(AB13>0,25460.22,0) | ... AY23: =IF(AY13>0,25460.22,0)
B24: Specialty Capital Loan | P24: 0 | Q24: 0 | R24: 0 | S24: 0 | T24: 90052.62 | U24: =IF(U14>0,25888.16,0) | V24: =IF(V14>0,25888.16,0) | W24: =IF(W14>0,25888.16,0) | X24: =IF(X14>0,25888.16,0) | Y24: =IF(Y14>0,25888.16,0) | Z24: =IF(Z14>0,25888.16,0) | AA24: =IF(AA14>0,25888.16,0) | AB24: =IF(AB14>0,25888.16,0) | ... AY24: =IF(AY14>0,25888.16,0)
B25: Norbrook Inc Loan | P25: 0 | Q25: 0 | R25: 0 | S25: 0 | T25: 0 | U25: =U15*0.08/12 | V25: =V15*0.08/12 | W25: =W15*0.08/12 | X25: =X15*0.08/12 | Y25: =Y15*0.08/12 | Z25: =Z15*0.08/12 | AA25: =AA15*0.08/12 | AB25: =AB15*0.08/12 | ... AY25: =AY15*0.08/12
B26: TOTAL DEBT SERVICE | P26: =SUM(P19:P25) | Q26: =SUM(Q19:Q25) | R26: =SUM(R19:R25) | S26: =SUM(S19:S25) | T26: =SUM(T19:T25) | U26: =SUM(U19:U25) | V26: =SUM(V19:V25) | W26: =SUM(W19:W25) | ... AY26: =SUM(AY19:AY25)
B28: OWNER EQUITY / INTERCOMPANY
B29: Intercompany Net Position | P29: 224773.04 | Q29: 224773.04 | R29: 358106.37 | S29: 436439.7 | T29: 0 | U29: 0 | V29: 0 | W29: 0 | X29: 0 | Y29: 0 | Z29: 0 | AA29: 0 | AB29: 0 | AC29: 0 | AD29: 0 | AE29: 0 | AF29: 0 | AG29: 0 | AH29: 0 | AI29: 0 | AJ29: 0 | AK29: 0 | AL29: 0 | AM29: 0 | AN29: 0 | AO29: 0 | AP29: 0 | AQ29: 0 | AR29: 0 | AS29: 0 | AT29: 0 | AU29: 0 | AV29: 0 | AW29: 0 | AX29: 0 | AY29: 0

Sheet Cash Flow Forecast
B2: Cash Flow Forecast
B3: Actuals: Jan-Apr 2026 (light green). Forecast: May 2026 onwards. Net Change formulas sum operations + investing + financing.
B4: Monthly Cash Flow
B5: Line Item | C5: Annual Total | D5: Jan 2025 | E5: Feb 2025 | F5: Mar 2025 | G5: Apr 2025 | H5: May 2025 | I5: Jun 2025 | J5: Jul 2025 | K5: Aug 2025 | L5: Sep 2025 | M5: Oct 2025 | N5: Nov 2025 | O5: Dec 2025 | P5: Jan 2026 | Q5: Feb 2026 | R5: Mar 2026 | S5: Apr 2026 | T5: May 2026 | U5: Jun 2026 | V5: Jul 2026 | W5: Aug 2026 | X5: Sep 2026 | Y5: Oct 2026 | Z5: Nov 2026 | AA5: Dec 2026 | AB5: Jan 2027 | AC5: Feb 2027 | AD5: Mar 2027 | AE5: Apr 2027 | AF5: May 2027 | AG5: Jun 2027 | AH5: Jul 2027 | AI5: Aug 2027 | AJ5: Sep 2027 | AK5: Oct 2027 | AL5: Nov 2027 | AM5: Dec 2027 | AN5: Jan 2028 | AO5: Feb 2028 | AP5: Mar 2028 | AQ5: Apr 2028 | AR5: May 2028 | AS5: Jun 2028 | AT5: Jul 2028 | AU5: Aug 2028 | AV5: Sep 2028 | AW5: Oct 2028 | AX5: Nov 2028 | AY5: Dec 2028 | BA5: 2025 | BB5: =BA5+1 | BC5: =BB5+1 | BD5: =BC5+1 | BF5: LTM May 2026
B6: CASH INFLOWS
B7: Total Cash Sales | P7: ='Sales Forecast'!P18 | Q7: ='Sales Forecast'!Q18 | R7: ='Sales Forecast'!R18 | S7: ='Sales Forecast'!S18 | T7: ='Sales Forecast'!T18 | U7: ='Sales Forecast'!U18 | V7: ='Sales Forecast'!V18 | W7: ='Sales Forecast'!W18 | ... AY7: ='Sales Forecast'!AY18
B9: OPERATING OUTFLOWS
B10: Property Costs | P10: 147113.46 | Q10: 146344.65 | R10: 147382.66 | S10: 148059.43 | T10: 147112.25 | U10: ='P&L'!U19 | V10: ='P&L'!V19 | W10: ='P&L'!W19 | X10: ='P&L'!X19 | Y10: ='P&L'!Y19 | Z10: ='P&L'!Z19 | AA10: ='P&L'!AA19 | AB10: ='P&L'!AB19 | ... AM10: ='P&L'!AM19 | AN10: 156071.4 | AO10: 156071.4 | AP10: 156071.4 | AQ10: 156071.4 | AR10: 156071.4 | AS10: 156071.4 | AT10: 156071.4 | AU10: 156071.4 | AV10: 156071.4 | AW10: 156071.4 | AX10: 156071.4 | AY10: 156071.4
B11: Staff Costs | P11: 681232.98 | Q11: 590412.06 | R11: 628953.81 | S11: 576480.98 | T11: 598615.61 | U11: ='P&L'!U15 | V11: ='P&L'!V15 | W11: ='P&L'!W15 | X11: ='P&L'!X15 | Y11: ='P&L'!Y15 | Z11: ='P&L'!Z15 | AA11: ='P&L'!AA15 | AB11: ='P&L'!AB15 | ... AM11: ='P&L'!AM15 | AN11: 647462.64 | AO11: 647462.64 | AP11: 647462.64 | AQ11: 647462.64 | AR11: 647462.64 | AS11: 647462.64 | AT11: 647462.64 | AU11: 647462.64 | AV11: 647462.64 | AW11: 647462.64 | AX11: 647462.64 | AY11: 647462.64
B12: Utilities | P12: 7087.42 | Q12: 9973.09 | R12: 7034.72 | S12: 7270.22 | T12: 8720.11 | U12: ='P&L'!U18 | V12: ='P&L'!V18 | W12: ='P&L'!W18 | X12: ='P&L'!X18 | Y12: ='P&L'!Y18 | Z12: ='P&L'!Z18 | AA12: ='P&L'!AA18 | AB12: ='P&L'!AB18 | ... AM12: ='P&L'!AM18 | AN12: 9380.48 | AO12: 9380.48 | AP12: 8753.05 | AQ12: 8753.05 | AR12: 8753.05 | AS12: 8753.05 | AT12: 8753.05 | AU12: 8753.05 | AV12: 8753.05 | AW12: 8753.05 | AX12: 8753.05 | AY12: 8753.05
B13: Marketing & Promotion | P13: 27740.18 | Q13: 27007.49 | R13: 16681.8 | S13: 5975.58 | T13: 16948.9 | U13: ='P&L'!U14 | V13: ='P&L'!V14 | W13: ='P&L'!W14 | X13: ='P&L'!X14 | Y13: ='P&L'!Y14 | Z13: ='P&L'!Z14 | AA13: ='P&L'!AA14 | AB13: ='P&L'!AB14 | ... AM13: ='P&L'!AM14 | AN13: 18331.93 | AO13: 18331.93 | AP13: 18331.93 | AQ13: 18331.93 | AR13: 18331.93 | AS13: 18331.93 | AT13: 18331.93 | AU13: 18331.93 | AV13: 18331.93 | AW13: 18331.93 | AX13: 18331.93 | AY13: 18331.93
B14: Administrative & G&A | P14: 32760.81 | Q14: 38409.23 | R14: 33297.16 | S14: 28817.49 | T14: 37431.59 | U14: ='P&L'!U16 | V14: ='P&L'!V16 | W14: ='P&L'!W16 | X14: ='P&L'!X16 | Y14: ='P&L'!Y16 | Z14: ='P&L'!Z16 | AA14: ='P&L'!AA16 | AB14: ='P&L'!AB16 | ... AM14: ='P&L'!AM16 | AN14: 40486.01 | AO14: 40486.01 | AP14: 40486.01 | AQ14: 40486.01 | AR14: 40486.01 | AS14: 40486.01 | AT14: 40486.01 | AU14: 40486.01 | AV14: 40486.01 | AW14: 40486.01 | AX14: 40486.01 | AY14: 40486.01
B15: Professional Fees | P15: 42733.79 | Q15: 24202.3 | R15: 22556.84 | S15: 25366 | T15: 24041.72 | U15: ='P&L'!U17 | V15: ='P&L'!V17 | W15: ='P&L'!W17 | X15: ='P&L'!X17 | Y15: ='P&L'!Y17 | Z15: ='P&L'!Z17 | AA15: ='P&L'!AA17 | AB15: ='P&L'!AB17 | ... AM15: ='P&L'!AM17 | AN15: 26003.5 | AO15: 26003.5 | AP15: 26003.5 | AQ15: 26003.5 | AR15: 26003.5 | AS15: 26003.5 | AT15: 26003.5 | AU15: 26003.5 | AV15: 26003.5 | AW15: 26003.5 | AX15: 26003.5 | AY15: 26003.5
B16: Travel & Meals | P16: 6819.03 | Q16: 3543.33 | R16: 6002.36 | S16: 2789.61 | T16: 4111.78 | U16: ='BK P&L'!U50+'CC P&L'!U50+'DN P&L'!U50+'LF P&L'!U50+'MR P&L'!U50+'OP P&L'!U50+'PH P&L'!U50+'RH P&L'!U50+'SB P&L'!U50+'SM P&L'!U50+'WP P&L'!U50+'WW P&L'!U50+'HO P&L'!U30 | V16: ='BK P&L'!V50+'CC P&L'!V50+'DN P&L'!V50+'LF P&L'!V50+'MR P&L'!V50+'OP P&L'!V50+'PH P&L'!V50+'RH P&L'!V50+'SB P&L'!V50+'SM P&L'!V50+'WP P&L'!V50+'WW P&L'!V50+'HO P&L'!V30 | W16: ='BK P&L'!W50+'CC P&L'!W50+'DN P&L'!W50+'LF P&L'!W50+'MR P&L'!W50+'OP P&L'!W50+'PH P&L'!W50+'RH P&L'!W50+'SB P&L'!W50+'SM P&L'!W50+'WP P&L'!W50+'WW P&L'!W50+'HO P&L'!W30 | X16: ='BK P&L'!X50+'CC P&L'!X50+'DN P&L'!X50+'LF P&L'!X50+'MR P&L'!X50+'OP P&L'!X50+'PH P&L'!X50+'RH P&L'!X50+'SB P&L'!X50+'SM P&L'!X50+'WP P&L'!X50+'WW P&L'!X50+'HO P&L'!X30 | Y16: ='BK P&L'!Y50+'CC P&L'!Y50+'DN P&L'!Y50+'LF P&L'!Y50+'MR P&L'!Y50+'OP P&L'!Y50+'PH P&L'!Y50+'RH P&L'!Y50+'SB P&L'!Y50+'SM P&L'!Y50+'WP P&L'!Y50+'WW P&L'!Y50+'HO P&L'!Y30 | Z16: ='BK P&L'!Z50+'CC P&L'!Z50+'DN P&L'!Z50+'LF P&L'!Z50+'MR P&L'!Z50+'OP P&L'!Z50+'PH P&L'!Z50+'RH P&L'!Z50+'SB P&L'!Z50+'SM P&L'!Z50+'WP P&L'!Z50+'WW P&L'!Z50+'HO P&L'!Z30 | AA16: ='BK P&L'!AA50+'CC P&L'!AA50+'DN P&L'!AA50+'LF P&L'!AA50+'MR P&L'!AA50+'OP P&L'!AA50+'PH P&L'!AA50+'RH P&L'!AA50+'SB P&L'!AA50+'SM P&L'!AA50+'WP P&L'!AA50+'WW P&L'!AA50+'HO P&L'!AA30 | AB16: ='BK P&L'!AB50+'CC P&L'!AB50+'DN P&L'!AB50+'LF P&L'!AB50+'MR P&L'!AB50+'OP P&L'!AB50+'PH P&L'!AB50+'RH P&L'!AB50+'SB P&L'!AB50+'SM P&L'!AB50+'WP P&L'!AB50+'WW P&L'!AB50+'HO P&L'!AB30 | ... AM16: ='BK P&L'!AM50+'CC P&L'!AM50+'DN P&L'!AM50+'LF P&L'!AM50+'MR P&L'!AM50+'OP P&L'!AM50+'PH P&L'!AM50+'RH P&L'!AM50+'SB P&L'!AM50+'SM P&L'!AM50+'WP P&L'!AM50+'WW P&L'!AM50+'HO P&L'!AM30 | AN16: 4447.31 | AO16: 4447.31 | AP16: 4447.31 | AQ16: 4447.31 | AR16: 4447.31 | AS16: 4447.31 | AT16: 4447.31 | AU16: 4447.31 | AV16: 4447.31 | AW16: 4447.31 | AX16: 4447.31 | AY16: 4447.31
B17: Merchant Fees & COGS | P17: 65117.3 | Q17: 67419.26 | R17: 61727.36 | S17: 65364.98 | T17: =T7*(Assumptions!$C$19+Assumptions!$C$20) | U17: ='P&L'!U12 | V17: ='P&L'!V12 | W17: ='P&L'!W12 | X17: ='P&L'!X12 | Y17: ='P&L'!Y12 | Z17: ='P&L'!Z12 | AA17: ='P&L'!AA12 | AB17: ='P&L'!AB12 | ... AM17: ='P&L'!AM12 | AN17: =AN7*(Assumptions!$C$19+Assumptions!$C$20) | AO17: =AO7*(Assumptions!$C$19+Assumptions!$C$20) | AP17: =AP7*(Assumptions!$C$19+Assumptions!$C$20) | AQ17: =AQ7*(Assumptions!$C$19+Assumptions!$C$20) | AR17: =AR7*(Assumptions!$C$19+Assumptions!$C$20) | AS17: =AS7*(Assumptions!$C$19+Assumptions!$C$20) | AT17: =AT7*(Assumptions!$C$19+Assumptions!$C$20) | AU17: =AU7*(Assumptions!$C$19+Assumptions!$C$20) | ... AY17: =AY7*(Assumptions!$C$19+Assumptions!$C$20)
B18: Studio Start Up Costs | P18: 0 | Q18: 0 | R18: 0 | S18: 0 | T18: 0 | U18: 0 | V18: 0 | W18: 0 | X18: 0 | Y18: 0 | Z18: 0 | AA18: 0 | AB18: 0 | AC18: 0 | AD18: 0 | AE18: 0 | AF18: 0 | AG18: 0 | AH18: 0 | AI18: 0 | AJ18: 0 | AK18: 0 | AL18: 0 | AM18: 0 | AN18: 0 | AO18: 0 | AP18: 0 | AQ18: 0 | AR18: 0 | AS18: 0 | AT18: 0 | AU18: 0 | AV18: 0 | AW18: 0 | AX18: 0 | AY18: 0
B19: Taxes | P19: 3673 | Q19: 8816 | R19: 3673 | S19: 3673 | T19: 5387.33 | U19: ='P&L'!U25+'P&L'!U26 | V19: ='P&L'!V25+'P&L'!V26 | W19: ='P&L'!W25+'P&L'!W26 | X19: ='P&L'!X25+'P&L'!X26 | Y19: ='P&L'!Y25+'P&L'!Y26 | Z19: ='P&L'!Z25+'P&L'!Z26 | AA19: ='P&L'!AA25+'P&L'!AA26 | AB19: ='P&L'!AB25+'P&L'!AB26 | ... AM19: ='P&L'!AM25+'P&L'!AM26 | AN19: 5826.93 | AO19: 5826.93 | AP19: 5826.93 | AQ19: 5826.93 | AR19: 5826.93 | AS19: 5826.93 | AT19: 5826.93 | AU19: 5826.93 | AV19: 5826.93 | AW19: 5826.93 | AX19: 5826.93 | AY19: 5826.93
B20: PF Interest Expense | X20: =X49 | Y20: =Y49 | Z20: =Z49 | AA20: =AA49 | AB20: =AB49 | AC20: =AC49 | AD20: =AD49 | AE20: =AE49 | ... AY20: =AY49
B21: PF Fees (Debt Fees and Legal) | X21: ='Sources and Uses'!C15+'Sources and Uses'!C16
B22: Total Operating Expenses | P22: =SUM(P10:P21) | Q22: =SUM(Q10:Q21) | R22: =SUM(R10:R21) | S22: =SUM(S10:S21) | T22: =SUM(T10:T21) | U22: =SUM(U10:U21) | V22: =SUM(V10:V21) | W22: =SUM(W10:W21) | ... AY22: =SUM(AY10:AY21)
B23: Net Cash from Operations | P23: =P7-P22 | Q23: =Q7-Q22 | R23: =R7-R22 | S23: =S7-S22 | T23: =T7-T22 | U23: =U7-U22 | V23: =V7-V22 | W23: =W7-W22 | ... AY23: =AY7-AY22
B25: INVESTING ACTIVITIES
B26: Equipment & Furniture | P26: 0 | Q26: 2497.4 | R26: 0 | S26: 0 | T26: 0 | U26: 0 | V26: 0 | W26: 0 | X26: 0 | Y26: 0 | Z26: 0 | AA26: 0 | AB26: 0 | AC26: 0 | AD26: 0 | AE26: 0 | AF26: 0 | AG26: 0 | AH26: 0 | AI26: 0 | AJ26: 0 | AK26: 0 | AL26: 0 | AM26: 0 | AN26: 0 | AO26: 0 | AP26: 0 | AQ26: 0 | AR26: 0 | AS26: 0 | AT26: 0 | AU26: 0 | AV26: 0 | AW26: 0 | AX26: 0 | AY26: 0
B27: Leasehold Improvements | P27: -17810.67 | Q27: -7094.5 | R27: -24075 | S27: -1035.5 | T27: 0 | U27: 0 | V27: -275000 | W27: -160000 | X27: 0 | Y27: 0 | Z27: 0 | AA27: 0 | AB27: 0 | AC27: 0 | AD27: 0 | AE27: 0 | AF27: 0 | AG27: 0 | AH27: 0 | AI27: 0 | AJ27: 0 | AK27: 0 | AL27: 0 | AM27: 0 | AN27: 0 | AO27: 0 | AP27: 0 | AQ27: 0 | AR27: 0 | AS27: 0 | AT27: 0 | AU27: 0 | AV27: 0 | AW27: 0 | AX27: 0 | AY27: 0
B28: Deposits | P28: 0 | Q28: 0 | R28: 0 | S28: 0 | T28: 0 | U28: 0 | V28: 0 | W28: 0 | X28: 0 | Y28: 0 | Z28: 0 | AA28: 0 | AB28: 0 | AC28: 0 | AD28: 0 | AE28: 0 | AF28: 0 | AG28: 0 | AH28: 0 | AI28: 0 | AJ28: 0 | AK28: 0 | AL28: 0 | AM28: 0 | AN28: 0 | AO28: 0 | AP28: 0 | AQ28: 0 | AR28: 0 | AS28: 0 | AT28: 0 | AU28: 0 | AV28: 0 | AW28: 0 | AX28: 0 | AY28: 0
B29: Net Investing | P29: =SUM(P26:P28) | Q29: =SUM(Q26:Q28) | R29: =SUM(R26:R28) | S29: =SUM(S26:S28) | T29: =SUM(T26:T28) | U29: =SUM(U26:U28) | V29: =SUM(V26:V28) | W29: =SUM(W26:W28) | ... AY29: =SUM(AY26:AY28)
B31: FINANCING ACTIVITIES
B32: Loan Proceeds | P32: 9059.38 | Q32: 9059.38 | R32: 9059.38 | S32: 12507.09 | T32: 0 | U32: 0 | V32: 0 | W32: 0 | X32: =X45 | Y32: 0 | Z32: 0 | AB32: 0 | AC32: 0 | AD32: 0 | AE32: 0 | AF32: 0 | AG32: 0 | AH32: 0 | AI32: 0 | AJ32: 0 | AK32: 0 | AL32: 0 | AM32: 0 | AN32: 0 | AO32: 0 | AP32: 0 | AQ32: 0 | AR32: 0 | AS32: 0 | AT32: 0 | AU32: 0 | AV32: 0 | AW32: 0 | AX32: 0 | AY32: 0
B33: Loan Repayments | P33: -132128.24 | Q33: -122128.76 | R33: -132834.5 | S33: -114793.66 | T33: =-'Cash, Debt & Equity'!T26 | U33: =-'Cash, Debt & Equity'!U26 | V33: =-'Cash, Debt & Equity'!V26 | W33: =-'Cash, Debt & Equity'!W26 | X33: =-'Cash, Debt & Equity'!X26 | Y33: =-'Cash, Debt & Equity'!Y26 | Z33: =-'Cash, Debt & Equity'!Z26 | AA33: =-'Cash, Debt & Equity'!AA26 | ... AY33: =-'Cash, Debt & Equity'!AY26
B34: Intercompany / Owner Contributions | P34: 0 | Q34: 0 | R34: 133333.33 | S34: 78333.33 | T34: 0 | U34: 0 | V34: 0 | W34: 0 | X34: 0 | Y34: 0 | Z34: -100000 | AA34: 0 | AB34: 0 | AC34: 0 | AD34: 0 | AE34: 0 | AF34: 0 | AG34: 0 | AH34: 0 | AI34: 0 | AJ34: 0 | AK34: 0 | AL34: 0 | AM34: 0 | AN34: 0 | AO34: 0 | AP34: 0 | AQ34: 0 | AR34: 0 | AS34: 0 | AT34: 0 | AU34: 0 | AV34: 0 | AW34: 0 | AX34: 0 | AY34: 0
B35: Net Financing | P35: =SUM(P32:P34) | Q35: =SUM(Q32:Q34) | R35: =SUM(R32:R34) | S35: =SUM(S32:S34) | T35: =SUM(T32:T34) | U35: =SUM(U32:U34) | V35: =SUM(V32:V34) | W35: =SUM(W32:W34) | ... AY35: =SUM(AY32:AY34)
B37: NET CHANGE IN CASH
B38: Net Change in Cash | P38: =P23+P29+P35 | Q38: =Q23+Q29+Q35 | R38: =R23+R29+R35 | S38: =S23+S29+S35 | T38: =T23+T29+T35 | U38: =U23+U29+U35 | V38: =V23+V29+V35 | W38: =W23+W29+W35 | ... AY38: =AY23+AY29+AY35
B39: Beginning Cash Balance | P39: =P40-P38 | Q39: =P40 | R39: =Q40 | S39: =R40 | T39: =S40 | U39: =T40 | V39: =U40 | W39: =V40 | X39: =W40 | ... AY39: =AX40
B40: Ending Cash Balance | P40: 187021.69 | Q40: 261314.24 | R40: 237762.6 | S40: 473976.03 | T40: =T39+T38 | U40: =U39+U38 | V40: =V39+V38 | W40: =W39+W38 | X40: =X39+X38 | Y40: =Y39+Y38 | Z40: =Z39+Z38 | AA40: =AA39+AA38 | ... AY40: =AY39+AY38
B42: PF Debt At Close
B44: New Debt, Beg of Period | X44: 0 | Y44: =X47 | Z44: =Y47 | AA44: =Z47 | AB44: =AA47 | AC44: =AB47 | AD44: =AC47 | AE44: =AD47 | AF44: =AE47 | ... AY44: =AX47
B45: Increase (+) | X45: ='Sources and Uses'!C20
B46: Paydown (-) | X46: 0 | Y46: 0 | Z46: 0 | AA46: 0 | AB46: 0 | AC46: 0 | AD46: 0 | AE46: 0 | AF46: 0 | AG46: 0 | AH46: 0 | AI46: 0 | AJ46: 0 | AK46: 0 | AL46: 0 | AM46: 0 | AN46: 0 | AO46: 0 | AP46: 0 | AQ46: 0 | AR46: 0 | AS46: 0 | AT46: 0 | AU46: 0 | AV46: 0 | AW46: 0 | AX46: 0 | AY46: 0
B47: New Debt, End of Period | X47: =SUM(X44:X46) | Y47: =SUM(Y44:Y46) | Z47: =SUM(Z44:Z46) | AA47: =SUM(AA44:AA46) | AB47: =SUM(AB44:AB46) | AC47: =SUM(AC44:AC46) | AD47: =SUM(AD44:AD46) | AE47: =SUM(AE44:AE46) | ... AY47: =SUM(AY44:AY46) | BB47: =AA47 | BC47: =AM47 | BD47: =AY47 | BF47: =BB47
B49: Cash Interest | C49: ='Sources and Uses'!D20 | X49: =$C$49*AVERAGE(X44,X47)/12 | Y49: =$C$49*AVERAGE(Y44,Y47)/12 | Z49: =$C$49*AVERAGE(Z44,Z47)/12 | AA49: =$C$49*AVERAGE(AA44,AA47)/12 | AB49: =$C$49*AVERAGE(AB44,AB47)/12 | AC49: =$C$49*AVERAGE(AC44,AC47)/12 | AD49: =$C$49*AVERAGE(AD44,AD47)/12 | AE49: =$C$49*AVERAGE(AE44,AE47)/12 | ... AY49: =$C$49*AVERAGE(AY44,AY47)/12 | BB49: =SUM(P49:AA49) | BC49: =SUM(AB49:AM49) | BD49: =SUM(AN49:AY49)
B51: Studio Level EBITDA | D51: =Summary!D37 | E51: =Summary!E37 | F51: =Summary!F37 | G51: =Summary!G37 | H51: =Summary!H37 | I51: =Summary!I37 | J51: =Summary!J37 | K51: =Summary!K37 | ... AY51: =Summary!AY37 | BB51: =SUM(P51:AA51) | BC51: =SUM(AB51:AM51) | BD51: =SUM(AN51:AY51) | BF51: =SUM(I51:T51)
B52: Corporate Level EBITDA | D52: =Summary!D22 | E52: =Summary!E22 | F52: =Summary!F22 | G52: =Summary!G22 | H52: =Summary!H22 | I52: =Summary!I22 | J52: =Summary!J22 | K52: =Summary!K22 | ... AY52: =Summary!AY22 | BB52: =SUM(P52:AA52) | BC52: =SUM(AB52:AM52) | BD52: =SUM(AN52:AY52) | BF52: =SUM(I52:T52)
B53: Adjusted Corporate Level EBITDA | D53: =Summary!D39 | E53: =Summary!E39 | F53: =Summary!F39 | G53: =Summary!G39 | H53: =Summary!H39 | I53: =Summary!I39 | J53: =Summary!J39 | K53: =Summary!K39 | ... AY53: =Summary!AY39 | BB53: =SUM(P53:AA53) | BC53: =SUM(AB53:AM53) | BD53: =SUM(AN53:AY53) | BF53: =SUM(I53:T53)
B55: Debt / LTM Studio Level EBITDA | X55: =X47/SUM(M51:X51) | Y55: =Y47/SUM(N51:Y51) | Z55: =Z47/SUM(O51:Z51) | AA55: =AA47/SUM(P51:AA51) | AB55: =AB47/SUM(Q51:AB51) | AC55: =AC47/SUM(R51:AC51) | AD55: =AD47/SUM(S51:AD51) | AE55: =AE47/SUM(T51:AE51) | ... AY55: =AY47/SUM(AN51:AY51) | BB55: =BB47/BB51 | BC55: =BC47/BC51 | BD55: =BD47/BD51 | BF55: =BF47/BF51
B56: Debt / Corporate Level EBITDA | X56: =X47/SUM(M52:X52) | Y56: =Y47/SUM(N52:Y52) | Z56: =Z47/SUM(O52:Z52) | AA56: =AA47/SUM(P52:AA52) | AB56: =AB47/SUM(Q52:AB52) | AC56: =AC47/SUM(R52:AC52) | AD56: =AD47/SUM(S52:AD52) | AE56: =AE47/SUM(T52:AE52) | ... AY56: =AY47/SUM(AN52:AY52) | BB56: =BB47/BB52 | BC56: =BC47/BC52 | BD56: =BD47/BD52 | BF56: =BF47/BF52
B57: Debt / Adjusted Corporate Level EBITDA | X57: =X47/SUM(M53:X53) | Y57: =Y47/SUM(N53:Y53) | Z57: =Z47/SUM(O53:Z53) | AA57: =AA47/SUM(P53:AA53) | AB57: =AB47/SUM(Q53:AB53) | AC57: =AC47/SUM(R53:AC53) | AD57: =AD47/SUM(S53:AD53) | AE57: =AE47/SUM(T53:AE53) | ... AY57: =AY47/SUM(AN53:AY53) | BB57: =BB47/BB53 | BC57: =BC47/BC53 | BD57: =BD47/BD53 | BF57: =BF47/BF53
B58: Corporate Level EBITDA / Cash Interest | X58: =X52/X49 | Y58: =Y52/Y49 | Z58: =Z52/Z49 | AA58: =AA52/AA49 | AB58: =AB52/AB49 | AC58: =AC52/AC49 | AD58: =AD52/AD49 | AE58: =AE52/AE49 | ... AY58: =AY52/AY49 | BB58: =IFERROR(BB52/BB49,"NA") | BC58: =IFERROR(BC52/BC49,"NA") | BD58: =IFERROR(BD52/BD49,"NA") | BF58: =IFERROR(BF52/BF49,"NA")

Sheet P&L
B2: Profit & Loss (Consolidated)
B3: Actuals Jan-Apr 2026. Forecast May 2026+ uses formulas from Sales Forecast and Assumptions.
B4: Monthly P&L
B5: Line Item | D5: Jan 2025 | E5: Feb 2025 | F5: Mar 2025 | G5: Apr 2025 | H5: May 2025 | I5: Jun 2025 | J5: Jul 2025 | K5: Aug 2025 | L5: Sep 2025 | M5: Oct 2025 | N5: Nov 2025 | O5: Dec 2025 | P5: Jan 2026 | Q5: Feb 2026 | R5: Mar 2026 | S5: Apr 2026 | T5: May 2026 | U5: Jun 2026 | V5: Jul 2026 | W5: Aug 2026 | X5: Sep 2026 | Y5: Oct 2026 | Z5: Nov 2026 | AA5: Dec 2026 | AB5: Jan 2027 | AC5: Feb 2027 | AD5: Mar 2027 | AE5: Apr 2027 | AF5: May 2027 | AG5: Jun 2027 | AH5: Jul 2027 | AI5: Aug 2027 | AJ5: Sep 2027 | AK5: Oct 2027 | AL5: Nov 2027 | AM5: Dec 2027 | AN5: Jan 2028 | AO5: Feb 2028 | AP5: Mar 2028 | AQ5: Apr 2028 | AR5: May 2028 | AS5: Jun 2028 | AT5: Jul 2028 | AU5: Aug 2028 | AV5: Sep 2028 | AW5: Oct 2028 | AX5: Nov 2028 | AY5: Dec 2028
B6: Session Revenue | D6: 444458.84 | E6: 541393.76 | F6: 704822.04 | G6: 684557.59 | H6: 741695.39 | I6: 732460.21 | J6: 728344.66 | K6: 718819.72 | L6: 720323.37 | M6: 736168.74 | N6: 706551.99 | O6: 690895.82 | P6: 1000204 | Q6: 866507.65 | R6: 867748.4 | S6: 790938.82 | T6: 807497.91 | U6: ='Sales Forecast'!U18*Assumptions!$C$12+'Sales Forecast'!T18*Assumptions!$D$12+'Sales Forecast'!S18*Assumptions!$E$12+'Sales Forecast'!R18*Assumptions!$F$12+'Sales Forecast'!Q18*Assumptions!$G$12+'Sales Forecast'!P18*Assumptions!$H$12+'Sales Forecast'!U101*Assumptions!$I$12 | V6: ='Sales Forecast'!V18*Assumptions!$C$12+'Sales Forecast'!U18*Assumptions!$D$12+'Sales Forecast'!T18*Assumptions!$E$12+'Sales Forecast'!S18*Assumptions!$F$12+'Sales Forecast'!R18*Assumptions!$G$12+'Sales Forecast'!Q18*Assumptions!$H$12+'Sales Forecast'!P18*Assumptions!$I$12 | W6: ='Sales Forecast'!W18*Assumptions!$C$12+'Sales Forecast'!V18*Assumptions!$D$12+'Sales Forecast'!U18*Assumptions!$E$12+'Sales Forecast'!T18*Assumptions!$F$12+'Sales Forecast'!S18*Assumptions!$G$12+'Sales Forecast'!R18*Assumptions!$H$12+'Sales Forecast'!Q18*Assumptions!$I$12 | X6: ='Sales Forecast'!X18*Assumptions!$C$12+'Sales Forecast'!W18*Assumptions!$D$12+'Sales Forecast'!V18*Assumptions!$E$12+'Sales Forecast'!U18*Assumptions!$F$12+'Sales Forecast'!T18*Assumptions!$G$12+'Sales Forecast'!S18*Assumptions!$H$12+'Sales Forecast'!R18*Assumptions!$I$12 | Y6: ='Sales Forecast'!Y18*Assumptions!$C$12+'Sales Forecast'!X18*Assumptions!$D$12+'Sales Forecast'!W18*Assumptions!$E$12+'Sales Forecast'!V18*Assumptions!$F$12+'Sales Forecast'!U18*Assumptions!$G$12+'Sales Forecast'!T18*Assumptions!$H$12+'Sales Forecast'!S18*Assumptions!$I$12 | Z6: ='Sales Forecast'!Z18*Assumptions!$C$12+'Sales Forecast'!Y18*Assumptions!$D$12+'Sales Forecast'!X18*Assumptions!$E$12+'Sales Forecast'!W18*Assumptions!$F$12+'Sales Forecast'!V18*Assumptions!$G$12+'Sales Forecast'!U18*Assumptions!$H$12+'Sales Forecast'!T18*Assumptions!$I$12 | AA6: ='Sales Forecast'!AA18*Assumptions!$C$12+'Sales Forecast'!Z18*Assumptions!$D$12+'Sales Forecast'!Y18*Assumptions!$E$12+'Sales Forecast'!X18*Assumptions!$F$12+'Sales Forecast'!W18*Assumptions!$G$12+'Sales Forecast'!V18*Assumptions!$H$12+'Sales Forecast'!U18*Assumptions!$I$12 | AB6: ='Sales Forecast'!AB18*Assumptions!$C$12+'Sales Forecast'!AA18*Assumptions!$D$12+'Sales Forecast'!Z18*Assumptions!$E$12+'Sales Forecast'!Y18*Assumptions!$F$12+'Sales Forecast'!X18*Assumptions!$G$12+'Sales Forecast'!W18*Assumptions!$H$12+'Sales Forecast'!V18*Assumptions!$I$12 | AC6: ='Sales Forecast'!AC18*Assumptions!$C$12+'Sales Forecast'!AB18*Assumptions!$D$12+'Sales Forecast'!AA18*Assumptions!$E$12+'Sales Forecast'!Z18*Assumptions!$F$12+'Sales Forecast'!Y18*Assumptions!$G$12+'Sales Forecast'!X18*Assumptions!$H$12+'Sales Forecast'!W18*Assumptions!$I$12 | ... AY6: ='Sales Forecast'!AY18*Assumptions!$C$12+'Sales Forecast'!AX18*Assumptions!$D$12+'Sales Forecast'!AW18*Assumptions!$E$12+'Sales Forecast'!AV18*Assumptions!$F$12+'Sales Forecast'!AU18*Assumptions!$G$12+'Sales Forecast'!AT18*Assumptions!$H$12+'Sales Forecast'!AS18*Assumptions!$I$12
B7: Breakage Revenue | D7: 75237.94 | E7: 109399.17 | F7: 140651.46 | G7: 149516.51 | H7: 181344.3 | I7: 149213.5 | J7: 157965.23 | K7: 206864.97 | L7: 213185.16 | M7: 179766.24 | N7: 238121.51 | O7: 304457.14 | P7: 139780.94 | Q7: 155452.01 | R7: 132350.01 | S7: 142563.17 | T7: 141174.57 | U7: ='Sales Forecast'!U18*Assumptions!$C$13+'Sales Forecast'!T18*Assumptions!$D$13+'Sales Forecast'!S18*Assumptions!$E$13+'Sales Forecast'!R18*Assumptions!$F$13+'Sales Forecast'!Q18*Assumptions!$G$13+'Sales Forecast'!P18*Assumptions!$H$13+'Sales Forecast'!U101*Assumptions!$I$13 | V7: ='Sales Forecast'!V18*Assumptions!$C$13+'Sales Forecast'!U18*Assumptions!$D$13+'Sales Forecast'!T18*Assumptions!$E$13+'Sales Forecast'!S18*Assumptions!$F$13+'Sales Forecast'!R18*Assumptions!$G$13+'Sales Forecast'!Q18*Assumptions!$H$13+'Sales Forecast'!P18*Assumptions!$I$13 | W7: ='Sales Forecast'!W18*Assumptions!$C$13+'Sales Forecast'!V18*Assumptions!$D$13+'Sales Forecast'!U18*Assumptions!$E$13+'Sales Forecast'!T18*Assumptions!$F$13+'Sales Forecast'!S18*Assumptions!$G$13+'Sales Forecast'!R18*Assumptions!$H$13+'Sales Forecast'!Q18*Assumptions!$I$13 | X7: ='Sales Forecast'!X18*Assumptions!$C$13+'Sales Forecast'!W18*Assumptions!$D$13+'Sales Forecast'!V18*Assumptions!$E$13+'Sales Forecast'!U18*Assumptions!$F$13+'Sales Forecast'!T18*Assumptions!$G$13+'Sales Forecast'!S18*Assumptions!$H$13+'Sales Forecast'!R18*Assumptions!$I$13 | Y7: ='Sales Forecast'!Y18*Assumptions!$C$13+'Sales Forecast'!X18*Assumptions!$D$13+'Sales Forecast'!W18*Assumptions!$E$13+'Sales Forecast'!V18*Assumptions!$F$13+'Sales Forecast'!U18*Assumptions!$G$13+'Sales Forecast'!T18*Assumptions!$H$13+'Sales Forecast'!S18*Assumptions!$I$13 | Z7: ='Sales Forecast'!Z18*Assumptions!$C$13+'Sales Forecast'!Y18*Assumptions!$D$13+'Sales Forecast'!X18*Assumptions!$E$13+'Sales Forecast'!W18*Assumptions!$F$13+'Sales Forecast'!V18*Assumptions!$G$13+'Sales Forecast'!U18*Assumptions!$H$13+'Sales Forecast'!T18*Assumptions!$I$13 | AA7: ='Sales Forecast'!AA18*Assumptions!$C$13+'Sales Forecast'!Z18*Assumptions!$D$13+'Sales Forecast'!Y18*Assumptions!$E$13+'Sales Forecast'!X18*Assumptions!$F$13+'Sales Forecast'!W18*Assumptions!$G$13+'Sales Forecast'!V18*Assumptions!$H$13+'Sales Forecast'!U18*Assumptions!$I$13 | AB7: ='Sales Forecast'!AB18*Assumptions!$C$13+'Sales Forecast'!AA18*Assumptions!$D$13+'Sales Forecast'!Z18*Assumptions!$E$13+'Sales Forecast'!Y18*Assumptions!$F$13+'Sales Forecast'!X18*Assumptions!$G$13+'Sales Forecast'!W18*Assumptions!$H$13+'Sales Forecast'!V18*Assumptions!$I$13 | AC7: ='Sales Forecast'!AC18*Assumptions!$C$13+'Sales Forecast'!AB18*Assumptions!$D$13+'Sales Forecast'!AA18*Assumptions!$E$13+'Sales Forecast'!Z18*Assumptions!$F$13+'Sales Forecast'!Y18*Assumptions!$G$13+'Sales Forecast'!X18*Assumptions!$H$13+'Sales Forecast'!W18*Assumptions!$I$13 | ... AY7: ='Sales Forecast'!AY18*Assumptions!$C$13+'Sales Forecast'!AX18*Assumptions!$D$13+'Sales Forecast'!AW18*Assumptions!$E$13+'Sales Forecast'!AV18*Assumptions!$F$13+'Sales Forecast'!AU18*Assumptions!$G$13+'Sales Forecast'!AT18*Assumptions!$H$13+'Sales Forecast'!AS18*Assumptions!$I$13
B8: Retail Sales | D8: 20273 | E8: 19453.92 | F8: 17164.03 | G8: 18478 | H8: 19384 | I8: 28826 | J8: 20010 | K8: 19175 | L8: 19247.98 | M8: 19640 | N8: 21643.2 | O8: 20189 | P8: 23308 | Q8: 19847 | R8: 17655 | S8: 18479 | T8: 13825.81 | U8: ='BK P&L'!U18+'CC P&L'!U18+'DN P&L'!U18+'LF P&L'!U18+'MR P&L'!U18+'OP P&L'!U18+'PH P&L'!U18+'RH P&L'!U18+'SB P&L'!U18+'SM P&L'!U18+'WP P&L'!U18+'WW P&L'!U18 | V8: ='BK P&L'!V18+'CC P&L'!V18+'DN P&L'!V18+'LF P&L'!V18+'MR P&L'!V18+'OP P&L'!V18+'PH P&L'!V18+'RH P&L'!V18+'SB P&L'!V18+'SM P&L'!V18+'WP P&L'!V18+'WW P&L'!V18 | W8: ='BK P&L'!W18+'CC P&L'!W18+'DN P&L'!W18+'LF P&L'!W18+'MR P&L'!W18+'OP P&L'!W18+'PH P&L'!W18+'RH P&L'!W18+'SB P&L'!W18+'SM P&L'!W18+'WP P&L'!W18+'WW P&L'!W18 | X8: ='BK P&L'!X18+'CC P&L'!X18+'DN P&L'!X18+'LF P&L'!X18+'MR P&L'!X18+'OP P&L'!X18+'PH P&L'!X18+'RH P&L'!X18+'SB P&L'!X18+'SM P&L'!X18+'WP P&L'!X18+'WW P&L'!X18 | Y8: ='BK P&L'!Y18+'CC P&L'!Y18+'DN P&L'!Y18+'LF P&L'!Y18+'MR P&L'!Y18+'OP P&L'!Y18+'PH P&L'!Y18+'RH P&L'!Y18+'SB P&L'!Y18+'SM P&L'!Y18+'WP P&L'!Y18+'WW P&L'!Y18 | Z8: ='BK P&L'!Z18+'CC P&L'!Z18+'DN P&L'!Z18+'LF P&L'!Z18+'MR P&L'!Z18+'OP P&L'!Z18+'PH P&L'!Z18+'RH P&L'!Z18+'SB P&L'!Z18+'SM P&L'!Z18+'WP P&L'!Z18+'WW P&L'!Z18 | AA8: ='BK P&L'!AA18+'CC P&L'!AA18+'DN P&L'!AA18+'LF P&L'!AA18+'MR P&L'!AA18+'OP P&L'!AA18+'PH P&L'!AA18+'RH P&L'!AA18+'SB P&L'!AA18+'SM P&L'!AA18+'WP P&L'!AA18+'WW P&L'!AA18 | AB8: ='BK P&L'!AB18+'CC P&L'!AB18+'DN P&L'!AB18+'LF P&L'!AB18+'MR P&L'!AB18+'OP P&L'!AB18+'PH P&L'!AB18+'RH P&L'!AB18+'SB P&L'!AB18+'SM P&L'!AB18+'WP P&L'!AB18+'WW P&L'!AB18 | ... AM8: ='BK P&L'!AM18+'CC P&L'!AM18+'DN P&L'!AM18+'LF P&L'!AM18+'MR P&L'!AM18+'OP P&L'!AM18+'PH P&L'!AM18+'RH P&L'!AM18+'SB P&L'!AM18+'SM P&L'!AM18+'WP P&L'!AM18+'WW P&L'!AM18 | AN8: 16653.27 | AO8: 16653.27 | AP8: 16653.27 | AQ8: 16653.27 | AR8: 16653.27 | AS8: 16653.27 | AT8: 16653.27 | AU8: 16653.27 | AV8: 16653.27 | AW8: 16653.27 | AX8: 16653.27 | AY8: 16653.27
B9: Refunds | D9: -16377.01 | E9: -10335.55 | F9: -14180.05 | G9: -17645.51 | H9: -12735.29 | I9: -10897.91 | J9: -13385.21 | K9: -12377.04 | L9: -18282.51 | M9: -22049.66 | N9: -15320.98 | O9: -18935.02 | P9: -20830.24 | Q9: -15645.66 | R9: -16880.65 | S9: -12793.11 | T9: -9390.21 | U9: =(U6+U7)*Assumptions!$C$17 | V9: =(V6+V7)*Assumptions!$C$17 | W9: =(W6+W7)*Assumptions!$C$17 | X9: =(X6+X7)*Assumptions!$C$17 | Y9: =(Y6+Y7)*Assumptions!$C$17 | Z9: =(Z6+Z7)*Assumptions!$C$17 | AA9: =(AA6+AA7)*Assumptions!$C$17 | AB9: =(AB6+AB7)*Assumptions!$C$17 | ... AY9: =(AY6+AY7)*Assumptions!$C$17
B10: Discounts | D10: -73972.55 | E10: -63470.28 | F10: -69852.24 | G10: -68577.95 | H10: -75810.5 | I10: -59569.88 | J10: -56128.38 | K10: -56204.78 | L10: -59582.4 | M10: -54374.17 | N10: -48649.06 | O10: -54144.13 | P10: -59600.85 | Q10: -56707.91 | R10: -53962.12 | S10: -51310.18 | T10: -35101.57 | U10: =(U6+U7)*Assumptions!$C$18 | V10: =(V6+V7)*Assumptions!$C$18 | W10: =(W6+W7)*Assumptions!$C$18 | X10: =(X6+X7)*Assumptions!$C$18 | Y10: =(Y6+Y7)*Assumptions!$C$18 | Z10: =(Z6+Z7)*Assumptions!$C$18 | AA10: =(AA6+AA7)*Assumptions!$C$18 | AB10: =(AB6+AB7)*Assumptions!$C$18 | ... AY10: =(AY6+AY7)*Assumptions!$C$18
B11: Total Revenue | D11: 629355.56 | E11: 695448.39 | F11: 845088.61 | G11: 803508.37 | H11: 877719.53 | I11: 853012.79 | J11: 844889.73 | K11: 882190.18 | L11: 877190.19 | M11: 861368.93 | N11: 903526.46 | O11: 943564.31 | P11: 1082861.8 | Q11: 969453.09 | R11: 946910.64 | S11: 887877.7 | T11: 918006.51 | U11: =U6+U7+U8+U9+U10 | V11: =V6+V7+V8+V9+V10 | W11: =W6+W7+W8+W9+W10 | X11: =X6+X7+X8+X9+X10 | Y11: =Y6+Y7+Y8+Y9+Y10 | Z11: =Z6+Z7+Z8+Z9+Z10 | AA11: =AA6+AA7+AA8+AA9+AA10 | AB11: =AB6+AB7+AB8+AB9+AB10 | ... AY11: =AY6+AY7+AY8+AY9+AY10
B12: COGS & Merchant Fees | P12: 38009.85 | Q12: 38497.03 | R12: 34960.53 | S12: 36936.49 | T12: 27088.66 | U12: =U11*(Assumptions!$C$19+Assumptions!$C$20) | V12: =V11*(Assumptions!$C$19+Assumptions!$C$20) | W12: =W11*(Assumptions!$C$19+Assumptions!$C$20) | X12: =X11*(Assumptions!$C$19+Assumptions!$C$20) | Y12: =Y11*(Assumptions!$C$19+Assumptions!$C$20) | Z12: =Z11*(Assumptions!$C$19+Assumptions!$C$20) | AA12: =AA11*(Assumptions!$C$19+Assumptions!$C$20) | AB12: =AB11*(Assumptions!$C$19+Assumptions!$C$20) | ... AY12: =AY11*(Assumptions!$C$19+Assumptions!$C$20)
B13: Gross Profit | D13: 587714.4 | E13: 664601.97 | F13: 810233.79 | G13: 766400.55 | H13: 846558.9 | I13: 817869.28 | J13: 811691.7 | K13: 847262.55 | L13: 844736.53 | M13: 829313.19 | N13: 869551.4 | O13: 888842.62 | P13: 1044852 | Q13: 930956.06 | R13: 911950.11 | S13: 850941.21 | T13: 890917.85 | U13: =U11-U12 | V13: =V11-V12 | W13: =W11-W12 | X13: =X11-X12 | Y13: =Y11-Y12 | Z13: =Z11-Z12 | AA13: =AA11-AA12 | AB13: =AB11-AB12 | ... AY13: =AY11-AY12
B14: Marketing | D14: 19034.32 | E14: 17063.4 | F14: 25178.17 | G14: 17943.65 | H14: 25913.01 | I14: 34869.84 | J14: 23544.8 | K14: 25878.64 | L14: 30151.1 | M14: 31586.11 | N14: 40588.79 | O14: 31249.9 | P14: 27740.18 | Q14: 27007.49 | R14: 16681.8 | S14: 5975.58 | T14: 5982.17 | U14: ='BK P&L'!U33+'CC P&L'!U33+'DN P&L'!U33+'LF P&L'!U33+'MR P&L'!U33+'OP P&L'!U33+'PH P&L'!U33+'RH P&L'!U33+'SB P&L'!U33+'SM P&L'!U33+'WP P&L'!U33+'WW P&L'!U33+'HO P&L'!U12 | V14: ='BK P&L'!V33+'CC P&L'!V33+'DN P&L'!V33+'LF P&L'!V33+'MR P&L'!V33+'OP P&L'!V33+'PH P&L'!V33+'RH P&L'!V33+'SB P&L'!V33+'SM P&L'!V33+'WP P&L'!V33+'WW P&L'!V33+'HO P&L'!V12 | W14: ='BK P&L'!W33+'CC P&L'!W33+'DN P&L'!W33+'LF P&L'!W33+'MR P&L'!W33+'OP P&L'!W33+'PH P&L'!W33+'RH P&L'!W33+'SB P&L'!W33+'SM P&L'!W33+'WP P&L'!W33+'WW P&L'!W33+'HO P&L'!W12 | X14: ='BK P&L'!X33+'CC P&L'!X33+'DN P&L'!X33+'LF P&L'!X33+'MR P&L'!X33+'OP P&L'!X33+'PH P&L'!X33+'RH P&L'!X33+'SB P&L'!X33+'SM P&L'!X33+'WP P&L'!X33+'WW P&L'!X33+'HO P&L'!X12 | Y14: ='BK P&L'!Y33+'CC P&L'!Y33+'DN P&L'!Y33+'LF P&L'!Y33+'MR P&L'!Y33+'OP P&L'!Y33+'PH P&L'!Y33+'RH P&L'!Y33+'SB P&L'!Y33+'SM P&L'!Y33+'WP P&L'!Y33+'WW P&L'!Y33+'HO P&L'!Y12 | Z14: ='BK P&L'!Z33+'CC P&L'!Z33+'DN P&L'!Z33+'LF P&L'!Z33+'MR P&L'!Z33+'OP P&L'!Z33+'PH P&L'!Z33+'RH P&L'!Z33+'SB P&L'!Z33+'SM P&L'!Z33+'WP P&L'!Z33+'WW P&L'!Z33+'HO P&L'!Z12 | AA14: ='BK P&L'!AA33+'CC P&L'!AA33+'DN P&L'!AA33+'LF P&L'!AA33+'MR P&L'!AA33+'OP P&L'!AA33+'PH P&L'!AA33+'RH P&L'!AA33+'SB P&L'!AA33+'SM P&L'!AA33+'WP P&L'!AA33+'WW P&L'!AA33+'HO P&L'!AA12 | AB14: ='BK P&L'!AB33+'CC P&L'!AB33+'DN P&L'!AB33+'LF P&L'!AB33+'MR P&L'!AB33+'OP P&L'!AB33+'PH P&L'!AB33+'RH P&L'!AB33+'SB P&L'!AB33+'SM P&L'!AB33+'WP P&L'!AB33+'WW P&L'!AB33+'HO P&L'!AB12 | ... AY14: ='BK P&L'!AY33+'CC P&L'!AY33+'DN P&L'!AY33+'LF P&L'!AY33+'MR P&L'!AY33+'OP P&L'!AY33+'PH P&L'!AY33+'RH P&L'!AY33+'SB P&L'!AY33+'SM P&L'!AY33+'WP P&L'!AY33+'WW P&L'!AY33+'HO P&L'!AY12
B15: Payroll | D15: 419319.36 | E15: 423621.65 | F15: 479539.11 | G15: 456441.26 | H15: 558270.32 | I15: 533362.29 | J15: 551786.76 | K15: 563606.75 | L15: 576144.94 | M15: 597447.09 | N15: 566914.01 | O15: 601056.92 | P15: 681232.98 | Q15: 590412.06 | R15: 628953.81 | S15: 576480.98 | T15: 589210.62 | U15: ='BK P&L'!U38+'CC P&L'!U38+'DN P&L'!U38+'LF P&L'!U38+'MR P&L'!U38+'OP P&L'!U38+'PH P&L'!U38+'RH P&L'!U38+'SB P&L'!U38+'SM P&L'!U38+'WP P&L'!U38+'WW P&L'!U38+'HO P&L'!U17 | V15: ='BK P&L'!V38+'CC P&L'!V38+'DN P&L'!V38+'LF P&L'!V38+'MR P&L'!V38+'OP P&L'!V38+'PH P&L'!V38+'RH P&L'!V38+'SB P&L'!V38+'SM P&L'!V38+'WP P&L'!V38+'WW P&L'!V38+'HO P&L'!V17 | W15: ='BK P&L'!W38+'CC P&L'!W38+'DN P&L'!W38+'LF P&L'!W38+'MR P&L'!W38+'OP P&L'!W38+'PH P&L'!W38+'RH P&L'!W38+'SB P&L'!W38+'SM P&L'!W38+'WP P&L'!W38+'WW P&L'!W38+'HO P&L'!W17 | X15: ='BK P&L'!X38+'CC P&L'!X38+'DN P&L'!X38+'LF P&L'!X38+'MR P&L'!X38+'OP P&L'!X38+'PH P&L'!X38+'RH P&L'!X38+'SB P&L'!X38+'SM P&L'!X38+'WP P&L'!X38+'WW P&L'!X38+'HO P&L'!X17 | Y15: ='BK P&L'!Y38+'CC P&L'!Y38+'DN P&L'!Y38+'LF P&L'!Y38+'MR P&L'!Y38+'OP P&L'!Y38+'PH P&L'!Y38+'RH P&L'!Y38+'SB P&L'!Y38+'SM P&L'!Y38+'WP P&L'!Y38+'WW P&L'!Y38+'HO P&L'!Y17 | Z15: ='BK P&L'!Z38+'CC P&L'!Z38+'DN P&L'!Z38+'LF P&L'!Z38+'MR P&L'!Z38+'OP P&L'!Z38+'PH P&L'!Z38+'RH P&L'!Z38+'SB P&L'!Z38+'SM P&L'!Z38+'WP P&L'!Z38+'WW P&L'!Z38+'HO P&L'!Z17 | AA15: ='BK P&L'!AA38+'CC P&L'!AA38+'DN P&L'!AA38+'LF P&L'!AA38+'MR P&L'!AA38+'OP P&L'!AA38+'PH P&L'!AA38+'RH P&L'!AA38+'SB P&L'!AA38+'SM P&L'!AA38+'WP P&L'!AA38+'WW P&L'!AA38+'HO P&L'!AA17 | AB15: ='BK P&L'!AB38+'CC P&L'!AB38+'DN P&L'!AB38+'LF P&L'!AB38+'MR P&L'!AB38+'OP P&L'!AB38+'PH P&L'!AB38+'RH P&L'!AB38+'SB P&L'!AB38+'SM P&L'!AB38+'WP P&L'!AB38+'WW P&L'!AB38+'HO P&L'!AB17 | ... AY15: ='BK P&L'!AY38+'CC P&L'!AY38+'DN P&L'!AY38+'LF P&L'!AY38+'MR P&L'!AY38+'OP P&L'!AY38+'PH P&L'!AY38+'RH P&L'!AY38+'SB P&L'!AY38+'SM P&L'!AY38+'WP P&L'!AY38+'WW P&L'!AY38+'HO P&L'!AY17
B16: Software | D16: 14252.66 | E16: 8816.29 | F16: 10929.2 | G16: 12816.7 | H16: 13026.09 | I16: 12037.55 | J16: 10467.78 | K16: 14382.58 | L16: 12170.58 | M16: 13845.85 | N16: 13927.97 | O16: 15405.24 | P16: 14854.43 | Q16: 23709.03 | R16: 10924.01 | S16: 13421.72 | T16: 14118.08 | U16: ='BK P&L'!U42+'CC P&L'!U42+'DN P&L'!U42+'LF P&L'!U42+'MR P&L'!U42+'OP P&L'!U42+'PH P&L'!U42+'RH P&L'!U42+'SB P&L'!U42+'SM P&L'!U42+'WP P&L'!U42+'WW P&L'!U42+'HO P&L'!U22 | V16: ='BK P&L'!V42+'CC P&L'!V42+'DN P&L'!V42+'LF P&L'!V42+'MR P&L'!V42+'OP P&L'!V42+'PH P&L'!V42+'RH P&L'!V42+'SB P&L'!V42+'SM P&L'!V42+'WP P&L'!V42+'WW P&L'!V42+'HO P&L'!V22 | W16: ='BK P&L'!W42+'CC P&L'!W42+'DN P&L'!W42+'LF P&L'!W42+'MR P&L'!W42+'OP P&L'!W42+'PH P&L'!W42+'RH P&L'!W42+'SB P&L'!W42+'SM P&L'!W42+'WP P&L'!W42+'WW P&L'!W42+'HO P&L'!W22 | X16: ='BK P&L'!X42+'CC P&L'!X42+'DN P&L'!X42+'LF P&L'!X42+'MR P&L'!X42+'OP P&L'!X42+'PH P&L'!X42+'RH P&L'!X42+'SB P&L'!X42+'SM P&L'!X42+'WP P&L'!X42+'WW P&L'!X42+'HO P&L'!X22 | Y16: ='BK P&L'!Y42+'CC P&L'!Y42+'DN P&L'!Y42+'LF P&L'!Y42+'MR P&L'!Y42+'OP P&L'!Y42+'PH P&L'!Y42+'RH P&L'!Y42+'SB P&L'!Y42+'SM P&L'!Y42+'WP P&L'!Y42+'WW P&L'!Y42+'HO P&L'!Y22 | Z16: ='BK P&L'!Z42+'CC P&L'!Z42+'DN P&L'!Z42+'LF P&L'!Z42+'MR P&L'!Z42+'OP P&L'!Z42+'PH P&L'!Z42+'RH P&L'!Z42+'SB P&L'!Z42+'SM P&L'!Z42+'WP P&L'!Z42+'WW P&L'!Z42+'HO P&L'!Z22 | AA16: ='BK P&L'!AA42+'CC P&L'!AA42+'DN P&L'!AA42+'LF P&L'!AA42+'MR P&L'!AA42+'OP P&L'!AA42+'PH P&L'!AA42+'RH P&L'!AA42+'SB P&L'!AA42+'SM P&L'!AA42+'WP P&L'!AA42+'WW P&L'!AA42+'HO P&L'!AA22 | AB16: ='BK P&L'!AB42+'CC P&L'!AB42+'DN P&L'!AB42+'LF P&L'!AB42+'MR P&L'!AB42+'OP P&L'!AB42+'PH P&L'!AB42+'RH P&L'!AB42+'SB P&L'!AB42+'SM P&L'!AB42+'WP P&L'!AB42+'WW P&L'!AB42+'HO P&L'!AB22 | ... AY16: ='BK P&L'!AY42+'CC P&L'!AY42+'DN P&L'!AY42+'LF P&L'!AY42+'MR P&L'!AY42+'OP P&L'!AY42+'PH P&L'!AY42+'RH P&L'!AY42+'SB P&L'!AY42+'SM P&L'!AY42+'WP P&L'!AY42+'WW P&L'!AY42+'HO P&L'!AY22
B17: Professional Fees | D17: 12762.86 | E17: 6986.62 | F17: 6754.78 | G17: 2824.89 | H17: 14193.46 | I17: 28217.6 | J17: 16267.87 | K17: 22546.69 | L17: 25022.6 | M17: 59823.54 | N17: 47681.74 | O17: 59459.49 | P17: 42733.79 | Q17: 24202.3 | R17: 22556.84 | S17: 25366 | T17: 30273 | U17: ='BK P&L'!U47+'CC P&L'!U47+'DN P&L'!U47+'LF P&L'!U47+'MR P&L'!U47+'OP P&L'!U47+'PH P&L'!U47+'RH P&L'!U47+'SB P&L'!U47+'SM P&L'!U47+'WP P&L'!U47+'WW P&L'!U47+'HO P&L'!U27 | V17: ='BK P&L'!V47+'CC P&L'!V47+'DN P&L'!V47+'LF P&L'!V47+'MR P&L'!V47+'OP P&L'!V47+'PH P&L'!V47+'RH P&L'!V47+'SB P&L'!V47+'SM P&L'!V47+'WP P&L'!V47+'WW P&L'!V47+'HO P&L'!V27 | W17: ='BK P&L'!W47+'CC P&L'!W47+'DN P&L'!W47+'LF P&L'!W47+'MR P&L'!W47+'OP P&L'!W47+'PH P&L'!W47+'RH P&L'!W47+'SB P&L'!W47+'SM P&L'!W47+'WP P&L'!W47+'WW P&L'!W47+'HO P&L'!W27 | X17: ='BK P&L'!X47+'CC P&L'!X47+'DN P&L'!X47+'LF P&L'!X47+'MR P&L'!X47+'OP P&L'!X47+'PH P&L'!X47+'RH P&L'!X47+'SB P&L'!X47+'SM P&L'!X47+'WP P&L'!X47+'WW P&L'!X47+'HO P&L'!X27 | Y17: ='BK P&L'!Y47+'CC P&L'!Y47+'DN P&L'!Y47+'LF P&L'!Y47+'MR P&L'!Y47+'OP P&L'!Y47+'PH P&L'!Y47+'RH P&L'!Y47+'SB P&L'!Y47+'SM P&L'!Y47+'WP P&L'!Y47+'WW P&L'!Y47+'HO P&L'!Y27 | Z17: ='BK P&L'!Z47+'CC P&L'!Z47+'DN P&L'!Z47+'LF P&L'!Z47+'MR P&L'!Z47+'OP P&L'!Z47+'PH P&L'!Z47+'RH P&L'!Z47+'SB P&L'!Z47+'SM P&L'!Z47+'WP P&L'!Z47+'WW P&L'!Z47+'HO P&L'!Z27 | AA17: ='BK P&L'!AA47+'CC P&L'!AA47+'DN P&L'!AA47+'LF P&L'!AA47+'MR P&L'!AA47+'OP P&L'!AA47+'PH P&L'!AA47+'RH P&L'!AA47+'SB P&L'!AA47+'SM P&L'!AA47+'WP P&L'!AA47+'WW P&L'!AA47+'HO P&L'!AA27 | AB17: ='BK P&L'!AB47+'CC P&L'!AB47+'DN P&L'!AB47+'LF P&L'!AB47+'MR P&L'!AB47+'OP P&L'!AB47+'PH P&L'!AB47+'RH P&L'!AB47+'SB P&L'!AB47+'SM P&L'!AB47+'WP P&L'!AB47+'WW P&L'!AB47+'HO P&L'!AB27 | ... AY17: ='BK P&L'!AY47+'CC P&L'!AY47+'DN P&L'!AY47+'LF P&L'!AY47+'MR P&L'!AY47+'OP P&L'!AY47+'PH P&L'!AY47+'RH P&L'!AY47+'SB P&L'!AY47+'SM P&L'!AY47+'WP P&L'!AY47+'WW P&L'!AY47+'HO P&L'!AY27
B18: Utilities | D18: 3290.78 | E18: 5292.9 | F18: 4950.78 | G18: 5342.61 | H18: 5724.64 | I18: 5320.05 | J18: 5193.56 | K18: 7807.63 | L18: 8276.28 | M18: 8293.94 | N18: 9023.46 | O18: 7849.86 | P18: 7087.42 | Q18: 9973.09 | R18: 7034.72 | S18: 7270.22 | T18: 7128.54 | U18: ='BK P&L'!U56+'CC P&L'!U56+'DN P&L'!U56+'LF P&L'!U56+'MR P&L'!U56+'OP P&L'!U56+'PH P&L'!U56+'RH P&L'!U56+'SB P&L'!U56+'SM P&L'!U56+'WP P&L'!U56+'WW P&L'!U56 | V18: ='BK P&L'!V56+'CC P&L'!V56+'DN P&L'!V56+'LF P&L'!V56+'MR P&L'!V56+'OP P&L'!V56+'PH P&L'!V56+'RH P&L'!V56+'SB P&L'!V56+'SM P&L'!V56+'WP P&L'!V56+'WW P&L'!V56 | W18: ='BK P&L'!W56+'CC P&L'!W56+'DN P&L'!W56+'LF P&L'!W56+'MR P&L'!W56+'OP P&L'!W56+'PH P&L'!W56+'RH P&L'!W56+'SB P&L'!W56+'SM P&L'!W56+'WP P&L'!W56+'WW P&L'!W56 | X18: ='BK P&L'!X56+'CC P&L'!X56+'DN P&L'!X56+'LF P&L'!X56+'MR P&L'!X56+'OP P&L'!X56+'PH P&L'!X56+'RH P&L'!X56+'SB P&L'!X56+'SM P&L'!X56+'WP P&L'!X56+'WW P&L'!X56 | Y18: ='BK P&L'!Y56+'CC P&L'!Y56+'DN P&L'!Y56+'LF P&L'!Y56+'MR P&L'!Y56+'OP P&L'!Y56+'PH P&L'!Y56+'RH P&L'!Y56+'SB P&L'!Y56+'SM P&L'!Y56+'WP P&L'!Y56+'WW P&L'!Y56 | Z18: ='BK P&L'!Z56+'CC P&L'!Z56+'DN P&L'!Z56+'LF P&L'!Z56+'MR P&L'!Z56+'OP P&L'!Z56+'PH P&L'!Z56+'RH P&L'!Z56+'SB P&L'!Z56+'SM P&L'!Z56+'WP P&L'!Z56+'WW P&L'!Z56 | AA18: ='BK P&L'!AA56+'CC P&L'!AA56+'DN P&L'!AA56+'LF P&L'!AA56+'MR P&L'!AA56+'OP P&L'!AA56+'PH P&L'!AA56+'RH P&L'!AA56+'SB P&L'!AA56+'SM P&L'!AA56+'WP P&L'!AA56+'WW P&L'!AA56 | AB18: ='BK P&L'!AB56+'CC P&L'!AB56+'DN P&L'!AB56+'LF P&L'!AB56+'MR P&L'!AB56+'OP P&L'!AB56+'PH P&L'!AB56+'RH P&L'!AB56+'SB P&L'!AB56+'SM P&L'!AB56+'WP P&L'!AB56+'WW P&L'!AB56 | ... AY18: ='BK P&L'!AY56+'CC P&L'!AY56+'DN P&L'!AY56+'LF P&L'!AY56+'MR P&L'!AY56+'OP P&L'!AY56+'PH P&L'!AY56+'RH P&L'!AY56+'SB P&L'!AY56+'SM P&L'!AY56+'WP P&L'!AY56+'WW P&L'!AY56
B19: Property Costs | D19: 109746.49 | E19: 96893.54 | F19: 108142.11 | G19: 115917.92 | H19: 114881.56 | I19: 116880.2 | J19: 119885.67 | K19: 130853.31 | L19: 139047 | M19: 145628.28 | N19: 161382.55 | O19: 146607.13 | P19: 147113.46 | Q19: 146344.65 | R19: 147382.66 | S19: 148059.43 | T19: 149341.42 | U19: ='BK P&L'!U61+'CC P&L'!U61+'DN P&L'!U61+'LF P&L'!U61+'MR P&L'!U61+'OP P&L'!U61+'PH P&L'!U61+'RH P&L'!U61+'SB P&L'!U61+'SM P&L'!U61+'WP P&L'!U61+'WW P&L'!U61+'HO P&L'!U32 | V19: ='BK P&L'!V61+'CC P&L'!V61+'DN P&L'!V61+'LF P&L'!V61+'MR P&L'!V61+'OP P&L'!V61+'PH P&L'!V61+'RH P&L'!V61+'SB P&L'!V61+'SM P&L'!V61+'WP P&L'!V61+'WW P&L'!V61+'HO P&L'!V32 | W19: ='BK P&L'!W61+'CC P&L'!W61+'DN P&L'!W61+'LF P&L'!W61+'MR P&L'!W61+'OP P&L'!W61+'PH P&L'!W61+'RH P&L'!W61+'SB P&L'!W61+'SM P&L'!W61+'WP P&L'!W61+'WW P&L'!W61+'HO P&L'!W32 | X19: ='BK P&L'!X61+'CC P&L'!X61+'DN P&L'!X61+'LF P&L'!X61+'MR P&L'!X61+'OP P&L'!X61+'PH P&L'!X61+'RH P&L'!X61+'SB P&L'!X61+'SM P&L'!X61+'WP P&L'!X61+'WW P&L'!X61+'HO P&L'!X32 | Y19: ='BK P&L'!Y61+'CC P&L'!Y61+'DN P&L'!Y61+'LF P&L'!Y61+'MR P&L'!Y61+'OP P&L'!Y61+'PH P&L'!Y61+'RH P&L'!Y61+'SB P&L'!Y61+'SM P&L'!Y61+'WP P&L'!Y61+'WW P&L'!Y61+'HO P&L'!Y32 | Z19: ='BK P&L'!Z61+'CC P&L'!Z61+'DN P&L'!Z61+'LF P&L'!Z61+'MR P&L'!Z61+'OP P&L'!Z61+'PH P&L'!Z61+'RH P&L'!Z61+'SB P&L'!Z61+'SM P&L'!Z61+'WP P&L'!Z61+'WW P&L'!Z61+'HO P&L'!Z32 | AA19: ='BK P&L'!AA61+'CC P&L'!AA61+'DN P&L'!AA61+'LF P&L'!AA61+'MR P&L'!AA61+'OP P&L'!AA61+'PH P&L'!AA61+'RH P&L'!AA61+'SB P&L'!AA61+'SM P&L'!AA61+'WP P&L'!AA61+'WW P&L'!AA61+'HO P&L'!AA32 | AB19: ='BK P&L'!AB61+'CC P&L'!AB61+'DN P&L'!AB61+'LF P&L'!AB61+'MR P&L'!AB61+'OP P&L'!AB61+'PH P&L'!AB61+'RH P&L'!AB61+'SB P&L'!AB61+'SM P&L'!AB61+'WP P&L'!AB61+'WW P&L'!AB61+'HO P&L'!AB32 | ... AY19: ='BK P&L'!AY61+'CC P&L'!AY61+'DN P&L'!AY61+'LF P&L'!AY61+'MR P&L'!AY61+'OP P&L'!AY61+'PH P&L'!AY61+'RH P&L'!AY61+'SB P&L'!AY61+'SM P&L'!AY61+'WP P&L'!AY61+'WW P&L'!AY61+'HO P&L'!AY32
B20: HO Other (Util+Fin) | P20: 0 | Q20: 0 | R20: 0 | S20: 0 | T20: 1193.14 | U20: 1193.14 | V20: 1193.14 | W20: 1193.14 | X20: 1193.14 | Y20: 1193.14 | Z20: 1193.14 | AA20: 1193.14 | AB20: 1193.14 | AC20: 1193.14 | AD20: 1193.14 | AE20: 1193.14 | AF20: 1193.14 | AG20: 1193.14 | AH20: 1193.14 | AI20: 1193.14 | AJ20: 1193.14 | AK20: 1193.14 | AL20: 1193.14 | AM20: 1193.14 | AN20: 1193.14 | AO20: 1193.14 | AP20: 0 | AQ20: 0 | AR20: 0 | AS20: 0 | AT20: 0 | AU20: 0 | AV20: 0 | AW20: 0 | AX20: 0 | AY20: 0
B21: Total Operating Expenses | D21: 598853.02 | E21: 591281.77 | F21: 661491.6 | G21: 644054.36 | H21: 760286.58 | I21: 785644.31 | J21: 759734.38 | K21: 802009.51 | L21: 834091.69 | M21: 910855.68 | N21: 885287.73 | O21: 893553.72 | P21: 945487.67 | Q21: 846207.66 | R21: 863798.35 | S21: 797830.67 | T21: 817186.31 | U21: =U14+U15+U16+U17+U18+U19+U20 | V21: =V14+V15+V16+V17+V18+V19+V20 | W21: =W14+W15+W16+W17+W18+W19+W20 | X21: =X14+X15+X16+X17+X18+X19+X20 | Y21: =Y14+Y15+Y16+Y17+Y18+Y19+Y20 | Z21: =Z14+Z15+Z16+Z17+Z18+Z19+Z20 | AA21: =AA14+AA15+AA16+AA17+AA18+AA19+AA20 | AB21: =AB14+AB15+AB16+AB17+AB18+AB19+AB20 | ... AY21: =AY14+AY15+AY16+AY17+AY18+AY19+AY20
B22: Net Operating Income | D22: -11138.62 | E22: 73320.2 | F22: 148742.19 | G22: 122346.19 | H22: 86272.32 | I22: 32224.97 | J22: 51957.32 | K22: 45253.04 | L22: 10644.84 | M22: -81542.49 | N22: -15736.33 | O22: -4711.1 | P22: 99364.32 | Q22: 84748.4 | R22: 48151.76 | S22: 53110.54 | T22: 73731.54 | U22: =U13-U21 | V22: =V13-V21 | W22: =W13-W21 | X22: =X13-X21 | Y22: =Y13-Y21 | Z22: =Z13-Z21 | AA22: =AA13-AA21 | AB22: =AB13-AB21 | ... AY22: =AY13-AY21
B23: Depreciation | D23: 15294.91 | E23: 17544.5 | F23: 17656.42 | G23: 19776.91 | H23: 19918.2 | I23: 23461.73 | J23: 23564.06 | K23: 24731.79 | L23: 28257.89 | M23: 30554.12 | N23: 31457.54 | O23: 18346.69 | P23: 30633.94 | Q23: 30665.6 | R23: 30876.78 | S23: 30893.75 | T23: 30876.78 | U23: ='BK P&L'!U65+'CC P&L'!U65+'DN P&L'!U65+'LF P&L'!U65+'MR P&L'!U65+'OP P&L'!U65+'PH P&L'!U65+'RH P&L'!U65+'SB P&L'!U65+'SM P&L'!U65+'WP P&L'!U65+'WW P&L'!U65+'HO P&L'!U38 | V23: ='BK P&L'!V65+'CC P&L'!V65+'DN P&L'!V65+'LF P&L'!V65+'MR P&L'!V65+'OP P&L'!V65+'PH P&L'!V65+'RH P&L'!V65+'SB P&L'!V65+'SM P&L'!V65+'WP P&L'!V65+'WW P&L'!V65+'HO P&L'!V38 | W23: ='BK P&L'!W65+'CC P&L'!W65+'DN P&L'!W65+'LF P&L'!W65+'MR P&L'!W65+'OP P&L'!W65+'PH P&L'!W65+'RH P&L'!W65+'SB P&L'!W65+'SM P&L'!W65+'WP P&L'!W65+'WW P&L'!W65+'HO P&L'!W38 | X23: ='BK P&L'!X65+'CC P&L'!X65+'DN P&L'!X65+'LF P&L'!X65+'MR P&L'!X65+'OP P&L'!X65+'PH P&L'!X65+'RH P&L'!X65+'SB P&L'!X65+'SM P&L'!X65+'WP P&L'!X65+'WW P&L'!X65+'HO P&L'!X38 | Y23: ='BK P&L'!Y65+'CC P&L'!Y65+'DN P&L'!Y65+'LF P&L'!Y65+'MR P&L'!Y65+'OP P&L'!Y65+'PH P&L'!Y65+'RH P&L'!Y65+'SB P&L'!Y65+'SM P&L'!Y65+'WP P&L'!Y65+'WW P&L'!Y65+'HO P&L'!Y38 | Z23: ='BK P&L'!Z65+'CC P&L'!Z65+'DN P&L'!Z65+'LF P&L'!Z65+'MR P&L'!Z65+'OP P&L'!Z65+'PH P&L'!Z65+'RH P&L'!Z65+'SB P&L'!Z65+'SM P&L'!Z65+'WP P&L'!Z65+'WW P&L'!Z65+'HO P&L'!Z38 | AA23: ='BK P&L'!AA65+'CC P&L'!AA65+'DN P&L'!AA65+'LF P&L'!AA65+'MR P&L'!AA65+'OP P&L'!AA65+'PH P&L'!AA65+'RH P&L'!AA65+'SB P&L'!AA65+'SM P&L'!AA65+'WP P&L'!AA65+'WW P&L'!AA65+'HO P&L'!AA38 | AB23: ='BK P&L'!AB65+'CC P&L'!AB65+'DN P&L'!AB65+'LF P&L'!AB65+'MR P&L'!AB65+'OP P&L'!AB65+'PH P&L'!AB65+'RH P&L'!AB65+'SB P&L'!AB65+'SM P&L'!AB65+'WP P&L'!AB65+'WW P&L'!AB65+'HO P&L'!AB38 | ... AM23: ='BK P&L'!AM65+'CC P&L'!AM65+'DN P&L'!AM65+'LF P&L'!AM65+'MR P&L'!AM65+'OP P&L'!AM65+'PH P&L'!AM65+'RH P&L'!AM65+'SB P&L'!AM65+'SM P&L'!AM65+'WP P&L'!AM65+'WW P&L'!AM65+'HO P&L'!AM38 | AN23: 30882.44 | AO23: 30882.44 | AP23: 30882.44 | AQ23: 30882.44 | AR23: 30882.44 | AS23: 30882.44 | AT23: 30882.44 | AU23: 30882.44 | AV23: 30882.44 | AW23: 30882.44 | AX23: 30882.44 | AY23: 30882.44
B24: Interest Expense | P24: 28621.88 | Q24: 28621.88 | R24: 28621.88 | S24: 32069.59 | T24: 23912.5 | U24: ='BK P&L'!U66+'CC P&L'!U66+'DN P&L'!U66+'LF P&L'!U66+'MR P&L'!U66+'OP P&L'!U66+'PH P&L'!U66+'RH P&L'!U66+'SB P&L'!U66+'SM P&L'!U66+'WP P&L'!U66+'WW P&L'!U66+'HO P&L'!U39 | V24: ='BK P&L'!V66+'CC P&L'!V66+'DN P&L'!V66+'LF P&L'!V66+'MR P&L'!V66+'OP P&L'!V66+'PH P&L'!V66+'RH P&L'!V66+'SB P&L'!V66+'SM P&L'!V66+'WP P&L'!V66+'WW P&L'!V66+'HO P&L'!V39 | W24: ='BK P&L'!W66+'CC P&L'!W66+'DN P&L'!W66+'LF P&L'!W66+'MR P&L'!W66+'OP P&L'!W66+'PH P&L'!W66+'RH P&L'!W66+'SB P&L'!W66+'SM P&L'!W66+'WP P&L'!W66+'WW P&L'!W66+'HO P&L'!W39 | X24: ='BK P&L'!X66+'CC P&L'!X66+'DN P&L'!X66+'LF P&L'!X66+'MR P&L'!X66+'OP P&L'!X66+'PH P&L'!X66+'RH P&L'!X66+'SB P&L'!X66+'SM P&L'!X66+'WP P&L'!X66+'WW P&L'!X66+'HO P&L'!X39 | Y24: ='BK P&L'!Y66+'CC P&L'!Y66+'DN P&L'!Y66+'LF P&L'!Y66+'MR P&L'!Y66+'OP P&L'!Y66+'PH P&L'!Y66+'RH P&L'!Y66+'SB P&L'!Y66+'SM P&L'!Y66+'WP P&L'!Y66+'WW P&L'!Y66+'HO P&L'!Y39 | Z24: ='BK P&L'!Z66+'CC P&L'!Z66+'DN P&L'!Z66+'LF P&L'!Z66+'MR P&L'!Z66+'OP P&L'!Z66+'PH P&L'!Z66+'RH P&L'!Z66+'SB P&L'!Z66+'SM P&L'!Z66+'WP P&L'!Z66+'WW P&L'!Z66+'HO P&L'!Z39 | AA24: ='BK P&L'!AA66+'CC P&L'!AA66+'DN P&L'!AA66+'LF P&L'!AA66+'MR P&L'!AA66+'OP P&L'!AA66+'PH P&L'!AA66+'RH P&L'!AA66+'SB P&L'!AA66+'SM P&L'!AA66+'WP P&L'!AA66+'WW P&L'!AA66+'HO P&L'!AA39 | AB24: ='BK P&L'!AB66+'CC P&L'!AB66+'DN P&L'!AB66+'LF P&L'!AB66+'MR P&L'!AB66+'OP P&L'!AB66+'PH P&L'!AB66+'RH P&L'!AB66+'SB P&L'!AB66+'SM P&L'!AB66+'WP P&L'!AB66+'WW P&L'!AB66+'HO P&L'!AB39 | ... AM24: ='BK P&L'!AM66+'CC P&L'!AM66+'DN P&L'!AM66+'LF P&L'!AM66+'MR P&L'!AM66+'OP P&L'!AM66+'PH P&L'!AM66+'RH P&L'!AM66+'SB P&L'!AM66+'SM P&L'!AM66+'WP P&L'!AM66+'WW P&L'!AM66+'HO P&L'!AM39 | AN24: =14026 | AO24: =14026 | AP24: =14026 | AQ24: =14026 | AR24: =14026 | AS24: =14026 | AT24: =14026 | AU24: =14026 | ... AY24: =14026
B25: Taxes Paid | D25: 0 | E25: 9041.24 | F25: 1700 | G25: 800 | H25: 0 | I25: 0 | J25: 0 | K25: 0 | L25: 0 | M25: 11790 | N25: 0 | O25: 0 | P25: 0 | Q25: 5143 | R25: 0 | S25: 0 | T25: 800 | U25: ='BK P&L'!U67+'CC P&L'!U67+'DN P&L'!U67+'LF P&L'!U67+'MR P&L'!U67+'OP P&L'!U67+'PH P&L'!U67+'RH P&L'!U67+'SB P&L'!U67+'SM P&L'!U67+'WP P&L'!U67+'WW P&L'!U67+'HO P&L'!U33 | V25: ='BK P&L'!V67+'CC P&L'!V67+'DN P&L'!V67+'LF P&L'!V67+'MR P&L'!V67+'OP P&L'!V67+'PH P&L'!V67+'RH P&L'!V67+'SB P&L'!V67+'SM P&L'!V67+'WP P&L'!V67+'WW P&L'!V67+'HO P&L'!V33 | W25: ='BK P&L'!W67+'CC P&L'!W67+'DN P&L'!W67+'LF P&L'!W67+'MR P&L'!W67+'OP P&L'!W67+'PH P&L'!W67+'RH P&L'!W67+'SB P&L'!W67+'SM P&L'!W67+'WP P&L'!W67+'WW P&L'!W67+'HO P&L'!W33 | X25: ='BK P&L'!X67+'CC P&L'!X67+'DN P&L'!X67+'LF P&L'!X67+'MR P&L'!X67+'OP P&L'!X67+'PH P&L'!X67+'RH P&L'!X67+'SB P&L'!X67+'SM P&L'!X67+'WP P&L'!X67+'WW P&L'!X67+'HO P&L'!X33 | Y25: ='BK P&L'!Y67+'CC P&L'!Y67+'DN P&L'!Y67+'LF P&L'!Y67+'MR P&L'!Y67+'OP P&L'!Y67+'PH P&L'!Y67+'RH P&L'!Y67+'SB P&L'!Y67+'SM P&L'!Y67+'WP P&L'!Y67+'WW P&L'!Y67+'HO P&L'!Y33 | Z25: ='BK P&L'!Z67+'CC P&L'!Z67+'DN P&L'!Z67+'LF P&L'!Z67+'MR P&L'!Z67+'OP P&L'!Z67+'PH P&L'!Z67+'RH P&L'!Z67+'SB P&L'!Z67+'SM P&L'!Z67+'WP P&L'!Z67+'WW P&L'!Z67+'HO P&L'!Z33 | AA25: ='BK P&L'!AA67+'CC P&L'!AA67+'DN P&L'!AA67+'LF P&L'!AA67+'MR P&L'!AA67+'OP P&L'!AA67+'PH P&L'!AA67+'RH P&L'!AA67+'SB P&L'!AA67+'SM P&L'!AA67+'WP P&L'!AA67+'WW P&L'!AA67+'HO P&L'!AA33 | AB25: ='BK P&L'!AB67+'CC P&L'!AB67+'DN P&L'!AB67+'LF P&L'!AB67+'MR P&L'!AB67+'OP P&L'!AB67+'PH P&L'!AB67+'RH P&L'!AB67+'SB P&L'!AB67+'SM P&L'!AB67+'WP P&L'!AB67+'WW P&L'!AB67+'HO P&L'!AB33 | ... AM25: ='BK P&L'!AM67+'CC P&L'!AM67+'DN P&L'!AM67+'LF P&L'!AM67+'MR P&L'!AM67+'OP P&L'!AM67+'PH P&L'!AM67+'RH P&L'!AM67+'SB P&L'!AM67+'SM P&L'!AM67+'WP P&L'!AM67+'WW P&L'!AM67+'HO P&L'!AM33 | AN25: 266.67 | AO25: 266.67 | AP25: 266.67 | AQ25: 266.67 | AR25: 266.67 | AS25: 266.67 | AT25: 266.67 | AU25: 266.67 | AV25: 266.67 | AW25: 266.67 | AX25: 266.67 | AY25: 266.67
B26: Property Taxes | D26: 3356.51 | E26: 3526.51 | F26: 3441.51 | G26: 3807.51 | H26: 3441.51 | I26: 4369.71 | J26: 8502.45 | K26: 3441.51 | L26: 3441.51 | M26: 5926.47 | N26: 3441.51 | O26: 3441.52 | P26: 3673 | Q26: 3673 | R26: 3673 | S26: 3673 | T26: 3673 | U26: 3673 | V26: 3673 | W26: 3673 | X26: 3673 | Y26: 3673 | Z26: 3673 | AA26: 3673 | AB26: 3673 | AC26: 3673 | AD26: 3673 | AE26: 3673 | AF26: 3673 | AG26: 3673 | AH26: 3673 | AI26: 3673 | AJ26: 3673 | AK26: 3673 | AL26: 3673 | AM26: 3673 | AN26: 3673 | AO26: 3673 | AP26: 3673 | AQ26: 3673 | AR26: 3673 | AS26: 3673 | AT26: 3673 | AU26: 3673 | AV26: 3673 | AW26: 3673 | AX26: 3673 | AY26: 3673
B27: Total Other Expenses | D27: 18651.42 | E27: 30112.25 | F27: 22797.93 | G27: 24384.42 | H27: 23359.71 | I27: 27831.44 | J27: 32066.51 | K27: 28173.3 | L27: 46144.4 | M27: 56646.6 | N27: 53770.93 | O27: 41660.09 | P27: 62905.92 | Q27: 68103.48 | R27: 63171.66 | S27: 62636.34 | T27: 64262.28 | U27: =U23+U24+U25+U26 | V27: =V23+V24+V25+V26 | W27: =W23+W24+W25+W26 | X27: =X23+X24+X25+X26 | Y27: =Y23+Y24+Y25+Y26 | Z27: =Z23+Z24+Z25+Z26 | AA27: =AA23+AA24+AA25+AA26 | AB27: =AB23+AB24+AB25+AB26 | ... AY27: =AY23+AY24+AY25+AY26
B28: Net Income | D28: -29790.04 | E28: 43207.95 | F28: 125944.26 | G28: 97961.77 | H28: 62912.61 | I28: 4393.53 | J28: 19890.81 | K28: 17079.74 | L28: -35499.56 | M28: -138189.09 | N28: -69507.26 | O28: -46371.19 | P28: 36458.4 | Q28: 16644.92 | R28: -15019.9 | S28: -9525.8 | T28: 9469.26 | U28: =U22-U27 | V28: =V22-V27 | W28: =W22-W27 | X28: =X22-X27 | Y28: =Y22-Y27 | Z28: =Z22-Z27 | AA28: =AA22-AA27 | AB28: =AB22-AB27 | ... AY28: =AY22-AY27
B30: ADJUSTED EBITDA RECONCILIATION
B31: Net Operating Income (from above) | D31: =D22 | E31: =E22 | F31: =F22 | G31: =G22 | H31: =H22 | I31: =I22 | J31: =J22 | K31: =K22 | ... AY31: =AY22
B32: Add Backs:
B33: West Portal Start-Up Costs | P33: 16222.39 | Q33: 17111.26 | R33: 14310.31 | S33: 19092.69 | T33: 16815 | U33: 0 | V33: 0 | W33: 0 | X33: 0 | Y33: 0 | Z33: 0 | AA33: 0 | AB33: 0 | AC33: 0 | AD33: 0 | AE33: 0 | AF33: 0 | AG33: 0 | AH33: 0 | AI33: 0 | AJ33: 0 | AK33: 0 | AL33: 0 | AM33: 0 | AN33: 0 | AO33: 0 | AP33: 0 | AQ33: 0 | AR33: 0 | AS33: 0 | AT33: 0 | AU33: 0 | AV33: 0 | AW33: 0 | AX33: 0 | AY33: 0
B34: ADP Error | P34: 0 | Q34: 0 | R34: 45000 | S34: 0 | T34: 0 | U34: 0 | V34: 0 | W34: 0 | X34: 0 | Y34: 0 | Z34: 0 | AA34: 0 | AB34: 0 | AC34: 0 | AD34: 0 | AE34: 0 | AF34: 0 | AG34: 0 | AH34: 0 | AI34: 0 | AJ34: 0 | AK34: 0 | AL34: 0 | AM34: 0 | AN34: 0 | AO34: 0 | AP34: 0 | AQ34: 0 | AR34: 0 | AS34: 0 | AT34: 0 | AU34: 0 | AV34: 0 | AW34: 0 | AX34: 0 | AY34: 0
B35: One-Time Legal Fees | P35: 2957 | Q35: 0 | R35: =3995.5 | S35: 0 | T35: 0 | U35: 0 | V35: 0 | W35: 0 | X35: 0 | Y35: 0 | Z35: 0 | AA35: 0 | AB35: 0 | AC35: 0 | AD35: 0 | AE35: 0 | AF35: 0 | AG35: 0 | AH35: 0 | AI35: 0 | AJ35: 0 | AK35: 0 | AL35: 0 | AM35: 0 | AN35: 0 | AO35: 0 | AP35: 0 | AQ35: 0 | AR35: 0 | AS35: 0 | AT35: 0 | AU35: 0 | AV35: 0 | AW35: 0 | AX35: 0 | AY35: 0
B36: Santa Barbara Start Up | P36: 3481 | Q36: 0 | R36: 0 | S36: 0 | T36: 0 | U36: 0 | V36: 0 | W36: 0 | X36: 0 | Y36: 0 | Z36: 0 | AA36: 0 | AB36: 0 | AC36: 0 | AD36: 0 | AE36: 0 | AF36: 0 | AG36: 0 | AH36: 0 | AI36: 0 | AJ36: 0 | AK36: 0 | AL36: 0 | AM36: 0 | AN36: 0 | AO36: 0 | AP36: 0 | AQ36: 0 | AR36: 0 | AS36: 0 | AT36: 0 | AU36: 0 | AV36: 0 | AW36: 0 | AX36: 0 | AY36: 0
B37: One-Time Accounting Fees | P37: 19887.5 | Q37: 0 | R37: 0 | S37: 0 | T37: 0 | U37: 0 | V37: 0 | W37: 0 | X37: 0 | Y37: 0 | Z37: 0 | AA37: 0 | AB37: 0 | AC37: 0 | AD37: 0 | AE37: 0 | AF37: 0 | AG37: 0 | AH37: 0 | AI37: 0 | AJ37: 0 | AK37: 0 | AL37: 0 | AM37: 0 | AN37: 0 | AO37: 0 | AP37: 0 | AQ37: 0 | AR37: 0 | AS37: 0 | AT37: 0 | AU37: 0 | AV37: 0 | AW37: 0 | AX37: 0 | AY37: 0
B38: Total Add Backs | D38: =SUM(D33:D37) | E38: =SUM(E33:E37) | F38: =SUM(F33:F37) | G38: =SUM(G33:G37) | H38: =SUM(H33:H37) | I38: =SUM(I33:I37) | J38: =SUM(J33:J37) | K38: =SUM(K33:K37) | ... AY38: =SUM(AY33:AY37)
B39: Adjusted EBITDA | D39: =D31+D38 | E39: =E31+E38 | F39: =F31+F38 | G39: =G31+G38 | H39: =H31+H38 | I39: =I31+I38 | J39: =J31+J38 | K39: =K31+K38 | ... AY39: =AY31+AY38

Sheet All Studios Summary
B2: All Studios — Summary
B4: Studio / Metric | D4: Jan 2025 | E4: Feb 2025 | F4: Mar 2025 | G4: Apr 2025 | H4: May 2025 | I4: Jun 2025 | J4: Jul 2025 | K4: Aug 2025 | L4: Sep 2025 | M4: Oct 2025 | N4: Nov 2025 | O4: Dec 2025 | P4: Jan 2026 | Q4: Feb 2026 | R4: Mar 2026 | S4: Apr 2026 | T4: May 2026 | U4: Jun 2026 | V4: Jul 2026 | W4: Aug 2026 | X4: Sep 2026 | Y4: Oct 2026 | Z4: Nov 2026 | AA4: Dec 2026 | AB4: Jan 2027 | AC4: Feb 2027 | AD4: Mar 2027 | AE4: Apr 2027 | AF4: May 2027 | AG4: Jun 2027 | AH4: Jul 2027 | AI4: Aug 2027 | AJ4: Sep 2027 | AK4: Oct 2027 | AL4: Nov 2027 | AM4: Dec 2027 | AN4: Jan 2028 | AO4: Feb 2028 | AP4: Mar 2028 | AQ4: Apr 2028 | AR4: May 2028 | AS4: Jun 2028 | AT4: Jul 2028 | AU4: Aug 2028 | AV4: Sep 2028 | AW4: Oct 2028 | AX4: Nov 2028 | AY4: Dec 2028
B5: Berkeley (BK)
B6: Total Revenue | D6: ='BK P&L'!D21 | E6: ='BK P&L'!E21 | F6: ='BK P&L'!F21 | G6: ='BK P&L'!G21 | H6: ='BK P&L'!H21 | I6: ='BK P&L'!I21 | J6: ='BK P&L'!J21 | K6: ='BK P&L'!K21 | ... AY6: ='BK P&L'!AY21
B7: Gross Profit | D7: ='BK P&L'!D26 | E7: ='BK P&L'!E26 | F7: ='BK P&L'!F26 | G7: ='BK P&L'!G26 | H7: ='BK P&L'!H26 | I7: ='BK P&L'!I26 | J7: ='BK P&L'!J26 | K7: ='BK P&L'!K26 | ... AY7: ='BK P&L'!AY26
B8: Total Operating Expenses | D8: ='BK P&L'!D62 | E8: ='BK P&L'!E62 | F8: ='BK P&L'!F62 | G8: ='BK P&L'!G62 | H8: ='BK P&L'!H62 | I8: ='BK P&L'!I62 | J8: ='BK P&L'!J62 | K8: ='BK P&L'!K62 | ... AY8: ='BK P&L'!AY62
B9: Net Operating Income | D9: ='BK P&L'!D63 | E9: ='BK P&L'!E63 | F9: ='BK P&L'!F63 | G9: ='BK P&L'!G63 | H9: ='BK P&L'!H63 | I9: ='BK P&L'!I63 | J9: ='BK P&L'!J63 | K9: ='BK P&L'!K63 | ... AY9: ='BK P&L'!AY63
B11: Culver City (CC)
B12: Total Revenue | D12: ='CC P&L'!D21 | E12: ='CC P&L'!E21 | F12: ='CC P&L'!F21 | G12: ='CC P&L'!G21 | H12: ='CC P&L'!H21 | I12: ='CC P&L'!I21 | J12: ='CC P&L'!J21 | K12: ='CC P&L'!K21 | ... AY12: ='CC P&L'!AY21
B13: Gross Profit | D13: ='CC P&L'!D26 | E13: ='CC P&L'!E26 | F13: ='CC P&L'!F26 | G13: ='CC P&L'!G26 | H13: ='CC P&L'!H26 | I13: ='CC P&L'!I26 | J13: ='CC P&L'!J26 | K13: ='CC P&L'!K26 | ... AY13: ='CC P&L'!AY26
B14: Total Operating Expenses | D14: ='CC P&L'!D62 | E14: ='CC P&L'!E62 | F14: ='CC P&L'!F62 | G14: ='CC P&L'!G62 | H14: ='CC P&L'!H62 | I14: ='CC P&L'!I62 | J14: ='CC P&L'!J62 | K14: ='CC P&L'!K62 | ... AY14: ='CC P&L'!AY62
B15: Net Operating Income | D15: ='CC P&L'!D63 | E15: ='CC P&L'!E63 | F15: ='CC P&L'!F63 | G15: ='CC P&L'!G63 | H15: ='CC P&L'!H63 | I15: ='CC P&L'!I63 | J15: ='CC P&L'!J63 | K15: ='CC P&L'!K63 | ... AY15: ='CC P&L'!AY63
B17: Danville (DN)
B18: Total Revenue | D18: ='DN P&L'!D21 | E18: ='DN P&L'!E21 | F18: ='DN P&L'!F21 | G18: ='DN P&L'!G21 | H18: ='DN P&L'!H21 | I18: ='DN P&L'!I21 | J18: ='DN P&L'!J21 | K18: ='DN P&L'!K21 | ... AY18: ='DN P&L'!AY21
B19: Gross Profit | D19: ='DN P&L'!D26 | E19: ='DN P&L'!E26 | F19: ='DN P&L'!F26 | G19: ='DN P&L'!G26 | H19: ='DN P&L'!H26 | I19: ='DN P&L'!I26 | J19: ='DN P&L'!J26 | K19: ='DN P&L'!K26 | ... AY19: ='DN P&L'!AY26
B20: Total Operating Expenses | D20: ='DN P&L'!D62 | E20: ='DN P&L'!E62 | F20: ='DN P&L'!F62 | G20: ='DN P&L'!G62 | H20: ='DN P&L'!H62 | I20: ='DN P&L'!I62 | J20: ='DN P&L'!J62 | K20: ='DN P&L'!K62 | ... AY20: ='DN P&L'!AY62
B21: Net Operating Income | D21: ='DN P&L'!D63 | E21: ='DN P&L'!E63 | F21: ='DN P&L'!F63 | G21: ='DN P&L'!G63 | H21: ='DN P&L'!H63 | I21: ='DN P&L'!I63 | J21: ='DN P&L'!J63 | K21: ='DN P&L'!K63 | ... AY21: ='DN P&L'!AY63
B23: Lafayette (LF)
B24: Total Revenue | D24: ='LF P&L'!D21 | E24: ='LF P&L'!E21 | F24: ='LF P&L'!F21 | G24: ='LF P&L'!G21 | H24: ='LF P&L'!H21 | I24: ='LF P&L'!I21 | J24: ='LF P&L'!J21 | K24: ='LF P&L'!K21 | ... AY24: ='LF P&L'!AY21
B25: Gross Profit | D25: ='LF P&L'!D26 | E25: ='LF P&L'!E26 | F25: ='LF P&L'!F26 | G25: ='LF P&L'!G26 | H25: ='LF P&L'!H26 | I25: ='LF P&L'!I26 | J25: ='LF P&L'!J26 | K25: ='LF P&L'!K26 | ... AY25: ='LF P&L'!AY26
B26: Total Operating Expenses | D26: ='LF P&L'!D62 | E26: ='LF P&L'!E62 | F26: ='LF P&L'!F62 | G26: ='LF P&L'!G62 | H26: ='LF P&L'!H62 | I26: ='LF P&L'!I62 | J26: ='LF P&L'!J62 | K26: ='LF P&L'!K62 | ... AY26: ='LF P&L'!AY62
B27: Net Operating Income | D27: ='LF P&L'!D63 | E27: ='LF P&L'!E63 | F27: ='LF P&L'!F63 | G27: ='LF P&L'!G63 | H27: ='LF P&L'!H63 | I27: ='LF P&L'!I63 | J27: ='LF P&L'!J63 | K27: ='LF P&L'!K63 | ... AY27: ='LF P&L'!AY63
B29: Marin (MR)
B30: Total Revenue | D30: ='MR P&L'!D21 | E30: ='MR P&L'!E21 | F30: ='MR P&L'!F21 | G30: ='MR P&L'!G21 | H30: ='MR P&L'!H21 | I30: ='MR P&L'!I21 | J30: ='MR P&L'!J21 | K30: ='MR P&L'!K21 | ... AY30: ='MR P&L'!AY21
B31: Gross Profit | D31: ='MR P&L'!D26 | E31: ='MR P&L'!E26 | F31: ='MR P&L'!F26 | G31: ='MR P&L'!G26 | H31: ='MR P&L'!H26 | I31: ='MR P&L'!I26 | J31: ='MR P&L'!J26 | K31: ='MR P&L'!K26 | ... AY31: ='MR P&L'!AY26
B32: Total Operating Expenses | D32: ='MR P&L'!D62 | E32: ='MR P&L'!E62 | F32: ='MR P&L'!F62 | G32: ='MR P&L'!G62 | H32: ='MR P&L'!H62 | I32: ='MR P&L'!I62 | J32: ='MR P&L'!J62 | K32: ='MR P&L'!K62 | ... AY32: ='MR P&L'!AY62
B33: Net Operating Income | D33: ='MR P&L'!D63 | E33: ='MR P&L'!E63 | F33: ='MR P&L'!F63 | G33: ='MR P&L'!G63 | H33: ='MR P&L'!H63 | I33: ='MR P&L'!I63 | J33: ='MR P&L'!J63 | K33: ='MR P&L'!K63 | ... AY33: ='MR P&L'!AY63
B35: Ocean Park (OP)
B36: Total Revenue | D36: ='OP P&L'!D21 | E36: ='OP P&L'!E21 | F36: ='OP P&L'!F21 | G36: ='OP P&L'!G21 | H36: ='OP P&L'!H21 | I36: ='OP P&L'!I21 | J36: ='OP P&L'!J21 | K36: ='OP P&L'!K21 | ... AY36: ='OP P&L'!AY21
B37: Gross Profit | D37: ='OP P&L'!D26 | E37: ='OP P&L'!E26 | F37: ='OP P&L'!F26 | G37: ='OP P&L'!G26 | H37: ='OP P&L'!H26 | I37: ='OP P&L'!I26 | J37: ='OP P&L'!J26 | K37: ='OP P&L'!K26 | ... AY37: ='OP P&L'!AY26
B38: Total Operating Expenses | D38: ='OP P&L'!D62 | E38: ='OP P&L'!E62 | F38: ='OP P&L'!F62 | G38: ='OP P&L'!G62 | H38: ='OP P&L'!H62 | I38: ='OP P&L'!I62 | J38: ='OP P&L'!J62 | K38: ='OP P&L'!K62 | ... AY38: ='OP P&L'!AY62
B39: Net Operating Income | D39: ='OP P&L'!D63 | E39: ='OP P&L'!E63 | F39: ='OP P&L'!F63 | G39: ='OP P&L'!G63 | H39: ='OP P&L'!H63 | I39: ='OP P&L'!I63 | J39: ='OP P&L'!J63 | K39: ='OP P&L'!K63 | ... AY39: ='OP P&L'!AY63
B41: Presidio Heights (PH)
B42: Total Revenue | D42: ='PH P&L'!D21 | E42: ='PH P&L'!E21 | F42: ='PH P&L'!F21 | G42: ='PH P&L'!G21 | H42: ='PH P&L'!H21 | I42: ='PH P&L'!I21 | J42: ='PH P&L'!J21 | K42: ='PH P&L'!K21 | ... AY42: ='PH P&L'!AY21
B43: Gross Profit | D43: ='PH P&L'!D26 | E43: ='PH P&L'!E26 | F43: ='PH P&L'!F26 | G43: ='PH P&L'!G26 | H43: ='PH P&L'!H26 | I43: ='PH P&L'!I26 | J43: ='PH P&L'!J26 | K43: ='PH P&L'!K26 | ... AY43: ='PH P&L'!AY26
B44: Total Operating Expenses | D44: ='PH P&L'!D62 | E44: ='PH P&L'!E62 | F44: ='PH P&L'!F62 | G44: ='PH P&L'!G62 | H44: ='PH P&L'!H62 | I44: ='PH P&L'!I62 | J44: ='PH P&L'!J62 | K44: ='PH P&L'!K62 | ... AY44: ='PH P&L'!AY62
B45: Net Operating Income | D45: ='PH P&L'!D63 | E45: ='PH P&L'!E63 | F45: ='PH P&L'!F63 | G45: ='PH P&L'!G63 | H45: ='PH P&L'!H63 | I45: ='PH P&L'!I63 | J45: ='PH P&L'!J63 | K45: ='PH P&L'!K63 | ... AY45: ='PH P&L'!AY63
B47: Russian Hill (RH)
B48: Total Revenue | D48: ='RH P&L'!D21 | E48: ='RH P&L'!E21 | F48: ='RH P&L'!F21 | G48: ='RH P&L'!G21 | H48: ='RH P&L'!H21 | I48: ='RH P&L'!I21 | J48: ='RH P&L'!J21 | K48: ='RH P&L'!K21 | ... AY48: ='RH P&L'!AY21
B49: Gross Profit | D49: ='RH P&L'!D26 | E49: ='RH P&L'!E26 | F49: ='RH P&L'!F26 | G49: ='RH P&L'!G26 | H49: ='RH P&L'!H26 | I49: ='RH P&L'!I26 | J49: ='RH P&L'!J26 | K49: ='RH P&L'!K26 | ... AY49: ='RH P&L'!AY26
B50: Total Operating Expenses | D50: ='RH P&L'!D62 | E50: ='RH P&L'!E62 | F50: ='RH P&L'!F62 | G50: ='RH P&L'!G62 | H50: ='RH P&L'!H62 | I50: ='RH P&L'!I62 | J50: ='RH P&L'!J62 | K50: ='RH P&L'!K62 | ... AY50: ='RH P&L'!AY62
B51: Net Operating Income | D51: ='RH P&L'!D63 | E51: ='RH P&L'!E63 | F51: ='RH P&L'!F63 | G51: ='RH P&L'!G63 | H51: ='RH P&L'!H63 | I51: ='RH P&L'!I63 | J51: ='RH P&L'!J63 | K51: ='RH P&L'!K63 | ... AY51: ='RH P&L'!AY63
B53: Santa Barbara (SB)
B54: Total Revenue | D54: ='SB P&L'!D21 | E54: ='SB P&L'!E21 | F54: ='SB P&L'!F21 | G54: ='SB P&L'!G21 | H54: ='SB P&L'!H21 | I54: ='SB P&L'!I21 | J54: ='SB P&L'!J21 | K54: ='SB P&L'!K21 | ... AY54: ='SB P&L'!AY21
B55: Gross Profit | D55: ='SB P&L'!D26 | E55: ='SB P&L'!E26 | F55: ='SB P&L'!F26 | G55: ='SB P&L'!G26 | H55: ='SB P&L'!H26 | I55: ='SB P&L'!I26 | J55: ='SB P&L'!J26 | K55: ='SB P&L'!K26 | ... AY55: ='SB P&L'!AY26
B56: Total Operating Expenses | D56: ='SB P&L'!D62 | E56: ='SB P&L'!E62 | F56: ='SB P&L'!F62 | G56: ='SB P&L'!G62 | H56: ='SB P&L'!H62 | I56: ='SB P&L'!I62 | J56: ='SB P&L'!J62 | K56: ='SB P&L'!K62 | ... AY56: ='SB P&L'!AY62
B57: Net Operating Income | D57: ='SB P&L'!D63 | E57: ='SB P&L'!E63 | F57: ='SB P&L'!F63 | G57: ='SB P&L'!G63 | H57: ='SB P&L'!H63 | I57: ='SB P&L'!I63 | J57: ='SB P&L'!J63 | K57: ='SB P&L'!K63 | ... AY57: ='SB P&L'!AY63
B59: Santa Monica (SM)
B60: Total Revenue | D60: ='SM P&L'!D21 | E60: ='SM P&L'!E21 | F60: ='SM P&L'!F21 | G60: ='SM P&L'!G21 | H60: ='SM P&L'!H21 | I60: ='SM P&L'!I21 | J60: ='SM P&L'!J21 | K60: ='SM P&L'!K21 | ... AY60: ='SM P&L'!AY21
B61: Gross Profit | D61: ='SM P&L'!D26 | E61: ='SM P&L'!E26 | F61: ='SM P&L'!F26 | G61: ='SM P&L'!G26 | H61: ='SM P&L'!H26 | I61: ='SM P&L'!I26 | J61: ='SM P&L'!J26 | K61: ='SM P&L'!K26 | ... AY61: ='SM P&L'!AY26
B62: Total Operating Expenses | D62: ='SM P&L'!D62 | E62: ='SM P&L'!E62 | F62: ='SM P&L'!F62 | G62: ='SM P&L'!G62 | H62: ='SM P&L'!H62 | I62: ='SM P&L'!I62 | J62: ='SM P&L'!J62 | K62: ='SM P&L'!K62 | ... AY62: ='SM P&L'!AY62
B63: Net Operating Income | D63: ='SM P&L'!D63 | E63: ='SM P&L'!E63 | F63: ='SM P&L'!F63 | G63: ='SM P&L'!G63 | H63: ='SM P&L'!H63 | I63: ='SM P&L'!I63 | J63: ='SM P&L'!J63 | K63: ='SM P&L'!K63 | ... AY63: ='SM P&L'!AY63
B65: West Portal (WP)
B66: Total Revenue | D66: ='WP P&L'!D21 | E66: ='WP P&L'!E21 | F66: ='WP P&L'!F21 | G66: ='WP P&L'!G21 | H66: ='WP P&L'!H21 | I66: ='WP P&L'!I21 | J66: ='WP P&L'!J21 | K66: ='WP P&L'!K21 | ... AY66: ='WP P&L'!AY21
B67: Gross Profit | D67: ='WP P&L'!D26 | E67: ='WP P&L'!E26 | F67: ='WP P&L'!F26 | G67: ='WP P&L'!G26 | H67: ='WP P&L'!H26 | I67: ='WP P&L'!I26 | J67: ='WP P&L'!J26 | K67: ='WP P&L'!K26 | ... AY67: ='WP P&L'!AY26
B68: Total Operating Expenses | D68: ='WP P&L'!D62 | E68: ='WP P&L'!E62 | F68: ='WP P&L'!F62 | G68: ='WP P&L'!G62 | H68: ='WP P&L'!H62 | I68: ='WP P&L'!I62 | J68: ='WP P&L'!J62 | K68: ='WP P&L'!K62 | ... AY68: ='WP P&L'!AY62
B69: Net Operating Income | D69: ='WP P&L'!D63 | E69: ='WP P&L'!E63 | F69: ='WP P&L'!F63 | G69: ='WP P&L'!G63 | H69: ='WP P&L'!H63 | I69: ='WP P&L'!I63 | J69: ='WP P&L'!J63 | K69: ='WP P&L'!K63 | ... AY69: ='WP P&L'!AY63
B71: Westwood (WW)
B72: Total Revenue | D72: ='WW P&L'!D21 | E72: ='WW P&L'!E21 | F72: ='WW P&L'!F21 | G72: ='WW P&L'!G21 | H72: ='WW P&L'!H21 | I72: ='WW P&L'!I21 | J72: ='WW P&L'!J21 | K72: ='WW P&L'!K21 | ... AY72: ='WW P&L'!AY21
B73: Gross Profit | D73: ='WW P&L'!D26 | E73: ='WW P&L'!E26 | F73: ='WW P&L'!F26 | G73: ='WW P&L'!G26 | H73: ='WW P&L'!H26 | I73: ='WW P&L'!I26 | J73: ='WW P&L'!J26 | K73: ='WW P&L'!K26 | ... AY73: ='WW P&L'!AY26
B74: Total Operating Expenses | D74: ='WW P&L'!D62 | E74: ='WW P&L'!E62 | F74: ='WW P&L'!F62 | G74: ='WW P&L'!G62 | H74: ='WW P&L'!H62 | I74: ='WW P&L'!I62 | J74: ='WW P&L'!J62 | K74: ='WW P&L'!K62 | ... AY74: ='WW P&L'!AY62
B75: Net Operating Income | D75: ='WW P&L'!D63 | E75: ='WW P&L'!E63 | F75: ='WW P&L'!F63 | G75: ='WW P&L'!G63 | H75: ='WW P&L'!H63 | I75: ='WW P&L'!I63 | J75: ='WW P&L'!J63 | K75: ='WW P&L'!K63 | ... AY75: ='WW P&L'!AY63

Sheet BK P&L
B2: Berkeley (BK) — Profit & Loss
B4: Monthly P&L (Detail)
B5: Line Item | D5: Jan 2025 | E5: Feb 2025 | F5: Mar 2025 | G5: Apr 2025 | H5: May 2025 | I5: Jun 2025 | J5: Jul 2025 | K5: Aug 2025 | L5: Sep 2025 | M5: Oct 2025 | N5: Nov 2025 | O5: Dec 2025 | P5: Jan 2026 | Q5: Feb 2026 | R5: Mar 2026 | S5: Apr 2026 | T5: May 2026 | U5: Jun 2026 | V5: Jul 2026 | W5: Aug 2026 | X5: Sep 2026 | Y5: Oct 2026 | Z5: Nov 2026 | AA5: Dec 2026 | AB5: Jan 2027 | AC5: Feb 2027 | AD5: Mar 2027 | AE5: Apr 2027 | AF5: May 2027 | AG5: Jun 2027 | AH5: Jul 2027 | AI5: Aug 2027 | AJ5: Sep 2027 | AK5: Oct 2027 | AL5: Nov 2027 | AM5: Dec 2027 | AN5: Jan 2028 | AO5: Feb 2028 | AP5: Mar 2028 | AQ5: Apr 2028 | AR5: May 2028 | AS5: Jun 2028 | AT5: Jul 2028 | AU5: Aug 2028 | AV5: Sep 2028 | AW5: Oct 2028 | AX5: Nov 2028 | AY5: Dec 2028
B6: INCOME | D6: 0 | E6: 0 | F6: 0 | G6: 0 | H6: 0 | I6: 0 | J6: 0 | K6: 0 | L6: 0 | M6: 0 | N6: 0 | O6: 0
B7: 401001 Machine | D7: 48512.85 | E7: 54342.24 | F7: 64934.84 | G7: 59274.01 | H7: 61380.05 | I7: 59220.81 | J7: 60156.33 | K7: 65762.1 | L7: 63020.69 | M7: 62222.95 | N7: 58675.46 | O7: 57148.4 | P7: 67553.69 | Q7: 60691.23 | R7: 63647.98 | S7: 60903.08 | T7: 59469.95 | U7: =U13*0.598021 | V7: =V13*0.598021 | W7: =W13*0.598021 | X7: =X13*0.598021 | Y7: =Y13*0.598021 | Z7: =Z13*0.598021 | AA7: =AA13*0.598021 | AB7: =AB13*0.598021 | ... AY7: =AY13*0.598021
B8: 401002 Private Pilates | D8: 3365 | E8: 5164 | F8: 6259.32 | G8: 7063.11 | H8: 6195.11 | I8: 4351.11 | J8: 4420.26 | K8: 6743.11 | L8: 6140 | M8: 3768.5 | N8: 5134 | O8: 4124 | P8: 4967 | Q8: 6520 | R8: 7898 | S8: 6484 | T8: 4535 | U8: =U13*0.061196 | V8: =V13*0.061196 | W8: =W13*0.061196 | X8: =X13*0.061196 | Y8: =Y13*0.061196 | Z8: =Z13*0.061196 | AA8: =AA13*0.061196 | AB8: =AB13*0.061196 | ... AY8: =AY13*0.061196
B9: 401003 Class Pass | D9: 28443.58 | E9: 27468.5 | F9: 27758.08 | G9: 30356.52 | H9: 29776.53 | I9: 29108.34 | J9: 28187.52 | K9: 27520.95 | L9: 26184.97 | M9: 24804.33 | N9: 26840.92 | O9: 26286.98 | P9: 28869.3 | Q9: 25522.33 | R9: 29455.32 | S9: 30289 | T9: 26097.27 | U9: =U13*0.270003 | V9: =V13*0.270003 | W9: =W13*0.270003 | X9: =X13*0.270003 | Y9: =Y13*0.270003 | Z9: =Z13*0.270003 | AA9: =AA13*0.270003 | AB9: =AB13*0.270003 | ... AY9: =AY13*0.270003
B10: 401004 Mighty Teacher Training | D10: 640 | E10: 320 | F10: 0 | G10: 0 | H10: 1280 | I10: 2320 | J10: 5457.5 | K10: 0 | L10: 0 | M10: 0 | N10: 0 | O10: 0 | P10: 21644.5 | Q10: 6831 | R10: 0 | S10: 0 | T10: 0 | U10: =U13*0.067362 | V10: =V13*0.067362 | W10: =W13*0.067362 | X10: =X13*0.067362 | Y10: =Y13*0.067362 | Z10: =Z13*0.067362 | AA10: =AA13*0.067362 | AB10: =AB13*0.067362 | ... AY10: =AY13*0.067362
B11: 401005 Livestream Classes | D11: 0 | E11: 14 | F11: 25.8 | G11: 65.6 | H11: 23.6 | I11: 73 | J11: 59 | K11: 132 | L11: 115 | M11: 23.6 | N11: 23.6 | O11: 14 | P11: 49.4 | Q11: 64.9 | R11: 82.6 | S11: 18.22 | T11: 31.56 | U11: =U13*0.000509 | V11: =V13*0.000509 | W11: =W13*0.000509 | X11: =X13*0.000509 | Y11: =Y13*0.000509 | Z11: =Z13*0.000509 | AA11: =AA13*0.000509 | AB11: =AB13*0.000509 | ... AY11: =AY13*0.000509
B12: 401006 Wellhub | D12: 0 | E12: 0 | F12: 0 | G12: 0 | H12: 0 | I12: 0 | J12: 44.66 | K12: 52.54 | L12: 52.54 | M12: 0 | N12: 149.74 | O12: 202.28 | P12: 289 | Q12: 341.54 | R12: 289 | S12: 309.99 | T12: 202.28 | U12: =U13*0.002909 | V12: =V13*0.002909 | W12: =W13*0.002909 | X12: =X13*0.002909 | Y12: =Y13*0.002909 | Z12: =Z13*0.002909 | AA12: =AA13*0.002909 | AB12: =AB13*0.002909 | ... AY12: =AY13*0.002909
B13: Total Sessions | D13: 80961.43 | E13: 87308.74 | F13: 98978.04 | G13: 96759.24 | H13: 98655.29 | I13: 95073.26 | J13: 98325.27 | K13: 100210.7 | L13: 95513.2 | M13: 90819.38 | N13: 90823.72 | O13: 87775.66 | P13: 123372.89 | Q13: 99971 | R13: 101372.9 | S13: 98004.29 | T13: 90336.06 | U13: ='Sales Forecast'!U6*Assumptions!$C$12+'Sales Forecast'!T6*Assumptions!$D$12+'Sales Forecast'!S6*Assumptions!$E$12+'Sales Forecast'!R6*Assumptions!$F$12+'Sales Forecast'!Q6*Assumptions!$G$12+'Sales Forecast'!P6*Assumptions!$H$12+'Sales Forecast'!U102*Assumptions!$I$12 | V13: ='Sales Forecast'!V6*Assumptions!$C$12+'Sales Forecast'!U6*Assumptions!$D$12+'Sales Forecast'!T6*Assumptions!$E$12+'Sales Forecast'!S6*Assumptions!$F$12+'Sales Forecast'!R6*Assumptions!$G$12+'Sales Forecast'!Q6*Assumptions!$H$12+'Sales Forecast'!P6*Assumptions!$I$12 | W13: ='Sales Forecast'!W6*Assumptions!$C$12+'Sales Forecast'!V6*Assumptions!$D$12+'Sales Forecast'!U6*Assumptions!$E$12+'Sales Forecast'!T6*Assumptions!$F$12+'Sales Forecast'!S6*Assumptions!$G$12+'Sales Forecast'!R6*Assumptions!$H$12+'Sales Forecast'!Q6*Assumptions!$I$12 | X13: ='Sales Forecast'!X6*Assumptions!$C$12+'Sales Forecast'!W6*Assumptions!$D$12+'Sales Forecast'!V6*Assumptions!$E$12+'Sales Forecast'!U6*Assumptions!$F$12+'Sales Forecast'!T6*Assumptions!$G$12+'Sales Forecast'!S6*Assumptions!$H$12+'Sales Forecast'!R6*Assumptions!$I$12 | Y13: ='Sales Forecast'!Y6*Assumptions!$C$12+'Sales Forecast'!X6*Assumptions!$D$12+'Sales Forecast'!W6*Assumptions!$E$12+'Sales Forecast'!V6*Assumptions!$F$12+'Sales Forecast'!U6*Assumptions!$G$12+'Sales Forecast'!T6*Assumptions!$H$12+'Sales Forecast'!S6*Assumptions!$I$12 | Z13: ='Sales Forecast'!Z6*Assumptions!$C$12+'Sales Forecast'!Y6*Assumptions!$D$12+'Sales Forecast'!X6*Assumptions!$E$12+'Sales Forecast'!W6*Assumptions!$F$12+'Sales Forecast'!V6*Assumptions!$G$12+'Sales Forecast'!U6*Assumptions!$H$12+'Sales Forecast'!T6*Assumptions!$I$12 | AA13: ='Sales Forecast'!AA6*Assumptions!$C$12+'Sales Forecast'!Z6*Assumptions!$D$12+'Sales Forecast'!Y6*Assumptions!$E$12+'Sales Forecast'!X6*Assumptions!$F$12+'Sales Forecast'!W6*Assumptions!$G$12+'Sales Forecast'!V6*Assumptions!$H$12+'Sales Forecast'!U6*Assumptions!$I$12 | AB13: ='Sales Forecast'!AB6*Assumptions!$C$12+'Sales Forecast'!AA6*Assumptions!$D$12+'Sales Forecast'!Z6*Assumptions!$E$12+'Sales Forecast'!Y6*Assumptions!$F$12+'Sales Forecast'!X6*Assumptions!$G$12+'Sales Forecast'!W6*Assumptions!$H$12+'Sales Forecast'!V6*Assumptions!$I$12 | AC13: ='Sales Forecast'!AC6*Assumptions!$C$12+'Sales Forecast'!AB6*Assumptions!$D$12+'Sales Forecast'!AA6*Assumptions!$E$12+'Sales Forecast'!Z6*Assumptions!$F$12+'Sales Forecast'!Y6*Assumptions!$G$12+'Sales Forecast'!X6*Assumptions!$H$12+'Sales Forecast'!W6*Assumptions!$I$12 | ... AY13: ='Sales Forecast'!AY6*Assumptions!$C$12+'Sales Forecast'!AX6*Assumptions!$D$12+'Sales Forecast'!AW6*Assumptions!$E$12+'Sales Forecast'!AV6*Assumptions!$F$12+'Sales Forecast'!AU6*Assumptions!$G$12+'Sales Forecast'!AT6*Assumptions!$H$12+'Sales Forecast'!AS6*Assumptions!$I$12
B14: 403001 Machine Breakage | D14: 10480.79 | E14: 16179.03 | F14: 20305.86 | G14: 20513.48 | H14: 23721.52 | I14: 17938.2 | J14: 14764.55 | K14: 15127.93 | L14: 32901.88 | M14: 22861.69 | N14: 31868.08 | O14: 31038.14 | P14: 17169.98 | Q14: 24950.31 | R14: 19308.85 | S14: 22389.08 | T14: 17746.33 | U14: =U17*0.952386 | V14: =V17*0.952386 | W14: =W17*0.952386 | X14: =X17*0.952386 | Y14: =Y17*0.952386 | Z14: =Z17*0.952386 | AA14: =AA17*0.952386 | AB14: =AB17*0.952386 | ... AY14: =AY17*0.952386
B15: 403003 Private Pilates Breakage | D15: 495 | E15: 3040 | F15: 2615 | G15: 1345 | H15: 1185 | I15: 3540 | J15: 2208 | K15: 2677.5 | L15: 1750 | M15: 1282 | N15: 3100 | O15: 2415 | P15: 1385 | Q15: 430 | R15: 965 | S15: 1375 | T15: 1085 | U15: =U17*0.047211 | V15: =V17*0.047211 | W15: =W17*0.047211 | X15: =X17*0.047211 | Y15: =Y17*0.047211 | Z15: =Z17*0.047211 | AA15: =AA17*0.047211 | AB15: =AB17*0.047211 | ... AY15: =AY17*0.047211
B16: 403004 Other Breakage | D16: 0 | E16: 0 | F16: 0 | G16: 47.2 | H16: 0 | I16: 0 | J16: 0 | K16: 0 | L16: 0 | M16: 35.4 | N16: 0 | O16: 47.2 | P16: 0 | Q16: 35.4 | R16: 0 | S16: 0 | T16: 0 | U16: =U17*0.000402 | V16: =V17*0.000402 | W16: =W17*0.000402 | X16: =X17*0.000402 | Y16: =Y17*0.000402 | Z16: =Z17*0.000402 | AA16: =AA17*0.000402 | AB16: =AB17*0.000402 | ... AY16: =AY17*0.000402
B17: Total Breakage Revenue | D17: 10975.79 | E17: 19219.03 | F17: 22920.86 | G17: 21905.68 | H17: 24906.52 | I17: 23158.2 | J17: 19237.55 | K17: 25185.43 | L17: 34651.88 | M17: 24429.09 | N17: 38110.08 | O17: 38362.84 | P17: 18554.98 | Q17: 25415.71 | R17: 20273.85 | S17: 23764.08 | T17: 18831.33 | U17: ='Sales Forecast'!U6*Assumptions!$C$13+'Sales Forecast'!T6*Assumptions!$D$13+'Sales Forecast'!S6*Assumptions!$E$13+'Sales Forecast'!R6*Assumptions!$F$13+'Sales Forecast'!Q6*Assumptions!$G$13+'Sales Forecast'!P6*Assumptions!$H$13+'Sales Forecast'!U102*Assumptions!$I$13 | V17: ='Sales Forecast'!V6*Assumptions!$C$13+'Sales Forecast'!U6*Assumptions!$D$13+'Sales Forecast'!T6*Assumptions!$E$13+'Sales Forecast'!S6*Assumptions!$F$13+'Sales Forecast'!R6*Assumptions!$G$13+'Sales Forecast'!Q6*Assumptions!$H$13+'Sales Forecast'!P6*Assumptions!$I$13 | W17: ='Sales Forecast'!W6*Assumptions!$C$13+'Sales Forecast'!V6*Assumptions!$D$13+'Sales Forecast'!U6*Assumptions!$E$13+'Sales Forecast'!T6*Assumptions!$F$13+'Sales Forecast'!S6*Assumptions!$G$13+'Sales Forecast'!R6*Assumptions!$H$13+'Sales Forecast'!Q6*Assumptions!$I$13 | X17: ='Sales Forecast'!X6*Assumptions!$C$13+'Sales Forecast'!W6*Assumptions!$D$13+'Sales Forecast'!V6*Assumptions!$E$13+'Sales Forecast'!U6*Assumptions!$F$13+'Sales Forecast'!T6*Assumptions!$G$13+'Sales Forecast'!S6*Assumptions!$H$13+'Sales Forecast'!R6*Assumptions!$I$13 | Y17: ='Sales Forecast'!Y6*Assumptions!$C$13+'Sales Forecast'!X6*Assumptions!$D$13+'Sales Forecast'!W6*Assumptions!$E$13+'Sales Forecast'!V6*Assumptions!$F$13+'Sales Forecast'!U6*Assumptions!$G$13+'Sales Forecast'!T6*Assumptions!$H$13+'Sales Forecast'!S6*Assumptions!$I$13 | Z17: ='Sales Forecast'!Z6*Assumptions!$C$13+'Sales Forecast'!Y6*Assumptions!$D$13+'Sales Forecast'!X6*Assumptions!$E$13+'Sales Forecast'!W6*Assumptions!$F$13+'Sales Forecast'!V6*Assumptions!$G$13+'Sales Forecast'!U6*Assumptions!$H$13+'Sales Forecast'!T6*Assumptions!$I$13 | AA17: ='Sales Forecast'!AA6*Assumptions!$C$13+'Sales Forecast'!Z6*Assumptions!$D$13+'Sales Forecast'!Y6*Assumptions!$E$13+'Sales Forecast'!X6*Assumptions!$F$13+'Sales Forecast'!W6*Assumptions!$G$13+'Sales Forecast'!V6*Assumptions!$H$13+'Sales Forecast'!U6*Assumptions!$I$13 | AB17: ='Sales Forecast'!AB6*Assumptions!$C$13+'Sales Forecast'!AA6*Assumptions!$D$13+'Sales Forecast'!Z6*Assumptions!$E$13+'Sales Forecast'!Y6*Assumptions!$F$13+'Sales Forecast'!X6*Assumptions!$G$13+'Sales Forecast'!W6*Assumptions!$H$13+'Sales Forecast'!V6*Assumptions!$I$13 | AC17: ='Sales Forecast'!AC6*Assumptions!$C$13+'Sales Forecast'!AB6*Assumptions!$D$13+'Sales Forecast'!AA6*Assumptions!$E$13+'Sales Forecast'!Z6*Assumptions!$F$13+'Sales Forecast'!Y6*Assumptions!$G$13+'Sales Forecast'!X6*Assumptions!$H$13+'Sales Forecast'!W6*Assumptions!$I$13 | ... AY17: ='Sales Forecast'!AY6*Assumptions!$C$13+'Sales Forecast'!AX6*Assumptions!$D$13+'Sales Forecast'!AW6*Assumptions!$E$13+'Sales Forecast'!AV6*Assumptions!$F$13+'Sales Forecast'!AU6*Assumptions!$G$13+'Sales Forecast'!AT6*Assumptions!$H$13+'Sales Forecast'!AS6*Assumptions!$I$13
B18: 404000 Retail Sales | D18: 3473 | E18: 2711 | F18: 2259 | G18: 2631 | H18: 2405 | I18: 4161 | J18: 2652 | K18: 2867 | L18: 2571 | M18: 1868 | N18: 1688 | O18: 2220 | P18: 2152 | Q18: 1414 | R18: 1104 | S18: 2254 | T18: 2098 | U18: =1731 | V18: =1731 | W18: =1731 | X18: =1731 | Y18: =1731 | Z18: =1731 | AA18: =1731 | AB18: =1731 | ... AY18: =1731
B19: 406000 Refunds | D19: -3038 | E19: -3570 | F19: -4134 | G19: -6153 | H19: -2902 | I19: -1475.01 | J19: -1196 | K19: -914.01 | L19: -1970 | M19: -1215 | N19: -1510 | O19: -3423 | P19: 3600 | Q19: 1510 | R19: 2088 | S19: 3980 | T19: 1700 | U19: =('Sales Forecast'!U6*Assumptions!$C$12+'Sales Forecast'!T6*Assumptions!$D$12+'Sales Forecast'!S6*Assumptions!$E$12+'Sales Forecast'!R6*Assumptions!$F$12+'Sales Forecast'!Q6*Assumptions!$G$12+'Sales Forecast'!P6*Assumptions!$H$12+'Sales Forecast'!U6*Assumptions!$C$13+'Sales Forecast'!T6*Assumptions!$D$13+'Sales Forecast'!S6*Assumptions!$E$13+'Sales Forecast'!R6*Assumptions!$F$13+'Sales Forecast'!Q6*Assumptions!$G$13+'Sales Forecast'!P6*Assumptions!$H$13+1731)*Assumptions!$C$17 | V19: =('Sales Forecast'!V6*Assumptions!$C$12+'Sales Forecast'!U6*Assumptions!$D$12+'Sales Forecast'!T6*Assumptions!$E$12+'Sales Forecast'!S6*Assumptions!$F$12+'Sales Forecast'!R6*Assumptions!$G$12+'Sales Forecast'!Q6*Assumptions!$H$12+'Sales Forecast'!P6*Assumptions!$I$12+'Sales Forecast'!V6*Assumptions!$C$13+'Sales Forecast'!U6*Assumptions!$D$13+'Sales Forecast'!T6*Assumptions!$E$13+'Sales Forecast'!S6*Assumptions!$F$13+'Sales Forecast'!R6*Assumptions!$G$13+'Sales Forecast'!Q6*Assumptions!$H$13+'Sales Forecast'!P6*Assumptions!$I$13+1731)*Assumptions!$C$17 | W19: =('Sales Forecast'!W6*Assumptions!$C$12+'Sales Forecast'!V6*Assumptions!$D$12+'Sales Forecast'!U6*Assumptions!$E$12+'Sales Forecast'!T6*Assumptions!$F$12+'Sales Forecast'!S6*Assumptions!$G$12+'Sales Forecast'!R6*Assumptions!$H$12+'Sales Forecast'!Q6*Assumptions!$I$12+'Sales Forecast'!W6*Assumptions!$C$13+'Sales Forecast'!V6*Assumptions!$D$13+'Sales Forecast'!U6*Assumptions!$E$13+'Sales Forecast'!T6*Assumptions!$F$13+'Sales Forecast'!S6*Assumptions!$G$13+'Sales Forecast'!R6*Assumptions!$H$13+'Sales Forecast'!Q6*Assumptions!$I$13+1731)*Assumptions!$C$17 | X19: =('Sales Forecast'!X6*Assumptions!$C$12+'Sales Forecast'!W6*Assumptions!$D$12+'Sales Forecast'!V6*Assumptions!$E$12+'Sales Forecast'!U6*Assumptions!$F$12+'Sales Forecast'!T6*Assumptions!$G$12+'Sales Forecast'!S6*Assumptions!$H$12+'Sales Forecast'!R6*Assumptions!$I$12+'Sales Forecast'!X6*Assumptions!$C$13+'Sales Forecast'!W6*Assumptions!$D$13+'Sales Forecast'!V6*Assumptions!$E$13+'Sales Forecast'!U6*Assumptions!$F$13+'Sales Forecast'!T6*Assumptions!$G$13+'Sales Forecast'!S6*Assumptions!$H$13+'Sales Forecast'!R6*Assumptions!$I$13+1731)*Assumptions!$C$17 | Y19: =('Sales Forecast'!Y6*Assumptions!$C$12+'Sales Forecast'!X6*Assumptions!$D$12+'Sales Forecast'!W6*Assumptions!$E$12+'Sales Forecast'!V6*Assumptions!$F$12+'Sales Forecast'!U6*Assumptions!$G$12+'Sales Forecast'!T6*Assumptions!$H$12+'Sales Forecast'!S6*Assumptions!$I$12+'Sales Forecast'!Y6*Assumptions!$C$13+'Sales Forecast'!X6*Assumptions!$D$13+'Sales Forecast'!W6*Assumptions!$E$13+'Sales Forecast'!V6*Assumptions!$F$13+'Sales Forecast'!U6*Assumptions!$G$13+'Sales Forecast'!T6*Assumptions!$H$13+'Sales Forecast'!S6*Assumptions!$I$13+1731)*Assumptions!$C$17 | Z19: =('Sales Forecast'!Z6*Assumptions!$C$12+'Sales Forecast'!Y6*Assumptions!$D$12+'Sales Forecast'!X6*Assumptions!$E$12+'Sales Forecast'!W6*Assumptions!$F$12+'Sales Forecast'!V6*Assumptions!$G$12+'Sales Forecast'!U6*Assumptions!$H$12+'Sales Forecast'!T6*Assumptions!$I$12+'Sales Forecast'!Z6*Assumptions!$C$13+'Sales Forecast'!Y6*Assumptions!$D$13+'Sales Forecast'!X6*Assumptions!$E$13+'Sales Forecast'!W6*Assumptions!$F$13+'Sales Forecast'!V6*Assumptions!$G$13+'Sales Forecast'!U6*Assumptions!$H$13+'Sales Forecast'!T6*Assumptions!$I$13+1731)*Assumptions!$C$17 | AA19: =('Sales Forecast'!AA6*Assumptions!$C$12+'Sales Forecast'!Z6*Assumptions!$D$12+'Sales Forecast'!Y6*Assumptions!$E$12+'Sales Forecast'!X6*Assumptions!$F$12+'Sales Forecast'!W6*Assumptions!$G$12+'Sales Forecast'!V6*Assumptions!$H$12+'Sales Forecast'!U6*Assumptions!$I$12+'Sales Forecast'!AA6*Assumptions!$C$13+'Sales Forecast'!Z6*Assumptions!$D$13+'Sales Forecast'!Y6*Assumptions!$E$13+'Sales Forecast'!X6*Assumptions!$F$13+'Sales Forecast'!W6*Assumptions!$G$13+'Sales Forecast'!V6*Assumptions!$H$13+'Sales Forecast'!U6*Assumptions!$I$13+1731)*Assumptions!$C$17 | AB19: =('Sales Forecast'!AB6*Assumptions!$C$12+'Sales Forecast'!AA6*Assumptions!$D$12+'Sales Forecast'!Z6*Assumptions!$E$12+'Sales Forecast'!Y6*Assumptions!$F$12+'Sales Forecast'!X6*Assumptions!$G$12+'Sales Forecast'!W6*Assumptions!$H$12+'Sales Forecast'!V6*Assumptions!$I$12+'Sales Forecast'!AB6*Assumptions!$C$13+'Sales Forecast'!AA6*Assumptions!$D$13+'Sales Forecast'!Z6*Assumptions!$E$13+'Sales Forecast'!Y6*Assumptions!$F$13+'Sales Forecast'!X6*Assumptions!$G$13+'Sales Forecast'!W6*Assumptions!$H$13+'Sales Forecast'!V6*Assumptions!$I$13+1731)*Assumptions!$C$17 | AC19: =('Sales Forecast'!AC6*Assumptions!$C$12+'Sales Forecast'!AB6*Assumptions!$D$12+'Sales Forecast'!AA6*Assumptions!$E$12+'Sales Forecast'!Z6*Assumptions!$F$12+'Sales Forecast'!Y6*Assumptions!$G$12+'Sales Forecast'!X6*Assumptions!$H$12+'Sales Forecast'!W6*Assumptions!$I$12+'Sales Forecast'!AC6*Assumptions!$C$13+'Sales Forecast'!AB6*Assumptions!$D$13+'Sales Forecast'!AA6*Assumptions!$E$13+'Sales Forecast'!Z6*Assumptions!$F$13+'Sales Forecast'!Y6*Assumptions!$G$13+'Sales Forecast'!X6*Assumptions!$H$13+'Sales Forecast'!W6*Assumptions!$I$13+1731)*Assumptions!$C$17 | ... AY19: =('Sales Forecast'!AY6*Assumptions!$C$12+'Sales Forecast'!AX6*Assumptions!$D$12+'Sales Forecast'!AW6*Assumptions!$E$12+'Sales Forecast'!AV6*Assumptions!$F$12+'Sales Forecast'!AU6*Assumptions!$G$12+'Sales Forecast'!AT6*Assumptions!$H$12+'Sales Forecast'!AS6*Assumptions!$I$12+'Sales Forecast'!AY6*Assumptions!$C$13+'Sales Forecast'!AX6*Assumptions!$D$13+'Sales Forecast'!AW6*Assumptions!$E$13+'Sales Forecast'!AV6*Assumptions!$F$13+'Sales Forecast'!AU6*Assumptions!$G$13+'Sales Forecast'!AT6*Assumptions!$H$13+'Sales Forecast'!AS6*Assumptions!$I$13+1731)*Assumptions!$C$17
B20: 407000 Discounts | D20: -7378.7 | E20: -4533.12 | F20: -6389.54 | G20: -5172.1 | H20: -5087.8 | I20: -7287.54 | J20: -3691.2 | K20: -5800.96 | L20: -3071.62 | M20: -3528.96 | N20: -3664.12 | O20: -2720.3 | P20: 7048.4 | Q20: 3527.26 | R20: 2111.8 | S20: 4735.7 | T20: 2292.2 | U20: =('Sales Forecast'!U6*Assumptions!$C$12+'Sales Forecast'!T6*Assumptions!$D$12+'Sales Forecast'!S6*Assumptions!$E$12+'Sales Forecast'!R6*Assumptions!$F$12+'Sales Forecast'!Q6*Assumptions!$G$12+'Sales Forecast'!P6*Assumptions!$H$12+'Sales Forecast'!U6*Assumptions!$C$13+'Sales Forecast'!T6*Assumptions!$D$13+'Sales Forecast'!S6*Assumptions!$E$13+'Sales Forecast'!R6*Assumptions!$F$13+'Sales Forecast'!Q6*Assumptions!$G$13+'Sales Forecast'!P6*Assumptions!$H$13+1731)*Assumptions!$C$18 | V20: =('Sales Forecast'!V6*Assumptions!$C$12+'Sales Forecast'!U6*Assumptions!$D$12+'Sales Forecast'!T6*Assumptions!$E$12+'Sales Forecast'!S6*Assumptions!$F$12+'Sales Forecast'!R6*Assumptions!$G$12+'Sales Forecast'!Q6*Assumptions!$H$12+'Sales Forecast'!P6*Assumptions!$I$12+'Sales Forecast'!V6*Assumptions!$C$13+'Sales Forecast'!U6*Assumptions!$D$13+'Sales Forecast'!T6*Assumptions!$E$13+'Sales Forecast'!S6*Assumptions!$F$13+'Sales Forecast'!R6*Assumptions!$G$13+'Sales Forecast'!Q6*Assumptions!$H$13+'Sales Forecast'!P6*Assumptions!$I$13+1731)*Assumptions!$C$18 | W20: =('Sales Forecast'!W6*Assumptions!$C$12+'Sales Forecast'!V6*Assumptions!$D$12+'Sales Forecast'!U6*Assumptions!$E$12+'Sales Forecast'!T6*Assumptions!$F$12+'Sales Forecast'!S6*Assumptions!$G$12+'Sales Forecast'!R6*Assumptions!$H$12+'Sales Forecast'!Q6*Assumptions!$I$12+'Sales Forecast'!W6*Assumptions!$C$13+'Sales Forecast'!V6*Assumptions!$D$13+'Sales Forecast'!U6*Assumptions!$E$13+'Sales Forecast'!T6*Assumptions!$F$13+'Sales Forecast'!S6*Assumptions!$G$13+'Sales Forecast'!R6*Assumptions!$H$13+'Sales Forecast'!Q6*Assumptions!$I$13+1731)*Assumptions!$C$18 | X20: =('Sales Forecast'!X6*Assumptions!$C$12+'Sales Forecast'!W6*Assumptions!$D$12+'Sales Forecast'!V6*Assumptions!$E$12+'Sales Forecast'!U6*Assumptions!$F$12+'Sales Forecast'!T6*Assumptions!$G$12+'Sales Forecast'!S6*Assumptions!$H$12+'Sales Forecast'!R6*Assumptions!$I$12+'Sales Forecast'!X6*Assumptions!$C$13+'Sales Forecast'!W6*Assumptions!$D$13+'Sales Forecast'!V6*Assumptions!$E$13+'Sales Forecast'!U6*Assumptions!$F$13+'Sales Forecast'!T6*Assumptions!$G$13+'Sales Forecast'!S6*Assumptions!$H$13+'Sales Forecast'!R6*Assumptions!$I$13+1731)*Assumptions!$C$18 | Y20: =('Sales Forecast'!Y6*Assumptions!$C$12+'Sales Forecast'!X6*Assumptions!$D$12+'Sales Forecast'!W6*Assumptions!$E$12+'Sales Forecast'!V6*Assumptions!$F$12+'Sales Forecast'!U6*Assumptions!$G$12+'Sales Forecast'!T6*Assumptions!$H$12+'Sales Forecast'!S6*Assumptions!$I$12+'Sales Forecast'!Y6*Assumptions!$C$13+'Sales Forecast'!X6*Assumptions!$D$13+'Sales Forecast'!W6*Assumptions!$E$13+'Sales Forecast'!V6*Assumptions!$F$13+'Sales Forecast'!U6*Assumptions!$G$13+'Sales Forecast'!T6*Assumptions!$H$13+'Sales Forecast'!S6*Assumptions!$I$13+1731)*Assumptions!$C$18 | Z20: =('Sales Forecast'!Z6*Assumptions!$C$12+'Sales Forecast'!Y6*Assumptions!$D$12+'Sales Forecast'!X6*Assumptions!$E$12+'Sales Forecast'!W6*Assumptions!$F$12+'Sales Forecast'!V6*Assumptions!$G$12+'Sales Forecast'!U6*Assumptions!$H$12+'Sales Forecast'!T6*Assumptions!$I$12+'Sales Forecast'!Z6*Assumptions!$C$13+'Sales Forecast'!Y6*Assumptions!$D$13+'Sales Forecast'!X6*Assumptions!$E$13+'Sales Forecast'!W6*Assumptions!$F$13+'Sales Forecast'!V6*Assumptions!$G$13+'Sales Forecast'!U6*Assumptions!$H$13+'Sales Forecast'!T6*Assumptions!$I$13+1731)*Assumptions!$C$18 | AA20: =('Sales Forecast'!AA6*Assumptions!$C$12+'Sales Forecast'!Z6*Assumptions!$D$12+'Sales Forecast'!Y6*Assumptions!$E$12+'Sales Forecast'!X6*Assumptions!$F$12+'Sales Forecast'!W6*Assumptions!$G$12+'Sales Forecast'!V6*Assumptions!$H$12+'Sales Forecast'!U6*Assumptions!$I$12+'Sales Forecast'!AA6*Assumptions!$C$13+'Sales Forecast'!Z6*Assumptions!$D$13+'Sales Forecast'!Y6*Assumptions!$E$13+'Sales Forecast'!X6*Assumptions!$F$13+'Sales Forecast'!W6*Assumptions!$G$13+'Sales Forecast'!V6*Assumptions!$H$13+'Sales Forecast'!U6*Assumptions!$I$13+1731)*Assumptions!$C$18 | AB20: =('Sales Forecast'!AB6*Assumptions!$C$12+'Sales Forecast'!AA6*Assumptions!$D$12+'Sales Forecast'!Z6*Assumptions!$E$12+'Sales Forecast'!Y6*Assumptions!$F$12+'Sales Forecast'!X6*Assumptions!$G$12+'Sales Forecast'!W6*Assumptions!$H$12+'Sales Forecast'!V6*Assumptions!$I$12+'Sales Forecast'!AB6*Assumptions!$C$13+'Sales Forecast'!AA6*Assumptions!$D$13+'Sales Forecast'!Z6*Assumptions!$E$13+'Sales Forecast'!Y6*Assumptions!$F$13+'Sales Forecast'!X6*Assumptions!$G$13+'Sales Forecast'!W6*Assumptions!$H$13+'Sales Forecast'!V6*Assumptions!$I$13+1731)*Assumptions!$C$18 | AC20: =('Sales Forecast'!AC6*Assumptions!$C$12+'Sales Forecast'!AB6*Assumptions!$D$12+'Sales Forecast'!AA6*Assumptions!$E$12+'Sales Forecast'!Z6*Assumptions!$F$12+'Sales Forecast'!Y6*Assumptions!$G$12+'Sales Forecast'!X6*Assumptions!$H$12+'Sales Forecast'!W6*Assumptions!$I$12+'Sales Forecast'!AC6*Assumptions!$C$13+'Sales Forecast'!AB6*Assumptions!$D$13+'Sales Forecast'!AA6*Assumptions!$E$13+'Sales Forecast'!Z6*Assumptions!$F$13+'Sales Forecast'!Y6*Assumptions!$G$13+'Sales Forecast'!X6*Assumptions!$H$13+'Sales Forecast'!W6*Assumptions!$I$13+1731)*Assumptions!$C$18 | ... AY20: =('Sales Forecast'!AY6*Assumptions!$C$12+'Sales Forecast'!AX6*Assumptions!$D$12+'Sales Forecast'!AW6*Assumptions!$E$12+'Sales Forecast'!AV6*Assumptions!$F$12+'Sales Forecast'!AU6*Assumptions!$G$12+'Sales Forecast'!AT6*Assumptions!$H$12+'Sales Forecast'!AS6*Assumptions!$I$12+'Sales Forecast'!AY6*Assumptions!$C$13+'Sales Forecast'!AX6*Assumptions!$D$13+'Sales Forecast'!AW6*Assumptions!$E$13+'Sales Forecast'!AV6*Assumptions!$F$13+'Sales Forecast'!AU6*Assumptions!$G$13+'Sales Forecast'!AT6*Assumptions!$H$13+'Sales Forecast'!AS6*Assumptions!$I$13+1731)*Assumptions!$C$18
B21: TOTAL REVENUE | D21: 102263.72 | E21: 108290.08 | F21: 118514.77 | G21: 113589.27 | H21: 119796.34 | I21: 114548.96 | J21: 115924.45 | K21: 121824.66 | L21: 127769.46 | M21: 112372.51 | N21: 125447.68 | O21: 122215.2 | P21: 133431.47 | Q21: 121763.45 | R21: 118550.95 | S21: 115306.67 | T21: 107273.19 | U21: =U13+U17+U18+U19+U20 | V21: =V13+V17+V18+V19+V20 | W21: =W13+W17+W18+W19+W20 | X21: =X13+X17+X18+X19+X20 | Y21: =Y13+Y17+Y18+Y19+Y20 | Z21: =Z13+Z17+Z18+Z19+Z20 | AA21: =AA13+AA17+AA18+AA19+AA20 | AB21: =AB13+AB17+AB18+AB19+AB20 | ... AY21: =AY13+AY17+AY18+AY19+AY20
B22: COST OF GOODS SOLD | D22: 0 | E22: 0 | F22: 0 | G22: 0 | H22: 0 | I22: 0 | J22: 0 | K22: 0 | L22: 0 | M22: 0 | N22: 0 | O22: 0
B23: 501000 Product Cost | D23: 1635 | E23: 1240.75 | F23: 1097.25 | G23: 1298.5 | H23: 1160.5 | I23: 1974.75 | J23: 1301 | K23: 1424.5 | L23: 1231 | M23: 896.5 | N23: 836.5 | O23: 1078 | P23: 1064.8 | Q23: 699.7 | R23: 552 | S23: 1117 | T23: 1037.7 | U23: =U21*Assumptions!$C$20 | V23: =V21*Assumptions!$C$20 | W23: =W21*Assumptions!$C$20 | X23: =X21*Assumptions!$C$20 | Y23: =Y21*Assumptions!$C$20 | Z23: =Z21*Assumptions!$C$20 | AA23: =AA21*Assumptions!$C$20 | AB23: =AB21*Assumptions!$C$20 | ... AY23: =AY21*Assumptions!$C$20
B24: 506000 Merchant Account Fees | D24: 3612.09 | E24: 3333.58 | F24: 3314.08 | G24: 3895.12 | H24: 2604.04 | I24: 2902.85 | J24: 2543.4 | K24: 3738.8 | L24: 2974.49 | M24: 2918.1 | N24: 2598.16 | O24: 2820.42 | P24: 3389.06 | Q24: 3622.31 | R24: 2884.21 | S24: 3288.71 | T24: 2178.41 | U24: =U21*Assumptions!$C$19 | V24: =V21*Assumptions!$C$19 | W24: =W21*Assumptions!$C$19 | X24: =X21*Assumptions!$C$19 | Y24: =Y21*Assumptions!$C$19 | Z24: =Z21*Assumptions!$C$19 | AA24: =AA21*Assumptions!$C$19 | AB24: =AB21*Assumptions!$C$19 | ... AY24: =AY21*Assumptions!$C$19
B25: Total Cost of Goods Sold | D25: 5247.09 | E25: 4574.33 | F25: 4411.33 | G25: 5193.62 | H25: 3764.54 | I25: 4877.6 | J25: 3844.4 | K25: 5163.3 | L25: 4205.49 | M25: 3814.6 | N25: 3434.66 | O25: 5011.79 | P25: 4453.86 | Q25: 4322.01 | R25: 3436.21 | S25: 4405.71 | T25: 3216.11 | U25: =U23+U24 | V25: =V23+V24 | W25: =W23+W24 | X25: =X23+X24 | Y25: =Y23+Y24 | Z25: =Z23+Z24 | AA25: =AA23+AA24 | AB25: =AB23+AB24 | ... AY25: =AY23+AY24
B26: GROSS PROFIT | D26: 97016.63 | E26: 103715.75 | F26: 114103.44 | G26: 108395.65 | H26: 116031.8 | I26: 109671.36 | J26: 112080.05 | K26: 116661.36 | L26: 123563.97 | M26: 108557.91 | N26: 122013.02 | O26: 117203.41 | P26: 128977.61 | Q26: 117441.44 | R26: 115114.74 | S26: 110900.96 | T26: 104057.08 | U26: =U21-U25 | V26: =V21-V25 | W26: =W21-W25 | X26: =X21-X25 | Y26: =Y21-Y25 | Z26: =Z21-Z25 | AA26: =AA21-AA25 | AB26: =AB21-AB25 | ... AY26: =AY21-AY25
B27: OPERATING EXPENSES
B28: 601001 Paid Ads | D28: 1300 | E28: 300 | F28: 0 | G28: 0 | H28: 0 | I28: 2407.42 | J28: 300 | K28: 0 | L28: 0 | M28: 0 | N28: 890.91 | O28: 607.27 | P28: 890.91 | Q28: 89.99 | R28: 0 | S28: 0 | T28: 0 | U28: 0 | V28: 0 | W28: 0 | X28: 0 | Y28: 0 | Z28: 0 | AA28: 0 | AB28: 0 | AC28: 0 | AD28: 0 | AE28: 0 | AF28: 0 | AG28: 0 | AH28: 0 | AI28: 0 | AJ28: 0 | AK28: 0 | AL28: 0 | AM28: 0 | AN28: 0 | AO28: 0 | AP28: 0 | AQ28: 0 | AR28: 0 | AS28: 0 | AT28: 0 | AU28: 0 | AV28: 0 | AW28: 0 | AX28: 0 | AY28: 0
B29: 601005 Content Creation | P29: 0 | Q29: 0 | R29: 0 | S29: 0 | T29: 0 | U29: 0 | V29: 0 | W29: 0 | X29: 0 | Y29: 0 | Z29: 0 | AA29: 0 | AB29: 0 | AC29: 0 | AD29: 0 | AE29: 0 | AF29: 0 | AG29: 0 | AH29: 0 | AI29: 0 | AJ29: 0 | AK29: 0 | AL29: 0 | AM29: 0 | AN29: 0 | AO29: 0 | AP29: 0 | AQ29: 0 | AR29: 0 | AS29: 0 | AT29: 0 | AU29: 0 | AV29: 0 | AW29: 0 | AX29: 0 | AY29: 0
B30: 601006 General Marketing | D30: 0 | E30: 0 | F30: 0 | G30: 0 | H30: 0 | I30: 0 | J30: 0 | K30: 0 | L30: 0 | M30: 0 | N30: 0 | O30: 128.98 | P30: 0 | Q30: 0 | R30: 0 | S30: 0 | T30: 0 | U30: 0 | V30: 0 | W30: 0 | X30: 0 | Y30: 0 | Z30: 0 | AA30: 0 | AB30: 0 | AC30: 0 | AD30: 0 | AE30: 0 | AF30: 0 | AG30: 0 | AH30: 0 | AI30: 0 | AJ30: 0 | AK30: 0 | AL30: 0 | AM30: 0 | AN30: 0 | AO30: 0 | AP30: 0 | AQ30: 0 | AR30: 0 | AS30: 0 | AT30: 0 | AU30: 0 | AV30: 0 | AW30: 0 | AX30: 0 | AY30: 0
B31: 601007 Contractors/Agencies | P31: 0 | Q31: 0 | R31: 0 | S31: 0 | T31: 0 | U31: 0 | V31: 0 | W31: 0 | X31: 0 | Y31: 0 | Z31: 0 | AA31: 0 | AB31: 0 | AC31: 0 | AD31: 0 | AE31: 0 | AF31: 0 | AG31: 0 | AH31: 0 | AI31: 0 | AJ31: 0 | AK31: 0 | AL31: 0 | AM31: 0 | AN31: 0 | AO31: 0 | AP31: 0 | AQ31: 0 | AR31: 0 | AS31: 0 | AT31: 0 | AU31: 0 | AV31: 0 | AW31: 0 | AX31: 0 | AY31: 0
B32: 601010 Website Development | P32: 0 | Q32: 0 | R32: 0 | S32: 0 | T32: 0 | U32: 0 | V32: 0 | W32: 0 | X32: 0 | Y32: 0 | Z32: 0 | AA32: 0 | AB32: 0 | AC32: 0 | AD32: 0 | AE32: 0 | AF32: 0 | AG32: 0 | AH32: 0 | AI32: 0 | AJ32: 0 | AK32: 0 | AL32: 0 | AM32: 0 | AN32: 0 | AO32: 0 | AP32: 0 | AQ32: 0 | AR32: 0 | AS32: 0 | AT32: 0 | AU32: 0 | AV32: 0 | AW32: 0 | AX32: 0 | AY32: 0
B33: Total Marketing | D33: 1300 | E33: 300 | F33: 0 | G33: 0 | H33: 0 | I33: 2407.42 | J33: 300 | K33: 0 | L33: 0 | M33: 0 | N33: 890.91 | O33: 736.25 | P33: 890.91 | Q33: 89.99 | R33: 0 | S33: 0 | T33: 0 | U33: =U28+U29+U30+U31+U32 | V33: =V28+V29+V30+V31+V32 | W33: =W28+W29+W30+W31+W32 | X33: =X28+X29+X30+X31+X32 | Y33: =Y28+Y29+Y30+Y31+Y32 | Z33: =Z28+Z29+Z30+Z31+Z32 | AA33: =AA28+AA29+AA30+AA31+AA32 | AB33: =AB28+AB29+AB30+AB31+AB32 | ... AY33: =AY28+AY29+AY30+AY31+AY32
B34: 602001 Wages | D34: 34343.42 | E34: 35495.95 | F34: 36875.91 | G34: 31272.57 | H34: 35386.68 | I34: 34209.55 | J34: 33486.1 | K34: 36620.89 | L34: 34907.82 | M34: 35061.25 | N34: 34827.27 | O34: 44487.69 | P34: 53569.86 | Q34: 45269.74 | R34: 50483.61 | S34: 48918.6 | T34: 46519.09 | U34: 43315.25 | V34: 38833.52 | W34: 41413.73 | X34: 43268.43 | Y34: 45285.75 | Z34: 47951.33 | AA34: 51055.88 | AB34: 40664.36 | AC34: 40625.33 | AD34: 34619.86 | AE34: 35938.11 | AF34: 42329.64 | AG34: 37828.54 | AH34: 34441.26 | AI34: 36324.13 | AJ34: 37477.66 | AK34: 39849.89 | AL34: 40707.25 | AM34: 44854.49 | AN34: 40664.36 | AO34: 40625.33 | AP34: 34619.86 | AQ34: 35938.11 | AR34: 42329.64 | AS34: 37828.54 | AT34: 34441.26 | AU34: 36324.13 | AV34: 37477.66 | AW34: 39849.89 | AX34: 40707.25 | AY34: 44854.49
B35: 602004 Payroll Taxes | D35: 5601.59 | E35: 4241.17 | F35: 4058.89 | G35: 3607.45 | H35: 3918.25 | I35: 3681.89 | J35: 3764.68 | K35: 4102.57 | L35: 3992.68 | M35: 3965.95 | N35: 4189.02 | O35: 4860.72 | P35: 8608.49 | Q35: 4671.71 | R35: 4875.87 | S35: 4083.91 | T35: 3866.81 | U35: 4859.37 | V35: 4356.58 | W35: 4646.05 | X35: 4854.12 | Y35: 5080.43 | Z35: 5379.47 | AA35: 5727.76 | AB35: 4561.98 | AC35: 4557.6 | AD35: 3883.87 | AE35: 4031.76 | AF35: 4748.8 | AG35: 4243.84 | AH35: 3863.83 | AI35: 4075.06 | AJ35: 4204.47 | AK35: 4470.6 | AL35: 4566.79 | AM35: 5032.05 | AN35: 4561.98 | AO35: 4557.6 | AP35: 3883.87 | AQ35: 4031.76 | AR35: 4748.8 | AS35: 4243.84 | AT35: 3863.83 | AU35: 4075.06 | AV35: 4204.47 | AW35: 4470.6 | AX35: 4566.79 | AY35: 5032.05
B36: 602005 Employee Benefits | D36: 1318.33 | E36: 1778.42 | F36: 7.8 | G36: -899.08 | H36: -1369.81 | I36: 319.78 | J36: 1066.69 | K36: 1575.46 | L36: 1590.26 | M36: 2472.71 | N36: 774.91 | O36: 281.72 | P36: 576.08 | Q36: 604.43 | R36: 788.96 | S36: 594.32 | T36: 505.23 | U36: 560.18 | V36: 502.22 | W36: 535.59 | X36: 559.58 | Y36: 585.66 | Z36: 620.14 | AA36: 660.29 | AB36: 525.9 | AC36: 525.39 | AD36: 447.73 | AE36: 464.77 | AF36: 547.43 | AG36: 489.22 | AH36: 445.42 | AI36: 469.77 | AJ36: 484.69 | AK36: 515.36 | AL36: 526.45 | AM36: 580.09 | AN36: 525.9 | AO36: 525.39 | AP36: 447.73 | AQ36: 464.77 | AR36: 547.43 | AS36: 489.22 | AT36: 445.42 | AU36: 469.77 | AV36: 484.69 | AW36: 515.36 | AX36: 526.45 | AY36: 580.09
B37: 602010 Payroll Processing Fees | D37: 862.93 | E37: 334.34 | F37: 331.49 | G37: 463.71 | H37: 345.74 | I37: 342.89 | J37: 342.89 | K37: 518.61 | L37: 351.44 | M37: 351.44 | N37: 357.14 | O37: 1458.02 | P37: 2263.63 | Q37: 2268.79 | R37: 3275.92 | S37: 2263.27 | T37: 2125.12 | U37: 2200.62 | V37: 1972.92 | W37: 2104.01 | X37: 2198.24 | Y37: 2300.73 | Z37: 2436.15 | AA37: 2593.88 | AB37: 2065.94 | AC37: 2063.96 | AD37: 1758.85 | AE37: 1825.82 | AF37: 2150.54 | AG37: 1921.87 | AH37: 1749.78 | AI37: 1845.44 | AJ37: 1904.04 | AK37: 2024.56 | AL37: 2068.12 | AM37: 2278.82 | AN37: 2065.94 | AO37: 2063.96 | AP37: 1758.85 | AQ37: 1825.82 | AR37: 2150.54 | AS37: 1921.87 | AT37: 1749.78 | AU37: 1845.44 | AV37: 1904.04 | AW37: 2024.56 | AX37: 2068.12 | AY37: 2278.82
B38: Total Payroll | D38: 55306.44 | E38: 51485.19 | F38: 56435.6 | G38: 47706.41 | H38: 53233.19 | I38: 50750.47 | J38: 50784.82 | K38: 55687.65 | L38: 52430.8 | M38: 52739.82 | N38: 51997.08 | O38: 55295.41 | P38: 65018.06 | Q38: 52814.67 | R38: 59424.36 | S38: 55860.1 | T38: 53016.25 | U38: =U34+U35+U36+U37 | V38: =V34+V35+V36+V37 | W38: =W34+W35+W36+W37 | X38: =X34+X35+X36+X37 | Y38: =Y34+Y35+Y36+Y37 | Z38: =Z34+Z35+Z36+Z37 | AA38: =AA34+AA35+AA36+AA37 | AB38: =AB34+AB35+AB36+AB37 | ... AY38: =AY34+AY35+AY36+AY37
B39: 603000 Software & Web Services | D39: 789.62 | E39: 837.5 | F39: 595.3 | G39: 1222.24 | H39: 1287.99 | I39: 1042.77 | J39: 707.99 | K39: 1705.78 | L39: 626.99 | M39: 736.08 | N39: 831.09 | O39: 736.08 | P39: 790.53 | Q39: 1351.94 | R39: 737.08 | S39: 763.26 | T39: 762.26 | U39: 864.31 | V39: 864.31 | W39: 864.31 | X39: 864.31 | Y39: 864.31 | Z39: 864.31 | AA39: 864.31 | AB39: 864.31 | AC39: 864.31 | AD39: 864.31 | AE39: 864.31 | AF39: 864.31 | AG39: 864.31 | AH39: 864.31 | AI39: 864.31 | AJ39: 864.31 | AK39: 864.31 | AL39: 864.31 | AM39: 864.31 | AN39: 864.31 | AO39: 864.31 | AP39: 864.31 | AQ39: 864.31 | AR39: 864.31 | AS39: 864.31 | AT39: 864.31 | AU39: 864.31 | AV39: 864.31 | AW39: 864.31 | AX39: 864.31 | AY39: 864.31
B40: 608000 Insurance | D40: 239.07 | E40: 239.07 | F40: 239.07 | G40: 239.07 | H40: 239.07 | I40: 239.07 | J40: 239.07 | K40: 239.07 | L40: 239.07 | M40: 451.07 | N40: 451.07 | O40: 451.07 | P40: 94.62 | Q40: 94.62 | R40: 230.72 | S40: 230.72 | T40: 251.35 | U40: 154.38 | V40: 154.38 | W40: 154.38 | X40: 154.38 | Y40: 154.38 | Z40: 154.38 | AA40: 154.38 | AB40: 154.38 | AC40: 154.38 | AD40: 154.38 | AE40: 154.38 | AF40: 154.38 | AG40: 154.38 | AH40: 154.38 | AI40: 154.38 | AJ40: 154.38 | AK40: 154.38 | AL40: 154.38 | AM40: 154.38 | AN40: 154.38 | AO40: 154.38 | AP40: 154.38 | AQ40: 154.38 | AR40: 154.38 | AS40: 154.38 | AT40: 154.38 | AU40: 154.38 | AV40: 154.38 | AW40: 154.38 | AX40: 154.38 | AY40: 154.38
B41: 610000 Office Supplies | P41: 689.59 | Q41: 149.49 | R41: 768.45 | S41: 736.05 | T41: 0 | U41: 556.05 | V41: 556.05 | W41: 556.05 | X41: 556.05 | Y41: 556.05 | Z41: 556.05 | AA41: 556.05 | AB41: 556.05 | AC41: 556.05 | AD41: 556.05 | AE41: 556.05 | AF41: 556.05 | AG41: 556.05 | AH41: 556.05 | AI41: 556.05 | AJ41: 556.05 | AK41: 556.05 | AL41: 556.05 | AM41: 556.05 | AN41: 556.05 | AO41: 556.05 | AP41: 556.05 | AQ41: 556.05 | AR41: 556.05 | AS41: 556.05 | AT41: 556.05 | AU41: 556.05 | AV41: 556.05 | AW41: 556.05 | AX41: 556.05 | AY41: 556.05
B42: Total Software & Admin | D42: =D39+D40+D41 | E42: =E39+E40+E41 | F42: =F39+F40+F41 | G42: =G39+G40+G41 | H42: =H39+H40+H41 | I42: =I39+I40+I41 | J42: =J39+J40+J41 | K42: =K39+K40+K41 | ... AY42: =AY39+AY40+AY41
B43: 604100 Legal Fees | D43: 0 | E43: 0 | F43: 220 | G43: 0 | H43: 0 | I43: 0 | J43: 0 | K43: 0 | L43: 0 | M43: 0 | N43: 0 | O43: 0 | P43: 0 | Q43: 0 | R43: 0 | S43: 0 | T43: 0 | U43: 0 | V43: 0 | W43: 0 | X43: 0 | Y43: 0 | Z43: 0 | AA43: 0 | AB43: 0 | AC43: 0 | AD43: 0 | AE43: 0 | AF43: 0 | AG43: 0 | AH43: 0 | AI43: 0 | AJ43: 0 | AK43: 0 | AL43: 0 | AM43: 0 | AN43: 0 | AO43: 0 | AP43: 0 | AQ43: 0 | AR43: 0 | AS43: 0 | AT43: 0 | AU43: 0 | AV43: 0 | AW43: 0 | AX43: 0 | AY43: 0
B44: 604200 Accounting | D44: 321.75 | E44: 143 | F44: 225.5 | G44: 45.5 | H44: 2095.5 | I44: 45.5 | J44: 45.5 | K44: 951.75 | L44: 52.5 | M44: 0 | N44: 154.54 | O44: 101.6 | P44: 0 | Q44: 301.82 | R44: 440 | S44: 0 | T44: 0 | U44: 136.49 | V44: 136.49 | W44: 136.49 | X44: 136.49 | Y44: 136.49 | Z44: 136.49 | AA44: 136.49 | AB44: 136.49 | AC44: 136.49 | AD44: 136.49 | AE44: 136.49 | AF44: 136.49 | AG44: 136.49 | AH44: 136.49 | AI44: 136.49 | AJ44: 136.49 | AK44: 136.49 | AL44: 136.49 | AM44: 136.49 | AN44: 136.49 | AO44: 136.49 | AP44: 136.49 | AQ44: 136.49 | AR44: 136.49 | AS44: 136.49 | AT44: 136.49 | AU44: 136.49 | AV44: 136.49 | AW44: 136.49 | AX44: 136.49 | AY44: 136.49
B45: 604300 Recruiting | D45: 0 | E45: 0 | F45: 0 | G45: 75 | H45: 0 | I45: 0 | J45: 0 | K45: 0 | L45: 0 | M45: 0 | N45: 0 | O45: 0 | P45: 0 | Q45: 0 | R45: 0 | S45: 0 | T45: 0 | U45: 0 | V45: 0 | W45: 0 | X45: 0 | Y45: 0 | Z45: 0 | AA45: 0 | AB45: 0 | AC45: 0 | AD45: 0 | AE45: 0 | AF45: 0 | AG45: 0 | AH45: 0 | AI45: 0 | AJ45: 0 | AK45: 0 | AL45: 0 | AM45: 0 | AN45: 0 | AO45: 0 | AP45: 0 | AQ45: 0 | AR45: 0 | AS45: 0 | AT45: 0 | AU45: 0 | AV45: 0 | AW45: 0 | AX45: 0 | AY45: 0
B46: 604400 Other Professional Fees | D46: 0 | E46: 0 | F46: 0 | G46: 0 | H46: 0 | I46: 0 | J46: 479.1 | K46: 479.1 | L46: 479.1 | M46: 481 | N46: 481 | O46: 497.2 | P46: 517 | Q46: 517 | R46: 517 | S46: 517 | T46: 517 | U46: 380.51 | V46: 380.51 | W46: 380.51 | X46: 380.51 | Y46: 380.51 | Z46: 380.51 | AA46: 380.51 | AB46: 380.51 | AC46: 380.51 | AD46: 380.51 | AE46: 380.51 | AF46: 380.51 | AG46: 380.51 | AH46: 380.51 | AI46: 380.51 | AJ46: 380.51 | AK46: 380.51 | AL46: 380.51 | AM46: 380.51 | AN46: 380.51 | AO46: 380.51 | AP46: 380.51 | AQ46: 380.51 | AR46: 380.51 | AS46: 380.51 | AT46: 380.51 | AU46: 380.51 | AV46: 380.51 | AW46: 380.51 | AX46: 380.51 | AY46: 380.51
B47: Total Professional Fees | D47: 321.75 | E47: 143 | F47: 445.5 | G47: 120.5 | H47: 2095.5 | I47: 45.5 | J47: 524.6 | K47: 1430.85 | L47: 531.6 | M47: 481 | N47: 635.54 | O47: 598.8 | P47: 517 | Q47: 818.82 | R47: 957 | S47: 517 | T47: 517 | U47: =U43+U44+U45+U46 | V47: =V43+V44+V45+V46 | W47: =W43+W44+W45+W46 | X47: =X43+X44+X45+X46 | Y47: =Y43+Y44+Y45+Y46 | Z47: =Z43+Z44+Z45+Z46 | AA47: =AA43+AA44+AA45+AA46 | AB47: =AB43+AB44+AB45+AB46 | ... AY47: =AY43+AY44+AY45+AY46
B48: 605000 Travel | P48: 17.1 | Q48: 34 | R48: 6.02 | S48: 12.53 | T48: 0 | U48: 21.44 | V48: 21.44 | W48: 21.44 | X48: 21.44 | Y48: 21.44 | Z48: 21.44 | AA48: 21.44 | AB48: 21.44 | AC48: 21.44 | AD48: 21.44 | AE48: 21.44 | AF48: 21.44 | AG48: 21.44 | AH48: 21.44 | AI48: 21.44 | AJ48: 21.44 | AK48: 21.44 | AL48: 21.44 | AM48: 21.44 | AN48: 21.44 | AO48: 21.44 | AP48: 21.44 | AQ48: 21.44 | AR48: 21.44 | AS48: 21.44 | AT48: 21.44 | AU48: 21.44 | AV48: 21.44 | AW48: 21.44 | AX48: 21.44 | AY48: 21.44
B49: 606000 Meals | D49: 0 | E49: 0 | F49: 93.28 | G49: 96.02 | H49: 0 | I49: 17.77 | J49: 0 | K49: 114.05 | L49: 280.75 | M49: 72.09 | N49: 357.66 | O49: 224.29 | P49: 122.32 | Q49: 90.59 | R49: 78.12 | S49: 92.19 | T49: 0 | U49: 117.98 | V49: 117.98 | W49: 117.98 | X49: 117.98 | Y49: 117.98 | Z49: 117.98 | AA49: 117.98 | AB49: 117.98 | AC49: 117.98 | AD49: 117.98 | AE49: 117.98 | AF49: 117.98 | AG49: 117.98 | AH49: 117.98 | AI49: 117.98 | AJ49: 117.98 | AK49: 117.98 | AL49: 117.98 | AM49: 117.98 | AN49: 117.98 | AO49: 117.98 | AP49: 117.98 | AQ49: 117.98 | AR49: 117.98 | AS49: 117.98 | AT49: 117.98 | AU49: 117.98 | AV49: 117.98 | AW49: 117.98 | AX49: 117.98 | AY49: 117.98
B50: Total Travel & Meals | D50: =D48+D49 | E50: =E48+E49 | F50: =F48+F49 | G50: =G48+G49 | H50: =H48+H49 | I50: =I48+I49 | J50: =J48+J49 | K50: =K48+K49 | ... AY50: =AY48+AY49
B51: 616001 Electricity | P51: 0 | Q51: 0 | R51: 0 | S51: 0 | T51: 0 | U51: 0 | V51: 0 | W51: 0 | X51: 0 | Y51: 0 | Z51: 0 | AA51: 0 | AB51: 0 | AC51: 0 | AD51: 0 | AE51: 0 | AF51: 0 | AG51: 0 | AH51: 0 | AI51: 0 | AJ51: 0 | AK51: 0 | AL51: 0 | AM51: 0 | AN51: 0 | AO51: 0 | AP51: 0 | AQ51: 0 | AR51: 0 | AS51: 0 | AT51: 0 | AU51: 0 | AV51: 0 | AW51: 0 | AX51: 0 | AY51: 0
B52: 616002 Internet & TV | P52: 212.35 | Q52: 212.35 | R52: 212.35 | S52: 212.35 | T52: 0 | U52: 70.32 | V52: 70.32 | W52: 70.32 | X52: 70.32 | Y52: 70.32 | Z52: 70.32 | AA52: 70.32 | AB52: 70.32 | AC52: 70.32 | AD52: 70.32 | AE52: 70.32 | AF52: 70.32 | AG52: 70.32 | AH52: 70.32 | AI52: 70.32 | AJ52: 70.32 | AK52: 70.32 | AL52: 70.32 | AM52: 70.32 | AN52: 70.32 | AO52: 70.32 | AP52: 70.32 | AQ52: 70.32 | AR52: 70.32 | AS52: 70.32 | AT52: 70.32 | AU52: 70.32 | AV52: 70.32 | AW52: 70.32 | AX52: 70.32 | AY52: 70.32
B53: 616003 Phone service | D53: 107.21 | E53: 107.34 | F53: 107.34 | G53: 107.34 | H53: 107.12 | I53: 192.37 | J53: 107.12 | K53: 107.12 | L53: 107.12 | M53: 109.65 | N53: 109.7 | O53: 116.73 | P53: 116.81 | Q53: 2776.16 | R53: 116.75 | S53: 116.75 | T53: 116.73 | U53: 258.84 | V53: 258.84 | W53: 258.84 | X53: 258.84 | Y53: 258.84 | Z53: 258.84 | AA53: 258.84 | AB53: 258.84 | AC53: 258.84 | AD53: 258.84 | AE53: 258.84 | AF53: 258.84 | AG53: 258.84 | AH53: 258.84 | AI53: 258.84 | AJ53: 258.84 | AK53: 258.84 | AL53: 258.84 | AM53: 258.84 | AN53: 258.84 | AO53: 258.84 | AP53: 258.84 | AQ53: 258.84 | AR53: 258.84 | AS53: 258.84 | AT53: 258.84 | AU53: 258.84 | AV53: 258.84 | AW53: 258.84 | AX53: 258.84 | AY53: 258.84
B54: 616004 Water & sewer | P54: 0 | Q54: 0 | R54: 0 | S54: 0 | T54: 0 | U54: 0 | V54: 0 | W54: 0 | X54: 0 | Y54: 0 | Z54: 0 | AA54: 0 | AB54: 0 | AC54: 0 | AD54: 0 | AE54: 0 | AF54: 0 | AG54: 0 | AH54: 0 | AI54: 0 | AJ54: 0 | AK54: 0 | AL54: 0 | AM54: 0 | AN54: 0 | AO54: 0 | AP54: 0 | AQ54: 0 | AR54: 0 | AS54: 0 | AT54: 0 | AU54: 0 | AV54: 0 | AW54: 0 | AX54: 0 | AY54: 0
B55: 616005 Disposal Services | P55: 0 | Q55: 0 | R55: 0 | S55: 0 | T55: 0 | U55: 0 | V55: 0 | W55: 0 | X55: 0 | Y55: 0 | Z55: 0 | AA55: 0 | AB55: 0 | AC55: 0 | AD55: 0 | AE55: 0 | AF55: 0 | AG55: 0 | AH55: 0 | AI55: 0 | AJ55: 0 | AK55: 0 | AL55: 0 | AM55: 0 | AN55: 0 | AO55: 0 | AP55: 0 | AQ55: 0 | AR55: 0 | AS55: 0 | AT55: 0 | AU55: 0 | AV55: 0 | AW55: 0 | AX55: 0 | AY55: 0
B56: Total Utilities | D56: 107.21 | E56: 107.34 | F56: 107.34 | G56: 107.34 | H56: 107.12 | I56: 192.37 | J56: 107.12 | K56: 107.12 | L56: 107.12 | M56: 109.65 | N56: 109.7 | O56: 116.73 | P56: 329.16 | Q56: 2988.51 | R56: 329.1 | S56: 329.1 | T56: 329.08 | U56: =U51+U52+U53+U54+U55 | V56: =V51+V52+V53+V54+V55 | W56: =W51+W52+W53+W54+W55 | X56: =X51+X52+X53+X54+X55 | Y56: =Y51+Y52+Y53+Y54+Y55 | Z56: =Z51+Z52+Z53+Z54+Z55 | AA56: =AA51+AA52+AA53+AA54+AA55 | AB56: =AB51+AB52+AB53+AB54+AB55 | ... AY56: =AY51+AY52+AY53+AY54+AY55
B57: 701000 Rent | D57: 6916.2 | E57: 6916.2 | F57: 6916.2 | G57: 6916.2 | H57: 6916.2 | I57: 6916.2 | J57: 6916.2 | K57: 6916.2 | L57: 6916.2 | M57: 6916.2 | N57: 6916.2 | O57: 6916.2 | P57: 6916.2 | Q57: 6916.2 | R57: 6916.2 | S57: 6916.2 | T57: 6916.2 | U57: 7077.57 | V57: 7077.57 | W57: 7077.57 | X57: 7077.57 | Y57: 7077.57 | Z57: 7077.57 | AA57: 7077.57 | AB57: 7077.57 | AC57: 7077.57 | AD57: 7077.57 | AE57: 7077.57 | AF57: 7077.57 | AG57: 7077.57 | AH57: 7077.57 | AI57: 7077.57 | AJ57: 7077.57 | AK57: 7077.57 | AL57: 7077.57 | AM57: 7077.57 | AN57: 7077.57 | AO57: 7077.57 | AP57: 7077.57 | AQ57: 7077.57 | AR57: 7077.57 | AS57: 7077.57 | AT57: 7077.57 | AU57: 7077.57 | AV57: 7077.57 | AW57: 7077.57 | AX57: 7077.57 | AY57: 7077.57
B58: 702000 Security | D58: 0 | E58: 0 | F58: 31.99 | G58: 31.99 | H58: 31.99 | I58: 31.99 | J58: 31.99 | K58: 31.99 | L58: 31.99 | M58: 31.99 | N58: 31.99 | O58: 34.99 | P58: 34.99 | Q58: 34.99 | R58: 34.99 | S58: 34.99 | T58: 34.99 | U58: 35.81 | V58: 35.81 | W58: 35.81 | X58: 35.81 | Y58: 35.81 | Z58: 35.81 | AA58: 35.81 | AB58: 35.81 | AC58: 35.81 | AD58: 35.81 | AE58: 35.81 | AF58: 35.81 | AG58: 35.81 | AH58: 35.81 | AI58: 35.81 | AJ58: 35.81 | AK58: 35.81 | AL58: 35.81 | AM58: 35.81 | AN58: 35.81 | AO58: 35.81 | AP58: 35.81 | AQ58: 35.81 | AR58: 35.81 | AS58: 35.81 | AT58: 35.81 | AU58: 35.81 | AV58: 35.81 | AW58: 35.81 | AX58: 35.81 | AY58: 35.81
B59: 703000 Cleaning | D59: 98.68 | E59: 0 | F59: 0 | G59: 0 | H59: 155.45 | I59: 122.39 | J59: 418.3 | K59: 93.4 | L59: 83.79 | M59: 199.79 | N59: 913.28 | O59: 223.88 | P59: 732.99 | Q59: 198.34 | R59: 743.55 | S59: 346.55 | T59: 246.89 | U59: 517.15 | V59: 517.15 | W59: 517.15 | X59: 517.15 | Y59: 517.15 | Z59: 517.15 | AA59: 517.15 | AB59: 517.15 | AC59: 517.15 | AD59: 517.15 | AE59: 517.15 | AF59: 517.15 | AG59: 517.15 | AH59: 517.15 | AI59: 517.15 | AJ59: 517.15 | AK59: 517.15 | AL59: 517.15 | AM59: 517.15 | AN59: 517.15 | AO59: 517.15 | AP59: 517.15 | AQ59: 517.15 | AR59: 517.15 | AS59: 517.15 | AT59: 517.15 | AU59: 517.15 | AV59: 517.15 | AW59: 517.15 | AX59: 517.15 | AY59: 517.15
B60: 705000 Property Maintenance | D60: 7602.49 | E60: 1203.41 | F60: 1203.41 | G60: 1203.41 | H60: 1203.41 | I60: 1203.41 | J60: 1203.41 | K60: 1203.41 | L60: 1203.41 | M60: 1203.41 | N60: 1203.41 | O60: 1203.41 | P60: 800 | Q60: 800 | R60: 800 | S60: 800 | T60: 800 | U60: 818.67 | V60: 818.67 | W60: 818.67 | X60: 818.67 | Y60: 818.67 | Z60: 818.67 | AA60: 818.67 | AB60: 818.67 | AC60: 818.67 | AD60: 818.67 | AE60: 818.67 | AF60: 818.67 | AG60: 818.67 | AH60: 818.67 | AI60: 818.67 | AJ60: 818.67 | AK60: 818.67 | AL60: 818.67 | AM60: 818.67 | AN60: 818.67 | AO60: 818.67 | AP60: 818.67 | AQ60: 818.67 | AR60: 818.67 | AS60: 818.67 | AT60: 818.67 | AU60: 818.67 | AV60: 818.67 | AW60: 818.67 | AX60: 818.67 | AY60: 818.67
B61: Total Property Costs | D61: 14871.04 | E61: 8119.61 | F61: 8151.6 | G61: 8151.6 | H61: 8457.05 | I61: 8373.99 | J61: 8569.9 | K61: 8805.07 | L61: 8235.39 | M61: 8351.39 | N61: 9064.88 | O61: 8378.48 | P61: 8484.18 | Q61: 7949.53 | R61: 8494.74 | S61: 8097.74 | T61: 7998.08 | U61: =U57+U58+U59+U60 | V61: =V57+V58+V59+V60 | W61: =W57+W58+W59+W60 | X61: =X57+X58+X59+X60 | Y61: =Y57+Y58+Y59+Y60 | Z61: =Z57+Z58+Z59+Z60 | AA61: =AA57+AA58+AA59+AA60 | AB61: =AB57+AB58+AB59+AB60 | ... AY61: =AY57+AY58+AY59+AY60
B62: TOTAL OPERATING EXPENSES | D62: 75219.97 | E62: 63462.62 | F62: 66987.79 | G62: 58845.52 | H62: 67706.9 | I62: 64765.81 | J62: 66366.43 | K62: 68959.91 | L62: 63501.45 | M62: 63626.39 | N62: 65482.4 | O62: 66951.07 | P62: 76953.47 | Q62: 66382.16 | R62: 71025.59 | S62: 67335.39 | T62: 64099.98 | U62: =U33+U38+U42+U47+U50+U56+U61 | V62: =V33+V38+V42+V47+V50+V56+V61 | W62: =W33+W38+W42+W47+W50+W56+W61 | X62: =X33+X38+X42+X47+X50+X56+X61 | Y62: =Y33+Y38+Y42+Y47+Y50+Y56+Y61 | Z62: =Z33+Z38+Z42+Z47+Z50+Z56+Z61 | AA62: =AA33+AA38+AA42+AA47+AA50+AA56+AA61 | AB62: =AB33+AB38+AB42+AB47+AB50+AB56+AB61 | ... AY62: =AY33+AY38+AY42+AY47+AY50+AY56+AY61
B63: NET OPERATING INCOME (EBITDA) | D63: 21796.66 | E63: 40253.13 | F63: 47115.65 | G63: 49550.13 | H63: 48324.9 | I63: 44905.55 | J63: 45713.62 | K63: 47701.45 | L63: 60062.52 | M63: 44931.52 | N63: 56530.62 | O63: 50252.34 | P63: 52024.14 | Q63: 51059.28 | R63: 44089.15 | S63: 43565.57 | T63: 39957.1 | U63: =U26-U62 | V63: =V26-V62 | W63: =W26-W62 | X63: =X26-X62 | Y63: =Y26-Y62 | Z63: =Z26-Z62 | AA63: =AA26-AA62 | AB63: =AB26-AB62 | ... AY63: =AY26-AY62
B64: OTHER
B65: 810000 Depreciation | D65: 1842.1 | E65: 1850.23 | F65: 1850.23 | G65: 1853.38 | H65: 1855.96 | I65: 1855.96 | J65: 1855.96 | K65: 1855.96 | L65: 1882.97 | M65: 1882.97 | N65: 1882.97 | O65: 1483.6 | P65: 1833.55 | Q65: 1833.55 | R65: 1833.55 | S65: 1833.55 | T65: 1833.55 | U65: 1833.55 | V65: 1833.55 | W65: 1833.55 | X65: 1833.55 | Y65: 1833.55 | Z65: 1833.55 | AA65: 1833.55 | AB65: 1833.55 | AC65: 1833.55 | AD65: 1833.55 | AE65: 1833.55 | AF65: 1833.55 | AG65: 1833.55 | AH65: 1833.55 | AI65: 1833.55 | AJ65: 1833.55 | AK65: 1833.55 | AL65: 1833.55 | AM65: 1833.55 | AN65: =AN69*0.929227 | AO65: =AO69*0.929227 | AP65: =AP69*0.929227 | AQ65: =AQ69*0.929227 | AR65: =AR69*0.929227 | AS65: =AS69*0.929227 | AT65: =AT69*0.929227 | AU65: =AU69*0.929227 | ... AY65: =AY69*0.929227
B66: 901000 Interest Expense | P66: 0 | Q66: 0 | R66: 0 | S66: 0 | T66: 0 | U66: 0 | V66: 0 | W66: 0 | X66: 0 | Y66: 0 | Z66: 0 | AA66: 0 | AB66: 0 | AC66: 0 | AD66: 0 | AE66: 0 | AF66: 0 | AG66: 0 | AH66: 0 | AI66: 0 | AJ66: 0 | AK66: 0 | AL66: 0 | AM66: 0 | AN66: 0 | AO66: 0 | AP66: 0 | AQ66: 0 | AR66: 0 | AS66: 0 | AT66: 0 | AU66: 0 | AV66: 0 | AW66: 0 | AX66: 0 | AY66: 0
B67: 902000 Taxes Paid | P67: 0 | Q67: 558.6 | R67: 0 | S67: 0 | T67: 0 | U67: 0 | V67: 0 | W67: 0 | X67: 0 | Y67: 0 | Z67: 0 | AA67: 0 | AB67: 0 | AC67: 0 | AD67: 0 | AE67: 0 | AF67: 0 | AG67: 0 | AH67: 0 | AI67: 0 | AJ67: 0 | AK67: 0 | AL67: 0 | AM67: 0 | AN67: =AN69*0.070773 | AO67: =AO69*0.070773 | AP67: =AP69*0.070773 | AQ67: =AQ69*0.070773 | AR67: =AR69*0.070773 | AS67: =AS69*0.070773 | AT67: =AT69*0.070773 | AU67: =AU69*0.070773 | ... AY67: =AY69*0.070773
B68: 903000 Property taxes | D68: 0 | E68: 0 | F68: 0 | G68: 366 | H68: 0 | I68: 0 | J68: 0 | K68: 0 | L68: 0 | M68: 0 | N68: 0 | O68: 0 | P68: 0 | Q68: 0 | R68: 0 | S68: 0 | T68: 0 | U68: 0 | V68: 0 | W68: 0 | X68: 0 | Y68: 0 | Z68: 0 | AA68: 0 | AB68: 0 | AC68: 0 | AD68: 0 | AE68: 0 | AF68: 0 | AG68: 0 | AH68: 0 | AI68: 0 | AJ68: 0 | AK68: 0 | AL68: 0 | AM68: 0 | AN68: 0 | AO68: 0 | AP68: 0 | AQ68: 0 | AR68: 0 | AS68: 0 | AT68: 0 | AU68: 0 | AV68: 0 | AW68: 0 | AX68: 0 | AY68: 0
B69: Total Other Expenses | D69: 1842.1 | E69: 1850.23 | F69: 1850.23 | G69: 2219.38 | H69: 1855.96 | I69: 1855.96 | J69: 1855.96 | K69: 1855.96 | L69: 1882.97 | M69: 1882.97 | N69: 1882.97 | O69: 1483.6 | P69: 1833.55 | Q69: 2392.15 | R69: 1833.55 | S69: 1833.55 | T69: 1833.55 | U69: 0 | V69: 0 | W69: 0 | X69: 0 | Y69: 0 | Z69: 0 | AA69: 0 | AB69: 0 | AC69: 0 | AD69: 0 | AE69: 0 | AF69: 0 | AG69: 0 | AH69: 0 | AI69: 0 | AJ69: 0 | AK69: 0 | AL69: 0 | AM69: 0 | AN69: 0 | AO69: 0 | AP69: 0 | AQ69: 0 | AR69: 0 | AS69: 0 | AT69: 0 | AU69: 0 | AV69: 0 | AW69: 0 | AX69: 0 | AY69: 0
B70: NET INCOME | D70: 19954.56 | E70: 38402.9 | F70: 45265.42 | G70: 47330.75 | H70: 46468.94 | I70: 43049.59 | J70: 43857.66 | K70: 45845.49 | L70: 58179.55 | M70: 43048.55 | N70: 54647.65 | O70: 48768.74 | P70: 50190.59 | Q70: 48667.13 | R70: 42255.6 | S70: 41732.02 | T70: 38123.55 | U70: =U63-U69 | V70: =V63-V69 | W70: =W63-W69 | X70: =X63-X69 | Y70: =Y63-Y69 | Z70: =Z63-Z69 | AA70: =AA63-AA69 | AB70: =AB63-AB69 | ... AY70: =AY63-AY69

Sheet CC P&L
B2: Culver City (CC) — Profit & Loss
B4: Monthly P&L (Detail)
B5: Line Item | D5: Jan 2025 | E5: Feb 2025 | F5: Mar 2025 | G5: Apr 2025 | H5: May 2025 | I5: Jun 2025 | J5: Jul 2025 | K5: Aug 2025 | L5: Sep 2025 | M5: Oct 2025 | N5: Nov 2025 | O5: Dec 2025 | P5: Jan 2026 | Q5: Feb 2026 | R5: Mar 2026 | S5: Apr 2026 | T5: May 2026 | U5: Jun 2026 | V5: Jul 2026 | W5: Aug 2026 | X5: Sep 2026 | Y5: Oct 2026 | Z5: Nov 2026 | AA5: Dec 2026 | AB5: Jan 2027 | AC5: Feb 2027 | AD5: Mar 2027 | AE5: Apr 2027 | AF5: May 2027 | AG5: Jun 2027 | AH5: Jul 2027 | AI5: Aug 2027 | AJ5: Sep 2027 | AK5: Oct 2027 | AL5: Nov 2027 | AM5: Dec 2027 | AN5: Jan 2028 | AO5: Feb 2028 | AP5: Mar 2028 | AQ5: Apr 2028 | AR5: May 2028 | AS5: Jun 2028 | AT5: Jul 2028 | AU5: Aug 2028 | AV5: Sep 2028 | AW5: Oct 2028 | AX5: Nov 2028 | AY5: Dec 2028
B6: INCOME | D6: 0 | E6: 0 | F6: 0 | G6: 0 | H6: 0 | I6: 0 | J6: 0 | K6: 0 | L6: 0 | M6: 0 | N6: 0 | O6: 0
B7: 401001 Machine | D7: 0 | E7: 0 | F7: 0 | G7: 0 | H7: 0 | I7: 0 | J7: 0 | K7: 42 | L7: 7077.37 | M7: 16280.87 | N7: 14326 | O7: 16551.11 | P7: 20397.9 | Q7: 19548.71 | R7: 20502.29 | S7: 17774.52 | T7: 16596.07 | U7: =U13*0.510234 | V7: =V13*0.510234 | W7: =W13*0.510234 | X7: =X13*0.510234 | Y7: =Y13*0.510234 | Z7: =Z13*0.510234 | AA7: =AA13*0.510234 | AB7: =AB13*0.510234 | ... AY7: =AY13*0.510234
B8: 401002 Private Pilates | D8: 0 | E8: 0 | F8: 0 | G8: 0 | H8: 0 | I8: 0 | J8: 0 | K8: 0 | L8: 415 | M8: 945 | N8: 860 | O8: 940 | P8: 1170 | Q8: 1512 | R8: 1002 | S8: 333 | T8: 628 | U8: =U13*0.026202 | V8: =V13*0.026202 | W8: =W13*0.026202 | X8: =X13*0.026202 | Y8: =Y13*0.026202 | Z8: =Z13*0.026202 | AA8: =AA13*0.026202 | AB8: =AB13*0.026202 | ... AY8: =AY13*0.026202
B9: 401003 Class Pass | D9: 0 | E9: 0 | F9: 0 | G9: 0 | H9: 0 | I9: 0 | J9: 0 | K9: 0 | L9: 4370.27 | M9: 10831.25 | N9: 12060.69 | O9: 11638.45 | P9: 16587.97 | Q9: 15654.65 | R9: 18636.28 | S9: 15895 | T9: 15302.32 | U9: =U13*0.435551 | V9: =V13*0.435551 | W9: =W13*0.435551 | X9: =X13*0.435551 | Y9: =Y13*0.435551 | Z9: =Z13*0.435551 | AA9: =AA13*0.435551 | AB9: =AB13*0.435551 | ... AY9: =AY13*0.435551
B10: 401004 Mighty Teacher Training | D10: 0 | E10: 0 | F10: 0 | G10: 0 | H10: 0 | I10: 0 | J10: 0 | K10: 0 | L10: 0 | M10: 0 | N10: 0 | O10: 0 | P10: 0 | Q10: 1845.46 | R10: 961.04 | S10: 0 | T10: 0 | U10: =U13*0.018306 | V10: =V13*0.018306 | W10: =W13*0.018306 | X10: =X13*0.018306 | Y10: =Y13*0.018306 | Z10: =Z13*0.018306 | AA10: =AA13*0.018306 | AB10: =AB13*0.018306 | ... AY10: =AY13*0.018306
B11: 401005 Livestream Classes | D11: 0 | E11: 0 | F11: 0 | G11: 0 | H11: 0 | I11: 0 | J11: 0 | K11: 0 | L11: 0 | M11: 0 | N11: 0 | O11: 0 | P11: 0 | Q11: 0 | R11: 0 | S11: 37.6 | T11: 65.22 | U11: =U13*0.000245 | V11: =V13*0.000245 | W11: =W13*0.000245 | X11: =X13*0.000245 | Y11: =Y13*0.000245 | Z11: =Z13*0.000245 | AA11: =AA13*0.000245 | AB11: =AB13*0.000245 | ... AY11: =AY13*0.000245
B12: 401006 Wellhub | D12: 0 | E12: 0 | F12: 0 | G12: 0 | H12: 0 | I12: 0 | J12: 0 | K12: 0 | L12: 0 | M12: 0 | N12: 0 | O12: 122.4 | P12: 336.6 | Q12: 367.2 | R12: 501.84 | S12: 244.8 | T12: 82.62 | U12: =U13*0.009461 | V12: =V13*0.009461 | W12: =W13*0.009461 | X12: =X13*0.009461 | Y12: =Y13*0.009461 | Z12: =Z13*0.009461 | AA12: =AA13*0.009461 | AB12: =AB13*0.009461 | ... AY12: =AY13*0.009461
B13: Total Sessions | D13: 0 | E13: 0 | F13: 0 | G13: 0 | H13: 0 | I13: 0 | J13: 0 | K13: 42 | L13: 11862.64 | M13: 28057.12 | N13: 27246.69 | O13: 29251.96 | P13: 38492.47 | Q13: 38928.02 | R13: 41603.45 | S13: 34284.92 | T13: 32674.23 | U13: ='Sales Forecast'!U7*Assumptions!$C$12+'Sales Forecast'!T7*Assumptions!$D$12+'Sales Forecast'!S7*Assumptions!$E$12+'Sales Forecast'!R7*Assumptions!$F$12+'Sales Forecast'!Q7*Assumptions!$G$12+'Sales Forecast'!P7*Assumptions!$H$12+'Sales Forecast'!U103*Assumptions!$I$12 | V13: ='Sales Forecast'!V7*Assumptions!$C$12+'Sales Forecast'!U7*Assumptions!$D$12+'Sales Forecast'!T7*Assumptions!$E$12+'Sales Forecast'!S7*Assumptions!$F$12+'Sales Forecast'!R7*Assumptions!$G$12+'Sales Forecast'!Q7*Assumptions!$H$12+'Sales Forecast'!P7*Assumptions!$I$12 | W13: ='Sales Forecast'!W7*Assumptions!$C$12+'Sales Forecast'!V7*Assumptions!$D$12+'Sales Forecast'!U7*Assumptions!$E$12+'Sales Forecast'!T7*Assumptions!$F$12+'Sales Forecast'!S7*Assumptions!$G$12+'Sales Forecast'!R7*Assumptions!$H$12+'Sales Forecast'!Q7*Assumptions!$I$12 | X13: ='Sales Forecast'!X7*Assumptions!$C$12+'Sales Forecast'!W7*Assumptions!$D$12+'Sales Forecast'!V7*Assumptions!$E$12+'Sales Forecast'!U7*Assumptions!$F$12+'Sales Forecast'!T7*Assumptions!$G$12+'Sales Forecast'!S7*Assumptions!$H$12+'Sales Forecast'!R7*Assumptions!$I$12 | Y13: ='Sales Forecast'!Y7*Assumptions!$C$12+'Sales Forecast'!X7*Assumptions!$D$12+'Sales Forecast'!W7*Assumptions!$E$12+'Sales Forecast'!V7*Assumptions!$F$12+'Sales Forecast'!U7*Assumptions!$G$12+'Sales Forecast'!T7*Assumptions!$H$12+'Sales Forecast'!S7*Assumptions!$I$12 | Z13: ='Sales Forecast'!Z7*Assumptions!$C$12+'Sales Forecast'!Y7*Assumptions!$D$12+'Sales Forecast'!X7*Assumptions!$E$12+'Sales Forecast'!W7*Assumptions!$F$12+'Sales Forecast'!V7*Assumptions!$G$12+'Sales Forecast'!U7*Assumptions!$H$12+'Sales Forecast'!T7*Assumptions!$I$12 | AA13: ='Sales Forecast'!AA7*Assumptions!$C$12+'Sales Forecast'!Z7*Assumptions!$D$12+'Sales Forecast'!Y7*Assumptions!$E$12+'Sales Forecast'!X7*Assumptions!$F$12+'Sales Forecast'!W7*Assumptions!$G$12+'Sales Forecast'!V7*Assumptions!$H$12+'Sales Forecast'!U7*Assumptions!$I$12 | AB13: ='Sales Forecast'!AB7*Assumptions!$C$12+'Sales Forecast'!AA7*Assumptions!$D$12+'Sales Forecast'!Z7*Assumptions!$E$12+'Sales Forecast'!Y7*Assumptions!$F$12+'Sales Forecast'!X7*Assumptions!$G$12+'Sales Forecast'!W7*Assumptions!$H$12+'Sales Forecast'!V7*Assumptions!$I$12 | AC13: ='Sales Forecast'!AC7*Assumptions!$C$12+'Sales Forecast'!AB7*Assumptions!$D$12+'Sales Forecast'!AA7*Assumptions!$E$12+'Sales Forecast'!Z7*Assumptions!$F$12+'Sales Forecast'!Y7*Assumptions!$G$12+'Sales Forecast'!X7*Assumptions!$H$12+'Sales Forecast'!W7*Assumptions!$I$12 | ... AY13: ='Sales Forecast'!AY7*Assumptions!$C$12+'Sales Forecast'!AX7*Assumptions!$D$12+'Sales Forecast'!AW7*Assumptions!$E$12+'Sales Forecast'!AV7*Assumptions!$F$12+'Sales Forecast'!AU7*Assumptions!$G$12+'Sales Forecast'!AT7*Assumptions!$H$12+'Sales Forecast'!AS7*Assumptions!$I$12
B14: 403001 Machine Breakage | D14: 0 | E14: 0 | F14: 0 | G14: 0 | H14: 0 | I14: 0 | J14: 0 | K14: 0 | L14: 251.2 | M14: 1268.4 | N14: 4314.82 | O14: 5585 | P14: 2890.72 | Q14: 4105.76 | R14: 2843.53 | S14: 4737.65 | T14: 4879.41 | U14: =U17*0.979836 | V14: =V17*0.979836 | W14: =W17*0.979836 | X14: =X17*0.979836 | Y14: =Y17*0.979836 | Z14: =Z17*0.979836 | AA14: =AA17*0.979836 | AB14: =AB17*0.979836 | ... AY14: =AY17*0.979836
B15: 403003 Private Pilates Breakage | D15: 0 | E15: 0 | F15: 0 | G15: 0 | H15: 0 | I15: 0 | J15: 0 | K15: 0 | L15: 0 | M15: 595 | N15: 675 | O15: 785 | P15: 0 | Q15: 225 | R15: 0 | S15: 75 | T15: 230 | U15: =U17*0.020164 | V15: =V17*0.020164 | W15: =W17*0.020164 | X15: =X17*0.020164 | Y15: =Y17*0.020164 | Z15: =Z17*0.020164 | AA15: =AA17*0.020164 | AB15: =AB17*0.020164 | ... AY15: =AY17*0.020164
B16: 403004 Other Breakage | D16: 0 | E16: 0 | F16: 0 | G16: 0 | H16: 0 | I16: 0 | J16: 0 | K16: 0 | L16: 0 | M16: 0 | N16: 0 | O16: 0 | P16: 0 | Q16: 0 | R16: 0 | S16: 0 | T16: 0 | U16: 0 | V16: 0 | W16: 0 | X16: 0 | Y16: 0 | Z16: 0 | AA16: 0 | AB16: 0 | AC16: 0 | AD16: 0 | AE16: 0 | AF16: 0 | AG16: 0 | AH16: 0 | AI16: 0 | AJ16: 0 | AK16: 0 | AL16: 0 | AM16: 0 | AN16: 0 | AO16: 0 | AP16: 0 | AQ16: 0 | AR16: 0 | AS16: 0 | AT16: 0 | AU16: 0 | AV16: 0 | AW16: 0 | AX16: 0 | AY16: 0
B17: Total Breakage Revenue | D17: 0 | E17: 0 | F17: 0 | G17: 0 | H17: 0 | I17: 0 | J17: 0 | K17: 0 | L17: 251.2 | M17: 1863.4 | N17: 4989.82 | O17: 6370 | P17: 2890.72 | Q17: 4330.76 | R17: 2843.53 | S17: 4812.65 | T17: 5109.41 | U17: ='Sales Forecast'!U7*Assumptions!$C$13+'Sales Forecast'!T7*Assumptions!$D$13+'Sales Forecast'!S7*Assumptions!$E$13+'Sales Forecast'!R7*Assumptions!$F$13+'Sales Forecast'!Q7*Assumptions!$G$13+'Sales Forecast'!P7*Assumptions!$H$13+'Sales Forecast'!U103*Assumptions!$I$13 | V17: ='Sales Forecast'!V7*Assumptions!$C$13+'Sales Forecast'!U7*Assumptions!$D$13+'Sales Forecast'!T7*Assumptions!$E$13+'Sales Forecast'!S7*Assumptions!$F$13+'Sales Forecast'!R7*Assumptions!$G$13+'Sales Forecast'!Q7*Assumptions!$H$13+'Sales Forecast'!P7*Assumptions!$I$13 | W17: ='Sales Forecast'!W7*Assumptions!$C$13+'Sales Forecast'!V7*Assumptions!$D$13+'Sales Forecast'!U7*Assumptions!$E$13+'Sales Forecast'!T7*Assumptions!$F$13+'Sales Forecast'!S7*Assumptions!$G$13+'Sales Forecast'!R7*Assumptions!$H$13+'Sales Forecast'!Q7*Assumptions!$I$13 | X17: ='Sales Forecast'!X7*Assumptions!$C$13+'Sales Forecast'!W7*Assumptions!$D$13+'Sales Forecast'!V7*Assumptions!$E$13+'Sales Forecast'!U7*Assumptions!$F$13+'Sales Forecast'!T7*Assumptions!$G$13+'Sales Forecast'!S7*Assumptions!$H$13+'Sales Forecast'!R7*Assumptions!$I$13 | Y17: ='Sales Forecast'!Y7*Assumptions!$C$13+'Sales Forecast'!X7*Assumptions!$D$13+'Sales Forecast'!W7*Assumptions!$E$13+'Sales Forecast'!V7*Assumptions!$F$13+'Sales Forecast'!U7*Assumptions!$G$13+'Sales Forecast'!T7*Assumptions!$H$13+'Sales Forecast'!S7*Assumptions!$I$13 | Z17: ='Sales Forecast'!Z7*Assumptions!$C$13+'Sales Forecast'!Y7*Assumptions!$D$13+'Sales Forecast'!X7*Assumptions!$E$13+'Sales Forecast'!W7*Assumptions!$F$13+'Sales Forecast'!V7*Assumptions!$G$13+'Sales Forecast'!U7*Assumptions!$H$13+'Sales Forecast'!T7*Assumptions!$I$13 | AA17: ='Sales Forecast'!AA7*Assumptions!$C$13+'Sales Forecast'!Z7*Assumptions!$D$13+'Sales Forecast'!Y7*Assumptions!$E$13+'Sales Forecast'!X7*Assumptions!$F$13+'Sales Forecast'!W7*Assumptions!$G$13+'Sales Forecast'!V7*Assumptions!$H$13+'Sales Forecast'!U7*Assumptions!$I$13 | AB17: ='Sales Forecast'!AB7*Assumptions!$C$13+'Sales Forecast'!AA7*Assumptions!$D$13+'Sales Forecast'!Z7*Assumptions!$E$13+'Sales Forecast'!Y7*Assumptions!$F$13+'Sales Forecast'!X7*Assumptions!$G$13+'Sales Forecast'!W7*Assumptions!$H$13+'Sales Forecast'!V7*Assumptions!$I$13 | AC17: ='Sales Forecast'!AC7*Assumptions!$C$13+'Sales Forecast'!AB7*Assumptions!$D$13+'Sales Forecast'!AA7*Assumptions!$E$13+'Sales Forecast'!Z7*Assumptions!$F$13+'Sales Forecast'!Y7*Assumptions!$G$13+'Sales Forecast'!X7*Assumptions!$H$13+'Sales Forecast'!W7*Assumptions!$I$13 | ... AY17: ='Sales Forecast'!AY7*Assumptions!$C$13+'Sales Forecast'!AX7*Assumptions!$D$13+'Sales Forecast'!AW7*Assumptions!$E$13+'Sales Forecast'!AV7*Assumptions!$F$13+'Sales Forecast'!AU7*Assumptions!$G$13+'Sales Forecast'!AT7*Assumptions!$H$13+'Sales Forecast'!AS7*Assumptions!$I$13
B18: 404000 Retail Sales | D18: 0 | E18: 0 | F18: 0 | G18: 0 | H18: 0 | I18: 0 | J18: 0 | K18: 0 | L18: 1068 | M18: 1968 | N18: 1402 | O18: 1200 | P18: 1794 | Q18: 1344 | R18: 1586 | S18: 946 | T18: 928 | U18: =1417.5 | V18: =1417.5 | W18: =1417.5 | X18: =1417.5 | Y18: =1417.5 | Z18: =1417.5 | AA18: =1417.5 | AB18: =1417.5 | ... AY18: =1417.5
B19: 406000 Refunds | D19: 0 | E19: 0 | F19: 0 | G19: 0 | H19: 0 | I19: 0 | J19: 0 | K19: 0 | L19: 0 | M19: 0 | N19: -1110 | O19: -414 | P19: 1048 | Q19: 740 | R19: 500 | S19: 245 | T19: 443 | U19: =('Sales Forecast'!U7*Assumptions!$C$12+'Sales Forecast'!T7*Assumptions!$D$12+'Sales Forecast'!S7*Assumptions!$E$12+'Sales Forecast'!R7*Assumptions!$F$12+'Sales Forecast'!Q7*Assumptions!$G$12+'Sales Forecast'!P7*Assumptions!$H$12+'Sales Forecast'!U7*Assumptions!$C$13+'Sales Forecast'!T7*Assumptions!$D$13+'Sales Forecast'!S7*Assumptions!$E$13+'Sales Forecast'!R7*Assumptions!$F$13+'Sales Forecast'!Q7*Assumptions!$G$13+'Sales Forecast'!P7*Assumptions!$H$13+1417.5)*Assumptions!$C$17 | V19: =('Sales Forecast'!V7*Assumptions!$C$12+'Sales Forecast'!U7*Assumptions!$D$12+'Sales Forecast'!T7*Assumptions!$E$12+'Sales Forecast'!S7*Assumptions!$F$12+'Sales Forecast'!R7*Assumptions!$G$12+'Sales Forecast'!Q7*Assumptions!$H$12+'Sales Forecast'!P7*Assumptions!$I$12+'Sales Forecast'!V7*Assumptions!$C$13+'Sales Forecast'!U7*Assumptions!$D$13+'Sales Forecast'!T7*Assumptions!$E$13+'Sales Forecast'!S7*Assumptions!$F$13+'Sales Forecast'!R7*Assumptions!$G$13+'Sales Forecast'!Q7*Assumptions!$H$13+'Sales Forecast'!P7*Assumptions!$I$13+1417.5)*Assumptions!$C$17 | W19: =('Sales Forecast'!W7*Assumptions!$C$12+'Sales Forecast'!V7*Assumptions!$D$12+'Sales Forecast'!U7*Assumptions!$E$12+'Sales Forecast'!T7*Assumptions!$F$12+'Sales Forecast'!S7*Assumptions!$G$12+'Sales Forecast'!R7*Assumptions!$H$12+'Sales Forecast'!Q7*Assumptions!$I$12+'Sales Forecast'!W7*Assumptions!$C$13+'Sales Forecast'!V7*Assumptions!$D$13+'Sales Forecast'!U7*Assumptions!$E$13+'Sales Forecast'!T7*Assumptions!$F$13+'Sales Forecast'!S7*Assumptions!$G$13+'Sales Forecast'!R7*Assumptions!$H$13+'Sales Forecast'!Q7*Assumptions!$I$13+1417.5)*Assumptions!$C$17 | X19: =('Sales Forecast'!X7*Assumptions!$C$12+'Sales Forecast'!W7*Assumptions!$D$12+'Sales Forecast'!V7*Assumptions!$E$12+'Sales Forecast'!U7*Assumptions!$F$12+'Sales Forecast'!T7*Assumptions!$G$12+'Sales Forecast'!S7*Assumptions!$H$12+'Sales Forecast'!R7*Assumptions!$I$12+'Sales Forecast'!X7*Assumptions!$C$13+'Sales Forecast'!W7*Assumptions!$D$13+'Sales Forecast'!V7*Assumptions!$E$13+'Sales Forecast'!U7*Assumptions!$F$13+'Sales Forecast'!T7*Assumptions!$G$13+'Sales Forecast'!S7*Assumptions!$H$13+'Sales Forecast'!R7*Assumptions!$I$13+1417.5)*Assumptions!$C$17 | Y19: =('Sales Forecast'!Y7*Assumptions!$C$12+'Sales Forecast'!X7*Assumptions!$D$12+'Sales Forecast'!W7*Assumptions!$E$12+'Sales Forecast'!V7*Assumptions!$F$12+'Sales Forecast'!U7*Assumptions!$G$12+'Sales Forecast'!T7*Assumptions!$H$12+'Sales Forecast'!S7*Assumptions!$I$12+'Sales Forecast'!Y7*Assumptions!$C$13+'Sales Forecast'!X7*Assumptions!$D$13+'Sales Forecast'!W7*Assumptions!$E$13+'Sales Forecast'!V7*Assumptions!$F$13+'Sales Forecast'!U7*Assumptions!$G$13+'Sales Forecast'!T7*Assumptions!$H$13+'Sales Forecast'!S7*Assumptions!$I$13+1417.5)*Assumptions!$C$17 | Z19: =('Sales Forecast'!Z7*Assumptions!$C$12+'Sales Forecast'!Y7*Assumptions!$D$12+'Sales Forecast'!X7*Assumptions!$E$12+'Sales Forecast'!W7*Assumptions!$F$12+'Sales Forecast'!V7*Assumptions!$G$12+'Sales Forecast'!U7*Assumptions!$H$12+'Sales Forecast'!T7*Assumptions!$I$12+'Sales Forecast'!Z7*Assumptions!$C$13+'Sales Forecast'!Y7*Assumptions!$D$13+'Sales Forecast'!X7*Assumptions!$E$13+'Sales Forecast'!W7*Assumptions!$F$13+'Sales Forecast'!V7*Assumptions!$G$13+'Sales Forecast'!U7*Assumptions!$H$13+'Sales Forecast'!T7*Assumptions!$I$13+1417.5)*Assumptions!$C$17 | AA19: =('Sales Forecast'!AA7*Assumptions!$C$12+'Sales Forecast'!Z7*Assumptions!$D$12+'Sales Forecast'!Y7*Assumptions!$E$12+'Sales Forecast'!X7*Assumptions!$F$12+'Sales Forecast'!W7*Assumptions!$G$12+'Sales Forecast'!V7*Assumptions!$H$12+'Sales Forecast'!U7*Assumptions!$I$12+'Sales Forecast'!AA7*Assumptions!$C$13+'Sales Forecast'!Z7*Assumptions!$D$13+'Sales Forecast'!Y7*Assumptions!$E$13+'Sales Forecast'!X7*Assumptions!$F$13+'Sales Forecast'!W7*Assumptions!$G$13+'Sales Forecast'!V7*Assumptions!$H$13+'Sales Forecast'!U7*Assumptions!$I$13+1417.5)*Assumptions!$C$17 | AB19: =('Sales Forecast'!AB7*Assumptions!$C$12+'Sales Forecast'!AA7*Assumptions!$D$12+'Sales Forecast'!Z7*Assumptions!$E$12+'Sales Forecast'!Y7*Assumptions!$F$12+'Sales Forecast'!X7*Assumptions!$G$12+'Sales Forecast'!W7*Assumptions!$H$12+'Sales Forecast'!V7*Assumptions!$I$12+'Sales Forecast'!AB7*Assumptions!$C$13+'Sales Forecast'!AA7*Assumptions!$D$13+'Sales Forecast'!Z7*Assumptions!$E$13+'Sales Forecast'!Y7*Assumptions!$F$13+'Sales Forecast'!X7*Assumptions!$G$13+'Sales Forecast'!W7*Assumptions!$H$13+'Sales Forecast'!V7*Assumptions!$I$13+1417.5)*Assumptions!$C$17 | AC19: =('Sales Forecast'!AC7*Assumptions!$C$12+'Sales Forecast'!AB7*Assumptions!$D$12+'Sales Forecast'!AA7*Assumptions!$E$12+'Sales Forecast'!Z7*Assumptions!$F$12+'Sales Forecast'!Y7*Assumptions!$G$12+'Sales Forecast'!X7*Assumptions!$H$12+'Sales Forecast'!W7*Assumptions!$I$12+'Sales Forecast'!AC7*Assumptions!$C$13+'Sales Forecast'!AB7*Assumptions!$D$13+'Sales Forecast'!AA7*Assumptions!$E$13+'Sales Forecast'!Z7*Assumptions!$F$13+'Sales Forecast'!Y7*Assumptions!$G$13+'Sales Forecast'!X7*Assumptions!$H$13+'Sales Forecast'!W7*Assumptions!$I$13+1417.5)*Assumptions!$C$17 | ... AY19: =('Sales Forecast'!AY7*Assumptions!$C$12+'Sales Forecast'!AX7*Assumptions!$D$12+'Sales Forecast'!AW7*Assumptions!$E$12+'Sales Forecast'!AV7*Assumptions!$F$12+'Sales Forecast'!AU7*Assumptions!$G$12+'Sales Forecast'!AT7*Assumptions!$H$12+'Sales Forecast'!AS7*Assumptions!$I$12+'Sales Forecast'!AY7*Assumptions!$C$13+'Sales Forecast'!AX7*Assumptions!$D$13+'Sales Forecast'!AW7*Assumptions!$E$13+'Sales Forecast'!AV7*Assumptions!$F$13+'Sales Forecast'!AU7*Assumptions!$G$13+'Sales Forecast'!AT7*Assumptions!$H$13+'Sales Forecast'!AS7*Assumptions!$I$13+1417.5)*Assumptions!$C$17
B20: 407000 Discounts | D20: 0 | E20: 0 | F20: 0 | G20: 0 | H20: 0 | I20: 0 | J20: 0 | K20: -635 | L20: -7992.7 | M20: -3983.8 | N20: -6214.6 | O20: -4542.6 | P20: 5079.6 | Q20: 2303.3 | R20: 2607.5 | S20: 2783.2 | T20: 1884.8 | U20: =('Sales Forecast'!U7*Assumptions!$C$12+'Sales Forecast'!T7*Assumptions!$D$12+'Sales Forecast'!S7*Assumptions!$E$12+'Sales Forecast'!R7*Assumptions!$F$12+'Sales Forecast'!Q7*Assumptions!$G$12+'Sales Forecast'!P7*Assumptions!$H$12+'Sales Forecast'!U7*Assumptions!$C$13+'Sales Forecast'!T7*Assumptions!$D$13+'Sales Forecast'!S7*Assumptions!$E$13+'Sales Forecast'!R7*Assumptions!$F$13+'Sales Forecast'!Q7*Assumptions!$G$13+'Sales Forecast'!P7*Assumptions!$H$13+1417.5)*Assumptions!$C$18 | V20: =('Sales Forecast'!V7*Assumptions!$C$12+'Sales Forecast'!U7*Assumptions!$D$12+'Sales Forecast'!T7*Assumptions!$E$12+'Sales Forecast'!S7*Assumptions!$F$12+'Sales Forecast'!R7*Assumptions!$G$12+'Sales Forecast'!Q7*Assumptions!$H$12+'Sales Forecast'!P7*Assumptions!$I$12+'Sales Forecast'!V7*Assumptions!$C$13+'Sales Forecast'!U7*Assumptions!$D$13+'Sales Forecast'!T7*Assumptions!$E$13+'Sales Forecast'!S7*Assumptions!$F$13+'Sales Forecast'!R7*Assumptions!$G$13+'Sales Forecast'!Q7*Assumptions!$H$13+'Sales Forecast'!P7*Assumptions!$I$13+1417.5)*Assumptions!$C$18 | W20: =('Sales Forecast'!W7*Assumptions!$C$12+'Sales Forecast'!V7*Assumptions!$D$12+'Sales Forecast'!U7*Assumptions!$E$12+'Sales Forecast'!T7*Assumptions!$F$12+'Sales Forecast'!S7*Assumptions!$G$12+'Sales Forecast'!R7*Assumptions!$H$12+'Sales Forecast'!Q7*Assumptions!$I$12+'Sales Forecast'!W7*Assumptions!$C$13+'Sales Forecast'!V7*Assumptions!$D$13+'Sales Forecast'!U7*Assumptions!$E$13+'Sales Forecast'!T7*Assumptions!$F$13+'Sales Forecast'!S7*Assumptions!$G$13+'Sales Forecast'!R7*Assumptions!$H$13+'Sales Forecast'!Q7*Assumptions!$I$13+1417.5)*Assumptions!$C$18 | X20: =('Sales Forecast'!X7*Assumptions!$C$12+'Sales Forecast'!W7*Assumptions!$D$12+'Sales Forecast'!V7*Assumptions!$E$12+'Sales Forecast'!U7*Assumptions!$F$12+'Sales Forecast'!T7*Assumptions!$G$12+'Sales Forecast'!S7*Assumptions!$H$12+'Sales Forecast'!R7*Assumptions!$I$12+'Sales Forecast'!X7*Assumptions!$C$13+'Sales Forecast'!W7*Assumptions!$D$13+'Sales Forecast'!V7*Assumptions!$E$13+'Sales Forecast'!U7*Assumptions!$F$13+'Sales Forecast'!T7*Assumptions!$G$13+'Sales Forecast'!S7*Assumptions!$H$13+'Sales Forecast'!R7*Assumptions!$I$13+1417.5)*Assumptions!$C$18 | Y20: =('Sales Forecast'!Y7*Assumptions!$C$12+'Sales Forecast'!X7*Assumptions!$D$12+'Sales Forecast'!W7*Assumptions!$E$12+'Sales Forecast'!V7*Assumptions!$F$12+'Sales Forecast'!U7*Assumptions!$G$12+'Sales Forecast'!T7*Assumptions!$H$12+'Sales Forecast'!S7*Assumptions!$I$12+'Sales Forecast'!Y7*Assumptions!$C$13+'Sales Forecast'!X7*Assumptions!$D$13+'Sales Forecast'!W7*Assumptions!$E$13+'Sales Forecast'!V7*Assumptions!$F$13+'Sales Forecast'!U7*Assumptions!$G$13+'Sales Forecast'!T7*Assumptions!$H$13+'Sales Forecast'!S7*Assumptions!$I$13+1417.5)*Assumptions!$C$18 | Z20: =('Sales Forecast'!Z7*Assumptions!$C$12+'Sales Forecast'!Y7*Assumptions!$D$12+'Sales Forecast'!X7*Assumptions!$E$12+'Sales Forecast'!W7*Assumptions!$F$12+'Sales Forecast'!V7*Assumptions!$G$12+'Sales Forecast'!U7*Assumptions!$H$12+'Sales Forecast'!T7*Assumptions!$I$12+'Sales Forecast'!Z7*Assumptions!$C$13+'Sales Forecast'!Y7*Assumptions!$D$13+'Sales Forecast'!X7*Assumptions!$E$13+'Sales Forecast'!W7*Assumptions!$F$13+'Sales Forecast'!V7*Assumptions!$G$13+'Sales Forecast'!U7*Assumptions!$H$13+'Sales Forecast'!T7*Assumptions!$I$13+1417.5)*Assumptions!$C$18 | AA20: =('Sales Forecast'!AA7*Assumptions!$C$12+'Sales Forecast'!Z7*Assumptions!$D$12+'Sales Forecast'!Y7*Assumptions!$E$12+'Sales Forecast'!X7*Assumptions!$F$12+'Sales Forecast'!W7*Assumptions!$G$12+'Sales Forecast'!V7*Assumptions!$H$12+'Sales Forecast'!U7*Assumptions!$I$12+'Sales Forecast'!AA7*Assumptions!$C$13+'Sales Forecast'!Z7*Assumptions!$D$13+'Sales Forecast'!Y7*Assumptions!$E$13+'Sales Forecast'!X7*Assumptions!$F$13+'Sales Forecast'!W7*Assumptions!$G$13+'Sales Forecast'!V7*Assumptions!$H$13+'Sales Forecast'!U7*Assumptions!$I$13+1417.5)*Assumptions!$C$18 | AB20: =('Sales Forecast'!AB7*Assumptions!$C$12+'Sales Forecast'!AA7*Assumptions!$D$12+'Sales Forecast'!Z7*Assumptions!$E$12+'Sales Forecast'!Y7*Assumptions!$F$12+'Sales Forecast'!X7*Assumptions!$G$12+'Sales Forecast'!W7*Assumptions!$H$12+'Sales Forecast'!V7*Assumptions!$I$12+'Sales Forecast'!AB7*Assumptions!$C$13+'Sales Forecast'!AA7*Assumptions!$D$13+'Sales Forecast'!Z7*Assumptions!$E$13+'Sales Forecast'!Y7*Assumptions!$F$13+'Sales Forecast'!X7*Assumptions!$G$13+'Sales Forecast'!W7*Assumptions!$H$13+'Sales Forecast'!V7*Assumptions!$I$13+1417.5)*Assumptions!$C$18 | AC20: =('Sales Forecast'!AC7*Assumptions!$C$12+'Sales Forecast'!AB7*Assumptions!$D$12+'Sales Forecast'!AA7*Assumptions!$E$12+'Sales Forecast'!Z7*Assumptions!$F$12+'Sales Forecast'!Y7*Assumptions!$G$12+'Sales Forecast'!X7*Assumptions!$H$12+'Sales Forecast'!W7*Assumptions!$I$12+'Sales Forecast'!AC7*Assumptions!$C$13+'Sales Forecast'!AB7*Assumptions!$D$13+'Sales Forecast'!AA7*Assumptions!$E$13+'Sales Forecast'!Z7*Assumptions!$F$13+'Sales Forecast'!Y7*Assumptions!$G$13+'Sales Forecast'!X7*Assumptions!$H$13+'Sales Forecast'!W7*Assumptions!$I$13+1417.5)*Assumptions!$C$18 | ... AY20: =('Sales Forecast'!AY7*Assumptions!$C$12+'Sales Forecast'!AX7*Assumptions!$D$12+'Sales Forecast'!AW7*Assumptions!$E$12+'Sales Forecast'!AV7*Assumptions!$F$12+'Sales Forecast'!AU7*Assumptions!$G$12+'Sales Forecast'!AT7*Assumptions!$H$12+'Sales Forecast'!AS7*Assumptions!$I$12+'Sales Forecast'!AY7*Assumptions!$C$13+'Sales Forecast'!AX7*Assumptions!$D$13+'Sales Forecast'!AW7*Assumptions!$E$13+'Sales Forecast'!AV7*Assumptions!$F$13+'Sales Forecast'!AU7*Assumptions!$G$13+'Sales Forecast'!AT7*Assumptions!$H$13+'Sales Forecast'!AS7*Assumptions!$I$13+1417.5)*Assumptions!$C$18
B21: TOTAL REVENUE | D21: 0 | E21: 0 | F21: 0 | G21: 0 | H21: 0 | I21: 0 | J21: 0 | K21: -593 | L21: 5189.14 | M21: 27904.72 | N21: 26313.91 | O21: 31865.36 | P21: 37049.59 | Q21: 41559.48 | R21: 42925.48 | S21: 37015.37 | T21: 36383.84 | U21: =U13+U17+U18+U19+U20 | V21: =V13+V17+V18+V19+V20 | W21: =W13+W17+W18+W19+W20 | X21: =X13+X17+X18+X19+X20 | Y21: =Y13+Y17+Y18+Y19+Y20 | Z21: =Z13+Z17+Z18+Z19+Z20 | AA21: =AA13+AA17+AA18+AA19+AA20 | AB21: =AB13+AB17+AB18+AB19+AB20 | ... AY21: =AY13+AY17+AY18+AY19+AY20
B22: COST OF GOODS SOLD | D22: 0 | E22: 0 | F22: 0 | G22: 0 | H22: 0 | I22: 0 | J22: 0 | K22: 0 | L22: 0 | M22: 0 | N22: 0 | O22: 0
B23: 501000 Product Cost | D23: 0 | E23: 0 | F23: 0 | G23: 0 | H23: 0 | I23: 0 | J23: 0 | K23: 0 | L23: 523.5 | M23: 966.1 | N23: 696 | O23: 590.1 | P23: 817.2 | Q23: 667.6 | R23: 782.7 | S23: 474.5 | T23: 464 | U23: =U21*Assumptions!$C$20 | V23: =V21*Assumptions!$C$20 | W23: =W21*Assumptions!$C$20 | X23: =X21*Assumptions!$C$20 | Y23: =Y21*Assumptions!$C$20 | Z23: =Z21*Assumptions!$C$20 | AA23: =AA21*Assumptions!$C$20 | AB23: =AB21*Assumptions!$C$20 | ... AY23: =AY21*Assumptions!$C$20
B24: 506000 Merchant Account Fees | D24: 0 | E24: 0 | F24: 0 | G24: 0 | H24: 0 | I24: 0 | J24: 1.41 | K24: 27.12 | L24: 586.97 | M24: 1101.43 | N24: 667.92 | O24: 901.09 | P24: 997.56 | Q24: 898.16 | R24: 1146.66 | S24: 855.58 | T24: 876.72 | U24: =U21*Assumptions!$C$19 | V24: =V21*Assumptions!$C$19 | W24: =W21*Assumptions!$C$19 | X24: =X21*Assumptions!$C$19 | Y24: =Y21*Assumptions!$C$19 | Z24: =Z21*Assumptions!$C$19 | AA24: =AA21*Assumptions!$C$19 | AB24: =AB21*Assumptions!$C$19 | ... AY24: =AY21*Assumptions!$C$19
B25: Total Cost of Goods Sold | D25: 0 | E25: 0 | F25: 0 | G25: 0 | H25: 0 | I25: 0 | J25: 1.41 | K25: 27.12 | L25: 1110.47 | M25: 2067.53 | N25: 1363.92 | O25: 3864.81 | P25: 1814.76 | Q25: 1565.76 | R25: 1929.36 | S25: 1330.08 | T25: 1340.72 | U25: =U23+U24 | V25: =V23+V24 | W25: =W23+W24 | X25: =X23+X24 | Y25: =Y23+Y24 | Z25: =Z23+Z24 | AA25: =AA23+AA24 | AB25: =AB23+AB24 | ... AY25: =AY23+AY24
B26: GROSS PROFIT | D26: 0 | E26: 0 | F26: 0 | G26: 0 | H26: 0 | I26: 0 | J26: -1.41 | K26: -620.12 | L26: 4078.67 | M26: 25837.19 | N26: 24949.99 | O26: 28000.55 | P26: 35234.83 | Q26: 39993.72 | R26: 40996.12 | S26: 35685.29 | T26: 35043.12 | U26: =U21-U25 | V26: =V21-V25 | W26: =W21-W25 | X26: =X21-X25 | Y26: =Y21-Y25 | Z26: =Z21-Z25 | AA26: =AA21-AA25 | AB26: =AB21-AB25 | ... AY26: =AY21-AY25
B27: OPERATING EXPENSES
B28: 601001 Paid Ads | D28: 0 | E28: 0 | F28: 0 | G28: 0 | H28: 0 | I28: 0 | J28: 0 | K28: 2508.98 | L28: 2301.77 | M28: 2373.48 | N28: 3126.18 | O28: 1853.28 | P28: 1338.08 | Q28: 1423.13 | R28: 557.1 | S28: 0 | T28: 0 | U28: 747.17 | V28: 747.17 | W28: 747.17 | X28: 747.17 | Y28: 747.17 | Z28: 747.17 | AA28: 747.17 | AB28: 747.17 | AC28: 747.17 | AD28: 747.17 | AE28: 747.17 | AF28: 747.17 | AG28: 747.17 | AH28: 747.17 | AI28: 747.17 | AJ28: 747.17 | AK28: 747.17 | AL28: 747.17 | AM28: 747.17 | AN28: 747.17 | AO28: 747.17 | AP28: 747.17 | AQ28: 747.17 | AR28: 747.17 | AS28: 747.17 | AT28: 747.17 | AU28: 747.17 | AV28: 747.17 | AW28: 747.17 | AX28: 747.17 | AY28: 747.17
B29: 601005 Content Creation | P29: 0 | Q29: 0 | R29: 0 | S29: 0 | T29: 0 | U29: 0 | V29: 0 | W29: 0 | X29: 0 | Y29: 0 | Z29: 0 | AA29: 0 | AB29: 0 | AC29: 0 | AD29: 0 | AE29: 0 | AF29: 0 | AG29: 0 | AH29: 0 | AI29: 0 | AJ29: 0 | AK29: 0 | AL29: 0 | AM29: 0 | AN29: 0 | AO29: 0 | AP29: 0 | AQ29: 0 | AR29: 0 | AS29: 0 | AT29: 0 | AU29: 0 | AV29: 0 | AW29: 0 | AX29: 0 | AY29: 0
B30: 601006 General Marketing | D30: 0 | E30: 0 | F30: 0 | G30: 0 | H30: 0 | I30: 0 | J30: 0 | K30: 0 | L30: 1370.24 | M30: 189.72 | N30: 0 | O30: 129.56 | P30: 0 | Q30: 0 | R30: 0 | S30: 0 | T30: 0 | U30: 0 | V30: 0 | W30: 0 | X30: 0 | Y30: 0 | Z30: 0 | AA30: 0 | AB30: 0 | AC30: 0 | AD30: 0 | AE30: 0 | AF30: 0 | AG30: 0 | AH30: 0 | AI30: 0 | AJ30: 0 | AK30: 0 | AL30: 0 | AM30: 0 | AN30: 0 | AO30: 0 | AP30: 0 | AQ30: 0 | AR30: 0 | AS30: 0 | AT30: 0 | AU30: 0 | AV30: 0 | AW30: 0 | AX30: 0 | AY30: 0
B31: 601007 Contractors/Agencies | P31: 0 | Q31: 0 | R31: 0 | S31: 0 | T31: 0 | U31: 0 | V31: 0 | W31: 0 | X31: 0 | Y31: 0 | Z31: 0 | AA31: 0 | AB31: 0 | AC31: 0 | AD31: 0 | AE31: 0 | AF31: 0 | AG31: 0 | AH31: 0 | AI31: 0 | AJ31: 0 | AK31: 0 | AL31: 0 | AM31: 0 | AN31: 0 | AO31: 0 | AP31: 0 | AQ31: 0 | AR31: 0 | AS31: 0 | AT31: 0 | AU31: 0 | AV31: 0 | AW31: 0 | AX31: 0 | AY31: 0
B32: 601010 Website Development | P32: 0 | Q32: 0 | R32: 0 | S32: 0 | T32: 0 | U32: 0 | V32: 0 | W32: 0 | X32: 0 | Y32: 0 | Z32: 0 | AA32: 0 | AB32: 0 | AC32: 0 | AD32: 0 | AE32: 0 | AF32: 0 | AG32: 0 | AH32: 0 | AI32: 0 | AJ32: 0 | AK32: 0 | AL32: 0 | AM32: 0 | AN32: 0 | AO32: 0 | AP32: 0 | AQ32: 0 | AR32: 0 | AS32: 0 | AT32: 0 | AU32: 0 | AV32: 0 | AW32: 0 | AX32: 0 | AY32: 0
B33: Total Marketing | D33: 0 | E33: 0 | F33: 0 | G33: 0 | H33: 0 | I33: 0 | J33: 0 | K33: 2508.98 | L33: 3672.01 | M33: 2875.47 | N33: 3126.18 | O33: 2402.84 | P33: 1338.08 | Q33: 1423.13 | R33: 557.1 | S33: 0 | T33: 0 | U33: =U28+U29+U30+U31+U32 | V33: =V28+V29+V30+V31+V32 | W33: =W28+W29+W30+W31+W32 | X33: =X28+X29+X30+X31+X32 | Y33: =Y28+Y29+Y30+Y31+Y32 | Z33: =Z28+Z29+Z30+Z31+Z32 | AA33: =AA28+AA29+AA30+AA31+AA32 | AB33: =AB28+AB29+AB30+AB31+AB32 | ... AY33: =AY28+AY29+AY30+AY31+AY32
B34: 602001 Wages | D34: 0 | E34: 0 | F34: 0 | G34: 0 | H34: 0 | I34: 0 | J34: 0 | K34: 1885.71 | L34: 15103.08 | M34: 23363.57 | N34: 21188.67 | O34: 19923.59 | P34: 19792.41 | Q34: 21148.5 | R34: 23707.86 | S34: 21562.97 | T34: 20706.63 | U34: 20091.59 | V34: 21765.89 | W34: 19254.44 | X34: 20091.59 | Y34: 21765.89 | Z34: 22603.04 | AA34: 21765.89 | AB34: 21765.89 | AC34: 24277.34 | AD34: 22603.04 | AE34: 22022.61 | AF34: 21786.79 | AG34: 21760.62 | AH34: 25464.53 | AI34: 30068.98 | AJ34: 30715.76 | AK34: 29176.34 | AL34: 28512.63 | AM34: 28358.26 | AN34: 21765.89 | AO34: 24277.34 | AP34: 22603.04 | AQ34: 22022.61 | AR34: 21786.79 | AS34: 21760.62 | AT34: 25464.53 | AU34: 30068.98 | AV34: 30715.76 | AW34: 29176.34 | AX34: 28512.63 | AY34: 28358.26
B35: 602004 Payroll Taxes | D35: 0 | E35: 0 | F35: 0 | G35: 0 | H35: 0 | I35: 0 | J35: 0 | K35: 221.57 | L35: 1916.96 | M35: 2799.78 | N35: 2538.32 | O35: 2445.34 | P35: 3244.47 | Q35: 2155.86 | R35: 2294.08 | S35: 2133.96 | T35: 1999.79 | U35: 2290.5 | V35: 2481.37 | W35: 2195.06 | X35: 2290.5 | Y35: 2481.37 | Z35: 2576.81 | AA35: 2481.37 | AB35: 2481.37 | AC35: 2767.68 | AD35: 2576.81 | AE35: 2510.64 | AF35: 2483.75 | AG35: 2480.77 | AH35: 2903.02 | AI35: 3427.94 | AJ35: 3501.68 | AK35: 3326.18 | AL35: 3250.52 | AM35: 3232.92 | AN35: 2481.37 | AO35: 2767.68 | AP35: 2576.81 | AQ35: 2510.64 | AR35: 2483.75 | AS35: 2480.77 | AT35: 2903.02 | AU35: 3427.94 | AV35: 3501.68 | AW35: 3326.18 | AX35: 3250.52 | AY35: 3232.92
B36: 602005 Employee Benefits | D36: 0 | E36: 0 | F36: 0 | G36: 0 | H36: 0 | I36: 0 | J36: 0 | K36: 0 | L36: 0 | M36: 360 | N36: 160 | O36: -29.15 | P36: 362.04 | Q36: 867.02 | R36: 756.24 | S36: 567.73 | T36: 577.5 | U36: 594.98 | V36: 644.56 | W36: 570.19 | X36: 594.98 | Y36: 644.56 | Z36: 669.35 | AA36: 644.56 | AB36: 644.56 | AC36: 718.94 | AD36: 669.35 | AE36: 652.17 | AF36: 645.18 | AG36: 644.41 | AH36: 754.09 | AI36: 890.45 | AJ36: 909.6 | AK36: 864.01 | AL36: 844.36 | AM36: 839.79 | AN36: 644.56 | AO36: 718.94 | AP36: 669.35 | AQ36: 652.17 | AR36: 645.18 | AS36: 644.41 | AT36: 754.09 | AU36: 890.45 | AV36: 909.6 | AW36: 864.01 | AX36: 844.36 | AY36: 839.79
B37: 602010 Payroll Processing Fees | D37: 0 | E37: 0 | F37: 0 | G37: 0 | H37: 0 | I37: 0 | J37: 0 | K37: 0 | L37: 683.48 | M37: 618.56 | N37: 635.68 | O37: 774.21 | P37: 676.22 | Q37: 1136.79 | R37: 1540.85 | S37: 1035.47 | T37: 857.68 | U37: 1022.93 | V37: 1108.17 | W37: 980.31 | X37: 1022.93 | Y37: 1108.17 | Z37: 1150.8 | AA37: 1108.17 | AB37: 1108.17 | AC37: 1236.04 | AD37: 1150.8 | AE37: 1121.25 | AF37: 1109.24 | AG37: 1107.91 | AH37: 1296.48 | AI37: 1530.91 | AJ37: 1563.84 | AK37: 1485.47 | AL37: 1451.67 | AM37: 1443.81 | AN37: 1108.17 | AO37: 1236.04 | AP37: 1150.8 | AQ37: 1121.25 | AR37: 1109.24 | AS37: 1107.91 | AT37: 1296.48 | AU37: 1530.91 | AV37: 1563.84 | AW37: 1485.47 | AX37: 1451.67 | AY37: 1443.81
B38: Total Payroll | D38: 0 | E38: 0 | F38: 0 | G38: 0 | H38: 0 | I38: 0 | J38: 0 | K38: 2107.28 | L38: 23080.28 | M38: 31197.11 | N38: 27596.68 | O38: 24342.34 | P38: 24075.14 | Q38: 25308.17 | R38: 28299.03 | S38: 25300.13 | T38: 24141.6 | U38: =U34+U35+U36+U37 | V38: =V34+V35+V36+V37 | W38: =W34+W35+W36+W37 | X38: =X34+X35+X36+X37 | Y38: =Y34+Y35+Y36+Y37 | Z38: =Z34+Z35+Z36+Z37 | AA38: =AA34+AA35+AA36+AA37 | AB38: =AB34+AB35+AB36+AB37 | ... AY38: =AY34+AY35+AY36+AY37
B39: 603000 Software & Web Services | D39: 0 | E39: 0 | F39: 0 | G39: 0 | H39: 0 | I39: 0 | J39: 0 | K39: 1228 | L39: 956.25 | M39: 769.89 | N39: 791.49 | O39: 948.68 | P39: 910.98 | Q39: 1253.44 | R39: 881.08 | S39: 840.06 | T39: 1223.66 | U39: 903.34 | V39: 903.34 | W39: 903.34 | X39: 903.34 | Y39: 903.34 | Z39: 903.34 | AA39: 903.34 | AB39: 903.34 | AC39: 903.34 | AD39: 903.34 | AE39: 903.34 | AF39: 903.34 | AG39: 903.34 | AH39: 903.34 | AI39: 903.34 | AJ39: 903.34 | AK39: 903.34 | AL39: 903.34 | AM39: 903.34 | AN39: 903.34 | AO39: 903.34 | AP39: 903.34 | AQ39: 903.34 | AR39: 903.34 | AS39: 903.34 | AT39: 903.34 | AU39: 903.34 | AV39: 903.34 | AW39: 903.34 | AX39: 903.34 | AY39: 903.34
B40: 608000 Insurance | D40: 0 | E40: 0 | F40: 0 | G40: 0 | H40: 0 | I40: 0 | J40: 0 | K40: 363.58 | L40: 1526.84 | M40: 2684.45 | N40: 107.45 | O40: 107.45 | P40: 314.75 | Q40: 314.75 | R40: 612.95 | S40: 580.03 | T40: 431.04 | U40: 423.7 | V40: 423.7 | W40: 423.7 | X40: 423.7 | Y40: 423.7 | Z40: 423.7 | AA40: 423.7 | AB40: 423.7 | AC40: 423.7 | AD40: 423.7 | AE40: 423.7 | AF40: 423.7 | AG40: 423.7 | AH40: 423.7 | AI40: 423.7 | AJ40: 423.7 | AK40: 423.7 | AL40: 423.7 | AM40: 423.7 | AN40: 423.7 | AO40: 423.7 | AP40: 423.7 | AQ40: 423.7 | AR40: 423.7 | AS40: 423.7 | AT40: 423.7 | AU40: 423.7 | AV40: 423.7 | AW40: 423.7 | AX40: 423.7 | AY40: 423.7
B41: 610000 Office Supplies | P41: 601.06 | Q41: 153.33 | R41: 1031.56 | S41: 363.63 | T41: 0 | U41: 499.75 | V41: 499.75 | W41: 499.75 | X41: 499.75 | Y41: 499.75 | Z41: 499.75 | AA41: 499.75 | AB41: 499.75 | AC41: 499.75 | AD41: 499.75 | AE41: 499.75 | AF41: 499.75 | AG41: 499.75 | AH41: 499.75 | AI41: 499.75 | AJ41: 499.75 | AK41: 499.75 | AL41: 499.75 | AM41: 499.75 | AN41: 499.75 | AO41: 499.75 | AP41: 499.75 | AQ41: 499.75 | AR41: 499.75 | AS41: 499.75 | AT41: 499.75 | AU41: 499.75 | AV41: 499.75 | AW41: 499.75 | AX41: 499.75 | AY41: 499.75
B42: Total Software & Admin | D42: =D39+D40+D41 | E42: =E39+E40+E41 | F42: =F39+F40+F41 | G42: =G39+G40+G41 | H42: =H39+H40+H41 | I42: =I39+I40+I41 | J42: =J39+J40+J41 | K42: =K39+K40+K41 | ... AY42: =AY39+AY40+AY41
B43: 604100 Legal Fees | P43: 0 | Q43: 0 | R43: 0 | S43: 0 | T43: 0 | U43: 0 | V43: 0 | W43: 0 | X43: 0 | Y43: 0 | Z43: 0 | AA43: 0 | AB43: 0 | AC43: 0 | AD43: 0 | AE43: 0 | AF43: 0 | AG43: 0 | AH43: 0 | AI43: 0 | AJ43: 0 | AK43: 0 | AL43: 0 | AM43: 0 | AN43: 0 | AO43: 0 | AP43: 0 | AQ43: 0 | AR43: 0 | AS43: 0 | AT43: 0 | AU43: 0 | AV43: 0 | AW43: 0 | AX43: 0 | AY43: 0
B44: 604200 Accounting | D44: 0 | E44: 0 | F44: 0 | G44: 0 | H44: 0 | I44: 0 | J44: 0 | K44: 800 | L44: 29.87 | M44: 0 | N44: 154.54 | O44: 101.59 | P44: 0 | Q44: 301.82 | R44: 880 | S44: 2870 | T44: 1116.82 | U44: 341.86 | V44: 341.86 | W44: 341.86 | X44: 341.86 | Y44: 341.86 | Z44: 341.86 | AA44: 341.86 | AB44: 341.86 | AC44: 341.86 | AD44: 341.86 | AE44: 341.86 | AF44: 341.86 | AG44: 341.86 | AH44: 341.86 | AI44: 341.86 | AJ44: 341.86 | AK44: 341.86 | AL44: 341.86 | AM44: 341.86 | AN44: 341.86 | AO44: 341.86 | AP44: 341.86 | AQ44: 341.86 | AR44: 341.86 | AS44: 341.86 | AT44: 341.86 | AU44: 341.86 | AV44: 341.86 | AW44: 341.86 | AX44: 341.86 | AY44: 341.86
B45: 604300 Recruiting | P45: 0 | Q45: 0 | R45: 0 | S45: 0 | T45: 0 | U45: 0 | V45: 0 | W45: 0 | X45: 0 | Y45: 0 | Z45: 0 | AA45: 0 | AB45: 0 | AC45: 0 | AD45: 0 | AE45: 0 | AF45: 0 | AG45: 0 | AH45: 0 | AI45: 0 | AJ45: 0 | AK45: 0 | AL45: 0 | AM45: 0 | AN45: 0 | AO45: 0 | AP45: 0 | AQ45: 0 | AR45: 0 | AS45: 0 | AT45: 0 | AU45: 0 | AV45: 0 | AW45: 0 | AX45: 0 | AY45: 0
B46: 604400 Other Professional Fees | D46: 0 | E46: 0 | F46: 0 | G46: 0 | H46: 0 | I46: 0 | J46: 0 | K46: 0 | L46: 0 | M46: 481 | N46: 1093.5 | O46: 497.18 | P46: 516 | Q46: 516 | R46: 516 | S46: 516 | T46: 516 | U46: 174.14 | V46: 174.14 | W46: 174.14 | X46: 174.14 | Y46: 174.14 | Z46: 174.14 | AA46: 174.14 | AB46: 174.14 | AC46: 174.14 | AD46: 174.14 | AE46: 174.14 | AF46: 174.14 | AG46: 174.14 | AH46: 174.14 | AI46: 174.14 | AJ46: 174.14 | AK46: 174.14 | AL46: 174.14 | AM46: 174.14 | AN46: 174.14 | AO46: 174.14 | AP46: 174.14 | AQ46: 174.14 | AR46: 174.14 | AS46: 174.14 | AT46: 174.14 | AU46: 174.14 | AV46: 174.14 | AW46: 174.14 | AX46: 174.14 | AY46: 174.14
B47: Total Professional Fees | D47: 0 | E47: 0 | F47: 0 | G47: 0 | H47: 0 | I47: 0 | J47: 0 | K47: 800 | L47: 29.87 | M47: 481 | N47: 1248.04 | O47: 598.77 | P47: 516 | Q47: 817.82 | R47: 1396 | S47: 3386 | T47: 1632.82 | U47: =U43+U44+U45+U46 | V47: =V43+V44+V45+V46 | W47: =W43+W44+W45+W46 | X47: =X43+X44+X45+X46 | Y47: =Y43+Y44+Y45+Y46 | Z47: =Z43+Z44+Z45+Z46 | AA47: =AA43+AA44+AA45+AA46 | AB47: =AB43+AB44+AB45+AB46 | ... AY47: =AY43+AY44+AY45+AY46
B48: 605000 Travel | P48: 420.63 | Q48: 159.5 | R48: 271.5 | S48: 0 | T48: 0 | U48: 340.41 | V48: 340.41 | W48: 340.41 | X48: 340.41 | Y48: 340.41 | Z48: 340.41 | AA48: 340.41 | AB48: 340.41 | AC48: 340.41 | AD48: 340.41 | AE48: 340.41 | AF48: 340.41 | AG48: 340.41 | AH48: 340.41 | AI48: 340.41 | AJ48: 340.41 | AK48: 340.41 | AL48: 340.41 | AM48: 340.41 | AN48: 340.41 | AO48: 340.41 | AP48: 340.41 | AQ48: 340.41 | AR48: 340.41 | AS48: 340.41 | AT48: 340.41 | AU48: 340.41 | AV48: 340.41 | AW48: 340.41 | AX48: 340.41 | AY48: 340.41
B49: 606000 Meals | D49: 0 | E49: 0 | F49: 0 | G49: 0 | H49: 0 | I49: 0 | J49: 150.32 | K49: 0 | L49: 1160.57 | M49: 276.56 | N49: 178.87 | O49: 771.91 | P49: 0 | Q49: 43.24 | R49: 141.74 | S49: 15.7 | T49: 63.02 | U49: 80.22 | V49: 80.22 | W49: 80.22 | X49: 80.22 | Y49: 80.22 | Z49: 80.22 | AA49: 80.22 | AB49: 80.22 | AC49: 80.22 | AD49: 80.22 | AE49: 80.22 | AF49: 80.22 | AG49: 80.22 | AH49: 80.22 | AI49: 80.22 | AJ49: 80.22 | AK49: 80.22 | AL49: 80.22 | AM49: 80.22 | AN49: 80.22 | AO49: 80.22 | AP49: 80.22 | AQ49: 80.22 | AR49: 80.22 | AS49: 80.22 | AT49: 80.22 | AU49: 80.22 | AV49: 80.22 | AW49: 80.22 | AX49: 80.22 | AY49: 80.22
B50: Total Travel & Meals | D50: =D48+D49 | E50: =E48+E49 | F50: =F48+F49 | G50: =G48+G49 | H50: =H48+H49 | I50: =I48+I49 | J50: =J48+J49 | K50: =K48+K49 | ... AY50: =AY48+AY49
B51: 616001 Electricity | D51: 0 | E51: 0 | F51: 0 | G51: 0 | H51: 0 | I51: 0 | J51: 0 | K51: 0 | L51: 1342.56 | M51: 330.08 | N51: 331.87 | O51: 324.32 | P51: 347.43 | Q51: 327.14 | R51: 449.57 | S51: 414.77 | T51: 384.52 | U51: 389.78 | V51: 389.78 | W51: 389.78 | X51: 389.78 | Y51: 389.78 | Z51: 389.78 | AA51: 389.78 | AB51: 389.78 | AC51: 389.78 | AD51: 389.78 | AE51: 389.78 | AF51: 389.78 | AG51: 389.78 | AH51: 389.78 | AI51: 389.78 | AJ51: 389.78 | AK51: 389.78 | AL51: 389.78 | AM51: 389.78 | AN51: 389.78 | AO51: 389.78 | AP51: 389.78 | AQ51: 389.78 | AR51: 389.78 | AS51: 389.78 | AT51: 389.78 | AU51: 389.78 | AV51: 389.78 | AW51: 389.78 | AX51: 389.78 | AY51: 389.78
B52: 616002 Internet & TV | P52: 81.25 | Q52: 93.09 | R52: 93.09 | S52: 93 | T52: 0 | U52: 91.29 | V52: 91.29 | W52: 91.29 | X52: 91.29 | Y52: 91.29 | Z52: 91.29 | AA52: 91.29 | AB52: 91.29 | AC52: 91.29 | AD52: 91.29 | AE52: 91.29 | AF52: 91.29 | AG52: 91.29 | AH52: 91.29 | AI52: 91.29 | AJ52: 91.29 | AK52: 91.29 | AL52: 91.29 | AM52: 91.29 | AN52: 91.29 | AO52: 91.29 | AP52: 91.29 | AQ52: 91.29 | AR52: 91.29 | AS52: 91.29 | AT52: 91.29 | AU52: 91.29 | AV52: 91.29 | AW52: 91.29 | AX52: 91.29 | AY52: 91.29
